Workbook
Name test_Data_Enrollment_Summarizes_Data: #REF!

Sheet Quarter 1
J1: Total Number of Abbott Children | M1: ='Provider Planning Budget'!E5 -> 45
E2: Provider Reported Expenditures | F2: Provider Balance Prior to Ependiture Review | G2: Budget Modification Approved by the District | H2: District Calculated Expenditures 1st Quarter | I2: Unapproved / Approved Funds Expended (July-Sept.) | J2: DOE Share of DOE/DHS Shared Costs | M2: 0.7673
A3: Report Due Tuesday, October 15, 2019 by 3:00PM | D3: September Under Enrollment | J3: Change DOE Share of DOE/DHS Shared Costs
C4: NPS Approved | J4: DOE Share of Center-Wide Costs
A5: EXPENDITURES (Cash Paid Out) | C5: 2018-19Budget | E5: (July-Sept.) | F5: (July-Sept.) | H5: (July-Sept.) | I5: (District Use) | J5: Fund Balance | K5: . | N5: Proration Changes
A6: EDUCATIONAL PROGRAM COSTS (Instructional) 10-MONTH COST ONLY EXCLUDING BENEFITS
A7: Teacher Salary | C7: ='Provider Planning Budget'!H18 -> 169561 | D7: =C7/(A$63-C$13-C$14)*D$5*D$65 -> 0 | E7: 3452 | F7: =C7+D7-E7 -> 166109 | I7: =H7-E7 -> -3452 | J7: =IF(H7>0,(C7+D7+G7-H7),F7+G7) -> 166109
A8: Teacher Assistant Salary | C8: ='Provider Planning Budget'!H20 -> 86836 | D8: =C8/(A$63-C$13-C$14)*D$5*D$65 -> 0 | E8: 4700 | F8: =C8+D8-E8 -> 82136 | I8: =H8-E8 -> -4700 | J8: =IF(H8>0,C8-H8,F8) -> 82136
A9: Floating Teacher Assistant Salary | C9: ='Provider Planning Budget'!H21 -> 19800 | D9: =C9/(A$63-C$13-C$14)*D$5*D$65 -> 0 | E9: 863 | F9: =C9+D9-E9 -> 18937 | I9: =H9-E9 -> -863 | J9: =IF(H9>0,C9-H9,F9) -> 18937
A10: Teacher, Assistant and Floater Benefits | C10: ='Provider Planning Budget'!H23 -> 38599.75 | D10: =C10/(A$63-C$13-C$14)*D$5*D$65 -> 0 | E10: 11173 | F10: =C10+D10-E10 -> 27426.75 | I10: =H10-E10 -> -11173 | J10: =IF(H10>0,C10-H10,F10) -> 27426.75
A11: Substitute Teacher Daily Rate (Stipend) | C11: ='Provider Planning Budget'!H25 -> 3000 | D11: =C11/(A$63-C$13-C$14)*D$5*D$65 -> 0 | E11: 3338 | F11: =C11+D11-E11 -> -338 | I11: =H11-E11 -> -3338 | J11: =IF(H11>0,C11-H11,F11) -> -338
A12: Substitute Assistant Daily Rate (Stipend) | C12: ='Provider Planning Budget'!H26 -> 4800 | D12: =C12/(A$63-C$13-C$14)*D$5*D$65 -> 0 | F12: =C12+D12-E12 -> 4800 | I12: =H12-E12 -> 0 | J12: =IF(H12>0,C12-H12,F12) -> 4800
A13: Classroom Materials and Supplies | C13: ='Provider Planning Budget'!H28 -> 6000 | D13: =C13/(A$63-C$13-C$14)*D$5*D$65 -> 0 | E13: 2031 | F13: =C13+D13-E13 -> 3969 | I13: =H13-E13 -> -2031 | J13: =IF(H13>0,C13-H13,F13) -> 3969
A14: Classroom Technology | C14: ='Provider Planning Budget'!H29 -> 3000 | D14: =C14/(A$63-C$13-C$14)*D$5*D$65 -> 0 | F14: =C14+D14-E14 -> 3000 | I14: =H14-E14 -> 0 | J14: =IF(H14>0,C14-H14,F14) -> 3000
A15: Field Trips w/ Transportation | C15: ='Provider Planning Budget'!H30 -> 4500 | D15: =C15/(A$63-C$13-C$14)*D$5*D$65 -> 0 | E15: 560 | F15: =C15+D15-E15 -> 3940 | I15: =H15-E15 -> -560 | J15: =IF(H15>0,C15-H15,F15) -> 3940
A16: Family Worker Salary | C16: ='Provider Planning Budget'!H32 -> 24551.798 | D16: =C16/(A$63-C$13-C$14)*D$5*D$65 -> 0 | E16: 4870 | F16: =C16+D16-E16 -> 19681.798 | I16: =H16-E16 -> -4870 | J16: =IF(H16>0,C16-H16,F16) -> 19681.798
A17: Family Worker Benefits | C17: ='Provider Planning Budget'!H33 -> 0 | D17: =C17/(A$63-C$13-C$14)*D$5*D$65 -> 0 | F17: =C17+D17-E17 -> 0 | I17: =H17-E17 -> 0 | J17: =IF(H17>0,C17-H17,F17) -> 0
A18: Food CACFP; September - June (for contracted preschool children only) | C18: ='Provider Planning Budget'!H37 -> 0 | D18: =C18/(A$63-C$13-C$14)*D$5*D$65 -> 0 | F18: =C18+D18-E18 -> 0 | I18: =H18-E18 -> 0 | J18: =IF(H18>0,C18-H18,F18) -> 0
A19: Food Worker Salary (cook) | C19: ='Provider Planning Budget'!H38 -> 7500.4588 | D19: =C19/(A$63-C$13-C$14)*D$5*D$65 -> 0 | E19: 424 | F19: =C19+D19-E19 -> 7076.4588 | I19: =H19-E19 -> -424 | J19: =IF(H19>0,C19-H19,F19) -> 7076.4588
A20: Food Worker Salary (cook asst.) | C20: ='Provider Planning Budget'!H40 -> 0 | D20: =C20/(A$63-C$13-C$14)*D$5*D$65 -> 0 | F20: =C20+D20-E20 -> 0 | I20: =H20-E20 -> 0 | J20: =IF(H20>0,C20-H20,F20) -> 0
A21: Food Worker Benefits (Cook & Assist. Cook) | C21: ='Provider Planning Budget'!H39+'Provider Planning Budget'!H41 -> 0 | D21: =C21/(A$63-C$13-C$14)*D$5*D$65 -> 0 | F21: =C21+D21-E21 -> 0 | I21: =H21-E21 -> 0 | J21: =IF(H21>0,C21-H21,F21) -> 0
A22: Social Security (6.20%) | C22: ='Provider Planning Budget'!H44 -> 19595.054 | D22: =C22/(A$63-C$13-C$14)*D$5*D$65 -> 0 | E22: =17649*N22 -> 1094.238 | F22: =C22+D22-E22 -> 18500.816 | I22: =H22-E22 -> -1094.238 | J22: =IF(H22>0,C22-H22,F22) -> 18500.816 | N22: 0.062
A23: Medicare (1.45%) | C23: ='Provider Planning Budget'!H45 -> 4582.7142 | D23: =C23/(A$63-C$13-C$14)*D$5*D$65 -> 0 | E23: =17647*N23 -> 255.8815 | F23: =C23+D23-E23 -> 4326.8327 | I23: =H23-E23 -> -255.8815 | J23: =IF(H23>0,C23-H23,F23) -> 4326.8327 | N23: 0.0145
A24: Unemployment (2.80%) | C24: ='Provider Planning Budget'!H46 -> 8849.3792 | D24: =C24/(A$63-C$13-C$14)*D$5*D$65 -> 0 | E24: =17647*N24 -> 494.116 | F24: =C24+D24-E24 -> 8355.2632 | I24: =H24-E24 -> -494.116 | J24: =IF(H24>0,C24-H24,F24) -> 8355.2632 | N24: 0.028
A25: Disability (0.50%) | C25: ='Provider Planning Budget'!H47 -> 1580.2463 | D25: =C25/(A$63-C$13-C$14)*D$5*D$65 -> 0 | E25: =17647*N25 -> 88.235 | F25: =C25+D25-E25 -> 1492.0113 | I25: =H25-E25 -> -88.235 | J25: =IF(H25>0,C25-H25,F25) -> 1492.0113 | N25: 0.005
A26: Sub-Total | C26: =SUM(C7:C25) -> 402756.4 | D26: =SUM(D7:D25) -> 0 | E26: =SUM(E7:E25) -> 33343.471 | F26: =SUM(F7:F25) -> 369412.93 | G26: =SUM(G7:G25) -> 0 | H26: =SUM(H7:H25) -> 0 | I26: =SUM(I7:I25) -> -33343.471 | J26: =SUM(J7:J25) -> 369412.93
A27: ADMINISTRATIVE SUPPORT COSTS (NON-Instructional) 12-MONTH COST ONLY EXCLUDING BENEFITS
A28: Director Salary | C28: ='Provider Planning Budget'!H54 -> 44183.837 | D28: =C28/(A$63-C$13-C$14)*D$5*D$65 -> 0 | E28: 13288 | F28: =C28+D28-E28 -> 30895.837 | I28: =H28-E28 -> -13288 | J28: =IF(H28>0,C28-H28,F28) -> 30895.837
A29: Director Benefits | C29: ='Provider Planning Budget'!H55 -> 8103.1837 | D29: =C29/(A$63-C$13-C$14)*D$5*D$65 -> 0 | E29: 4306 | F29: =C29+D29-E29 -> 3797.1837 | I29: =H29-E29 -> -4306 | J29: =IF(H29>0,C29-H29,F29) -> 3797.1837
A30: Clerical Salary | C30: ='Provider Planning Budget'!H56 -> 3836.7347 | D30: =C30/(A$63-C$13-C$14)*D$5*D$65 -> 0 | E30: 3329 | F30: =C30+D30-E30 -> 507.73469 | I30: =H30-E30 -> -3329 | J30: =IF(H30>0,C30-H30,F30) -> 507.73469
A31: Clerical Benefits | C31: ='Provider Planning Budget'!H57 -> 0 | D31: =C31/(A$63-C$13-C$14)*D$5*D$65 -> 0 | F31: =C31+D31-E31 -> 0 | I31: =H31-E31 -> 0 | J31: =IF(H31>0,C31-H31,F31) -> 0
A32: Janitor Salary | C32: ='Provider Planning Budget'!H58 -> 8440.8163 | D32: =C32/(A$63-C$13-C$14)*D$5*D$65 -> 0 | E32: 1496 | F32: =C32+D32-E32 -> 6944.8163 | I32: =H32-E32 -> -1496 | J32: =IF(H32>0,C32-H32,F32) -> 6944.8163
A33: Janitor Benefits | C33: ='Provider Planning Budget'!H59 -> 0 | D33: =C33/(A$63-C$13-C$14)*D$5*D$65 -> 0 | F33: =C33+D33-E33 -> 0 | I33: =H33-E33 -> 0 | J33: =IF(H33>0,C33-H33,F33) -> 0
A34: Security Guard Salary | C34: ='Provider Planning Budget'!H60 -> 15346.939 | D34: =C34/(A$63-C$13-C$14)*D$5*D$65 -> 0 | E34: 5157 | F34: =C34+D34-E34 -> 10189.939 | I34: =H34-E34 -> -5157 | J34: =IF(H34>0,C34-H34,F34) -> 10189.939
A35: Secufity Guard Benefits | C35: ='Provider Planning Budget'!H61 -> 0 | D35: =C35/(A$63-C$13-C$14)*D$5*D$65 -> 0 | F35: =C35+D35-E35 -> 0 | I35: =H35-E35 -> 0 | J35: =IF(H35>0,C35-H35,F35) -> 0
A36: Social Security (6.20%) | C36: ='Provider Planning Budget'!H62 -> 4452.1162 | D36: =C36/(A$63-C$13-C$14)*D$5*D$65 -> 0 | E36: =23270*N36 -> 1442.74 | F36: =C36+D36-E36 -> 3009.3762 | I36: =H36-E36 -> -1442.74 | J36: =IF(H36>0,C36-H36,F36) -> 3009.3762 | N36: 0.062
A37: Medicare (1.45%) | C37: ='Provider Planning Budget'!H63 -> 1041.2207 | D37: =C37/(A$63-C$13-C$14)*D$5*D$65 -> 0 | E37: =23270*N37 -> 337.415 | F37: =C37+D37-E37 -> 703.80573 | I37: =H37-E37 -> -337.415 | J37: =IF(H37>0,C37-H37,F37) -> 703.80573 | N37: 0.0145
A38: Unemployment (2.80%) | C38: ='Provider Planning Budget'!H64 -> 2010.6331 | D38: =C38/(A$63-C$13-C$14)*D$5*D$65 -> 0 | E38: =23270*N38 -> 651.56 | F38: =C38+D38-E38 -> 1359.0731 | I38: =H38-E38 -> -651.56 | J38: =IF(H38>0,C38-H38,F38) -> 1359.0731 | N38: 0.028
A39: Disability (0.50%) | C39: ='Provider Planning Budget'!H65 -> 359.04163 | D39: =C39/(A$63-C$13-C$14)*D$5*D$65 -> 0 | E39: =23270*N39 -> 116.35 | F39: =C39+D39-E39 -> 242.69163 | I39: =H39-E39 -> -116.35 | J39: =IF(H39>0,C39-H39,F39) -> 242.69163 | N39: 0.005
A40: INDIRECT COSTS -- SPACE COSTS AND ALL OTHER ALLOWABLE INDIRECT (NON-Instructional) 12-MONTH COSTS
A41: Rent, Mortgage, Other Space Costs | C41: ='Provider Planning Budget'!H69 -> 91120.914 | D41: =C41/(A$63-C$13-C$14)*D$5*D$65 -> 0 | E41: 22780 | F41: =C41+D41-E41 -> 68340.914 | I41: =H41-E41 -> -22780 | J41: =IF(H41>0,C41-H41,F41) -> 68340.914
A42: Office Equipment>$2000 and Repair | C42: ='Provider Planning Budget'!H73 -> 3069.3878 | D42: =C42/(A$63-C$13-C$14)*D$5*D$65 -> 0 | E42: 802 | F42: =C42+D42-E42 -> 2267.3878 | I42: =H42-E42 -> -802 | J42: =IF(H42>0,C42-H42,F42) -> 2267.3878
A43: Office Materials and Supplies | C43: ='Provider Planning Budget'!H74 -> 2302.0408 | D43: =C43/(A$63-C$13-C$14)*D$5*D$65 -> 0 | E43: 18 | F43: =C43+D43-E43 -> 2284.0408 | I43: =H43-E43 -> -18 | J43: =IF(H43>0,C43-H43,F43) -> 2284.0408
A44: Food-Related Paper Supplies | C44: ='Provider Planning Budget'!H75 -> 767.34694 | D44: =C44/(A$63-C$13-C$14)*D$5*D$65 -> 0 | F44: =C44+D44-E44 -> 767.34694 | I44: =H44-E44 -> 0 | J44: =IF(H44>0,C44-H44,F44) -> 767.34694
A45: Cleaning Supplies | C45: ='Provider Planning Budget'!H76 -> 767.34694 | D45: =C45/(A$63-C$13-C$14)*D$5*D$65 -> 0 | E45: 90 | F45: =C45+D45-E45 -> 677.34694 | I45: =H45-E45 -> -90 | J45: =IF(H45>0,C45-H45,F45) -> 677.34694
A46: Food for Meetings | C46: ='Provider Planning Budget'!H77 -> 383.67347 | D46: =C46/(A$63-C$13-C$14)*D$5*D$65 -> 0 | F46: =C46+D46-E46 -> 383.67347 | I46: =H46-E46 -> 0 | J46: =IF(H46>0,C46-H46,F46) -> 383.67347
A47: Building/Grounds Maintenance/Repair | C47: ='Provider Planning Budget'!H78 -> 3836.7347 | D47: =C47/(A$63-C$13-C$14)*D$5*D$65 -> 0 | E47: 567 | F47: =C47+D47-E47 -> 3269.7347 | I47: =H47-E47 -> -567 | J47: =IF(H47>0,C47-H47,F47) -> 3269.7347
A48: Utilities | C48: ='Provider Planning Budget'!H79 -> 7673.4694 | D48: =C48/(A$63-C$13-C$14)*D$5*D$65 -> 0 | E48: 3906 | F48: =C48+D48-E48 -> 3767.4694 | I48: =H48-E48 -> -3906 | J48: =IF(H48>0,C48-H48,F48) -> 3767.4694
A49: Telecommunications Services | C49: ='Provider Planning Budget'!H80 -> 1688.1633 | D49: =C49/(A$63-C$13-C$14)*D$5*D$65 -> 0 | E49: 249 | F49: =C49+D49-E49 -> 1439.1633 | I49: =H49-E49 -> -249 | J49: =IF(H49>0,C49-H49,F49) -> 1439.1633
A50: Security Equipment | C50: ='Provider Planning Budget'!H81 -> 306.93878 | D50: =C50/(A$63-C$13-C$14)*D$5*D$65 -> 0 | E50: 194 | F50: =C50+D50-E50 -> 112.93878 | I50: =H50-E50 -> -194 | J50: =IF(H50>0,C50-H50,F50) -> 112.93878
A51: Insurance | C51: ='Provider Planning Budget'!H82 -> 4604.0816 | D51: =C51/(A$63-C$13-C$14)*D$5*D$65 -> 0 | E51: 1351 | F51: =C51+D51-E51 -> 3253.0816 | I51: =H51-E51 -> -1351 | J51: =IF(H51>0,C51-H51,F51) -> 3253.0816
A52: Accounting Fees | C52: ='Provider Planning Budget'!H83 -> 5371.4286 | D52: =C52/(A$63-C$13-C$14)*D$5*D$65 -> 0 | E52: 2566 | F52: =C52+D52-E52 -> 2805.4286 | I52: =H52-E52 -> -2566 | J52: =IF(H52>0,C52-H52,F52) -> 2805.4286
A53: Payroll Preparation Fees | C53: ='Provider Planning Budget'!H84 -> 1534.6939 | D53: =C53/(A$63-C$13-C$14)*D$5*D$65 -> 0 | E53: 537 | F53: =C53+D53-E53 -> 997.69388 | I53: =H53-E53 -> -537 | J53: =IF(H53>0,C53-H53,F53) -> 997.69388
A54: Advertising | C54: ='Provider Planning Budget'!H85 -> 383.67347 | D54: =C54/(A$63-C$13-C$14)*D$5*D$65 -> 0 | F54: =C54+D54-E54 -> 383.67347 | I54: =H54-E54 -> 0 | J54: =IF(H54>0,C54-H54,F54) -> 383.67347
A55: Staff Transportation | C55: ='Provider Planning Budget'!H86 -> 376 | D55: =C55/(A$63-C$13-C$14)*D$5*D$65 -> 0 | E55: 118 | F55: =C55+D55-E55 -> 258 | I55: =H55-E55 -> -118 | J55: =IF(H55>0,C55-H55,F55) -> 258
A56: Profit (if applicable) | C56: ='Provider Planning Budget'!H87 -> 0 | D56: =C56/(A$63-C$13-C$14)*D$5*D$65 -> 0 | F56: =C56+D56-E56 -> 0 | I56: =H56-E56 -> 0 | J56: =IF(H56>0,C56-H56,F56) -> 0
A57: ='Provider Planning Budget'!A91 -> (Insert item name or brief description on this line.) | C57: ='Provider Planning Budget'!I91 -> 0 | D57: =C57/(A$63-C$13-C$14)*D$5*D$65 -> 0 | F57: =C57+D57-E57 -> 0 | I57: =H57-E57 -> 0 | J57: =IF(H57>0,C57-H57,F57) -> 0
A58: ='Provider Planning Budget'!A92 -> (Insert item name or brief description on this line.) | C58: ='Provider Planning Budget'!I92 -> 0 | D58: =C58/(A$63-C$13-C$14)*D$5*D$65 -> 0 | F58: =C58+D58-E58 -> 0 | I58: =H58-E58 -> 0 | J58: =IF(H58>0,C58-H58,F58) -> 0
A59: ='Provider Planning Budget'!A93 -> (Insert item name or brief description on this line.) | C59: ='Provider Planning Budget'!I93 -> 0 | D59: =C59/(A$63-C$13-C$14)*D$5*D$65 -> 0 | F59: =C59+D59-E59 -> 0 | I59: =H59-E59 -> 0 | J59: =IF(H59>0,C59-H59,F59) -> 0
A60: ='Provider Planning Budget'!A94 -> (Insert item name or brief description on this line.) | C60: ='Provider Planning Budget'!I94 -> 0 | D60: =C60/(A$63-C$13-C$14)*D$5*D$65 -> 0 | F60: =C60+D60-E60 -> 0 | I60: =H60-E60 -> 0 | J60: =IF(H60>0,C60-H60,F60) -> 0
A61: ='Provider Planning Budget'!A95 -> (Insert item name or brief description on this line.) | C61: ='Provider Planning Budget'!I95 -> 0 | D61: =C61/(A$63-C$13-C$14)*D$5*D$65 -> 0 | F61: =C61+D61-E61 -> 0 | I61: =H61-E61 -> 0 | J61: =IF(H61>0,C61-H61,F61) -> 0
D62: =C62/(A$63-C$13-C$14)*D$5*D$65 -> 0 | F62: =C62+D62-E62 -> 0 | I62: =H62-E62 -> 0 | J62: =IF(H62>0,C62-H62,F62) -> 0
A63: =SUM(C7:C25,C28:C39,C41:C62) -> 614716.82 | D63: =SUM(D7:D25,D28:D39,D41:D62) -> 0
A64: TOTAL CASH PAID OUT | D64: =D65*D5 -> 0 | E64: =SUM(E7:E25,E28:E39,E41:E62) -> 96645.535 | F64: =SUM(F7:F25,F28:F39,F41:F62) -> 518071.28 | G64: =SUM(G7:G25,G28:G39,G41:G62) -> 0 | H64: =SUM(H7:H25,H28:H39,H41:H62) -> 0 | I64: =SUM(I7:I25,I28:I39,I41:I62) -> -96645.535 | J64: =SUM(J7:J25,J28:J39,J41:J62) -> 518071.28
C65: =A63/10/75 -> 819.62242 | D65: =(A63-C13-C14)/10/M1 -> 1346.0374

Sheet GL Q1
A1: URBAN LEAGUE OF ESSEX COUNTY
A2: General Ledger.111.Abbott PreSchool
A3: July - September, 2019
B5: Date | C5: Transaction Type | D5: Num | E5: Name | F5: Memo/Description | G5: Class | H5: Debit | I5: Credit
A6: 7200 Salaries & Related Expenses
A7: 7220 Salaries & Wages
A8: 7222 Staff
A9: 7222h Teacher
B10: Beginning Balance
B11: 07/31/2019 | C11: Journal Entry | D11: 00127 Salaries | F11: Salary Allocation - July | G11: 111 Abbott | H11: 8298.87
B12: 08/31/2019 | C12: Journal Entry | D12: 175 | F12: Salary Allocation - August | G12: 111 Abbott | H12: 8175.82
B13: 09/25/2019 | C13: Journal Entry | D13: 242 | F13: Salary Allocation - September | G13: 111 Abbott | H13: =25010.78-567.9 -> 24442.88
A14: Total for 7222h Teacher | H14: =SUM(H11:H13) -> 40917.57 | J14: 40917.57
A15: Total for 7222 Staff | H15: =SUM(H14) -> 40917.57
A16: Total for 7220 Salaries & Wages | H16: =SUM(H15) -> 40917.57
A17: 7240 Employee Benefits
A18: 7241 Health Insurance
B19: Beginning Balance
B20: 07/31/2019 | C20: Journal Entry | D20: 153 | G20: 111 Abbott | H20: 6712
B21: 08/30/2019 | C21: Journal Entry | D21: 202 | F21: Employee Health Insurance 08/15/19 - 09/15/19 | G21: 111 Abbott | H21: 6712
B22: 09/01/2019 | C22: Bill | D22: 292271815 | E22: Horizon Blue Cross Blue Shield of NJ | F22: To record Horizon Exp. Billing Period 9/15/19 - 10/15/19 | G22: 111 Abbott | H22: 6712
A23: Total for 7241 Health Insurance | H23: =SUM(H20:H22) -> 20136 | J23: 20135.58
A24: 7242 Life and Dental Insurance
B25: Beginning Balance
B26: 07/31/2019 | C26: Journal Entry | D26: 00132 Benefits | G26: 111 Abbott | H26: 454.62
B27: 08/31/2019 | C27: Journal Entry | D27: 208 | G27: 111 Abbott | H27: 454.62
B28: 09/01/2019 | C28: Bill | D28: 09.01.19PL | E28: Principal Financial Group | F28: Life, Dental & AD&D - ABBOTT | G28: 111 Abbott | H28: 390.74
A29: Total for 7242 Life and Dental Insurance | H29: =SUM(H26:H28) -> 1299.98 | J29: 1299.98
A30: Total for 7240 Employee Benefits | H30: =H23+H29 -> 21435.98 | I30: 3216.34
A31: 7250 Payroll Taxes, etc.
A32: 7245 Worker's Compensation Insurance
A33: 7248 Allocated W Comp
B34: Beginning Balance
B35: 07/31/2019 | C35: Journal Entry | D35: 139 | F35: Workers Comp Alloc | G35: 111 Abbott | H35: 324.42
B36: 08/31/2019 | C36: Journal Entry | D36: 192 | F36: Workers Comp Alloc | G36: 111 Abbott | H36: 235
B37: 09/30/2019 | C37: Journal Entry | D37: 272 | F37: Workers Comp Alloc | G37: 111 Abbott | H37: 782
A38: Total for 7248 Allocated W Comp | H38: 1341.42
A39: Total for 7245 Worker's Compensation Insurance | H39: 1341.42 | J39: 1227.53
A40: 7260 Payroll Service Fees
A41: 7260.1 Allocated Payroll Fees
B42: Beginning Balance
B43: 07/31/2019 | C43: Journal Entry | D43: 146 | F43: Payroll Fees | G43: 111 Abbott | H43: 122.73
B44: 08/31/2019 | C44: Journal Entry | D44: 198 | F44: Payroll Fees | G44: 111 Abbott | H44: 102
B45: 09/30/2019 | C45: Journal Entry | D45: 251 | F45: Payroll Fees | G45: 111 Abbott | H45: 312
A46: Total for 7260.1 Allocated Payroll Fees | H46: 536.73
A47: Total for 7260 Payroll Service Fees | H47: 536.73
A48: Total for 7200 Salaries & Related Expenses | H48: 65361.89 | I48: 3216.34
A49: 7500 Contract Service Expenses
A50: 7515 IT Support
A51: 7515.5 Allocated IT consultants
B52: Beginning Balance
B53: 07/31/2019 | C53: Journal Entry | D53: 142 | F53: IT Consultants | G53: 111 Abbott | H53: 212.09
B54: 08/31/2019 | C54: Journal Entry | D54: 181 | F54: IT Consultants | G54: 111 Abbott | H54: 181
B55: 09/30/2019 | C55: Journal Entry | D55: 252 | F55: IT Consultants | G55: 111 Abbott | H55: 629
A56: Total for 7515.5 Allocated IT consultants | H56: 1022.09
A57: Total for 7515 IT Support | H57: 1022.09
A58: 7520 Accounting Fees
A59: 7521 Allocated Acctg and Audit
B60: Beginning Balance
B61: 07/31/2019 | C61: Journal Entry | D61: 145 | F61: Acctg Fee Alloc | G61: 111 Abbott | H61: 1303.86
B62: 08/31/2019 | C62: Journal Entry | D62: 180 | F62: Acctg Fee Alloc | G62: 111 Abbott | H62: 237
B63: 09/30/2019 | C63: Journal Entry | D63: 253 | F63: Acctg Fee Alloc | G63: 111 Abbott | H63: 1025
A64: Total for 7521 Allocated Acctg and Audit | H64: 2565.86
A65: Total for 7520 Accounting Fees | H65: 2565.86
A66: Total for 7500 Contract Service Expenses | H66: 3587.95
A67: 8100 Operating Expenses
A68: 8108 Program Supplies
B69: Beginning Balance
A70: Total for 8108 Program Supplies
A71: 8110 Supplies
B72: Beginning Balance
A73: Total for 8110 Supplies
A74: 8112 Alloc Supplies
B75: Beginning Balance
B76: 07/31/2019 | C76: Journal Entry | D76: 144 | F76: Supplies Alloc | G76: 111 Abbott | H76: 48.58
B77: 08/31/2019 | C77: Journal Entry | D77: 185 | F77: Supplies Alloc | G77: 111 Abbott | H77: 41
A78: Total for 8112 Alloc Supplies | H78: 89.58
A79: Total for 8110 Supplies with subs | H79: 89.58
A80: 8130 Telephone & Telecommunications
A81: 8135.5 Allocated Telephone
B82: Beginning Balance
B83: 07/31/2019 | C83: Journal Entry | D83: 147 | F83: Telephone | G83: 111 Abbott | H83: 62.14
B84: 08/31/2019 | C84: Journal Entry | D84: 187 | F84: Telephone | G84: 111 Abbott | H84: 53
B85: 09/30/2019 | C85: Journal Entry | D85: 262 | F85: Telephone | G85: 111 Abbott | H85: 134
A86: Total for 8135.5 Allocated Telephone | H86: 249.14
A87: Total for 8130 Telephone & Telecommunications | H87: 249.14
A88: 8140 Postage & Shipping
B89: 08/31/2019 | C89: Journal Entry | D89: 196 | F89: Postage | G89: 111 Abbott | H89: 18
A90: Total for 8140 Postage & Shipping | H90: 18
A91: 8160 Computer Software & Hardware
A92: 8161 Allocated Comp -Software
B93: Beginning Balance
A94: Total for 8161 Allocated Comp -Software
A95: Total for 8160 Computer Software & Hardware
A96: 8191 Web Hosting Alloc
B97: Beginning Balance
B98: 07/31/2019 | C98: Journal Entry | D98: 152 | F98: Web hosting | G98: 111 Abbott | H98: 22.01
B99: 08/31/2019 | C99: Journal Entry | D99: 188 | F99: Web hosting | G99: 111 Abbott | H99: 19
B100: 09/30/2019 | C100: Journal Entry | D100: 254 | F100: Web hosting | G100: 111 Abbott | H100: 65
A101: Total for 8191 Web Hosting Alloc | H101: 106.01
...

Sheet Salary Alloc Q1
B1: Abbott Staffing
B3: For the Quarter ending September 30, 2019
I6: Total
N7: 0.03
E8: Annual Salary | F8: Budget | H8: July - Sept | I8: Abbott | J8: Other | K8: Food | L8: Facilites | M8: Wrap Around | N8: Workers Comp
B9: Teachers | C9: 3 | G9: =F9/E14 -> 0 | I9: =H9*K7 -> 0
D10: Jhonny Janvier | E10: 58583
D11: Bertrilla Simons | E11: 57717 | H11: 3452.38 | I11: 3452.38 | N11: =I11*$N$7 -> 103.5714
D12: Mellisa Thorpe | E12: 53261
D13: Quintella Hollins | H13: 2979.83 | I13: 2979.83
E14: =SUM(E10:E13) -> 169561 | F14: 169561
B15: Teacher Assistants | C15: 3 | D15: W Hill | G15: =F15/E19 -> 0
D16: R Stewart | E16: 34413 | H16: 2100.52 | I16: 2100.52 | N16: =I16*$N$7 -> 63.0156
D17: Niquita Loftin | E17: 25872 | H17: 975 | I17: 975 | N17: =I17*$N$7 -> 29.25
D18: R Bryant | E18: 26551 | H18: 1625.38 | I18: 1625.38 | N18: =I18*$N$7 -> 48.7614 | O18: =SUM(N11:N18) -> 244.5984
E19: =SUM(E15:E18) -> 86836 | F19: 86836
B20: Wrap Worker | D20: R Woodridge | H20: 3150 | M20: 3150
N22: =I22*$N$7 -> 0
B23: Floater | C23: 0.5 | D23: S Rambaran | E23: 19800 | F23: 19800 | G23: =F23/E23 -> 1 | H23: 862.54 | I23: 862.54 | N23: =I23*$N$7 -> 25.8762 | O23: =N23 -> 25.8762
N24: =I24*$N$7 -> 0
B25: Substitutes | D25: D Brown | G25: 1 | H25: 3337.5 | I25: 3337.5 | N25: =I25*$N$7 -> 100.125 | O25: =SUM(N23:N25) -> 126.0012 | P25: =SUM(O18:O25) -> 396.4758
N26: =I26*$N$7 -> 0
B27: Family Worker | C27: 1 | D27: Daphne McMillan | E27: 30076 | F27: 24552 | G27: =F27/E27 -> 0.81633196 | H27: 5965.44 | I27: =H27*G27 -> 4869.7793 | J27: =H27-I27 -> 1095.6607 | N27: =I27*$N$7 -> 146.09338 | O27: Unallow
J28: =H28*I1 -> 0 | N28: =I28*$N$7 -> 0
B29: Cook | C29: 0.5 | D29: P Tyler | E29: 19549 | F29: 7500 | G29: =F29/E29 -> 0.38365134 | H29: 1106.38 | I29: =H29*G29 -> 424.46417 | J29: =H29-I29 -> 681.91583 | N29: =I29*$N$7 -> 12.733925 | O29: Unallow
F30: =SUM(F9:F29) -> 308249 | H30: =SUM(H9:H29) -> 25554.97 | I30: =SUM(I9:I29) -> 20627.393 | J30: =SUM(J9:J29) -> 1777.5765 | K30: =SUM(K9:K29) -> 0 | M30: =SUM(M9:M29) -> 3150 | N30: =SUM(N9:N29) -> 529.4269
B33: Program Director | C33: 1 | D33: Heather Dance | E33: 70000 | F33: 57580 | G33: =F33/E33 -> 0.82257143 | H33: 16153.86 | I33: =H33*G33 -> 13287.704 | J33: =H33-I33 -> 2866.1563 | N33: =I33*$N$7 -> 398.63111 | O33: =N33*G33 -> 327.90256
J34: =H34*I7 -> 0 | N34: =I34*$N$7 -> 0
B35: Clerical | C35: 0.5 | D35: S Alford | E35: 10000 | F35: 3837 | G35: =F35/E35 -> 0.3837 | H35: 8676.96 | I35: =H35*G35 -> 3329.3496 | J35: =H35-I35 -> 5347.6104 | N35: =I35*$N$7 -> 99.880487 | O35: Unallow
N36: =I36*$N$7 -> 0
B37: Custodian | C37: 1 | D37: P Bennett | E37: 22000 | F37: 8441 | G37: =F37/E37 -> 0.38368182 | H37: 3900 | I37: =H37*G37 -> 1496.3591 | J37: =H37-I37 -> 2403.6409 | N37: =I37*$N$7 -> 44.890773 | O37: Unallow
N38: =I38*$N$7 -> 0
B39: Security Guard | D39: Cora Andrews | E39: 20000 | F39: 15347 | G39: =F39/E39 -> 0.76735 | H39: 6720 | I39: =H39*G39 -> 5156.592 | J39: =H39-I39 -> 1563.408 | N39: =I39*$N$7 -> 154.69776 | O39: Unallow
F40: =SUM(F33:F39) -> 85205 | H40: =SUM(H33:H39) -> 35450.82 | I40: =SUM(I33:I39) -> 23270.004 | J40: =SUM(J33:J39) -> 12180.816 | K40: =SUM(K33:K39) -> 0 | L40: =SUM(L33:L39) -> 0 | M40: =SUM(M33:M39) -> 0 | N40: =SUM(N33:N39) -> 698.10013
F45: =SUM(F42:F44) -> 0 | I45: =SUM(I42:I44) -> 0 | M45: =SUM(M42:M44) -> 0 | N45: =SUM(N42:N44) -> 0
F47: =F30+F40+F45 -> 393454 | H47: =H30+H40+H45 -> 61005.79 | I47: =I30+I40+I45 -> 43897.398 | J47: =J30+J40+J45 -> 13958.392 | K47: =K30+K40+K45 -> 0 | L47: =L30+L40+L45 -> 0 | M47: =M30+M40+M45 -> 3150 | N47: =N30+N40+N45 -> 1227.527
I48: Abbott | J48: Other | K48: Food | L48: =L8 -> Facilites | M48: Wrap Around
J50: =J47/$H$47 -> 0.22880438 | K50: =K47/$H$47 -> 0 | L50: =L47/$H$47 -> 0 | M50: =M47/$H$47 -> 0.051634443

Sheet Benefit Q1
B1: Abbott Staffing
B3: For the Quarter ending September 30, 2019
F6: Total | M6: =SUM(M9:M15) -> 281.69
E7: Health Ins | J7: Dental Ins | N7: Total | O7: Rate | P7: Allocated
D8: Budget | E8: Q1 | F8: July | G8: August | H8: Sept | J8: Q1 | K8: July | L8: August | M8: Sept | N8: Q1
B9: Teachers | C9: Johnny Javier | D9: 46750 | E9: =SUM(F9:H9) -> 1989.99 | F9: 663.33 | G9: 663.33 | H9: 663.33 | J9: =SUM(K9:M9) -> 236.67 | K9: 78.89 | L9: 78.89 | M9: 78.89 | N9: =E9+J9 -> 2226.66 | O9: 1 | P9: =N9*O9 -> 2226.66
C10: Bertrilla Simons | E10: =SUM(F10:H10) -> 2344.74 | F10: 781.58 | G10: 781.58 | H10: 781.58 | J10: =SUM(K10:M10) -> 233.13 | K10: 77.71 | L10: 77.71 | M10: 77.71 | N10: =E10+J10 -> 2577.87 | O10: 1 | P10: =N10*O10 -> 2577.87
C11: Rita Castellanos | E11: =SUM(F11:H11) -> 0 | J11: =SUM(K11:M11) -> 0 | N11: =E11+J11 -> 0 | P11: =N11*O11 -> 0
E12: =SUM(F12:H12) -> 0 | J12: =SUM(K12:M12) -> 0 | N12: =E12+J12 -> 0 | P12: =N12*O12 -> 0
B13: Teacher Assistants | C13: W Hill | D13: 0 | E13: =SUM(F13:H13) -> 0 | J13: =SUM(K13:M13) -> 182.07 | K13: 60.69 | L13: 60.69 | M13: 60.69 | N13: =E13+J13 -> 182.07 | O13: 1 | P13: =N13*O13 -> 182.07
C14: R Stewart | E14: =SUM(F14:H14) -> 3355.95 | F14: 1118.65 | G14: 1118.65 | H14: 1118.65 | J14: =SUM(K14:M14) -> 193.2 | K14: 64.4 | L14: 64.4 | M14: 64.4 | N14: =E14+J14 -> 3549.15 | O14: 1 | P14: =N14*O14 -> 3549.15
C15: R Bryant | E15: =SUM(F15:H15) -> 2637.63 | F15: 879.21 | G15: 879.21 | H15: 879.21 | J15: =SUM(K15:M15) -> 0 | N15: =E15+J15 -> 2637.63 | O15: 1 | P15: =N15*O15 -> 2637.63 | Q15: =SUM(P9:P15) -> 11173.38
E16: =SUM(F16:H16) -> 0 | J16: =SUM(K16:M16) -> 0 | N16: =E16+J16 -> 0 | P16: =N16*O16 -> 0 | Q16: =SUM(Q10:Q15) -> 11173.38
B17: Floater | C17: S Rambaran | D17: 0 | E17: =SUM(F17:H17) -> 0 | J17: =SUM(K17:M17) -> 0 | N17: =E17+J17 -> 0 | P17: =N17*O17 -> 0
C18: D Brown | E18: =SUM(F18:H18) -> 0 | J18: =SUM(K18:M18) -> 0 | N18: =E18+J18 -> 0 | P18: =N18*O18 -> 0
C19: R Woodridge | E19: =SUM(F19:H19) -> 0 | J19: =SUM(K19:M19) -> 0 | N19: =E19+J19 -> 0 | P19: =N19*O19 -> 0
E20: =SUM(F20:H20) -> 0 | J20: =SUM(K20:M20) -> 0 | N20: =E20+J20 -> 0 | P20: =N20*O20 -> 0
B21: Substitutes | C21: N Muhammad | D21: 0 | E21: =SUM(F21:H21) -> 0 | J21: =SUM(K21:M21) -> 0 | N21: =E21+J21 -> 0 | P21: =N21*O21 -> 0
E22: =SUM(F22:H22) -> 0 | J22: =SUM(K22:M22) -> 0 | N22: =E22+J22 -> 0 | P22: =N22*O22 -> 0
B23: Family Worker | C23: Daphne McMillan | D23: 0 | E23: =SUM(F23:H23) -> 2799.567 | F23: 933.189 | G23: 933.189 | H23: 933.189 | J23: =SUM(K23:M23) -> 0 | N23: =E23+J23 -> 2799.567 | O23: 1 | P23: =N23*O23 -> 2799.567 | Q23: Unallow
D24: 0 | E24: =SUM(F24:H24) -> 0 | J24: =SUM(K24:M24) -> 0 | N24: =E24+J24 -> 0 | P24: =N24*O24 -> 0
B25: Cook | C25: P Tyler | D25: 0 | E25: =SUM(F25:H25) -> 0 | J25: =SUM(K25:M25) -> 0 | N25: =E25+J25 -> 0 | P25: =N25*O25 -> 0
D26: =SUM(D9:D25) -> 46750 | E26: =SUM(E9:E25) -> 13127.877 | F26: =SUM(F9:F25) -> 4375.959 | G26: =SUM(G9:G25) -> 4375.959 | H26: =SUM(H9:H25) -> 4375.959 | J26: =SUM(J9:J25) -> 845.07 | K26: =SUM(K9:K25) -> 281.69 | L26: =SUM(L9:L25) -> 281.69 | M26: =SUM(M9:M25) -> 281.69 | N26: =SUM(N9:N25) -> 13972.947 | P26: =SUM(P9:P25) -> 13972.947
P27: =N27*O27 -> 0
N28: =E28+J28 -> 0 | P28: =N28*O28 -> 0
B29: Program Director | C29: Heather Dance | D29: 4220 | E29: =SUM(F29:H29) -> 4907.31 | F29: 1635.77 | G29: 1635.77 | H29: 1635.77 | J29: =SUM(K29:M29) -> 327.15 | K29: 109.05 | L29: 109.05 | M29: 109.05 | N29: =E29+J29 -> 5234.46 | O29: ='Salary Alloc Q1'!G33 -> 0.82257143 | P29: =N29*O29 -> 4305.7172
E30: =SUM(F30:H30) -> 0 | J30: =SUM(K30:M30) -> 0 | N30: =E30+J30 -> 0 | P30: =N30*O30 -> 0
B31: Clerical | C31: S Alford | D31: 2406 | E31: =SUM(F31:H31) -> 2100.39 | F31: 700.13 | G31: 700.13 | H31: 700.13 | J31: =SUM(K31:M31) -> 127.76 | K31: 63.88 | L31: 63.88 | N31: =E31+J31 -> 2228.15 | O31: ='Salary Alloc Q1'!G35 -> 0.3837 | P31: =N31*O31 -> 854.94115 | Q31: Unallow
E32: =SUM(F32:H32) -> 0 | J32: =SUM(K32:M32) -> 0 | N32: =E32+J32 -> 0 | P32: =N32*O32 -> 0
B33: Custodian | C33: Darnell Davis | E33: =SUM(F33:H33) -> 0 | J33: =SUM(K33:M33) -> 0 | N33: =E33+J33 -> 0 | P33: =N33*O33 -> 0
E34: =SUM(F34:H34) -> 0 | J34: =SUM(K34:M34) -> 0 | N34: =E34+J34 -> 0 | P34: =N34*O34 -> 0
B35: Security Guard | C35: Cora Andrews | E35: =SUM(F35:H35) -> 0 | J35: =SUM(K35:M35) -> 0 | N35: =E35+J35 -> 0 | P35: =N35*O35 -> 0
D36: =SUM(D29:D35) -> 6626 | E36: =SUM(E29:E35) -> 7007.7 | F36: =SUM(F29:F35) -> 2335.9 | G36: =SUM(G29:G35) -> 2335.9 | H36: =SUM(H29:H35) -> 2335.9 | J36: =SUM(J29:J35) -> 454.91 | K36: =SUM(K29:K35) -> 172.93 | L36: =SUM(L29:L35) -> 172.93 | M36: =SUM(M29:M35) -> 109.05 | N36: =SUM(N29:N35) -> 7462.61 | P36: =SUM(P29:P35) -> 5160.6584
P37: =N37*O37 -> 0
P38: =N38*O38 -> 0
P39: =N39*O39 -> 0
P40: =N40*O40 -> 0
D41: =SUM(D38:D40) -> 0 | F41: =SUM(F38:F40) -> 0 | K41: =SUM(K38:K40) -> 0
D43: =D26+D36+D41 -> 53376 | E43: =E26+E36+E41 -> 20135.577 | F43: =F26+F36+F41 -> 6711.859 | G43: =G26+G36+G41 -> 6711.859 | H43: =H26+H36+H41 -> 6711.859 | J43: =J26+J36+J41 -> 1299.98 | K43: =K26+K36+K41 -> 454.62 | L43: =L26+L36+L41 -> 454.62 | M43: =M26+M36+M41 -> 390.74 | N43: =N26+N36+N41 -> 21435.557 | O43: =O26+O36+O41 -> 0 | P43: =P26+P36+P41 -> 19133.605

Sheet Quarter 2
J1: Total Number of Abbott Children | M1: ='Quarter 1'!M1 -> 45
D2: October - December Under Enrollment | E2: Provider Reported Expenditures | F2: Provider Balance Prior to Ependiture Review | G2: Budget Modification Approved by the District | H2: District Calculated Expenditures 2nd Quarter | I2: Unapproved Funds Expended (Oct. - Dec.) | J2: DOE Share of DOE/DHS Shared Costs | M2: ='Quarter 1'!M2 -> 0.7673
A3: Report Due Wednesday JANUARY 15, 2020 by 3:00PM | J3: Change DOE Share of DOE/DHS Shared Costs | M3: ='Quarter 1'!M3 -> 0
C4: NPS Approved | J4: DOE Share of Center-Wide Costs
A5: EXPENDITURES (Cash Paid Out) | C5: 2018-19 Budget | D5: 0 | E5: (Oct. - Dec.) | F5: (Oct. - Dec.) | H5: (Oct. - Dec.) | I5: (District Use) | J5: Fund Balance | K5: Comments
A6: EDUCATIONAL PROGRAM COSTS (Instructional) 10-MONTH COST ONLY EXCLUDING BENEFITS
A7: Teacher Salary | C7: ='Quarter 1'!J7 -> 166109 | D7: =C7/(A$63-C$13-C$14)*D$5*D$65 -> 0 | E7: ='Salary Report Q2'!O14 -> 43622.68 | F7: =C7+D7-E7 -> 122486.32 | I7: =H7-E7 -> -43622.68 | J7: =IF(H7>0,(C7+D7+G7-H7),F7+G7) -> 122486.32
A8: Teacher Assistant Salary | C8: ='Quarter 1'!J8 -> 82136 | D8: =C8/(A$63-C$13-C$14)*D$5*D$65 -> 0 | E8: ='Salary Report Q2'!O19 -> 28009.65 | F8: =C8+D8-E8 -> 54126.35 | I8: =H8-E8 -> -28009.65 | J8: =IF(H8>0,(C8+D8+G8-H8),F8+G8) -> 54126.35
A9: Floating Teacher Assistant Salary | C9: ='Quarter 1'!J9 -> 18937 | D9: =C9/(A$63-C$13-C$14)*D$5*D$65 -> 0 | E9: ='Salary Report Q2'!I24 -> 6083.9 | F9: =C9+D9-E9 -> 12853.1 | I9: =H9-E9 -> -6083.9 | J9: =IF(H9>0,(C9+D9+G9-H9),F9+G9) -> 12853.1
A10: Teacher, Assistant and Floater Benefits | C10: ='Quarter 1'!J10 -> 27426.75 | D10: =C10/(A$63-C$13-C$14)*D$5*D$65 -> 0 | E10: 8202 | F10: =C10+D10-E10 -> 19224.75 | I10: =H10-E10 -> -8202 | J10: =IF(H10>0,(C10+D10+G10-H10),F10+G10) -> 19224.75
A11: Substitute Teacher Daily Rate (Stipend) | C11: ='Quarter 1'!J11 -> -338 | D11: =C11/(A$63-C$13-C$14)*D$5*D$65 -> 0 | F11: =C11+D11-E11 -> -338 | I11: =H11-E11 -> 0 | J11: =IF(H11>0,(C11+D11+G11-H11),F11+G11) -> -338
A12: Substitute Assistant Daily Rate (Stipend) | C12: ='Quarter 1'!J12 -> 4800 | D12: =C12/(A$63-C$13-C$14)*D$5*D$65 -> 0 | E12: ='Salary Report Q2'!I26 -> 3112.8 | F12: =C12+D12-E12 -> 1687.2 | I12: =H12-E12 -> -3112.8 | J12: =IF(H12>0,(C12+D12+G12-H12),F12+G12) -> 1687.2
A13: Classroom Materials and Supplies | C13: ='Quarter 1'!J13 -> 3969 | E13: 436 | F13: =C13+D13-E13 -> 3533 | I13: =H13-E13 -> -436 | J13: =IF(H13>0,(C13+D13+G13-H13),F13+G13) -> 3533
A14: Classroom Technology | C14: ='Quarter 1'!J14 -> 3000 | F14: =C14+D14-E14 -> 3000 | I14: =H14-E14 -> 0 | J14: =IF(H14>0,(C14+D14+G14-H14),F14+G14) -> 3000
A15: Field Trips w/ Transportation | C15: ='Quarter 1'!J15 -> 3940 | D15: =C15/(A$63-C$13-C$14)*D$5*D$65 -> 0 | E15: 600 | F15: =C15+D15-E15 -> 3340 | I15: =H15-E15 -> -600 | J15: =IF(H15>0,(C15+D15+G15-H15),F15+G15) -> 3340
A16: Family Worker Salary | C16: ='Quarter 1'!J16 -> 19681.798 | D16: =C16/(A$63-C$13-C$14)*D$5*D$65 -> 0 | E16: ='Salary Report Q2'!I28 -> 6493.5289 | F16: =C16+D16-E16 -> 13188.269 | I16: =H16-E16 -> -6493.5289 | J16: =IF(H16>0,(C16+D16+G16-H16),F16+G16) -> 13188.269
A17: Family Worker Benefits | C17: ='Quarter 1'!J17 -> 0 | D17: =C17/(A$63-C$13-C$14)*D$5*D$65 -> 0 | F17: =C17+D17-E17 -> 0 | I17: =H17-E17 -> 0 | J17: =IF(H17>0,(C17+D17+G17-H17),F17+G17) -> 0
A18: Food CACFP; September - June (for contracted preschool children only) | C18: ='Quarter 1'!J18 -> 0 | D18: =C18/(A$63-C$13-C$14)*D$5*D$65 -> 0 | F18: =C18+D18-E18 -> 0 | I18: =H18-E18 -> 0 | J18: =IF(H18>0,(C18+D18+G18-H18),F18+G18) -> 0
A19: Food Worker Salary (cook) | C19: ='Quarter 1'!J19 -> 7076.4588 | D19: =C19/(A$63-C$13-C$14)*D$5*D$65 -> 0 | E19: ='Salary Report Q2'!I30 -> 1426.1203 | F19: =C19+D19-E19 -> 5650.3385 | I19: =H19-E19 -> -1426.1203 | J19: =IF(H19>0,(C19+D19+G19-H19),F19+G19) -> 5650.3385
A20: Food Worker Salary (cook asst.) | C20: ='Quarter 1'!J20 -> 0 | D20: =C20/(A$63-C$13-C$14)*D$5*D$65 -> 0 | F20: =C20+D20-E20 -> 0 | I20: =H20-E20 -> 0 | J20: =IF(H20>0,(C20+D20+G20-H20),F20+G20) -> 0
A21: Food Worker Benefits (Cook & Assist. Cook) | C21: ='Quarter 1'!J21 -> 0 | D21: =C21/(A$63-C$13-C$14)*D$5*D$65 -> 0 | F21: =C21+D21-E21 -> 0 | I21: =H21-E21 -> 0 | J21: =IF(H21>0,(C21+D21+G21-H21),F21+G21) -> 0 | K21: =E7+E8+E9+E16+E19 -> 85635.879
A22: Social Security (6.20%) | C22: ='Quarter 1'!J22 -> 18500.816 | D22: =C22/(A$63-C$13-C$14)*D$5*D$65 -> 0 | E22: =K21*K22 -> 5309.4245 | F22: =C22+D22-E22 -> 13191.391 | I22: =H22-E22 -> -5309.4245 | J22: =IF(H22>0,(C22+D22+G22-H22),F22+G22) -> 13191.391 | K22: 0.062
A23: Medicare (1.45%) | C23: ='Quarter 1'!J23 -> 4326.8327 | D23: =C23/(A$63-C$13-C$14)*D$5*D$65 -> 0 | E23: =K21*K23 -> 1241.7202 | F23: =C23+D23-E23 -> 3085.1125 | I23: =H23-E23 -> -1241.7202 | J23: =IF(H23>0,(C23+D23+G23-H23),F23+G23) -> 3085.1125 | K23: 0.0145
A24: Unemployment (2.80%) | C24: ='Quarter 1'!J24 -> 8355.2632 | D24: =C24/(A$63-C$13-C$14)*D$5*D$65 -> 0 | E24: =K21*K24 -> 2397.8046 | F24: =C24+D24-E24 -> 5957.4586 | I24: =H24-E24 -> -2397.8046 | J24: =IF(H24>0,(C24+D24+G24-H24),F24+G24) -> 5957.4586 | K24: 0.028
A25: Disability (0.50%) | C25: ='Quarter 1'!J25 -> 1492.0113 | D25: =C25/(A$63-C$13-C$14)*D$5*D$65 -> 0 | E25: =K21*K25 -> 428.1794 | F25: =C25+D25-E25 -> 1063.8319 | I25: =H25-E25 -> -428.1794 | J25: =IF(H25>0,(C25+D25+G25-H25),F25+G25) -> 1063.8319 | K25: 0.005
A26: Sub-Total | C26: =SUM(C7:C25) -> 369412.93 | D26: =SUM(D7:D25) -> 0 | E26: =SUM(E7:E25) -> 107363.81 | F26: =SUM(F7:F25) -> 262049.12 | G26: =SUM(G7:G25) -> 0 | H26: =SUM(H7:H25) -> 0 | I26: =SUM(I7:I25) -> -107363.81 | J26: =SUM(J7:J25) -> 262049.12
A27: ADMINISTRATIVE SUPPORT COSTS (NON-Instructional) 12-MONTH COST ONLY EXCLUDING BENEFITS
A28: Director Salary | C28: ='Quarter 1'!J28 -> 30895.837 | D28: =C28/(A$63-C$13-C$14)*D$5*D$65 -> 0 | E28: ='Salary Report Q2'!I34 -> 15502.321 | F28: =C28+D28-E28 -> 15393.516 | I28: =H28-E28 -> -15502.321 | J28: =IF(H28>0,(C28+D28+G28-H28),F28+G28) -> 15393.516
A29: Director Benefits | C29: ='Quarter 1'!J29 -> 3797.1837 | D29: =C29/(A$63-C$13-C$14)*D$5*D$65 -> 0 | E29: 4135 | F29: =C29+D29-E29 -> -337.81633 | I29: =H29-E29 -> -4135 | J29: =IF(H29>0,(C29+D29+G29-H29),F29+G29) -> -337.81633
A30: Clerical Salary | C30: ='Quarter 1'!J30 -> 507.73469 | D30: =C30/(A$63-C$13-C$14)*D$5*D$65 -> 0 | E30: ='Salary Report Q2'!H36 -> 0 | F30: =C30+D30-E30 -> 507.73469 | I30: =H30-E30 -> 0 | J30: =IF(H30>0,(C30+D30+G30-H30),F30+G30) -> 507.73469
A31: Clerical Benefits | C31: ='Quarter 1'!J31 -> 0 | D31: =C31/(A$63-C$13-C$14)*D$5*D$65 -> 0 | F31: =C31+D31-E31 -> 0 | I31: =H31-E31 -> 0 | J31: =IF(H31>0,(C31+D31+G31-H31),F31+G31) -> 0
A32: Janitor Salary | C32: ='Quarter 1'!J32 -> 6944.8163 | D32: =C32/(A$63-C$13-C$14)*D$5*D$65 -> 0 | E32: ='Salary Report Q2'!I38 -> 1715.8251 | F32: =C32+D32-E32 -> 5228.9912 | I32: =H32-E32 -> -1715.8251 | J32: =IF(H32>0,(C32+D32+G32-H32),F32+G32) -> 5228.9912
A33: Janitor Benefits | C33: ='Quarter 1'!J33 -> 0 | D33: =C33/(A$63-C$13-C$14)*D$5*D$65 -> 0 | F33: =C33+D33-E33 -> 0 | I33: =H33-E33 -> 0 | J33: =IF(H33>0,(C33+D33+G33-H33),F33+G33) -> 0
A34: Security Guard Salary | C34: ='Quarter 1'!J34 -> 10189.939 | D34: =C34/(A$63-C$13-C$14)*D$5*D$65 -> 0 | E34: ='Salary Report Q2'!I40 -> 6016.024 | F34: =C34+D34-E34 -> 4173.9148 | I34: =H34-E34 -> -6016.024 | J34: =IF(H34>0,(C34+D34+G34-H34),F34+G34) -> 4173.9148
A35: Secufity Guard Benefits | C35: ='Quarter 1'!J35 -> 0 | D35: =C35/(A$63-C$13-C$14)*D$5*D$65 -> 0 | F35: =C35+D35-E35 -> 0 | I35: =H35-E35 -> 0 | J35: =IF(H35>0,(C35+D35+G35-H35),F35+G35) -> 0 | K35: =E28+E32+E34 -> 23234.17
A36: Social Security (6.20%) | C36: ='Quarter 1'!J36 -> 3009.3762 | D36: =C36/(A$63-C$13-C$14)*D$5*D$65 -> 0 | E36: =K35*K36 -> 1440.5185 | F36: =C36+D36-E36 -> 1568.8577 | I36: =H36-E36 -> -1440.5185 | J36: =IF(H36>0,(C36+D36+G36-H36),F36+G36) -> 1568.8577 | K36: 0.062
A37: Medicare (1.45%) | C37: ='Quarter 1'!J37 -> 703.80573 | D37: =C37/(A$63-C$13-C$14)*D$5*D$65 -> 0 | E37: =K35*K37 -> 336.89547 | F37: =C37+D37-E37 -> 366.91027 | I37: =H37-E37 -> -336.89547 | J37: =IF(H37>0,(C37+D37+G37-H37),F37+G37) -> 366.91027 | K37: 0.0145
A38: Unemployment (2.80%) | C38: ='Quarter 1'!J38 -> 1359.0731 | D38: =C38/(A$63-C$13-C$14)*D$5*D$65 -> 0 | E38: =K35*K38 -> 650.55676 | F38: =C38+D38-E38 -> 708.51638 | I38: =H38-E38 -> -650.55676 | J38: =IF(H38>0,(C38+D38+G38-H38),F38+G38) -> 708.51638 | K38: 0.028
A39: Disability (0.50%) | C39: ='Quarter 1'!J39 -> 242.69163 | D39: =C39/(A$63-C$13-C$14)*D$5*D$65 -> 0 | E39: =K35*K39 -> 116.17085 | F39: =C39+D39-E39 -> 126.52078 | I39: =H39-E39 -> -116.17085 | J39: =IF(H39>0,(C39+D39+G39-H39),F39+G39) -> 126.52078 | K39: 0.005
A40: INDIRECT COSTS -- SPACE COSTS AND ALL OTHER ALLOWABLE INDIRECT (NON-Instructional) 12-MONTH COSTS
A41: Rent, Mortgage, Other Space Costs | C41: ='Quarter 1'!J41 -> 68340.914 | D41: =C41/(A$63-C$13-C$14)*D$5*D$65 -> 0 | E41: 22780 | F41: =C41+D41-E41 -> 45560.914 | I41: =H41-E41 -> -22780 | J41: =IF(H41>0,(C41+D41+G41-H41),F41+G41) -> 45560.914
A42: Office Equipment>$2000 and Repair | C42: ='Quarter 1'!J42 -> 2267.3878 | D42: =C42/(A$63-C$13-C$14)*D$5*D$65 -> 0 | E42: 1284 | F42: =C42+D42-E42 -> 983.38776 | I42: =H42-E42 -> -1284 | J42: =IF(H42>0,(C42+D42+G42-H42),F42+G42) -> 983.38776
A43: Office Materials and Supplies | C43: ='Quarter 1'!J43 -> 2284.0408 | D43: =C43/(A$63-C$13-C$14)*D$5*D$65 -> 0 | E43: 716 | F43: =C43+D43-E43 -> 1568.0408 | I43: =H43-E43 -> -716 | J43: =IF(H43>0,(C43+D43+G43-H43),F43+G43) -> 1568.0408
A44: Food-Related Paper Supplies | C44: ='Quarter 1'!J44 -> 767.34694 | D44: =C44/(A$63-C$13-C$14)*D$5*D$65 -> 0 | E44: 300 | F44: =C44+D44-E44 -> 467.34694 | I44: =H44-E44 -> -300 | J44: =IF(H44>0,(C44+D44+G44-H44),F44+G44) -> 467.34694
A45: Cleaning Supplies | C45: ='Quarter 1'!J45 -> 677.34694 | D45: =C45/(A$63-C$13-C$14)*D$5*D$65 -> 0 | E45: 200 | F45: =C45+D45-E45 -> 477.34694 | I45: =H45-E45 -> -200 | J45: =IF(H45>0,(C45+D45+G45-H45),F45+G45) -> 477.34694
A46: Food for Meetings | C46: ='Quarter 1'!J46 -> 383.67347 | D46: =C46/(A$63-C$13-C$14)*D$5*D$65 -> 0 | F46: =C46+D46-E46 -> 383.67347 | I46: =H46-E46 -> 0 | J46: =IF(H46>0,(C46+D46+G46-H46),F46+G46) -> 383.67347
A47: Building/Grounds Maintenance/Repair | C47: ='Quarter 1'!J47 -> 3269.7347 | D47: =C47/(A$63-C$13-C$14)*D$5*D$65 -> 0 | E47: 118 | F47: =C47+D47-E47 -> 3151.7347 | I47: =H47-E47 -> -118 | J47: =IF(H47>0,(C47+D47+G47-H47),F47+G47) -> 3151.7347
A48: Utilities | C48: ='Quarter 1'!J48 -> 3767.4694 | D48: =C48/(A$63-C$13-C$14)*D$5*D$65 -> 0 | E48: 4460 | F48: =C48+D48-E48 -> -692.53061 | I48: =H48-E48 -> -4460 | J48: =IF(H48>0,(C48+D48+G48-H48),F48+G48) -> -692.53061
A49: Telecommunications Services | C49: ='Quarter 1'!J49 -> 1439.1633 | D49: =C49/(A$63-C$13-C$14)*D$5*D$65 -> 0 | E49: 753 | F49: =C49+D49-E49 -> 686.16327 | I49: =H49-E49 -> -753 | J49: =IF(H49>0,(C49+D49+G49-H49),F49+G49) -> 686.16327
A50: Security Equipment | C50: ='Quarter 1'!J50 -> 112.93878 | D50: =C50/(A$63-C$13-C$14)*D$5*D$65 -> 0 | F50: =C50+D50-E50 -> 112.93878 | I50: =H50-E50 -> 0 | J50: =IF(H50>0,(C50+D50+G50-H50),F50+G50) -> 112.93878
A51: Insurance | C51: ='Quarter 1'!J51 -> 3253.0816 | D51: =C51/(A$63-C$13-C$14)*D$5*D$65 -> 0 | E51: 4051 | F51: =C51+D51-E51 -> -797.91837 | I51: =H51-E51 -> -4051 | J51: =IF(H51>0,(C51+D51+G51-H51),F51+G51) -> -797.91837
A52: Accounting Fees | C52: ='Quarter 1'!J52 -> 2805.4286 | D52: =C52/(A$63-C$13-C$14)*D$5*D$65 -> 0 | E52: 5856 | F52: =C52+D52-E52 -> -3050.5714 | I52: =H52-E52 -> -5856 | J52: =IF(H52>0,(C52+D52+G52-H52),F52+G52) -> -3050.5714
A53: Payroll Preparation Fees | C53: ='Quarter 1'!J53 -> 997.69388 | D53: =C53/(A$63-C$13-C$14)*D$5*D$65 -> 0 | E53: 1113 | F53: =C53+D53-E53 -> -115.30612 | I53: =H53-E53 -> -1113 | J53: =IF(H53>0,(C53+D53+G53-H53),F53+G53) -> -115.30612
A54: Advertising | C54: ='Quarter 1'!J54 -> 383.67347 | D54: =C54/(A$63-C$13-C$14)*D$5*D$65 -> 0 | F54: =C54+D54-E54 -> 383.67347 | I54: =H54-E54 -> 0 | J54: =IF(H54>0,(C54+D54+G54-H54),F54+G54) -> 383.67347
A55: Staff Transportation | C55: ='Quarter 1'!J55 -> 258 | D55: =C55/(A$63-C$13-C$14)*D$5*D$65 -> 0 | E55: 142 | F55: =C55+D55-E55 -> 116 | I55: =H55-E55 -> -142 | J55: =IF(H55>0,(C55+D55+G55-H55),F55+G55) -> 116
A56: Profit | C56: ='Quarter 1'!J56 -> 0 | D56: =C56/(A$63-C$13-C$14)*D$5*D$65 -> 0 | F56: =C56+D56-E56 -> 0 | I56: =H56-E56 -> 0 | J56: =IF(H56>0,(C56+D56+G56-H56),F56+G56) -> 0
A57: ='Quarter 1'!A57:B57 -> (Insert item name or brief description on this line.) | C57: ='Quarter 1'!J57 -> 0 | D57: =C57/(A$63-C$13-C$14)*D$5*D$65 -> 0 | F57: =C57+D57-E57 -> 0 | I57: =H57-E57 -> 0 | J57: =IF(H57>0,(C57+D57+G57-H57),F57+G57) -> 0
A58: ='Quarter 1'!A58:B58 -> (Insert item name or brief description on this line.) | C58: ='Quarter 1'!J58 -> 0 | D58: =C58/(A$63-C$13-C$14)*D$5*D$65 -> 0 | F58: =C58+D58-E58 -> 0 | I58: =H58-E58 -> 0 | J58: =IF(H58>0,(C58+D58+G58-H58),F58+G58) -> 0
A59: ='Quarter 1'!A59:B59 -> (Insert item name or brief description on this line.) | C59: ='Quarter 1'!J59 -> 0 | D59: =C59/(A$63-C$13-C$14)*D$5*D$65 -> 0 | F59: =C59+D59-E59 -> 0 | I59: =H59-E59 -> 0 | J59: =IF(H59>0,(C59+D59+G59-H59),F59+G59) -> 0
A60: ='Quarter 1'!A60:B60 -> (Insert item name or brief description on this line.) | C60: ='Quarter 1'!J60 -> 0 | D60: =C60/(A$63-C$13-C$14)*D$5*D$65 -> 0 | F60: =C60+D60-E60 -> 0 | I60: =H60-E60 -> 0 | J60: =IF(H60>0,(C60+D60+G60-H60),F60+G60) -> 0
A61: ='Quarter 1'!A61:B61 -> (Insert item name or brief description on this line.) | C61: ='Quarter 1'!J61 -> 0 | D61: =C61/(A$63-C$13-C$14)*D$5*D$65 -> 0 | F61: =C61+D61-E61 -> 0 | I61: =IF(H61>E61,0,H61-E61) -> 0 | J61: =IF(H61>0,(C61+D61+G61-H61),F61+G61) -> 0
C62: ='Quarter 1'!J62 -> 0 | D62: =C62/(A$63-C$13-C$14)*D$5*D$65 -> 0 | F62: =C62+D62-E62 -> 0 | I62: =IF(H62>E62,0,H62-E62) -> 0 | J62: =IF(H62>0,(C62+D62+G62-H62),F62+G62) -> 0
A63: =SUM(C$7:C$25,C$28:C$39,C$41:C$62) -> 518071.28 | D63: =SUM(D7:D25,D28:D39,D41:D62) -> 0
A64: TOTAL CASH PAID OUT | D64: =D65*D5 -> 0 | E64: =SUM(E7:E25,E28:E63) -> 179050.12 | F64: =SUM(F7:F25,F28:F63) -> 339021.16 | G64: =SUM(G7:G25,G28:G63) -> 0 | H64: =SUM(H7:H25,H28:H63) -> 0 | I64: =SUM(I7:I25,I28:I63) -> -179050.12 | J64: =SUM(J7:J25,J28:J63) -> 339021.16
C65: ='Quarter 1'!C65 -> 819.62242 | D65: ='Quarter 1'!D65 -> 1346.0374

Sheet GL Q2
A1: URBAN LEAGUE OF ESSEX COUNTY
A2: General Ledger.111 Abbott
A3: October - December, 2019
B5: Date | C5: Transaction Type | D5: Num | E5: Name | F5: Memo/Description | G5: Class | H5: Debit | I5: Credit | J5: Check #
A6: 7200 Salaries & Related Expenses
A7: 7220 Salaries & Wages
A8: 7222 Staff
A9: 7222h Teacher
B10: Beginning Balance
B11: 10/31/2019 | C11: Journal Entry | D11: 19-437 | F11: Salary Allocation - October | G11: 111 Abbott | H11: 31023.86
B12: 11/30/2019 | C12: Journal Entry | D12: 39 | F12: Salary Allocation - November | G12: 111 Abbott | H12: 46682
B13: 12/31/2019 | C13: Journal Entry | D13: 121 | F13: Salary Allocation - December | G13: 111 Abbott | H13: 31274
A14: Total for 7222h Teacher | H14: 108979.86
A15: Total for 7222 Staff | H15: 108979.86
A16: Total for 7220 Salaries & Wages | H16: 108979.86
A17: 7240 Employee Benefits
A18: 7241 Health Insurance
B19: Beginning Balance
B20: 10/11/2019 | C20: Bill | D20: 292534359 | E20: Horizon Blue Cross Blue Shield of NJ | F20: To record Horizon Exp. Billing Period10/15/19 - 11/15/19 | G20: 111 Abbott | H20: 6289.53 | J20: 12569
B21: 11/01/2019 | C21: Bill | D21: 292676700 | E21: Horizon Blue Cross Blue Shield of NJ | F21: To record Horizon Exp. Billing Period 11/15/19 - 12/15/19 | G21: 111 Abbott | H21: 6576.95 | J21: 12658
B22: 12/01/2019 | C22: Bill | D22: 292879522 | E22: Horizon Blue Cross Blue Shield of NJ | F22: To record Horizon Exp. Billing Period 12/15/19 - 01/15/20 | G22: 111 Abbott | H22: 6576.97 | J22: 12820
A23: Total for 7241 Health Insurance | H23: 19443.45
A24: 7242 Life and Dental Insurance
B25: Beginning Balance
B26: 10/01/2019 | C26: Bill | D26: 10.01.19PL | E26: Principal Financial Group | F26: Life, Dental & AD&D | G26: 111 Abbott | H26: 412.41 | J26: 12527
B27: 11/01/2019 | C27: Bill | D27: 11.01.19PG | E27: Principal Financial Group | F27: Life, Dental & AD&D | G27: 111 Abbott | H27: 2392.96 | J27: 12665
B28: 12/01/2019 | C28: Bill | D28: 12.01.19PG | E28: Principal Financial Group | F28: Life, Dental & AD&D | G28: 111 Abbott | H28: 439.2 | J28: 12822
A29: Total for 7242 Life and Dental Insurance | H29: 3244.57
A30: 7243 Disability Ins
B31: Beginning Balance
B32: 12/01/2019 | C32: Bill | D32: 12.01.19DN | E32: Dearborn Life Insurance Co. | F32: Life Insurance for the Period: 12/01/19 - 02/29/20 | G32: 111 Abbott | H32: 25.5 | J32: 12819
A33: Total for 7243 Disability Ins | H33: 25.5
A34: 7244 Employee Contrib - Health
B35: Beginning Balance
B36: 10/31/2019 | C36: Journal Entry | D36: 63 | F36: Employee Medical Contrib | G36: 111 Abbott | I36: 1084.8
B37: 11/30/2019 | C37: Journal Entry | D37: 64 | F37: Employee Medical Contrib | G37: 111 Abbott | I37: 2109.46
B38: 12/31/2019 | C38: Journal Entry | D38: 137 | F38: Employee Medical Contrib | G38: 111 Abbott | I38: 1406
A39: Total for 7244 Employee Contrib - Health | I39: 4600.26
A40: 7247 Emp-ee Contrib -Dental
B41: Beginning Balance
B42: 10/31/2019 | C42: Journal Entry | D42: 65 | F42: Employee Dental Contrib | G42: 111 Abbott | I42: 20.97
B43: 11/30/2019 | C43: Journal Entry | D43: 66 | F43: Employee Dental Contrib | G43: 111 Abbott | I43: 39.14
B44: 12/31/2019 | C44: Journal Entry | D44: 138 | F44: Employee Dental Contrib | G44: 111 Abbott | I44: 49
B45: 12/31/2019 | C45: Journal Entry | D45: 138 | F45: Employee Dental Contrib | G45: 111 Abbott | I45: 9
A46: Total for 7247 Emp-ee Contrib -Dental | I46: 118.11
A47: Total for 7240 Employee Benefits | H47: 22713.52 | I47: 4718.37
A48: 7250 Payroll Taxes, etc.
A49: 7245 Worker's Compensation Insurance
A50: 7248 Allocated W Comp
B51: Beginning Balance
B52: 10/30/2019 | C52: Journal Entry | D52: 57 | F52: Workers Comp Alloc | G52: 111 Abbott | H52: 919
B53: 11/30/2019 | C53: Journal Entry | D53: 56 | F53: Workers Comp Alloc | G53: 111 Abbott | H53: 1106
B54: 12/30/2019 | C54: Journal Entry | D54: 123 | F54: Workers Comp Alloc | G54: 111 Abbott | H54: 928
A55: Total for 7248 Allocated W Comp | H55: 2953
A56: Total for 7245 Worker's Compensation Insurance | H56: 2953
A57: 7251 Social Security
B58: Beginning Balance
B59: 10/30/2019 | C59: Journal Entry | D59: 22 | F59: Fica | G59: 111 Abbott | H59: 1832
B60: 11/30/2019 | C60: Journal Entry | D60: 53 | F60: Fica | G60: 111 Abbott | H60: 2706
B61: 12/30/2019 | C61: Journal Entry | D61: 132 | F61: Fica | G61: 111 Abbott | H61: 1702
A62: Total for 7251 Social Security | H62: 6240
A63: 7252 Medicare
B64: Beginning Balance
B65: 10/30/2019 | C65: Journal Entry | D65: 26 | F65: Medi Alloc | G65: 111 Abbott | H65: 428
B66: 11/30/2019 | C66: Journal Entry | D66: 49 | F66: Medi Alloc | G66: 111 Abbott | H66: 660
B67: 12/30/2019 | C67: Journal Entry | D67: 131 | F67: Medi Alloc | G67: 111 Abbott | H67: 443
A68: Total for 7252 Medicare | H68: 1531
A69: 7253 Unemployment
B70: Beginning Balance
B71: 10/30/2019 | C71: Journal Entry | D71: 30 | F71: SUI Alloc | G71: 111 Abbott | H71: 439
B72: 11/30/2019 | C72: Journal Entry | D72: 45 | F72: SUI Alloc | G72: 111 Abbott | H72: 661
B73: 12/30/2019 | C73: Journal Entry | D73: 127 | F73: SUI Alloc | G73: 111 Abbott | H73: 418
A74: Total for 7253 Unemployment | H74: 1518
A75: 7254 Disability
B76: Beginning Balance
B77: 10/30/2019 | C77: Journal Entry | D77: 21 | F77: Disability Alloc | G77: 111 Abbott | H77: 86
B78: 11/30/2019 | C78: Journal Entry | D78: 54 | F78: Disability Alloc | G78: 111 Abbott | H78: 130
B79: 12/30/2019 | C79: Journal Entry | D79: 136 | F79: Disability Alloc | G79: 111 Abbott | H79: 82
A80: Total for 7254 Disability | H80: 298
A81: Total for 7250 Payroll Taxes, etc. | H81: 12540
A82: 7260 Payroll Service Fees
A83: 7260.1 Allocated Payroll Fees
B84: Beginning Balance
B85: 10/30/2019 | C85: Journal Entry | D85: 36 | F85: Payroll Fees | G85: 111 Abbott | H85: 304
B86: 11/30/2019 | C86: Journal Entry | D86: 47 | F86: Payroll Fees | G86: 111 Abbott | H86: 487
B87: 12/30/2019 | C87: Journal Entry | D87: 129 | F87: Payroll Fees | G87: 111 Abbott | H87: 322
A88: Total for 7260.1 Allocated Payroll Fees | H88: 1113
A89: Total for 7260 Payroll Service Fees | H89: 1113
A90: Total for 7200 Salaries & Related Expenses
A91: 7500 Contract Service Expenses
A92: 7515 IT Support
A93: 7515.5 Allocated IT consultants
B94: Beginning Balance
B95: 10/31/2019 | C95: Journal Entry | D95: 24 | F95: IT Consultants | G95: 111 Abbott | H95: 722
B96: 11/30/2019 | C96: Journal Entry | D96: 51 | F96: IT Consultants | G96: 111 Abbott | H96: 740
A97: Total for 7515.5 Allocated IT consultants | H97: 1462
A98: Total for 7515 IT Support | H98: 1462
A99: 7520 Accounting Fees
A100: 7521 Allocated Acctg and Audit
B101: Beginning Balance
...

Sheet P and L 
A1: URBAN LEAGUE OF ESSEX COUNTY
A2: Profit and Loss. ABBOTT.19.20
A3: July 2019 - June 2020
B5: Jul - Sep, 2019 | C5: Oct - Dec, 2019 | D5: Jan - Mar, 2020 | E5: Apr - Jun, 2020 | F5: Total
A6: Income
A7: 4500 Revenue from Government Grants | F7: =(((B7)+(C7))+(D7))+(E7) -> 0
A8: 4530 State Grants | F8: =(((B8)+(C8))+(D8))+(E8) -> 0
A9: 4536 NPS - Abbott | F9: =(((B9)+(C9))+(D9))+(E9) -> 0
A10: 4536.1 Abbott Benefit Reimb | B10: =24567.67 -> 24567.67 | C10: =15583.44 -> 15583.44 | F10: =(((B10)+(C10))+(D10))+(E10) -> 40151.11
A11: Total 4536 NPS - Abbott | B11: =(B9)+(B10) -> 24567.67 | C11: =(C9)+(C10) -> 15583.44 | D11: =(D9)+(D10) -> 0 | E11: =(E9)+(E10) -> 0 | F11: =(((B11)+(C11))+(D11))+(E11) -> 40151.11
A12: 4537.1 Abbott FYE 19-20 | B12: =47988.45 -> 47988.45 | C12: =143980.79 -> 143980.79 | F12: =(((B12)+(C12))+(D12))+(E12) -> 191969.24
A13: Total 4530 State Grants | B13: =((B8)+(B11))+(B12) -> 72556.12 | C13: =((C8)+(C11))+(C12) -> 159564.23 | D13: =((D8)+(D11))+(D12) -> 0 | E13: =((E8)+(E11))+(E12) -> 0 | F13: =(((B13)+(C13))+(D13))+(E13) -> 232120.35
A14: Total 4500 Revenue from Government Grants | B14: =(B7)+(B13) -> 72556.12 | C14: =(C7)+(C13) -> 159564.23 | D14: =(D7)+(D13) -> 0 | E14: =(E7)+(E13) -> 0 | F14: =(((B14)+(C14))+(D14))+(E14) -> 232120.35
A15: 5000 Revenue from Government Agencies | F15: =(((B15)+(C15))+(D15))+(E15) -> 0
A16: 5030 State Contracts/PFP Fees | B16: =413.29 -> 413.29 | C16: =1538.89 -> 1538.89 | F16: =(((B16)+(C16))+(D16))+(E16) -> 1952.18
A17: Total 5000 Revenue from Government Agencies | B17: =(B15)+(B16) -> 413.29 | C17: =(C15)+(C16) -> 1538.89 | D17: =(D15)+(D16) -> 0 | E17: =(E15)+(E16) -> 0 | F17: =(((B17)+(C17))+(D17))+(E17) -> 1952.18
A18: 5100 Revenue from Sales & Fees | F18: =(((B18)+(C18))+(D18))+(E18) -> 0
A19: 5132 Private Pay Fees | B19: =0.02 -> 0.02 | F19: =(((B19)+(C19))+(D19))+(E19) -> 0.02
A20: Total 5100 Revenue from Sales & Fees | B20: =(B18)+(B19) -> 0.02 | C20: =(C18)+(C19) -> 0 | D20: =(D18)+(D19) -> 0 | E20: =(E18)+(E19) -> 0 | F20: =(((B20)+(C20))+(D20))+(E20) -> 0.02
A21: Total Income | B21: =((B14)+(B17))+(B20) -> 72969.43 | C21: =((C14)+(C17))+(C20) -> 161103.12 | D21: =((D14)+(D17))+(D20) -> 0 | E21: =((E14)+(E17))+(E20) -> 0 | F21: =(((B21)+(C21))+(D21))+(E21) -> 234072.55
A22: Gross Profit | B22: =(B21)-(0) -> 72969.43 | C22: =(C21)-(0) -> 161103.12 | D22: =(D21)-(0) -> 0 | E22: =(E21)-(0) -> 0 | F22: =(((B22)+(C22))+(D22))+(E22) -> 234072.55
A23: Expenses
A24: 7200 Salaries & Related Expenses | F24: =(((B24)+(C24))+(D24))+(E24) -> 0
A25: 7220 Salaries & Wages | F25: =(((B25)+(C25))+(D25))+(E25) -> 0
A26: 7222 Staff | F26: =(((B26)+(C26))+(D26))+(E26) -> 0
A27: 7222h Teacher | B27: =45929.7 -> 45929.7 | C27: =108979.86 -> 108979.86 | F27: =(((B27)+(C27))+(D27))+(E27) -> 154909.56
A28: Total 7222 Staff | B28: =(B26)+(B27) -> 45929.7 | C28: =(C26)+(C27) -> 108979.86 | D28: =(D26)+(D27) -> 0 | E28: =(E26)+(E27) -> 0 | F28: =(((B28)+(C28))+(D28))+(E28) -> 154909.56
A29: Total 7220 Salaries & Wages | B29: =(B25)+(B28) -> 45929.7 | C29: =(C25)+(C28) -> 108979.86 | D29: =(D25)+(D28) -> 0 | E29: =(E25)+(E28) -> 0 | F29: =(((B29)+(C29))+(D29))+(E29) -> 154909.56
A30: 7240 Employee Benefits | F30: =(((B30)+(C30))+(D30))+(E30) -> 0
A31: 7241 Health Insurance | B31: =16961.97 -> 16961.97 | C31: =19443.45 -> 19443.45 | D31: =6576.97 -> 6576.97 | F31: =(((B31)+(C31))+(D31))+(E31) -> 42982.39
A32: 7242 Life and Dental Insurance | B32: =977.18 -> 977.18 | C32: =3244.57 -> 3244.57 | D32: =441.72 -> 441.72 | F32: =(((B32)+(C32))+(D32))+(E32) -> 4663.47
A33: 7243 Disability Ins | B33: =25.5 -> 25.5 | C33: =25.5 -> 25.5 | F33: =(((B33)+(C33))+(D33))+(E33) -> 51
A34: 7244 Employee Contrib - Health | B34: =-3208.1 -> -3208.1 | C34: =-4600.26 -> -4600.26 | F34: =(((B34)+(C34))+(D34))+(E34) -> -7808.36
A35: 7247 Emp-ee Contrib -Dental | B35: =-38.97 -> -38.97 | C35: =-118.11 -> -118.11 | F35: =(((B35)+(C35))+(D35))+(E35) -> -157.08
A36: Total 7240 Employee Benefits | B36: =(((((B30)+(B31))+(B32))+(B33))+(B34))+(B35) -> 14717.58 | C36: =(((((C30)+(C31))+(C32))+(C33))+(C34))+(C35) -> 17995.15 | D36: =(((((D30)+(D31))+(D32))+(D33))+(D34))+(D35) -> 7018.69 | E36: =(((((E30)+(E31))+(E32))+(E33))+(E34))+(E35) -> 0 | F36: =(((B36)+(C36))+(D36))+(E36) -> 39731.42
A37: 7250 Payroll Taxes, etc. | F37: =(((B37)+(C37))+(D37))+(E37) -> 0
A38: 7245 Worker's Compensation Insurance | F38: =(((B38)+(C38))+(D38))+(E38) -> 0
A39: 7248 Allocated W Comp | B39: =1341.42 -> 1341.42 | C39: =2953 -> 2953 | F39: =(((B39)+(C39))+(D39))+(E39) -> 4294.42
A40: Total 7245 Worker's Compensation Insurance | B40: =(B38)+(B39) -> 1341.42 | C40: =(C38)+(C39) -> 2953 | D40: =(D38)+(D39) -> 0 | E40: =(E38)+(E39) -> 0 | F40: =(((B40)+(C40))+(D40))+(E40) -> 4294.42
A41: 7251 Social Security | B41: =2608.59 -> 2608.59 | C41: =6240 -> 6240 | F41: =(((B41)+(C41))+(D41))+(E41) -> 8848.59
A42: 7252 Medicare | B42: =610.19 -> 610.19 | C42: =1531 -> 1531 | F42: =(((B42)+(C42))+(D42))+(E42) -> 2141.19
A43: 7253 Unemployment | B43: =681.4 -> 681.4 | C43: =1518 -> 1518 | F43: =(((B43)+(C43))+(D43))+(E43) -> 2199.4
A44: 7254 Disability | B44: =133.44 -> 133.44 | C44: =298 -> 298 | F44: =(((B44)+(C44))+(D44))+(E44) -> 431.44
A45: Total 7250 Payroll Taxes, etc. | B45: =(((((B37)+(B40))+(B41))+(B42))+(B43))+(B44) -> 5375.04 | C45: =(((((C37)+(C40))+(C41))+(C42))+(C43))+(C44) -> 12540 | D45: =(((((D37)+(D40))+(D41))+(D42))+(D43))+(D44) -> 0 | E45: =(((((E37)+(E40))+(E41))+(E42))+(E43))+(E44) -> 0 | F45: =(((B45)+(C45))+(D45))+(E45) -> 17915.04
A46: 7260 Payroll Service Fees | F46: =(((B46)+(C46))+(D46))+(E46) -> 0
A47: 7260.1 Allocated Payroll Fees | B47: =536.73 -> 536.73 | C47: =1113 -> 1113 | F47: =(((B47)+(C47))+(D47))+(E47) -> 1649.73
A48: Total 7260 Payroll Service Fees | B48: =(B46)+(B47) -> 536.73 | C48: =(C46)+(C47) -> 1113 | D48: =(D46)+(D47) -> 0 | E48: =(E46)+(E47) -> 0 | F48: =(((B48)+(C48))+(D48))+(E48) -> 1649.73
A49: Total 7200 Salaries & Related Expenses | B49: =((((B24)+(B29))+(B36))+(B45))+(B48) -> 66559.05 | C49: =((((C24)+(C29))+(C36))+(C45))+(C48) -> 140628.01 | D49: =((((D24)+(D29))+(D36))+(D45))+(D48) -> 7018.69 | E49: =((((E24)+(E29))+(E36))+(E45))+(E48) -> 0 | F49: =(((B49)+(C49))+(D49))+(E49) -> 214205.75
A50: 7500 Contract Service Expenses | F50: =(((B50)+(C50))+(D50))+(E50) -> 0
A51: 7515 IT Support | F51: =(((B51)+(C51))+(D51))+(E51) -> 0
A52: 7515.5 Allocated IT consultants | B52: =393.09 -> 393.09 | C52: =1462 -> 1462 | F52: =(((B52)+(C52))+(D52))+(E52) -> 1855.09
A53: Total 7515 IT Support | B53: =(B51)+(B52) -> 393.09 | C53: =(C51)+(C52) -> 1462 | D53: =(D51)+(D52) -> 0 | E53: =(E51)+(E52) -> 0 | F53: =(((B53)+(C53))+(D53))+(E53) -> 1855.09
A54: 7520 Accounting Fees | F54: =(((B54)+(C54))+(D54))+(E54) -> 0
A55: 7521 Allocated Acctg and Audit | B55: =2565.86 -> 2565.86 | C55: =5856 -> 5856 | F55: =(((B55)+(C55))+(D55))+(E55) -> 8421.86
A56: Total 7520 Accounting Fees | B56: =(B54)+(B55) -> 2565.86 | C56: =(C54)+(C55) -> 5856 | D56: =(D54)+(D55) -> 0 | E56: =(E54)+(E55) -> 0 | F56: =(((B56)+(C56))+(D56))+(E56) -> 8421.86
A57: Total 7500 Contract Service Expenses | B57: =((B50)+(B53))+(B56) -> 2958.95 | C57: =((C50)+(C53))+(C56) -> 7318 | D57: =((D50)+(D53))+(D56) -> 0 | E57: =((E50)+(E53))+(E56) -> 0 | F57: =(((B57)+(C57))+(D57))+(E57) -> 10276.95
A58: 8100 Operating Expenses | F58: =(((B58)+(C58))+(D58))+(E58) -> 0
A59: 8110 Supplies | F59: =(((B59)+(C59))+(D59))+(E59) -> 0
A60: 8112 Alloc Supplies | B60: =89.58 -> 89.58 | C60: =1216 -> 1216 | F60: =(((B60)+(C60))+(D60))+(E60) -> 1305.58
A61: Total 8110 Supplies | B61: =(B59)+(B60) -> 89.58 | C61: =(C59)+(C60) -> 1216 | D61: =(D59)+(D60) -> 0 | E61: =(E59)+(E60) -> 0 | F61: =(((B61)+(C61))+(D61))+(E61) -> 1305.58
A62: 8130 Telephone & Telecommunications | F62: =(((B62)+(C62))+(D62))+(E62) -> 0
A63: 8135.5 Allocated Telephone | B63: =249.14 -> 249.14 | C63: =753 -> 753 | F63: =(((B63)+(C63))+(D63))+(E63) -> 1002.14
A64: Total 8130 Telephone & Telecommunications | B64: =(B62)+(B63) -> 249.14 | C64: =(C62)+(C63) -> 753 | D64: =(D62)+(D63) -> 0 | E64: =(E62)+(E63) -> 0 | F64: =(((B64)+(C64))+(D64))+(E64) -> 1002.14
A65: 8140 Postage & Shipping | B65: =18 -> 18 | C65: =72 -> 72 | F65: =(((B65)+(C65))+(D65))+(E65) -> 90
A66: 8191 Web Hosting Alloc | B66: =106.01 -> 106.01 | C66: =227 -> 227 | F66: =(((B66)+(C66))+(D66))+(E66) -> 333.01
A67: Total 8100 Operating Expenses | B67: =((((B58)+(B61))+(B64))+(B65))+(B66) -> 462.73 | C67: =((((C58)+(C61))+(C64))+(C65))+(C66) -> 2268 | D67: =((((D58)+(D61))+(D64))+(D65))+(D66) -> 0 | E67: =((((E58)+(E61))+(E64))+(E65))+(E66) -> 0 | F67: =(((B67)+(C67))+(D67))+(E67) -> 2730.73
A68: 8200 Facility & Equipment Expenses | F68: =(((B68)+(C68))+(D68))+(E68) -> 0
A69: 8210 Utilities | F69: =(((B69)+(C69))+(D69))+(E69) -> 0
A70: 8210.1 504 Utilities | B70: =3080.88 -> 3080.88 | C70: =2961.74 -> 2961.74 | F70: =(((B70)+(C70))+(D70))+(E70) -> 6042.62
A71: 8210.5 Allocated Utilities | B71: =410.5 -> 410.5 | C71: =1105 -> 1105 | F71: =(((B71)+(C71))+(D71))+(E71) -> 1515.5
A72: Total 8210 Utilities | B72: =((B69)+(B70))+(B71) -> 3491.38 | C72: =((C69)+(C70))+(C71) -> 4066.74 | D72: =((D69)+(D70))+(D71) -> 0 | E72: =((E69)+(E70))+(E71) -> 0 | F72: =(((B72)+(C72))+(D72))+(E72) -> 7558.12
A73: 8211 Water | B73: =414.99 -> 414.99 | C73: =393.18 -> 393.18 | F73: =(((B73)+(C73))+(D73))+(E73) -> 808.17
A74: 8220 Equipment Rental, Repair & Maintenance | F74: =(((B74)+(C74))+(D74))+(E74) -> 0
A75: 8229.1 Allocated Cost | B75: =803.61 -> 803.61 | C75: =1771 -> 1771 | F75: =(((B75)+(C75))+(D75))+(E75) -> 2574.61
A76: Total 8220 Equipment Rental, Repair & Maintenance | B76: =(B74)+(B75) -> 803.61 | C76: =(C74)+(C75) -> 1771 | D76: =(D74)+(D75) -> 0 | E76: =(E74)+(E75) -> 0 | F76: =(((B76)+(C76))+(D76))+(E76) -> 2574.61
A77: 8230 Building Repair & Maintenance | B77: =566.75 -> 566.75 | C77: =4287.5 -> 4287.5 | F77: =(((B77)+(C77))+(D77))+(E77) -> 4854.25
A78: 8231 Alarm Services | B78: =193.5 -> 193.5 | F78: =(((B78)+(C78))+(D78))+(E78) -> 193.5
A79: 8239 Alloc Repairs and Maint | B79: =397.87 -> 397.87 | C79: =1284 -> 1284 | F79: =(((B79)+(C79))+(D79))+(E79) -> 1681.87
A80: Total 8230 Building Repair & Maintenance | B80: =((B77)+(B78))+(B79) -> 1158.12 | C80: =((C77)+(C78))+(C79) -> 5571.5 | D80: =((D77)+(D78))+(D79) -> 0 | E80: =((E77)+(E78))+(E79) -> 0 | F80: =(((B80)+(C80))+(D80))+(E80) -> 6729.62
A81: 8240 Maintenance Supplies | C81: =118 -> 118 | F81: =(((B81)+(C81))+(D81))+(E81) -> 118
A82: 8250 Mortgage Interest Expense | F82: =(((B82)+(C82))+(D82))+(E82) -> 0
A83: 8250.1 Allocated Mortgage Interest | B83: =687 -> 687 | C83: =1552 -> 1552 | F83: =(((B83)+(C83))+(D83))+(E83) -> 2239
A84: Total 8250 Mortgage Interest Expense | B84: =(B82)+(B83) -> 687 | C84: =(C82)+(C83) -> 1552 | D84: =(D82)+(D83) -> 0 | E84: =(E82)+(E83) -> 0 | F84: =(((B84)+(C84))+(D84))+(E84) -> 2239
A85: 8260 Property Insurance | F85: =(((B85)+(C85))+(D85))+(E85) -> 0
A86: 8264 Other | F86: =(((B86)+(C86))+(D86))+(E86) -> 0
A87: 8266 Allocated Insurance | B87: =1351.28 -> 1351.28 | C87: =3379 -> 3379 | F87: =(((B87)+(C87))+(D87))+(E87) -> 4730.28
A88: Total 8264 Other | B88: =(B86)+(B87) -> 1351.28 | C88: =(C86)+(C87) -> 3379 | D88: =(D86)+(D87) -> 0 | E88: =(E86)+(E87) -> 0 | F88: =(((B88)+(C88))+(D88))+(E88) -> 4730.28
A89: Total 8260 Property Insurance | B89: =(B85)+(B88) -> 1351.28 | C89: =(C85)+(C88) -> 3379 | D89: =(D85)+(D88) -> 0 | E89: =(E85)+(E88) -> 0 | F89: =(((B89)+(C89))+(D89))+(E89) -> 4730.28
A90: Total 8200 Facility & Equipment Expenses | B90: =(((((((B68)+(B72))+(B73))+(B76))+(B80))+(B81))+(B84))+(B89) -> 7906.38 | C90: =(((((((C68)+(C72))+(C73))+(C76))+(C80))+(C81))+(C84))+(C89) -> 16851.42 | D90: =(((((((D68)+(D72))+(D73))+(D76))+(D80))+(D81))+(D84))+(D89) -> 0 | E90: =(((((((E68)+(E72))+(E73))+(E76))+(E80))+(E81))+(E84))+(E89) -> 0 | F90: =(((B90)+(C90))+(D90))+(E90) -> 24757.8
A91: 8300 Travel & Meetings Expenses | F91: =(((B91)+(C91))+(D91))+(E91) -> 0
A92: 8310 Transportation & Parking | B92: =118 -> 118 | C92: =142.1 -> 142.1 | F92: =(((B92)+(C92))+(D92))+(E92) -> 260.1
A93: 8360 Field Trips | B93: =560 -> 560 | C93: =600 -> 600 | F93: =(((B93)+(C93))+(D93))+(E93) -> 1160
A94: Total 8300 Travel & Meetings Expenses | B94: =((B91)+(B92))+(B93) -> 678 | C94: =((C91)+(C92))+(C93) -> 742.1 | D94: =((D91)+(D92))+(D93) -> 0 | E94: =((E91)+(E92))+(E93) -> 0 | F94: =(((B94)+(C94))+(D94))+(E94) -> 1420.1
A95: 8400 Other Client Specific Expenses | F95: =(((B95)+(C95))+(D95))+(E95) -> 0
A96: 8405 Classroom Materials & Supplies | B96: =3300.94 -> 3300.94 | C96: =435.65 -> 435.65 | F96: =(((B96)+(C96))+(D96))+(E96) -> 3736.59
A97: 8425 Expungement Services | B97: =20 -> 20 | C97: =30 -> 30 | F97: =(((B97)+(C97))+(D97))+(E97) -> 50
A98: 8540 Staff Development/Training | B98: =1690 -> 1690 | D98: =558 -> 558 | F98: =(((B98)+(C98))+(D98))+(E98) -> 2248
A99: Total 8400 Other Client Specific Expenses | B99: =(((B95)+(B96))+(B97))+(B98) -> 5010.94 | C99: =(((C95)+(C96))+(C97))+(C98) -> 465.65 | D99: =(((D95)+(D96))+(D97))+(D98) -> 558 | E99: =(((E95)+(E96))+(E97))+(E98) -> 0 | F99: =(((B99)+(C99))+(D99))+(E99) -> 6034.59
A100: 8500 Other Expenses | F100: =(((B100)+(C100))+(D100))+(E100) -> 0
A101: 8520 Insurance - Non-Employee Related | C101: =672 -> 672 | F101: =(((B101)+(C101))+(D101))+(E101) -> 672
...

Sheet Salary Report Q2
B1: Abbott Staffing
B3: For the Quarter ending December 31, 2019
I6: Total
N7: 0.03
E8: Annual Salary | F8: Budget | H8: Oct - Dec | I8: Abbott | J8: Other | K8: Food | L8: Facilites | M8: Wrap Around | N8: Workers Comp
B9: Teachers | C9: 3 | G9: =F9/E15 -> 0 | I9: =H9*K7 -> 0
D10: Jhonny Janvier | H10: 2361.16 | I10: 2361.16
D11: Bertrilla Simons | E11: 57717 | H11: 18825.24 | I11: 18825.24 | N11: =I11*$N$7 -> 564.7572
C12: 50000 | D12: Felicia Mitchell | E12: 50000 | H12: 6431.42 | I12: 6431.42
D13: Mellisa Thorpe | E13: 53261
D14: Quintella Hollins | H14: 16004.86 | I14: 16004.86 | O14: =SUM(I10:I14) -> 43622.68
E15: =SUM(E10:E14) -> 160978 | F15: 169561
B16: Teacher Assistants | C16: 3 | D16: W Hill | G16: =F16/E20 -> 0
D17: R Stewart | E17: 34413 | H17: 11295.73 | I17: 11295.73 | N17: =I17*$N$7 -> 338.8719
D18: Niquita Loftin | E18: 25872 | H18: 7816.23 | I18: 7816.23 | N18: =I18*$N$7 -> 234.4869
D19: R Bryant | E19: 26551 | H19: 8897.69 | I19: 8897.69 | N19: =I19*$N$7 -> 266.9307 | O19: =SUM(I17:I19) -> 28009.65
E20: =SUM(E16:E19) -> 86836 | F20: 86836 | O20: =SUM(O14:O19) -> 71632.33
B21: Wrap Worker | D21: R Woodridge | H21: 3302.5 | M21: =H21 -> 3302.5
N23: =I23*$N$7 -> 0
B24: Floater | C24: 0.5 | D24: S Rambaran | E24: 19800 | F24: 19800 | G24: =F24/E24 -> 1 | H24: 6083.9 | I24: 6083.9 | N24: =I24*$N$7 -> 182.517 | O24: =N24 -> 182.517
N25: =I25*$N$7 -> 0
B26: Substitutes | D26: D Brown | G26: 1 | H26: 3112.8 | I26: 3112.8 | N26: =I26*$N$7 -> 93.384 | O26: =SUM(N24:N26) -> 275.901 | P26: =SUM(O19:O26) -> 100100.4
N27: =I27*$N$7 -> 0
B28: Family Worker | C28: 1 | D28: Daphne McMillan | E28: 30076 | F28: 24552 | G28: =F28/E28 -> 0.81633196 | H28: 7954.52 | I28: =H28*G28 -> 6493.5289 | J28: =H28-I28 -> 1460.9911 | N28: =I28*$N$7 -> 194.80587 | O28: Unallow
N29: =I29*$N$7 -> 0
B30: Cook | C30: 0.5 | D30: P Tyler | E30: 19549 | F30: 7500 | G30: =F30/E30 -> 0.38365134 | H30: 3717.23 | I30: =H30*G30 -> 1426.1203 | J30: =H30-I30 -> 2291.1097 | N30: =I30*$N$7 -> 42.783608 | O30: Unallow
F31: =SUM(F9:F30) -> 308249 | H31: =SUM(H9:H30) -> 95803.28 | I31: =SUM(I9:I30) -> 88748.679 | J31: =SUM(J9:J30) -> 3752.1008 | K31: =SUM(K9:K30) -> 0 | M31: =SUM(M9:M30) -> 3302.5 | N31: =SUM(N9:N30) -> 1918.5372
B34: Program Director | C34: 1 | D34: Heather Dance | E34: 70000 | F34: 57580 | G34: =F34/E34 -> 0.82257143 | H34: 18846.17 | I34: =H34*G34 -> 15502.321 | J34: =H34-I34 -> 3343.849 | N34: =I34*$N$7 -> 465.06963 | O34: =N34*G34 -> 382.55299
N35: =I35*$N$7 -> 0
B36: Clerical | C36: 0.5 | D36: S Alford | E36: 10000 | F36: 3837 | G36: =F36/E36 -> 0.3837 | I36: =H36*G36 -> 0 | J36: =H36-I36 -> 0 | N36: =I36*$N$7 -> 0 | O36: Unallow
N37: =I37*$N$7 -> 0
B38: Custodian | C38: 1 | D38: P Bennett | E38: 22000 | F38: 8441 | G38: =F38/E38 -> 0.38368182 | H38: 4472 | I38: =H38*G38 -> 1715.8251 | J38: =H38-I38 -> 2756.1749 | N38: =I38*$N$7 -> 51.474753 | O38: Unallow
N39: =I39*$N$7 -> 0
B40: Security Guard | D40: Cora Andrews | E40: 20000 | F40: 15347 | G40: =F40/E40 -> 0.76735 | H40: 7840 | I40: =H40*G40 -> 6016.024 | J40: =H40-I40 -> 1823.976 | N40: =I40*$N$7 -> 180.48072 | O40: Unallow
F41: =SUM(F34:F40) -> 85205 | H41: =SUM(H34:H40) -> 31158.17 | I41: =SUM(I34:I40) -> 23234.17 | J41: =SUM(J34:J40) -> 7923.9999 | K41: =SUM(K34:K40) -> 0 | L41: =SUM(L34:L40) -> 0 | M41: =SUM(M34:M40) -> 0 | N41: =SUM(N34:N40) -> 697.0251
F46: =SUM(F43:F45) -> 0 | I46: =SUM(I43:I45) -> 0 | M46: =SUM(M43:M45) -> 0 | N46: =SUM(N43:N45) -> 0
F48: =F31+F41+F46 -> 393454 | H48: =H31+H41+H46 -> 126961.45 | I48: =I31+I41+I46 -> 111982.85 | J48: =J31+J41+J46 -> 11676.101 | K48: =K31+K41+K46 -> 0 | L48: =L31+L41+L46 -> 0 | M48: =M31+M41+M46 -> 3302.5 | N48: =N31+N41+N46 -> 2615.5623 | S48: 18009139000x
I49: Abbott | J49: Other | K49: Food | L49: =L8 -> Facilites | M49: Wrap Around | S49: Sandra Jerry
J51: =J48/$H$48 -> 0.091965717 | K51: =K48/$H$48 -> 0 | L51: =L48/$H$48 -> 0 | M51: =M48/$H$48 -> 0.026011833

Sheet Salary Details
C1: Urban League of Essex County
C2: Abbott Salaries
C3: 10/01/2019 - 12/31/2019
A5: Department_Desc | B5: Employee_Code | C5: Employee_Name | D5: Position | E5: Paydate | F5: Start_Date | G5: End_Date | H5: Gross Pay | I5: Hours | J5: Check_# | K5: Distribution | L5: Transaction_# | M5: Adjust
A6: Abbott | B6: A002 | C6: ANDREWS, CORA | D6: Security Guard | E6: 43742 | F6: 43723 | G6: 43736 | H6: 560 | I6: 40 | J6: 209886773 | K6: C3C5C41A7 - 209886773 - 000550 | L6: C3C5C41A7
A7: Abbott | B7: A002 | C7: ANDREWS, CORA | D7: Security Guard | E7: 43742 | F7: 43723 | G7: 43736 | H7: 560 | I7: 40 | J7: 209886773 | K7: C3C5C41A7 - 209886773 - 000570 | L7: C3C5C41A7
A8: Abbott | B8: A002 | C8: ANDREWS, CORA | D8: Security Guard | E8: 43756 | F8: 43737 | G8: 43750 | H8: 562.62 | I8: 40.12 | J8: 212386264 | K8: 498337E58 - 212386264 - 000550 | L8: 498337E58
A9: Abbott | B9: A002 | C9: ANDREWS, CORA | D9: Security Guard | E9: 43756 | F9: 43737 | G9: 43750 | H9: 562.63 | I9: 40.13 | J9: 212386264 | K9: 498337E58 - 212386264 - 000570 | L9: 498337E58
A10: Abbott | B10: A002 | C10: ANDREWS, CORA | D10: Security Guard | E10: 43770 | F10: 43751 | G10: 43764 | H10: 560 | I10: 40 | J10: 214643815 | K10: A7011EC06 - 214643815 - 000550 | L10: A7011EC06
A11: Abbott | B11: A002 | C11: ANDREWS, CORA | D11: Security Guard | E11: 43770 | F11: 43751 | G11: 43764 | H11: 560 | I11: 40 | J11: 214643815 | K11: A7011EC06 - 214643815 - 000570 | L11: A7011EC06
A12: Abbott | B12: A002 | C12: ANDREWS, CORA | D12: Security Guard | E12: 43784 | F12: 43765 | G12: 43778 | H12: 560 | I12: 40 | J12: 216803173 | K12: 2A0FE99C0 - 216803173 - 000550 | L12: 2A0FE99C0
A13: Abbott | B13: A002 | C13: ANDREWS, CORA | D13: Security Guard | E13: 43784 | F13: 43765 | G13: 43778 | H13: 560 | I13: 40 | J13: 216803173 | K13: 2A0FE99C0 - 216803173 - 000570 | L13: 2A0FE99C0
A14: Abbott | B14: A002 | C14: ANDREWS, CORA | D14: Security Guard | E14: 43798 | F14: 43779 | G14: 43792 | H14: 560 | I14: 40 | J14: 219435869 | K14: 80E3439F4 - 219435869 - 000550 | L14: 80E3439F4
A15: Abbott | B15: A002 | C15: ANDREWS, CORA | D15: Security Guard | E15: 43798 | F15: 43779 | G15: 43792 | H15: 560 | I15: 40 | J15: 219435869 | K15: 80E3439F4 - 219435869 - 000570 | L15: 80E3439F4
A16: Abbott | B16: A002 | C16: ANDREWS, CORA | D16: Security Guard | E16: 43812 | F16: 43793 | G16: 43806 | H16: 560 | I16: 40 | J16: 221999735 | K16: 24FE78CF5 - 221999735 - 000550 | L16: 24FE78CF5
A17: Abbott | B17: A002 | C17: ANDREWS, CORA | D17: Security Guard | E17: 43812 | F17: 43793 | G17: 43806 | H17: 560 | I17: 40 | J17: 221999735 | K17: 24FE78CF5 - 221999735 - 000570 | L17: 24FE78CF5
... A19: Abbott | B19: A002 | C19: ANDREWS, CORA | D19: Security Guard | E19: 43826 | F19: 43807 | G19: 43820 | H19: 562.63 | I19: 40.13 | J19: 223886743 | K19: 06DA7FE21 - 223886743 - 000570 | L19: 06DA7FE21
H20: =SUM(H6:H19) -> 7850.5
F21: Less: Overtime | H21: -10.5
H22: =SUM(H20:H21) -> 7840
A25: Abbott | B25: A06G | C25: BENNETT, PATRICIA A | D25: Custodian | E25: 43742 | F25: 43723 | G25: 43736 | H25: 650 | I25: 50 | J25: 209886774 | K25: C3C5C41A7 - 209886774 - 650 | L25: C3C5C41A7
A26: Abbott | B26: A06G | C26: BENNETT, PATRICIA A | D26: Custodian | E26: 43756 | F26: 43737 | G26: 43750 | H26: 650 | I26: 50 | J26: 212386265 | K26: 498337E58 - 212386265 - 650 | L26: 498337E58
A27: Abbott | B27: A06G | C27: BENNETT, PATRICIA A | D27: Custodian | E27: 43770 | F27: 43751 | G27: 43764 | H27: 650 | I27: 50 | J27: 214643816 | K27: A7011EC06 - 214643816 - 650 | L27: A7011EC06
A28: Abbott | B28: A06G | C28: BENNETT, PATRICIA A | D28: Custodian | E28: 43784 | F28: 43765 | G28: 43778 | H28: 650 | I28: 50 | J28: 216803174 | K28: 2A0FE99C0 - 216803174 - 650 | L28: 2A0FE99C0
A29: Abbott | B29: A06G | C29: BENNETT, PATRICIA A | D29: Custodian | E29: 43798 | F29: 43779 | G29: 43792 | H29: 650 | I29: 50 | J29: 219435870 | K29: 80E3439F4 - 219435870 - 650 | L29: 80E3439F4
A30: Abbott | B30: A06G | C30: BENNETT, PATRICIA A | D30: Custodian | E30: 43812 | F30: 43793 | G30: 43806 | H30: 572 | I30: 44 | J30: 221999736 | K30: 24FE78CF5 - 221999736 - 111 | L30: 24FE78CF5
A31: Abbott | B31: A06G | C31: BENNETT, PATRICIA A | D31: Custodian | E31: 43826 | F31: 43807 | G31: 43820 | H31: 650 | I31: 50 | J31: 223886744 | K31: 06DA7FE21 - 223886744 - 650 | L31: 06DA7FE21
H32: =SUM(H25:H31) -> 4472
A41: Abbott Wrap | B41: A03A | C41: BROWN, DENYSE | D41: WRAP AROUND STAFF | E41: 43742 | F41: 43723 | G41: 43736 | H41: 495 | I41: 49.5 | J41: 209886775 | K41: C3C5C41A7 - 209886775 - 111B | L41: C3C5C41A7
A42: Abbott Wrap | B42: A03A | C42: BROWN, DENYSE | D42: WRAP AROUND STAFF | E42: 43756 | F42: 43737 | G42: 43750 | H42: 617.5 | I42: 61.75 | J42: 212386266 | K42: 498337E58 - 212386266 - 111B | L42: 498337E58
A43: Abbott Wrap | B43: A03A | C43: BROWN, DENYSE | D43: WRAP AROUND STAFF | E43: 43770 | F43: 43751 | G43: 43764 | H43: 423.3 | I43: 42.33 | J43: 214643817 | K43: A7011EC06 - 214643817 - 111B | L43: A7011EC06
A44: Abbott Wrap | B44: A03A | C44: BROWN, DENYSE | D44: WRAP AROUND STAFF | E44: 43784 | F44: 43765 | G44: 43778 | H44: 460 | I44: 46 | J44: 216803175 | K44: 2A0FE99C0 - 216803175 - 111B | L44: 2A0FE99C0
A45: Abbott Wrap | B45: A03A | C45: BROWN, DENYSE | D45: WRAP AROUND STAFF | E45: 43798 | F45: 43779 | G45: 43792 | H45: 325 | I45: 32.5 | J45: 219435871 | K45: 80E3439F4 - 219435871 - 111B | L45: 80E3439F4
A46: Abbott Wrap | B46: A03A | C46: BROWN, DENYSE | D46: WRAP AROUND STAFF | E46: 43812 | F46: 43793 | G46: 43806 | H46: 282.5 | I46: 28.25 | J46: 221999737 | K46: 24FE78CF5 - 221999737 - 111B | L46: 24FE78CF5
A47: Abbott Wrap | B47: A03A | C47: BROWN, DENYSE | D47: WRAP AROUND STAFF | E47: 43826 | F47: 43807 | G47: 43820 | H47: 520 | I47: 52 | J47: 223886745 | K47: 06DA7FE21 - 223886745 - 111B | L47: 06DA7FE21
H48: =SUM(H41:H47) -> 3123.3
F49: Less: Overtime | H49: -10.5
H50: =SUM(H48:H49) -> 3112.8
A52: Abbott | B52: A009 | C52: BRYANT, RONI | D52: Teacher Assistant | E52: 43742 | F52: 43723 | G52: 43736 | H52: 1367.23 | I52: 65 | J52: 209886776 | K52: C3C5C41A7 - 209886776 - 111 | L52: C3C5C41A7
A53: Abbott | B53: A009 | C53: BRYANT, RONI | D53: Teacher Assistant | E53: 43756 | F53: 43737 | G53: 43750 | H53: 1357.23 | I53: 65 | J53: 212386267 | K53: 498337E58 - 212386267 - 111 | L53: 498337E58
A54: Abbott | B54: A009 | C54: BRYANT, RONI | D54: Teacher Assistant | E54: 43770 | F54: 43751 | G54: 43764 | H54: 1384.31 | I54: 65 | J54: 214643818 | K54: A7011EC06 - 214643818 - 111 | L54: A7011EC06
A55: Abbott | B55: A009 | C55: BRYANT, RONI | D55: Teacher Assistant | E55: 43784 | F55: 43765 | G55: 43778 | H55: 1327.23 | I55: 65 | J55: 216803176 | K55: 2A0FE99C0 - 216803176 - 111 | L55: 2A0FE99C0
A56: Abbott | B56: A009 | C56: BRYANT, RONI | D56: Teacher Assistant | E56: 43798 | F56: 43779 | G56: 43792 | H56: 1347.23 | I56: 65 | J56: 219435872 | K56: 80E3439F4 - 219435872 - 111 | L56: 80E3439F4
A57: Abbott | B57: A009 | C57: BRYANT, RONI | D57: Teacher Assistant | E57: 43812 | F57: 43793 | G57: 43806 | H57: 1347.23 | I57: 65 | J57: 221999738 | K57: 24FE78CF5 - 221999738 - 111 | L57: 24FE78CF5
A58: Abbott | B58: A009 | C58: BRYANT, RONI | D58: Teacher Assistant | E58: 43826 | F58: 43807 | G58: 43820 | H58: 1367.23 | I58: 65 | J58: 223886746 | K58: 06DA7FE21 - 223886746 - 111 | L58: 06DA7FE21
H59: =SUM(H52:H58) -> 9497.69
F60: Less: Wrap Around | H60: -570
F61: Less: Miscellaneous | H61: -30
H62: =SUM(H59:H61) -> 8897.69
A65: Abbott | B65: A05S | C65: DANCE-WILSON, HEATHER | D65: Director of Early Childhood | E65: 43742 | F65: 43723 | G65: 43736 | H65: 2692.31 | I65: 70 | J65: 209886779 | K65: C3C5C41A7 - 209886779 - 111 | L65: C3C5C41A7
A66: Abbott | B66: A05S | C66: DANCE-WILSON, HEATHER | D66: Director of Early Childhood | E66: 43756 | F66: 43737 | G66: 43750 | H66: 2692.31 | I66: 70 | J66: 212386270 | K66: 498337E58 - 212386270 - 111 | L66: 498337E58
A67: Abbott | B67: A05S | C67: DANCE-WILSON, HEATHER | D67: Director of Early Childhood | E67: 43770 | F67: 43751 | G67: 43764 | H67: 2692.31 | I67: 70 | J67: 214643821 | K67: A7011EC06 - 214643821 - 111 | L67: A7011EC06
A68: Abbott | B68: A05S | C68: DANCE-WILSON, HEATHER | D68: Director of Early Childhood | E68: 43784 | F68: 43765 | G68: 43778 | H68: 2692.31 | I68: 70 | J68: 216803179 | K68: 2A0FE99C0 - 216803179 - 111 | L68: 2A0FE99C0
A69: Abbott | B69: A05S | C69: DANCE-WILSON, HEATHER | D69: Director of Early Childhood | E69: 43798 | F69: 43779 | G69: 43792 | H69: 2692.31 | I69: 70 | J69: 219435875 | K69: 80E3439F4 - 219435875 - 111 | L69: 80E3439F4
A70: Abbott | B70: A05S | C70: DANCE-WILSON, HEATHER | D70: Director of Early Childhood | E70: 43812 | F70: 43793 | G70: 43806 | H70: 2692.31 | I70: 70 | J70: 221999741 | K70: 24FE78CF5 - 221999741 - 111 | L70: 24FE78CF5
A71: Abbott | B71: A05S | C71: DANCE-WILSON, HEATHER | D71: Director of Early Childhood | E71: 43826 | F71: 43807 | G71: 43820 | H71: 2692.31 | I71: 70 | J71: 223886749 | K71: 06DA7FE21 - 223886749 - 111 | L71: 06DA7FE21
H72: =SUM(H65:H71) -> 18846.17
A76: Abbott | B76: A06R | C76: HOLLINS, QUINTELLA D | D76: Lead Teacher | E76: 43742 | F76: 43723 | G76: 43736 | H76: 2279.21 | I76: 64.25 | J76: 209886785 | K76: C3C5C41A7 - 209886785 - 111 | L76: C3C5C41A7
A77: Abbott | B77: A06R | C77: HOLLINS, QUINTELLA D | D77: Lead Teacher | E77: 43756 | F77: 43737 | G77: 43750 | H77: 2305.82 | I77: 65 | J77: 212386276 | K77: 498337E58 - 212386276 - 111 | L77: 498337E58
A78: Abbott | B78: A06R | C78: HOLLINS, QUINTELLA D | D78: Lead Teacher | E78: 43770 | F78: 43751 | G78: 43764 | H78: 2305.82 | I78: 65 | J78: 214643827 | K78: A7011EC06 - 214643827 - 111 | L78: A7011EC06
A79: Abbott | B79: A06R | C79: HOLLINS, QUINTELLA D | D79: Lead Teacher | E79: 43784 | F79: 43765 | G79: 43778 | H79: 2305.82 | I79: 65 | J79: 216803185 | K79: 2A0FE99C0 - 216803185 - 111 | L79: 2A0FE99C0
A80: Abbott | B80: A06R | C80: HOLLINS, QUINTELLA D | D80: Lead Teacher | E80: 43798 | F80: 43779 | G80: 43792 | H80: 2279.21 | I80: 64.25 | J80: 219435881 | K80: 80E3439F4 - 219435881 - 111 | L80: 80E3439F4
A81: Abbott | B81: A06R | C81: HOLLINS, QUINTELLA D | D81: Lead Teacher | E81: 43812 | F81: 43793 | G81: 43806 | H81: 2223.16 | I81: 62.67 | J81: 221999748 | K81: 24FE78CF5 - 221999748 - 111 | L81: 24FE78CF5
A82: Abbott | B82: A06R | C82: HOLLINS, QUINTELLA D | D82: Lead Teacher | E82: 43826 | F82: 43807 | G82: 43820 | H82: 2305.82 | I82: 65 | J82: 223886756 | K82: 06DA7FE21 - 223886756 - 111 | L82: 06DA7FE21
H83: =SUM(H76:H82) -> 16004.86
A87: Abbott | B87: A06F | C87: JANVIER, JHONNY | D87: Abbott Teacher | E87: 43742 | F87: 43723 | G87: 43736 | H87: 2361.16 | I87: 56.25 | J87: 209886787 | K87: C3C5C41A7 - 209886787 - 111 | L87: C3C5C41A7
A92: Abbott | B92: A06Q | C92: LOFTIN, NIQUITA | D92: Temp. Teacher Asst. | E92: 43742 | F92: 43723 | G92: 43736 | H92: 877.83 | I92: 65 | J92: 209886791 | K92: C3C5C41A7 - 209886791 - 111 | L92: C3C5C41A7
A93: Abbott | B93: A06Q | C93: LOFTIN, NIQUITA | D93: Temp. Teacher Asst. | E93: 43756 | F93: 43737 | G93: 43750 | H93: 1176 | I93: 65 | J93: 212386281 | K93: 498337E58 - 212386281 - 111 | L93: 498337E58
A94: Abbott | B94: A06Q | C94: LOFTIN, NIQUITA | D94: Temp. Teacher Asst. | E94: 43770 | F94: 43751 | G94: 43764 | H94: 1176 | I94: 65 | J94: 214643832 | K94: A7011EC06 - 214643832 - 111 | L94: A7011EC06
A95: Abbott | B95: A06Q | C95: LOFTIN, NIQUITA | D95: Temp. Teacher Asst. | E95: 43784 | F95: 43765 | G95: 43778 | H95: 1058.4 | I95: 58.5 | J95: 216803190 | K95: 2A0FE99C0 - 216803190 - 111 | L95: 2A0FE99C0
A96: Abbott | B96: A06Q | C96: LOFTIN, NIQUITA | D96: Temp. Teacher Asst. | E96: 43798 | F96: 43779 | G96: 43792 | H96: 1176 | I96: 65 | J96: 219435886 | K96: 80E3439F4 - 219435886 - 111 | L96: 80E3439F4
A97: Abbott | B97: A06Q | C97: LOFTIN, NIQUITA | D97: Temp. Teacher Asst. | E97: 43812 | F97: 43793 | G97: 43806 | H97: 1176 | I97: 65 | J97: 221999753 | K97: 24FE78CF5 - 221999753 - 111 | L97: 24FE78CF5
A98: Abbott | B98: A06Q | C98: LOFTIN, NIQUITA | D98: Temp. Teacher Asst. | E98: 43826 | F98: 43807 | G98: 43820 | H98: 1176 | I98: 65 | J98: 223886761 | K98: 06DA7FE21 - 223886761 - 111 | L98: 06DA7FE21
H99: =SUM(H92:H98) -> 7816.23
A102: Abbott | B102: A03B | C102: MCMILLIAN, DAPHNE L. | D102: Family Worker | E102: 43742 | F102: 43723 | G102: 43736 | H102: 1236.36 | I102: 70 | J102: 209886793 | K102: C3C5C41A7 - 209886793 - 111 | L102: C3C5C41A7
A103: Abbott | B103: A03B | C103: MCMILLIAN, DAPHNE L. | D103: Family Worker | E103: 43756 | F103: 43737 | G103: 43750 | H103: 1236.36 | I103: 70 | J103: 212386283 | K103: 498337E58 - 212386283 - 111 | L103: 498337E58
A104: Abbott | B104: A03B | C104: MCMILLIAN, DAPHNE L. | D104: Family Worker | E104: 43770 | F104: 43751 | G104: 43764 | H104: 1216.36 | I104: 70 | J104: 214643835 | K104: A7011EC06 - 214643835 - 111 | L104: A7011EC06
A105: Abbott | B105: A03B | C105: MCMILLIAN, DAPHNE L. | D105: Family Worker | E105: 43784 | F105: 43765 | G105: 43778 | H105: 1216.36 | I105: 70 | J105: 216803193 | K105: 2A0FE99C0 - 216803193 - 111 | L105: 2A0FE99C0
A106: Abbott | B106: A03B | C106: MCMILLIAN, DAPHNE L. | D106: Family Worker | E106: 43798 | F106: 43779 | G106: 43792 | H106: 1216.36 | I106: 70 | J106: 219435889 | K106: 80E3439F4 - 219435889 - 111 | L106: 80E3439F4
A107: Abbott | B107: A03B | C107: MCMILLIAN, DAPHNE L. | D107: Family Worker | E107: 43812 | F107: 43793 | G107: 43806 | H107: 1196.36 | I107: 70 | J107: 221999756 | K107: 24FE78CF5 - 221999756 - 111 | L107: 24FE78CF5
A108: Abbott | B108: A03B | C108: MCMILLIAN, DAPHNE L. | D108: Family Worker | E108: 43826 | F108: 43807 | G108: 43820 | H108: 1236.36 | I108: 70 | J108: 223886764 | K108: 06DA7FE21 - 223886764 - 111 | L108: 06DA7FE21
H109: =SUM(H102:H108) -> 8554.52
F110: Less: Miscellaneous | H110: -600
H111: =SUM(H109:H110) -> 7954.52
A113: Abbott | B113: A06S | C113: MITCHELL, FELICIA | D113: Teacher | E113: 43770 | F113: 43751 | G113: 43764 | H113: 1261.81 | I113: 58.58 | J113: 214643836 | K113: A7011EC06 - 214643836 - 111 | L113: A7011EC06
A114: Abbott | B114: A06S | C114: MITCHELL, FELICIA | D114: Teacher | E114: 43784 | F114: 43765 | G114: 43778 | H114: 1114.7 | I114: 51.75 | J114: 216803194 | K114: 2A0FE99C0 - 216803194 - 111 | L114: 2A0FE99C0
A115: Abbott | B115: A06S | C115: MITCHELL, FELICIA | D115: Teacher | E115: 43798 | F115: 43779 | G115: 43792 | H115: 1400.1 | I115: 65 | J115: 219435890 | K115: 80E3439F4 - 219435890 - 111 | L115: 80E3439F4
A116: Abbott | B116: A06S | C116: MITCHELL, FELICIA | D116: Teacher | E116: 43812 | F116: 43793 | G116: 43806 | H116: 1260.09 | I116: 58.5 | J116: 221999757 | K116: 24FE78CF5 - 221999757 - 111 | L116: 24FE78CF5
A117: Abbott | B117: A06S | C117: MITCHELL, FELICIA | D117: Teacher | E117: 43826 | F117: 43807 | G117: 43820 | H117: 1394.72 | I117: 64.75 | J117: 223886765 | K117: 06DA7FE21 - 223886765 - 111 | L117: 06DA7FE21
H118: =SUM(H113:H117) -> 6431.42
A120: Abbott | B120: A03K | C120: RAMBARAN, SHARAINI JONI | D120: FLOATER/TEACHER ASSISTANT | E120: 43742 | F120: 43723 | G120: 43736 | H120: 987.08 | I120: 53.5 | J120: 209886795 | K120: C3C5C41A7 - 209886795 - 111 | L120: C3C5C41A7
A121: Abbott | B121: A03K | C121: RAMBARAN, SHARAINI JONI | D121: FLOATER/TEACHER ASSISTANT | E121: 43756 | F121: 43737 | G121: 43750 | H121: 1010.14 | I121: 54.75 | J121: 212386285 | K121: 498337E58 - 212386285 - 111 | L121: 498337E58
A122: Abbott | B122: A03K | C122: RAMBARAN, SHARAINI JONI | D122: FLOATER/TEACHER ASSISTANT | E122: 43770 | F122: 43751 | G122: 43764 | H122: 811.8 | I122: 44 | J122: 214643838 | K122: A7011EC06 - 214643838 - 111 | L122: A7011EC06
A123: Abbott | B123: A03K | C123: RAMBARAN, SHARAINI JONI | D123: FLOATER/TEACHER ASSISTANT | E123: 43784 | F123: 43765 | G123: 43778 | H123: 779.51 | I123: 42.25 | J123: 216803196 | K123: 2A0FE99C0 - 216803196 - 111 | L123: 2A0FE99C0
A124: Abbott | B124: A03K | C124: RAMBARAN, SHARAINI JONI | D124: FLOATER/TEACHER ASSISTANT | E124: 43798 | F124: 43779 | G124: 43792 | H124: 710.33 | I124: 38.5 | J124: 219435892 | K124: 80E3439F4 - 219435892 - 111 | L124: 80E3439F4
A125: Abbott | B125: A03K | C125: RAMBARAN, SHARAINI JONI | D125: FLOATER/TEACHER ASSISTANT | E125: 43812 | F125: 43793 | G125: 43806 | H125: 788.74 | I125: 42.75 | J125: 221999759 | K125: 24FE78CF5 - 221999759 - 111 | L125: 24FE78CF5
A126: Abbott | B126: A03K | C126: RAMBARAN, SHARAINI JONI | D126: FLOATER/TEACHER ASSISTANT | E126: 43826 | F126: 43807 | G126: 43820 | H126: 996.3 | I126: 54 | J126: 223886767 | K126: 06DA7FE21 - 223886767 - 111 | L126: 06DA7FE21
H127: =SUM(H120:H126) -> 6083.9
A129: Abbott | B129: A05V | C129: SIMMONS, BERTRILLA RENEE | D129: LEAD TEACHER | E129: 43742 | F129: 43723 | G129: 43736 | H129: 2684.05 | I129: 65 | J129: 209886798 | K129: C3C5C41A7 - 209886798 - 111 | L129: C3C5C41A7
A130: Abbott | B130: A05V | C130: SIMMONS, BERTRILLA RENEE | D130: LEAD TEACHER | E130: 43756 | F130: 43737 | G130: 43750 | H130: 2684.05 | I130: 65 | J130: 212386288 | K130: 498337E58 - 212386288 - 111 | L130: 498337E58
...

Sheet Benefits Q2
B1: Abbott Staffing
B3: For the Quarter ending December 31, 2019
F6: Total | M6: =SUM(M9:M15) -> 181.3
E7: Health Ins | J7: Dental Ins | N7: Total | O7: Rate | P7: Allocated
D8: Budget | E8: Q2 | F8: Oct | G8: Nov | H8: Dec | J8: Q2 | K8: Oct | L8: Nov | M8: Dec | N8: Q2
B9: Teachers | C9: Johnny Javier | D9: 46750 | E9: =SUM(F9:H9) -> -287.44 | F9: -287.44 | J9: =SUM(K9:M9) -> 37.76 | K9: 37.76 | N9: =E9+J9 -> -249.68 | O9: 1 | P9: =N9*O9 -> -249.68
C10: Bertrilla Simons | E10: =SUM(F10:H10) -> 2306.82 | F10: 768.94 | G10: 768.94 | H10: 768.94 | J10: =SUM(K10:M10) -> 111.14 | K10: 37.76 | L10: 37.76 | M10: 35.62 | N10: =E10+J10 -> 2417.96 | O10: 1 | P10: =N10*O10 -> 2417.96
C11: Quintella Hollins | D11: Disability - Sept | E11: =SUM(F11:H11) -> 4040.1 | F11: 1346.7 | G11: 1346.7 | H11: 1346.7 | J11: =SUM(K11:M11) -> 64.35 | M11: 64.35 | N11: =E11+J11 -> 4104.45 | P11: =N11*O11 -> 0
E12: =SUM(F12:H12) -> 0 | J12: =SUM(K12:M12) -> 0 | N12: =E12+J12 -> 0 | P12: =N12*O12 -> 0
B13: Teacher Assistants | C13: W Hill | D13: Disability - August | E13: =SUM(F13:H13) -> 0 | J13: =SUM(K13:M13) -> 111.14 | K13: 37.76 | L13: 37.76 | M13: 35.62 | N13: =E13+J13 -> 111.14 | O13: 1 | P13: =N13*O13 -> 111.14
C14: R Stewart | E14: =SUM(F14:H14) -> 3205.05 | F14: 1068.35 | G14: 1068.35 | H14: 1068.35 | J14: =SUM(K14:M14) -> 121.23 | K14: 37.76 | L14: 37.76 | M14: 45.71 | N14: =E14+J14 -> 3326.28 | O14: 1 | P14: =N14*O14 -> 3326.28
C15: R Bryant | E15: =SUM(F15:H15) -> 2596.41 | F15: 865.47 | G15: 865.47 | H15: 865.47 | J15: =SUM(K15:M15) -> 0 | N15: =E15+J15 -> 2596.41 | O15: 1 | P15: =N15*O15 -> 2596.41 | Q15: =SUM(P9:P15) -> 8202.11
E16: =SUM(F16:H16) -> 0 | J16: =SUM(K16:M16) -> 0 | N16: =E16+J16 -> 0 | P16: =N16*O16 -> 0
B17: Floater | C17: S Rambaran | D17: 0 | E17: =SUM(F17:H17) -> 0 | J17: =SUM(K17:M17) -> 0 | N17: =E17+J17 -> 0 | P17: =N17*O17 -> 0
C18: D Brown | E18: =SUM(F18:H18) -> 0 | J18: =SUM(K18:M18) -> 0 | N18: =E18+J18 -> 0 | P18: =N18*O18 -> 0
C19: R Woodridge | E19: =SUM(F19:H19) -> 0 | J19: =SUM(K19:M19) -> 0 | N19: =E19+J19 -> 0 | P19: =N19*O19 -> 0
E20: =SUM(F20:H20) -> 0 | J20: =SUM(K20:M20) -> 0 | N20: =E20+J20 -> 0 | P20: =N20*O20 -> 0
B21: Substitutes | C21: N Muhammad | D21: 0 | E21: =SUM(F21:H21) -> 0 | J21: =SUM(K21:M21) -> 0 | N21: =E21+J21 -> 0 | P21: =N21*O21 -> 0
E22: =SUM(F22:H22) -> 0 | J22: =SUM(K22:M22) -> 0 | N22: =E22+J22 -> 0 | P22: =N22*O22 -> 0
B23: Family Worker | C23: Daphne McMillan | D23: 0 | E23: =SUM(F23:H23) -> 2756.64 | F23: 918.88 | G23: 918.88 | H23: 918.88 | J23: =SUM(K23:M23) -> 0 | N23: =E23+J23 -> 2756.64 | O23: 1 | P23: =N23*O23 -> 2756.64 | Q23: Unallow
D24: 0 | E24: =SUM(F24:H24) -> 0 | J24: =SUM(K24:M24) -> 0 | N24: =E24+J24 -> 0 | P24: =N24*O24 -> 0
B25: Cook | C25: P Tyler | D25: 0 | E25: =SUM(F25:H25) -> 0 | J25: =SUM(K25:M25) -> 0 | N25: =E25+J25 -> 0 | P25: =N25*O25 -> 0
D26: =SUM(D9:D25) -> 46750 | E26: =SUM(E9:E25) -> 14617.58 | F26: =SUM(F9:F25) -> 4680.9 | G26: =SUM(G9:G25) -> 4968.34 | H26: =SUM(H9:H25) -> 4968.34 | J26: =SUM(J9:J25) -> 445.62 | K26: =SUM(K9:K25) -> 151.04 | L26: =SUM(L9:L25) -> 113.28 | M26: =SUM(M9:M25) -> 181.3 | N26: =SUM(N9:N25) -> 15063.2 | P26: =SUM(P9:P25) -> 10958.75
P27: =N27*O27 -> 0
N28: =E28+J28 -> 0 | P28: =N28*O28 -> 0
B29: Program Director | C29: Heather Dance | D29: 4220 | E29: =SUM(F29:H29) -> 4825.89 | F29: 1608.63 | G29: 1608.63 | H29: 1608.63 | J29: =SUM(K29:M29) -> 200.77 | K29: 68.21 | L29: 68.21 | M29: 64.35 | N29: =E29+J29 -> 5026.66 | O29: ='Salary Alloc Q1'!G33 -> 0.82257143 | P29: =N29*O29 -> 4134.7869
E30: =SUM(F30:H30) -> 0 | J30: =SUM(K30:M30) -> 0 | N30: =E30+J30 -> 0 | P30: =N30*O30 -> 0
B31: Clerical | C31: S Alford | D31: 2406 | J31: =SUM(K31:M31) -> 0 | N31: =E31+J31 -> 0 | O31: ='Salary Alloc Q1'!G35 -> 0.3837 | P31: =N31*O31 -> 0 | Q31: Unallow
E32: =SUM(F32:H32) -> 0 | J32: =SUM(K32:M32) -> 0 | N32: =E32+J32 -> 0 | P32: =N32*O32 -> 0
B33: Custodian | C33: Darnell Davis | E33: =SUM(F33:H33) -> 0 | J33: =SUM(K33:M33) -> 0 | N33: =E33+J33 -> 0 | P33: =N33*O33 -> 0
E34: =SUM(F34:H34) -> 0 | J34: =SUM(K34:M34) -> 0 | N34: =E34+J34 -> 0 | P34: =N34*O34 -> 0
B35: Security Guard | C35: Cora Andrews | E35: =SUM(F35:H35) -> 0 | J35: =SUM(K35:M35) -> 0 | N35: =E35+J35 -> 0 | P35: =N35*O35 -> 0
D36: =SUM(D29:D35) -> 6626 | E36: =SUM(E29:E35) -> 4825.89 | F36: =SUM(F29:F35) -> 1608.63 | G36: =SUM(G29:G35) -> 1608.63 | H36: =SUM(H29:H35) -> 1608.63 | J36: =SUM(J29:J35) -> 200.77 | K36: =SUM(K29:K35) -> 68.21 | L36: =SUM(L29:L35) -> 68.21 | M36: =SUM(M29:M35) -> 64.35 | N36: =SUM(N29:N35) -> 5026.66 | P36: =SUM(P29:P35) -> 4134.7869
P37: =N37*O37 -> 0
P38: =N38*O38 -> 0
P39: =N39*O39 -> 0
P40: =N40*O40 -> 0
D41: =SUM(D38:D40) -> 0 | F41: =SUM(F38:F40) -> 0 | K41: =SUM(K38:K40) -> 0
D43: =D26+D36+D41 -> 53376 | E43: =E26+E36+E41 -> 19443.47 | F43: =F26+F36+F41 -> 6289.53 | G43: =G26+G36+G41 -> 6576.97 | H43: =H26+H36+H41 -> 6576.97 | J43: =J26+J36+J41 -> 646.39 | K43: =K26+K36+K41 -> 219.25 | L43: =L26+L36+L41 -> 181.49 | M43: =M26+M36+M41 -> 245.65 | N43: =N26+N36+N41 -> 20089.86 | O43: =O26+O36+O41 -> 0 | P43: =P26+P36+P41 -> 15093.537

Sheet Quarter 3
K1: Total Number of Abbott Children | N1: ='Quarter 1'!M1 -> 45
D2: January - March Under Enrollment | E2: Provider Reported Expenditures | F2: Provider Balance Prior to Ependiture Review | G2: Budget Modification Approved by the District | H2: Budget Modification Request | I2: District Calculated Expenditures 3rd Quarter | J2: Unapproved / Approved Funds Expended (Jan - March | K2: DOE Share of DOE/DHS Shared Costs | N2: ='Quarter 1'!M2 -> 0.7673
A3: Report Due Wednesday, April 15, 2020 by 3:00PM | K3: Change DOE Share of DOE/DHS Shared Costs | N3: ='Quarter 1'!M3 -> 0
C4: NPS Approved | K4: DOE Share of Center-Wide Costs
A5: EXPENDITURES (Cash Paid Out) | C5: 2018-19 Budget | E5: (Jan- March) | F5: (Jan- March) | I5: (Jan- March) | J5: (District Use) | K5: Fund Balance | L5: Comments
A6: EDUCATIONAL PROGRAM COSTS (Instructional) 10-MONTH COST ONLY EXCLUDING BENEFITS
A7: Teacher Salary | C7: ='Quarter 2'!J7 -> 122486.32 | D7: =C7/(A$63-C$13-C$14)*D$5*D$65 -> 0 | E7: 0 | F7: =SUM(C7:D7)-E7 -> 122486.32 | J7: =IF(I7>E7,0,I7-E7) -> 0 | K7: =IF(I7>0,(C7+D7+G7-I7),F7+G7) -> 122486.32
A8: Teacher Assistant Salary | C8: ='Quarter 2'!J8 -> 54126.35 | D8: =C8/(A$63-C$13-C$14)*D$5*D$65 -> 0 | E8: 0 | F8: =SUM(C8:D8)-E8 -> 54126.35 | J8: =IF(I8>E8,0,I8-E8) -> 0 | K8: =IF(I8>0,(C8+D8+G8-I8),F8+G8) -> 54126.35
A9: Floating Teacher Assistant Salary | C9: ='Quarter 2'!J9 -> 12853.1 | D9: =C9/(A$63-C$13-C$14)*D$5*D$65 -> 0 | E9: 0 | F9: =SUM(C9:D9)-E9 -> 12853.1 | J9: =IF(I9>E9,0,I9-E9) -> 0 | K9: =IF(I9>0,(C9+D9+G9-I9),F9+G9) -> 12853.1
A10: Teacher, Assistant and Floater Benefits | C10: ='Quarter 2'!J10 -> 19224.75 | D10: =C10/(A$63-C$13-C$14)*D$5*D$65 -> 0 | E10: 19065.57 | F10: =SUM(C10:D10)-E10 -> 159.18 | J10: =IF(I10>E10,0,I10-E10) -> -19065.57 | K10: =IF(I10>0,(C10+D10+G10-I10),F10+G10) -> 159.18
A11: Substitute Teacher Daily Rate (Stipend) | C11: ='Quarter 2'!J11 -> -338 | D11: =C11/(A$63-C$13-C$14)*D$5*D$65 -> 0 | E11: 0 | F11: =SUM(C11:D11)-E11 -> -338 | J11: =IF(I11>E11,0,I11-E11) -> 0 | K11: =IF(I11>0,(C11+D11+G11-I11),F11+G11) -> -338
A12: Substitute Assistant Daily Rate (Stipend) | C12: ='Quarter 2'!J12 -> 1687.2 | D12: =C12/(A$63-C$13-C$14)*D$5*D$65 -> 0 | E12: 0 | F12: =SUM(C12:D12)-E12 -> 1687.2 | J12: =IF(I12>E12,0,I12-E12) -> 0 | K12: =IF(I12>0,(C12+D12+G12-I12),F12+G12) -> 1687.2
A13: Classroom Materials and Supplies | C13: ='Quarter 2'!J13 -> 3533 | E13: 3573.47 | F13: =SUM(C13:D13)-E13 -> -40.47 | J13: =IF(I13>E13,0,I13-E13) -> -3573.47 | K13: =IF(I13>0,(C13+D13+G13-I13),F13+G13) -> -40.47
A14: Classroom Technology | C14: ='Quarter 2'!J14 -> 3000 | E14: 2195.95 | F14: =SUM(C14:D14)-E14 -> 804.05 | J14: =IF(I14>E14,0,I14-E14) -> -2195.95 | K14: =IF(I14>0,(C14+D14+G14-I14),F14+G14) -> 804.05
A15: Field Trips w/ Transportation | C15: ='Quarter 2'!J15 -> 3340 | D15: =C15/(A$63-C$13-C$14)*D$5*D$65 -> 0 | E15: 300 | F15: =SUM(C15:D15)-E15 -> 3040 | J15: =IF(I15>E15,0,I15-E15) -> -300 | K15: =IF(I15>0,(C15+D15+G15-I15),F15+G15) -> 3040
A16: Family Worker Salary | C16: ='Quarter 2'!J16 -> 13188.269 | D16: =C16/(A$63-C$13-C$14)*D$5*D$65 -> 0 | E16: 0 | F16: =SUM(C16:D16)-E16 -> 13188.269 | J16: =IF(I16>E16,0,I16-E16) -> 0 | K16: =IF(I16>0,(C16+D16+G16-I16),F16+G16) -> 13188.269
A17: Family Worker Benefits | C17: ='Quarter 2'!J17 -> 0 | D17: =C17/(A$63-C$13-C$14)*D$5*D$65 -> 0 | E17: 19065.57 | F17: =SUM(C17:D17)-E17 -> -19065.57 | J17: =IF(I17>E17,0,I17-E17) -> -19065.57 | K17: =IF(I17>0,(C17+D17+G17-I17),F17+G17) -> -19065.57
A18: Food CACFP; September - June (for contracted preschool children only) | C18: ='Quarter 2'!J18 -> 0 | D18: =C18/(A$63-C$13-C$14)*D$5*D$65 -> 0 | E18: 0 | F18: =SUM(C18:D18)-E18 -> 0 | J18: =IF(I18>E18,0,I18-E18) -> 0 | K18: =IF(I18>0,(C18+D18+G18-I18),F18+G18) -> 0
A19: Food Worker Salary (cook) | C19: ='Quarter 2'!J19 -> 5650.3385 | D19: =C19/(A$63-C$13-C$14)*D$5*D$65 -> 0 | E19: 0 | F19: =SUM(C19:D19)-E19 -> 5650.3385 | J19: =IF(I19>E19,0,I19-E19) -> 0 | K19: =IF(I19>0,(C19+D19+G19-I19),F19+G19) -> 5650.3385
A20: Food Worker Salary (cook asst.) | C20: ='Quarter 2'!J20 -> 0 | D20: =C20/(A$63-C$13-C$14)*D$5*D$65 -> 0 | E20: 0 | F20: =SUM(C20:D20)-E20 -> 0 | J20: =IF(I20>E20,0,I20-E20) -> 0 | K20: =IF(I20>0,(C20+D20+G20-I20),F20+G20) -> 0
A21: Food Worker Benefits (Cook & Assist. Cook) | C21: ='Quarter 2'!J21 -> 0 | D21: =C21/(A$63-C$13-C$14)*D$5*D$65 -> 0 | E21: 19065.57 | F21: =SUM(C21:D21)-E21 -> -19065.57 | J21: =IF(I21>E21,0,I21-E21) -> -19065.57 | K21: =IF(I21>0,(C21+D21+G21-I21),F21+G21) -> -19065.57
A22: Social Security (6.20%) | C22: ='Quarter 2'!J22 -> 13191.391 | D22: =C22/(A$63-C$13-C$14)*D$5*D$65 -> 0 | E22: 0 | F22: =SUM(C22:D22)-E22 -> 13191.391 | J22: =IF(I22>E22,0,I22-E22) -> 0 | K22: =IF(I22>0,(C22+D22+G22-I22),F22+G22) -> 13191.391
A23: Medicare (1.45%) | C23: ='Quarter 2'!J23 -> 3085.1125 | D23: =C23/(A$63-C$13-C$14)*D$5*D$65 -> 0 | E23: 0 | F23: =SUM(C23:D23)-E23 -> 3085.1125 | J23: =IF(I23>E23,0,I23-E23) -> 0 | K23: =IF(I23>0,(C23+D23+G23-I23),F23+G23) -> 3085.1125
A24: Unemployment (2.80%) | C24: ='Quarter 2'!J24 -> 5957.4586 | D24: =C24/(A$63-C$13-C$14)*D$5*D$65 -> 0 | E24: 0 | F24: =SUM(C24:D24)-E24 -> 5957.4586 | J24: =IF(I24>E24,0,I24-E24) -> 0 | K24: =IF(I24>0,(C24+D24+G24-I24),F24+G24) -> 5957.4586
A25: Disability (0.50%) | C25: ='Quarter 2'!J25 -> 1063.8319 | D25: =C25/(A$63-C$13-C$14)*D$5*D$65 -> 0 | E25: 0 | F25: =SUM(C25:D25)-E25 -> 1063.8319 | J25: =IF(I25>E25,0,I25-E25) -> 0 | K25: =IF(I25>0,(C25+D25+G25-I25),F25+G25) -> 1063.8319
A26: Sub-Total | C26: =SUM(C7:C25) -> 262049.12 | E26: =SUM(E7:E25) -> 63266.13 | F26: =SUM(F7:F25) -> 198782.99 | I26: =SUM(I7:I25) -> 0 | J26: =SUM(J7:J25) -> -63266.13 | K26: =SUM(K7:K25) -> 198782.99
A27: ADMINISTRATIVE SUPPORT COSTS (NON-Instructional) 12-MONTH COST ONLY EXCLUDING BENEFITS
A28: Director Salary | C28: ='Quarter 2'!J28 -> 15393.516 | D28: =C28/(A$63-C$13-C$14)*D$5*D$65 -> 0 | E28: 0 | F28: =SUM(C28:D28)-E28 -> 15393.516 | J28: =IF(I28>E28,0,I28-E28) -> 0 | K28: =IF(I28>0,(C28+D28+G28-I28),F28+G28) -> 15393.516
A29: Director Benefits | C29: ='Quarter 2'!J29 -> -337.81633 | D29: =C29/(A$63-C$13-C$14)*D$5*D$65 -> 0 | E29: 19065.57 | F29: =SUM(C29:D29)-E29 -> -19403.386 | J29: =IF(I29>E29,0,I29-E29) -> -19065.57 | K29: =IF(I29>0,(C29+D29+G29-I29),F29+G29) -> -19403.386
A30: Clerical Salary | C30: ='Quarter 2'!J30 -> 507.73469 | D30: =C30/(A$63-C$13-C$14)*D$5*D$65 -> 0 | E30: 0 | F30: =SUM(C30:D30)-E30 -> 507.73469 | J30: =IF(I30>E30,0,I30-E30) -> 0 | K30: =IF(I30>0,(C30+D30+G30-I30),F30+G30) -> 507.73469
A31: Clerical Benefits | C31: ='Quarter 2'!J31 -> 0 | D31: =C31/(A$63-C$13-C$14)*D$5*D$65 -> 0 | E31: 19065.57 | F31: =SUM(C31:D31)-E31 -> -19065.57 | J31: =IF(I31>E31,0,I31-E31) -> -19065.57 | K31: =IF(I31>0,(C31+D31+G31-I31),F31+G31) -> -19065.57
A32: Janitor Salary | C32: ='Quarter 2'!J32 -> 5228.9912 | D32: =C32/(A$63-C$13-C$14)*D$5*D$65 -> 0 | E32: 0 | F32: =SUM(C32:D32)-E32 -> 5228.9912 | J32: =IF(I32>E32,0,I32-E32) -> 0 | K32: =IF(I32>0,(C32+D32+G32-I32),F32+G32) -> 5228.9912
A33: Janitor Benefits | C33: ='Quarter 2'!J33 -> 0 | D33: =C33/(A$63-C$13-C$14)*D$5*D$65 -> 0 | E33: 19065.57 | F33: =SUM(C33:D33)-E33 -> -19065.57 | J33: =IF(I33>E33,0,I33-E33) -> -19065.57 | K33: =IF(I33>0,(C33+D33+G33-I33),F33+G33) -> -19065.57
A34: Security Guard Salary | C34: ='Quarter 2'!J34 -> 4173.9148 | D34: =C34/(A$63-C$13-C$14)*D$5*D$65 -> 0 | E34: 0 | F34: =SUM(C34:D34)-E34 -> 4173.9148 | J34: =IF(I34>E34,0,I34-E34) -> 0 | K34: =IF(I34>0,(C34+D34+G34-I34),F34+G34) -> 4173.9148
A35: Secufity Guard Benefits | C35: ='Quarter 2'!J35 -> 0 | D35: =C35/(A$63-C$13-C$14)*D$5*D$65 -> 0 | E35: 19065.57 | F35: =SUM(C35:D35)-E35 -> -19065.57 | J35: =IF(I35>E35,0,I35-E35) -> -19065.57 | K35: =IF(I35>0,(C35+D35+G35-I35),F35+G35) -> -19065.57
A36: Social Security (6.20%) | C36: ='Quarter 2'!J36 -> 1568.8577 | D36: =C36/(A$63-C$13-C$14)*D$5*D$65 -> 0 | E36: 0 | F36: =SUM(C36:D36)-E36 -> 1568.8577 | J36: =IF(I36>E36,0,I36-E36) -> 0 | K36: =IF(I36>0,(C36+D36+G36-I36),F36+G36) -> 1568.8577
A37: Medicare (1.45%) | C37: ='Quarter 2'!J37 -> 366.91027 | D37: =C37/(A$63-C$13-C$14)*D$5*D$65 -> 0 | E37: 0 | F37: =SUM(C37:D37)-E37 -> 366.91027 | J37: =IF(I37>E37,0,I37-E37) -> 0 | K37: =IF(I37>0,(C37+D37+G37-I37),F37+G37) -> 366.91027
A38: Unemployment (2.80%) | C38: ='Quarter 2'!J38 -> 708.51638 | D38: =C38/(A$63-C$13-C$14)*D$5*D$65 -> 0 | E38: 0 | F38: =SUM(C38:D38)-E38 -> 708.51638 | J38: =IF(I38>E38,0,I38-E38) -> 0 | K38: =IF(I38>0,(C38+D38+G38-I38),F38+G38) -> 708.51638
A39: Disability (0.50%) | C39: ='Quarter 2'!J39 -> 126.52078 | D39: =C39/(A$63-C$13-C$14)*D$5*D$65 -> 0 | E39: 0 | F39: =SUM(C39:D39)-E39 -> 126.52078 | J39: =IF(I39>E39,0,I39-E39) -> 0 | K39: =IF(I39>0,(C39+D39+G39-I39),F39+G39) -> 126.52078
A40: INDIRECT COSTS -- SPACE COSTS AND ALL OTHER ALLOWABLE INDIRECT (NON-Instructional) 12-MONTH COSTS
A41: Rent, Mortgage, Other Space Costs | C41: ='Quarter 2'!J41 -> 45560.914 | D41: =C41/(A$63-C$13-C$14)*D$5*D$65 -> 0 | E41: 0 | F41: =SUM(C41:D41)-E41 -> 45560.914 | J41: =IF(I41>E41,0,I41-E41) -> 0 | K41: =IF(I41>0,(C41+D41+G41-I41),F41+G41) -> 45560.914
A42: Office Equipment>$2000 and Repair | C42: ='Quarter 2'!J42 -> 983.38776 | D42: =C42/(A$63-C$13-C$14)*D$5*D$65 -> 0 | E42: 0 | F42: =SUM(C42:D42)-E42 -> 983.38776 | J42: =IF(I42>E42,0,I42-E42) -> 0 | K42: =IF(I42>0,(C42+D42+G42-I42),F42+G42) -> 983.38776
A43: Office Materials and Supplies | C43: ='Quarter 2'!J43 -> 1568.0408 | D43: =C43/(A$63-C$13-C$14)*D$5*D$65 -> 0 | E43: 940 | F43: =SUM(C43:D43)-E43 -> 628.04082 | J43: =IF(I43>E43,0,I43-E43) -> -940 | K43: =IF(I43>0,(C43+D43+G43-I43),F43+G43) -> 628.04082
A44: Food-Related Paper Supplies | C44: ='Quarter 2'!J44 -> 467.34694 | D44: =C44/(A$63-C$13-C$14)*D$5*D$65 -> 0 | E44: 0 | F44: =SUM(C44:D44)-E44 -> 467.34694 | J44: =IF(I44>E44,0,I44-E44) -> 0 | K44: =IF(I44>0,(C44+D44+G44-I44),F44+G44) -> 467.34694
A45: Cleaning Supplies | C45: ='Quarter 2'!J45 -> 477.34694 | D45: =C45/(A$63-C$13-C$14)*D$5*D$65 -> 0 | E45: 1366.77 | F45: =SUM(C45:D45)-E45 -> -889.42306 | J45: =IF(I45>E45,0,I45-E45) -> -1366.77 | K45: =IF(I45>0,(C45+D45+G45-I45),F45+G45) -> -889.42306
A46: Food for Meetings | C46: ='Quarter 2'!J46 -> 383.67347 | D46: =C46/(A$63-C$13-C$14)*D$5*D$65 -> 0 | E46: 174.75 | F46: =SUM(C46:D46)-E46 -> 208.92347 | J46: =IF(I46>E46,0,I46-E46) -> -174.75 | K46: =IF(I46>0,(C46+D46+G46-I46),F46+G46) -> 208.92347
A47: Building/Grounds Maintenance/Repair | C47: ='Quarter 2'!J47 -> 3151.7347 | D47: =C47/(A$63-C$13-C$14)*D$5*D$65 -> 0 | E47: 3886.84 | F47: =SUM(C47:D47)-E47 -> -735.10531 | J47: =IF(I47>E47,0,I47-E47) -> -3886.84 | K47: =IF(I47>0,(C47+D47+G47-I47),F47+G47) -> -735.10531
A48: Utilities | C48: ='Quarter 2'!J48 -> -692.53061 | D48: =C48/(A$63-C$13-C$14)*D$5*D$65 -> 0 | E48: 4035.57 | F48: =SUM(C48:D48)-E48 -> -4728.1006 | J48: =IF(I48>E48,0,I48-E48) -> -4035.57 | K48: =IF(I48>0,(C48+D48+G48-I48),F48+G48) -> -4728.1006
A49: Telecommunications Services | C49: ='Quarter 2'!J49 -> 686.16327 | D49: =C49/(A$63-C$13-C$14)*D$5*D$65 -> 0 | E49: 756 | F49: =SUM(C49:D49)-E49 -> -69.836735 | J49: =IF(I49>E49,0,I49-E49) -> -756 | K49: =IF(I49>0,(C49+D49+G49-I49),F49+G49) -> -69.836735
A50: Security Equipment | C50: ='Quarter 2'!J50 -> 112.93878 | D50: =C50/(A$63-C$13-C$14)*D$5*D$65 -> 0 | E50: 1178.85 | F50: =SUM(C50:D50)-E50 -> -1065.9112 | J50: =IF(I50>E50,0,I50-E50) -> -1178.85 | K50: =IF(I50>0,(C50+D50+G50-I50),F50+G50) -> -1065.9112
A51: Insurance | C51: ='Quarter 2'!J51 -> -797.91837 | D51: =C51/(A$63-C$13-C$14)*D$5*D$65 -> 0 | E51: 2908 | F51: =SUM(C51:D51)-E51 -> -3705.9184 | J51: =IF(I51>E51,0,I51-E51) -> -2908 | K51: =IF(I51>0,(C51+D51+G51-I51),F51+G51) -> -3705.9184
A52: Accounting Fees | C52: ='Quarter 2'!J52 -> -3050.5714 | D52: =C52/(A$63-C$13-C$14)*D$5*D$65 -> 0 | E52: 3266 | F52: =SUM(C52:D52)-E52 -> -6316.5714 | J52: =IF(I52>E52,0,I52-E52) -> -3266 | K52: =IF(I52>0,(C52+D52+G52-I52),F52+G52) -> -6316.5714
... A56: Profit | C56: ='Quarter 2'!J56 -> 0 | D56: =C56/(A$63-C$13-C$14)*D$5*D$65 -> 0 | E56: 0 | F56: =SUM(C56:D56)-E56 -> 0 | J56: =IF(I56>E56,0,I56-E56) -> 0 | K56: =IF(I56>0,(C56+D56+G56-I56),F56+G56) -> 0
A57: ='Quarter 2'!A57:B57 -> (Insert item name or brief description on this line.) | C57: ='Quarter 2'!J57 -> 0 | D57: =C57/(A$63-C$13-C$14)*D$5*D$65 -> 0 | E57: 0 | F57: =SUM(C57:D57)-E57 -> 0 | J57: =IF(I57>E57,0,I57-E57) -> 0 | K57: =IF(I57>0,(C57+D57+G57-I57),F57+G57) -> 0
A58: ='Quarter 2'!A58:B58 -> (Insert item name or brief description on this line.) | C58: ='Quarter 2'!J58 -> 0 | D58: =C58/(A$63-C$13-C$14)*D$5*D$65 -> 0 | E58: 0 | F58: =SUM(C58:D58)-E58 -> 0 | J58: =IF(I58>E58,0,I58-E58) -> 0 | K58: =IF(I58>0,(C58+D58+G58-I58),F58+G58) -> 0
A59: ='Quarter 2'!A59:B59 -> (Insert item name or brief description on this line.) | C59: ='Quarter 2'!J59 -> 0 | D59: =C59/(A$63-C$13-C$14)*D$5*D$65 -> 0 | E59: 0 | F59: =SUM(C59:D59)-E59 -> 0 | J59: =IF(I59>E59,0,I59-E59) -> 0 | K59: =IF(I59>0,(C59+D59+G59-I59),F59+G59) -> 0
A60: ='Quarter 2'!A60:B60 -> (Insert item name or brief description on this line.) | C60: ='Quarter 2'!J60 -> 0 | D60: =C60/(A$63-C$13-C$14)*D$5*D$65 -> 0 | E60: 0 | F60: =SUM(C60:D60)-E60 -> 0 | J60: =IF(I60>E60,0,I60-E60) -> 0 | K60: =IF(I60>0,(C60+D60+G60-I60),F60+G60) -> 0
A61: ='Quarter 2'!A61:B61 -> (Insert item name or brief description on this line.) | C61: ='Quarter 2'!J61 -> 0 | D61: =C61/(A$63-C$13-C$14)*D$5*D$65 -> 0 | E61: 0 | F61: =SUM(C61:D61)-E61 -> 0 | J61: =IF(I61>E61,0,I61-E61) -> 0 | K61: =IF(I61>0,(C61+D61+G61-I61),F61+G61) -> 0
C62: ='Quarter 2'!J62 -> 0 | D62: =C62/(A$63-C$13-C$14)*D$5*D$65 -> 0 | F62: =SUM(C62:D62)-E62 -> 0 | J62: =IF(I62>E62,0,I62-E62) -> 0 | K62: =IF(I62>0,(C62+D62+G62-I62),F62+G62) -> 0
A63: =SUM(C7:C25,C28:C39,C41:C62) -> 339021.16 | D63: =SUM(D7:D25,D28:D39,D41:D62) -> 0
A64: TOTAL CASH PAID OUT | E64: =SUM(E7:E25,E28:E63) -> 158997.49 | F64: =SUM(F7:F25,F28:F63) -> 180023.67 | G64: =SUM(G7:G25,G28:G39,G41:G62) -> 0 | H64: =SUM(H7:H25,H28:H39,H41:H62) -> 0 | I64: =SUM(I7:I25,I28:I63) -> 0 | J64: =SUM(J7:J25,J28:J63) -> -158997.49 | K64: =SUM(K7:K25,K28:K63) -> 180023.67
C65: ='Quarter 1'!C65 -> 819.62242 | D65: ='Quarter 1'!D65 -> 1346.0374

Sheet PL Qrt 3
A1: URBAN LEAGUE OF ESSEX COUNTY
A2: Profit and Loss Detail
A3: January 1 - March 28, 2020
B5: Date | C5: Transaction Type | D5: Num | E5: Name | F5: Location | G5: Class | H5: Memo/Description | I5: Split | J5: Amount | K5: Balance
A6: Ordinary Income/Expenses
A7: Income
A8: 4500 Revenue from Government Grants
A9: 4530 State Grants
A10: 4537.1 Abbott FYE 19-20
B11: 01/01/2020 | C11: Invoice | D11: 201995 | E11: Grants/Contracts:Newark Public Schools (Abbott) | F11: 504 Central Ave | G11: 111 Abbott | H11: Abbott invoice for January 2020 | I11: 1100 Accounts/ Contributions Receivable | J11: 57003.89 | K11: 57003.89
B12: 02/01/2020 | C12: Invoice | D12: 202003 | E12: Grants/Contracts:Newark Public Schools (Abbott) | F12: 504 Central Ave | G12: 111 Abbott | H12: Amount Due for February 2020 Abbott Program | I12: 1100 Accounts/ Contributions Receivable | J12: 57003.89 | K12: 114007.78
B13: 03/01/2020 | C13: Invoice | D13: 202016 | E13: Grants/Contracts:Newark Public Schools (Abbott) | F13: 504 Central Ave | G13: 111 Abbott | H13: Amount Due for March 2020 Abbott Program | I13: 1100 Accounts/ Contributions Receivable | J13: 57003.89 | K13: 171011.67
A14: Total for 4537.1 Abbott FYE 19-20 | J14: 171011.67
A15: Total for 4530 State Grants | J15: 171011.67
A16: Total for 4500 Revenue from Government Grants | J16: 171011.67
A17: Total for Income | J17: 171011.67
A18: Expenses
A19: 7200 Salaries & Related Expenses
A20: 7220 Salaries & Wages
A21: 7222 Staff
A22: 7222h Teacher
B23: 01/31/2020 | C23: Journal Entry | D23: 212 | G23: 111 Abbott | I23: -Split- | J23: 31259 | K23: 31259
B24: 02/29/2020 | C24: Journal Entry | D24: 288 | G24: 111 Abbott | I24: -Split- | J24: 32417 | K24: 63676
A25: Total for 7222h Teacher | J25: 63676
A26: Total for 7222 Staff | J26: 63676
A27: Total for 7220 Salaries & Wages | J27: 63676
A28: 7240 Employee Benefits
A29: 7241 Health Insurance
B30: 01/01/2020 | C30: Bill | D30: 293105697 | E30: Horizon Blue Cross Blue Shield of NJ | G30: 111 Abbott | H30: To record Horizon Exp. Billing Period 01/15/20 - 02/15/20 | I30: 2000 Accounts Payable | J30: 6576.97 | K30: 6576.97
B31: 02/01/2020 | C31: Bill | D31: 293308978 | E31: Horizon Blue Cross Blue Shield of NJ | G31: 111 Abbott | H31: To record Horizon Exp. Billing Period 02/15/20 - 03/15/20 | I31: 2000 Accounts Payable | J31: 6576.97 | K31: 13153.94
B32: 03/01/2020 | C32: Bill | D32: 293512262 | E32: Horizon Blue Cross Blue Shield of NJ | G32: 111 Abbott | H32: To record Horizon Exp. Billing Period 03/15/20 - 04/15/20 | I32: 2000 Accounts Payable | J32: 6576.97 | K32: 19730.91
A33: Total for 7241 Health Insurance | J33: 19730.91
A34: 7242 Life and Dental Insurance
B35: 01/01/2020 | C35: Bill | D35: 01.01.20PL | E35: Principal Financial Group | G35: 111 Abbott | H35: Life, Dental & AD&D | I35: 2000 Accounts Payable | J35: 441.72 | K35: 441.72
B36: 02/01/2020 | C36: Bill | D36: 02.01.20PL | E36: Principal Financial Group | G36: 111 Abbott | H36: Life, Dental & AD&D | I36: 2000 Accounts Payable | J36: 441.72 | K36: 883.44
B37: 03/01/2020 | C37: Bill | D37: 03.01.20PL | E37: Principal Financial Group | G37: 111 Abbott | H37: Life, Dental & AD&D | I37: 2000 Accounts Payable | J37: 441.72 | K37: 1325.16
A38: Total for 7242 Life and Dental Insurance | J38: 1325.16
A39: 7243 Disability Ins
B40: 02/18/2020 | C40: Bill | D40: 02.18.20DG | E40: Dearborn Life Insurance Co. | G40: 111 Abbott | H40: Life Insurance for the Period: 03/01/20 - 05/31/20 | I40: 2000 Accounts Payable | J40: 25.5 | K40: 25.5
A41: Total for 7243 Disability Ins | J41: 25.5
A42: 7244 Employee Contrib - Health
B43: 01/31/2020 | C43: Journal Entry | D43: 213 | G43: 111 Abbott | H43: Employee Medical Contrib | I43: -Split- | J43: -981.45 | K43: -981.45
B44: 02/29/2020 | C44: Journal Entry | D44: 289 | G44: 111 Abbott | H44: Employee Medical Contrib | I44: -Split- | J44: -981.45 | K44: -1962.9
A45: Total for 7244 Employee Contrib - Health | J45: -1962.9
A46: 7247 Emp-ee Contrib -Dental
B47: 01/31/2020 | C47: Journal Entry | D47: 214 | G47: 111 Abbott | H47: Employee Dental Contrib | I47: -Split- | J47: -26.55 | K47: -26.55
B48: 02/29/2020 | C48: Journal Entry | D48: 290 | G48: 111 Abbott | H48: Employee Dental Contrib | I48: -Split- | J48: -26.55 | K48: -53.1
A49: Total for 7247 Emp-ee Contrib -Dental | J49: -53.1
A50: Total for 7240 Employee Benefits | J50: 19065.57
A51: 7250 Payroll Taxes, etc.
A52: 7245 Worker's Compensation Insurance
A53: 7248 Allocated W Comp
B54: 01/31/2020 | C54: Journal Entry | D54: 233 | G54: 111 Abbott | H54: Workers Comp Alloc | I54: -Split- | J54: 840 | K54: 840
B55: 02/28/2020 | C55: Journal Entry | D55: 248 | G55: 111 Abbott | H55: Workers Comp Alloc | I55: -Split- | J55: 840 | K55: 1680
A56: Total for 7248 Allocated W Comp | J56: 1680
A57: Total for 7245 Worker's Compensation Insurance | J57: 1680
A58: 7251 Social Security
B59: 01/30/2020 | C59: Journal Entry | D59: 229 | G59: 111 Abbott | H59: Fica | I59: -Split- | J59: 1885 | K59: 1885
B60: 02/28/2020 | C60: Journal Entry | D60: 287 | G60: 111 Abbott | H60: Fica | I60: -Split- | J60: 1946 | K60: 3831
A61: Total for 7251 Social Security | J61: 3831
A62: 7252 Medicare
B63: 01/30/2020 | C63: Journal Entry | D63: 230 | G63: 111 Abbott | H63: Medi Alloc | I63: -Split- | J63: 441 | K63: 441
B64: 02/28/2020 | C64: Journal Entry | D64: 283 | G64: 111 Abbott | H64: Medi Alloc | I64: -Split- | J64: 455 | K64: 896
A65: Total for 7252 Medicare | J65: 896
A66: 7253 Unemployment
B67: 01/31/2020 | C67: Journal Entry | D67: 232 | G67: 111 Abbott | H67: SUI Alloc | I67: -Split- | J67: 875 | K67: 875
B68: 02/28/2020 | C68: Journal Entry | D68: 285 | G68: 111 Abbott | H68: SUI Alloc | I68: -Split- | J68: 906 | K68: 1781
A69: Total for 7253 Unemployment | J69: 1781
A70: 7254 Disability
B71: 01/30/2020 | C71: Journal Entry | D71: 228 | G71: 111 Abbott | H71: Disability Alloc | I71: -Split- | J71: 172 | K71: 172
B72: 02/28/2020 | C72: Journal Entry | D72: 286 | G72: 111 Abbott | H72: Disability Alloc | I72: -Split- | J72: 178 | K72: 350
A73: Total for 7254 Disability | J73: 350
A74: Total for 7250 Payroll Taxes, etc. | J74: 8538
A75: 7260 Payroll Service Fees
A76: 7260.1 Allocated Payroll Fees
B77: 01/30/2020 | C77: Journal Entry | D77: 231 | G77: 111 Abbott | H77: Payroll Fees | I77: -Split- | J77: 437 | K77: 437
B78: 02/28/2020 | C78: Journal Entry | D78: 284 | G78: 111 Abbott | H78: Payroll Fees | I78: -Split- | J78: 355 | K78: 792
A79: Total for 7260.1 Allocated Payroll Fees | J79: 792
A80: Total for 7260 Payroll Service Fees | J80: 792
A81: Total for 7200 Salaries & Related Expenses | J81: 92071.57
A82: 7500 Contract Service Expenses
A83: 7515 IT Support
A84: 7515.5 Allocated IT consultants
B85: 01/31/2020 | C85: Journal Entry | D85: 235 | G85: 111 Abbott | H85: IT Consultants | I85: -Split- | J85: 1002 | K85: 1002
B86: 02/28/2020 | C86: Journal Entry | D86: 268 | G86: 111 Abbott | H86: IT Consultants | I86: -Split- | J86: 1002 | K86: 2004
A87: Total for 7515.5 Allocated IT consultants | J87: 2004
A88: Total for 7515 IT Support | J88: 2004
A89: 7520 Accounting Fees
A90: 7521 Allocated Acctg and Audit
B91: 01/31/2020 | C91: Journal Entry | D91: 234 | G91: 111 Abbott | H91: Allocated Acctg | I91: -Split- | J91: 1633 | K91: 1633
B92: 02/28/2020 | C92: Journal Entry | D92: 270 | G92: 111 Abbott | H92: Allocated Acctg | I92: -Split- | J92: 1633 | K92: 3266
A93: Total for 7521 Allocated Acctg and Audit | J93: 3266
A94: Total for 7520 Accounting Fees | J94: 3266
A95: Total for 7500 Contract Service Expenses | J95: 5270
A96: 8100 Operating Expenses
A97: 8108 Program Supplies
B98: 03/10/2020 | C98: Bill | D98: 03.10.20HWABBOTT | E98: Heather Wilson | F98: 504 Central Ave | G98: 111 Abbott | H98: Program Supplies | I98: 2000 Accounts Payable | J98: 174.75 | K98: 174.75
A99: Total for 8108 Program Supplies | J99: 174.75
A100: 8110 Supplies
A101: 8112 Alloc Supplies
...

Sheet Quarter 4
L1: Total Number of Abbott Children | O1: ='Quarter 1'!M1 -> 45
D2: April - June Under Enrollment | E2: Provider Reported Expenditures | F2: Provider Balance Prior to Ependiture Review | G2: Budget Modification Approved by the District | H2: Budget Modification Request | I2: Projected Balance after Budget Mod Request | J2: District Calculated Expenditures 4th Quarter | K2: Unapproved Funds Expended (April - June) | L2: DOE Share of DOE/DHS Shared Costs | O2: ='Quarter 1'!M2 -> 0.7673
A3: Report Due Tuesday, JUNE 30, 2020 by 3:00PM | L3: Change DOE Share of DOE/DHS Shared Costs | O3: ='Quarter 1'!M3 -> 0
C4: NPS Approved | L4: DOE Share of Center-Wide Costs | O4: ='Quarter 1'!M4 -> 0
A5: EXPENDITURES (Cash Paid Out) | C5: 2018-19 Budget | D5: 0 | E5: (April - June) | F5: (April - June) | J5: (April - June) | K5: (District Use) | L5: Fund Balance | M5: Comments
A6: EDUCATIONAL PROGRAM COSTS (Instructional) 10-MONTH COST ONLY EXCLUDING BENEFITS
A7: Teacher Salary | C7: ='Quarter 3'!K7 -> 122486.32 | D7: =C7/(A$63-C$13-C$14)*D$5*D$65 -> 0 | I7: =IF(G7=0,F7+H7,F7+G7) -> 0 | K7: =J7-E7 -> 0 | L7: =+(C7+G7)-J7 -> 122486.32
A8: Teacher Assistant Salary | C8: ='Quarter 3'!K8 -> 54126.35 | D8: =C8/(A$63-C$13-C$14)*D$5*D$65 -> 0 | I8: =IF(G8=0,F8+H8,F8+G8) -> 0 | K8: =J8-E8 -> 0 | L8: =+(C8+G8)-J8 -> 54126.35
A9: Floating Teacher Assistant Salary | C9: ='Quarter 3'!K9 -> 12853.1 | D9: =C9/(A$63-C$13-C$14)*D$5*D$65 -> 0 | I9: =IF(G9=0,F9+H9,F9+G9) -> 0 | K9: =J9-E9 -> 0 | L9: =+(C9+G9)-J9 -> 12853.1
A10: Teacher, Assistant and Floater Benefits | C10: ='Quarter 3'!K10 -> 159.18 | D10: =C10/(A$63-C$13-C$14)*D$5*D$65 -> 0 | I10: =IF(G10=0,F10+H10,F10+G10) -> 0 | K10: =J10-E10 -> 0 | L10: =+(C10+G10)-J10 -> 159.18
A11: Substitute Teacher Daily Rate (Stipend) | C11: ='Quarter 3'!K11 -> -338 | D11: =C11/(A$63-C$13-C$14)*D$5*D$65 -> 0 | I11: =IF(G11=0,F11+H11,F11+G11) -> 0 | K11: =J11-E11 -> 0 | L11: =+(C11+G11)-J11 -> -338
A12: Substitute Assistant Daily Rate (Stipend) | C12: ='Quarter 3'!K12 -> 1687.2 | D12: =C12/(A$63-C$13-C$14)*D$5*D$65 -> 0 | I12: =IF(G12=0,F12+H12,F12+G12) -> 0 | K12: =J12-E12 -> 0 | L12: =+(C12+G12)-J12 -> 1687.2
A13: Classroom Materials and Supplies | C13: ='Quarter 3'!K13 -> -40.47 | D13: =C13/(A$63-C$13-C$14)*D$5*D$65 -> 0 | I13: =IF(G13=0,F13+H13,F13+G13) -> 0 | K13: =J13-E13 -> 0 | L13: =+(C13+G13)-J13 -> -40.47
A14: Classroom Technology | C14: ='Quarter 3'!K14 -> 804.05 | D14: =C14/(A$63-C$13-C$14)*D$5*D$65 -> 0 | I14: =IF(G14=0,F14+H14,F14+G14) -> 0 | K14: =J14-E14 -> 0 | L14: =+(C14+G14)-J14 -> 804.05
A15: Field Trips w/ Transportation | C15: ='Quarter 3'!K15 -> 3040 | D15: =C15/(A$63-C$13-C$14)*D$5*D$65 -> 0 | I15: =IF(G15=0,F15+H15,F15+G15) -> 0 | K15: =J15-E15 -> 0 | L15: =+(C15+G15)-J15 -> 3040
A16: Family Worker Salary | C16: ='Quarter 3'!K16 -> 13188.269 | D16: =C16/(A$63-C$13-C$14)*D$5*D$65 -> 0 | I16: =IF(G16=0,F16+H16,F16+G16) -> 0 | K16: =J16-E16 -> 0 | L16: =+(C16+G16)-J16 -> 13188.269
A17: Family Worker Benefits | C17: ='Quarter 3'!K17 -> -19065.57 | D17: =C17/(A$63-C$13-C$14)*D$5*D$65 -> 0 | I17: =IF(G17=0,F17+H17,F17+G17) -> 0 | K17: =J17-E17 -> 0 | L17: =+(C17+G17)-J17 -> -19065.57
A18: Food CACFP; September - June (for contracted preschool children only) | C18: ='Quarter 3'!K18 -> 0 | D18: =C18/(A$63-C$13-C$14)*D$5*D$65 -> 0 | I18: =IF(G18=0,F18+H18,F18+G18) -> 0 | K18: =J18-E18 -> 0 | L18: =+(C18+G18)-J18 -> 0
... A25: Disability (0.50%) | C25: ='Quarter 3'!K25 -> 1063.8319 | D25: =C25/(A$63-C$13-C$14)*D$5*D$65 -> 0 | I25: =IF(G25=0,F25+H25,F25+G25) -> 0 | K25: =J25-E25 -> 0 | L25: =+(C25+G25)-J25 -> 1063.8319
A26: Sub-Total | C26: =SUM(C7:C25) -> 198782.99 | E26: =SUM(E7:E25) -> 0 | F26: =SUM(F7:F25) -> 0 | G26: =SUM(G7:G25) -> 0 | H26: =SUM(H7:H25) -> 0 | I26: =SUM(I7:I25) -> 0 | J26: =SUM(J7:J25) -> 0 | K26: =SUM(K7:K25) -> 0 | L26: =SUM(L7:L25) -> 198782.99
A27: ADMINISTRATIVE SUPPORT COSTS (NON-Instructional) 12-MONTH COST ONLY EXCLUDING BENEFITS
A28: Director Salary | C28: ='Quarter 3'!K28 -> 15393.516 | D28: =C28/(A$63-C$13-C$14)*D$5*D$65 -> 0 | I28: =IF(G28=0,F28+H28,F28+G28) -> 0 | K28: =J28-E28 -> 0 | L28: =+(C28+G28)-J28 -> 15393.516
A29: Director Benefits | C29: ='Quarter 3'!K29 -> -19403.386 | D29: =C29/(A$63-C$13-C$14)*D$5*D$65 -> 0 | I29: =IF(G29=0,F29+H29,F29+G29) -> 0 | K29: =J29-E29 -> 0 | L29: =+(C29+G29)-J29 -> -19403.386
A30: Clerical Salary | C30: ='Quarter 3'!K30 -> 507.73469 | D30: =C30/(A$63-C$13-C$14)*D$5*D$65 -> 0 | I30: =IF(G30=0,F30+H30,F30+G30) -> 0 | K30: =J30-E30 -> 0 | L30: =+(C30+G30)-J30 -> 507.73469
A31: Clerical Benefits | C31: ='Quarter 3'!K31 -> -19065.57 | D31: =C31/(A$63-C$13-C$14)*D$5*D$65 -> 0 | I31: =IF(G31=0,F31+H31,F31+G31) -> 0 | K31: =J31-E31 -> 0 | L31: =+(C31+G31)-J31 -> -19065.57
A32: Janitor Salary | C32: ='Quarter 3'!K32 -> 5228.9912 | D32: =C32/(A$63-C$13-C$14)*D$5*D$65 -> 0 | I32: =IF(G32=0,F32+H32,F32+G32) -> 0 | K32: =J32-E32 -> 0 | L32: =+(C32+G32)-J32 -> 5228.9912
A33: Janitor Benefits | C33: ='Quarter 3'!K33 -> -19065.57 | D33: =C33/(A$63-C$13-C$14)*D$5*D$65 -> 0 | I33: =IF(G33=0,F33+H33,F33+G33) -> 0 | K33: =J33-E33 -> 0 | L33: =+(C33+G33)-J33 -> -19065.57
A34: Security Guard Salary | C34: ='Quarter 3'!K34 -> 4173.9148 | D34: =C34/(A$63-C$13-C$14)*D$5*D$65 -> 0 | I34: =IF(G34=0,F34+H34,F34+G34) -> 0 | K34: =J34-E34 -> 0 | L34: =+(C34+G34)-J34 -> 4173.9148
A35: Secufity Guard Benefits | C35: ='Quarter 3'!K35 -> -19065.57 | D35: =C35/(A$63-C$13-C$14)*D$5*D$65 -> 0 | I35: =IF(G35=0,F35+H35,F35+G35) -> 0 | K35: =C35-I35 -> -19065.57 | L35: =+(C35+G35)-J35 -> -19065.57
A36: Social Security (6.20%) | C36: ='Quarter 3'!K36 -> 1568.8577 | D36: =C36/(A$63-C$13-C$14)*D$5*D$65 -> 0 | I36: =IF(G36=0,F36+H36,F36+G36) -> 0 | K36: =J36-E36 -> 0 | L36: =+(C36+G36)-J36 -> 1568.8577
A37: Medicare (1.45%) | C37: ='Quarter 3'!K37 -> 366.91027 | D37: =C37/(A$63-C$13-C$14)*D$5*D$65 -> 0 | I37: =IF(G37=0,F37+H37,F37+G37) -> 0 | K37: =J37-E37 -> 0 | L37: =+(C37+G37)-J37 -> 366.91027
A38: Unemployment (2.80%) | C38: ='Quarter 3'!K38 -> 708.51638 | D38: =C38/(A$63-C$13-C$14)*D$5*D$65 -> 0 | I38: =IF(G38=0,F38+H38,F38+G38) -> 0 | K38: =J38-E38 -> 0 | L38: =+(C38+G38)-J38 -> 708.51638
A39: Disability (0.50%) | C39: ='Quarter 3'!K39 -> 126.52078 | D39: =C39/(A$63-C$13-C$14)*D$5*D$65 -> 0 | I39: =IF(G39=0,F39+H39,F39+G39) -> 0 | K39: =J39-E39 -> 0 | L39: =+(C39+G39)-J39 -> 126.52078
A40: INDIRECT COSTS -- SPACE COSTS AND ALL OTHER ALLOWABLE INDIRECT (NON-Instructional) 12-MONTH COSTS
A41: Rent, Mortgage, Other Space Costs | C41: ='Quarter 3'!K41 -> 45560.914 | D41: =C41/(A$63-C$13-C$14)*D$5*D$65 -> 0 | I41: =IF(G41=0,F41+H41,F41+G41) -> 0 | K41: =J41-E41 -> 0 | L41: =+(C41+G41)-J41 -> 45560.914
A42: Office Equipment>$2000 and Repair | C42: ='Quarter 3'!K42 -> 983.38776 | D42: =C42/(A$63-C$13-C$14)*D$5*D$65 -> 0 | I42: =IF(G42=0,F42+H42,F42+G42) -> 0 | K42: =J42-E42 -> 0 | L42: =+(C42+G42)-J42 -> 983.38776
A43: Office Materials and Supplies | C43: ='Quarter 3'!K43 -> 628.04082 | D43: =C43/(A$63-C$13-C$14)*D$5*D$65 -> 0 | I43: =IF(G43=0,F43+H43,F43+G43) -> 0 | K43: =J43-E43 -> 0 | L43: =+(C43+G43)-J43 -> 628.04082
A44: Food-Related Paper Supplies | C44: ='Quarter 3'!K44 -> 467.34694 | D44: =C44/(A$63-C$13-C$14)*D$5*D$65 -> 0 | I44: =IF(G44=0,F44+H44,F44+G44) -> 0 | K44: =J44-E44 -> 0 | L44: =+(C44+G44)-J44 -> 467.34694
A45: Cleaning Supplies | C45: ='Quarter 3'!K45 -> -889.42306 | D45: =C45/(A$63-C$13-C$14)*D$5*D$65 -> 0 | I45: =IF(G45=0,F45+H45,F45+G45) -> 0 | K45: =J45-E45 -> 0 | L45: =+(C45+G45)-J45 -> -889.42306
A46: Food for Meetings | C46: ='Quarter 3'!K46 -> 208.92347 | D46: =C46/(A$63-C$13-C$14)*D$5*D$65 -> 0 | I46: =IF(G46=0,F46+H46,F46+G46) -> 0 | K46: =J46-E46 -> 0 | L46: =+(C46+G46)-J46 -> 208.92347
A47: Building/Grounds Maintenance/Repair | C47: ='Quarter 3'!K47 -> -735.10531 | D47: =C47/(A$63-C$13-C$14)*D$5*D$65 -> 0 | I47: =IF(G47=0,F47+H47,F47+G47) -> 0 | K47: =J47-E47 -> 0 | L47: =+(C47+G47)-J47 -> -735.10531
A48: Utilities | C48: ='Quarter 3'!K48 -> -4728.1006 | D48: =C48/(A$63-C$13-C$14)*D$5*D$65 -> 0 | I48: =IF(G48=0,F48+H48,F48+G48) -> 0 | K48: =J48-E48 -> 0 | L48: =+(C48+G48)-J48 -> -4728.1006
A49: Telecommunications Services | C49: ='Quarter 3'!K49 -> -69.836735 | D49: =C49/(A$63-C$13-C$14)*D$5*D$65 -> 0 | I49: =IF(G49=0,F49+H49,F49+G49) -> 0 | K49: =J49-E49 -> 0 | L49: =+(C49+G49)-J49 -> -69.836735
A50: Security Equipment | C50: ='Quarter 3'!K50 -> -1065.9112 | D50: =C50/(A$63-C$13-C$14)*D$5*D$65 -> 0 | I50: =IF(G50=0,F50+H50,F50+G50) -> 0 | K50: =J50-E50 -> 0 | L50: =+(C50+G50)-J50 -> -1065.9112
A51: Insurance | C51: ='Quarter 3'!K51 -> -3705.9184 | D51: =C51/(A$63-C$13-C$14)*D$5*D$65 -> 0 | I51: =IF(G51=0,F51+H51,F51+G51) -> 0 | K51: =J51-E51 -> 0 | L51: =+(C51+G51)-J51 -> -3705.9184
A52: Accounting Fees | C52: ='Quarter 3'!K52 -> -6316.5714 | D52: =C52/(A$63-C$13-C$14)*D$5*D$65 -> 0 | I52: =IF(G52=0,F52+H52,F52+G52) -> 0 | K52: =J52-E52 -> 0 | L52: =+(C52+G52)-J52 -> -6316.5714
... A56: Profit | C56: ='Quarter 3'!K56 -> 0 | D56: =C56/(A$63-C$13-C$14)*D$5*D$65 -> 0 | I56: =IF(G56=0,F56+H56,F56+G56) -> 0 | K56: =J56-E56 -> 0 | L56: =+(C56+G56)-J56 -> 0
A57: ='Quarter 3'!A57:B57 -> (Insert item name or brief description on this line.) | C57: ='Quarter 3'!K57 -> 0 | D57: =C57/(A$63-C$13-C$14)*D$5*D$65 -> 0 | I57: =IF(G57=0,F57+H57,F57+G57) -> 0 | K57: =J57-E57 -> 0 | L57: =+(C57+G57)-J57 -> 0
A58: ='Quarter 3'!A58:B58 -> (Insert item name or brief description on this line.) | C58: ='Quarter 3'!K58 -> 0 | D58: =C58/(A$63-C$13-C$14)*D$5*D$65 -> 0 | I58: =IF(G58=0,F58+H58,F58+G58) -> 0 | K58: =J58-E58 -> 0 | L58: =+(C58+G58)-J58 -> 0
A59: ='Quarter 3'!A59:B59 -> (Insert item name or brief description on this line.) | C59: ='Quarter 3'!K59 -> 0 | D59: =C59/(A$63-C$13-C$14)*D$5*D$65 -> 0 | I59: =IF(G59=0,F59+H59,F59+G59) -> 0 | K59: =J59-E59 -> 0 | L59: =IF(J59>0,(C59+D59+G59-J59),(F59+H59)) -> 0
A60: ='Quarter 3'!A60:B60 -> (Insert item name or brief description on this line.) | C60: ='Quarter 3'!K60 -> 0 | D60: =C60/(A$63-C$13-C$14)*D$5*D$65 -> 0 | I60: =IF(G60=0,F60+H60,F60+G60) -> 0 | K60: =J60-E60 -> 0 | L60: =IF(J60>0,(C60+D60+G60-J60),(F60+H60)) -> 0
A61: ='Quarter 3'!A61:B61 -> (Insert item name or brief description on this line.) | C61: ='Quarter 3'!K61 -> 0 | D61: =C61/(A$63-C$13-C$14)*D$5*D$65 -> 0 | I61: =IF(G61=0,F61+H61,F61+G61) -> 0 | K61: =IF(J61>E61,0,J61-E61) -> 0 | L61: =IF(J61>0,(C61+D61+G61-J61),(F61+H61)) -> 0
C62: ='Quarter 3'!K62 -> 0 | D62: =C62/(A$63-C$13-C$14)*D$5*D$65 -> 0 | I62: =IF(G62=0,F62+H62,F62+G62) -> 0 | K62: =IF(J62>E62,0,J62-E62) -> 0 | L62: =IF(J62>0,(C62+D62+G62-J62),(F62+H62)) -> 0
A63: =SUM(C7:C25,C28:C39,C41:C62) -> 180023.67 | D63: =SUM(D41:D62,D28:D39,D7:D25) -> 0
A64: TOTAL CASH PAID OUT | D64: =D65*D5 -> 0 | E64: =SUM(E7:E25,E28:E63) -> 0 | F64: =SUM(F7:F25,F28:F63) -> 0 | G64: =SUM(G7:G25,G28:G63) -> 0 | H64: =SUM(H7:H25,H28:H63) -> 0 | I64: =SUM(I7:I25,I28:I63) -> 0 | J64: =SUM(J7:J25,J28:J63) -> 0 | K64: =SUM(K7:K25,K28:K63) -> -19065.57 | L64: =SUM(L7:L25,L28:L63) -> 180023.67
C65: 1417.801 | D65: ='Quarter 1'!D65 -> 1346.0374 | E65: ='Quarter 1'!D65 -> 1346.0374

Sheet Quarter 1 - 4
J1: Total Number of Abbott Children | M1: ='Quarter 1'!M1 -> 45
J2: DOE Share of DOE/DHS Shared Costs | M2: ='Quarter 1'!M2 -> 0.7673
C3: NPS Approved | D3: 1st Qrt (July 2018-September 2018) | E3: 2nd Qrt (October 2018 -December2018) | F3: 3rd Qrt (January 2019 - March 2019) | G3: 4th Qrt (April 2019 - June 2019) | J3: Change DOE Share of DOE/DHS Shared Costs | M3: ='Quarter 1'!M3 -> 0
H4: Budget Modifications | J4: DOE Share of Center-Wide Costs | M4: 0
A5: EXPENDITURES (Cash Paid Out) | I5: 1st-4th Quarters | J5: Fund Balance | K5: Comments
A7: Teacher Salary | C7: ='Quarter 1'!C7 -> 169561 | D7: =IF('Quarter 1'!H7<=0,'Quarter 1'!E7,'Quarter 1'!H7) -> 3452 | E7: =IF('Quarter 2'!H7<=0,'Quarter 2'!E7,'Quarter 2'!H7) -> 43622.68 | F7: =IF('Quarter 3'!H7<=0,'Quarter 3'!E7,'Quarter 3'!H7) -> 0 | G7: =IF('Quarter 4'!H7<=0,'Quarter 4'!E7,'Quarter 4'!H7) -> 0 | H7: =SUM('Quarter 1'!G7,'Quarter 2'!G7,'Quarter 3'!G7,'Quarter 4'!G7) -> 0 | I7: =SUM(D7:G7) -> 47074.68 | J7: =(C7+H7)-SUM(D7:G7) -> 122486.32
A8: Teacher Assistant Salary | C8: ='Quarter 1'!C8 -> 86836 | D8: =IF('Quarter 1'!H8<=0,'Quarter 1'!E8,'Quarter 1'!H8) -> 4700 | E8: =+'Quarter 2'!E8 -> 28009.65 | F8: =+'Quarter 3'!I8 -> 0 | G8: =+'Quarter 4'!J8 -> 0 | H8: =SUM('Quarter 1'!G8,'Quarter 2'!G8,'Quarter 3'!G8,'Quarter 4'!G8) -> 0 | I8: =SUM(D8:G8) -> 32709.65 | J8: =(C8+H8)-SUM(D8:G8) -> 54126.35
A9: Floating Teacher Assistant Salary | C9: ='Quarter 1'!C9 -> 19800 | D9: =IF('Quarter 1'!H9<=0,'Quarter 1'!E9,'Quarter 1'!H9) -> 863 | E9: =+'Quarter 2'!E9 -> 6083.9 | F9: =+'Quarter 3'!I9 -> 0 | G9: =+'Quarter 4'!J9 -> 0 | H9: =SUM('Quarter 1'!G9,'Quarter 2'!G9,'Quarter 3'!G9,'Quarter 4'!G9) -> 0 | I9: =SUM(D9:G9) -> 6946.9 | J9: =(C9+H9)-SUM(D9:G9) -> 12853.1
A10: Teacher, Assistant and Floater Benefits | C10: ='Quarter 1'!C10 -> 38599.75 | D10: =IF('Quarter 1'!H10<=0,'Quarter 1'!E10,'Quarter 1'!H10) -> 11173 | E10: =+'Quarter 2'!E10 -> 8202 | F10: =+'Quarter 3'!I10 -> 0 | G10: =+'Quarter 4'!J10 -> 0 | H10: =SUM('Quarter 1'!G10,'Quarter 2'!G10,'Quarter 3'!G10,'Quarter 4'!G10) -> 0 | I10: =SUM(D10:G10) -> 19375 | J10: =(C10+H10)-SUM(D10:G10) -> 19224.75
A11: Substitute Teacher Daily Rate (Stipend) | C11: ='Quarter 1'!C11 -> 3000 | D11: =IF('Quarter 1'!H11<=0,'Quarter 1'!E11,'Quarter 1'!H11) -> 3338 | E11: =+'Quarter 2'!E11 -> 0 | F11: =+'Quarter 3'!I11 -> 0 | G11: =+'Quarter 4'!J11 -> 0 | H11: =SUM('Quarter 1'!G11,'Quarter 2'!G11,'Quarter 3'!G11,'Quarter 4'!G11) -> 0 | I11: =SUM(D11:G11) -> 3338 | J11: =(C11+H11)-SUM(D11:G11) -> -338
A12: Substitute Assistant Daily Rate (Stipend) | C12: ='Quarter 1'!C12 -> 4800 | D12: =IF('Quarter 1'!H12<=0,'Quarter 1'!E12,'Quarter 1'!H12) -> 0 | E12: =+'Quarter 2'!E12 -> 3112.8 | F12: =+'Quarter 3'!I12 -> 0 | G12: =+'Quarter 4'!J12 -> 0 | H12: =SUM('Quarter 1'!G12,'Quarter 2'!G12,'Quarter 3'!G12,'Quarter 4'!G12) -> 0 | I12: =SUM(D12:G12) -> 3112.8 | J12: =(C12+H12)-SUM(D12:G12) -> 1687.2
A13: Classroom Materials and Supplies | C13: ='Quarter 1'!C13 -> 6000 | D13: =IF('Quarter 1'!H13<=0,'Quarter 1'!E13,'Quarter 1'!H13) -> 2031 | E13: =+'Quarter 2'!E13 -> 436 | F13: =+'Quarter 3'!I13 -> 0 | G13: =+'Quarter 4'!J13 -> 0 | H13: =SUM('Quarter 1'!G13,'Quarter 2'!G13,'Quarter 3'!G13,'Quarter 4'!G13) -> 0 | I13: =SUM(D13:G13) -> 2467 | J13: =(C13+H13)-SUM(D13:G13) -> 3533
A14: Classroom Technology | C14: ='Quarter 1'!C14 -> 3000 | D14: =IF('Quarter 1'!H14<=0,'Quarter 1'!E14,'Quarter 1'!H14) -> 0 | E14: =+'Quarter 2'!E14 -> 0 | F14: =+'Quarter 3'!I14 -> 0 | G14: =+'Quarter 4'!J14 -> 0 | H14: =SUM('Quarter 1'!G14,'Quarter 2'!G14,'Quarter 3'!G14,'Quarter 4'!G14) -> 0 | I14: =SUM(D14:G14) -> 0 | J14: =(C14+H14)-SUM(D14:G14) -> 3000
A15: Field Trips w/ Transportation | C15: ='Quarter 1'!C15 -> 4500 | D15: =IF('Quarter 1'!H15<=0,'Quarter 1'!E15,'Quarter 1'!H15) -> 560 | E15: =+'Quarter 2'!E15 -> 600 | F15: =+'Quarter 3'!I15 -> 0 | G15: =+'Quarter 4'!J15 -> 0 | H15: =SUM('Quarter 1'!G15,'Quarter 2'!G15,'Quarter 3'!G15,'Quarter 4'!G15) -> 0 | I15: =SUM(D15:G15) -> 1160 | J15: =(C15+H15)-SUM(D15:G15) -> 3340
A16: Family Worker Salary | C16: ='Quarter 1'!C16 -> 24551.798 | D16: =IF('Quarter 1'!H16<=0,'Quarter 1'!E16,'Quarter 1'!H16) -> 4870 | E16: =+'Quarter 2'!E16 -> 6493.5289 | F16: =+'Quarter 3'!I16 -> 0 | G16: =+'Quarter 4'!J16 -> 0 | H16: =SUM('Quarter 1'!G16,'Quarter 2'!G16,'Quarter 3'!G16,'Quarter 4'!G16) -> 0 | I16: =SUM(D16:G16) -> 11363.529 | J16: =(C16+H16)-SUM(D16:G16) -> 13188.269
A17: Family Worker Benefits | C17: ='Quarter 1'!C17 -> 0 | D17: =IF('Quarter 1'!H17<=0,'Quarter 1'!E17,'Quarter 1'!H17) -> 0 | E17: =+'Quarter 2'!E17 -> 0 | F17: =+'Quarter 3'!I17 -> 0 | G17: =+'Quarter 4'!J17 -> 0 | H17: =SUM('Quarter 1'!G17,'Quarter 2'!G17,'Quarter 3'!G17,'Quarter 4'!G17) -> 0 | I17: =SUM(D17:G17) -> 0 | J17: =(C17+H17)-SUM(D17:G17) -> 0
A18: Food CACFP; September - June (for contracted preschool children only) | C18: ='Quarter 1'!C18 -> 0 | D18: =IF('Quarter 1'!H18<=0,'Quarter 1'!E18,'Quarter 1'!H18) -> 0 | E18: =+'Quarter 2'!E18 -> 0 | F18: =+'Quarter 3'!I18 -> 0 | G18: =+'Quarter 4'!J18 -> 0 | H18: =SUM('Quarter 1'!G18,'Quarter 2'!G18,'Quarter 3'!G18,'Quarter 4'!G18) -> 0 | I18: =SUM(D18:G18) -> 0 | J18: =(C18+H18)-SUM(D18:G18) -> 0
A19: Food Worker Salary (cook) | C19: ='Quarter 1'!C19 -> 7500.4588 | D19: =IF('Quarter 1'!H19<=0,'Quarter 1'!E19,'Quarter 1'!H19) -> 424 | E19: =+'Quarter 2'!E19 -> 1426.1203 | F19: =+'Quarter 3'!I19 -> 0 | G19: =+'Quarter 4'!J19 -> 0 | H19: =SUM('Quarter 1'!G19,'Quarter 2'!G19,'Quarter 3'!G19,'Quarter 4'!G19) -> 0 | I19: =SUM(D19:G19) -> 1850.1203 | J19: =(C19+H19)-SUM(D19:G19) -> 5650.3385
... A25: Disability (0.50%) | C25: ='Quarter 1'!C25 -> 1580.2463 | D25: =IF('Quarter 1'!H25<=0,'Quarter 1'!E25,'Quarter 1'!H25) -> 88.235 | E25: =+'Quarter 2'!E25 -> 428.1794 | F25: =+'Quarter 3'!I25 -> 0 | G25: =+'Quarter 4'!J25 -> 0 | H25: =SUM('Quarter 1'!G25,'Quarter 2'!G25,'Quarter 3'!G25,'Quarter 4'!G25) -> 0 | I25: =SUM(D25:G25) -> 516.4144 | J25: =(C25+H25)-SUM(D25:G25) -> 1063.8319
A26: Sub-Total | C26: =SUM(C7:C25) -> 402756.4 | D26: =SUM(D7:D25) -> 33343.471 | E26: =SUM(E7:E25) -> 107363.81 | F26: =SUM(F7:F25) -> 0 | G26: =SUM(G7:G25) -> 0 | I26: =SUM(I7:I25) -> 140707.28 | J26: =SUM(J7:J25) -> 262049.12
A27: ADMINISTRATIVE SUPPORT COSTS (NON-Instructional) 12-MONTH COST ONLY EXCLUDING BENEFITS
A28: Director Salary | C28: ='Quarter 1'!C28 -> 44183.837 | D28: =+'Quarter 1'!E28 -> 13288 | E28: =+'Quarter 2'!E28 -> 15502.321 | F28: =+'Quarter 3'!I28 -> 0 | G28: =+'Quarter 4'!J28 -> 0 | H28: =SUM('Quarter 1'!G28,'Quarter 2'!G28,'Quarter 3'!G28,'Quarter 4'!G28) -> 0 | I28: =SUM(D28:G28) -> 28790.321 | J28: =(C28+H28)-SUM(D28:G28) -> 15393.516
A29: Director Benefits | C29: ='Quarter 1'!C29 -> 8103.1837 | D29: =+'Quarter 1'!E29 -> 4306 | E29: =+'Quarter 2'!E29 -> 4135 | F29: =+'Quarter 3'!I29 -> 0 | G29: =+'Quarter 4'!J29 -> 0 | H29: =SUM('Quarter 1'!G29,'Quarter 2'!G29,'Quarter 3'!G29,'Quarter 4'!G29) -> 0 | I29: =SUM(D29:G29) -> 8441 | J29: =(C29+H29)-SUM(D29:G29) -> -337.81633
A30: Clerical Salary | C30: ='Quarter 1'!C30 -> 3836.7347 | D30: =+'Quarter 1'!E30 -> 3329 | E30: =+'Quarter 2'!E30 -> 0 | F30: =+'Quarter 3'!I30 -> 0 | G30: =+'Quarter 4'!J30 -> 0 | H30: =SUM('Quarter 1'!G30,'Quarter 2'!G30,'Quarter 3'!G30,'Quarter 4'!G30) -> 0 | I30: =SUM(D30:G30) -> 3329 | J30: =(C30+H30)-SUM(D30:G30) -> 507.73469
A31: Clerical Benefits | C31: ='Quarter 1'!C31 -> 0 | D31: =+'Quarter 1'!E31 -> 0 | E31: =+'Quarter 2'!E31 -> 0 | F31: =+'Quarter 3'!I31 -> 0 | G31: =+'Quarter 4'!J31 -> 0 | H31: =SUM('Quarter 1'!G31,'Quarter 2'!G31,'Quarter 3'!G31,'Quarter 4'!G31) -> 0 | I31: =SUM(D31:G31) -> 0 | J31: =(C31+H31)-SUM(D31:G31) -> 0
A32: Janitor Salary | C32: ='Quarter 1'!C32 -> 8440.8163 | D32: =+'Quarter 1'!E32 -> 1496 | E32: =+'Quarter 2'!E32 -> 1715.8251 | F32: =+'Quarter 3'!I32 -> 0 | G32: =+'Quarter 4'!J32 -> 0 | H32: =SUM('Quarter 1'!G32,'Quarter 2'!G32,'Quarter 3'!G32,'Quarter 4'!G32) -> 0 | I32: =SUM(D32:G32) -> 3211.8251 | J32: =(C32+H32)-SUM(D32:G32) -> 5228.9912
A33: Janitor Benefits | C33: ='Quarter 1'!C33 -> 0 | D33: =+'Quarter 1'!E33 -> 0 | E33: =+'Quarter 2'!E33 -> 0 | F33: =+'Quarter 3'!I33 -> 0 | G33: =+'Quarter 4'!J33 -> 0 | H33: =SUM('Quarter 1'!G33,'Quarter 2'!G33,'Quarter 3'!G33,'Quarter 4'!G33) -> 0 | I33: =SUM(D33:G33) -> 0 | J33: =(C33+H33)-SUM(D33:G33) -> 0
A34: Security Guard Salary | C34: ='Quarter 1'!C34 -> 15346.939 | D34: =+'Quarter 1'!E34 -> 5157 | E34: =+'Quarter 2'!E34 -> 6016.024 | F34: =+'Quarter 3'!I34 -> 0 | G34: =+'Quarter 4'!J34 -> 0 | H34: =SUM('Quarter 1'!G34,'Quarter 2'!G34,'Quarter 3'!G34,'Quarter 4'!G34) -> 0 | I34: =SUM(D34:G34) -> 11173.024 | J34: =(C34+H34)-SUM(D34:G34) -> 4173.9148
A35: Secufity Guard Benefits | C35: ='Quarter 1'!C35 -> 0 | D35: =+'Quarter 1'!E35 -> 0 | E35: =+'Quarter 2'!E35 -> 0 | F35: =+'Quarter 3'!I35 -> 0 | G35: =+'Quarter 4'!J35 -> 0 | H35: =SUM('Quarter 1'!G35,'Quarter 2'!G35,'Quarter 3'!G35,'Quarter 4'!G35) -> 0 | I35: =SUM(D35:G35) -> 0 | J35: =(C35+H35)-SUM(D35:G35) -> 0
A36: Social Security (6.20%) | C36: ='Quarter 1'!C36 -> 4452.1162 | D36: =+'Quarter 1'!E36 -> 1442.74 | E36: =+'Quarter 2'!E36 -> 1440.5185 | F36: =+'Quarter 3'!I36 -> 0 | G36: =+'Quarter 4'!J36 -> 0 | H36: =SUM('Quarter 1'!G36,'Quarter 2'!G36,'Quarter 3'!G36,'Quarter 4'!G36) -> 0 | I36: =SUM(D36:G36) -> 2883.2585 | J36: =(C36+H36)-SUM(D36:G36) -> 1568.8577
A37: Medicare (1.45%) | C37: ='Quarter 1'!C37 -> 1041.2207 | D37: =+'Quarter 1'!E37 -> 337.415 | E37: =+'Quarter 2'!E37 -> 336.89547 | F37: =+'Quarter 3'!I37 -> 0 | G37: =+'Quarter 4'!J37 -> 0 | H37: =SUM('Quarter 1'!G37,'Quarter 2'!G37,'Quarter 3'!G37,'Quarter 4'!G37) -> 0 | I37: =SUM(D37:G37) -> 674.31047 | J37: =(C37+H37)-SUM(D37:G37) -> 366.91027
A38: Unemployment (2.80%) | C38: ='Quarter 1'!C38 -> 2010.6331 | D38: =+'Quarter 1'!E38 -> 651.56 | E38: =+'Quarter 2'!E38 -> 650.55676 | F38: =+'Quarter 3'!I38 -> 0 | G38: =+'Quarter 4'!J38 -> 0 | H38: =SUM('Quarter 1'!G38,'Quarter 2'!G38,'Quarter 3'!G38,'Quarter 4'!G38) -> 0 | I38: =SUM(D38:G38) -> 1302.1168 | J38: =(C38+H38)-SUM(D38:G38) -> 708.51638
A39: Disability (0.50%) | C39: ='Quarter 1'!C39 -> 359.04163 | D39: =+'Quarter 1'!E39 -> 116.35 | E39: =+'Quarter 2'!E39 -> 116.17085 | F39: =+'Quarter 3'!I39 -> 0 | G39: =+'Quarter 4'!J39 -> 0 | H39: =SUM('Quarter 1'!G39,'Quarter 2'!G39,'Quarter 3'!G39,'Quarter 4'!G39) -> 0 | I39: =SUM(D39:G39) -> 232.52085 | J39: =(C39+H39)-SUM(D39:G39) -> 126.52078
A40: INDIRECT COSTS -- SPACE COSTS AND ALL OTHER ALLOWABLE INDIRECT (NON-Instructional) 12-MONTH COSTS
A41: Rent, Mortgage, Other Space Costs | C41: ='Quarter 1'!C41 -> 91120.914 | D41: =+'Quarter 1'!E41 -> 22780 | E41: =+'Quarter 2'!E41 -> 22780 | F41: =+'Quarter 3'!I41 -> 0 | G41: =+'Quarter 4'!J41 -> 0 | H41: =SUM('Quarter 1'!G41,'Quarter 2'!G41,'Quarter 3'!G41,'Quarter 4'!G41) -> 0 | I41: =SUM(D41:G41) -> 45560 | J41: =(C41+H41)-SUM(D41:G41) -> 45560.914
A42: Office Equipment>$2000 and Repair | C42: ='Quarter 1'!C42 -> 3069.3878 | D42: =+'Quarter 1'!E42 -> 802 | E42: =+'Quarter 2'!E42 -> 1284 | F42: =+'Quarter 3'!I42 -> 0 | G42: =+'Quarter 4'!J42 -> 0 | H42: =SUM('Quarter 1'!G42,'Quarter 2'!G42,'Quarter 3'!G42,'Quarter 4'!G42) -> 0 | I42: =SUM(D42:G42) -> 2086 | J42: =(C42+H42)-SUM(D42:G42) -> 983.38776
A43: Office Materials and Supplies | C43: ='Quarter 1'!C43 -> 2302.0408 | D43: =+'Quarter 1'!E43 -> 18 | E43: =+'Quarter 2'!E43 -> 716 | F43: =+'Quarter 3'!I43 -> 0 | G43: =+'Quarter 4'!J43 -> 0 | H43: =SUM('Quarter 1'!G43,'Quarter 2'!G43,'Quarter 3'!G43,'Quarter 4'!G43) -> 0 | I43: =SUM(D43:G43) -> 734 | J43: =(C43+H43)-SUM(D43:G43) -> 1568.0408
A44: Food-Related Paper Supplies | C44: ='Quarter 1'!C44 -> 767.34694 | D44: =+'Quarter 1'!E44 -> 0 | E44: =+'Quarter 2'!E44 -> 300 | F44: =+'Quarter 3'!I44 -> 0 | G44: =+'Quarter 4'!J44 -> 0 | H44: =SUM('Quarter 1'!G44,'Quarter 2'!G44,'Quarter 3'!G44,'Quarter 4'!G44) -> 0 | I44: =SUM(D44:G44) -> 300 | J44: =(C44+H44)-SUM(D44:G44) -> 467.34694
A45: Cleaning Supplies | C45: ='Quarter 1'!C45 -> 767.34694 | D45: =+'Quarter 1'!E45 -> 90 | E45: =+'Quarter 2'!E45 -> 200 | F45: =+'Quarter 3'!I45 -> 0 | G45: =+'Quarter 4'!J45 -> 0 | H45: =SUM('Quarter 1'!G45,'Quarter 2'!G45,'Quarter 3'!G45,'Quarter 4'!G45) -> 0 | I45: =SUM(D45:G45) -> 290 | J45: =(C45+H45)-SUM(D45:G45) -> 477.34694
A46: Food for Meetings | C46: ='Quarter 1'!C46 -> 383.67347 | D46: =+'Quarter 1'!E46 -> 0 | E46: =+'Quarter 2'!E46 -> 0 | F46: =+'Quarter 3'!I46 -> 0 | G46: =+'Quarter 4'!J46 -> 0 | H46: =SUM('Quarter 1'!G46,'Quarter 2'!G46,'Quarter 3'!G46,'Quarter 4'!G46) -> 0 | I46: =SUM(D46:G46) -> 0 | J46: =(C46+H46)-SUM(D46:G46) -> 383.67347
A47: Building/Grounds Maintenance/Repair | C47: ='Quarter 1'!C47 -> 3836.7347 | D47: =+'Quarter 1'!E47 -> 567 | E47: =+'Quarter 2'!E47 -> 118 | F47: =+'Quarter 3'!I47 -> 0 | G47: =+'Quarter 4'!J47 -> 0 | H47: =SUM('Quarter 1'!G47,'Quarter 2'!G47,'Quarter 3'!G47,'Quarter 4'!G47) -> 0 | I47: =SUM(D47:G47) -> 685 | J47: =(C47+H47)-SUM(D47:G47) -> 3151.7347
A48: Utilities | C48: ='Quarter 1'!C48 -> 7673.4694 | D48: =+'Quarter 1'!E48 -> 3906 | E48: =+'Quarter 2'!E48 -> 4460 | F48: =+'Quarter 3'!I48 -> 0 | G48: =+'Quarter 4'!J48 -> 0 | H48: =SUM('Quarter 1'!G48,'Quarter 2'!G48,'Quarter 3'!G48,'Quarter 4'!G48) -> 0 | I48: =SUM(D48:G48) -> 8366 | J48: =(C48+H48)-SUM(D48:G48) -> -692.53061
A49: Telecommunications Services | C49: ='Quarter 1'!C49 -> 1688.1633 | D49: =+'Quarter 1'!E49 -> 249 | E49: =+'Quarter 2'!E49 -> 753 | F49: =+'Quarter 3'!I49 -> 0 | G49: =+'Quarter 4'!J49 -> 0 | H49: =SUM('Quarter 1'!G49,'Quarter 2'!G49,'Quarter 3'!G49,'Quarter 4'!G49) -> 0 | I49: =SUM(D49:G49) -> 1002 | J49: =(C49+H49)-SUM(D49:G49) -> 686.16327
A50: Security Equipment | C50: ='Quarter 1'!C50 -> 306.93878 | D50: =+'Quarter 1'!E50 -> 194 | E50: =+'Quarter 2'!E50 -> 0 | F50: =+'Quarter 3'!I50 -> 0 | G50: =+'Quarter 4'!J50 -> 0 | H50: =SUM('Quarter 1'!G50,'Quarter 2'!G50,'Quarter 3'!G50,'Quarter 4'!G50) -> 0 | I50: =SUM(D50:G50) -> 194 | J50: =(C50+H50)-SUM(D50:G50) -> 112.93878
A51: Insurance | C51: ='Quarter 1'!C51 -> 4604.0816 | D51: =+'Quarter 1'!E51 -> 1351 | E51: =+'Quarter 2'!E51 -> 4051 | F51: =+'Quarter 3'!I51 -> 0 | G51: =+'Quarter 4'!J51 -> 0 | H51: =SUM('Quarter 1'!G51,'Quarter 2'!G51,'Quarter 3'!G51,'Quarter 4'!G51) -> 0 | I51: =SUM(D51:G51) -> 5402 | J51: =(C51+H51)-SUM(D51:G51) -> -797.91837
A52: Accounting Fees | C52: ='Quarter 1'!C52 -> 5371.4286 | D52: =+'Quarter 1'!E52 -> 2566 | E52: =+'Quarter 2'!E52 -> 5856 | F52: =+'Quarter 3'!I52 -> 0 | G52: =+'Quarter 4'!J52 -> 0 | H52: =SUM('Quarter 1'!G52,'Quarter 2'!G52,'Quarter 3'!G52,'Quarter 4'!G52) -> 0 | I52: =SUM(D52:G52) -> 8422 | J52: =(C52+H52)-SUM(D52:G52) -> -3050.5714
... A56: Profit | C56: ='Quarter 1'!C56 -> 0 | D56: =+'Quarter 1'!E56 -> 0 | E56: =+'Quarter 2'!E56 -> 0 | F56: =+'Quarter 3'!I56 -> 0 | G56: =+'Quarter 4'!J56 -> 0 | H56: =SUM('Quarter 1'!G56,'Quarter 2'!G56,'Quarter 3'!G56,'Quarter 4'!G56) -> 0 | I56: =SUM(D56:G56) -> 0 | J56: =(C56+H56)-SUM(D56:G56) -> 0
A57: ='Quarter 1'!A57:B57 -> (Insert item name or brief description on this line.) | C57: ='Quarter 1'!C57 -> 0 | D57: =+'Quarter 1'!E57 -> 0 | E57: =+'Quarter 2'!E57 -> 0 | F57: =+'Quarter 3'!I57 -> 0 | G57: =+'Quarter 4'!J57 -> 0 | H57: =SUM('Quarter 1'!G57,'Quarter 2'!G57,'Quarter 3'!G57,'Quarter 4'!G57) -> 0 | I57: =SUM(D57:G57) -> 0 | J57: =(C57+H57)-SUM(D57:G57) -> 0
A58: ='Quarter 1'!A58:B58 -> (Insert item name or brief description on this line.) | C58: ='Quarter 1'!C58 -> 0 | D58: =+'Quarter 1'!E58 -> 0 | E58: =+'Quarter 2'!E58 -> 0 | F58: =IF('Quarter 3'!$I58>0,'Quarter 3'!$I58,'Quarter 3'!$E58) -> 0 | G58: ='Quarter 4'!J58 -> 0 | H58: =SUM('Quarter 1'!G58,'Quarter 2'!G58,'Quarter 3'!G58,'Quarter 4'!G58) -> 0 | I58: =SUM(D58:G58) -> 0 | J58: =C58-SUM(D58:G58) -> 0
A59: ='Quarter 1'!A59:B59 -> (Insert item name or brief description on this line.) | C59: ='Quarter 1'!C59 -> 0 | D59: =+'Quarter 1'!E59 -> 0 | E59: =+'Quarter 2'!E59 -> 0 | F59: =IF('Quarter 3'!$I59>0,'Quarter 3'!$I59,'Quarter 3'!$E59) -> 0 | G59: ='Quarter 4'!J59 -> 0 | H59: =SUM('Quarter 1'!G59,'Quarter 2'!G59,'Quarter 3'!G59,'Quarter 4'!G59) -> 0 | I59: =SUM(D59:G59) -> 0 | J59: =C59-SUM(D59:G59) -> 0
A60: ='Quarter 1'!A60:B60 -> (Insert item name or brief description on this line.) | C60: ='Quarter 1'!C60 -> 0 | D60: =+'Quarter 1'!E60 -> 0 | E60: =+'Quarter 2'!E60 -> 0 | F60: =IF('Quarter 3'!$I60>0,'Quarter 3'!$I60,'Quarter 3'!$E60) -> 0 | G60: ='Quarter 4'!J60 -> 0 | H60: =SUM('Quarter 1'!G60,'Quarter 2'!G60,'Quarter 3'!G60,'Quarter 4'!G60) -> 0 | I60: =SUM(D60:G60) -> 0 | J60: =C60-SUM(D60:G60) -> 0
A61: ='Quarter 1'!A61:B61 -> (Insert item name or brief description on this line.) | C61: ='Quarter 1'!C61 -> 0 | D61: =+'Quarter 1'!E61 -> 0 | E61: =+'Quarter 2'!E61 -> 0 | F61: =IF('Quarter 3'!$I61>0,'Quarter 3'!$I61,'Quarter 3'!$E61) -> 0 | G61: ='Quarter 4'!J61 -> 0 | H61: =SUM('Quarter 1'!G61,'Quarter 2'!G61,'Quarter 3'!G61,'Quarter 4'!G61) -> 0 | I61: =SUM(D61:G61) -> 0 | J61: =C61-SUM(D61:G61) -> 0
C62: ='Quarter 1'!C62 -> 0 | D62: =+'Quarter 1'!E62 -> 0 | E62: =+'Quarter 2'!E62 -> 0 | F62: =IF('Quarter 3'!$I62>0,'Quarter 3'!$I62,'Quarter 3'!$E62) -> 0 | G62: =IF('Quarter 4'!$J62<=0,'Quarter 4'!$E62,'Quarter 4'!$J62) -> 0 | H62: =SUM('Quarter 1'!G62,'Quarter 2'!G62,'Quarter 3'!G62,'Quarter 4'!G62) -> 0 | I62: =SUM(D62:G62) -> 0 | J62: =C62-SUM(D62:G62) -> 0
A63: =SUM(C7:C25,C28:C39,C41:C62) -> 614716.82
A64: TOTAL CASH PAID OUT | D64: =SUM(D7:D25,D28:D63) -> 96645.535 | E64: =SUM(E7:E25,E28:E63) -> 179050.12 | F64: =SUM(F7:F25,F28:F63) -> 0 | G64: =SUM(G7:G25,G28:G63) -> 0 | H64: =SUM(H41:H62,H28:H39,H7:H25) -> 0 | I64: =SUM(I7:I25,I28:I63) -> 275695.66 | J64: =SUM(J7:J25,J28:J63) -> 339021.16

Sheet Schedule A Personnel
A1: 2019-20 SCHEDULE A: Provider Personnel Detail
A3: District: | B3: ='[1]CACFP Worksheet'!B4:D4 -> Newark | D3: Provider: | F3: ='[1]CACFP Worksheet'!B5 -> Urban League Of Essex County
A16: Employee Name | B16: School/Site Name | C16: Job Title | D16: Full-Time Equivalent | E16: Salary Step (if applicable) | F16: 10 Month 2018-19 Salary | G16: 2018-19 Benefits | H16: 12 Month 2019-20 Salary | I16: 10 Month 2019-20 Slary | J16: 2019-20 Benefits | K16: 2016-17 & 2019-20 Staff Salary Increase
A17: SAMPLE: John Doe | C17: Teacher | D17: 1 | E17: M2 | F17: 50000 | G17: 9000 | H17: =F17*1.16 -> 58000 | J17: 9000
A18: SAMPLE: Jane Doe | C18: Clerical Worker | D18: 1 | E18: n/a | F18: 45000 | G18: 6250 | H18: =F18*1.16 -> 52200 | J18: 6406
A19: Teachers
A20: ='[1]4 Teachers'!C5&" "&'[1]4 Teachers'!B5 -> Jhonny Janvier | B20: ='[1]4 Teachers'!A5 -> Urban League | C20: Teacher | D20: ='[1]4 Teachers'!H5 -> 1 | E20: ='[1]4 Teachers'!G5 -> 9 | F20: ='[1]4 Teachers'!I5 -> 58583 | I20: =F20 -> 58583 | K20: ='[1]4 Teachers'!N5 -> 1465
A21: ='[1]4 Teachers'!C6&" "&'[1]4 Teachers'!B6 -> Bertrilla Simmons | B21: ='[1]4 Teachers'!A6 -> Urban League | C21: Teacher | D21: ='[1]4 Teachers'!H6 -> 1 | E21: ='[1]4 Teachers'!G6 -> 9 | F21: ='[1]4 Teachers'!I6 -> 57717 | I21: =F21 -> 57717 | K21: ='[1]4 Teachers'!N6 -> 1443
A22: ='[1]4 Teachers'!C7&" "&'[1]4 Teachers'!B7 -> Melissa Thorpe | B22: ='[1]4 Teachers'!A7 -> Urban League | C22: Teacher | D22: ='[1]4 Teachers'!H8 -> #REF! | E22: ='[1]4 Teachers'!G7 -> 9 | F22: ='[1]4 Teachers'!I7 -> 53261 | I22: =F22 -> 53261 | K22: ='[1]4 Teachers'!N8 -> 0
D23: =SUM(D20:D22) -> #REF! | I23: =SUM(I20:I22) -> 169561
A24: Teacher Assistants
A25: ='[1]4a Teacher Assistants'!C5&" "&'[1]4a Teacher Assistants'!B5 -> Robin Stewart | B25: ='[1]4a Teacher Assistants'!A5 -> Urban League | C25: Teacher Assistant | D25: ='[1]4a Teacher Assistants'!G5 -> 1 | E25: ='[1]4a Teacher Assistants'!F5 -> 0 | F25: ='[1]4a Teacher Assistants'!H5 -> 34413 | I25: =F25 -> 34413 | K25: ='[1]4a Teacher Assistants'!M5 -> 1720
A26: ='[1]4a Teacher Assistants'!C6&" "&'[1]4a Teacher Assistants'!B6 -> Wynora Hill | B26: ='[1]4a Teacher Assistants'!A6 -> Urban League | C26: Teacher Assistant | D26: ='[1]4a Teacher Assistants'!G6 -> 1 | E26: ='[1]4a Teacher Assistants'!F6 -> 0 | F26: ='[1]4a Teacher Assistants'!H6 -> 25872 | I26: =F26 -> 25872 | K26: ='[1]4a Teacher Assistants'!M6 -> 1294
A27: ='[1]4a Teacher Assistants'!C7&" "&'[1]4a Teacher Assistants'!B7 -> Roni Bryant | B27: ='[1]4a Teacher Assistants'!A7 -> Urban League | C27: Teacher Assistant | D27: ='[1]4a Teacher Assistants'!G7 -> 1 | E27: ='[1]4a Teacher Assistants'!F7 -> 0 | F27: ='[1]4a Teacher Assistants'!H7 -> 26551 | I27: =F27 -> 26551 | K27: ='[1]4a Teacher Assistants'!M7 -> 1328
D28: =SUM(D25:D27) -> 3 | I28: =SUM(I25:I27) -> 86836
A29: Floater Teacher Assistant
A30: ='[1]4b Floater Teacher Assistants'!C5&" "&'[1]4b Floater Teacher Assistants'!B5 -> Sharaini Rambaran | B30: ='[1]4b Floater Teacher Assistants'!A5 -> Urban League | C30: Floater Teacher Assist | D30: ='[1]4b Floater Teacher Assistants'!G5 -> 1 | E30: ='[1]4b Floater Teacher Assistants'!F5 -> 2 | F30: ='[1]4b Floater Teacher Assistants'!H5 -> 19800 | I30: =F30 -> 19800 | K30: ='[1]4b Floater Teacher Assistants'!M5 -> 495
D32: =SUM(D30:D31) -> 1 | I32: =SUM(I30:I31) -> 19800
A33: Employee Name | B33: School/Site Name | C33: Job Title | D33: Full-Time Equivalent | E33: Salary Step (if applicable) | F33: 10 Month 2018-19 Salary | G33: 2018-19 Benefits | H33: 12 Month 2019-20 Salary | I33: 10 Month 2019-20 Slary | J33: 2019-20 Benefits
A34: Family/Parent Liason
A35: ='[1]4c Family Worker'!$C$5&" "&'[1]4c Family Worker'!$B$5 -> Daphne L McMillian | B35: ='[1]4c Family Worker'!$A$5 -> Urban League | C35: Family Worker | D35: ='[1]4c Family Worker'!$G$5 -> 1 | E35: ='[1]4c Family Worker'!$F$5 -> 20 | F35: 21224 | H35: =I35/0.8163 -> 30075.952 | I35: 24551 | K35: ='[1]4c Family Worker'!N5 -> 1842
A36: ='[1]4c Family Worker'!$C$6&" "&'[1]4c Family Worker'!$B$6 -> #REF! | B36: ='[1]4c Family Worker'!$A$6 -> #REF! | C36: Family Worker | D36: ='[1]4c Family Worker'!$G$6 -> #REF! | E36: ='[1]4c Family Worker'!$F$6 -> #REF! | F36: ='[1]4c Family Worker'!$H$6 -> #REF! | H36: =I36/0.8163 -> #REF! | I36: =F36 -> #REF! | K36: ='[1]4c Family Worker'!N6 -> 0 | L36: =IF(D36>0,D36*H36," ") -> #REF!
L37: =IF(D37>0,D37*H37," ")
L38: =IF(D38>0,D38*H38," ")
D39: =SUM(D35:D38) -> #REF! | H39: =SUM(H35:H38) -> #REF!
A40: Program Directors | L40: =IF(D40>0,D40*H40," ")
A41: Heather Wilson | B41: Urban League | C41: Director | D41: 1 | E41: ='[1]Director Salary Scale'!B11 -> Tier 3* | F41: 57580 | H41: 57580 | I41: =H41*0.7673 -> 44181.134
D43: =SUM(D41:D42) -> 1 | H43: =SUM(H41:H42) -> 57580
A44: Food (Cook and Cook Assistant) Workers | L44: =IF(D44>0,D44*H44," ")
A45: Patricia Taylor | B45: Urban League | D45: 0.5 | E45: 0 | F45: 15000 | H45: =I45/0.7673 -> 19549.068 | I45: 15000 | L45: =IF(D45>0,D45*H45," ") -> 9774.5341
L46: =IF(D46>0,D46*H46," ")
L47: =IF(D47>0,D47*H47," ")
A48: Secretarial and Clerical Assistants | L48: =IF(D48>0,D48*H48," ")
B49: Urban League | C49: Clerical Assistant | D49: 0.5 | E49: 0 | F49: 18000 | H49: =I49/0.7673 -> 23458.882 | I49: 18000 | L49: =IF(D49>0,D49*H49," ") -> 11729.441
L50: =IF(D50>0,D50*H50," ")
L51: =IF(D51>0,D51*H51," ")
A52: Custodian | L52: =IF(D52>0,D52*H52," ")
B53: Urban League | C53: Custodian | D53: 0.5 | E53: 0 | F53: 22000 | H53: =I53/0.7673 -> 28671.967 | I53: 22000 | L53: =IF(D53>0,D53*H53," ") -> 14335.983
L55: =IF(D55>0,D55*H55," ")
L56: =IF(D56>0,D56*H56," ")
A57: Security Guard | L57: =IF(D57>0,D57*H57," ")
A58: Cora Andrews | B58: Urban League | C58: Security | D58: 1 | E58: 0 | F58: 19760 | H58: =I58/0.7673 -> 25752.639 | I58: 19760 | L58: =IF(D58>0,D58*H58," ") -> 25752.639
H59: =I59/0.7673 -> 0 | L59: =IF(D59>0,D59*H59," ")
L60: =IF(D60>0,D60*H60," ")
A61: Other Positions
H62: =I62/0.7673 -> 0
H63: =I63/0.7673 -> 0
H64: =I64/0.7673 -> 0
H65: =I65/0.7673 -> 0

Sheet Provider Planning Budget
A1: 2019-20 Private Provider One-Year Budget Planning Worksheet - NOT Approved
A4: Classrooms Serving Contracted Eligible Children: | E4: 3 | F4: District Name: | H4: ='[1]Schedule A Personnel'!B3 -> Newark
A5: Contracted Eligible Children: | E5: =E4*15 -> 45 | F5: Provider Name: | H5: ='[1]Schedule A Personnel'!F3 -> Urban League Of Essex County
A6: Other Students in Classrooms with Contracted Eligible Children: | F6: Program Type: | H6: Expanded Head Start (Fully State-Funded)
A7: All Other Classrooms: | E7: =E8/15 -> 0 | F7: Non-profit Status: | H7: Center/parent company is 501(c)(3) non-profit
A8: All Other Children: | F8: Facility Ownership: | H8: Site facilities owned by provider/parent company
F9: DCF License Number:
A11: District School Calendar Days: | E11: 188
A12: DOE Share of Annual Costs: | E12: =E11/245 -> 0.76734694
A14: Total Budget Amount | H14: =45*13660 -> 614700
A15: Expense | D15: FTE/ Quantity | E15: Unit Cost / Average Unit Cost | F15: DOE Share of Costs in Contracted Classrooms | H15: Total Cost
A17: EDUCATIONAL PROGRAM COSTS
A18: Teacher Salary | D18: =E4 -> 3 | E18: =AVERAGE('[1]Schedule A Personnel'!I20:I22) -> 56520.333 | F18: =E5/(E5+E6) -> 1 | H18: =+D18*E18*F18 -> 169561
A20: Teacher Assistant Salary | D20: =E4 -> 3 | E20: =AVERAGE('[1]4a Teacher Assistants'!H5:H7) -> 28945.333 | F20: =E5/(E5+E6) -> 1 | H20: =+D20*E20*F20 -> 86836
A21: Floating Teacher Assistant Salary | D21: ='[1]Schedule A Personnel'!D30 -> 1 | E21: ='[1]4b Floater Teacher Assistants'!H5 -> 19800 | F21: =E5/(E5+E6) -> 1 | H21: =+D21*E21*F21 -> 19800
A23: Teacher/Assistant Teacher Benefits | D23: =SUM(D18:D21) -> 7 | E23: 5514.25 | F23: =E5/(E5+E6) -> 1 | H23: =+D23*E23*F23 -> 38599.75
A25: Substitute Teacher Stipend | D25: =D18 -> 3 | E25: 1000 | F25: =E5/(E5+E6) -> 1 | H25: =+D25*E25*F25 -> 3000
A26: Substitute Assistant Teacher Stipend | D26: =D20+D21 -> 4 | E26: 1200 | F26: =E5/(E5+E6) -> 1 | H26: =+D26*E26*F26 -> 4800
A28: Classroom Materials and Supplies | D28: =E4 -> 3 | E28: 2000 | F28: =E5/(E5+E6) -> 1 | H28: =+D28*E28*F28 -> 6000
A29: Classroom Technology | D29: =E4 -> 3 | E29: 1000 | F29: =E5/(E5+E6) -> 1 | H29: =+D29*E29*F29 -> 3000
A30: Field Trips w/ Transportation | D30: =E5 -> 45 | E30: 100 | F30: 1 | H30: =+D30*E30*F30 -> 4500
A32: Family Worker Salary | D32: =E5/45 -> 1 | E32: ='[1]Schedule A Personnel'!H35 -> 30075.952 | F32: =200/245 -> 0.81632653 | H32: =+D32*E32*F32 -> 24551.798
A33: Family Worker Benefits | F33: 1 | H33: =+D33*E33*F33 -> 0
A35: Expense | D35: FTE/ Quantity | E35: Unit Cost / Average Unit Cost | F35: DOE Share of Annual Costs | G35: DOE Share of Center-Wide Costs | H35: Total Cost
A36: Food-Related Costs (CACFP participant, non-reimbursable costs)
A37: Food (for contracted preschool children only) | F37: 1 | H37: =E37*F37 -> 0
A38: Food Worker Salary (cook) | D38: 0.5 | E38: ='[1]Schedule A Personnel'!$H$45 -> 19549.068 | F38: =E12 -> 0.76734694 | G38: =E5/(E5+E6+E8) -> 1 | H38: =+D38*E38*F38*G38 -> 7500.4588
A39: Food Worker Benefits (cook) | F39: =E12 -> 0.76734694 | G39: =E5/(E5+E6+E8) -> 1 | H39: =+D39*E39*F39*G39 -> 0
A40: Assistant Food Worker Salary (asst. cook) | F40: =E12 -> 0.76734694 | G40: =E5/(E5+E6+E8) -> 1 | H40: =+D40*E40*F40*G40 -> 0
A41: Assistant Food Worker Benefits (asst. cook) | F41: =E12 -> 0.76734694 | G41: =E5/(E5+E6+E8) -> 1 | H41: =+D41*E41*F41*G41 -> 0
A43: Employer Payroll Taxes (For Educational Program Positions only)
A44: Social Security (6.20%) | H44: =(H18+H20+H21+H25+H26+H32+H38+H40)*0.062 -> 19595.054
A45: Medicare (1.45%) | H45: =(H18+H20+H21+H25+H26+H32+H38+H40)*0.0145 -> 4582.7142
A46: Unemployment (2.80%) | H46: =(H18+H20+H21+H25+H26+H32+H38+H40)*0.028 -> 8849.3792
A47: Disability (0.50%) | H47: =(H18+H20+H21+H25+H26+H32+H38+H40)*0.005 -> 1580.2463
A49: SUBTOTAL, Educational Program Costs | H49: =H47+H46+H45+H44+H41+H40+H39+H38+H37+H33+H32+H30+H29+H28+H26+H25+H23+H21+H20+H18 -> 402756.4
A50: Expense | D50: FTE | E50: Total Cost | F50: DOE Share of Annual Costs | G50: DOE Share of Center-Wide Costs | H50: Total Cost
A52: ADMINISTRATIVE SUPPORT AND INDIRECT COSTS
A53: SUPPORT COSTS
A54: Director Salary | D54: 1 | E54: 57580 | F54: =E$12 -> 0.76734694 | G54: =E5/(E5+E6+E8) -> 1 | H54: =D54*E54*F54*G54 -> 44183.837
A55: Director Benefits | D55: 1 | E55: 10560 | F55: =E$12 -> 0.76734694 | G55: =E5/(E5+E6+E8) -> 1 | H55: =D55*E55*F55*G55 -> 8103.1837
A56: Clerical Salary | D56: 0.5 | E56: 10000 | F56: =E$12 -> 0.76734694 | G56: =E5/(E5+E6+E8) -> 1 | H56: =D56*E56*F56*G56 -> 3836.7347
A57: Clerical Benefits | D57: 0.5 | E57: 0 | F57: =E$12 -> 0.76734694 | G57: =E5/(E5+E6+E8) -> 1 | H57: =D57*E57*F57*G57 -> 0
A58: Custodian Salary | D58: 0.5 | E58: 22000 | F58: =E$12 -> 0.76734694 | G58: =E5/(E5+E6+E8) -> 1 | H58: =D58*E58*F58*G58 -> 8440.8163
A59: Custodian Benefits | F59: =E$12 -> 0.76734694 | G59: =E5/(E5+E6+E8) -> 1 | H59: =D59*E59*F59*G59 -> 0
A60: Security Guard Salary | D60: 1 | E60: 20000 | F60: =E$12 -> 0.76734694 | G60: =E5/(E5+E6+E8) -> 1 | H60: =D60*E60*F60*G60 -> 15346.939
A61: Security Guard Benefits | F61: =E12 -> 0.76734694 | G61: =E5/(E5+E6+E8) -> 1 | H61: =D61*E61*F61*G61 -> 0
A62: Social Security (6.20%) | H62: =(H56+H58+H54+H60)*0.062 -> 4452.1162
A63: Medicare (1.45%) | H63: =(H56+H58+H54+H60)*0.0145 -> 1041.2207
A64: Unemployment (2.80%) | H64: =(H56+H58+H54+H60)*0.028 -> 2010.6331
A65: Disability (0.50%) | H65: =(H56+H58+H54+H60)*0.005 -> 359.04163
A67: Expense | E67: Total Cost | F67: DOE Share of Annual Costs | G67: DOE Share of Center-Wide Costs | H67: Total Cost
A68: INDIRECT COSTS -- SPACE COSTS
A69: Rent, Mortgage, Other Space Costs | E69: 118748 | F69: =E$12 -> 0.76734694 | G69: =E5/(E5+E6+E8) -> 1 | H69: =E69*F69*G69 -> 91120.914
A71: Expense | E71: Total Cost | F71: DOE Share of Annual Costs | G71: DOE Share of Center-Wide Costs | H71: Total Cost
A72: INDIRECT COSTS -- ALL OTHER ALLOWABLE INDIRECT
A73: Office Equipment>$2000 and Repair | E73: 4000 | F73: =E$12 -> 0.76734694 | G73: =E5/(E5+E6+E8) -> 1 | H73: =E73*F73*G73 -> 3069.3878
A74: Office Materials and Supplies | E74: 3000 | F74: =E$12 -> 0.76734694 | G74: =E5/(E5+E6+E8) -> 1 | H74: =E74*F74*G74 -> 2302.0408
A75: Food-Related Paper Supplies | E75: 1000 | F75: =E$12 -> 0.76734694 | G75: =E5/(E5+E6+E8) -> 1 | H75: =E75*F75*G75 -> 767.34694
A76: Cleaning Supplies | E76: 1000 | F76: =E$12 -> 0.76734694 | G76: =E5/(E5+E6+E8) -> 1 | H76: =E76*F76*G76 -> 767.34694
A77: Food for Meetings | E77: 500 | F77: =E$12 -> 0.76734694 | G77: =E5/(E5+E6+E8) -> 1 | H77: =E77*F77*G77 -> 383.67347
A78: Building/Grounds Maintenance/Repair | E78: 5000 | F78: =E$12 -> 0.76734694 | G78: =E5/(E5+E6+E8) -> 1 | H78: =E78*F78*G78 -> 3836.7347
A79: Utilities | E79: 10000 | F79: =E$12 -> 0.76734694 | G79: =E5/(E5+E6+E8) -> 1 | H79: =E79*F79*G79 -> 7673.4694
A80: Telecommunications Services | E80: 2200 | F80: =E$12 -> 0.76734694 | G80: =E5/(E5+E6+E8) -> 1 | H80: =E80*F80*G80 -> 1688.1633
A81: Security | E81: 400 | F81: =E$12 -> 0.76734694 | G81: =E5/(E5+E6+E8) -> 1 | H81: =E81*F81*G81 -> 306.93878
A82: Insurance | E82: 6000 | F82: =E$12 -> 0.76734694 | G82: =E5/(E5+E6+E8) -> 1 | H82: =E82*F82*G82 -> 4604.0816
A83: Accounting Fees | E83: 7000 | F83: =E$12 -> 0.76734694 | G83: =E5/(E5+E6+E8) -> 1 | H83: =E83*F83*G83 -> 5371.4286
A84: Payroll Preparation Fees | E84: 2000 | F84: =E$12 -> 0.76734694 | G84: =E5/(E5+E6+E8) -> 1 | H84: =E84*F84*G84 -> 1534.6939
A85: Advertising | E85: 500 | F85: =E$12 -> 0.76734694 | G85: =E5/(E5+E6+E8) -> 1 | H85: =E85*F85*G85 -> 383.67347
A86: Staff Transportation | E86: 490 | F86: =E$12 -> 0.76734694 | G86: =E5/(E5+E6+E8) -> 1 | H86: =E86*F86*G86 -> 376
A87: Profit, if Applicable (Max of 2.5% of Ed Costs) | F87: 1 | G87: 1 | H87: =E87*F87*G87 -> 0
A88: Subtotal of Above Administrative Support and Indirect Costs | H88: =SUM(H73:I87)+SUM(H54:I65)+H69 -> 211960.42
A90: Other Approved Budgeted Costs
A91: (Insert item name or brief description on this line.) | G91: =$E$12 -> 0.76734694 | H91: =$E$5/($E$5+$E$6+$E$8) -> 1 | I91: =F91*G91*H91 -> 0
A92: (Insert item name or brief description on this line.) | G92: =$E$12 -> 0.76734694 | H92: =$E$5/($E$5+$E$6+$E$8) -> 1 | I92: =F92*G92*H92 -> 0
A93: (Insert item name or brief description on this line.) | G93: =$E$12 -> 0.76734694 | H93: =$E$5/($E$5+$E$6+$E$8) -> 1 | I93: =F93*G93*H93 -> 0
A94: (Insert item name or brief description on this line.) | G94: =$E$12 -> 0.76734694 | H94: =$E$5/($E$5+$E$6+$E$8) -> 1 | I94: =F94*G94*H94 -> 0
A95: (Insert item name or brief description on this line.) | G95: =$E$12 -> 0.76734694 | H95: =$E$5/($E$5+$E$6+$E$8) -> 1 | I95: =F95*G95*H95 -> 0
A96: SUBTOTAL, Other Approved Budgeted Costs | I96: =SUM(I91:I95) -> 0
A98: PROVIDER PROGRAM TOTALS
A99: Total Cost | I99: =H49+H88+I96 -> 614716.82
A100: Per-Pupil Cost | I100: =I99/E5 -> 13660.374
A101: =IF(I99>I101,"UNBALANCED BUDGET MUST REDUCE BUDGET-PROVIDER PROGRAM TOTALS"," ") | H101: =IF(I99>I101,I101-I99,0) -> 0 | I101: 614717
A102: DISTRICT ADJUSTMENTS (amounts withheld for items to be purchased by the district) FOR DISTRICT USE ONLY
A103: =A28 -> Classroom Materials and Supplies | I103: =-H28 -> -6000
A104: =A29 -> Classroom Technology | I104: =-H29 -> -3000
A105: Benefits | H105: =I105/3 -> -15567.645 | I105: =-H23-H33-H39-H41-H55-H57-H59-H61 -> -46702.934
A106: Salary Increase | I106: =SUM('[1]Schedule A Personnel'!K20:K39) -> #REF!
A107: Salary Increase Payroll Taxes | I107: =I106*0.15 -> #REF!
A108: Total Cost Less District Adjustments | I108: =I99+SUM(I103:I107) -> #REF!
A109: Per-Pupil Cost Less District Adjustments | I109: =I108/E5 -> #REF!
J112: Site facilities owned by provider/parent company
J113: Site facilities leased from unrelated party
J114: Site facilities leased from related party
J115: Other Private Provider
J116: Enhanced Head Start (State and Federally Funded)
J117: Expanded Head Start (Fully State-Funded)
J118: Center/parent company is 501(c)(3) non-profit
J119: Center/parent company is other non-profit
J120: Center/parent company is for-profit

Sheet Monthly Enrollment Tracker
A1: Contracted Slots by Location | B1: 45
A2: Month | B2: Holiness
A3: September
A4: October
A5: November
A6: December
A7: January
A8: February
A9: March
A10: April
A11: May
A12: June
A14: Sub Total | B14: =SUM(B3:B12) -> 0 | C14: =SUM(C3:C12) -> 0 | D14: =SUM(D3:D12) -> 0 | E14: =SUM(E3:E12) -> 0 | F14: =SUM(F3:F12) -> 0 | G14: =SUM(G3:G12) -> 0 | H14: =SUM(H3:H12) -> 0 | I14: =SUM(I3:I12) -> 0 | ... L14: =SUM(L3:L12) -> 0 | M14: =SUM(B14:L14) -> 0
