Workbook

Sheet Qrt 3 2019
B1: Urban League of Essex County
B2: Neighborhood Revitalization Tax Credit Project 2019 (NRTC)
B3: Grant # 2019-02240-0483-00
B4: October- December 2019
C6: Previous Quarter | E6: Current QTR | G6: Cummulated Expense | I6: Budgeted | K6: Remain
A8: Line # | B8: Personnel: Administration
A9: 1 | B9: Admin - Personnel - Finance | C9: 6346.13 | E9: 2961.15 | G9: =C9+E9 -> 9307.28 | I9: 10000 | K9: =+I9-G9 -> 692.72 | M9: =G9/I9 -> 0.930728
B10: Admin - Fringes- Finance @15% | C10: 951.92 | E10: =E9*0.15 -> 444.1725 | G10: =C10+E10 -> 1396.0925 | I10: 2500 | K10: =+I10-G10 -> 1103.9075 | M10: =G10/I10 -> 0.558437
A11: 2 | B11: Program - Personnel - Tech Staff -D Sharif | G11: =C11+E11 -> 0 | I11: 23398.75 | K11: =+I11-G11 -> 23398.75 | M11: =G11/I11 -> 0
B12: Program - Fringes @ 15% | G12: =C12+E12 -> 0 | I12: 5312.5 | K12: =+I12-G12 -> 5312.5 | M12: =G12/I12 -> 0
B13: Sub-Total | C13: =SUM(C9:C12) -> 7298.05 | E13: =SUM(E9:E12) -> 3405.3225 | G13: =SUM(G9:G12) -> 10703.373 | I13: =SUM(I9:I12) -> 41211.25 | K13: =SUM(K9:K12) -> 30507.877
B15: Economic Development- Tech House
A16: 3 | B16: Admin - Computer Equip | G16: =C16+E16 -> 0 | I16: 28298.75 | K16: =+I16-G16 -> 28298.75
A17: 4 | B17: Program - Pre- Development Loan | C17: 111026 | E17: 0 | G17: =C17+E17 -> 111026 | I17: 111026 | K17: =+I17-G17 -> 0
B18: Program - Taxes, Insurance and Utilities | C18: 8220.1 | E18: 610.4 | G18: =C18+E18 -> 8830.5 | I18: 10700 | K18: =+I18-G18 -> 1869.5
A19: 5 | B19: Program - Exterior Renovations | C19: 7792.5 | E19: 13000.22 | G19: =C19+E19 -> 20792.72 | I19: 58764 | K19: =+I19-G19 -> 37971.28
B20: Sub-Total | C20: =SUM(C16:C19) -> 127038.6 | E20: =SUM(E16:E19) -> 13610.62 | G20: =SUM(G16:G19) -> 140649.22 | I20: =SUM(I16:I19) -> 208788.75 | K20: =SUM(K16:K19) -> 68139.53
B24: Grant Total | C24: =C13+C20 -> 134336.65 | E24: =E13+E20 -> 17015.942 | G24: =G13+G20 -> 151352.59 | I24: =I13+I20 -> 250000 | K24: =K13+K20 -> 98647.408
C26: FSR #3 | E26: Paid

Sheet PL Qrt 3 2019
A1: URBAN LEAGUE OF ESSEX COUNTY
A2: General Ledger- 335 NRTC 2019
A3: October - December, 2019
B5: Date | C5: Transaction Type | D5: Num | E5: Name | F5: Memo/Description | G5: Class | H5: Debit | I5: check Info
A6: 7200 Salaries & Related Expenses
A7: 7220 Salaries & Wages
B8: Beginning Balance
B9: 10/31/2019 | C9: Journal Entry | D9: 19-437 | F9: Salary Allocation - October | G9: 335 NRTC 19 | H9: 846.15
B10: 11/30/2019 | C10: Journal Entry | D10: 39 | F10: Salary Allocation - November | G10: 335 NRTC 19 | H10: 1269
B11: 12/31/2019 | C11: Journal Entry | D11: 121 | F11: Salary Allocation - December | G11: 335 NRTC 19 | H11: 846
A12: Total for 7220 Salaries & Wages | H12: 2961.15
A13: 8600 Housing Development
A14: 8602 Rehab of Existing Facility
B15: Beginning Balance
B16: 11/22/2019 | C16: Bill | D16: 2 | E16: Mark Tirondola Painting Contractor Inc | F16: 2nd Payment for Facade Improvements 152 Littleton Ave | G16: 335 NRTC 19 | H16: 6000.22
B17: 12/18/2019 | C17: Bill | D17: 3 | E17: Mark Tirondola Painting Contractor Inc | F17: 3rd Payment for Facade Improvements 152 Littleton Ave | G17: 335 NRTC 19 | H17: 7000
A18: Total for 8602 Rehab of Existing Facility | H18: 13000.22
A19: 8605 Holding Cost
A20: 8606 Property Taxes
B21: Beginning Balance
A22: Total for 8606 Property Taxes
A23: 8606.1 Property Insurance
B24: Beginning Balance
A25: Total for 8606.1 Property Insurance
A26: 8606.3 Utilities
B27: Beginning Balance
B28: 10/17/2019 | C28: Bill | D28: 11480180 | E28: City of Newark/Water | F28: Holding Costs: Water 152 Littleton Ave. Oct 2019 | G28: 335 NRTC 19 | H28: 78.12
B29: 11/15/2019 | C29: Bill | D29: 600506294993 | E29: PSE&G | F29: 152 Littleton Ave. Acct # 73 766 329 05 Utilities 10/16/19 - 11/13/19 | G29: 335 NRTC 19 | H29: 58.98
B30: 11/19/2019 | C30: Bill | D30: 11517227 | E30: City of Newark/Water | F30: Holding Costs: Water 152 Littleton Ave. Nov 2019 | G30: 335 NRTC 19 | H30: 78.12
B31: 12/16/2019 | C31: Bill | D31: 11557357 | E31: City of Newark/Water | F31: Holding Costs: Water 152 Littleton Ave. Dec 2019 | G31: 335 NRTC 19 | H31: 78.12
B32: 12/18/2019 | C32: Bill | D32: 600306373110 | E32: PSE&G | F32: 152 Littleton Ave. Acct # 73 766 329 05 Utilities 11/14/19 - 12/16/19 | G32: 335 NRTC 19 | H32: 317.06
A33: Total for 8606.3 Utilities | H33: 610.4
A34: 8606.6 Water
B35: Beginning Balance
A36: Total for 8606.6 Water
A37: Total for 8605 Holding Cost | H37: 610.4
A38: Total for 8600 Housing Development | H38: 13610.62
A41: Tuesday, Jan 14, 2020 10:33:13 AM GMT-8

Sheet Qrt 4 2019
B1: Urban League of Essex County
B2: Neighborhood Revitalization Tax Credit Project 2019 (NRTC)
B3: Grant # 2019-02240-0483-00
B4: October- December 2019
C6: Previous Quarter | E6: Current QTR | G6: Cummulated Expense | I6: Budgeted | K6: Remain
A8: Line # | B8: Personnel: Administration
A9: 1 | B9: Admin - Personnel - Finance | C9: ='Qrt 3 2019'!E9 -> 2961.15 | G9: =E9+'Qrt 3 2019'!G9 -> 9307.28 | I9: 10000 | K9: =+I9-G9 -> 692.72 | M9: =G9/I9 -> 0.930728
B10: Admin - Fringes- Finance @15% | C10: ='Qrt 3 2019'!E10 -> 444.1725 | E10: 0 | G10: =E10+'Qrt 3 2019'!G10 -> 1396.0925 | I10: 2500 | K10: =+I10-G10 -> 1103.9075 | M10: =G10/I10 -> 0.558437
A11: 2 | B11: Program - Personnel - Tech Staff -D Sharif | C11: ='Qrt 3 2019'!E11 -> 0 | G11: =E11+'Qrt 3 2019'!G11 -> 0 | I11: 23398.75 | K11: =+I11-G11 -> 23398.75 | M11: =G11/I11 -> 0
B12: Program - Fringes @ 15% | C12: ='Qrt 3 2019'!E12 -> 0 | E12: 0 | G12: =E12+'Qrt 3 2019'!G12 -> 0 | I12: 5312.5 | K12: =+I12-G12 -> 5312.5 | M12: =G12/I12 -> 0
B13: Sub-Total | C13: =SUM(C9:C12) -> 3405.3225 | E13: =SUM(E9:E12) -> 0 | G13: =SUM(G9:G12) -> 10703.373 | I13: =SUM(I9:I12) -> 41211.25 | K13: =SUM(K9:K12) -> 30507.877
B15: Economic Development- Tech House
A16: 3 | B16: Admin - Computer Equip | C16: ='Qrt 3 2019'!E16 -> 0 | E16: 0 | G16: =E16+'Qrt 3 2019'!G16 -> 0 | I16: 28298.75 | K16: =+I16-G16 -> 28298.75
A17: 4 | B17: Program - Pre- Development Loan | C17: ='Qrt 3 2019'!E17 -> 0 | E17: 0 | G17: =E17+'Qrt 3 2019'!G17 -> 111026 | I17: 111026 | K17: =+I17-G17 -> 0
B18: Program - Taxes, Insurance and Utilities | C18: ='Qrt 3 2019'!E18 -> 610.4 | E18: 0 | G18: =E18+'Qrt 3 2019'!G18 -> 8830.5 | I18: 10700 | K18: =+I18-G18 -> 1869.5
A19: 5 | B19: Program - Exterior Renovations | C19: ='Qrt 3 2019'!E19 -> 13000.22 | E19: 0 | G19: =E19+'Qrt 3 2019'!G19 -> 20792.72 | I19: 58764 | K19: =+I19-G19 -> 37971.28
B20: Sub-Total | C20: =SUM(C16:C19) -> 13610.62 | E20: =SUM(E16:E19) -> 0 | G20: =SUM(G16:G19) -> 140649.22 | I20: =SUM(I16:I19) -> 208788.75 | K20: =SUM(K16:K19) -> 68139.53
B24: Grant Total | C24: =C13+C20 -> 17015.942 | E24: =E13+E20 -> 0 | G24: =G13+G20 -> 151352.59 | I24: =I13+I20 -> 250000 | K24: =K13+K20 -> 98647.408
C26: FSR #3 | E26: Paid

Sheet PL Qrt 4 2019
A1: URBAN LEAGUE OF ESSEX COUNTY
A2: Profit and Loss Detail
A3: October - December, 2019
B5: Date | C5: Transaction Type | D5: Num | E5: Name | F5: Location | G5: Class | H5: Memo/Description | I5: Split | J5: Amount | K5: Balance
A6: Ordinary Income/Expenses
A7: Income
A8: 4500 Revenue from Government Grants
A9: 4530 State Grants
B10: 10/24/2019 | C10: Invoice | D10: 201937 | E10: Grants/Contracts:NRTC:State of NJ NRTC - 2018 | G10: 334 NRTC 2018 Grant | H10: To record receivable from January 2018 - Sept Invoice 2018 | I10: 1100 Accounts/ Contributions Receivable | J10: 165000 | K10: 165000
A11: Total for 4530 State Grants | J11: 165000
A12: Total for 4500 Revenue from Government Grants | J12: 165000
A13: Total for Income | J13: 165000
A14: Expenses
A15: 7200 Salaries & Related Expenses
A16: 7240 Employee Benefits
A17: 7244 Employee Contrib - Health
B18: 10/31/2019 | C18: Journal Entry | D18: 63 | G18: 334 NRTC 2018 Grant | H18: Employee Medical Contrib | I18: -Split- | J18: -47.04 | K18: -47.04
B19: 11/30/2019 | C19: Journal Entry | D19: 64 | G19: 334 NRTC 2018 Grant | H19: Employee Medical Contrib | I19: -Split- | J19: -57.54 | K19: -104.58
B20: 12/31/2019 | C20: Journal Entry | D20: 137 | G20: 334 NRTC 2018 Grant | H20: Employee Medical Contrib | I20: -Split- | J20: -56 | K20: -160.58
A21: Total for 7244 Employee Contrib - Health | J21: -160.58
A22: 7247 Emp-ee Contrib -Dental
B23: 10/31/2019 | C23: Journal Entry | D23: 65 | G23: 334 NRTC 2018 Grant | H23: Employee Dental Contrib | I23: -Split- | J23: -5.72 | K23: -5.72
B24: 11/30/2019 | C24: Journal Entry | D24: 66 | G24: 334 NRTC 2018 Grant | H24: Employee Dental Contrib | I24: -Split- | J24: -11.91 | K24: -17.63
B25: 12/31/2019 | C25: Journal Entry | D25: 138 | G25: 334 NRTC 2018 Grant | H25: Employee Dental Contrib | I25: -Split- | J25: -8 | K25: -25.63
A26: Total for 7247 Emp-ee Contrib -Dental | J26: -25.63
A27: Total for 7240 Employee Benefits | J27: -186.21
A28: Total for 7200 Salaries & Related Expenses | J28: -186.21
A29: 7500 Contract Service Expenses
A30: 7560 Professional fees - other
B31: 11/25/2019 | C31: Expense | G31: 334 NRTC 2018 Grant | H31: AIA PRODUCTS / DUES | I31: 2150 Credit Cards:Visa Card-8978 | J31: 32.99 | K31: 32.99
B32: 11/25/2019 | C32: Expense | G32: 334 NRTC 2018 Grant | H32: AIA PRODUCTS / DUES | I32: 2150 Credit Cards:Visa Card-8978 | J32: 32.99 | K32: 65.98
B33: 11/25/2019 | C33: Expense | G33: 334 NRTC 2018 Grant | H33: AIA PRODUCTS / DUES | I33: 2150 Credit Cards:Visa Card-8978 | J33: 32.99 | K33: 98.97
A34: Total for 7560 Professional fees - other | J34: 98.97
A35: Total for 7500 Contract Service Expenses | J35: 98.97
A36: 8500 Other Expenses
A37: 8580 Licenses & Fees
B38: 10/10/2019 | C38: Bill | D38: 2019132030481 | E38: Passaic Valley Sewerage Commission | F38: 05 NRTC 18:231 Fairmount Ave1 | G38: 334 NRTC 2018 Grant | H38: Construction Costs: Sewer Application Fees/Permit 231 Fairmount Ave | I38: 2000 Accounts Payable | J38: 994.75 | K38: 994.75
A39: Total for 8580 Licenses & Fees | J39: 994.75
A40: Total for 8500 Other Expenses | J40: 994.75
A41: 8600 Housing Development
A42: 8605 Holding Cost
A43: 8606 Property Taxes
B44: 11/01/2019 | C44: Bill | D44: 103962_2019Q4 | E44: City of Newark. | F44: 05 NRTC 18:231 Fairmount Ave | G44: 334 NRTC 2018 Grant | H44: 231 Fairmount Ave - 2019 Q4 R.E Taxes | I44: 2000 Accounts Payable | J44: 1629.48 | K44: 1629.48
A45: Total for 8606 Property Taxes | J45: 1629.48
A46: 8606.1 Property Insurance
B47: 10/10/2019 | C47: Bill | D47: CP 164 3606B | E47: Massey Insurance Agency | F47: 05 NRTC 18:204 S. 6th St | G47: 334 NRTC 2018 Grant | H47: Property & Liability Insurance - 6 mos Premium October 2019 - July 2020 - 204 South 6th Street | I47: 2000 Accounts Payable | J47: 1660.46 | K47: 1660.46
A48: Total for 8606.1 Property Insurance | J48: 1660.46
A49: 8606.2 Repairs
B50: 10/09/2019 | C50: Bill | D50: 10.09.19PP | E50: Petty Cash | G50: 334 NRTC 2018 Grant | H50: Cleanup Lots on Fairmount Ave. | I50: 2000 Accounts Payable | J50: 80 | K50: 80
A51: Total for 8606.2 Repairs | J51: 80
A52: 8606.3 Utilities
B53: 10/10/2019 | C53: Bill | D53: 11441444 | E53: City of Newark/Water | F53: 05 NRTC 18:231 Fairmount Ave | G53: 334 NRTC 2018 Grant | H53: Water Expense 231 Fairmount Ave. Sept 2019 | I53: 2000 Accounts Payable | J53: 39.26 | K53: 39.26
B54: 11/06/2019 | C54: Bill | D54: 11480383 | E54: City of Newark/Water | F54: 05 NRTC 18:231 Fairmount Ave | G54: 334 NRTC 2018 Grant | H54: Water Expense 231 Fairmount Ave. Oct 2019 | I54: 2000 Accounts Payable | J54: 38.68 | K54: 77.94
B55: 11/06/2019 | C55: Bill | D55: 603805565118 | E55: PSE&G | F55: 05 NRTC 18:204 S. 6th St | G55: 334 NRTC 2018 Grant | H55: Electric Charges - 204 S. 6th St - 09/17/19 - 10/15/19 | I55: 2000 Accounts Payable | J55: 15.94 | K55: 93.88
B56: 11/06/2019 | C56: Bill | D56: 600906220639 | E56: PSE&G | F56: 05 NRTC 18:231 Fairmount Ave1 | G56: 334 NRTC 2018 Grant | H56: Acct #73 484 776 07 231 Fairmount Ave 09/17/19 - 10/17/19 | I56: 2000 Accounts Payable | J56: 16.33 | K56: 110.21
B57: 12/05/2019 | C57: Bill | D57: 11517434 | E57: City of Newark/Water | F57: 05 NRTC 18:231 Fairmount Ave | G57: 334 NRTC 2018 Grant | H57: Water Expense 231 Fairmount Ave. Nov 2019 | I57: 2000 Accounts Payable | J57: 38.68 | K57: 148.89
B58: 12/05/2019 | C58: Bill | D58: 605105022972 | E58: PSE&G | F58: 05 NRTC 18:231 Fairmount Ave1 | G58: 334 NRTC 2018 Grant | H58: Acct #73 484 776 07 231 Fairmount Ave 10/16/19 - 11/13/19 | I58: 2000 Accounts Payable | J58: 21.11 | K58: 170
B59: 12/05/2019 | C59: Bill | D59: 11514530 | E59: City of Newark/Water | F59: 04 ULEC Projects:479 So 14th St | G59: 334 NRTC 2018 Grant | H59: Water Expense 479 S 14th St. Nov 2019 | I59: 2000 Accounts Payable | J59: 38.68 | K59: 208.68
B60: 12/05/2019 | C60: Bill | D60: 603006591409 | E60: PSE&G | F60: 05 NRTC 18:204 S. 6th St | G60: 334 NRTC 2018 Grant | H60: Electric Charges - 204 S. 6th St - 10/16/19 - 11/13/19 | I60: 2000 Accounts Payable | J60: 7.31 | K60: 215.99
A61: Total for 8606.3 Utilities | J61: 215.99
A62: 8606.4 Interest Exp
B63: 10/01/2019 | C63: Bill | D63: 10.01.19_231 | E63: Local Initiatives Support Corp. | F63: 05 NRTC 18:231 Fairmount Ave1 | G63: 334 NRTC 2018 Grant | H63: Construction Loan Interest Oct 2019 231 Fairmount Ave | I63: 2000 Accounts Payable | J63: 10.41 | K63: 10.41
B64: 10/01/2019 | C64: Bill | D64: 10.01.19_204 | E64: Local Initiatives Support Corp. | F64: 05 NRTC 18:204 S. 6th St | G64: 334 NRTC 2018 Grant | H64: Construction Loan Interest Oct 2019 204 S 6th Street | I64: 2000 Accounts Payable | J64: 10.41 | K64: 20.82
B65: 10/31/2019 | C65: Journal Entry | D65: 19-113 | F65: 06 NRTC 16:513 Central Ave | G65: 334 NRTC 2018 Grant | H65: To reconcile balance to statement | I65: -Split- | J65: 12466.42 | K65: 12487.24
B66: 11/01/2019 | C66: Bill | D66: 11.01.19_13410 | E66: Local Initiatives Support Corp. | F66: 05 NRTC 18:231 Fairmount Ave1 | G66: 334 NRTC 2018 Grant | H66: Construction Loan Interest 231 Fairmount Ave | I66: 2000 Accounts Payable | J66: 10.41 | K66: 12497.65
B67: 11/01/2019 | C67: Bill | D67: 11.01.19_13411 | E67: Local Initiatives Support Corp. | F67: 05 NRTC 18:204 S. 6th St | G67: 334 NRTC 2018 Grant | H67: Construction Loan Interest 204 S 6th Street | I67: 2000 Accounts Payable | J67: 10.41 | K67: 12508.06
A68: Total for 8606.4 Interest Exp | J68: 12508.06
A69: 8606.6 Water
B70: 10/10/2019 | C70: Bill | D70: 11441076 | E70: City of Newark/Water | F70: 05 NRTC 18:204 S. 6th St | G70: 334 NRTC 2018 Grant | H70: City of Newark Water: 204 S 6th Street Sept 2019 | I70: 2000 Accounts Payable | J70: 36.26 | K70: 36.26
B71: 11/06/2019 | C71: Bill | D71: 11480014 | E71: City of Newark/Water | F71: 05 NRTC 18:204 S. 6th St | G71: 334 NRTC 2018 Grant | H71: City of Newark Water: 204 S 6th St Oct 2019 | I71: 2000 Accounts Payable | J71: 41.73 | K71: 77.99
B72: 12/05/2019 | C72: Bill | D72: 11517051 | E72: City of Newark/Water | F72: 05 NRTC 18:204 S. 6th St | G72: 334 NRTC 2018 Grant | H72: City of Newark Water: 204 S 6th St Nov 2019 | I72: 2000 Accounts Payable | J72: 38.68 | K72: 116.67
A73: Total for 8606.6 Water | J73: 116.67
A74: Total for 8605 Holding Cost | J74: 16210.66
A75: Total for 8600 Housing Development | J75: 16210.66
A76: Total for Expenses | J76: 17118.17
A77: Net Income | J77: 147881.83
A80: Sunday, Feb 16, 2020 09:57:49 AM GMT-8 - Cash Basis
