Workbook

Sheet Allocations
B1: Urban League of Essex County 2019 Code 0297 | E1: 041 Social Enter Thriftworks | F1: 111 Abbott | G1: 111B Wrap Fees | H1: 111A Other | I1: 111F Food Prog | J1: 112 EHS/Toddler | K1: EHS 112 A Fees | L1: 114 Summer Camp | M1: 222 DCF Coding | N1: 223 OICA June 30 | O1: 225 Americorp | P1: 334 NRTC 18 40K | Q1: 335 NRTC 19 40K | R1: 339 ULEC OC | S1: 368 Wells Fargo 165K | T1: 451 SENIORS / USJP | U1: 452 PACE $211K | V1: 460 Ihop Training $34k | W1: 468 Nwk Alliance $95K | X1: 467 United Airlines 125K Business Dev | Y1: 502 ESG Housing $75 Salaries $18750 | Z1: 454 Prudential #1 18-19 Workforce | AA1: 515 NUL -HUD 2018 PARS $27.5k salaries | AB1: 525 CDBG -Irvington -Housing $19K | AC1: 560Capital 1 Save Up FOC $15K- $4k Salary KJ | AD1: 561 LISC FOC $50K | AE1: 567 Chase FOC Wksp 3K- Delete | AF1: 563 -Prudential #1 18-19 FOC | AG1: 600Admin | AH1: 610 CEO Victoria Fdn | AI1: 620 CFO | AJ1: 630 COO | AK1: 640 Development | AL1: 650 Facilities | AM1: Proof
C2: K Period | E2: % | F2: % | I2: % | J2: % | L2: % | M2: % | N2: % | O2: % | P2: % | Q2: % | S2: % | T2: % | X2: % | Y2: % | Z2: 90000 | AA2: % | AC2: % | AF2: 45000 | AH2: % | AI2: % | AJ2: % | AK2: % | AL2: %
D3: Contract | AA3: 09/30/19
D4: Percentage
E5: 1 | F5: 2 | G5: 3 | H5: 4 | I5: 5 | J5: 6 | K5: 7 | L5: 8 | M5: 9 | N5: 10 | O5: 11 | P5: 12 | Q5: 13 | R5: 14 | S5: 15 | T5: 16 | U5: 17 | V5: 18 | W5: 19 | X5: 20 | Y5: 21 | Z5: 22 | AA5: 23 | AB5: 24 | AC5: 25 | AD5: 26 | AE5: 27 | AF5: 28 | AG5: 29 | AH5: 30 | AI5: 31 | AJ5: 32 | AK5: 33 | AL5: 34
B6: 12 Month Projections | C6: PAYCOM DEPT.
A7: 1 | B7: AIKEN-SANZONE, Charlene | C7: Americorp | O7: 1 | AM7: =SUM(F7:AL7) -> 1 | AO7: =B7 -> AIKEN-SANZONE, Charlene
A8: 2 | B8: AIKEN-SANZONE, Charlene June 30 | C8: OICA | N8: 1 | AM8: =SUM(F8:AL8) -> 1 | AO8: =B8 -> AIKEN-SANZONE, Charlene June 30
A9: 3 | B9: ALFORD, Sebrania R. | C9: Abbott | F9: 0.65 | J9: 0.35 | AM9: =SUM(F9:AL9) -> 1 | AO9: =B9 -> ALFORD, Sebrania R.
A10: 4 | B10: ALMANZAR, Alberto | C10: USJP | T10: 1 | AM10: =SUM(F10:AL10) -> 1 | AO10: =B10 -> ALMANZAR, Alberto
A11: 5 | B11: ANDREWS, Cora - Summer | C11: Abbott | F11: 0.5 | L11: 0.5 | AM11: =SUM(F11:AL11) -> 1 | AO11: =B11 -> ANDREWS, Cora - Summer
A12: 6 | B12: ANDREWS, Cora | C12: Abbott | F12: 0.77 | J12: 0.23 | AM12: =SUM(F12:AL12) -> 1 | AO12: =B12 -> ANDREWS, Cora
A13: 7 | B13: ANDREWS, Courtney A. | C13: Americorp | O13: 1 | AM13: =SUM(F13:AL13) -> 1 | AO13: =B13 -> ANDREWS, Courtney A.
A14: 8 | B14: BIRDSONG, Rhonda June 30 | C14: OICA | N14: 1 | AM14: =SUM(F14:AL14) -> 1 | AO14: =B14 -> BIRDSONG, Rhonda June 30
A15: 9 | B15: Bizi, Raymond | C15: Americorp | O15: 1 | AM15: =SUM(F15:AL15) -> 1 | AO15: =B15 -> Bizi, Raymond
A16: 10 | B16: BROWN,Denise- Wrap | C16: Abbott | F16: 0 | G16: 1 | AM16: =SUM(F16:AL16) -> 1 | AO16: =B16 -> BROWN,Denise- Wrap
A17: 11 | B17: BROWN,Denise - Summer | C17: Abbott | L17: 1 | AM17: =SUM(F17:AL17) -> 1 | AO17: =B17 -> BROWN,Denise - Summer
A18: 12 | B18: BRYANT, Roni- Summer | C18: Abbott | F18: 0 | L18: 1 | AM18: =SUM(F18:AL18) -> 1 | AO18: =B18 -> BRYANT, Roni- Summer
A19: 13 | B19: BRYANT, Roni | C19: Abbott | F19: 1 | AM19: =SUM(F19:AL19) -> 1 | AO19: =B19 -> BRYANT, Roni
A20: 14 | B20: BUTLER, Ciji | C20: USJP | T20: 1 | AM20: =SUM(F20:AL20) -> 1 | AO20: =B20 -> BUTLER, Ciji
A21: 15 | B21: CAMPBELL, Nikiesha K. | C21: Americorp | O21: 1 | AM21: =SUM(F21:AL21) -> 1 | AO21: =B21 -> CAMPBELL, Nikiesha K.
A22: 16 | B22: CASTELLANOS, Rita J. | C22: Abbott | F22: 1 | AM22: =SUM(F22:AL22) -> 1 | AO22: =B22 -> CASTELLANOS, Rita J.
A23: 17 | B23: CERNA, Irene | C23: USJP | T23: 1 | AM23: =SUM(F23:AL23) -> 1 | AO23: =B23 -> CERNA, Irene
A24: 18 | B24: COLEMAN, Zabrina J. | C24: EHS | J24: 1 | AM24: =SUM(F24:AL24) -> 1 | AO24: =B24 -> COLEMAN, Zabrina J.
A25: 19 | B25: COOPER, Cassandra June 30 | C25: OICA | N25: 1 | AM25: =SUM(F25:AL25) -> 1 | AO25: =B25 -> COOPER, Cassandra June 30
A26: 20 | B26: COOPER, Cassandra July | C26: FOC, ESG | Y26: 0.25 | AF26: 0.75 | AM26: =SUM(F26:AL26) -> 1 | AO26: =B26 -> COOPER, Cassandra July
A27: 21 | B27: Counts, Monique Lamae | C27: Americorp | O27: 1 | AM27: =SUM(F27:AL27) -> 1 | AO27: =B27 -> Counts, Monique Lamae
A28: 22 | B28: DANCE-WILSON, Heather | C28: Abbott | F28: 0.77 | H28: 0.23 | J28: 0 | AM28: =SUM(F28:AL28) -> 1 | AO28: =B28 -> DANCE-WILSON, Heather
A29: 23 | B29: DANIELS-CRAFTON, Glenda | C29: EHS | J29: 1 | AM29: =SUM(F29:AL29) -> 1 | AO29: =B29 -> DANIELS-CRAFTON, Glenda
A30: 24 | B30: ELLIS, Joseph | C30: OICA | N30: 1 | AM30: =SUM(F30:AL30) -> 1 | AO30: =B30 -> ELLIS, Joseph
A31: 25 | B31: FITZPATRICK, Cynthia E. - Aug 31 | C31: EHS | J31: 1 | AM31: =SUM(F31:AL31) -> 1 | AO31: =B31 -> FITZPATRICK, Cynthia E. - Aug 31
A32: 26 | B32: FITZPATRICK, Cynthia E. - Toddlers | C32: EHS/ Toddlers | J32: 1 | AM32: =SUM(F32:AL32) -> 1 | AO32: =B32 -> FITZPATRICK, Cynthia E. - Toddlers
A33: 27 | B33: FRANCOIS, Darlene | C33: Americorp | O33: 1 | AM33: =SUM(F33:AL33) -> 1 | AO33: =B33 -> FRANCOIS, Darlene
A34: 28 | B34: FRASER, Vivian Cox | C34: Admin | P34: 0.18 | AH34: 0.82 | AM34: =SUM(F34:AL34) -> 1 | AO34: =B34 -> FRASER, Vivian Cox
A35: 29 | B35: FRASER, Vivian Cox- July | C35: Admin | AH35: 1 | AM35: =SUM(F35:AL35) -> 1 | AO35: =B35 -> FRASER, Vivian Cox- July
A36: 30 | B36: FRAZIER, Alice | C36: Workforce | W36: 1 | X36: 0 | AM36: =SUM(F36:AL36) -> 1 | AO36: =B36 -> FRAZIER, Alice
A37: 31 | B37: Freeman, Jibri | C37: Americorp | O37: 1 | AM37: =SUM(E37:AL37) -> 1 | AO37: =B37 -> Freeman, Jibri
A38: 32 | B38: GARRETT, Dorian S. | C38: EHS | J38: 1 | AM38: =SUM(E38:AL38) -> 1 | AO38: =B38 -> GARRETT, Dorian S.
A39: 33 | B39: GARRETT, Shakia | C39: EHS | J39: 1 | AM39: =SUM(E39:AL39) -> 1 | AO39: =B39 -> GARRETT, Shakia
A40: 34 | B40: GBAMOKOLLIE, Molly | C40: Facilities | AL40: 1 | AM40: =SUM(E40:AL40) -> 1 | AO40: =B40 -> GBAMOKOLLIE, Molly
A41: 35 | B41: GREEN, Yolanda - | C41: EHS | J41: 1 | AM41: =SUM(E41:AL41) -> 1 | AO41: =B41 -> GREEN, Yolanda -
A42: 36 | B42: GREEN, Yolanda - Toddlers | C42: EHS/ Toddlers | J42: 1 | AM42: =SUM(E42:AL42) -> 1 | AO42: =B42 -> GREEN, Yolanda - Toddlers
A43: 37 | B43: HAMILTON, Marchetta | C43: EHS | J43: 1 | AM43: =SUM(E43:AL43) -> 1 | AO43: =B43 -> HAMILTON, Marchetta
A44: 38 | B44: HERBERT, Marina R. | C44: EHS | J44: 1 | AM44: =SUM(E44:AL44) -> 1 | AO44: =B44 -> HERBERT, Marina R.
A45: 39 | B45: HIGGINS, Rosa M. April | C45: FOC | P45: 0.5 | AB45: 0.25 | AC45: 0 | AF45: 0.25 | AM45: =SUM(E45:AL45) -> 1 | AO45: =B45 -> HIGGINS, Rosa M. April
A46: 40 | B46: HIGGINS, Rosa M. May 1 | C46: FOC | P46: 0.5 | AB46: 0.3 | AC46: 0 | AD46: 0.2 | AM46: =SUM(E46:AL46) -> 1 | AO46: =B46 -> HIGGINS, Rosa M. May 1
A47: 41 | B47: HIGGINS, Rosa M. July | C47: LISC, CDBG irvington | AB47: 0.25 | AC47: 0 | AD47: 0.4 | AF47: 0.35 | AM47: =SUM(E47:AL47) -> 1 | AO47: =B47 -> HIGGINS, Rosa M. July
A48: 42 | B48: HILL, Katina | C48: EHS | J48: 1 | AM48: =SUM(E48:AL48) -> 1 | AO48: =B48 -> HILL, Katina
A49: 43 | B49: HILL, Nyjira | C49: EHS | J49: 1 | AM49: =SUM(E49:AL49) -> 1 | AO49: =B49 -> HILL, Nyjira
A50: 44 | B50: HILL, Wynora - Summer | C50: Abbott | F50: 0 | L50: 1 | AM50: =SUM(E50:AL50) -> 1 | AO50: =B50 -> HILL, Wynora - Summer
A51: 45 | B51: HILL, Wynora | C51: Abbott | F51: 1 | AM51: =SUM(E51:AL51) -> 1 | AO51: =B51 -> HILL, Wynora
A52: 46 | B52: HOLLINS, QUINTELLA | C52: Abbott | F52: 1 | AM52: =SUM(E52:AL52) -> 1 | AO52: =B52 -> HOLLINS, QUINTELLA
A53: 47 | B53: HOWARD, Cheryl | C53: NRTC | P53: 1 | AM53: =SUM(E53:AL53) -> 1 | AO53: =B53 -> HOWARD, Cheryl
A54: 48 | B54: HOWARD, Cheryl - July | C54: NRTC | E54: 1 | AM54: =SUM(E54:AL54) -> 1 | AO54: =B54 -> HOWARD, Cheryl - July
A55: 49 | B55: HOWARD, Walter | C55: Thriftworks | E55: 1 | AM55: =SUM(E55:AL55) -> 1 | AO55: =B55 -> HOWARD, Walter
A56: 50 | B56: JOHNSON, Kamilla R. April | C56: FOC, Housing, OICA | N56: 0.2 | P56: 0.1 | AA56: 0.25 | AB56: 0.25 | AC56: 0.1 | AD56: 0.1 | AM56: =SUM(E56:AL56) -> 1 | AO56: =B56 -> JOHNSON, Kamilla R. April
A57: 51 | B57: JOHNSON, Kamilla R. May | C57: FOC, Housing, OICA | N57: 0 | P57: 0.1 | AA57: 0.25 | AB57: 0.25 | AC57: 0.1 | AD57: 0.3 | AM57: =SUM(E57:AL57) -> 1 | AO57: =B57 -> JOHNSON, Kamilla R. May
A58: 52 | B58: JOHNSON, Kamilla R. June | C58: FOC, Housing, OICA | AA58: 0.3 | AB58: 0.25 | AC58: 0.05 | AD58: 0.4 | AE58: 0 | AM58: =SUM(E58:AL58) -> 1 | AO58: =B58 -> JOHNSON, Kamilla R. June
A59: 53 | B59: LANE-MEGA, Lataeya - Replacemt | C59: Abbott | F59: 1 | AM59: =SUM(E59:AL59) -> 1 | AO59: =B59 -> LANE-MEGA, Lataeya - Replacemt
A60: 54 | B60: LEWIS, Felicia M. | C60: EHS | J60: 1 | AM60: =SUM(E60:AL60) -> 1 | AO60: =B60 -> LEWIS, Felicia M.
A61: 55 | B61: LEWIS, Jaleeah C. | C61: EHS | J61: 1 | AM61: =SUM(E61:AL61) -> 1 | AO61: =B61 -> LEWIS, Jaleeah C.
A62: 56 | B62: LEWIS, Tavonna | C62: EHS | J62: 1 | AM62: =SUM(E62:AL62) -> 1 | AO62: =B62 -> LEWIS, Tavonna
A63: 57 | B63: LOFTIN, NIQUITA | C63: Abbott | F63: 1 | AM63: =SUM(E63:AL63) -> 1 | AO63: =B63 -> LOFTIN, NIQUITA
A64: 58 | B64: MAJETTE, Juanita L. | C64: Americorp | O64: 1 | AM64: =SUM(E64:AL64) -> 1 | AO64: =B64 -> MAJETTE, Juanita L.
A65: 59 | B65: MARROW, Mary Elizabeth | C65: EHS | J65: 1 | AM65: =SUM(E65:AL65) -> 1 | AO65: =B65 -> MARROW, Mary Elizabeth
A66: 60 | B66: MARTINEZ, Joanna | C66: USJP | T66: 1 | AM66: =SUM(E66:AL66) -> 1 | AO66: =B66 -> MARTINEZ, Joanna
A67: 61 | B67: MARTINEZ, Joanna - August | C67: USJP, Finance | T67: 0.95 | AI67: 0.05 | AM67: =SUM(E67:AL67) -> 1 | AO67: =B67 -> MARTINEZ, Joanna - August
A68: 62 | B68: MCMILLIAN, Daphne L. | C68: Abbott | F68: 0.8 | H68: 0.2 | AM68: =SUM(E68:AL68) -> 1 | AO68: =B68 -> MCMILLIAN, Daphne L.
A69: 63 | B69: MCMILLIAN, Daphne L. - Summer | C69: Abbott | F69: 1 | L69: 0 | AM69: =SUM(E69:AL69) -> 1 | AO69: =B69 -> MCMILLIAN, Daphne L. - Summer
A70: 64 | B70: MEGGETT, Bonita L. | C70: EHS | J70: 1 | AM70: =SUM(E70:AL70) -> 1 | AO70: =B70 -> MEGGETT, Bonita L.
A71: 65 | B71: MORRIS, GWEN | C71: USJP | T71: 1 | AM71: =SUM(E71:AL71) -> 1 | AO71: =B71 -> MORRIS, GWEN
A72: 66 | B72: RAMBARAN, Sharaini J. | C72: Abbott | F72: 0.5 | G72: 0.5 | AM72: =SUM(E72:AL72) -> 1 | AO72: =B72 -> RAMBARAN, Sharaini J.
A73: 67 | B73: RAMBARAN, Sharaini J. - Summer | C73: Abbott | L73: 1 | AM73: =SUM(E73:AL73) -> 1 | AO73: =B73 -> RAMBARAN, Sharaini J. - Summer
A74: 68 | B74: REED, Melissa | C74: Americorp | O74: 1 | AM74: =SUM(E74:AL74) -> 1 | AO74: =B74 -> REED, Melissa
A75: 69 | B75: Robinson, Chantee | C75: Americorp | O75: 1 | AM75: =SUM(E75:AL75) -> 1 | AO75: =B75 -> Robinson, Chantee
A76: 70 | B76: ROBBINS, Leonard | C76: Real Estate | R76: 1 | AM76: =SUM(E76:AL76) -> 1 | AO76: =B76 -> ROBBINS, Leonard
A77: 71 | B77: Rogers, Lakeshia | C77: Americorp | O77: 1 | AM77: =SUM(E77:AL77) -> 1 | AO77: =B77 -> Rogers, Lakeshia
A78: 72 | B78: SANTIAGO-RAMOS, Jose A. | C78: Facilities | F78: 0.77 | AL78: 0.23 | AM78: =SUM(E78:AL78) -> 1 | AO78: =B78 -> SANTIAGO-RAMOS, Jose A.
A79: 73 | B79: SERMON, Patricia April | C79: FOC, Housing, OICA, COO | N79: 0.5 | T79: 0.2 | AA79: 0.1 | AF79: 0 | AJ79: 0.2 | AM79: =SUM(E79:AL79) -> 1 | AO79: =B79 -> SERMON, Patricia April
A80: 74 | B80: SERMON, Patricia May | C80: FOC, Housing, OICA, COO | T80: 0.2 | AA80: 0.1 | AD80: 0.5 | AJ80: 0.2 | AM80: =SUM(E80:AL80) -> 1 | AO80: =B80 -> SERMON, Patricia May
A81: 75 | B81: SERMON, Patricia June | C81: FOC, Housing, OICA, COO | T81: 0.9 | AA81: 0.1 | AM81: =SUM(E81:AL81) -> 1 | AO81: =B81 -> SERMON, Patricia June
A82: 76 | B82: SERMON, Patricia July | C82: FOC, Housing, OICA, COO | T82: 0.2 | AA82: 0.1 | AB82: 0.1 | AD82: 0.5 | AF82: 0.1 | AJ82: 0 | AM82: =SUM(E82:AL82) -> 1 | AO82: =B82 -> SERMON, Patricia July
A83: 77 | B83: SERMON, Patricia August | C83: FOC, Housing, OICA, COO | T83: 0.2 | AA83: 0.1 | AB83: 0.1 | AD83: 0.5 | AF83: 0.1 | AJ83: 0 | AM83: =SUM(E83:AL83) -> 1 | AO83: =B83 -> SERMON, Patricia August
A84: 78 | B84: SESSOMS, Donna M. | C84: Americorp | O84: 1 | AM84: =SUM(E84:AL84) -> 1 | AO84: =B84 -> SESSOMS, Donna M.
A85: 79 | B85: SHARIF, Darrin S. - April | C85: Admin, Coding, WF | M85: 0.25 | S85: 0.75 | AM85: =SUM(E85:AL85) -> 1 | AO85: =B85 -> SHARIF, Darrin S. - April
A86: 80 | B86: SHARIF, Darrin S. - July | C86: Admin, Coding, WF | M86: 0.3 | S86: 0.7 | AM86: =SUM(E86:AL86) -> 1 | AO86: =B86 -> SHARIF, Darrin S. - July
A87: 81 | B87: SIMMONS, Bertrilla R. | C87: Abbott | F87: 1 | AM87: =SUM(E87:AL87) -> 1 | AO87: =B87 -> SIMMONS, Bertrilla R.
A88: 82 | B88: STEWART, Robin D - Summer | C88: Abbott | F88: 0 | L88: 1 | AM88: =SUM(E88:AL88) -> 1 | AO88: =B88 -> STEWART, Robin D - Summer
A89: 83 | B89: STEWART, Robin D | C89: Abbott | F89: 1 | AM89: =SUM(E89:AL89) -> 1 | AO89: =B89 -> STEWART, Robin D
A90: 84 | B90: TYLER, Patricia | C90: Abbott | F90: 0.77 | I90: 0.23 | AM90: =SUM(E90:AL90) -> 1 | AO90: =B90 -> TYLER, Patricia
A91: 85 | B91: TYLER, Patricia - Summer | C91: Abbott | L91: 1 | AM91: =SUM(E91:AL91) -> 1 | AO91: =B91 -> TYLER, Patricia - Summer
A92: 86 | B92: WAH, Alexia | C92: EHS | J92: 1 | AM92: =SUM(E92:AL92) -> 1 | AO92: =B92 -> WAH, Alexia
A93: 87 | B93: WARD, Richard G. - April | C93: Admin | M93: 0.1 | Q93: 0.1 | AI93: 0.8 | AM93: =SUM(E93:AL93) -> 1 | AO93: =B93 -> WARD, Richard G. - April
A94: 88 | B94: WARD, Richard G. -May | C94: Admin | M94: 0.1 | Q94: 0.1 | AI94: 0.8 | AM94: =SUM(E94:AL94) -> 1 | AO94: =B94 -> WARD, Richard G. -May
A95: 89 | B95: WARD, Richard G. - August | C95: USJP, Finance, Coding, NRTC 19 | M95: 0.2 | Q95: 0.1 | T95: 0.1 | AI95: 0.6 | AM95: =SUM(E95:AL95) -> 1 | AO95: =B95 -> WARD, Richard G. - August
A96: 90 | B96: Wardwick, Lamar | C96: NRTC, Housing, PARS, ESG | P96: 0.5 | Y96: 0.25 | AA96: 0.25 | AM96: =SUM(E96:AL96) -> 1 | AO96: =B96 -> Wardwick, Lamar
A97: 91 | B97: WILLIAMS, Kilaina | C97: EHS | J97: 1 | AM97: =SUM(E97:AL97) -> 1 | AO97: =B97 -> WILLIAMS, Kilaina
A98: 92 | B98: WOODRIDGE, Rosalind | C98: Abbott | F98: 0 | G98: 1 | AM98: =SUM(E98:AL98) -> 1 | AO98: =B98 -> WOODRIDGE, Rosalind
A99: 93 | B99: WOODRIDGE, Rosalind - Summer | C99: Abbott | L99: 1 | AM99: =SUM(E99:AL99) -> 1 | AO99: =B99 -> WOODRIDGE, Rosalind - Summer
A100: 94 | B100: WILJEAMPS, St Louis | C100: Americorp | O100: 1 | AM100: =SUM(E100:AL100) -> 1 | AO100: =B100 -> WILJEAMPS, St Louis
...

Sheet 2019  SALARIES MASTER Salary 
F3: 0.05 | AW3: $180K to June 30
AN4: 10 months | AR4: 12 Months | AU4: 59300 | AW4: 60000 | BC4: $3k | BE4: $6k
B5: SALARIES 2019 | C5: 2018 FY BUDGET | D5: Bi Weekly | E5: Annual Budget | F5: Salary Adj | G5: Salary Revised | H5: 43476 | I5: 43490 | J5: 43504 | K5: 43518 | L5: 43532 | M5: 43546 | N5: 43560 | O5: 43574 | P5: 43588 | Q5: 43602 | R5: 43616 | S5: 43630 | T5: 43644 | U5: 43646 | W5: 43658 | X5: 43672 | Y5: 43686 | Z5: 43700 | AA5: 43714 | AB5: 43728 | AD5: 43742 | AE5: 43756 | AF5: 43770 | AG5: 43784 | AH5: 43798 | AI5: 43812 | AJ5: 43826 | AL5: TOTAL | AN5: =+Allocations!E1 -> 041 Social Enter Thriftworks | AO5: =+Allocations!F1 -> 111 Abbott | AP5: =+Allocations!G1 -> 111B Wrap Fees | AQ5: =+Allocations!H1 -> 111A Other | AR5: =+Allocations!I1 -> 111F Food Prog | AS5: =+Allocations!J1 -> 112 EHS/Toddler | AT5: =+Allocations!K1 -> EHS 112 A Fees | AU5: =+Allocations!L1 -> 114 Summer Camp | ... BV5: =+Allocations!AM1 -> Proof
B6: Salaried | E6: 26 | H6: 1 | I6: 2 | J6: 3 | K6: 4 | L6: 5 | M6: 6 | N6: 7 | O6: 8 | P6: 9 | Q6: 10 | R6: 11 | S6: 12 | T6: 13 | W6: 14 | X6: 15 | Y6: 16 | Z6: 17 | AA6: 18 | AB6: 19 | AD6: 20 | AE6: 21 | AF6: 22 | AG6: 23 | AH6: 24 | AI6: 25 | AJ6: 26 | AL6: 2 | AN6: =Allocations!E5 -> 1 | AO6: =Allocations!F5 -> 2 | AP6: =Allocations!G5 -> 3 | AQ6: =Allocations!H5 -> 4 | AR6: =Allocations!I5 -> 5 | AS6: =Allocations!J5 -> 6 | AT6: =Allocations!K5 -> 7 | AU6: =Allocations!L5 -> 8 | ... BU6: =Allocations!AL5 -> 34
A7: =Allocations!A7 -> 1 | B7: =Allocations!B7 -> AIKEN-SANZONE, Charlene | C7: =Allocations!C7 -> Americorp | D7: 234.685 | E7: =D7*$E$6 -> 6101.81 | G7: =SUM(E7:F7) -> 6101.81 | H7: 211.4 | I7: 211.4 | J7: 528.16 | K7: 528.16 | L7: 528.16 | M7: 528.16 | N7: 528.16 | O7: 528.16 | AL7: =SUM(P7:R7) -> 0 | AM7: =B7 -> AIKEN-SANZONE, Charlene | AN7: =Allocations!E7*$AL7 -> 0 | AO7: =T7+U7+V7 -> 0 | AP7: =U7+V7+W7 -> 0 | AQ7: =V7+W7+X7 -> 0 | AR7: =W7+X7+Y7 -> 0 | AS7: =X7+Y7+Z7 -> 0 | AT7: =Y7+Z7+AA7 -> 0 | AU7: =Allocations!L7*$AL7 -> 0 | AV7: =Allocations!M7*$AL7 -> 0 | AW7: =Allocations!N7*$AL7 -> 0 | AX7: =Allocations!O7*$AL7 -> 0 | AY7: =Allocations!P7*$AL7 -> 0 | AZ7: =Allocations!Q7*$AL7 -> 0 | BA7: =Allocations!R7*$AL7 -> 0 | BB7: =Allocations!S7*$AL7 -> 0 | ... BU7: =Allocations!AL7*$AL7 -> 0 | BV7: =SUM(AN7:BU7) -> 0 | BW7: =AL7-BV7 -> 0 | BX7: =B7 -> AIKEN-SANZONE, Charlene
A8: =Allocations!A8 -> 2 | B8: =Allocations!B8 -> AIKEN-SANZONE, Charlene June 30 | C8: =Allocations!C8 -> OICA | D8: 1080 | E8: =D8*$E$6/2 -> 14040 | G8: =SUM(E8:F8) -> 14040 | H8: 161.15 | I8: 316.76 | J8: 0 | O8: =SUM(O7) -> 528.16 | AL8: =SUM(P8:R8) -> 0 | AM8: =B8 -> AIKEN-SANZONE, Charlene June 30 | AN8: =Allocations!E8*$AL8 -> 0 | AO8: =Allocations!F8*$AL8 -> 0 | AP8: =Allocations!G8*$AL8 -> 0 | AQ8: =Allocations!H8*$AL8 -> 0 | AR8: =Allocations!I8*$AL8 -> 0 | AS8: =Allocations!J8*$AL8 -> 0 | AT8: =Allocations!K8*$AL8 -> 0 | AU8: =Allocations!L8*$AL8 -> 0 | ... BU8: =Allocations!AL8*$AL8 -> 0 | BV8: =SUM(AN8:BU8) -> 0 | BW8: =AL8-BV8 -> 0 | BX8: =B8 -> AIKEN-SANZONE, Charlene June 30
A9: =Allocations!A9 -> 3 | B9: =Allocations!B9 -> ALFORD, Sebrania R. | C9: =Allocations!C9 -> Abbott | D9: 1807.7 | E9: =D9*$E$6 -> 47000.2 | G9: =SUM(E9:F9) -> 47000.2 | H9: 1807.7 | I9: 1807.7 | J9: 1807.7 | K9: 1807.7 | L9: 1807.7 | M9: 1807.7 | N9: 1807.7 | O9: 1807.7 | P9: 1807.7 | Q9: 1807.7 | R9: 1807.7 | S9: 1807.7 | T9: 1817.7 | W9: 1817.7 | X9: 1867.7 | Y9: 1526.16 | Z9: 1807.7 | AA9: 1807.7 | AL9: =SUM(P9:R9) -> 5423.1 | AM9: =B9 -> ALFORD, Sebrania R. | AN9: =Allocations!E9*$AL9 -> 0 | AO9: =Allocations!F9*$AL9 -> 3525.015 | AP9: =Allocations!G9*$AL9 -> 0 | AQ9: =Allocations!H9*$AL9 -> 0 | AR9: =Allocations!I9*$AL9 -> 0 | AS9: =Allocations!J9*$AL9 -> 1898.085 | AT9: =Allocations!K9*$AL9 -> 0 | AU9: =Allocations!L9*$AL9 -> 0 | ... BU9: =Allocations!AL9*$AL9 -> 0 | BV9: =SUM(AN9:BU9) -> 5423.1 | BW9: =AL9-BV9 -> 0 | BX9: =B9 -> ALFORD, Sebrania R.
A10: =Allocations!A10 -> 4 | B10: =Allocations!B10 -> ALMANZAR, Alberto | C10: =Allocations!C10 -> USJP | D10: 865.2 | E10: =D10*$E$6 -> 22495.2 | G10: =SUM(E10:F10) -> 22495.2 | H10: 865.2 | I10: 865.2 | J10: 865.2 | K10: 432.6 | L10: 865.2 | M10: 865.2 | N10: 778.68 | O10: 865.2 | P10: 692.16 | Q10: 692.16 | R10: 865.2 | S10: 778.68 | T10: 865.2 | U10: 932.6 | W10: 346.08 | X10: 865.2 | Y10: 865.2 | Z10: 865.2 | AA10: 865.2 | AB10: 403.76 | AL10: =SUM(P10:R10) -> 2249.52 | AM10: =B10 -> ALMANZAR, Alberto | AN10: =Allocations!E10*$AL10 -> 0 | AO10: =Allocations!F10*$AL10 -> 0 | AP10: =Allocations!G10*$AL10 -> 0 | AQ10: =Allocations!H10*$AL10 -> 0 | AR10: =Allocations!I10*$AL10 -> 0 | AS10: =Allocations!J10*$AL10 -> 0 | AT10: =Allocations!K10*$AL10 -> 0 | AU10: =Allocations!L10*$AL10 -> 0 | ... BU10: =Allocations!AL10*$AL10 -> 0 | BV10: =SUM(AN10:BU10) -> 2249.52 | BW10: =AL10-BV10 -> 0 | BX10: =B10 -> ALMANZAR, Alberto
A11: =Allocations!A11 -> 5 | B11: =Allocations!B11 -> ANDREWS, Cora - Summer | C11: =Allocations!C11 -> Abbott | E11: =D11*$E$6 -> 0 | F11: =E11*$F$3 -> 0 | G11: =SUM(E11:F11) -> 0 | W11: 1120 | X11: 1120 | Y11: 1120 | Z11: 1120 | AL11: =SUM(P11:R11) -> 0 | AM11: =B11 -> ANDREWS, Cora - Summer | AN11: =Allocations!E11*$AL11 -> 0 | AO11: =Allocations!F11*$AL11 -> 0 | AP11: =Allocations!G11*$AL11 -> 0 | AQ11: =Allocations!H11*$AL11 -> 0 | AR11: =Allocations!I11*$AL11 -> 0 | AS11: =Allocations!J11*$AL11 -> 0 | AT11: =Allocations!K11*$AL11 -> 0 | AU11: =Allocations!L11*$AL11 -> 0 | ... BU11: =Allocations!AL11*$AL11 -> 0 | BV11: =SUM(AN11:BU11) -> 0 | BW11: =AL11-BV11 -> 0 | BX11: =B11 -> ANDREWS, Cora - Summer
A12: =Allocations!A12 -> 6 | B12: =Allocations!B12 -> ANDREWS, Cora | C12: =Allocations!C12 -> Abbott | D12: 760 | E12: =D12*$E$6 -> 19760 | G12: =SUM(E12:F12) -> 19760 | H12: 762.38 | I12: 760 | J12: 757.63 | K12: 763.56 | L12: 763.56 | M12: 767.13 | N12: 763.56 | O12: 763.56 | P12: 760 | Q12: 760 | R12: 760 | S12: 760 | T12: 760 | AA12: 1120 | AB12: 1120 | AD12: 1120 | AE12: 1125.25 | AF12: 1120 | AG12: 1120 | AH12: 1120 | AL12: =SUM(P12:R12) -> 2280 | AM12: =B12 -> ANDREWS, Cora | AN12: =Allocations!E12*$AL12 -> 0 | AO12: =Allocations!F12*$AL12 -> 1755.6 | AP12: =Allocations!G12*$AL12 -> 0 | AQ12: =Allocations!H12*$AL12 -> 0 | AR12: =Allocations!I12*$AL12 -> 0 | AS12: =Allocations!J12*$AL12 -> 524.4 | AT12: =Allocations!K12*$AL12 -> 0 | AU12: =Allocations!L12*$AL12 -> 0 | ... BU12: =Allocations!AL12*$AL12 -> 0 | BV12: =SUM(AN12:BU12) -> 2280 | BW12: =AL12-BV12 -> 0 | BX12: =B12 -> ANDREWS, Cora
A13: =Allocations!A13 -> 7 | B13: =Allocations!B13 -> ANDREWS, Courtney A. | C13: =Allocations!C13 -> Americorp | D13: 485.77 | E13: =D13*$E$6 -> 12630.02 | G13: =SUM(E13:F13) -> 12630.02 | AL13: =SUM(P13:R13) -> 0 | AM13: =B13 -> ANDREWS, Courtney A. | AN13: =Allocations!E13*$AL13 -> 0 | AO13: =Allocations!F13*$AL13 -> 0 | AP13: =Allocations!G13*$AL13 -> 0 | AQ13: =Allocations!H13*$AL13 -> 0 | AR13: =Allocations!I13*$AL13 -> 0 | AS13: =Allocations!J13*$AL13 -> 0 | AT13: =Allocations!K13*$AL13 -> 0 | AU13: =Allocations!L13*$AL13 -> 0 | ... BU13: =Allocations!AL13*$AL13 -> 0 | BV13: =SUM(AN13:BU13) -> 0 | BW13: =AL13-BV13 -> 0 | BX13: =B13 -> ANDREWS, Courtney A.
A14: =Allocations!A14 -> 8 | B14: =Allocations!B14 -> BIRDSONG, Rhonda June 30 | C14: =Allocations!C14 -> OICA | D14: 1884.62 | E14: =D14*$E$6/2 -> 24500.06 | G14: =SUM(E14:F14) -> 24500.06 | H14: 1884.62 | I14: 1884.62 | J14: 1884.62 | K14: 1884.62 | L14: 1884.62 | M14: 1884.62 | N14: 1884.62 | O14: 1884.62 | P14: 1884.62 | Q14: 1884.62 | R14: 1884.62 | S14: 1776.93 | T14: 1444.43 | AL14: =SUM(P14:R14) -> 5653.86 | AM14: =B14 -> BIRDSONG, Rhonda June 30 | AN14: =Allocations!E14*$AL14 -> 0 | AO14: =Allocations!F14*$AL14 -> 0 | AP14: =Allocations!G14*$AL14 -> 0 | AQ14: =Allocations!H14*$AL14 -> 0 | AR14: =Allocations!I14*$AL14 -> 0 | AS14: =Allocations!J14*$AL14 -> 0 | AT14: =Allocations!K14*$AL14 -> 0 | AU14: =Allocations!L14*$AL14 -> 0 | ... BU14: =Allocations!AL14*$AL14 -> 0 | BV14: =SUM(AN14:BU14) -> 5653.86 | BW14: =AL14-BV14 -> 0 | BX14: =B14 -> BIRDSONG, Rhonda June 30
A15: =Allocations!A15 -> 9 | B15: Bizi,Raymond | C15: =Allocations!C15 -> Americorp | D15: 211.26 | E15: =D15*$E$6 -> 5492.76 | G15: =SUM(E15:F15) -> 5492.76 | I15: 211.26 | J15: 528.16 | K15: 528.16 | L15: 528.16 | M15: 528.16 | N15: 528.16 | O15: 528.16 | S15: 528.16 | AL15: =SUM(P15:R15) -> 0 | AM15: =B15 -> Bizi,Raymond | AN15: =Allocations!E15*$AL15 -> 0 | AO15: =Allocations!F15*$AL15 -> 0 | AP15: =Allocations!G15*$AL15 -> 0 | AQ15: =Allocations!H15*$AL15 -> 0 | AR15: =Allocations!I15*$AL15 -> 0 | AS15: =Allocations!J15*$AL15 -> 0 | AT15: =Allocations!K15*$AL15 -> 0 | AU15: =Allocations!L15*$AL15 -> 0 | ... BU15: =Allocations!AL15*$AL15 -> 0 | BV15: =SUM(AN15:BU15) -> 0 | BW15: =AL15-BV15 -> 0 | BX15: =B15 -> Bizi,Raymond
A16: =Allocations!A16 -> 10 | B16: =Allocations!B16 -> BROWN,Denise- Wrap | C16: =Allocations!C16 -> Abbott | D16: 732.26 | E16: =D16*$E$6 -> 19038.76 | G16: =SUM(E16:F16) -> 19038.76 | H16: 733.88 | I16: 682.39 | J16: 500.37 | K16: 673.75 | L16: 708.61 | M16: 707.76 | N16: 774.25 | O16: 382.38 | P16: 185.25 | Q16: 646.01 | R16: 676.88 | S16: 467.88 | T16: 399 | AA16: 60 | AB16: 282.5 | AD16: 495 | AE16: 617.5 | AF16: 423.3 | AG16: 460 | AH16: 325 | AL16: =SUM(P16:R16) -> 1508.14 | AM16: =B16 -> BROWN,Denise- Wrap | AN16: =Allocations!E16*$AL16 -> 0 | AO16: =Allocations!F16*$AL16 -> 0 | AP16: =Allocations!G16*$AL16 -> 1508.14 | AQ16: =Allocations!H16*$AL16 -> 0 | AR16: =Allocations!I16*$AL16 -> 0 | AS16: =Allocations!J16*$AL16 -> 0 | AT16: =Allocations!K16*$AL16 -> 0 | AU16: =Allocations!L16*$AL16 -> 0 | ... BU16: =Allocations!AL16*$AL16 -> 0 | BV16: =SUM(AN16:BU16) -> 1508.14 | BW16: =AL16-BV16 -> 0 | BX16: =B16 -> BROWN,Denise- Wrap
A17: =Allocations!A17 -> 11 | B17: =Allocations!B17 -> BROWN,Denise - Summer | C17: =Allocations!C17 -> Abbott | W17: 687.5 | X17: 800 | Y17: 730 | Z17: 777.5 | AA17: 0 | AB17: 0 | AL17: =SUM(P17:R17) -> 0 | AM17: =B17 -> BROWN,Denise - Summer | AN17: =Allocations!E17*$AL17 -> 0 | AO17: =Allocations!F17*$AL17 -> 0 | AP17: =Allocations!G17*$AL17 -> 0 | AQ17: =Allocations!H17*$AL17 -> 0 | AR17: =Allocations!I17*$AL17 -> 0 | AS17: =Allocations!J17*$AL17 -> 0 | AT17: =Allocations!K17*$AL17 -> 0 | AU17: =Allocations!L17*$AL17 -> 0 | ... BU17: =Allocations!AL17*$AL17 -> 0 | BV17: =SUM(AN17:BU17) -> 0 | BW17: =AL17-BV17 -> 0 | BX17: =B17 -> BROWN,Denise - Summer
A18: =Allocations!A18 -> 12 | B18: =Allocations!B18 -> BRYANT, Roni- Summer | C18: =Allocations!C18 -> Abbott | E18: =D18*$E$6 -> 0 | F18: =E18*$F$3 -> 0 | G18: =SUM(E18:F18) -> 0 | W18: 1008 | X18: 1160 | Y18: 1120 | Z18: 1130 | AA18: 0 | AB18: 0 | AL18: =SUM(P18:R18) -> 0 | AM18: =B18 -> BRYANT, Roni- Summer | AN18: =Allocations!E18*$AL18 -> 0 | AO18: =Allocations!F18*$AL18 -> 0 | AP18: =Allocations!G18*$AL18 -> 0 | AQ18: =Allocations!H18*$AL18 -> 0 | AR18: =Allocations!I18*$AL18 -> 0 | AS18: =Allocations!J18*$AL18 -> 0 | AT18: =Allocations!K18*$AL18 -> 0 | AU18: =Allocations!L18*$AL18 -> 0 | ... BU18: =Allocations!AL18*$AL18 -> 0 | BV18: =SUM(AN18:BU18) -> 0 | BW18: =AL18-BV18 -> 0 | BX18: =B18 -> BRYANT, Roni- Summer
A19: =Allocations!A19 -> 13 | B19: BRYANT, Roni | C19: =Allocations!C19 -> Abbott | D19: 1279.14 | E19: =D19*$E$6 -> 33257.64 | G19: =SUM(E19:F19) -> 33257.64 | H19: 1208.14 | I19: 1268.14 | J19: 1248.14 | K19: 1268.14 | L19: 1258.14 | M19: 1268.14 | N19: 1268.14 | O19: 1268.14 | P19: 1208.14 | Q19: 1282.27 | R19: 1228.14 | S19: 1002.51 | T19: 1022.51 | AA19: 358.15 | AB19: 1337.23 | AD19: 1367.23 | AE19: 1357.23 | AF19: 1384.31 | AG19: 1327.23 | AH19: 1347.23 | AL19: =SUM(P19:R19) -> 3718.55 | AM19: =B19 -> BRYANT, Roni | AN19: =Allocations!E19*$AL19 -> 0 | AO19: =Allocations!F19*$AL19 -> 3718.55 | AP19: =Allocations!G19*$AL19 -> 0 | AQ19: =Allocations!H19*$AL19 -> 0 | AR19: =Allocations!I19*$AL19 -> 0 | AS19: =Allocations!J19*$AL19 -> 0 | AT19: =Allocations!K19*$AL19 -> 0 | AU19: =Allocations!L19*$AL19 -> 0 | ... BU19: =Allocations!AL19*$AL19 -> 0 | BV19: =SUM(AN19:BU19) -> 3718.55 | BW19: =AL19-BV19 -> 0 | BX19: =B19 -> BRYANT, Roni
A20: =Allocations!A20 -> 14 | B20: BUTLER, Ciji | C20: =Allocations!C20 -> USJP | D20: 1538.47 | E20: =D20*$E$6 -> 40000.22 | G20: =SUM(E20:F20) -> 40000.22 | H20: 1538.47 | I20: 1538.47 | J20: 1538.47 | K20: 1538.47 | L20: 1538.47 | M20: 1538.47 | N20: 1538.47 | O20: 1538.47 | P20: 1538.47 | Q20: 2051 | AL20: =SUM(P20:R20) -> 3589.47 | AM20: =B20 -> BUTLER, Ciji | AN20: =Allocations!E20*$AL20 -> 0 | AO20: =Allocations!F20*$AL20 -> 0 | AP20: =Allocations!G20*$AL20 -> 0 | AQ20: =Allocations!H20*$AL20 -> 0 | AR20: =Allocations!I20*$AL20 -> 0 | AS20: =Allocations!J20*$AL20 -> 0 | AT20: =Allocations!K20*$AL20 -> 0 | AU20: =Allocations!L20*$AL20 -> 0 | ... BU20: =Allocations!AL20*$AL20 -> 0 | BV20: =SUM(AN20:BU20) -> 3589.47 | BW20: =AL20-BV20 -> 0 | BX20: =B20 -> BUTLER, Ciji
A21: =Allocations!A21 -> 15 | B21: =Allocations!B21 -> CAMPBELL, Nikiesha K. | C21: =Allocations!C21 -> Americorp | D21: 485.77 | E21: =D21*$E$6 -> 12630.02 | G21: =SUM(E21:F21) -> 12630.02 | H21: 291.46 | AL21: =SUM(P21:R21) -> 0 | AM21: =B21 -> CAMPBELL, Nikiesha K. | AN21: =Allocations!E21*$AL21 -> 0 | AO21: =Allocations!F21*$AL21 -> 0 | AP21: =Allocations!G21*$AL21 -> 0 | AQ21: =Allocations!H21*$AL21 -> 0 | AR21: =Allocations!I21*$AL21 -> 0 | AS21: =Allocations!J21*$AL21 -> 0 | AT21: =Allocations!K21*$AL21 -> 0 | AU21: =Allocations!L21*$AL21 -> 0 | ... BU21: =Allocations!AL21*$AL21 -> 0 | BV21: =SUM(AN21:BU21) -> 0 | BW21: =AL21-BV21 -> 0 | BX21: =B21 -> CAMPBELL, Nikiesha K.
A22: =Allocations!A22 -> 16 | B22: =Allocations!B22 -> CASTELLANOS, Rita J. | C22: =Allocations!C22 -> Abbott | D22: 2278.37 | E22: =D22*$E$6 -> 59237.62 | G22: =SUM(E22:F22) -> 59237.62 | H22: 2354 | I22: 2330.17 | J22: 2363.45 | K22: 2363.45 | L22: 2325.64 | M22: 2344.55 | N22: 2363.45 | O22: 1796.22 | AL22: =SUM(P22:R22) -> 0 | AM22: =B22 -> CASTELLANOS, Rita J. | AN22: =Allocations!E22*$AL22 -> 0 | AO22: =Allocations!F22*$AL22 -> 0 | AP22: =Allocations!G22*$AL22 -> 0 | AQ22: =Allocations!H22*$AL22 -> 0 | AR22: =Allocations!I22*$AL22 -> 0 | AS22: =Allocations!J22*$AL22 -> 0 | AT22: =Allocations!K22*$AL22 -> 0 | AU22: =Allocations!L22*$AL22 -> 0 | ... BU22: =Allocations!AL22*$AL22 -> 0 | BV22: =SUM(AN22:BU22) -> 0 | BW22: =AL22-BV22 -> 0 | BX22: =B22 -> CASTELLANOS, Rita J.
A23: =Allocations!A23 -> 17 | B23: =Allocations!B23 -> CERNA, Irene | C23: =Allocations!C23 -> USJP | D23: 1153.85 | E23: =D23*$E$6 -> 30000.1 | G23: =SUM(E23:F23) -> 30000.1 | H23: 1153.85 | I23: 1153.85 | J23: 1153.85 | K23: 1153.85 | L23: 1153.85 | M23: 1153.85 | N23: 1153.85 | O23: 1153.85 | P23: 1153.85 | Q23: 1153.85 | R23: 1153.85 | S23: 1153.85 | T23: 1153.85 | U23: 461.44 | W23: 577.03 | X23: 1153.85 | Y23: 1153.85 | Z23: 1153.85 | AA23: 576.93 | AB23: 1153.85 | AD23: 1153.85 | AE23: 1038.47 | AF23: 1153.85 | AG23: 1153.85 | AH23: 1153.85 | AL23: =SUM(P23:R23) -> 3461.55 | AM23: =B23 -> CERNA, Irene | AN23: =Allocations!E23*$AL23 -> 0 | AO23: =Allocations!F23*$AL23 -> 0 | AP23: =Allocations!G23*$AL23 -> 0 | AQ23: =Allocations!H23*$AL23 -> 0 | AR23: =Allocations!I23*$AL23 -> 0 | AS23: =Allocations!J23*$AL23 -> 0 | AT23: =Allocations!K23*$AL23 -> 0 | AU23: =Allocations!L23*$AL23 -> 0 | ... BU23: =Allocations!AL23*$AL23 -> 0 | BV23: =SUM(AN23:BU23) -> 3461.55 | BW23: =AL23-BV23 -> 0 | BX23: =B23 -> CERNA, Irene
A24: =Allocations!A24 -> 18 | B24: =Allocations!B24 -> COLEMAN, Zabrina J. | C24: =Allocations!C24 -> EHS | D24: 960 | E24: =D24*$E$6 -> 24960 | G24: =SUM(E24:F24) -> 24960 | H24: 960 | I24: 960 | J24: 960 | K24: 960 | L24: 960 | M24: 960 | N24: 960 | O24: 933.84 | P24: 960 | Q24: 747.72 | R24: 960 | S24: 961.44 | T24: 960 | W24: 960 | X24: 864 | Y24: 987 | Z24: 960 | AL24: =SUM(P24:R24) -> 2667.72 | AM24: =B24 -> COLEMAN, Zabrina J. | AN24: =Allocations!E24*$AL24 -> 0 | AO24: =Allocations!F24*$AL24 -> 0 | AP24: =Allocations!G24*$AL24 -> 0 | AQ24: =Allocations!H24*$AL24 -> 0 | AR24: =Allocations!I24*$AL24 -> 0 | AS24: =Allocations!J24*$AL24 -> 2667.72 | AT24: =Allocations!K24*$AL24 -> 0 | AU24: =Allocations!L24*$AL24 -> 0 | ... BU24: =Allocations!AL24*$AL24 -> 0 | BV24: =SUM(AN24:BU24) -> 2667.72 | BW24: =AL24-BV24 -> 0 | BX24: =B24 -> COLEMAN, Zabrina J.
A25: =Allocations!A25 -> 19 | B25: =Allocations!B25 -> COOPER, Cassandra June 30 | C25: =Allocations!C25 -> OICA | D25: 1500 | E25: =D25*$E$6/2 -> 19500 | G25: =SUM(E25:F25) -> 19500 | H25: 1500 | I25: 1500 | J25: 1500 | K25: 1500 | L25: 1500 | M25: 1500 | N25: 1500 | O25: 1500 | P25: 1500 | Q25: 1500 | R25: 1500 | S25: 1285.71 | T25: 964.35 | AL25: =SUM(P25:R25) -> 4500 | AM25: =B25 -> COOPER, Cassandra June 30 | AN25: =Allocations!E25*$AL25 -> 0 | AO25: =Allocations!F25*$AL25 -> 0 | AP25: =Allocations!G25*$AL25 -> 0 | AQ25: =Allocations!H25*$AL25 -> 0 | AR25: =Allocations!I25*$AL25 -> 0 | AS25: =Allocations!J25*$AL25 -> 0 | AT25: =Allocations!K25*$AL25 -> 0 | AU25: =Allocations!L25*$AL25 -> 0 | ... BU25: =Allocations!AL25*$AL25 -> 0 | BV25: =SUM(AN25:BU25) -> 4500 | BW25: =AL25-BV25 -> 0 | BX25: =B25 -> COOPER, Cassandra June 30
A26: =Allocations!A26 -> 20 | B26: =Allocations!B26 -> COOPER, Cassandra July | C26: =Allocations!C26 -> FOC, ESG | W26: 685.76 | X26: 857.2 | Y26: 857.2 | Z26: 1135.79 | AA26: 857.2 | AB26: 857.2 | AD26: 857.2 | AE26: 771.48 | AF26: 857.2 | AG26: 857.2 | AH26: 857.2 | AL26: =SUM(P26:R26) -> 0 | AM26: =B26 -> COOPER, Cassandra July | AN26: =Allocations!E26*$AL26 -> 0 | AO26: =Allocations!F26*$AL26 -> 0 | AP26: =Allocations!G26*$AL26 -> 0 | AQ26: =Allocations!H26*$AL26 -> 0 | AR26: =Allocations!I26*$AL26 -> 0 | AS26: =Allocations!J26*$AL26 -> 0 | AT26: =Allocations!K26*$AL26 -> 0 | AU26: =Allocations!L26*$AL26 -> 0 | ... BU26: =Allocations!AL26*$AL26 -> 0 | BV26: =SUM(AN26:BU26) -> 0 | BW26: =AL26-BV26 -> 0 | BX26: =B26 -> COOPER, Cassandra July
A27: =Allocations!A27 -> 21 | B27: Counts, Monique Lamae | C27: =Allocations!C27 -> Americorp | D27: 528.16 | E27: =D27*$E$6 -> 13732.16 | G27: =SUM(E27:F27) -> 13732.16 | H27: 105.63 | I27: 528.16 | J27: 528.16 | K27: 528.16 | L27: 528.16 | M27: 528.16 | N27: 528.16 | O27: 528.16 | S27: 528.16 | T27: 528.16 | AL27: =SUM(P27:R27) -> 0 | AM27: =B27 -> Counts, Monique Lamae | AN27: =Allocations!E27*$AL27 -> 0 | AO27: =Allocations!F27*$AL27 -> 0 | AP27: =Allocations!G27*$AL27 -> 0 | AQ27: =Allocations!H27*$AL27 -> 0 | AR27: =Allocations!I27*$AL27 -> 0 | AS27: =Allocations!J27*$AL27 -> 0 | AT27: =Allocations!K27*$AL27 -> 0 | AU27: =Allocations!L27*$AL27 -> 0 | ... BU27: =Allocations!AL27*$AL27 -> 0 | BV27: =SUM(AN27:BU27) -> 0 | BW27: =AL27-BV27 -> 0 | BX27: =B27 -> Counts, Monique Lamae
A28: =Allocations!A28 -> 22 | B28: =Allocations!B28 -> DANCE-WILSON, Heather | C28: =Allocations!C28 -> Abbott | D28: 2692.31 | E28: =D28*$E$6 -> 70000.06 | F28: =E28*$F$3 -> 3500.003 | G28: =SUM(E28:F28) -> 73500.063 | H28: 2692.31 | I28: 2742.31 | J28: 2692.31 | K28: 2692.31 | L28: 2692.31 | M28: 2692.31 | N28: 2692.31 | O28: 2692.31 | P28: 2692.31 | Q28: 2692.31 | R28: 2692.31 | S28: 2692.31 | T28: 2692.31 | W28: 2692.31 | X28: 2692.31 | Y28: 2692.31 | Z28: 2692.31 | AA28: 2692.31 | AB28: 2692.31 | AD28: 2692.31 | AE28: 2692.31 | AF28: 2692.31 | AG28: 2692.31 | AH28: 2692.31 | AL28: =SUM(P28:R28) -> 8076.93 | AM28: =B28 -> DANCE-WILSON, Heather | AN28: =Allocations!E28*$AL28 -> 0 | AO28: =Allocations!F28*$AL28 -> 6219.2361 | AP28: =Allocations!G28*$AL28 -> 0 | AQ28: =Allocations!H28*$AL28 -> 1857.6939 | AR28: =Allocations!I28*$AL28 -> 0 | AS28: =Allocations!J28*$AL28 -> 0 | AT28: =Allocations!K28*$AL28 -> 0 | AU28: =Allocations!L28*$AL28 -> 0 | ... BU28: =Allocations!AL28*$AL28 -> 0 | BV28: =SUM(AN28:BU28) -> 8076.93 | BW28: =AL28-BV28 -> 0 | BX28: =B28 -> DANCE-WILSON, Heather | CI28: =Allocations!#REF! -> #REF! | CJ28: =Allocations!#REF! -> #REF! | CK28: =Allocations!#REF! -> #REF! | CL28: =Allocations!#REF! -> #REF! | CM28: =Allocations!#REF! -> #REF! | CN28: =Allocations!#REF! -> #REF! | CO28: =Allocations!#REF! -> #REF! | CP28: =Allocations!#REF! -> #REF! | ... XFA28: =Allocations!#REF! -> #REF!
A29: =Allocations!A29 -> 23 | B29: =Allocations!B29 -> DANIELS-CRAFTON, Glenda | C29: =Allocations!C29 -> EHS | D29: 960 | E29: =D29*$E$6 -> 24960 | G29: =SUM(E29:F29) -> 24960 | H29: 960 | I29: 964.5 | J29: 964.5 | K29: 960 | L29: 960 | M29: 960 | N29: 963.06 | O29: 960 | P29: 960 | Q29: 964.98 | R29: 963.06 | S29: 960 | T29: 960 | W29: 960 | X29: 960 | Y29: 1440 | Z29: 960 | AL29: =SUM(P29:R29) -> 2888.04 | AM29: =B29 -> DANIELS-CRAFTON, Glenda | AN29: =Allocations!E29*$AL29 -> 0 | AO29: =Allocations!F29*$AL29 -> 0 | AP29: =Allocations!G29*$AL29 -> 0 | AQ29: =Allocations!H29*$AL29 -> 0 | AR29: =Allocations!I29*$AL29 -> 0 | AS29: =Allocations!J29*$AL29 -> 2888.04 | AT29: =Allocations!K29*$AL29 -> 0 | AU29: =Allocations!L29*$AL29 -> 0 | ... BU29: =Allocations!AL29*$AL29 -> 0 | BV29: =SUM(AN29:BU29) -> 2888.04 | BW29: =AL29-BV29 -> 0 | BX29: =B29 -> DANIELS-CRAFTON, Glenda
A30: =Allocations!A30 -> 24 | B30: =Allocations!B30 -> ELLIS, Joseph | C30: =Allocations!C30 -> OICA | D30: 1400 | E30: =D30*$E$6/2 -> 18200 | G30: =SUM(E30:F30) -> 18200 | I30: 1600 | J30: 2800 | K30: 2800 | L30: 2520 | M30: 2800 | N30: 1400 | O30: 2000 | P30: 2000 | Q30: 2000 | AL30: =SUM(P30:R30) -> 4000 | AM30: =B30 -> ELLIS, Joseph | AN30: =Allocations!E30*$AL30 -> 0 | AO30: =Allocations!F30*$AL30 -> 0 | AP30: =Allocations!G30*$AL30 -> 0 | AQ30: =Allocations!H30*$AL30 -> 0 | AR30: =Allocations!I30*$AL30 -> 0 | AS30: =Allocations!J30*$AL30 -> 0 | AT30: =Allocations!K30*$AL30 -> 0 | AU30: =Allocations!L30*$AL30 -> 0 | ... BU30: =Allocations!AL30*$AL30 -> 0 | BV30: =SUM(AN30:BU30) -> 4000 | BW30: =AL30-BV30 -> 0 | BX30: =B30 -> ELLIS, Joseph
A31: =Allocations!A31 -> 25 | B31: =Allocations!B31 -> FITZPATRICK, Cynthia E. - Aug 31 | C31: =Allocations!C31 -> EHS | D31: 960 | E31: =D31*$E$6 -> 24960 | F31: =E31*$F$3 -> 1248 | G31: =SUM(E31:F31) -> 26208 | H31: 960 | I31: 960 | J31: 965.94 | K31: 963.84 | L31: 962.4 | M31: 961.44 | N31: 970.44 | O31: 967.98 | P31: 960.96 | Q31: 962.88 | R31: 977.82 | S31: 960 | T31: 960 | W31: 960 | X31: 960 | Y31: 961.44 | Z31: 967.2 | AL31: =SUM(P31:R31) -> 2901.66 | AM31: =B31 -> FITZPATRICK, Cynthia E. - Aug 31 | AN31: =Allocations!E31*$AL31 -> 0 | AO31: =Allocations!F31*$AL31 -> 0 | AP31: =Allocations!G31*$AL31 -> 0 | AQ31: =Allocations!H31*$AL31 -> 0 | AR31: =Allocations!I31*$AL31 -> 0 | AS31: =Allocations!J31*$AL31 -> 2901.66 | AT31: =Allocations!K31*$AL31 -> 0 | AU31: =Allocations!L31*$AL31 -> 0 | ... BU31: =Allocations!AL31*$AL31 -> 0 | BV31: =SUM(AN31:BU31) -> 2901.66 | BW31: =AL31-BV31 -> 0 | BX31: =B31 -> FITZPATRICK, Cynthia E. - Aug 31
A32: =Allocations!A32 -> 26 | B32: =Allocations!B32 -> FITZPATRICK, Cynthia E. - Toddlers | C32: =Allocations!C32 -> EHS/ Toddlers | AA32: 960 | AB32: 960 | AD32: 962.88 | AE32: 962.88 | AF32: 968.16 | AG32: 964.44 | AH32: 969.96 | AL32: =SUM(P32:R32) -> 0 | AM32: =B32 -> FITZPATRICK, Cynthia E. - Toddlers | AN32: =Allocations!E32*$AL32 -> 0 | AO32: =Allocations!F32*$AL32 -> 0 | AP32: =Allocations!G32*$AL32 -> 0 | AQ32: =Allocations!H32*$AL32 -> 0 | AR32: =Allocations!I32*$AL32 -> 0 | AS32: =Allocations!J32*$AL32 -> 0 | AT32: =Allocations!K32*$AL32 -> 0 | AU32: =Allocations!L32*$AL32 -> 0 | ... BU32: =Allocations!AL32*$AL32 -> 0 | BV32: =SUM(AN32:BU32) -> 0 | BW32: =AL32-BV32 -> 0 | BX32: =B32 -> FITZPATRICK, Cynthia E. - Toddlers
A33: =Allocations!A33 -> 27 | B33: =Allocations!B33 -> FRANCOIS, Darlene | C33: =Allocations!C33 -> Americorp | D33: 485.77 | E33: =D33*$E$6 -> 12630.02 | G33: =SUM(E33:F33) -> 12630.02 | H33: 502.86 | I33: 528.16 | J33: 528.16 | K33: 528.16 | L33: 528.16 | M33: 528.16 | N33: 528.16 | O33: 528.16 | S33: 528.16 | T33: 528.16 | AL33: =SUM(P33:R33) -> 0 | AM33: =B33 -> FRANCOIS, Darlene | AN33: =Allocations!E33*$AL33 -> 0 | AO33: =Allocations!F33*$AL33 -> 0 | AP33: =Allocations!G33*$AL33 -> 0 | AQ33: =Allocations!H33*$AL33 -> 0 | AR33: =Allocations!I33*$AL33 -> 0 | AS33: =Allocations!J33*$AL33 -> 0 | AT33: =Allocations!K33*$AL33 -> 0 | AU33: =Allocations!L33*$AL33 -> 0 | ... BU33: =Allocations!AL33*$AL33 -> 0 | BV33: =SUM(AN33:BU33) -> 0 | BW33: =AL33-BV33 -> 0 | BX33: =B33 -> FRANCOIS, Darlene
A34: =Allocations!A34 -> 28 | B34: =Allocations!B34 -> FRASER, Vivian Cox | C34: =Allocations!C34 -> Admin | D34: 5961.54 | E34: =D34*$E$6 -> 155000.04 | F34: =E34*$F$3 -> 7750.002 | G34: =SUM(E34:F34) -> 162750.04 | H34: 5192.31 | I34: 5192.31 | J34: 5192.31 | K34: 5192.31 | L34: 5192.31 | M34: 5192.31 | N34: 5192.31 | O34: 5961.54 | P34: 10115.38 | Q34: 5961.54 | R34: 5961.54 | S34: 5961.54 | T34: 5961.54 | W34: 5961.54 | X34: 5961.54 | AL34: =SUM(P34:R34) -> 22038.46 | AM34: =B34 -> FRASER, Vivian Cox | AN34: =Allocations!E34*$AL34 -> 0 | AO34: =Allocations!F34*$AL34 -> 0 | AP34: =Allocations!G34*$AL34 -> 0 | AQ34: =Allocations!H34*$AL34 -> 0 | AR34: =Allocations!I34*$AL34 -> 0 | AS34: =Allocations!J34*$AL34 -> 0 | AT34: =Allocations!K34*$AL34 -> 0 | AU34: =Allocations!L34*$AL34 -> 0 | ... BU34: =Allocations!AL34*$AL34 -> 0 | BV34: =SUM(AN34:BU34) -> 22038.46 | BW34: =AL34-BV34 -> 0 | BX34: =B34 -> FRASER, Vivian Cox
A35: =Allocations!A35 -> 29 | B35: =Allocations!B35 -> FRASER, Vivian Cox- July | Y35: 5961.54 | Z35: 5961.54 | AA35: 5961.54 | AB35: 5961.54 | AD35: 5961.54 | AE35: 5961.54 | AF35: 5961.54 | AG35: 5961.54 | AH35: 5961.54 | AL35: =SUM(P35:R35) -> 0 | AM35: =B35 -> FRASER, Vivian Cox- July | AN35: =Allocations!E35*$AL35 -> 0 | AO35: =Allocations!F35*$AL35 -> 0 | AP35: =Allocations!G35*$AL35 -> 0 | AQ35: =Allocations!H35*$AL35 -> 0 | AR35: =Allocations!I35*$AL35 -> 0 | AS35: =Allocations!J35*$AL35 -> 0 | AT35: =Allocations!K35*$AL35 -> 0 | AU35: =Allocations!L35*$AL35 -> 0 | ... BU35: =Allocations!AL35*$AL35 -> 0 | BV35: =SUM(AN35:BU35) -> 0 | BW35: =AL35-BV35 -> 0 | BX35: =B35 -> FRASER, Vivian Cox- July
A36: =Allocations!A36 -> 30 | B36: =Allocations!B36 -> FRAZIER, Alice | C36: =Allocations!C36 -> Workforce | D36: 3153.85 | E36: =D36*$E$6 -> 82000.1 | F36: =E36*$F$3 -> 4100.005 | G36: =SUM(E36:F36) -> 86100.105 | H36: 3153.85 | I36: 3153.85 | J36: 3153.85 | K36: 3153.85 | L36: 3153.85 | M36: 3153.85 | N36: 3153.85 | O36: 3153.85 | P36: 3153.85 | Q36: 3153.85 | R36: 3153.85 | S36: 3153.85 | T36: 3153.85 | W36: 3153.85 | X36: 3153.85 | Y36: 3153.85 | Z36: 3153.85 | AA36: 3153.85 | AB36: 3153.85 | AD36: 3153.85 | AE36: 3153.85 | AF36: 3153.85 | AG36: 3153.85 | AH36: 3153.85 | AL36: =SUM(P36:R36) -> 9461.55 | AM36: =B36 -> FRAZIER, Alice | AN36: =Allocations!E36*$AL36 -> 0 | AO36: =Allocations!F36*$AL36 -> 0 | AP36: =Allocations!G36*$AL36 -> 0 | AQ36: =Allocations!H36*$AL36 -> 0 | AR36: =Allocations!I36*$AL36 -> 0 | AS36: =Allocations!J36*$AL36 -> 0 | AT36: =Allocations!K36*$AL36 -> 0 | AU36: =Allocations!L36*$AL36 -> 0 | ... BU36: =Allocations!AL36*$AL36 -> 0 | BV36: =SUM(AN36:BU36) -> 9461.55 | BW36: =AL36-BV36 -> 0 | BX36: =B36 -> FRAZIER, Alice
A37: =Allocations!A37 -> 31 | B37: Freeman, Jibri | C37: =Allocations!C37 -> Americorp | D37: 528.16 | E37: =D37*$E$6 -> 13732.16 | G37: =SUM(E37:F37) -> 13732.16 | H37: 105.63 | I37: 528.16 | J37: 528.16 | K37: 528.16 | L37: 528.16 | M37: 528.16 | N37: 528.16 | O37: 528.16 | AL37: =SUM(P37:R37) -> 0 | AM37: =B37 -> Freeman, Jibri | AN37: =Allocations!E37*$AL37 -> 0 | AO37: =Allocations!F37*$AL37 -> 0 | AP37: =Allocations!G37*$AL37 -> 0 | AQ37: =Allocations!H37*$AL37 -> 0 | AR37: =Allocations!I37*$AL37 -> 0 | AS37: =Allocations!J37*$AL37 -> 0 | AT37: =Allocations!K37*$AL37 -> 0 | AU37: =Allocations!L37*$AL37 -> 0 | ... BU37: =Allocations!AL37*$AL37 -> 0 | BV37: =SUM(AN37:BU37) -> 0 | BW37: =AL37-BV37 -> 0 | BX37: =B37 -> Freeman, Jibri
A38: =Allocations!A38 -> 32 | B38: =Allocations!B38 -> GARRETT, Dorian S. | C38: =Allocations!C38 -> EHS | D38: 1227 | E38: =D38*$E$6 -> 31902 | G38: =SUM(E38:F38) -> 31902 | H38: 1064 | I38: 1264.72 | J38: 1129 | K38: 1285 | L38: 1277.08 | M38: 1273.84 | N38: 1283.92 | O38: 1284.1 | P38: 960.42 | Q38: 904.92 | R38: 738 | S38: 944.04 | T38: 960 | W38: 947.76 | X38: 942 | Y38: 903 | Z38: 960 | AL38: =SUM(P38:R38) -> 2603.34 | AM38: =B38 -> GARRETT, Dorian S. | AN38: =Allocations!E38*$AL38 -> 0 | AO38: =Allocations!F38*$AL38 -> 0 | AP38: =Allocations!G38*$AL38 -> 0 | AQ38: =Allocations!H38*$AL38 -> 0 | AR38: =Allocations!I38*$AL38 -> 0 | AS38: =Allocations!J38*$AL38 -> 2603.34 | AT38: =Allocations!K38*$AL38 -> 0 | AU38: =Allocations!L38*$AL38 -> 0 | ... BU38: =Allocations!AL38*$AL38 -> 0 | BV38: =SUM(AN38:BU38) -> 2603.34 | BW38: =AL38-BV38 -> 0 | BX38: =B38 -> GARRETT, Dorian S.
A39: =Allocations!A39 -> 33 | B39: =Allocations!B39 -> GARRETT, Shakia | C39: =Allocations!C39 -> EHS | D39: 700 | E39: =D39*$E$6 -> 18200 | G39: =SUM(E39:F39) -> 18200 | AL39: =SUM(P39:R39) -> 0 | AM39: =B39 -> GARRETT, Shakia | AN39: =Allocations!E39*$AL39 -> 0 | AO39: =Allocations!F39*$AL39 -> 0 | AP39: =Allocations!G39*$AL39 -> 0 | AQ39: =Allocations!H39*$AL39 -> 0 | AR39: =Allocations!I39*$AL39 -> 0 | AS39: =Allocations!J39*$AL39 -> 0 | AT39: =Allocations!K39*$AL39 -> 0 | AU39: =Allocations!L39*$AL39 -> 0 | ... BU39: =Allocations!AL39*$AL39 -> 0 | BV39: =SUM(AN39:BU39) -> 0 | BW39: =AL39-BV39 -> 0 | BX39: =B39 -> GARRETT, Shakia
A40: =Allocations!A40 -> 34 | B40: =Allocations!B40 -> GBAMOKOLLIE, Molly | C40: =Allocations!C40 -> Facilities | D40: 625 | E40: =D40*$E$6 -> 16250 | G40: =SUM(E40:F40) -> 16250 | H40: 437.5 | I40: 312.5 | AL40: =SUM(P40:R40) -> 0 | AM40: =B40 -> GBAMOKOLLIE, Molly | AN40: =Allocations!E40*$AL40 -> 0 | AO40: =Allocations!F40*$AL40 -> 0 | AP40: =Allocations!G40*$AL40 -> 0 | AQ40: =Allocations!H40*$AL40 -> 0 | AR40: =Allocations!I40*$AL40 -> 0 | AS40: =Allocations!J40*$AL40 -> 0 | AT40: =Allocations!K40*$AL40 -> 0 | AU40: =Allocations!L40*$AL40 -> 0 | ... BU40: =Allocations!AL40*$AL40 -> 0 | BV40: =SUM(AN40:BU40) -> 0 | BW40: =AL40-BV40 -> 0 | BX40: =B40 -> GBAMOKOLLIE, Molly
A41: =Allocations!A41 -> 35 | B41: =Allocations!B41 -> GREEN, Yolanda - | C41: =Allocations!C41 -> EHS | D41: 1225.86 | E41: =D41*$E$6 -> 31872.36 | F41: =E41*$F$3 -> 1593.618 | G41: =SUM(E41:F41) -> 33465.978 | H41: 1265.62 | I41: 1264.34 | J41: 1254.92 | K41: 1264.34 | L41: 1270.89 | M41: 1257.64 | N41: 1264.19 | O41: 1260.19 | P41: 1273.61 | Q41: 1263.06 | R41: 1259.07 | S41: 1253.65 | T41: 1265.62 | W41: 1277.6 | X41: 1279.52 | Y41: 1261.79 | Z41: 1277.6 | AL41: =SUM(P41:R41) -> 3795.74 | AM41: =B41 -> GREEN, Yolanda - | AN41: =Allocations!E41*$AL41 -> 0 | AO41: =Allocations!F41*$AL41 -> 0 | AP41: =Allocations!G41*$AL41 -> 0 | AQ41: =Allocations!H41*$AL41 -> 0 | AR41: =Allocations!I41*$AL41 -> 0 | AS41: =Allocations!J41*$AL41 -> 3795.74 | AT41: =Allocations!K41*$AL41 -> 0 | AU41: =Allocations!L41*$AL41 -> 0 | ... BU41: =Allocations!AL41*$AL41 -> 0 | BV41: =SUM(AN41:BU41) -> 3795.74 | BW41: =AL41-BV41 -> 0 | BX41: =B41 -> GREEN, Yolanda -
A42: =Allocations!A42 -> 36 | B42: =Allocations!B42 -> GREEN, Yolanda - Toddlers | C42: =Allocations!C42 -> EHS/ Toddlers | AA42: 1277.6 | AB42: 1280.15 | AD42: 1281.44 | AE42: 1284.89 | AF42: 1273.61 | AG42: 1294.52 | AH42: 1278.88 | AL42: =SUM(P42:R42) -> 0 | AM42: =B42 -> GREEN, Yolanda - Toddlers | AN42: =Allocations!E42*$AL42 -> 0 | AO42: =Allocations!F42*$AL42 -> 0 | AP42: =Allocations!G42*$AL42 -> 0 | AQ42: =Allocations!H42*$AL42 -> 0 | AR42: =Allocations!I42*$AL42 -> 0 | AS42: =Allocations!J42*$AL42 -> 0 | AT42: =Allocations!K42*$AL42 -> 0 | AU42: =Allocations!L42*$AL42 -> 0 | ... BU42: =Allocations!AL42*$AL42 -> 0 | BV42: =SUM(AN42:BU42) -> 0 | BW42: =AL42-BV42 -> 0 | BX42: =B42 -> GREEN, Yolanda - Toddlers
A43: =Allocations!A43 -> 37 | B43: =Allocations!B43 -> HAMILTON, Marchetta | C43: =Allocations!C43 -> EHS | D43: 991.5 | E43: =D43*$E$6 -> 25779 | G43: =SUM(E43:F43) -> 25779 | H43: 963 | I43: 991.5 | J43: 975 | K43: 981 | L43: 959.04 | M43: 966 | N43: 960 | O43: 982.5 | P43: 965.04 | Q43: 959.46 | R43: 973.5 | S43: 963 | T43: 963 | W43: 945 | X43: 960 | Y43: 1344 | Z43: 960 | AL43: =SUM(P43:R43) -> 2898 | AM43: =B43 -> HAMILTON, Marchetta | AN43: =Allocations!E43*$AL43 -> 0 | AO43: =Allocations!F43*$AL43 -> 0 | AP43: =Allocations!G43*$AL43 -> 0 | AQ43: =Allocations!H43*$AL43 -> 0 | AR43: =Allocations!I43*$AL43 -> 0 | AS43: =Allocations!J43*$AL43 -> 2898 | AT43: =Allocations!K43*$AL43 -> 0 | AU43: =Allocations!L43*$AL43 -> 0 | ... BU43: =Allocations!AL43*$AL43 -> 0 | BV43: =SUM(AN43:BU43) -> 2898 | BW43: =AL43-BV43 -> 0 | BX43: =B43 -> HAMILTON, Marchetta
A44: =Allocations!A44 -> 38 | B44: =Allocations!B44 -> HERBERT, Marina R. | C44: =Allocations!C44 -> EHS | D44: 943 | E44: =D44*$E$6 -> 24518 | G44: =SUM(E44:F44) -> 24518 | H44: 960 | I44: 960 | J44: 960 | K44: 960 | L44: 960 | M44: 945 | N44: 960 | O44: 941.76 | P44: 951.96 | Q44: 951 | R44: 969 | S44: 956.04 | T44: 960 | W44: 960 | X44: 902.28 | Y44: 512.88 | AL44: =SUM(P44:R44) -> 2871.96 | AM44: =B44 -> HERBERT, Marina R. | AN44: =Allocations!E44*$AL44 -> 0 | AO44: =Allocations!F44*$AL44 -> 0 | AP44: =Allocations!G44*$AL44 -> 0 | AQ44: =Allocations!H44*$AL44 -> 0 | AR44: =Allocations!I44*$AL44 -> 0 | AS44: =Allocations!J44*$AL44 -> 2871.96 | AT44: =Allocations!K44*$AL44 -> 0 | AU44: =Allocations!L44*$AL44 -> 0 | ... BU44: =Allocations!AL44*$AL44 -> 0 | BV44: =SUM(AN44:BU44) -> 2871.96 | BW44: =AL44-BV44 -> 0 | BX44: =B44 -> HERBERT, Marina R.
A45: =Allocations!A45 -> 39 | B45: =Allocations!B45 -> HIGGINS, Rosa M. April | C45: =Allocations!C45 -> FOC | D45: 1538.46 | E45: =D45*$E$6 -> 39999.96 | F45: =E45*$F$3 -> 1999.998 | G45: =SUM(E45:F45) -> 41999.958 | H45: 1538.46 | I45: 1538.46 | J45: 1538.46 | K45: 1538.46 | L45: 1538.46 | M45: 1538.46 | N45: 1538.46 | O45: 1538.46 | AL45: =SUM(P45:R45) -> 0 | AM45: =B45 -> HIGGINS, Rosa M. April | AN45: =Allocations!E45*$AL45 -> 0 | AO45: =Allocations!F45*$AL45 -> 0 | AP45: =Allocations!G45*$AL45 -> 0 | AQ45: =Allocations!H45*$AL45 -> 0 | AR45: =Allocations!I45*$AL45 -> 0 | AS45: =Allocations!J45*$AL45 -> 0 | AT45: =Allocations!K45*$AL45 -> 0 | AU45: =Allocations!L45*$AL45 -> 0 | ... BU45: =Allocations!AL45*$AL45 -> 0 | BV45: =SUM(AN45:BU45) -> 0 | BW45: =AL45-BV45 -> 0 | BX45: =B45 -> HIGGINS, Rosa M. April
A46: =Allocations!A46 -> 40 | B46: =Allocations!B46 -> HIGGINS, Rosa M. May 1 | C46: =Allocations!C46 -> FOC | P46: 1538.46 | Q46: 1538.46 | R46: 1538.46 | S46: 1538.46 | T46: 1538.46 | AL46: =SUM(P46:R46) -> 4615.38 | AM46: =B46 -> HIGGINS, Rosa M. May 1 | AN46: =Allocations!E46*$AL46 -> 0 | AO46: =Allocations!F46*$AL46 -> 0 | AP46: =Allocations!G46*$AL46 -> 0 | AQ46: =Allocations!H46*$AL46 -> 0 | AR46: =Allocations!I46*$AL46 -> 0 | AS46: =Allocations!J46*$AL46 -> 0 | AT46: =Allocations!K46*$AL46 -> 0 | AU46: =Allocations!L46*$AL46 -> 0 | ... BU46: =Allocations!AL46*$AL46 -> 0 | BV46: =SUM(AN46:BU46) -> 4615.38 | BW46: =AL46-BV46 -> 0 | BX46: =B46 -> HIGGINS, Rosa M. May 1
A47: =Allocations!A47 -> 41 | B47: =Allocations!B47 -> HIGGINS, Rosa M. July | C47: =Allocations!C47 -> LISC, CDBG irvington | W47: 1538.46 | X47: 1538.46 | Y47: 1538.46 | Z47: 1538.46 | AA47: 1538.46 | AB47: 1538.46 | AD47: 1538.46 | AE47: 1538.46 | AF47: 1538.46 | AG47: 1538.46 | AH47: 1538.46 | AL47: =SUM(P47:R47) -> 0 | AM47: =B47 -> HIGGINS, Rosa M. July | AN47: =Allocations!E47*$AL47 -> 0 | AO47: =Allocations!F47*$AL47 -> 0 | AP47: =Allocations!G47*$AL47 -> 0 | AQ47: =Allocations!H47*$AL47 -> 0 | AR47: =Allocations!I47*$AL47 -> 0 | AS47: =Allocations!J47*$AL47 -> 0 | AT47: =Allocations!K47*$AL47 -> 0 | AU47: =Allocations!L47*$AL47 -> 0 | ... BU47: =Allocations!AL47*$AL47 -> 0 | BV47: =SUM(AN47:BU47) -> 0 | BW47: =AL47-BV47 -> 0 | BX47: =B47 -> HIGGINS, Rosa M. July
A48: =Allocations!A48 -> 42 | B48: HILL, Katrina | C48: =Allocations!C48 -> EHS | D48: 508.25 | E48: =D48*$E$6 -> 13214.5 | G48: =SUM(E48:F48) -> 13214.5 | H48: 159.13 | I48: 494 | J48: 494 | K48: 486.88 | L48: 460.75 | M48: 494 | N48: 427.5 | O48: 631.75 | P48: 311.13 | Q48: 584.16 | R48: 522.5 | S48: 573.23 | T48: 676.88 | W48: 444.75 | X48: 650.75 | Y48: 445.05 | Z48: 500 | AL48: =SUM(P48:R48) -> 1417.79 | AM48: =B48 -> HILL, Katrina | AN48: =Allocations!E48*$AL48 -> 0 | AO48: =Allocations!F48*$AL48 -> 0 | AP48: =Allocations!G48*$AL48 -> 0 | AQ48: =Allocations!H48*$AL48 -> 0 | AR48: =Allocations!I48*$AL48 -> 0 | AS48: =Allocations!J48*$AL48 -> 1417.79 | AT48: =Allocations!K48*$AL48 -> 0 | AU48: =Allocations!L48*$AL48 -> 0 | ... BU48: =Allocations!AL48*$AL48 -> 0 | BV48: =SUM(AN48:BU48) -> 1417.79 | BW48: =AL48-BV48 -> 0 | BX48: =B48 -> HILL, Katrina
A49: =Allocations!A49 -> 43 | B49: =Allocations!B49 -> HILL, Nyjira | C49: =Allocations!C49 -> EHS | D49: 960 | E49: =D49*$E$6 -> 24960 | G49: =SUM(E49:F49) -> 24960 | H49: 957 | I49: 957 | J49: 960 | K49: 939.96 | L49: 948 | M49: 960 | N49: 949.92 | O49: 960 | P49: 954 | Q49: 953.88 | R49: 997.5 | S49: 960 | T49: 978 | W49: 960 | X49: 960 | Y49: 1910.4 | Z49: 960 | AL49: =SUM(P49:R49) -> 2905.38 | AM49: =B49 -> HILL, Nyjira | AN49: =Allocations!E49*$AL49 -> 0 | AO49: =Allocations!F49*$AL49 -> 0 | AP49: =Allocations!G49*$AL49 -> 0 | AQ49: =Allocations!H49*$AL49 -> 0 | AR49: =Allocations!I49*$AL49 -> 0 | AS49: =Allocations!J49*$AL49 -> 2905.38 | AT49: =Allocations!K49*$AL49 -> 0 | AU49: =Allocations!L49*$AL49 -> 0 | ... BU49: =Allocations!AL49*$AL49 -> 0 | BV49: =SUM(AN49:BU49) -> 2905.38 | BW49: =AL49-BV49 -> 0 | BX49: =B49 -> HILL, Nyjira
A50: =Allocations!A50 -> 44 | B50: =Allocations!B50 -> HILL, Wynora - Summer | C50: =Allocations!C50 -> Abbott | E50: =D50*$E$6 -> 0 | F50: =E50*$F$3 -> 0 | G50: =SUM(E50:F50) -> 0 | W50: 1084 | X50: 732 | Y50: 1164 | Z50: 1098 | AL50: =SUM(P50:R50) -> 0 | AM50: =B50 -> HILL, Wynora - Summer | AN50: =Allocations!E50*$AL50 -> 0 | AO50: =Allocations!F50*$AL50 -> 0 | AP50: =Allocations!G50*$AL50 -> 0 | AQ50: =Allocations!H50*$AL50 -> 0 | AR50: =Allocations!I50*$AL50 -> 0 | AS50: =Allocations!J50*$AL50 -> 0 | AT50: =Allocations!K50*$AL50 -> 0 | AU50: =Allocations!L50*$AL50 -> 0 | ... BU50: =Allocations!AL50*$AL50 -> 0 | BV50: =SUM(AN50:BU50) -> 0 | BW50: =AL50-BV50 -> 0 | BX50: =B50 -> HILL, Wynora - Summer
A51: =Allocations!A51 -> 45 | B51: =Allocations!B51 -> HILL, Wynora | C51: =Allocations!C51 -> Abbott | D51: 1329 | E51: =D51*$E$6 -> 34554 | G51: =SUM(E51:F51) -> 34554 | H51: 1208 | I51: 1308 | J51: 1298 | K51: 1288 | L51: 1251.26 | M51: 1328 | N51: 1348 | O51: 1348 | P51: 1228 | Q51: 1348 | R51: 1348 | S51: 1298 | T51: 918.5 | AL51: =SUM(P51:R51) -> 3924 | AM51: =B51 -> HILL, Wynora | AN51: =Allocations!E51*$AL51 -> 0 | AO51: =Allocations!F51*$AL51 -> 3924 | AP51: =Allocations!G51*$AL51 -> 0 | AQ51: =Allocations!H51*$AL51 -> 0 | AR51: =Allocations!I51*$AL51 -> 0 | AS51: =Allocations!J51*$AL51 -> 0 | AT51: =Allocations!K51*$AL51 -> 0 | AU51: =Allocations!L51*$AL51 -> 0 | ... BU51: =Allocations!AL51*$AL51 -> 0 | BV51: =SUM(AN51:BU51) -> 3924 | BW51: =AL51-BV51 -> 0 | BX51: =B51 -> HILL, Wynora
A52: =Allocations!A52 -> 46 | B52: =Allocations!B52 -> HOLLINS, QUINTELLA | C52: =Allocations!C52 -> Abbott | AA52: 674.01 | AB52: 2305.82 | AD52: 2279.21 | AE52: 2305.82 | AF52: 2305.82 | AG52: 2305.82 | AH52: 2279.21 | AL52: =SUM(P52:R52) -> 0 | AM52: =B52 -> HOLLINS, QUINTELLA | AN52: =Allocations!E52*$AL52 -> 0 | AO52: =Allocations!F52*$AL52 -> 0 | AP52: =Allocations!G52*$AL52 -> 0 | AQ52: =Allocations!H52*$AL52 -> 0 | AR52: =Allocations!I52*$AL52 -> 0 | AS52: =Allocations!J52*$AL52 -> 0 | AT52: =Allocations!K52*$AL52 -> 0 | AU52: =Allocations!L52*$AL52 -> 0 | ... BU52: =Allocations!AL52*$AL52 -> 0 | BV52: =SUM(AN52:BU52) -> 0 | BW52: =AL52-BV52 -> 0 | BX52: =B52 -> HOLLINS, QUINTELLA
A53: =Allocations!A53 -> 47 | B53: =Allocations!B53 -> HOWARD, Cheryl | C53: =Allocations!C53 -> NRTC | D53: 1769.23 | E53: =D53*$E$6 -> 45999.98 | G53: =SUM(E53:F53) -> 45999.98 | H53: 1769.23 | I53: 1769.23 | J53: 1769.23 | K53: 1769.23 | L53: 1769.23 | M53: 1769.23 | N53: 1769.23 | O53: 1769.23 | P53: 1769.23 | Q53: 1769.23 | R53: 1769.23 | S53: 1769.23 | T53: 1769.23 | AL53: =SUM(P53:R53) -> 5307.69 | AM53: =B53 -> HOWARD, Cheryl | AN53: =Allocations!E53*$AL53 -> 0 | AO53: =Allocations!F53*$AL53 -> 0 | AP53: =Allocations!G53*$AL53 -> 0 | AQ53: =Allocations!H53*$AL53 -> 0 | AR53: =Allocations!I53*$AL53 -> 0 | AS53: =Allocations!J53*$AL53 -> 0 | AT53: =Allocations!K53*$AL53 -> 0 | AU53: =Allocations!L53*$AL53 -> 0 | ... BU53: =Allocations!AL53*$AL53 -> 0 | BV53: =SUM(AN53:BU53) -> 5307.69 | BW53: =AL53-BV53 -> 0 | BX53: =B53 -> HOWARD, Cheryl
A54: =Allocations!A54 -> 48 | B54: =Allocations!B54 -> HOWARD, Cheryl - July | C54: =Allocations!C54 -> NRTC | W54: 1769.23 | X54: 1769.23 | AL54: =SUM(P54:R54) -> 0 | AM54: =B54 -> HOWARD, Cheryl - July | AN54: =Allocations!E54*$AL54 -> 0 | AO54: =Allocations!F54*$AL54 -> 0 | AP54: =Allocations!G54*$AL54 -> 0 | AQ54: =Allocations!H54*$AL54 -> 0 | AR54: =Allocations!I54*$AL54 -> 0 | AS54: =Allocations!J54*$AL54 -> 0 | AT54: =Allocations!K54*$AL54 -> 0 | AU54: =Allocations!L54*$AL54 -> 0 | ... BU54: =Allocations!AL54*$AL54 -> 0 | BV54: =SUM(AN54:BU54) -> 0 | BW54: =AL54-BV54 -> 0 | BX54: =B54 -> HOWARD, Cheryl - July
A55: =Allocations!A55 -> 49 | B55: =Allocations!B55 -> HOWARD, Walter | C55: =Allocations!C55 -> Thriftworks | D55: 1120 | E55: =D55*$E$6 -> 29120 | G55: =SUM(E55:F55) -> 29120 | AL55: =SUM(P55:R55) -> 0 | AM55: =B55 -> HOWARD, Walter | AN55: =Allocations!E55*$AL55 -> 0 | AO55: =Allocations!F55*$AL55 -> 0 | AP55: =Allocations!G55*$AL55 -> 0 | AQ55: =Allocations!H55*$AL55 -> 0 | AR55: =Allocations!I55*$AL55 -> 0 | AS55: =Allocations!J55*$AL55 -> 0 | AT55: =Allocations!K55*$AL55 -> 0 | AU55: =Allocations!L55*$AL55 -> 0 | ... BU55: =Allocations!AL55*$AL55 -> 0 | BV55: =SUM(AN55:BU55) -> 0 | BW55: =AL55-BV55 -> 0 | BX55: =B55 -> HOWARD, Walter
A56: =Allocations!A56 -> 50 | B56: =Allocations!B56 -> JOHNSON, Kamilla R. April | C56: =Allocations!C56 -> FOC, Housing, OICA | D56: 2307.7 | E56: =D56*$E$6 -> 60000.2 | G56: =SUM(E56:F56) -> 60000.2 | H56: 2307.7 | I56: 2307.7 | J56: 2307.7 | K56: 2307.7 | L56: 2307.7 | M56: 2307.7 | N56: 2307.7 | O56: 2307.7 | AL56: =SUM(P56:R56) -> 0 | AM56: =B56 -> JOHNSON, Kamilla R. April | AN56: =Allocations!E56*$AL56 -> 0 | AO56: =Allocations!F56*$AL56 -> 0 | AP56: =Allocations!G56*$AL56 -> 0 | AQ56: =Allocations!H56*$AL56 -> 0 | AR56: =Allocations!I56*$AL56 -> 0 | AS56: =Allocations!J56*$AL56 -> 0 | AT56: =Allocations!K56*$AL56 -> 0 | AU56: =Allocations!L56*$AL56 -> 0 | ... BU56: =Allocations!AL56*$AL56 -> 0 | BV56: =SUM(AN56:BU56) -> 0 | BW56: =AL56-BV56 -> 0 | BX56: =B56 -> JOHNSON, Kamilla R. April
A57: =Allocations!A57 -> 51 | B57: =Allocations!B57 -> JOHNSON, Kamilla R. May | C57: =Allocations!C57 -> FOC, Housing, OICA | F57: =E57*$F$3 -> 0 | G57: =SUM(E57:F57) -> 0 | P57: 2307.7 | Q57: 2307.7 | R57: 2307.7 | AL57: =SUM(P57:R57) -> 6923.1 | AM57: =B57 -> JOHNSON, Kamilla R. May | AN57: =Allocations!E57*$AL57 -> 0 | AO57: =Allocations!F57*$AL57 -> 0 | AP57: =Allocations!G57*$AL57 -> 0 | AQ57: =Allocations!H57*$AL57 -> 0 | AR57: =Allocations!I57*$AL57 -> 0 | AS57: =Allocations!J57*$AL57 -> 0 | AT57: =Allocations!K57*$AL57 -> 0 | AU57: =Allocations!L57*$AL57 -> 0 | ... BU57: =Allocations!AL57*$AL57 -> 0 | BV57: =SUM(AN57:BU57) -> 6923.1 | BW57: =AL57-BV57 -> 0 | BX57: =B57 -> JOHNSON, Kamilla R. May
A58: =Allocations!A58 -> 52 | B58: =Allocations!B58 -> JOHNSON, Kamilla R. June | C58: =Allocations!C58 -> FOC, Housing, OICA | S58: 2307.7 | T58: 2307.7 | W58: 2307.7 | Y58: 807.7 | AL58: =SUM(P58:R58) -> 0 | AM58: =B58 -> JOHNSON, Kamilla R. June | AN58: =Allocations!E58*$AL58 -> 0 | AO58: =Allocations!F58*$AL58 -> 0 | AP58: =Allocations!G58*$AL58 -> 0 | AQ58: =Allocations!H58*$AL58 -> 0 | AR58: =Allocations!I58*$AL58 -> 0 | AS58: =Allocations!J58*$AL58 -> 0 | AT58: =Allocations!K58*$AL58 -> 0 | AU58: =Allocations!L58*$AL58 -> 0 | ... BU58: =Allocations!AL58*$AL58 -> 0 | BV58: =SUM(AN58:BU58) -> 0 | BW58: =AL58-BV58 -> 0 | BX58: =B58 -> JOHNSON, Kamilla R. June
A59: =Allocations!A59 -> 53 | B59: =Allocations!B59 -> LANE-MEGA, Lataeya - Replacemt | C59: =Allocations!C59 -> Abbott | D59: 2288.58 | E59: =D59*$E$6 -> 59503.08 | G59: =SUM(E59:F59) -> 59503.08 | H59: 2363.45 | I59: 934.41 | AL59: =SUM(P59:R59) -> 0 | AM59: =B59 -> LANE-MEGA, Lataeya - Replacemt | AN59: =Allocations!E59*$AL59 -> 0 | AO59: =Allocations!F59*$AL59 -> 0 | AP59: =Allocations!G59*$AL59 -> 0 | AQ59: =Allocations!H59*$AL59 -> 0 | AR59: =Allocations!I59*$AL59 -> 0 | AS59: =Allocations!J59*$AL59 -> 0 | AT59: =Allocations!K59*$AL59 -> 0 | AU59: =Allocations!L59*$AL59 -> 0 | ... BU59: =Allocations!AL59*$AL59 -> 0 | BV59: =SUM(AN59:BU59) -> 0 | BW59: =AL59-BV59 -> 0 | BX59: =B59 -> LANE-MEGA, Lataeya - Replacemt
A60: =Allocations!A60 -> 54 | B60: =Allocations!B60 -> LEWIS, Felicia M. | C60: =Allocations!C60 -> EHS | D60: 960 | E60: =D60*$E$6 -> 24960 | G60: =SUM(E60:F60) -> 24960 | H60: 960 | I60: 982.5 | J60: 960 | K60: 963 | L60: 960 | M60: 964.5 | N60: 982.5 | O60: 968.82 | P60: 963 | Q60: 967.56 | R60: 971.88 | S60: 972 | T60: 966 | W60: 964.5 | X60: 960 | Y60: 1656 | Z60: 960 | AL60: =SUM(P60:R60) -> 2902.44 | AM60: =B60 -> LEWIS, Felicia M. | AN60: =Allocations!E60*$AL60 -> 0 | AO60: =Allocations!F60*$AL60 -> 0 | AP60: =Allocations!G60*$AL60 -> 0 | AQ60: =Allocations!H60*$AL60 -> 0 | AR60: =Allocations!I60*$AL60 -> 0 | AS60: =Allocations!J60*$AL60 -> 2902.44 | AT60: =Allocations!K60*$AL60 -> 0 | AU60: =Allocations!L60*$AL60 -> 0 | ... BU60: =Allocations!AL60*$AL60 -> 0 | BV60: =SUM(AN60:BU60) -> 2902.44 | BW60: =AL60-BV60 -> 0 | BX60: =B60 -> LEWIS, Felicia M.
A61: =Allocations!A61 -> 55 | B61: =Allocations!B61 -> LEWIS, Jaleeah C. | C61: =Allocations!C61 -> EHS | D61: 960 | E61: =D61*$E$6 -> 24960 | G61: =SUM(E61:F61) -> 24960 | AL61: =SUM(P61:R61) -> 0 | AM61: =B61 -> LEWIS, Jaleeah C. | AN61: =Allocations!E61*$AL61 -> 0 | AO61: =Allocations!F61*$AL61 -> 0 | AP61: =Allocations!G61*$AL61 -> 0 | AQ61: =Allocations!H61*$AL61 -> 0 | AR61: =Allocations!I61*$AL61 -> 0 | AS61: =Allocations!J61*$AL61 -> 0 | AT61: =Allocations!K61*$AL61 -> 0 | AU61: =Allocations!L61*$AL61 -> 0 | ... BU61: =Allocations!AL61*$AL61 -> 0 | BV61: =SUM(AN61:BU61) -> 0 | BW61: =AL61-BV61 -> 0 | BX61: =B61 -> LEWIS, Jaleeah C.
A62: =Allocations!A62 -> 56 | B62: =Allocations!B62 -> LEWIS, Tavonna | C62: =Allocations!C62 -> EHS | D62: 960 | E62: =D62*$E$6 -> 24960 | G62: =SUM(E62:F62) -> 24960 | H62: 960 | I62: 960 | J62: 960 | K62: 957 | L62: 948 | M62: 936 | N62: 936 | O62: 957 | P62: 957 | Q62: 957.96 | R62: 903.96 | S62: 954 | T62: 960 | W62: 909 | X62: 948 | Y62: 455.28 | Z62: 960 | AL62: =SUM(P62:R62) -> 2818.92 | AM62: =B62 -> LEWIS, Tavonna | AN62: =Allocations!E62*$AL62 -> 0 | AO62: =Allocations!F62*$AL62 -> 0 | AP62: =Allocations!G62*$AL62 -> 0 | AQ62: =Allocations!H62*$AL62 -> 0 | AR62: =Allocations!I62*$AL62 -> 0 | AS62: =Allocations!J62*$AL62 -> 2818.92 | AT62: =Allocations!K62*$AL62 -> 0 | AU62: =Allocations!L62*$AL62 -> 0 | ... BU62: =Allocations!AL62*$AL62 -> 0 | BV62: =SUM(AN62:BU62) -> 2818.92 | BW62: =AL62-BV62 -> 0 | BX62: =B62 -> LEWIS, Tavonna
A63: =Allocations!A63 -> 57 | B63: =Allocations!B63 -> LOFTIN, NIQUITA | C63: =Allocations!C63 -> Abbott | AA63: 225 | AB63: 750 | AD63: 877.83 | AE63: 1176 | AF63: 1176 | AG63: 1058.4 | AH63: 1176 | AL63: =SUM(P63:R63) -> 0 | AM63: =B63 -> LOFTIN, NIQUITA | AN63: =Allocations!E63*$AL63 -> 0 | AO63: =Allocations!F63*$AL63 -> 0 | AP63: =Allocations!G63*$AL63 -> 0 | AQ63: =Allocations!H63*$AL63 -> 0 | AR63: =Allocations!I63*$AL63 -> 0 | AS63: =Allocations!J63*$AL63 -> 0 | AT63: =Allocations!K63*$AL63 -> 0 | AU63: =Allocations!L63*$AL63 -> 0 | ... BU63: =Allocations!AL63*$AL63 -> 0 | BV63: =SUM(AN63:BU63) -> 0 | BW63: =AL63-BV63 -> 0 | BX63: =B63 -> LOFTIN, NIQUITA
A64: =Allocations!A64 -> 58 | B64: =Allocations!B64 -> MAJETTE, Juanita L. | C64: =Allocations!C64 -> Americorp | D64: 485.77 | E64: =D64*$E$6 -> 12630.02 | G64: =SUM(E64:F64) -> 12630.02 | AL64: =SUM(P64:R64) -> 0 | AM64: =B64 -> MAJETTE, Juanita L. | AN64: =Allocations!E64*$AL64 -> 0 | AO64: =Allocations!F64*$AL64 -> 0 | AP64: =Allocations!G64*$AL64 -> 0 | AQ64: =Allocations!H64*$AL64 -> 0 | AR64: =Allocations!I64*$AL64 -> 0 | AS64: =Allocations!J64*$AL64 -> 0 | AT64: =Allocations!K64*$AL64 -> 0 | AU64: =Allocations!L64*$AL64 -> 0 | ... BU64: =Allocations!AL64*$AL64 -> 0 | BV64: =SUM(AN64:BU64) -> 0 | BW64: =AL64-BV64 -> 0 | BX64: =B64 -> MAJETTE, Juanita L.
A65: =Allocations!A65 -> 59 | B65: =Allocations!B65 -> MARROW, Mary Elizabeth | C65: =Allocations!C65 -> EHS | D65: 960 | E65: =D65*$E$6 -> 24960 | G65: =SUM(E65:F65) -> 24960 | H65: 960 | I65: 960 | J65: 960 | K65: 960 | L65: 960 | M65: 960 | N65: 966 | O65: 967.38 | P65: 963 | Q65: 192 | R65: 0 | AL65: =SUM(P65:R65) -> 1155 | AM65: =B65 -> MARROW, Mary Elizabeth | AN65: =Allocations!E65*$AL65 -> 0 | AO65: =Allocations!F65*$AL65 -> 0 | AP65: =Allocations!G65*$AL65 -> 0 | AQ65: =Allocations!H65*$AL65 -> 0 | AR65: =Allocations!I65*$AL65 -> 0 | AS65: =Allocations!J65*$AL65 -> 1155 | AT65: =Allocations!K65*$AL65 -> 0 | AU65: =Allocations!L65*$AL65 -> 0 | ... BU65: =Allocations!AL65*$AL65 -> 0 | BV65: =SUM(AN65:BU65) -> 1155 | BW65: =AL65-BV65 -> 0 | BX65: =B65 -> MARROW, Mary Elizabeth
A66: =Allocations!A66 -> 60 | B66: =Allocations!B66 -> MARTINEZ, Joanna | C66: =Allocations!C66 -> USJP | D66: 1346.16 | E66: =D66*$E$6 -> 35000.16 | F66: =E66*$F$3 -> 1750.008 | G66: =SUM(E66:F66) -> 36750.168 | H66: 1346.16 | I66: 1371.16 | J66: 1346.16 | K66: 1346.16 | L66: 1346.16 | M66: 1346.16 | N66: 1346.16 | O66: 1346.16 | P66: 1730.78 | Q66: 1538.47 | R66: 1538.47 | S66: 1538.47 | T66: 1538.47 | U66: 1769.23 | W66: 769.23 | X66: 1538.47 | AL66: =SUM(P66:R66) -> 4807.72 | AM66: =B66 -> MARTINEZ, Joanna | AN66: =Allocations!E66*$AL66 -> 0 | AO66: =Allocations!F66*$AL66 -> 0 | AP66: =Allocations!G66*$AL66 -> 0 | AQ66: =Allocations!H66*$AL66 -> 0 | AR66: =Allocations!I66*$AL66 -> 0 | AS66: =Allocations!J66*$AL66 -> 0 | AT66: =Allocations!K66*$AL66 -> 0 | AU66: =Allocations!L66*$AL66 -> 0 | ... BU66: =Allocations!AL66*$AL66 -> 0 | BV66: =SUM(AN66:BU66) -> 4807.72 | BW66: =AL66-BV66 -> 0 | BX66: =B66 -> MARTINEZ, Joanna
A67: =Allocations!A67 -> 61 | B67: =Allocations!B67 -> MARTINEZ, Joanna - August | C67: =Allocations!C67 -> USJP, Finance | Y67: 1538.47 | Z67: 1538.47 | AA67: 1538.47 | AB67: 307.7 | AF67: 769.24 | AG67: 1538.47 | AH67: 1538.47 | AL67: =SUM(P67:R67) -> 0 | AM67: =B67 -> MARTINEZ, Joanna - August | AN67: =Allocations!E67*$AL67 -> 0 | AO67: =Allocations!F67*$AL67 -> 0 | AP67: =Allocations!G67*$AL67 -> 0 | AQ67: =Allocations!H67*$AL67 -> 0 | AR67: =Allocations!I67*$AL67 -> 0 | AS67: =Allocations!J67*$AL67 -> 0 | AT67: =Allocations!K67*$AL67 -> 0 | AU67: =Allocations!L67*$AL67 -> 0 | ... BU67: =Allocations!AL67*$AL67 -> 0 | BV67: =SUM(AN67:BU67) -> 0 | BW67: =AL67-BV67 -> 0 | BX67: =B67 -> MARTINEZ, Joanna - August
A68: =Allocations!A68 -> 62 | B68: =Allocations!B68 -> MCMILLIAN, Daphne L. | C68: =Allocations!C68 -> Abbott | D68: 1136.36 | E68: =D68*$E$6 -> 29545.36 | G68: =SUM(E68:F68) -> 29545.36 | H68: 1136.36 | I68: 1136.36 | J68: 1136.36 | K68: 1136.36 | L68: 1136.36 | M68: 1136.36 | N68: 1136.36 | O68: 1136.36 | P68: 1136.36 | Q68: 1136.36 | R68: 1136.36 | S68: 1136.36 | T68: 1136.36 | W68: 909.1 | X68: 909.09 | Y68: 909.09 | Z68: 909.08 | AA68: 1112.72 | AB68: 1216.36 | AD68: 1236.36 | AE68: 1236.36 | AF68: 1216.36 | AG68: 1216.36 | AH68: 1216.36 | AL68: =SUM(P68:R68) -> 3409.08 | AM68: =B68 -> MCMILLIAN, Daphne L. | AN68: =Allocations!E68*$AL68 -> 0 | AO68: =Allocations!F68*$AL68 -> 2727.264 | AP68: =Allocations!G68*$AL68 -> 0 | AQ68: =Allocations!H68*$AL68 -> 681.816 | AR68: =Allocations!I68*$AL68 -> 0 | AS68: =Allocations!J68*$AL68 -> 0 | AT68: =Allocations!K68*$AL68 -> 0 | AU68: =Allocations!L68*$AL68 -> 0 | ... BU68: =Allocations!AL68*$AL68 -> 0 | BV68: =SUM(AN68:BU68) -> 3409.08 | BW68: =AL68-BV68 -> 0 | BX68: =B68 -> MCMILLIAN, Daphne L.
A69: =Allocations!A69 -> 63 | B69: =Allocations!B69 -> MCMILLIAN, Daphne L. - Summer | C69: =Allocations!C69 -> Abbott | AL69: =SUM(P69:R69) -> 0 | AM69: =B69 -> MCMILLIAN, Daphne L. - Summer | AN69: =Allocations!E69*$AL69 -> 0 | AO69: =Allocations!F69*$AL69 -> 0 | AP69: =Allocations!G69*$AL69 -> 0 | AQ69: =Allocations!H69*$AL69 -> 0 | AR69: =Allocations!I69*$AL69 -> 0 | AS69: =Allocations!J69*$AL69 -> 0 | AT69: =Allocations!K69*$AL69 -> 0 | AU69: =Allocations!L69*$AL69 -> 0 | ... BU69: =Allocations!AL69*$AL69 -> 0 | BV69: =SUM(AN69:BU69) -> 0 | BW69: =AL69-BV69 -> 0 | BX69: =B69 -> MCMILLIAN, Daphne L. - Summer
A70: =Allocations!A70 -> 64 | B70: =Allocations!B70 -> MEGGETT, Bonita L. | C70: =Allocations!C70 -> EHS | D70: 960 | E70: =D70*$E$6 -> 24960 | G70: =SUM(E70:F70) -> 24960 | H70: 960 | I70: 960 | J70: 942 | K70: 957 | L70: 930 | M70: 951 | N70: 945 | O70: 954.96 | P70: 952.08 | Q70: 929.04 | R70: 949.92 | S70: 947.52 | T70: 933 | W70: 954 | X70: 960 | Y70: 1113 | Z70: 960 | AL70: =SUM(P70:R70) -> 2831.04 | AM70: =B70 -> MEGGETT, Bonita L. | AN70: =Allocations!E70*$AL70 -> 0 | AO70: =Allocations!F70*$AL70 -> 0 | AP70: =Allocations!G70*$AL70 -> 0 | AQ70: =Allocations!H70*$AL70 -> 0 | AR70: =Allocations!I70*$AL70 -> 0 | AS70: =Allocations!J70*$AL70 -> 2831.04 | AT70: =Allocations!K70*$AL70 -> 0 | AU70: =Allocations!L70*$AL70 -> 0 | ... BU70: =Allocations!AL70*$AL70 -> 0 | BV70: =SUM(AN70:BU70) -> 2831.04 | BW70: =AL70-BV70 -> 0 | BX70: =B70 -> MEGGETT, Bonita L.
A71: =Allocations!A71 -> 65 | B71: MORRIS, GWEN | C71: =Allocations!C71 -> USJP | D71: 2500 | E71: =D71*$E$6 -> 65000 | G71: =SUM(E71:F71) -> 65000 | H71: 2500 | I71: 2500 | J71: 2500 | K71: 2500 | L71: 2500 | M71: 2500 | N71: 2500 | O71: 2500 | P71: 2500 | Q71: 2500 | R71: 2500 | S71: 2500 | T71: 2500 | U71: 1250 | W71: 1250 | X71: 2500 | Y71: 2500 | Z71: 2500 | AA71: 2500 | AB71: 2500 | AD71: 2500 | AE71: 2500 | AF71: 2500 | AG71: 2500 | AH71: 2500 | AL71: =SUM(P71:R71) -> 7500 | AM71: =B71 -> MORRIS, GWEN | AN71: =Allocations!E71*$AL71 -> 0 | AO71: =Allocations!F71*$AL71 -> 0 | AP71: =Allocations!G71*$AL71 -> 0 | AQ71: =Allocations!H71*$AL71 -> 0 | AR71: =Allocations!I71*$AL71 -> 0 | AS71: =Allocations!J71*$AL71 -> 0 | AT71: =Allocations!K71*$AL71 -> 0 | AU71: =Allocations!L71*$AL71 -> 0 | ... BU71: =Allocations!AL71*$AL71 -> 0 | BV71: =SUM(AN71:BU71) -> 7500 | BW71: =AL71-BV71 -> 0 | BX71: =B71 -> MORRIS, GWEN
A72: =Allocations!A72 -> 66 | B72: =Allocations!B72 -> RAMBARAN, Sharaini J. | C72: =Allocations!C72 -> Abbott | D72: 960 | E72: =D72*$E$6 -> 24960 | G72: =SUM(E72:F72) -> 24960 | H72: 272.8 | I72: 743.6 | J72: 624.8 | K72: 730.4 | L72: 686.4 | M72: 682 | N72: 717.2 | O72: 814 | P72: 360.8 | Q72: 2140 | R72: 905.2 | S72: 849.6 | T72: 770.4 | AB72: 862.54 | AD72: 987.08 | AE72: 1010.14 | AF72: 811.8 | AG72: 779.51 | AH72: 710.33 | AL72: =SUM(P72:R72) -> 3406 | AM72: =B72 -> RAMBARAN, Sharaini J. | AN72: =Allocations!E72*$AL72 -> 0 | AO72: =Allocations!F72*$AL72 -> 1703 | AP72: =Allocations!G72*$AL72 -> 1703 | AQ72: =Allocations!H72*$AL72 -> 0 | AR72: =Allocations!I72*$AL72 -> 0 | AS72: =Allocations!J72*$AL72 -> 0 | AT72: =Allocations!K72*$AL72 -> 0 | AU72: =Allocations!L72*$AL72 -> 0 | ... BU72: =Allocations!AL72*$AL72 -> 0 | BV72: =SUM(AN72:BU72) -> 3406 | BW72: =AL72-BV72 -> 0 | BX72: =B72 -> RAMBARAN, Sharaini J.
A73: =Allocations!A73 -> 67 | B73: =Allocations!B73 -> RAMBARAN, Sharaini J. - Summer | C73: =Allocations!C73 -> Abbott | W73: 447.5 | X73: 600 | Y73: 537.5 | Z73: 432.5 | AL73: =SUM(P73:R73) -> 0 | AM73: =B73 -> RAMBARAN, Sharaini J. - Summer | AN73: =Allocations!E73*$AL73 -> 0 | AO73: =Allocations!F73*$AL73 -> 0 | AP73: =Allocations!G73*$AL73 -> 0 | AQ73: =Allocations!H73*$AL73 -> 0 | AR73: =Allocations!I73*$AL73 -> 0 | AS73: =Allocations!J73*$AL73 -> 0 | AT73: =Allocations!K73*$AL73 -> 0 | AU73: =Allocations!L73*$AL73 -> 0 | ... BU73: =Allocations!AL73*$AL73 -> 0 | BV73: =SUM(AN73:BU73) -> 0 | BW73: =AL73-BV73 -> 0 | BX73: =B73 -> RAMBARAN, Sharaini J. - Summer
A74: =Allocations!A74 -> 68 | B74: =Allocations!B74 -> REED, Melissa | C74: =Allocations!C74 -> Americorp | D74: 257.15 | E74: =D74*$E$6 -> 6685.9 | G74: =SUM(E74:F74) -> 6685.9 | AL74: =SUM(P74:R74) -> 0 | AM74: =B74 -> REED, Melissa | AN74: =Allocations!E74*$AL74 -> 0 | AO74: =Allocations!F74*$AL74 -> 0 | AP74: =Allocations!G74*$AL74 -> 0 | AQ74: =Allocations!H74*$AL74 -> 0 | AR74: =Allocations!I74*$AL74 -> 0 | AS74: =Allocations!J74*$AL74 -> 0 | AT74: =Allocations!K74*$AL74 -> 0 | AU74: =Allocations!L74*$AL74 -> 0 | ... BU74: =Allocations!AL74*$AL74 -> 0 | BV74: =SUM(AN74:BU74) -> 0 | BW74: =AL74-BV74 -> 0 | BX74: =B74 -> REED, Melissa
A75: =Allocations!A75 -> 69 | B75: Richardson, Chante | C75: =Allocations!C75 -> Americorp | D75: 528.16 | E75: =D75*$E$6 -> 13732.16 | G75: =SUM(E75:F75) -> 13732.16 | H75: 105.63 | I75: 528.16 | J75: 528.16 | K75: 528.16 | L75: 528.16 | M75: 528.16 | N75: 528.16 | O75: 528.16 | AL75: =SUM(P75:R75) -> 0 | AM75: =B75 -> Richardson, Chante | AN75: =Allocations!E75*$AL75 -> 0 | AO75: =Allocations!F75*$AL75 -> 0 | AP75: =Allocations!G75*$AL75 -> 0 | AQ75: =Allocations!H75*$AL75 -> 0 | AR75: =Allocations!I75*$AL75 -> 0 | AS75: =Allocations!J75*$AL75 -> 0 | AT75: =Allocations!K75*$AL75 -> 0 | AU75: =Allocations!L75*$AL75 -> 0 | ... BU75: =Allocations!AL75*$AL75 -> 0 | BV75: =SUM(AN75:BU75) -> 0 | BW75: =AL75-BV75 -> 0 | BX75: =B75 -> Richardson, Chante
A76: =Allocations!A76 -> 70 | B76: =Allocations!B76 -> ROBBINS, Leonard | C76: =Allocations!C76 -> Real Estate | D76: 2769.23 | E76: =D76*$E$6 -> 71999.98 | F76: =E76*$F$3 -> 3599.999 | G76: =SUM(E76:F76) -> 75599.979 | H76: 2769.23 | I76: 2769.23 | J76: 2769.23 | K76: 2769.23 | L76: 2769.23 | M76: 2769.23 | N76: 2769.23 | O76: 2769.23 | S76: 2769.23 | T76: 2769.23 | W76: 0 | X76: 0 | Y76: 0 | AD76: 0 | AE76: 0 | AF76: 0 | AG76: 0 | AH76: 0 | AI76: 0 | AJ76: 0 | AL76: =SUM(P76:R76) -> 0 | AM76: =B76 -> ROBBINS, Leonard | AN76: =Allocations!E76*$AL76 -> 0 | AO76: =Allocations!F76*$AL76 -> 0 | AP76: =Allocations!G76*$AL76 -> 0 | AQ76: =Allocations!H76*$AL76 -> 0 | AR76: =Allocations!I76*$AL76 -> 0 | AS76: =Allocations!J76*$AL76 -> 0 | AT76: =Allocations!K76*$AL76 -> 0 | AU76: =Allocations!L76*$AL76 -> 0 | ... BU76: =Allocations!AL76*$AL76 -> 0 | BV76: =SUM(AN76:BU76) -> 0 | BW76: =AL76-BV76 -> 0 | BX76: =B76 -> ROBBINS, Leonard
A77: =Allocations!A77 -> 71 | B77: Rogers, Lakeshia | C77: =Allocations!C77 -> Americorp | D77: 528.16 | E77: =D77*$E$6 -> 13732.16 | G77: =SUM(E77:F77) -> 13732.16 | H77: 105.63 | I77: 528.16 | J77: 528.16 | K77: 528.16 | L77: 528.16 | M77: 528.16 | N77: 528.16 | O77: 528.16 | S77: 528.16 | T77: 528.16 | AL77: =SUM(P77:R77) -> 0 | AM77: =B77 -> Rogers, Lakeshia | AN77: =Allocations!E77*$AL77 -> 0 | AO77: =Allocations!F77*$AL77 -> 0 | AP77: =Allocations!G77*$AL77 -> 0 | AQ77: =Allocations!H77*$AL77 -> 0 | AR77: =Allocations!I77*$AL77 -> 0 | AS77: =Allocations!J77*$AL77 -> 0 | AT77: =Allocations!K77*$AL77 -> 0 | AU77: =Allocations!L77*$AL77 -> 0 | ... BU77: =Allocations!AL77*$AL77 -> 0 | BV77: =SUM(AN77:BU77) -> 0 | BW77: =AL77-BV77 -> 0 | BX77: =B77 -> Rogers, Lakeshia
A78: =Allocations!A78 -> 72 | B78: =Allocations!B78 -> SANTIAGO-RAMOS, Jose A. | C78: =Allocations!C78 -> Facilities | D78: 1040 | E78: =D78*$E$6 -> 27040 | G78: =SUM(E78:F78) -> 27040 | H78: 364 | I78: 1134.25 | J78: 1313 | K78: 1000 | L78: 500 | AL78: =SUM(P78:R78) -> 0 | AM78: =B78 -> SANTIAGO-RAMOS, Jose A. | AN78: =Allocations!E78*$AL78 -> 0 | AO78: =Allocations!F78*$AL78 -> 0 | AP78: =Allocations!G78*$AL78 -> 0 | AQ78: =Allocations!H78*$AL78 -> 0 | AR78: =Allocations!I78*$AL78 -> 0 | AS78: =Allocations!J78*$AL78 -> 0 | AT78: =Allocations!K78*$AL78 -> 0 | AU78: =Allocations!L78*$AL78 -> 0 | ... BU78: =Allocations!AL78*$AL78 -> 0 | BV78: =SUM(AN78:BU78) -> 0 | BW78: =AL78-BV78 -> 0 | BX78: =B78 -> SANTIAGO-RAMOS, Jose A.
A79: =Allocations!A79 -> 73 | B79: =Allocations!B79 -> SERMON, Patricia April | C79: =Allocations!C79 -> FOC, Housing, OICA, COO | D79: 3153.85 | E79: =D79*$E$6 -> 82000.1 | F79: =E79*$F$3 -> 4100.005 | G79: =SUM(E79:F79) -> 86100.105 | H79: 3153.85 | I79: 3153.85 | J79: 3153.85 | K79: 3153.85 | L79: 3153.85 | M79: 3153.85 | N79: 3153.85 | O79: 3153.85 | AL79: =SUM(P79:R79) -> 0 | AM79: =B79 -> SERMON, Patricia April | AN79: =Allocations!E79*$AL79 -> 0 | AO79: =Allocations!F79*$AL79 -> 0 | AP79: =Allocations!G79*$AL79 -> 0 | AQ79: =Allocations!H79*$AL79 -> 0 | AR79: =Allocations!I79*$AL79 -> 0 | AS79: =Allocations!J79*$AL79 -> 0 | AT79: =Allocations!K79*$AL79 -> 0 | AU79: =Allocations!L79*$AL79 -> 0 | ... BU79: =Allocations!AL79*$AL79 -> 0 | BV79: =SUM(AN79:BU79) -> 0 | BW79: =AL79-BV79 -> 0 | BX79: =B79 -> SERMON, Patricia April
A80: =Allocations!A80 -> 74 | B80: =Allocations!B80 -> SERMON, Patricia May | C80: =Allocations!C80 -> FOC, Housing, OICA, COO | F80: =E80*$F$3 -> 0 | G80: =SUM(E80:F80) -> 0 | P80: 3153.85 | Q80: 3153.85 | R80: 3153.85 | AL80: =SUM(P80:R80) -> 9461.55 | AM80: =B80 -> SERMON, Patricia May | AN80: =Allocations!E80*$AL80 -> 0 | AO80: =Allocations!F80*$AL80 -> 0 | AP80: =Allocations!G80*$AL80 -> 0 | AQ80: =Allocations!H80*$AL80 -> 0 | AR80: =Allocations!I80*$AL80 -> 0 | AS80: =Allocations!J80*$AL80 -> 0 | AT80: =Allocations!K80*$AL80 -> 0 | AU80: =Allocations!L80*$AL80 -> 0 | ... BU80: =Allocations!AL80*$AL80 -> 0 | BV80: =SUM(AN80:BU80) -> 9461.55 | BW80: =AL80-BV80 -> 0 | BX80: =B80 -> SERMON, Patricia May
A81: =Allocations!A81 -> 75 | B81: =Allocations!B81 -> SERMON, Patricia June | C81: =Allocations!C81 -> FOC, Housing, OICA, COO | F81: =E81*$F$3 -> 0 | G81: =SUM(E81:F81) -> 0 | S81: 3153.85 | T81: 3153.85 | U81: 1576.93 | AL81: =SUM(P81:R81) -> 0 | AM81: =B81 -> SERMON, Patricia June | AN81: =Allocations!E81*$AL81 -> 0 | AO81: =Allocations!F81*$AL81 -> 0 | AP81: =Allocations!G81*$AL81 -> 0 | AQ81: =Allocations!H81*$AL81 -> 0 | AR81: =Allocations!I81*$AL81 -> 0 | AS81: =Allocations!J81*$AL81 -> 0 | AT81: =Allocations!K81*$AL81 -> 0 | AU81: =Allocations!L81*$AL81 -> 0 | ... BU81: =Allocations!AL81*$AL81 -> 0 | BV81: =SUM(AN81:BU81) -> 0 | BW81: =AL81-BV81 -> 0 | BX81: =B81 -> SERMON, Patricia June
A82: =Allocations!A82 -> 76 | B82: =Allocations!B82 -> SERMON, Patricia July | C82: =Allocations!C82 -> FOC, Housing, OICA, COO | W82: 1576.93 | X82: 3153.85 | AL82: =SUM(P82:R82) -> 0 | AM82: =B82 -> SERMON, Patricia July | AN82: =Allocations!E82*$AL82 -> 0 | AO82: =Allocations!F82*$AL82 -> 0 | AP82: =Allocations!G82*$AL82 -> 0 | AQ82: =Allocations!H82*$AL82 -> 0 | AR82: =Allocations!I82*$AL82 -> 0 | AS82: =Allocations!J82*$AL82 -> 0 | AT82: =Allocations!K82*$AL82 -> 0 | AU82: =Allocations!L82*$AL82 -> 0 | ... BU82: =Allocations!AL82*$AL82 -> 0 | BV82: =SUM(AN82:BU82) -> 0 | BW82: =AL82-BV82 -> 0 | BX82: =B82 -> SERMON, Patricia July
A83: =Allocations!A83 -> 77 | B83: =Allocations!B83 -> SERMON, Patricia August | C83: =Allocations!C83 -> FOC, Housing, OICA, COO | Y83: 3153.85 | Z83: 3153.85 | AA83: 3153.85 | AB83: 3153.85 | AD83: 3153.85 | AE83: 3153.85 | AF83: 3153.85 | AG83: 3153.85 | AH83: 3153.85 | AL83: =SUM(P83:R83) -> 0 | AM83: =B83 -> SERMON, Patricia August | AN83: =Allocations!E83*$AL83 -> 0 | AO83: =Allocations!F83*$AL83 -> 0 | AP83: =Allocations!G83*$AL83 -> 0 | AQ83: =Allocations!H83*$AL83 -> 0 | AR83: =Allocations!I83*$AL83 -> 0 | AS83: =Allocations!J83*$AL83 -> 0 | AT83: =Allocations!K83*$AL83 -> 0 | AU83: =Allocations!L83*$AL83 -> 0 | ... BU83: =Allocations!AL83*$AL83 -> 0 | BV83: =SUM(AN83:BU83) -> 0 | BW83: =AL83-BV83 -> 0 | BX83: =B83 -> SERMON, Patricia August
A84: =Allocations!A84 -> 78 | B84: =Allocations!B84 -> SESSOMS, Donna M. | C84: =Allocations!C84 -> Americorp | D84: 528.15 | E84: =D84*$E$6 -> 13731.9 | G84: =SUM(E84:F84) -> 13731.9 | H84: 528.15 | I84: 528.15 | J84: 528.15 | K84: 528.15 | L84: 528.15 | M84: 528.15 | N84: 528.16 | O84: 528.15 | S84: 528.16 | T84: 528.16 | AL84: =SUM(P84:R84) -> 0 | AM84: =B84 -> SESSOMS, Donna M. | AN84: =Allocations!E84*$AL84 -> 0 | AO84: =Allocations!F84*$AL84 -> 0 | AP84: =Allocations!G84*$AL84 -> 0 | AQ84: =Allocations!H84*$AL84 -> 0 | AR84: =Allocations!I84*$AL84 -> 0 | AS84: =Allocations!J84*$AL84 -> 0 | AT84: =Allocations!K84*$AL84 -> 0 | AU84: =Allocations!L84*$AL84 -> 0 | ... BU84: =Allocations!AL84*$AL84 -> 0 | BV84: =SUM(AN84:BU84) -> 0 | BW84: =AL84-BV84 -> 0 | BX84: =B84 -> SESSOMS, Donna M.
A85: =Allocations!A85 -> 79 | B85: =Allocations!B85 -> SHARIF, Darrin S. - April | C85: =Allocations!C85 -> Admin, Coding, WF | D85: 3269 | E85: =D85*$E$6 -> 84994 | F85: =E85*$F$3 -> 4249.7 | G85: =SUM(E85:F85) -> 89243.7 | H85: 3269 | I85: 3269 | J85: 3269 | K85: 3269 | L85: 3269 | M85: 3269 | N85: 3269 | O85: 3269 | P85: 3269 | Q85: 3269 | R85: 3269 | S85: 3269 | T85: 3269 | AL85: =SUM(P85:R85) -> 9807 | AM85: =B85 -> SHARIF, Darrin S. - April | AN85: =Allocations!E85*$AL85 -> 0 | AO85: =Allocations!F85*$AL85 -> 0 | AP85: =Allocations!G85*$AL85 -> 0 | AQ85: =Allocations!H85*$AL85 -> 0 | AR85: =Allocations!I85*$AL85 -> 0 | AS85: =Allocations!J85*$AL85 -> 0 | AT85: =Allocations!K85*$AL85 -> 0 | AU85: =Allocations!L85*$AL85 -> 0 | ... BU85: =Allocations!AL85*$AL85 -> 0 | BV85: =SUM(AN85:BU85) -> 9807 | BW85: =AL85-BV85 -> 0 | BX85: =B85 -> SHARIF, Darrin S. - April
A86: =Allocations!A86 -> 80 | B86: =Allocations!B86 -> SHARIF, Darrin S. - July | C86: =Allocations!C86 -> Admin, Coding, WF | F86: =E86*$F$3 -> 0 | G86: =SUM(E86:F86) -> 0 | W86: 3269 | X86: 3269 | Y86: 3269 | Z86: 3269 | AA86: 3269 | AB86: 3269 | AD86: 3269 | AE86: 3269 | AF86: 3269 | AG86: 3269 | AH86: 3269 | AL86: =SUM(P86:R86) -> 0 | AM86: =B86 -> SHARIF, Darrin S. - July | AN86: =Allocations!E86*$AL86 -> 0 | AO86: =Allocations!F86*$AL86 -> 0 | AP86: =Allocations!G86*$AL86 -> 0 | AQ86: =Allocations!H86*$AL86 -> 0 | AR86: =Allocations!I86*$AL86 -> 0 | AS86: =Allocations!J86*$AL86 -> 0 | AT86: =Allocations!K86*$AL86 -> 0 | AU86: =Allocations!L86*$AL86 -> 0 | ... BB86: =Allocations!S86*$AL86 -> 0 | BC86: =Allocations!U86*$AL86 -> 0 | BD86: =Allocations!U86*$AL86 -> 0 | BE86: =Allocations!V86*$AL86 -> 0 | BF86: =Allocations!W86*$AL86 -> 0 | BG86: =Allocations!X86*$AL86 -> 0 | BH86: =Allocations!Y86*$AL86 -> 0 | BI86: =Allocations!Z86*$AL86 -> 0 | BJ86: =Allocations!AA86*$AL86 -> 0 | BK86: =Allocations!AB86*$AL86 -> 0 | ... BU86: =Allocations!AL86*$AL86 -> 0 | BV86: =SUM(AN86:BU86) -> 0 | BW86: =AL86-BV86 -> 0 | BX86: =B86 -> SHARIF, Darrin S. - July
A87: =Allocations!A87 -> 81 | B87: =Allocations!B87 -> SIMMONS, Bertrilla R. | C87: =Allocations!C87 -> Abbott | D87: 2562.32 | E87: =D87*$E$6 -> 66620.32 | G87: =SUM(E87:F87) -> 66620.32 | H87: 2561.09 | I87: 2557.81 | J87: 2559.86 | K87: 2561.91 | L87: 2561.91 | M87: 2540.6 | N87: 2554.13 | O87: 2550.85 | P87: 2550.84 | Q87: 2552.9 | R87: 2550.85 | S87: 2561.09 | T87: 2048.87 | AA87: 768.33 | AB87: 2684.05 | AD87: 2684.05 | AE87: 2684.05 | AF87: 2720.94 | AG87: 2684.05 | AH87: 2684.05 | AL87: =SUM(P87:R87) -> 7654.59 | AM87: =B87 -> SIMMONS, Bertrilla R. | AN87: =Allocations!E87*$AL87 -> 0 | AO87: =Allocations!F87*$AL87 -> 7654.59 | AP87: =Allocations!G87*$AL87 -> 0 | AQ87: =Allocations!H87*$AL87 -> 0 | AR87: =Allocations!I87*$AL87 -> 0 | AS87: =Allocations!J87*$AL87 -> 0 | AT87: =Allocations!K87*$AL87 -> 0 | AU87: =Allocations!L87*$AL87 -> 0 | ... BU87: =Allocations!AL87*$AL87 -> 0 | BV87: =SUM(AN87:BU87) -> 7654.59 | BW87: =AL87-BV87 -> 0 | BX87: =B87 -> SIMMONS, Bertrilla R.
A88: =Allocations!A88 -> 82 | B88: =Allocations!B88 -> STEWART, Robin D - Summer | C88: =Allocations!C88 -> Abbott | E88: =D88*$E$6 -> 0 | F88: =E88*$F$3 -> 0 | G88: =SUM(E88:F88) -> 0 | AL88: =SUM(P88:R88) -> 0 | AM88: =B88 -> STEWART, Robin D - Summer | AN88: =Allocations!E88*$AL88 -> 0 | AO88: =Allocations!F88*$AL88 -> 0 | AP88: =Allocations!G88*$AL88 -> 0 | AQ88: =Allocations!H88*$AL88 -> 0 | AR88: =Allocations!I88*$AL88 -> 0 | AS88: =Allocations!J88*$AL88 -> 0 | AT88: =Allocations!K88*$AL88 -> 0 | AU88: =Allocations!L88*$AL88 -> 0 | ... BU88: =Allocations!AL88*$AL88 -> 0 | BV88: =SUM(AN88:BU88) -> 0 | BW88: =AL88-BV88 -> 0 | BX88: =B88 -> STEWART, Robin D - Summer
A89: =Allocations!A89 -> 83 | B89: =Allocations!B89 -> STEWART, Robin D | C89: =Allocations!C89 -> Abbott | D89: 1584.81 | E89: =D89*$E$6 -> 41205.06 | G89: =SUM(E89:F89) -> 41205.06 | H89: 1545.09 | I89: 1612.04 | J89: 1538.7 | K89: 1478.17 | L89: 1508.71 | M89: 1472.06 | N89: 1465.96 | O89: 1514.83 | P89: 1520.93 | Q89: 1490.39 | R89: 1514.82 | S89: 1514.83 | T89: 1184.98 | AA89: 458.11 | AB89: 1642.41 | AD89: 1572.92 | AE89: 1629.78 | AF89: 1632.8 | AG89: 1636.09 | AH89: 1611.08 | AL89: =SUM(P89:R89) -> 4526.14 | AM89: =B89 -> STEWART, Robin D | AN89: =Allocations!E89*$AL89 -> 0 | AO89: =Allocations!F89*$AL89 -> 4526.14 | AP89: =Allocations!G89*$AL89 -> 0 | AQ89: =Allocations!H89*$AL89 -> 0 | AR89: =Allocations!I89*$AL89 -> 0 | AS89: =Allocations!J89*$AL89 -> 0 | AT89: =Allocations!K89*$AL89 -> 0 | AU89: =Allocations!L89*$AL89 -> 0 | ... BU89: =Allocations!AL89*$AL89 -> 0 | BV89: =SUM(AN89:BU89) -> 4526.14 | BW89: =AL89-BV89 -> 0 | BX89: =B89 -> STEWART, Robin D
A90: =Allocations!A90 -> 84 | B90: =Allocations!B90 -> TYLER, Patricia | C90: =Allocations!C90 -> Abbott | D90: 568.7 | E90: =D90*$E$6 -> 14786.2 | G90: =SUM(E90:F90) -> 14786.2 | H90: 155.1 | I90: 568.7 | J90: 517 | K90: 511.83 | L90: 498.91 | M90: 553.19 | N90: 568.7 | O90: 568.7 | P90: 248.16 | Q90: 568.7 | R90: 568.7 | S90: 511.83 | T90: 589.38 | AA90: 594.55 | AB90: 511.83 | AD90: 568.7 | AE90: 568.7 | AF90: 511.83 | AG90: 589.38 | AH90: 454.96 | AL90: =SUM(P90:R90) -> 1385.56 | AM90: =B90 -> TYLER, Patricia | AN90: =Allocations!E90*$AL90 -> 0 | AO90: =Allocations!F90*$AL90 -> 1066.8812 | AP90: =Allocations!G90*$AL90 -> 0 | AQ90: =Allocations!H90*$AL90 -> 0 | AR90: =Allocations!I90*$AL90 -> 318.6788 | AS90: =Allocations!J90*$AL90 -> 0 | AT90: =Allocations!K90*$AL90 -> 0 | AU90: =Allocations!L90*$AL90 -> 0 | ... BU90: =Allocations!AL90*$AL90 -> 0 | BV90: =SUM(AN90:BU90) -> 1385.56 | BW90: =AL90-BV90 -> 0 | BX90: =B90 -> TYLER, Patricia
A91: =Allocations!A91 -> 85 | B91: =Allocations!B91 -> TYLER, Patricia - Summer | C91: =Allocations!C91 -> Abbott | W91: 460.13 | X91: 568.7 | Y91: 568.7 | Z91: 568.7 | AL91: =SUM(P91:R91) -> 0 | AM91: =B91 -> TYLER, Patricia - Summer | AN91: =Allocations!E91*$AL91 -> 0 | AO91: =Allocations!F91*$AL91 -> 0 | AP91: =Allocations!G91*$AL91 -> 0 | AQ91: =Allocations!H91*$AL91 -> 0 | AR91: =Allocations!I91*$AL91 -> 0 | AS91: =Allocations!J91*$AL91 -> 0 | AT91: =Allocations!K91*$AL91 -> 0 | AU91: =Allocations!L91*$AL91 -> 0 | ... BU91: =Allocations!AL91*$AL91 -> 0 | BV91: =SUM(AN91:BU91) -> 0 | BW91: =AL91-BV91 -> 0 | BX91: =B91 -> TYLER, Patricia - Summer
A92: =Allocations!A92 -> 86 | B92: =Allocations!B92 -> WAH, Alexia | C92: =Allocations!C92 -> EHS | D92: 926.76 | E92: =D92*$E$6 -> 24095.76 | G92: =SUM(E92:F92) -> 24095.76 | H92: 955.92 | I92: 933 | J92: 951 | K92: 960 | L92: 960 | M92: 935.16 | N92: 933.96 | O92: 838.92 | AL92: =SUM(P92:R92) -> 0 | AM92: =B92 -> WAH, Alexia | AN92: =Allocations!E92*$AL92 -> 0 | AO92: =Allocations!F92*$AL92 -> 0 | AP92: =Allocations!G92*$AL92 -> 0 | AQ92: =Allocations!H92*$AL92 -> 0 | AR92: =Allocations!I92*$AL92 -> 0 | AS92: =Allocations!J92*$AL92 -> 0 | AT92: =Allocations!K92*$AL92 -> 0 | AU92: =Allocations!L92*$AL92 -> 0 | ... BU92: =Allocations!AL92*$AL92 -> 0 | BV92: =SUM(AN92:BU92) -> 0 | BW92: =AL92-BV92 -> 0 | BX92: =B92 -> WAH, Alexia
A93: =Allocations!A93 -> 87 | B93: =Allocations!B93 -> WARD, Richard G. - April | C93: =Allocations!C93 -> Admin | D93: 4230.77 | E93: =D93*$E$6 -> 110000.02 | F93: =E93*$F$3 -> 5500.001 | G93: =SUM(E93:F93) -> 115500.02 | H93: 4230.77 | I93: 4230.77 | J93: 4230.77 | K93: 4230.77 | L93: 4230.77 | M93: 4230.77 | N93: 4230.77 | O93: 4230.77 | AL93: =SUM(P93:R93) -> 0 | AM93: =B93 -> WARD, Richard G. - April | AN93: =Allocations!E93*$AL93 -> 0 | AO93: =Allocations!F93*$AL93 -> 0 | AP93: =Allocations!G93*$AL93 -> 0 | AQ93: =Allocations!H93*$AL93 -> 0 | AR93: =Allocations!I93*$AL93 -> 0 | AS93: =Allocations!J93*$AL93 -> 0 | AT93: =Allocations!K93*$AL93 -> 0 | AU93: =Allocations!L93*$AL93 -> 0 | ... BU93: =Allocations!AL93*$AL93 -> 0 | BV93: =SUM(AN93:BU93) -> 0 | BW93: =AL93-BV93 -> 0 | BX93: =B93 -> WARD, Richard G. - April
A94: =Allocations!A94 -> 88 | B94: =Allocations!B94 -> WARD, Richard G. -May | C94: =Allocations!C94 -> Admin | F94: =E94*$F$3 -> 0 | G94: =SUM(E94:F94) -> 0 | P94: 4230.77 | Q94: 4230.77 | R94: 4230.77 | S94: 4230.77 | T94: 4230.77 | AL94: =SUM(P94:R94) -> 12692.31 | AM94: =B94 -> WARD, Richard G. -May | AN94: =Allocations!E94*$AL94 -> 0 | AO94: =Allocations!F94*$AL94 -> 0 | AP94: =Allocations!G94*$AL94 -> 0 | AQ94: =Allocations!H94*$AL94 -> 0 | AR94: =Allocations!I94*$AL94 -> 0 | AS94: =Allocations!J94*$AL94 -> 0 | AT94: =Allocations!K94*$AL94 -> 0 | AU94: =Allocations!L94*$AL94 -> 0 | ... BU94: =Allocations!AL94*$AL94 -> 0 | BV94: =SUM(AN94:BU94) -> 12692.31 | BW94: =AL94-BV94 -> 0 | BX94: =B94 -> WARD, Richard G. -May
A95: =Allocations!A95 -> 89 | B95: =Allocations!B95 -> WARD, Richard G. - August | C95: =Allocations!C95 -> USJP, Finance, Coding, NRTC 19 | F95: =E95*$F$3 -> 0 | G95: =SUM(E95:F95) -> 0 | W95: 4230.77 | X95: 4230.77 | Y95: 4230.77 | Z95: 4230.77 | AA95: 4230.77 | AB95: 4230.77 | AD95: 4230.77 | AE95: 4230.77 | AF95: 4230.77 | AG95: 4230.77 | AH95: 4230.77 | AL95: =SUM(P95:R95) -> 0 | AM95: =B95 -> WARD, Richard G. - August | AN95: =Allocations!E95*$AL95 -> 0 | AO95: =Allocations!F95*$AL95 -> 0 | AP95: =Allocations!G95*$AL95 -> 0 | AQ95: =Allocations!H95*$AL95 -> 0 | AR95: =Allocations!I95*$AL95 -> 0 | AS95: =Allocations!J95*$AL95 -> 0 | AT95: =Allocations!K95*$AL95 -> 0 | AU95: =Allocations!L95*$AL95 -> 0 | ... BU95: =Allocations!AL95*$AL95 -> 0 | BV95: =SUM(AN95:BU95) -> 0 | BW95: =AL95-BV95 -> 0 | BX95: =B95 -> WARD, Richard G. - August
A96: =Allocations!A96 -> 90 | B96: =Allocations!B96 -> Wardwick, Lamar | C96: =Allocations!C96 -> NRTC, Housing, PARS, ESG | D96: 1482 | E96: =D96*$E$6 -> 38532 | G96: =SUM(E96:F96) -> 38532 | H96: 1330 | I96: 1330 | J96: 1463 | K96: 1330 | L96: 1330 | M96: 1330 | N96: 1330 | O96: 1330 | P96: 1444 | Q96: 1330 | R96: 1330 | S96: 1330 | T96: 1330 | W96: 1795.5 | AL96: =SUM(P96:R96) -> 4104 | AM96: =B96 -> Wardwick, Lamar | AN96: =Allocations!E96*$AL96 -> 0 | AO96: =Allocations!F96*$AL96 -> 0 | AP96: =Allocations!G96*$AL96 -> 0 | AQ96: =Allocations!H96*$AL96 -> 0 | AR96: =Allocations!I96*$AL96 -> 0 | AS96: =Allocations!J96*$AL96 -> 0 | AT96: =Allocations!K96*$AL96 -> 0 | AU96: =Allocations!L96*$AL96 -> 0 | ... BU96: =Allocations!AL96*$AL96 -> 0 | BV96: =SUM(AN96:BU96) -> 4104 | BW96: =AL96-BV96 -> 0 | BX96: =B96 -> Wardwick, Lamar
A97: =Allocations!A97 -> 91 | B97: =Allocations!B97 -> WILLIAMS, Kilaina | C97: =Allocations!C97 -> EHS | D97: 646 | E97: =D97*$E$6 -> 16796 | G97: =SUM(E97:F97) -> 16796 | H97: 174.8 | I97: 631.75 | J97: 553.38 | K97: 550.05 | L97: 577.13 | M97: 609.52 | N97: 655.5 | O97: 604.87 | P97: 289.75 | Q97: 679.25 | R97: 661.01 | S97: 622.25 | T97: 709.38 | W97: 601.25 | X97: 368.13 | Z97: 500 | AL97: =SUM(P97:R97) -> 1630.01 | AM97: =B97 -> WILLIAMS, Kilaina | AN97: =Allocations!E97*$AL97 -> 0 | AO97: =Allocations!F97*$AL97 -> 0 | AP97: =Allocations!G97*$AL97 -> 0 | AQ97: =Allocations!H97*$AL97 -> 0 | AR97: =Allocations!I97*$AL97 -> 0 | AS97: =Allocations!J97*$AL97 -> 1630.01 | AT97: =Allocations!K97*$AL97 -> 0 | AU97: =Allocations!L97*$AL97 -> 0 | ... BU97: =Allocations!AL97*$AL97 -> 0 | BV97: =SUM(AN97:BU97) -> 1630.01 | BW97: =AL97-BV97 -> 0 | BX97: =B97 -> WILLIAMS, Kilaina
A98: =Allocations!A98 -> 92 | B98: =Allocations!B98 -> WOODRIDGE, Rosalind | C98: =Allocations!C98 -> Abbott | D98: 606.6 | E98: =D98*$E$6 -> 15771.6 | G98: =SUM(E98:F98) -> 15771.6 | H98: 165 | I98: 554.1 | J98: 429.2 | K98: 548.3 | L98: 560 | M98: 582.5 | N98: 600 | O98: 592.5 | P98: 255 | Q98: 535 | R98: 610 | S98: 460 | T98: 550 | AA98: 60 | AB98: 370 | AD98: 585 | AE98: 535 | AF98: 460 | AG98: 430 | AH98: 405 | AL98: =SUM(P98:R98) -> 1400 | AM98: =B98 -> WOODRIDGE, Rosalind | AN98: =Allocations!E98*$AL98 -> 0 | AO98: =Allocations!F98*$AL98 -> 0 | AP98: =Allocations!G98*$AL98 -> 1400 | AQ98: =Allocations!H98*$AL98 -> 0 | AR98: =Allocations!I98*$AL98 -> 0 | AS98: =Allocations!J98*$AL98 -> 0 | AT98: =Allocations!K98*$AL98 -> 0 | AU98: =Allocations!L98*$AL98 -> 0 | ... BU98: =Allocations!AL98*$AL98 -> 0 | BV98: =SUM(AN98:BU98) -> 1400 | BW98: =AL98-BV98 -> 0 | BX98: =B98 -> WOODRIDGE, Rosalind
A99: =Allocations!A99 -> 93 | B99: =Allocations!B99 -> WOODRIDGE, Rosalind - Summer | C99: =Allocations!C99 -> Abbott | W99: 720 | X99: 800 | Y99: 400 | Z99: 800 | AL99: =SUM(P99:R99) -> 0 | AM99: =B99 -> WOODRIDGE, Rosalind - Summer | AN99: =Allocations!E99*$AL99 -> 0 | AO99: =Allocations!F99*$AL99 -> 0 | AP99: =Allocations!G99*$AL99 -> 0 | AQ99: =Allocations!H99*$AL99 -> 0 | AR99: =Allocations!I99*$AL99 -> 0 | AS99: =Allocations!J99*$AL99 -> 0 | AT99: =Allocations!K99*$AL99 -> 0 | AU99: =Allocations!L99*$AL99 -> 0 | ... BU99: =Allocations!AL99*$AL99 -> 0 | BV99: =SUM(AN99:BU99) -> 0 | BW99: =AL99-BV99 -> 0 | BX99: =B99 -> WOODRIDGE, Rosalind - Summer
A100: =Allocations!A100 -> 94 | B100: =Allocations!B100 -> WILJEAMPS, St Louis | C100: =Allocations!C100 -> Americorp | D100: 475.34 | E100: =D100*$E$6 -> 12358.84 | G100: =SUM(E100:F100) -> 12358.84 | H100: 528.16 | I100: 528.16 | J100: 528.16 | K100: 528.16 | L100: 528.16 | M100: 528.16 | N100: 528.16 | O100: 528.16 | S100: 528.16 | T100: 528.16 | AL100: =SUM(P100:R100) -> 0 | AM100: =B100 -> WILJEAMPS, St Louis | AN100: =Allocations!E100*$AL100 -> 0 | AO100: =Allocations!F100*$AL100 -> 0 | AP100: =Allocations!G100*$AL100 -> 0 | AQ100: =Allocations!H100*$AL100 -> 0 | AR100: =Allocations!I100*$AL100 -> 0 | AS100: =Allocations!J100*$AL100 -> 0 | AT100: =Allocations!K100*$AL100 -> 0 | AU100: =Allocations!L100*$AL100 -> 0 | ... BU100: =Allocations!AL100*$AL100 -> 0 | BV100: =SUM(AN100:BU100) -> 0 | BW100: =AL100-BV100 -> 0 | BX100: =B100 -> WILJEAMPS, St Louis
A101: =Allocations!A101 -> 95 | B101: =Allocations!B101 -> Wint, Renee | C101: =Allocations!C101 -> Americorp | D101: 528.16 | E101: =D101*$E$6 -> 13732.16 | G101: =SUM(E101:F101) -> 13732.16 | J101: 475.34 | K101: 528.16 | L101: 528.16 | M101: 528.16 | N101: 528.16 | O101: 528.16 | S101: 528.16 | T101: 528.16 | AL101: =SUM(P101:R101) -> 0 | AM101: =B101 -> Wint, Renee | AN101: =Allocations!E101*$AL101 -> 0 | AO101: =Allocations!F101*$AL101 -> 0 | AP101: =Allocations!G101*$AL101 -> 0 | AQ101: =Allocations!H101*$AL101 -> 0 | AR101: =Allocations!I101*$AL101 -> 0 | AS101: =Allocations!J101*$AL101 -> 0 | AT101: =Allocations!K101*$AL101 -> 0 | AU101: =Allocations!L101*$AL101 -> 0 | ... BU101: =Allocations!AL101*$AL101 -> 0 | BV101: =SUM(AN101:BU101) -> 0 | BW101: =AL101-BV101 -> 0 | BX101: =B101 -> Wint, Renee
A102: =Allocations!A102 -> 96 | B102: =Allocations!B102 -> Janvier, Jhonny | C102: =Allocations!C102 -> Abbott | D102: 2641.38 | E102: =D102*$E$6 -> 68675.88 | G102: =SUM(E102:F102) -> 68675.88 | M102: 2480.86 | N102: 2622.99 | O102: 2844.51 | P102: 2641.38 | Q102: 2641.39 | R102: 2662.69 | S102: 2662.69 | T102: 2130.15 | AA102: 798.81 | AB102: 2728.45 | AD102: 2361.16 | AL102: =SUM(P102:R102) -> 7945.46 | AM102: =B102 -> Janvier, Jhonny | AN102: =Allocations!E102*$AL102 -> 0 | AO102: =Allocations!F102*$AL102 -> 7945.46 | AP102: =Allocations!G102*$AL102 -> 0 | AQ102: =Allocations!H102*$AL102 -> 0 | AR102: =Allocations!I102*$AL102 -> 0 | AS102: =Allocations!J102*$AL102 -> 0 | AT102: =Allocations!K102*$AL102 -> 0 | AU102: =Allocations!L102*$AL102 -> 0 | ... BU102: =Allocations!AL102*$AL102 -> 0 | BV102: =SUM(AN102:BU102) -> 7945.46 | BW102: =AL102-BV102 -> 0 | BX102: =B102 -> Janvier, Jhonny
...

Sheet 2019 Health Ins 
T3: Contract
Q4: 12 | T4: Percentage | U4: 10 months | Y4: 12 Months
B5: SALARIES 2018 | C5: 2018 FY BUDGET | E5: Jan | F5: Feb | G5: Mar | H5: Apr | I5: May | J5: Jun | K5: July | L5: August | M5: Sept | N5: Oct | O5: Nov | P5: Dec | Q5: TOTAL | R5: .80.20 | S5: Variance | U5: =+Allocations!E1 -> 041 Social Enter Thriftworks | V5: =+Allocations!F1 -> 111 Abbott | W5: =+Allocations!G1 -> 111B Wrap Fees | X5: =+Allocations!H1 -> 111A Other | Y5: =+Allocations!I1 -> 111F Food Prog | Z5: =+Allocations!J1 -> 112 EHS/Toddler | AA5: =+Allocations!K1 -> EHS 112 A Fees | AB5: =+Allocations!L1 -> 114 Summer Camp | ... BC5: =+Allocations!AM1 -> Proof
B6: Salaried | E6: 1 | F6: 2 | G6: 3 | H6: 4 | I6: 5 | J6: 6 | U6: 1 | V6: 2 | W6: 3 | X6: 4 | Y6: 5 | Z6: 6 | AA6: 7 | AB6: 8 | AC6: 9 | AD6: 10 | AE6: 11 | AF6: 12 | AG6: 13 | AH6: 14 | AI6: 15 | AJ6: 16 | AL6: 17 | AM6: 18 | AN6: 19 | AO6: 20 | AP6: 21 | AQ6: 22 | AR6: 23 | AS6: 24 | AT6: 25 | AU6: 26 | AV6: 27 | AW6: 28 | AX6: 29 | AY6: 30 | AZ6: 31 | BA6: 32 | BB6: 33
A7: =Allocations!A7 -> 1 | B7: =Allocations!B7 -> AIKEN-SANZONE, Charlene | C7: =Allocations!C7 -> Americorp | D7: =Allocations!#REF! -> #REF! | Q7: =SUM(E7:J7) -> 0 | R7: =E7 -> 0 | S7: 0 | T7: 0 | U7: =Allocations!E7*$Q7 -> 0 | V7: =Allocations!F7*$Q7 -> 0 | W7: =Allocations!G7*$Q7 -> 0 | X7: =Allocations!H7*$Q7 -> 0 | Y7: =Allocations!I7*$Q7 -> 0 | Z7: =Allocations!J7*$Q7 -> 0 | AA7: =Allocations!K7*$Q7 -> 0 | AB7: =Allocations!L7*$Q7 -> 0 | ... AV7: =Allocations!AF7*$Q7 -> 0 | AW7: =Allocations!AF7*$Q7 -> 0 | AX7: =Allocations!AG7*$Q7 -> 0 | AY7: =Allocations!AH7*$Q7 -> 0 | AZ7: =Allocations!AI7*$Q7 -> 0 | BA7: =Allocations!AJ7*$Q7 -> 0 | BB7: =Allocations!AK7*$Q7 -> 0 | BC7: =SUM(U7:BB7) -> 0 | BD7: =Q7-BC7 -> 0 | BE7: =B7 -> AIKEN-SANZONE, Charlene
A8: =Allocations!A8 -> 2 | B8: =Allocations!B8 -> AIKEN-SANZONE, Charlene June 30 | C8: =Allocations!C8 -> OICA | D8: =Allocations!#REF! -> #REF! | Q8: =SUM(E8:J8) -> 0 | R8: =E8 -> 0 | S8: =R8/Q8 -> #DIV/0! | T8: 0 | U8: =Allocations!E8*$Q8 -> 0 | V8: =Allocations!F8*$Q8 -> 0 | W8: =Allocations!G8*$Q8 -> 0 | X8: =Allocations!H8*$Q8 -> 0 | Y8: =Allocations!I8*$Q8 -> 0 | Z8: =Allocations!J8*$Q8 -> 0 | AA8: =Allocations!K8*$Q8 -> 0 | AB8: =Allocations!L8*$Q8 -> 0 | ... AV8: =Allocations!AF8*$Q8 -> 0 | AW8: =Allocations!AF8*$Q8 -> 0 | AX8: =Allocations!AG8*$Q8 -> 0 | AY8: =Allocations!AH8*$Q8 -> 0 | AZ8: =Allocations!AI8*$Q8 -> 0 | BA8: =Allocations!AJ8*$Q8 -> 0 | BB8: =Allocations!AK8*$Q8 -> 0 | BC8: =SUM(U8:BB8) -> 0 | BD8: =Q8-BC8 -> 0 | BE8: =B8 -> AIKEN-SANZONE, Charlene June 30
A9: =Allocations!A9 -> 3 | B9: =Allocations!B9 -> ALFORD, Sebrania R. | C9: =Allocations!C9 -> Abbott | D9: =Allocations!#REF! -> #REF! | E9: 700.13 | F9: 700.13 | G9: 700.13 | H9: 700.13 | I9: 700.13 | J9: 700.13 | K9: 700.13 | L9: 700.13 | M9: 700.13 | Q9: =SUM(E9:J9) -> 4200.78 | R9: =E9 -> 700.13 | T9: 0 | U9: =Allocations!E9*$Q9 -> 0 | V9: =Allocations!F9*$Q9 -> 2730.507 | W9: =Allocations!G9*$Q9 -> 0 | X9: =Allocations!H9*$Q9 -> 0 | Y9: =Allocations!I9*$Q9 -> 0 | Z9: =Allocations!J9*$Q9 -> 1470.273 | AA9: =Allocations!K9*$Q9 -> 0 | AB9: =Allocations!L9*$Q9 -> 0 | ... AV9: =Allocations!AF9*$Q9 -> 0 | AW9: =Allocations!AF9*$Q9 -> 0 | AX9: =Allocations!AG9*$Q9 -> 0 | AY9: =Allocations!AH9*$Q9 -> 0 | AZ9: =Allocations!AI9*$Q9 -> 0 | BA9: =Allocations!AJ9*$Q9 -> 0 | BB9: =Allocations!AK9*$Q9 -> 0 | BC9: =SUM(U9:BB9) -> 4200.78 | BD9: =Q9-BC9 -> 0 | BE9: =B9 -> ALFORD, Sebrania R.
A10: =Allocations!A10 -> 4 | B10: =Allocations!B10 -> ALMANZAR, Alberto | C10: =Allocations!C10 -> USJP | D10: =Allocations!#REF! -> #REF! | Q10: =SUM(E10:J10) -> 0 | R10: =E10 -> 0 | S10: =R10/Q10 -> #DIV/0! | T10: 0 | U10: =Allocations!E10*$Q10 -> 0 | V10: =Allocations!F10*$Q10 -> 0 | W10: =Allocations!G10*$Q10 -> 0 | X10: =Allocations!H10*$Q10 -> 0 | Y10: =Allocations!I10*$Q10 -> 0 | Z10: =Allocations!J10*$Q10 -> 0 | AA10: =Allocations!K10*$Q10 -> 0 | AB10: =Allocations!L10*$Q10 -> 0 | ... AV10: =Allocations!AF10*$Q10 -> 0 | AW10: =Allocations!AF10*$Q10 -> 0 | AX10: =Allocations!AG10*$Q10 -> 0 | AY10: =Allocations!AH10*$Q10 -> 0 | AZ10: =Allocations!AI10*$Q10 -> 0 | BA10: =Allocations!AJ10*$Q10 -> 0 | BB10: =Allocations!AK10*$Q10 -> 0 | BC10: =SUM(U10:BB10) -> 0 | BD10: =Q10-BC10 -> 0 | BE10: =B10 -> ALMANZAR, Alberto
A11: =Allocations!A11 -> 5 | B11: =Allocations!B11 -> ANDREWS, Cora - Summer | C11: =Allocations!C11 -> Abbott | D11: =Allocations!#REF! -> #REF! | Q11: =SUM(E11:J11) -> 0 | R11: =E11 -> 0 | T11: 0 | U11: =Allocations!E11*$Q11 -> 0 | V11: =Allocations!F11*$Q11 -> 0 | W11: =Allocations!G11*$Q11 -> 0 | X11: =Allocations!H11*$Q11 -> 0 | Y11: =Allocations!I11*$Q11 -> 0 | Z11: =Allocations!J11*$Q11 -> 0 | AA11: =Allocations!K11*$Q11 -> 0 | AB11: =Allocations!L11*$Q11 -> 0 | ... AV11: =Allocations!AF11*$Q11 -> 0 | AW11: =Allocations!AF11*$Q11 -> 0 | AX11: =Allocations!AG11*$Q11 -> 0 | AY11: =Allocations!AH11*$Q11 -> 0 | AZ11: =Allocations!AI11*$Q11 -> 0 | BA11: =Allocations!AJ11*$Q11 -> 0 | BB11: =Allocations!AK11*$Q11 -> 0 | BC11: =SUM(U11:BB11) -> 0 | BD11: =Q11-BC11 -> 0 | BE11: =B11 -> ANDREWS, Cora - Summer
A12: =Allocations!A12 -> 6 | B12: =Allocations!B12 -> ANDREWS, Cora | C12: =Allocations!C12 -> Abbott | D12: E | Q12: =SUM(E12:J12) -> 0 | R12: =E12 -> 0 | T12: 0 | U12: =Allocations!E12*$Q12 -> 0 | V12: =Allocations!F12*$Q12 -> 0 | W12: =Allocations!G12*$Q12 -> 0 | X12: =Allocations!H12*$Q12 -> 0 | Y12: =Allocations!I12*$Q12 -> 0 | Z12: =Allocations!J12*$Q12 -> 0 | AA12: =Allocations!K12*$Q12 -> 0 | AB12: =Allocations!L12*$Q12 -> 0 | ... AV12: =Allocations!AF12*$Q12 -> 0 | AW12: =Allocations!AF12*$Q12 -> 0 | AX12: =Allocations!AG12*$Q12 -> 0 | AY12: =Allocations!AH12*$Q12 -> 0 | AZ12: =Allocations!AI12*$Q12 -> 0 | BA12: =Allocations!AJ12*$Q12 -> 0 | BB12: =Allocations!AK12*$Q12 -> 0 | BC12: =SUM(U12:BB12) -> 0 | BD12: =Q12-BC12 -> 0 | BE12: =B12 -> ANDREWS, Cora
A13: =Allocations!A13 -> 7 | B13: =Allocations!B13 -> ANDREWS, Courtney A. | C13: =Allocations!C13 -> Americorp | D13: =Allocations!#REF! -> #REF! | Q13: =SUM(E13:J13) -> 0 | R13: =E13 -> 0 | T13: 0 | U13: =Allocations!E13*$Q13 -> 0 | V13: =Allocations!F13*$Q13 -> 0 | W13: =Allocations!G13*$Q13 -> 0 | X13: =Allocations!H13*$Q13 -> 0 | Y13: =Allocations!I13*$Q13 -> 0 | Z13: =Allocations!J13*$Q13 -> 0 | AA13: =Allocations!K13*$Q13 -> 0 | AB13: =Allocations!L13*$Q13 -> 0 | ... AV13: =Allocations!AF13*$Q13 -> 0 | AW13: =Allocations!AF13*$Q13 -> 0 | AX13: =Allocations!AG13*$Q13 -> 0 | AY13: =Allocations!AH13*$Q13 -> 0 | AZ13: =Allocations!AI13*$Q13 -> 0 | BA13: =Allocations!AJ13*$Q13 -> 0 | BB13: =Allocations!AK13*$Q13 -> 0 | BC13: =SUM(U13:BB13) -> 0 | BD13: =Q13-BC13 -> 0 | BE13: =B13 -> ANDREWS, Courtney A.
A14: =Allocations!A14 -> 8 | B14: =Allocations!B14 -> BIRDSONG, Rhonda June 30 | C14: =Allocations!C14 -> OICA | Q14: =SUM(E14:J14) -> 0 | R14: =E14 -> 0 | U14: =Allocations!E14*$Q14 -> 0 | V14: =Allocations!F14*$Q14 -> 0 | W14: =Allocations!G14*$Q14 -> 0 | X14: =Allocations!H14*$Q14 -> 0 | Y14: =Allocations!I14*$Q14 -> 0 | Z14: =Allocations!J14*$Q14 -> 0 | AA14: =Allocations!K14*$Q14 -> 0 | AB14: =Allocations!L14*$Q14 -> 0 | ... AV14: =Allocations!AF14*$Q14 -> 0 | AW14: =Allocations!AF14*$Q14 -> 0 | AX14: =Allocations!AG14*$Q14 -> 0 | AY14: =Allocations!AH14*$Q14 -> 0 | AZ14: =Allocations!AI14*$Q14 -> 0 | BA14: =Allocations!AJ14*$Q14 -> 0 | BB14: =Allocations!AK14*$Q14 -> 0 | BC14: =SUM(U14:BB14) -> 0 | BD14: =Q14-BC14 -> 0 | BE14: =B14 -> BIRDSONG, Rhonda June 30
A15: =Allocations!A15 -> 9 | B15: =Allocations!B15 -> Bizi, Raymond | C15: =Allocations!C15 -> Americorp | D15: =Allocations!#REF! -> #REF! | Q15: =SUM(E15:J15) -> 0 | R15: =E15 -> 0 | T15: 0 | U15: =Allocations!E15*$Q15 -> 0 | V15: =Allocations!F15*$Q15 -> 0 | W15: =Allocations!G15*$Q15 -> 0 | X15: =Allocations!H15*$Q15 -> 0 | Y15: =Allocations!I15*$Q15 -> 0 | Z15: =Allocations!J15*$Q15 -> 0 | AA15: =Allocations!K15*$Q15 -> 0 | AB15: =Allocations!L15*$Q15 -> 0 | ... AV15: =Allocations!AF15*$Q15 -> 0 | AW15: =Allocations!AF15*$Q15 -> 0 | AX15: =Allocations!AG15*$Q15 -> 0 | AY15: =Allocations!AH15*$Q15 -> 0 | AZ15: =Allocations!AI15*$Q15 -> 0 | BA15: =Allocations!AJ15*$Q15 -> 0 | BB15: =Allocations!AK15*$Q15 -> 0 | BC15: =SUM(U15:BB15) -> 0 | BD15: =Q15-BC15 -> 0 | BE15: =B15 -> Bizi, Raymond
A16: =Allocations!A16 -> 10 | B16: =Allocations!B16 -> BROWN,Denise- Wrap | C16: =Allocations!C16 -> Abbott | D16: =Allocations!#REF! -> #REF! | Q16: =SUM(E16:J16) -> 0 | R16: =E16 -> 0 | T16: 0 | U16: =Allocations!E16*$Q16 -> 0 | V16: =Allocations!F16*$Q16 -> 0 | W16: =Allocations!G16*$Q16 -> 0 | X16: =Allocations!H16*$Q16 -> 0 | Y16: =Allocations!I16*$Q16 -> 0 | Z16: =Allocations!J16*$Q16 -> 0 | AA16: =Allocations!K16*$Q16 -> 0 | AB16: =Allocations!L16*$Q16 -> 0 | ... AV16: =Allocations!AF16*$Q16 -> 0 | AW16: =Allocations!AF16*$Q16 -> 0 | AX16: =Allocations!AG16*$Q16 -> 0 | AY16: =Allocations!AH16*$Q16 -> 0 | AZ16: =Allocations!AI16*$Q16 -> 0 | BA16: =Allocations!AJ16*$Q16 -> 0 | BB16: =Allocations!AK16*$Q16 -> 0 | BC16: =SUM(U16:BB16) -> 0 | BD16: =Q16-BC16 -> 0 | BE16: =B16 -> BROWN,Denise- Wrap
A17: =Allocations!A17 -> 11 | B17: =Allocations!B17 -> BROWN,Denise - Summer | C17: =Allocations!C17 -> Abbott | Q17: =SUM(E17:J17) -> 0 | R17: =E17 -> 0 | U17: =Allocations!E17*$Q17 -> 0 | V17: =Allocations!F17*$Q17 -> 0 | W17: =Allocations!G17*$Q17 -> 0 | X17: =Allocations!H17*$Q17 -> 0 | Y17: =Allocations!I17*$Q17 -> 0 | Z17: =Allocations!J17*$Q17 -> 0 | AA17: =Allocations!K17*$Q17 -> 0 | AB17: =Allocations!L17*$Q17 -> 0 | ... AV17: =Allocations!AF17*$Q17 -> 0 | AW17: =Allocations!AF17*$Q17 -> 0 | AX17: =Allocations!AG17*$Q17 -> 0 | AY17: =Allocations!AH17*$Q17 -> 0 | AZ17: =Allocations!AI17*$Q17 -> 0 | BA17: =Allocations!AJ17*$Q17 -> 0 | BB17: =Allocations!AK17*$Q17 -> 0 | BC17: =SUM(U17:BB17) -> 0 | BD17: =Q17-BC17 -> 0 | BE17: =B17 -> BROWN,Denise - Summer
A18: =Allocations!A18 -> 12 | B18: =Allocations!B18 -> BRYANT, Roni- Summer | C18: =Allocations!C18 -> Abbott | D18: =Allocations!#REF! -> #REF! | Q18: =SUM(E18:J18) -> 0 | R18: =E18 -> 0 | T18: 0 | U18: =Allocations!E18*$Q18 -> 0 | V18: =Allocations!F18*$Q18 -> 0 | W18: =Allocations!G18*$Q18 -> 0 | X18: =Allocations!H18*$Q18 -> 0 | Y18: =Allocations!I18*$Q18 -> 0 | Z18: =Allocations!J18*$Q18 -> 0 | AA18: =Allocations!K18*$Q18 -> 0 | AB18: =Allocations!L18*$Q18 -> 0 | ... AV18: =Allocations!AF18*$Q18 -> 0 | AW18: =Allocations!AF18*$Q18 -> 0 | AX18: =Allocations!AG18*$Q18 -> 0 | AY18: =Allocations!AH18*$Q18 -> 0 | AZ18: =Allocations!AI18*$Q18 -> 0 | BA18: =Allocations!AJ18*$Q18 -> 0 | BB18: =Allocations!AK18*$Q18 -> 0 | BC18: =SUM(U18:BB18) -> 0 | BD18: =Q18-BC18 -> 0 | BE18: =B18 -> BRYANT, Roni- Summer
A19: =Allocations!A19 -> 13 | B19: =Allocations!B19 -> BRYANT, Roni | C19: =Allocations!C19 -> Abbott | E19: 879.21 | F19: 879.21 | G19: 879.21 | H19: 879.21 | I19: 879.21 | J19: 879.21 | K19: 879.21 | L19: 879.21 | M19: 879.21 | N19: 879.21 | O19: 865.47 | P19: 865.47 | Q19: =SUM(E19:J19) -> 5275.26 | R19: =E19 -> 879.21 | T19: 1 | U19: =Allocations!E19*$Q19 -> 0 | V19: =Allocations!F19*$Q19 -> 5275.26 | W19: =Allocations!G19*$Q19 -> 0 | X19: =Allocations!H19*$Q19 -> 0 | Y19: =Allocations!I19*$Q19 -> 0 | Z19: =Allocations!J19*$Q19 -> 0 | AA19: =Allocations!K19*$Q19 -> 0 | AB19: =Allocations!L19*$Q19 -> 0 | ... AV19: =Allocations!AF19*$Q19 -> 0 | AW19: =Allocations!AF19*$Q19 -> 0 | AX19: =Allocations!AG19*$Q19 -> 0 | AY19: =Allocations!AH19*$Q19 -> 0 | AZ19: =Allocations!AI19*$Q19 -> 0 | BA19: =Allocations!AJ19*$Q19 -> 0 | BB19: =Allocations!AK19*$Q19 -> 0 | BC19: =SUM(U19:BB19) -> 5275.26 | BD19: =Q19-BC19 -> 0 | BE19: =B19 -> BRYANT, Roni
A20: =Allocations!A20 -> 14 | B20: =Allocations!B20 -> BUTLER, Ciji | C20: =Allocations!C20 -> USJP | D20: =Allocations!#REF! -> #REF! | G20: 1370.88 | H20: 663.33 | I20: 663.33 | J20: -685.44 | K20: -685.44 | Q20: =SUM(E20:J20) -> 2012.1 | R20: =E20 -> 0 | T20: 0 | U20: =Allocations!E20*$Q20 -> 0 | V20: =Allocations!F20*$Q20 -> 0 | W20: =Allocations!G20*$Q20 -> 0 | X20: =Allocations!H20*$Q20 -> 0 | Y20: =Allocations!I20*$Q20 -> 0 | Z20: =Allocations!J20*$Q20 -> 0 | AA20: =Allocations!K20*$Q20 -> 0 | AB20: =Allocations!L20*$Q20 -> 0 | ... AV20: =Allocations!AF20*$Q20 -> 0 | AW20: =Allocations!AF20*$Q20 -> 0 | AX20: =Allocations!AG20*$Q20 -> 0 | AY20: =Allocations!AH20*$Q20 -> 0 | AZ20: =Allocations!AI20*$Q20 -> 0 | BA20: =Allocations!AJ20*$Q20 -> 0 | BB20: =Allocations!AK20*$Q20 -> 0 | BC20: =SUM(U20:BB20) -> 2012.1 | BD20: =Q20-BC20 -> 0 | BE20: =B20 -> BUTLER, Ciji
A21: =Allocations!A21 -> 15 | B21: =Allocations!B21 -> CAMPBELL, Nikiesha K. | C21: =Allocations!C21 -> Americorp | D21: =Allocations!#REF! -> #REF! | Q21: =SUM(E21:J21) -> 0 | R21: =E21 -> 0 | T21: 0 | U21: =Allocations!E21*$Q21 -> 0 | V21: =Allocations!F21*$Q21 -> 0 | W21: =Allocations!G21*$Q21 -> 0 | X21: =Allocations!H21*$Q21 -> 0 | Y21: =Allocations!I21*$Q21 -> 0 | Z21: =Allocations!J21*$Q21 -> 0 | AA21: =Allocations!K21*$Q21 -> 0 | AB21: =Allocations!L21*$Q21 -> 0 | ... AV21: =Allocations!AF21*$Q21 -> 0 | AW21: =Allocations!AF21*$Q21 -> 0 | AX21: =Allocations!AG21*$Q21 -> 0 | AY21: =Allocations!AH21*$Q21 -> 0 | AZ21: =Allocations!AI21*$Q21 -> 0 | BA21: =Allocations!AJ21*$Q21 -> 0 | BB21: =Allocations!AK21*$Q21 -> 0 | BC21: =SUM(U21:BB21) -> 0 | BD21: =Q21-BC21 -> 0 | BE21: =B21 -> CAMPBELL, Nikiesha K.
A22: =Allocations!A22 -> 16 | B22: =Allocations!B22 -> CASTELLANOS, Rita J. | C22: =Allocations!C22 -> Abbott | D22: =Allocations!#REF! -> #REF! | Q22: =SUM(E22:J22) -> 0 | R22: =E22 -> 0 | S22: =R22/Q22 -> #DIV/0! | T22: 0 | U22: =Allocations!E22*$Q22 -> 0 | V22: =Allocations!F22*$Q22 -> 0 | W22: =Allocations!G22*$Q22 -> 0 | X22: =Allocations!H22*$Q22 -> 0 | Y22: =Allocations!I22*$Q22 -> 0 | Z22: =Allocations!J22*$Q22 -> 0 | AA22: =Allocations!K22*$Q22 -> 0 | AB22: =Allocations!L22*$Q22 -> 0 | ... AV22: =Allocations!AF22*$Q22 -> 0 | AW22: =Allocations!AF22*$Q22 -> 0 | AX22: =Allocations!AG22*$Q22 -> 0 | AY22: =Allocations!AH22*$Q22 -> 0 | AZ22: =Allocations!AI22*$Q22 -> 0 | BA22: =Allocations!AJ22*$Q22 -> 0 | BB22: =Allocations!AK22*$Q22 -> 0 | BC22: =SUM(U22:BB22) -> 0 | BD22: =Q22-BC22 -> 0 | BE22: =B22 -> CASTELLANOS, Rita J.
A23: =Allocations!A23 -> 17 | B23: =Allocations!B23 -> CERNA, Irene | C23: =Allocations!C23 -> USJP | D23: =Allocations!#REF! -> #REF! | E23: 1118.65 | F23: 1118.65 | G23: 1118.65 | H23: 1118.65 | I23: 1118.65 | J23: 1118.65 | K23: 1118.65 | L23: 1118.65 | M23: 1118.65 | N23: 1118.65 | O23: 1068.35 | P23: 1068.35 | Q23: =SUM(E23:J23) -> 6711.9 | R23: =E23 -> 1118.65 | T23: 0 | U23: =Allocations!E23*$Q23 -> 0 | V23: =Allocations!F23*$Q23 -> 0 | W23: =Allocations!G23*$Q23 -> 0 | X23: =Allocations!H23*$Q23 -> 0 | Y23: =Allocations!I23*$Q23 -> 0 | Z23: =Allocations!J23*$Q23 -> 0 | AA23: =Allocations!K23*$Q23 -> 0 | AB23: =Allocations!L23*$Q23 -> 0 | ... AV23: =Allocations!AF23*$Q23 -> 0 | AW23: =Allocations!AF23*$Q23 -> 0 | AX23: =Allocations!AG23*$Q23 -> 0 | AY23: =Allocations!AH23*$Q23 -> 0 | AZ23: =Allocations!AI23*$Q23 -> 0 | BA23: =Allocations!AJ23*$Q23 -> 0 | BB23: =Allocations!AK23*$Q23 -> 0 | BC23: =SUM(U23:BB23) -> 6711.9 | BD23: =Q23-BC23 -> 0 | BE23: =B23 -> CERNA, Irene
A24: =Allocations!A24 -> 18 | B24: =Allocations!B24 -> COLEMAN, Zabrina J. | C24: =Allocations!C24 -> EHS | E24: 760.48 | F24: 760.48 | G24: 760.48 | H24: 760.48 | I24: 760.48 | J24: 760.48 | K24: 760.48 | L24: 760.48 | M24: 760.48 | Q24: =SUM(E24:J24) -> 4562.88 | R24: =E24 -> 760.48 | T24: 1 | U24: =Allocations!E24*$Q24 -> 0 | V24: =Allocations!F24*$Q24 -> 0 | W24: =Allocations!G24*$Q24 -> 0 | X24: =Allocations!H24*$Q24 -> 0 | Y24: =Allocations!I24*$Q24 -> 0 | Z24: =Allocations!J24*$Q24 -> 4562.88 | AA24: =Allocations!K24*$Q24 -> 0 | AB24: =Allocations!L24*$Q24 -> 0 | ... AV24: =Allocations!AF24*$Q24 -> 0 | AW24: =Allocations!AF24*$Q24 -> 0 | AX24: =Allocations!AG24*$Q24 -> 0 | AY24: =Allocations!AH24*$Q24 -> 0 | AZ24: =Allocations!AI24*$Q24 -> 0 | BA24: =Allocations!AJ24*$Q24 -> 0 | BB24: =Allocations!AK24*$Q24 -> 0 | BC24: =SUM(U24:BB24) -> 4562.88 | BD24: =Q24-BC24 -> 0 | BE24: =B24 -> COLEMAN, Zabrina J.
A25: =Allocations!A25 -> 19 | B25: =Allocations!B25 -> COOPER, Cassandra June 30 | C25: =Allocations!C25 -> OICA | D25: =Allocations!#REF! -> #REF! | Q25: =SUM(E25:J25) -> 0 | R25: =E25 -> 0 | S25: =R25/Q25 -> #DIV/0! | T25: 0 | U25: =Allocations!E25*$Q25 -> 0 | V25: =Allocations!F25*$Q25 -> 0 | W25: =Allocations!G25*$Q25 -> 0 | X25: =Allocations!H25*$Q25 -> 0 | Y25: =Allocations!I25*$Q25 -> 0 | Z25: =Allocations!J25*$Q25 -> 0 | AA25: =Allocations!K25*$Q25 -> 0 | AB25: =Allocations!L25*$Q25 -> 0 | ... AV25: =Allocations!AF25*$Q25 -> 0 | AW25: =Allocations!AF25*$Q25 -> 0 | AX25: =Allocations!AG25*$Q25 -> 0 | AY25: =Allocations!AH25*$Q25 -> 0 | AZ25: =Allocations!AI25*$Q25 -> 0 | BA25: =Allocations!AJ25*$Q25 -> 0 | BB25: =Allocations!AK25*$Q25 -> 0 | BC25: =SUM(U25:BB25) -> 0 | BD25: =Q25-BC25 -> 0 | BE25: =B25 -> COOPER, Cassandra June 30 | BT25: =Allocations!#REF! -> #REF! | BU25: =Allocations!#REF! -> #REF! | BV25: =Allocations!#REF! -> #REF! | BW25: =Allocations!#REF! -> #REF! | BX25: =Allocations!#REF! -> #REF! | BY25: =Allocations!#REF! -> #REF! | BZ25: =Allocations!#REF! -> #REF! | CA25: =Allocations!#REF! -> #REF! | ... XEH25: =Allocations!#REF! -> #REF!
A26: =Allocations!A26 -> 20 | B26: =Allocations!B26 -> COOPER, Cassandra July | C26: =Allocations!C26 -> FOC, ESG | Q26: =SUM(E26:J26) -> 0 | R26: =E26 -> 0 | U26: =Allocations!E26*$Q26 -> 0 | V26: =Allocations!F26*$Q26 -> 0 | W26: =Allocations!G26*$Q26 -> 0 | X26: =Allocations!H26*$Q26 -> 0 | Y26: =Allocations!I26*$Q26 -> 0 | Z26: =Allocations!J26*$Q26 -> 0 | AA26: =Allocations!K26*$Q26 -> 0 | AB26: =Allocations!L26*$Q26 -> 0 | ... AV26: =Allocations!AF26*$Q26 -> 0 | AW26: =Allocations!AF26*$Q26 -> 0 | AX26: =Allocations!AG26*$Q26 -> 0 | AY26: =Allocations!AH26*$Q26 -> 0 | AZ26: =Allocations!AI26*$Q26 -> 0 | BA26: =Allocations!AJ26*$Q26 -> 0 | BB26: =Allocations!AK26*$Q26 -> 0 | BC26: =SUM(U26:BB26) -> 0 | BD26: =Q26-BC26 -> 0 | BE26: =B26 -> COOPER, Cassandra July
A27: =Allocations!A27 -> 21 | B27: =Allocations!B27 -> Counts, Monique Lamae | C27: =Allocations!C27 -> Americorp | D27: =Allocations!#REF! -> #REF! | Q27: =SUM(E27:J27) -> 0 | R27: =E27 -> 0 | T27: 0 | U27: =Allocations!E27*$Q27 -> 0 | V27: =Allocations!F27*$Q27 -> 0 | W27: =Allocations!G27*$Q27 -> 0 | X27: =Allocations!H27*$Q27 -> 0 | Y27: =Allocations!I27*$Q27 -> 0 | Z27: =Allocations!J27*$Q27 -> 0 | AA27: =Allocations!K27*$Q27 -> 0 | AB27: =Allocations!L27*$Q27 -> 0 | ... AV27: =Allocations!AF27*$Q27 -> 0 | AW27: =Allocations!AF27*$Q27 -> 0 | AX27: =Allocations!AG27*$Q27 -> 0 | AY27: =Allocations!AH27*$Q27 -> 0 | AZ27: =Allocations!AI27*$Q27 -> 0 | BA27: =Allocations!AJ27*$Q27 -> 0 | BB27: =Allocations!AK27*$Q27 -> 0 | BC27: =SUM(U27:BB27) -> 0 | BD27: =Q27-BC27 -> 0 | BE27: =B27 -> Counts, Monique Lamae
A28: =Allocations!A28 -> 22 | B28: =Allocations!B28 -> DANCE-WILSON, Heather | C28: =Allocations!C28 -> Abbott | D28: =Allocations!#REF! -> #REF! | E28: 1635.77 | F28: 1635.77 | G28: 1635.77 | H28: 1635.77 | I28: 1635.77 | J28: 1635.77 | K28: 1635.77 | L28: 1635.77 | M28: 1635.77 | N28: 1635.77 | O28: 1608.63 | P28: 1608.63 | Q28: =SUM(E28:J28) -> 9814.62 | R28: =E28 -> 1635.77 | S28: =R28/Q28 -> 0.16666667 | T28: 0 | U28: =Allocations!E28*$Q28 -> 0 | V28: =Allocations!F28*$Q28 -> 7557.2574 | W28: =Allocations!G28*$Q28 -> 0 | X28: =Allocations!H28*$Q28 -> 2257.3626 | Y28: =Allocations!I28*$Q28 -> 0 | Z28: =Allocations!J28*$Q28 -> 0 | AA28: =Allocations!K28*$Q28 -> 0 | AB28: =Allocations!L28*$Q28 -> 0 | ... AV28: =Allocations!AF28*$Q28 -> 0 | AW28: =Allocations!AF28*$Q28 -> 0 | AX28: =Allocations!AG28*$Q28 -> 0 | AY28: =Allocations!AH28*$Q28 -> 0 | AZ28: =Allocations!AI28*$Q28 -> 0 | BA28: =Allocations!AJ28*$Q28 -> 0 | BB28: =Allocations!AK28*$Q28 -> 0 | BC28: =SUM(U28:BB28) -> 9814.62 | BD28: =Q28-BC28 -> 0 | BE28: =B28 -> DANCE-WILSON, Heather
A29: =Allocations!A29 -> 23 | B29: =Allocations!B29 -> DANIELS-CRAFTON, Glenda | C29: =Allocations!C29 -> EHS | E29: 2200.98 | F29: 2200.98 | G29: 2200.98 | H29: 2200.98 | I29: 2200.98 | J29: 2200.98 | K29: 2200.98 | L29: 2200.98 | M29: 2200.98 | Q29: =SUM(E29:J29) -> 13205.88 | R29: =E29 -> 2200.98 | U29: =Allocations!E29*$Q29 -> 0 | V29: =Allocations!F29*$Q29 -> 0 | W29: =Allocations!G29*$Q29 -> 0 | X29: =Allocations!H29*$Q29 -> 0 | Y29: =Allocations!I29*$Q29 -> 0 | Z29: =Allocations!J29*$Q29 -> 13205.88 | AA29: =Allocations!K29*$Q29 -> 0 | AB29: =Allocations!L29*$Q29 -> 0 | ... AV29: =Allocations!AF29*$Q29 -> 0 | AW29: =Allocations!AF29*$Q29 -> 0 | AX29: =Allocations!AG29*$Q29 -> 0 | AY29: =Allocations!AH29*$Q29 -> 0 | AZ29: =Allocations!AI29*$Q29 -> 0 | BA29: =Allocations!AJ29*$Q29 -> 0 | BB29: =Allocations!AK29*$Q29 -> 0 | BC29: =SUM(U29:BB29) -> 13205.88 | BD29: =Q29-BC29 -> 0 | BE29: =B29 -> DANIELS-CRAFTON, Glenda
A30: =Allocations!A30 -> 24 | B30: =Allocations!B30 -> ELLIS, Joseph | C30: =Allocations!C30 -> OICA | Q30: =SUM(E30:J30) -> 0 | R30: =E30 -> 0 | U30: =Allocations!E30*$Q30 -> 0 | V30: =Allocations!F30*$Q30 -> 0 | W30: =Allocations!G30*$Q30 -> 0 | X30: =Allocations!H30*$Q30 -> 0 | Y30: =Allocations!I30*$Q30 -> 0 | Z30: =Allocations!J30*$Q30 -> 0 | AA30: =Allocations!K30*$Q30 -> 0 | AB30: =Allocations!L30*$Q30 -> 0 | ... AV30: =Allocations!AF30*$Q30 -> 0 | AW30: =Allocations!AF30*$Q30 -> 0 | AX30: =Allocations!AG30*$Q30 -> 0 | AY30: =Allocations!AH30*$Q30 -> 0 | AZ30: =Allocations!AI30*$Q30 -> 0 | BA30: =Allocations!AJ30*$Q30 -> 0 | BB30: =Allocations!AK30*$Q30 -> 0 | BC30: =SUM(U30:BB30) -> 0 | BD30: =Q30-BC30 -> 0 | BE30: =B30 -> ELLIS, Joseph
A31: =Allocations!A31 -> 25 | B31: =Allocations!B31 -> FITZPATRICK, Cynthia E. - Aug 31 | C31: =Allocations!C31 -> EHS | D31: =Allocations!#REF! -> #REF! | E31: 1082.33 | F31: 1082.33 | G31: 1082.33 | H31: 1082.33 | I31: 1082.33 | J31: 1082.33 | K31: 1082.33 | L31: 1082.33 | M31: 1082.33 | N31: 1082.33 | O31: 1068.35 | P31: 1068.35 | Q31: =SUM(E31:J31) -> 6493.98 | R31: =E31 -> 1082.33 | T31: 0 | U31: =Allocations!E31*$Q31 -> 0 | V31: =Allocations!F31*$Q31 -> 0 | W31: =Allocations!G31*$Q31 -> 0 | X31: =Allocations!H31*$Q31 -> 0 | Y31: =Allocations!I31*$Q31 -> 0 | Z31: =Allocations!J31*$Q31 -> 6493.98 | AA31: =Allocations!K31*$Q31 -> 0 | AB31: =Allocations!L31*$Q31 -> 0 | ... AV31: =Allocations!AF31*$Q31 -> 0 | AW31: =Allocations!AF31*$Q31 -> 0 | AX31: =Allocations!AG31*$Q31 -> 0 | AY31: =Allocations!AH31*$Q31 -> 0 | AZ31: =Allocations!AI31*$Q31 -> 0 | BA31: =Allocations!AJ31*$Q31 -> 0 | BB31: =Allocations!AK31*$Q31 -> 0 | BC31: =SUM(U31:BB31) -> 6493.98 | BD31: =Q31-BC31 -> 0 | BE31: =B31 -> FITZPATRICK, Cynthia E. - Aug 31
A32: =Allocations!A32 -> 26 | B32: =Allocations!B32 -> FITZPATRICK, Cynthia E. - Toddlers | Q32: =SUM(E32:J32) -> 0 | R32: =E32 -> 0 | U32: =Allocations!E32*$Q32 -> 0 | V32: =Allocations!F32*$Q32 -> 0 | W32: =Allocations!G32*$Q32 -> 0 | X32: =Allocations!H32*$Q32 -> 0 | Y32: =Allocations!I32*$Q32 -> 0 | Z32: =Allocations!J32*$Q32 -> 0 | AA32: =Allocations!K32*$Q32 -> 0 | AB32: =Allocations!L32*$Q32 -> 0 | ... AV32: =Allocations!AF32*$Q32 -> 0 | AW32: =Allocations!AF32*$Q32 -> 0 | AX32: =Allocations!AG32*$Q32 -> 0 | AY32: =Allocations!AH32*$Q32 -> 0 | AZ32: =Allocations!AI32*$Q32 -> 0 | BA32: =Allocations!AJ32*$Q32 -> 0 | BB32: =Allocations!AK32*$Q32 -> 0 | BC32: =SUM(U32:BB32) -> 0 | BD32: =Q32-BC32 -> 0 | BE32: =B32 -> FITZPATRICK, Cynthia E. - Toddlers
A33: =Allocations!A33 -> 27 | B33: =Allocations!B33 -> FRANCOIS, Darlene | C33: =Allocations!C33 -> Americorp | D33: =Allocations!#REF! -> #REF! | Q33: =SUM(E33:J33) -> 0 | R33: =E33 -> 0 | T33: 0 | U33: =Allocations!E33*$Q33 -> 0 | V33: =Allocations!F33*$Q33 -> 0 | W33: =Allocations!G33*$Q33 -> 0 | X33: =Allocations!H33*$Q33 -> 0 | Y33: =Allocations!I33*$Q33 -> 0 | Z33: =Allocations!J33*$Q33 -> 0 | AA33: =Allocations!K33*$Q33 -> 0 | AB33: =Allocations!L33*$Q33 -> 0 | ... AV33: =Allocations!AF33*$Q33 -> 0 | AW33: =Allocations!AF33*$Q33 -> 0 | AX33: =Allocations!AG33*$Q33 -> 0 | AY33: =Allocations!AH33*$Q33 -> 0 | AZ33: =Allocations!AI33*$Q33 -> 0 | BA33: =Allocations!AJ33*$Q33 -> 0 | BB33: =Allocations!AK33*$Q33 -> 0 | BC33: =SUM(U33:BB33) -> 0 | BD33: =Q33-BC33 -> 0 | BE33: =B33 -> FRANCOIS, Darlene
A34: =Allocations!A34 -> 28 | B34: =Allocations!B34 -> FRASER, Vivian Cox | C34: =Allocations!C34 -> Admin | D34: =Allocations!#REF! -> #REF! | Q34: =SUM(E34:J34) -> 0 | R34: =E34 -> 0 | T34: 0 | U34: =Allocations!E34*$Q34 -> 0 | V34: =Allocations!F34*$Q34 -> 0 | W34: =Allocations!G34*$Q34 -> 0 | X34: =Allocations!H34*$Q34 -> 0 | Y34: =Allocations!I34*$Q34 -> 0 | Z34: =Allocations!J34*$Q34 -> 0 | AA34: =Allocations!K34*$Q34 -> 0 | AB34: =Allocations!L34*$Q34 -> 0 | ... AV34: =Allocations!AF34*$Q34 -> 0 | AW34: =Allocations!AF34*$Q34 -> 0 | AX34: =Allocations!AG34*$Q34 -> 0 | AY34: =Allocations!AH34*$Q34 -> 0 | AZ34: =Allocations!AI34*$Q34 -> 0 | BA34: =Allocations!AJ34*$Q34 -> 0 | BB34: =Allocations!AK34*$Q34 -> 0 | BC34: =SUM(U34:BB34) -> 0 | BD34: =Q34-BC34 -> 0 | BE34: =B34 -> FRASER, Vivian Cox
A35: =Allocations!A35 -> 29 | B35: =Allocations!B35 -> FRASER, Vivian Cox- July | C35: =Allocations!C35 -> Admin | Q35: =SUM(E35:J35) -> 0 | R35: =E35 -> 0 | U35: =Allocations!E35*$Q35 -> 0 | V35: =Allocations!F35*$Q35 -> 0 | W35: =Allocations!G35*$Q35 -> 0 | X35: =Allocations!H35*$Q35 -> 0 | Y35: =Allocations!I35*$Q35 -> 0 | Z35: =Allocations!J35*$Q35 -> 0 | AA35: =Allocations!K35*$Q35 -> 0 | AB35: =Allocations!L35*$Q35 -> 0 | ... AV35: =Allocations!AF35*$Q35 -> 0 | AW35: =Allocations!AF35*$Q35 -> 0 | AX35: =Allocations!AG35*$Q35 -> 0 | AY35: =Allocations!AH35*$Q35 -> 0 | AZ35: =Allocations!AI35*$Q35 -> 0 | BA35: =Allocations!AJ35*$Q35 -> 0 | BB35: =Allocations!AK35*$Q35 -> 0 | BC35: =SUM(U35:BB35) -> 0 | BD35: =Q35-BC35 -> 0 | BE35: =B35 -> FRASER, Vivian Cox- July
A36: =Allocations!A36 -> 30 | B36: =Allocations!B36 -> FRAZIER, Alice | C36: =Allocations!C36 -> Workforce | Q36: =SUM(E36:J36) -> 0 | R36: =E36 -> 0 | U36: =Allocations!E36*$Q36 -> 0 | V36: =Allocations!F36*$Q36 -> 0 | W36: =Allocations!G36*$Q36 -> 0 | X36: =Allocations!H36*$Q36 -> 0 | Y36: =Allocations!I36*$Q36 -> 0 | Z36: =Allocations!J36*$Q36 -> 0 | AA36: =Allocations!K36*$Q36 -> 0 | AB36: =Allocations!L36*$Q36 -> 0 | ... AV36: =Allocations!AF36*$Q36 -> 0 | AW36: =Allocations!AF36*$Q36 -> 0 | AX36: =Allocations!AG36*$Q36 -> 0 | AY36: =Allocations!AH36*$Q36 -> 0 | AZ36: =Allocations!AI36*$Q36 -> 0 | BA36: =Allocations!AJ36*$Q36 -> 0 | BB36: =Allocations!AK36*$Q36 -> 0 | BC36: =SUM(U36:BB36) -> 0 | BD36: =Q36-BC36 -> 0 | BE36: =B36 -> FRAZIER, Alice
A37: =Allocations!A37 -> 31 | B37: =Allocations!B37 -> Freeman, Jibri | C37: =Allocations!C37 -> Americorp | D37: =Allocations!#REF! -> #REF! | Q37: =SUM(E37:J37) -> 0 | R37: =E37 -> 0 | T37: 0 | U37: =Allocations!E37*$Q37 -> 0 | V37: =Allocations!F37*$Q37 -> 0 | W37: =Allocations!G37*$Q37 -> 0 | X37: =Allocations!H37*$Q37 -> 0 | Y37: =Allocations!I37*$Q37 -> 0 | Z37: =Allocations!J37*$Q37 -> 0 | AA37: =Allocations!K37*$Q37 -> 0 | AB37: =Allocations!L37*$Q37 -> 0 | ... AV37: =Allocations!AF37*$Q37 -> 0 | AW37: =Allocations!AF37*$Q37 -> 0 | AX37: =Allocations!AG37*$Q37 -> 0 | AY37: =Allocations!AH37*$Q37 -> 0 | AZ37: =Allocations!AI37*$Q37 -> 0 | BA37: =Allocations!AJ37*$Q37 -> 0 | BB37: =Allocations!AK37*$Q37 -> 0 | BC37: =SUM(U37:BB37) -> 0 | BD37: =Q37-BC37 -> 0 | BE37: =B37 -> Freeman, Jibri
A38: =Allocations!A38 -> 32 | B38: =Allocations!B38 -> GARRETT, Dorian S. | C38: =Allocations!C38 -> EHS | D38: E | E38: 668.74 | F38: 668.74 | G38: 668.74 | H38: 668.74 | I38: 668.74 | J38: 668.74 | K38: 668.74 | L38: 668.74 | M38: 668.74 | Q38: =SUM(E38:J38) -> 4012.44 | R38: =E38 -> 668.74 | T38: 0 | U38: =Allocations!E38*$Q38 -> 0 | V38: =Allocations!F38*$Q38 -> 0 | W38: =Allocations!G38*$Q38 -> 0 | X38: =Allocations!H38*$Q38 -> 0 | Y38: =Allocations!I38*$Q38 -> 0 | Z38: =Allocations!J38*$Q38 -> 4012.44 | AA38: =Allocations!K38*$Q38 -> 0 | AB38: =Allocations!L38*$Q38 -> 0 | ... AV38: =Allocations!AF38*$Q38 -> 0 | AW38: =Allocations!AF38*$Q38 -> 0 | AX38: =Allocations!AG38*$Q38 -> 0 | AY38: =Allocations!AH38*$Q38 -> 0 | AZ38: =Allocations!AI38*$Q38 -> 0 | BA38: =Allocations!AJ38*$Q38 -> 0 | BB38: =Allocations!AK38*$Q38 -> 0 | BC38: =SUM(U38:BB38) -> 4012.44 | BD38: =Q38-BC38 -> 0 | BE38: =B38 -> GARRETT, Dorian S.
A39: =Allocations!A39 -> 33 | B39: =Allocations!B39 -> GARRETT, Shakia | C39: =Allocations!C39 -> EHS | Q39: =SUM(E39:J39) -> 0 | R39: =E39 -> 0 | T39: 0 | U39: =Allocations!E39*$Q39 -> 0 | V39: =Allocations!F39*$Q39 -> 0 | W39: =Allocations!G39*$Q39 -> 0 | X39: =Allocations!H39*$Q39 -> 0 | Y39: =Allocations!I39*$Q39 -> 0 | Z39: =Allocations!J39*$Q39 -> 0 | AA39: =Allocations!K39*$Q39 -> 0 | AB39: =Allocations!L39*$Q39 -> 0 | ... AV39: =Allocations!AF39*$Q39 -> 0 | AW39: =Allocations!AF39*$Q39 -> 0 | AX39: =Allocations!AG39*$Q39 -> 0 | AY39: =Allocations!AH39*$Q39 -> 0 | AZ39: =Allocations!AI39*$Q39 -> 0 | BA39: =Allocations!AJ39*$Q39 -> 0 | BB39: =Allocations!AK39*$Q39 -> 0 | BC39: =SUM(U39:BB39) -> 0 | BD39: =Q39-BC39 -> 0 | BE39: =B39 -> GARRETT, Shakia
A40: =Allocations!A40 -> 34 | B40: =Allocations!B40 -> GBAMOKOLLIE, Molly | C40: =Allocations!C40 -> Facilities | Q40: =SUM(E40:J40) -> 0 | R40: =E40 -> 0 | S40: =R40/Q40 -> #DIV/0! | T40: 0 | U40: =Allocations!E40*$Q40 -> 0 | V40: =Allocations!F40*$Q40 -> 0 | W40: =Allocations!G40*$Q40 -> 0 | X40: =Allocations!H40*$Q40 -> 0 | Y40: =Allocations!I40*$Q40 -> 0 | Z40: =Allocations!J40*$Q40 -> 0 | AA40: =Allocations!K40*$Q40 -> 0 | AB40: =Allocations!L40*$Q40 -> 0 | ... AV40: =Allocations!AF40*$Q40 -> 0 | AW40: =Allocations!AF40*$Q40 -> 0 | AX40: =Allocations!AG40*$Q40 -> 0 | AY40: =Allocations!AH40*$Q40 -> 0 | AZ40: =Allocations!AI40*$Q40 -> 0 | BA40: =Allocations!AJ40*$Q40 -> 0 | BB40: =Allocations!AK40*$Q40 -> 0 | BC40: =SUM(U40:BB40) -> 0 | BD40: =Q40-BC40 -> 0 | BE40: =B40 -> GBAMOKOLLIE, Molly
A41: =Allocations!A41 -> 35 | B41: =Allocations!B41 -> GREEN, Yolanda - | C41: =Allocations!C41 -> EHS | E41: 962.13 | F41: 962.13 | G41: 962.13 | H41: 962.13 | I41: 962.13 | J41: 962.13 | K41: 962.13 | L41: 962.13 | M41: 962.13 | N41: 962.13 | O41: 946.06 | P41: 946.06 | Q41: =SUM(E41:J41) -> 5772.78 | R41: =E41 -> 962.13 | T41: 0 | U41: =Allocations!E41*$Q41 -> 0 | V41: =Allocations!F41*$Q41 -> 0 | W41: =Allocations!G41*$Q41 -> 0 | X41: =Allocations!H41*$Q41 -> 0 | Y41: =Allocations!I41*$Q41 -> 0 | Z41: =Allocations!J41*$Q41 -> 5772.78 | AA41: =Allocations!K41*$Q41 -> 0 | AB41: =Allocations!L41*$Q41 -> 0 | ... AV41: =Allocations!AF41*$Q41 -> 0 | AW41: =Allocations!AF41*$Q41 -> 0 | AX41: =Allocations!AG41*$Q41 -> 0 | AY41: =Allocations!AH41*$Q41 -> 0 | AZ41: =Allocations!AI41*$Q41 -> 0 | BA41: =Allocations!AJ41*$Q41 -> 0 | BB41: =Allocations!AK41*$Q41 -> 0 | BC41: =SUM(U41:BB41) -> 5772.78 | BD41: =Q41-BC41 -> 0 | BE41: =B41 -> GREEN, Yolanda -
A42: =Allocations!A42 -> 36 | B42: =Allocations!B42 -> GREEN, Yolanda - Toddlers | C42: EHS | Q42: =SUM(E42:J42) -> 0 | R42: =E42 -> 0 | U42: =Allocations!E42*$Q42 -> 0 | V42: =Allocations!F42*$Q42 -> 0 | W42: =Allocations!G42*$Q42 -> 0 | X42: =Allocations!H42*$Q42 -> 0 | Y42: =Allocations!I42*$Q42 -> 0 | Z42: =Allocations!J42*$Q42 -> 0 | AA42: =Allocations!K42*$Q42 -> 0 | AB42: =Allocations!L42*$Q42 -> 0 | ... AV42: =Allocations!AF42*$Q42 -> 0 | AW42: =Allocations!AF42*$Q42 -> 0 | AX42: =Allocations!AG42*$Q42 -> 0 | AY42: =Allocations!AH42*$Q42 -> 0 | AZ42: =Allocations!AI42*$Q42 -> 0 | BA42: =Allocations!AJ42*$Q42 -> 0 | BB42: =Allocations!AK42*$Q42 -> 0 | BC42: =SUM(U42:BB42) -> 0 | BD42: =Q42-BC42 -> 0 | BE42: =B42 -> GREEN, Yolanda - Toddlers
A43: =Allocations!A43 -> 37 | B43: =Allocations!B43 -> HAMILTON, Marchetta | C43: =Allocations!C43 -> EHS | Q43: =SUM(E43:J43) -> 0 | R43: =E43 -> 0 | T43: 0 | U43: =Allocations!E43*$Q43 -> 0 | V43: =Allocations!F43*$Q43 -> 0 | W43: =Allocations!G43*$Q43 -> 0 | X43: =Allocations!H43*$Q43 -> 0 | Y43: =Allocations!I43*$Q43 -> 0 | Z43: =Allocations!J43*$Q43 -> 0 | AA43: =Allocations!K43*$Q43 -> 0 | AB43: =Allocations!L43*$Q43 -> 0 | ... AV43: =Allocations!AF43*$Q43 -> 0 | AW43: =Allocations!AF43*$Q43 -> 0 | AX43: =Allocations!AG43*$Q43 -> 0 | AY43: =Allocations!AH43*$Q43 -> 0 | AZ43: =Allocations!AI43*$Q43 -> 0 | BA43: =Allocations!AJ43*$Q43 -> 0 | BB43: =Allocations!AK43*$Q43 -> 0 | BC43: =SUM(U43:BB43) -> 0 | BD43: =Q43-BC43 -> 0 | BE43: =B43 -> HAMILTON, Marchetta
A44: =Allocations!A44 -> 38 | B44: =Allocations!B44 -> HERBERT, Marina R. | C44: =Allocations!C44 -> EHS | E44: 828.18 | F44: 828.18 | G44: 828.18 | H44: 828.18 | I44: 828.18 | J44: 828.18 | K44: 828.18 | L44: 828.18 | M44: 828.18 | Q44: =SUM(E44:J44) -> 4969.08 | R44: =E44 -> 828.18 | S44: =R44/Q44 -> 0.16666667 | T44: 0 | U44: =Allocations!E44*$Q44 -> 0 | V44: =Allocations!F44*$Q44 -> 0 | W44: =Allocations!G44*$Q44 -> 0 | X44: =Allocations!H44*$Q44 -> 0 | Y44: =Allocations!I44*$Q44 -> 0 | Z44: =Allocations!J44*$Q44 -> 4969.08 | AA44: =Allocations!K44*$Q44 -> 0 | AB44: =Allocations!L44*$Q44 -> 0 | ... AV44: =Allocations!AF44*$Q44 -> 0 | AW44: =Allocations!AF44*$Q44 -> 0 | AX44: =Allocations!AG44*$Q44 -> 0 | AY44: =Allocations!AH44*$Q44 -> 0 | AZ44: =Allocations!AI44*$Q44 -> 0 | BA44: =Allocations!AJ44*$Q44 -> 0 | BB44: =Allocations!AK44*$Q44 -> 0 | BC44: =SUM(U44:BB44) -> 4969.08 | BD44: =Q44-BC44 -> 0 | BE44: =B44 -> HERBERT, Marina R.
A45: =Allocations!A45 -> 39 | B45: =Allocations!B45 -> HIGGINS, Rosa M. April | C45: =Allocations!C45 -> FOC | Q45: =SUM(E45:J45) -> 0 | R45: =E45 -> 0 | T45: 0 | U45: =Allocations!E45*$Q45 -> 0 | V45: =Allocations!F45*$Q45 -> 0 | W45: =Allocations!G45*$Q45 -> 0 | X45: =Allocations!H45*$Q45 -> 0 | Y45: =Allocations!I45*$Q45 -> 0 | Z45: =Allocations!J45*$Q45 -> 0 | AA45: =Allocations!K45*$Q45 -> 0 | AB45: =Allocations!L45*$Q45 -> 0 | ... AV45: =Allocations!AF45*$Q45 -> 0 | AW45: =Allocations!AF45*$Q45 -> 0 | AX45: =Allocations!AG45*$Q45 -> 0 | AY45: =Allocations!AH45*$Q45 -> 0 | AZ45: =Allocations!AI45*$Q45 -> 0 | BA45: =Allocations!AJ45*$Q45 -> 0 | BB45: =Allocations!AK45*$Q45 -> 0 | BC45: =SUM(U45:BB45) -> 0 | BD45: =Q45-BC45 -> 0 | BE45: =B45 -> HIGGINS, Rosa M. April
A46: =Allocations!A46 -> 40 | B46: =Allocations!B46 -> HIGGINS, Rosa M. May 1 | C46: =Allocations!C46 -> FOC | Q46: =SUM(E46:J46) -> 0 | R46: =E46 -> 0 | U46: =Allocations!E46*$Q46 -> 0 | V46: =Allocations!F46*$Q46 -> 0 | W46: =Allocations!G46*$Q46 -> 0 | X46: =Allocations!H46*$Q46 -> 0 | Y46: =Allocations!I46*$Q46 -> 0 | Z46: =Allocations!J46*$Q46 -> 0 | AA46: =Allocations!K46*$Q46 -> 0 | AB46: =Allocations!L46*$Q46 -> 0 | ... AV46: =Allocations!AF46*$Q46 -> 0 | AW46: =Allocations!AF46*$Q46 -> 0 | AX46: =Allocations!AG46*$Q46 -> 0 | AY46: =Allocations!AH46*$Q46 -> 0 | AZ46: =Allocations!AI46*$Q46 -> 0 | BA46: =Allocations!AJ46*$Q46 -> 0 | BB46: =Allocations!AK46*$Q46 -> 0 | BC46: =SUM(U46:BB46) -> 0 | BD46: =Q46-BC46 -> 0 | BE46: =B46 -> HIGGINS, Rosa M. May 1
A47: =Allocations!A47 -> 41 | B47: =Allocations!B47 -> HIGGINS, Rosa M. July | C47: =Allocations!C47 -> LISC, CDBG irvington | Q47: =SUM(E47:J47) -> 0 | R47: =E47 -> 0 | U47: =Allocations!E47*$Q47 -> 0 | V47: =Allocations!F47*$Q47 -> 0 | W47: =Allocations!G47*$Q47 -> 0 | X47: =Allocations!H47*$Q47 -> 0 | Y47: =Allocations!I47*$Q47 -> 0 | Z47: =Allocations!J47*$Q47 -> 0 | AA47: =Allocations!K47*$Q47 -> 0 | AB47: =Allocations!L47*$Q47 -> 0 | ... AV47: =Allocations!AF47*$Q47 -> 0 | AW47: =Allocations!AF47*$Q47 -> 0 | AX47: =Allocations!AG47*$Q47 -> 0 | AY47: =Allocations!AH47*$Q47 -> 0 | AZ47: =Allocations!AI47*$Q47 -> 0 | BA47: =Allocations!AJ47*$Q47 -> 0 | BB47: =Allocations!AK47*$Q47 -> 0 | BC47: =SUM(U47:BB47) -> 0 | BD47: =Q47-BC47 -> 0 | BE47: =B47 -> HIGGINS, Rosa M. July
A48: =Allocations!A48 -> 42 | B48: =Allocations!B48 -> HILL, Katina | C48: =Allocations!C48 -> EHS | Q48: =SUM(E48:J48) -> 0 | R48: =E48 -> 0 | T48: 0 | U48: =Allocations!E48*$Q48 -> 0 | V48: =Allocations!F48*$Q48 -> 0 | W48: =Allocations!G48*$Q48 -> 0 | X48: =Allocations!H48*$Q48 -> 0 | Y48: =Allocations!I48*$Q48 -> 0 | Z48: =Allocations!J48*$Q48 -> 0 | AA48: =Allocations!K48*$Q48 -> 0 | AB48: =Allocations!L48*$Q48 -> 0 | ... AV48: =Allocations!AF48*$Q48 -> 0 | AW48: =Allocations!AF48*$Q48 -> 0 | AX48: =Allocations!AG48*$Q48 -> 0 | AY48: =Allocations!AH48*$Q48 -> 0 | AZ48: =Allocations!AI48*$Q48 -> 0 | BA48: =Allocations!AJ48*$Q48 -> 0 | BB48: =Allocations!AK48*$Q48 -> 0 | BC48: =SUM(U48:BB48) -> 0 | BD48: =Q48-BC48 -> 0 | BE48: =B48 -> HILL, Katina
A49: =Allocations!A49 -> 43 | B49: =Allocations!B49 -> HILL, Nyjira | C49: =Allocations!C49 -> EHS | Q49: =SUM(E49:J49) -> 0 | R49: =E49 -> 0 | T49: 0 | U49: =Allocations!E49*$Q49 -> 0 | V49: =Allocations!F49*$Q49 -> 0 | W49: =Allocations!G49*$Q49 -> 0 | X49: =Allocations!H49*$Q49 -> 0 | Y49: =Allocations!I49*$Q49 -> 0 | Z49: =Allocations!J49*$Q49 -> 0 | AA49: =Allocations!K49*$Q49 -> 0 | AB49: =Allocations!L49*$Q49 -> 0 | ... AV49: =Allocations!AF49*$Q49 -> 0 | AW49: =Allocations!AF49*$Q49 -> 0 | AX49: =Allocations!AG49*$Q49 -> 0 | AY49: =Allocations!AH49*$Q49 -> 0 | AZ49: =Allocations!AI49*$Q49 -> 0 | BA49: =Allocations!AJ49*$Q49 -> 0 | BB49: =Allocations!AK49*$Q49 -> 0 | BC49: =SUM(U49:BB49) -> 0 | BD49: =Q49-BC49 -> 0 | BE49: =B49 -> HILL, Nyjira
A50: =Allocations!A50 -> 44 | B50: =Allocations!B50 -> HILL, Wynora - Summer | C50: =Allocations!C50 -> Abbott | Q50: =SUM(E50:J50) -> 0 | R50: =E50 -> 0 | T50: 0 | U50: =Allocations!E50*$Q50 -> 0 | V50: =Allocations!F50*$Q50 -> 0 | W50: =Allocations!G50*$Q50 -> 0 | X50: =Allocations!H50*$Q50 -> 0 | Y50: =Allocations!I50*$Q50 -> 0 | Z50: =Allocations!J50*$Q50 -> 0 | AA50: =Allocations!K50*$Q50 -> 0 | AB50: =Allocations!L50*$Q50 -> 0 | ... AV50: =Allocations!AF50*$Q50 -> 0 | AW50: =Allocations!AF50*$Q50 -> 0 | AX50: =Allocations!AG50*$Q50 -> 0 | AY50: =Allocations!AH50*$Q50 -> 0 | AZ50: =Allocations!AI50*$Q50 -> 0 | BA50: =Allocations!AJ50*$Q50 -> 0 | BB50: =Allocations!AK50*$Q50 -> 0 | BC50: =SUM(U50:BB50) -> 0 | BD50: =Q50-BC50 -> 0 | BE50: =B50 -> HILL, Wynora - Summer
A51: =Allocations!A51 -> 45 | B51: =Allocations!B51 -> HILL, Wynora | C51: =Allocations!C51 -> Abbott | Q51: =SUM(E51:J51) -> 0 | R51: =E51 -> 0 | T51: 0 | U51: =Allocations!E51*$Q51 -> 0 | V51: =Allocations!F51*$Q51 -> 0 | W51: =Allocations!G51*$Q51 -> 0 | X51: =Allocations!H51*$Q51 -> 0 | Y51: =Allocations!I51*$Q51 -> 0 | Z51: =Allocations!J51*$Q51 -> 0 | AA51: =Allocations!K51*$Q51 -> 0 | AB51: =Allocations!L51*$Q51 -> 0 | ... AV51: =Allocations!AF51*$Q51 -> 0 | AW51: =Allocations!AF51*$Q51 -> 0 | AX51: =Allocations!AG51*$Q51 -> 0 | AY51: =Allocations!AH51*$Q51 -> 0 | AZ51: =Allocations!AI51*$Q51 -> 0 | BA51: =Allocations!AJ51*$Q51 -> 0 | BB51: =Allocations!AK51*$Q51 -> 0 | BC51: =SUM(U51:BB51) -> 0 | BD51: =Q51-BC51 -> 0 | BE51: =B51 -> HILL, Wynora
A52: =Allocations!A52 -> 46 | B52: =Allocations!B52 -> HOLLINS, QUINTELLA | C52: =Allocations!C52 -> Abbott | O52: 1346.7 | P52: 1346.7 | Q52: =SUM(E52:J52) -> 0 | R52: =E52 -> 0
A53: =Allocations!A53 -> 47 | B53: =Allocations!B53 -> HOWARD, Cheryl | C53: =Allocations!C53 -> NRTC | E53: 1118.65 | F53: 1118.65 | G53: 1118.65 | H53: 1118.65 | I53: 1118.65 | J53: 1118.65 | Q53: =SUM(E53:J53) -> 6711.9 | R53: =E53 -> 1118.65 | T53: 0 | U53: =Allocations!E53*$Q53 -> 0 | V53: =Allocations!F53*$Q53 -> 0 | W53: =Allocations!G53*$Q53 -> 0 | X53: =Allocations!H53*$Q53 -> 0 | Y53: =Allocations!I53*$Q53 -> 0 | Z53: =Allocations!J53*$Q53 -> 0 | AA53: =Allocations!K53*$Q53 -> 0 | AB53: =Allocations!L53*$Q53 -> 0 | ... AV53: =Allocations!AF53*$Q53 -> 0 | AW53: =Allocations!AF53*$Q53 -> 0 | AX53: =Allocations!AG53*$Q53 -> 0 | AY53: =Allocations!AH53*$Q53 -> 0 | AZ53: =Allocations!AI53*$Q53 -> 0 | BA53: =Allocations!AJ53*$Q53 -> 0 | BB53: =Allocations!AK53*$Q53 -> 0 | BC53: =SUM(U53:BB53) -> 6711.9 | BD53: =Q53-BC53 -> 0 | BE53: =B53 -> HOWARD, Cheryl
A54: =Allocations!A54 -> 48 | B54: =Allocations!B54 -> HOWARD, Cheryl - July | C54: =Allocations!C54 -> NRTC | K54: 1118.65 | L54: 1118.65 | M54: 1118.65 | N54: 1118.65 | Q54: =SUM(E54:J54) -> 0 | R54: =E54 -> 0 | U54: =Allocations!E54*$Q54 -> 0 | V54: =Allocations!F54*$Q54 -> 0 | W54: =Allocations!G54*$Q54 -> 0 | X54: =Allocations!H54*$Q54 -> 0 | Y54: =Allocations!I54*$Q54 -> 0 | Z54: =Allocations!J54*$Q54 -> 0 | AA54: =Allocations!K54*$Q54 -> 0 | AB54: =Allocations!L54*$Q54 -> 0 | ... AV54: =Allocations!AF54*$Q54 -> 0 | AW54: =Allocations!AF54*$Q54 -> 0 | AX54: =Allocations!AG54*$Q54 -> 0 | AY54: =Allocations!AH54*$Q54 -> 0 | AZ54: =Allocations!AI54*$Q54 -> 0 | BA54: =Allocations!AJ54*$Q54 -> 0 | BB54: =Allocations!AK54*$Q54 -> 0 | BC54: =SUM(U54:BB54) -> 0 | BD54: =Q54-BC54 -> 0 | BE54: =B54 -> HOWARD, Cheryl - July
A55: =Allocations!A55 -> 49 | B55: =Allocations!B55 -> HOWARD, Walter | C55: =Allocations!C55 -> Thriftworks | Q55: =SUM(E55:J55) -> 0 | R55: =E55 -> 0 | U55: =Allocations!E55*$Q55 -> 0 | V55: =Allocations!F55*$Q55 -> 0 | W55: =Allocations!G55*$Q55 -> 0 | X55: =Allocations!H55*$Q55 -> 0 | Y55: =Allocations!I55*$Q55 -> 0 | Z55: =Allocations!J55*$Q55 -> 0 | AA55: =Allocations!K55*$Q55 -> 0 | AB55: =Allocations!L55*$Q55 -> 0 | ... AV55: =Allocations!AF55*$Q55 -> 0 | AW55: =Allocations!AF55*$Q55 -> 0 | AX55: =Allocations!AG55*$Q55 -> 0 | AY55: =Allocations!AH55*$Q55 -> 0 | AZ55: =Allocations!AI55*$Q55 -> 0 | BA55: =Allocations!AJ55*$Q55 -> 0 | BB55: =Allocations!AK55*$Q55 -> 0 | BC55: =SUM(U55:BB55) -> 0 | BD55: =Q55-BC55 -> 0 | BE55: =B55 -> HOWARD, Walter
A56: =Allocations!A56 -> 50 | B56: =Allocations!B56 -> JOHNSON, Kamilla R. April | C56: =Allocations!C56 -> FOC, Housing, OICA | E56: 1052.9 | F56: 1052.9 | G56: 1073.08 | H56: 1073.08 | I56: 1073.08 | J56: 1073.08 | K56: 1073.08 | Q56: =SUM(E56:J56) -> 6398.12 | R56: =E56 -> 1052.9 | T56: 0 | U56: =Allocations!E56*$Q56 -> 0 | V56: =Allocations!F56*$Q56 -> 0 | W56: =Allocations!G56*$Q56 -> 0 | X56: =Allocations!H56*$Q56 -> 0 | Y56: =Allocations!I56*$Q56 -> 0 | Z56: =Allocations!J56*$Q56 -> 0 | AA56: =Allocations!K56*$Q56 -> 0 | AB56: =Allocations!L56*$Q56 -> 0 | ... AV56: =Allocations!AF56*$Q56 -> 0 | AW56: =Allocations!AF56*$Q56 -> 0 | AX56: =Allocations!AG56*$Q56 -> 0 | AY56: =Allocations!AH56*$Q56 -> 0 | AZ56: =Allocations!AI56*$Q56 -> 0 | BA56: =Allocations!AJ56*$Q56 -> 0 | BB56: =Allocations!AK56*$Q56 -> 0 | BC56: =SUM(U56:BB56) -> 6398.12 | BD56: =Q56-BC56 -> 0 | BE56: =B56 -> JOHNSON, Kamilla R. April
A57: =Allocations!A57 -> 51 | B57: =Allocations!B57 -> JOHNSON, Kamilla R. May | C57: =Allocations!C57 -> FOC, Housing, OICA | Q57: =SUM(E57:J57) -> 0 | R57: =E57 -> 0 | T57: 0 | U57: =Allocations!E57*$Q57 -> 0 | V57: =Allocations!F57*$Q57 -> 0 | W57: =Allocations!G57*$Q57 -> 0 | X57: =Allocations!H57*$Q57 -> 0 | Y57: =Allocations!I57*$Q57 -> 0 | Z57: =Allocations!J57*$Q57 -> 0 | AA57: =Allocations!K57*$Q57 -> 0 | AB57: =Allocations!L57*$Q57 -> 0 | ... AV57: =Allocations!AF57*$Q57 -> 0 | AW57: =Allocations!AF57*$Q57 -> 0 | AX57: =Allocations!AG57*$Q57 -> 0 | AY57: =Allocations!AH57*$Q57 -> 0 | AZ57: =Allocations!AI57*$Q57 -> 0 | BA57: =Allocations!AJ57*$Q57 -> 0 | BB57: =Allocations!AK57*$Q57 -> 0 | BC57: =SUM(U57:BB57) -> 0 | BD57: =Q57-BC57 -> 0 | BE57: =B57 -> JOHNSON, Kamilla R. May
A58: =Allocations!A58 -> 52 | B58: =Allocations!B58 -> JOHNSON, Kamilla R. June | C58: =Allocations!C58 -> FOC, Housing, OICA | L58: 1073.08 | M58: 1073.08 | Q58: =SUM(E58:J58) -> 0 | R58: =E58 -> 0 | U58: =Allocations!E58*$Q58 -> 0 | V58: =Allocations!F58*$Q58 -> 0 | W58: =Allocations!G58*$Q58 -> 0 | X58: =Allocations!H58*$Q58 -> 0 | Y58: =Allocations!I58*$Q58 -> 0 | Z58: =Allocations!J58*$Q58 -> 0 | AA58: =Allocations!K58*$Q58 -> 0 | AB58: =Allocations!L58*$Q58 -> 0 | ... AV58: =Allocations!AF58*$Q58 -> 0 | AW58: =Allocations!AF58*$Q58 -> 0 | AX58: =Allocations!AG58*$Q58 -> 0 | AY58: =Allocations!AH58*$Q58 -> 0 | AZ58: =Allocations!AI58*$Q58 -> 0 | BA58: =Allocations!AJ58*$Q58 -> 0 | BB58: =Allocations!AK58*$Q58 -> 0 | BC58: =SUM(U58:BB58) -> 0 | BD58: =Q58-BC58 -> 0 | BE58: =B58 -> JOHNSON, Kamilla R. June
A59: =Allocations!A59 -> 53 | B59: =Allocations!B59 -> LANE-MEGA, Lataeya - Replacemt | C59: =Allocations!C59 -> Abbott | E59: 1736.35 | F59: 1736.35 | Q59: =SUM(E59:J59) -> 3472.7 | R59: =E59 -> 1736.35 | T59: 0 | U59: =Allocations!E59*$Q59 -> 0 | V59: =Allocations!F59*$Q59 -> 3472.7 | W59: =Allocations!G59*$Q59 -> 0 | X59: =Allocations!H59*$Q59 -> 0 | Y59: =Allocations!I59*$Q59 -> 0 | Z59: =Allocations!J59*$Q59 -> 0 | AA59: =Allocations!K59*$Q59 -> 0 | AB59: =Allocations!L59*$Q59 -> 0 | ... AV59: =Allocations!AF59*$Q59 -> 0 | AW59: =Allocations!AF59*$Q59 -> 0 | AX59: =Allocations!AG59*$Q59 -> 0 | AY59: =Allocations!AH59*$Q59 -> 0 | AZ59: =Allocations!AI59*$Q59 -> 0 | BA59: =Allocations!AJ59*$Q59 -> 0 | BB59: =Allocations!AK59*$Q59 -> 0 | BC59: =SUM(U59:BB59) -> 3472.7 | BD59: =Q59-BC59 -> 0 | BE59: =B59 -> LANE-MEGA, Lataeya - Replacemt
A60: =Allocations!A60 -> 54 | B60: =Allocations!B60 -> LEWIS, Felicia M. | C60: =Allocations!C60 -> EHS | E60: 677.56 | F60: 677.56 | G60: 677.56 | H60: 677.56 | I60: 677.56 | J60: 677.56 | K60: 677.56 | L60: 677.56 | M60: 677.56 | Q60: =SUM(E60:J60) -> 4065.36 | R60: =E60 -> 677.56 | T60: 0 | U60: =Allocations!E60*$Q60 -> 0 | V60: =Allocations!F60*$Q60 -> 0 | W60: =Allocations!G60*$Q60 -> 0 | X60: =Allocations!H60*$Q60 -> 0 | Y60: =Allocations!I60*$Q60 -> 0 | Z60: =Allocations!J60*$Q60 -> 4065.36 | AA60: =Allocations!K60*$Q60 -> 0 | AB60: =Allocations!L60*$Q60 -> 0 | ... AV60: =Allocations!AF60*$Q60 -> 0 | AW60: =Allocations!AF60*$Q60 -> 0 | AX60: =Allocations!AG60*$Q60 -> 0 | AY60: =Allocations!AH60*$Q60 -> 0 | AZ60: =Allocations!AI60*$Q60 -> 0 | BA60: =Allocations!AJ60*$Q60 -> 0 | BB60: =Allocations!AK60*$Q60 -> 0 | BC60: =SUM(U60:BB60) -> 4065.36 | BD60: =Q60-BC60 -> 0 | BE60: =B60 -> LEWIS, Felicia M.
A61: =Allocations!A61 -> 55 | B61: =Allocations!B61 -> LEWIS, Jaleeah C. | C61: =Allocations!C61 -> EHS | Q61: =SUM(E61:J61) -> 0 | R61: =E61 -> 0 | T61: 0 | U61: =Allocations!E61*$Q61 -> 0 | V61: =Allocations!F61*$Q61 -> 0 | W61: =Allocations!G61*$Q61 -> 0 | X61: =Allocations!H61*$Q61 -> 0 | Y61: =Allocations!I61*$Q61 -> 0 | Z61: =Allocations!J61*$Q61 -> 0 | AA61: =Allocations!K61*$Q61 -> 0 | AB61: =Allocations!L61*$Q61 -> 0 | ... AV61: =Allocations!AF61*$Q61 -> 0 | AW61: =Allocations!AF61*$Q61 -> 0 | AX61: =Allocations!AG61*$Q61 -> 0 | AY61: =Allocations!AH61*$Q61 -> 0 | AZ61: =Allocations!AI61*$Q61 -> 0 | BA61: =Allocations!AJ61*$Q61 -> 0 | BB61: =Allocations!AK61*$Q61 -> 0 | BC61: =SUM(U61:BB61) -> 0 | BD61: =Q61-BC61 -> 0 | BE61: =B61 -> LEWIS, Jaleeah C.
A62: =Allocations!A62 -> 56 | B62: =Allocations!B62 -> LEWIS, Tavonna | C62: =Allocations!C62 -> EHS | Q62: =SUM(E62:J62) -> 0 | R62: =E62 -> 0 | T62: 0 | U62: =Allocations!E62*$Q62 -> 0 | V62: =Allocations!F62*$Q62 -> 0 | W62: =Allocations!G62*$Q62 -> 0 | X62: =Allocations!H62*$Q62 -> 0 | Y62: =Allocations!I62*$Q62 -> 0 | Z62: =Allocations!J62*$Q62 -> 0 | AA62: =Allocations!K62*$Q62 -> 0 | AB62: =Allocations!L62*$Q62 -> 0 | ... AV62: =Allocations!AF62*$Q62 -> 0 | AW62: =Allocations!AF62*$Q62 -> 0 | AX62: =Allocations!AG62*$Q62 -> 0 | AY62: =Allocations!AH62*$Q62 -> 0 | AZ62: =Allocations!AI62*$Q62 -> 0 | BA62: =Allocations!AJ62*$Q62 -> 0 | BB62: =Allocations!AK62*$Q62 -> 0 | BC62: =SUM(U62:BB62) -> 0 | BD62: =Q62-BC62 -> 0 | BE62: =B62 -> LEWIS, Tavonna
A63: =Allocations!A63 -> 57 | B63: =Allocations!B63 -> LOFTIN, NIQUITA | C63: =Allocations!C63 -> Abbott | R63: =E63 -> 0
A64: =Allocations!A64 -> 58 | B64: =Allocations!B64 -> MAJETTE, Juanita L. | C64: =Allocations!C64 -> Americorp | Q64: =SUM(E64:J64) -> 0 | R64: =E64 -> 0 | T64: 0 | U64: =Allocations!E64*$Q64 -> 0 | V64: =Allocations!F64*$Q64 -> 0 | W64: =Allocations!G64*$Q64 -> 0 | X64: =Allocations!H64*$Q64 -> 0 | Y64: =Allocations!I64*$Q64 -> 0 | Z64: =Allocations!J64*$Q64 -> 0 | AA64: =Allocations!K64*$Q64 -> 0 | AB64: =Allocations!L64*$Q64 -> 0 | ... AV64: =Allocations!AF64*$Q64 -> 0 | AW64: =Allocations!AF64*$Q64 -> 0 | AX64: =Allocations!AG64*$Q64 -> 0 | AY64: =Allocations!AH64*$Q64 -> 0 | AZ64: =Allocations!AI64*$Q64 -> 0 | BA64: =Allocations!AJ64*$Q64 -> 0 | BB64: =Allocations!AK64*$Q64 -> 0 | BC64: =SUM(U64:BB64) -> 0 | BD64: =Q64-BC64 -> 0 | BE64: =B64 -> MAJETTE, Juanita L.
A65: =Allocations!A65 -> 59 | B65: =Allocations!B65 -> MARROW, Mary Elizabeth | C65: =Allocations!C65 -> EHS | Q65: =SUM(E65:J65) -> 0 | R65: =E65 -> 0 | S65: =R65/Q65 -> #DIV/0! | T65: 0 | U65: =Allocations!E65*$Q65 -> 0 | V65: =Allocations!F65*$Q65 -> 0 | W65: =Allocations!G65*$Q65 -> 0 | X65: =Allocations!H65*$Q65 -> 0 | Y65: =Allocations!I65*$Q65 -> 0 | Z65: =Allocations!J65*$Q65 -> 0 | AA65: =Allocations!K65*$Q65 -> 0 | AB65: =Allocations!L65*$Q65 -> 0 | ... AV65: =Allocations!AF65*$Q65 -> 0 | AW65: =Allocations!AF65*$Q65 -> 0 | AX65: =Allocations!AG65*$Q65 -> 0 | AY65: =Allocations!AH65*$Q65 -> 0 | AZ65: =Allocations!AI65*$Q65 -> 0 | BA65: =Allocations!AJ65*$Q65 -> 0 | BB65: =Allocations!AK65*$Q65 -> 0 | BC65: =SUM(U65:BB65) -> 0 | BD65: =Q65-BC65 -> 0 | BE65: =B65 -> MARROW, Mary Elizabeth
A66: =Allocations!A66 -> 60 | B66: =Allocations!B66 -> MARTINEZ, Joanna | C66: =Allocations!C66 -> USJP | E66: 1377.69 | F66: 1377.69 | G66: 1377.69 | H66: 1377.69 | I66: 1377.69 | J66: 1377.69 | K66: 1377.69 | Q66: =SUM(E66:J66) -> 8266.14 | R66: =E66 -> 1377.69 | T66: 0 | U66: =Allocations!E66*$Q66 -> 0 | V66: =Allocations!F66*$Q66 -> 0 | W66: =Allocations!G66*$Q66 -> 0 | X66: =Allocations!H66*$Q66 -> 0 | Y66: =Allocations!I66*$Q66 -> 0 | Z66: =Allocations!J66*$Q66 -> 0 | AA66: =Allocations!K66*$Q66 -> 0 | AB66: =Allocations!L66*$Q66 -> 0 | ... AV66: =Allocations!AF66*$Q66 -> 0 | AW66: =Allocations!AF66*$Q66 -> 0 | AX66: =Allocations!AG66*$Q66 -> 0 | AY66: =Allocations!AH66*$Q66 -> 0 | AZ66: =Allocations!AI66*$Q66 -> 0 | BA66: =Allocations!AJ66*$Q66 -> 0 | BB66: =Allocations!AK66*$Q66 -> 0 | BC66: =SUM(U66:BB66) -> 8266.14 | BD66: =Q66-BC66 -> 0 | BE66: =B66 -> MARTINEZ, Joanna
A67: =Allocations!A67 -> 61 | B67: =Allocations!B67 -> MARTINEZ, Joanna - August | C67: =Allocations!C67 -> USJP, Finance | L67: 1377.69 | M67: 1377.69 | N67: 1377.69 | O67: 1332.17 | P67: 1332.17 | Q67: =SUM(E67:J67) -> 0 | R67: =E67 -> 0 | U67: =Allocations!E67*$Q67 -> 0 | V67: =Allocations!F67*$Q67 -> 0 | W67: =Allocations!G67*$Q67 -> 0 | X67: =Allocations!H67*$Q67 -> 0 | Y67: =Allocations!I67*$Q67 -> 0 | Z67: =Allocations!J67*$Q67 -> 0 | AA67: =Allocations!K67*$Q67 -> 0 | AB67: =Allocations!L67*$Q67 -> 0 | ... AV67: =Allocations!AF67*$Q67 -> 0 | AW67: =Allocations!AF67*$Q67 -> 0 | AX67: =Allocations!AG67*$Q67 -> 0 | AY67: =Allocations!AH67*$Q67 -> 0 | AZ67: =Allocations!AI67*$Q67 -> 0 | BA67: =Allocations!AJ67*$Q67 -> 0 | BB67: =Allocations!AK67*$Q67 -> 0 | BC67: =SUM(U67:BB67) -> 0 | BD67: =Q67-BC67 -> 0 | BE67: =B67 -> MARTINEZ, Joanna - August
A68: =Allocations!A68 -> 62 | B68: =Allocations!B68 -> MCMILLIAN, Daphne L. | C68: =Allocations!C68 -> Abbott | E68: 933.18 | F68: 933.18 | G68: 933.18 | H68: 933.18 | I68: 933.18 | J68: 933.18 | M68: 933.18 | N68: 933.18 | O68: 918.88 | P68: 918.88 | Q68: =SUM(E68:J68) -> 5599.08 | R68: =E68 -> 933.18 | T68: 0 | U68: =Allocations!E68*$Q68 -> 0 | V68: =Allocations!F68*$Q68 -> 4479.264 | W68: =Allocations!G68*$Q68 -> 0 | X68: =Allocations!H68*$Q68 -> 1119.816 | Y68: =Allocations!I68*$Q68 -> 0 | Z68: =Allocations!J68*$Q68 -> 0 | AA68: =Allocations!K68*$Q68 -> 0 | AB68: =Allocations!L68*$Q68 -> 0 | ... AV68: =Allocations!AF68*$Q68 -> 0 | AW68: =Allocations!AF68*$Q68 -> 0 | AX68: =Allocations!AG68*$Q68 -> 0 | AY68: =Allocations!AH68*$Q68 -> 0 | AZ68: =Allocations!AI68*$Q68 -> 0 | BA68: =Allocations!AJ68*$Q68 -> 0 | BB68: =Allocations!AK68*$Q68 -> 0 | BC68: =SUM(U68:BB68) -> 5599.08 | BD68: =Q68-BC68 -> 0 | BE68: =B68 -> MCMILLIAN, Daphne L.
A69: =Allocations!A69 -> 63 | B69: =Allocations!B69 -> MCMILLIAN, Daphne L. - Summer | C69: =Allocations!C69 -> Abbott | K69: 933.18 | L69: 933.18 | Q69: =SUM(E69:J69) -> 0 | R69: =E69 -> 0 | U69: =Allocations!E69*$Q69 -> 0 | V69: =Allocations!F69*$Q69 -> 0 | W69: =Allocations!G69*$Q69 -> 0 | X69: =Allocations!H69*$Q69 -> 0 | Y69: =Allocations!I69*$Q69 -> 0 | Z69: =Allocations!J69*$Q69 -> 0 | AA69: =Allocations!K69*$Q69 -> 0 | AB69: =Allocations!L69*$Q69 -> 0 | ... AV69: =Allocations!AF69*$Q69 -> 0 | AW69: =Allocations!AF69*$Q69 -> 0 | AX69: =Allocations!AG69*$Q69 -> 0 | AY69: =Allocations!AH69*$Q69 -> 0 | AZ69: =Allocations!AI69*$Q69 -> 0 | BA69: =Allocations!AJ69*$Q69 -> 0 | BB69: =Allocations!AK69*$Q69 -> 0 | BC69: =SUM(U69:BB69) -> 0 | BD69: =Q69-BC69 -> 0 | BE69: =B69 -> MCMILLIAN, Daphne L. - Summer
A70: =Allocations!A70 -> 64 | B70: =Allocations!B70 -> MEGGETT, Bonita L. | C70: =Allocations!C70 -> EHS | Q70: =SUM(E70:J70) -> 0 | R70: =E70 -> 0 | T70: 0 | U70: =Allocations!E70*$Q70 -> 0 | V70: =Allocations!F70*$Q70 -> 0 | W70: =Allocations!G70*$Q70 -> 0 | X70: =Allocations!H70*$Q70 -> 0 | Y70: =Allocations!I70*$Q70 -> 0 | Z70: =Allocations!J70*$Q70 -> 0 | AA70: =Allocations!K70*$Q70 -> 0 | AB70: =Allocations!L70*$Q70 -> 0 | ... AV70: =Allocations!AF70*$Q70 -> 0 | AW70: =Allocations!AF70*$Q70 -> 0 | AX70: =Allocations!AG70*$Q70 -> 0 | AY70: =Allocations!AH70*$Q70 -> 0 | AZ70: =Allocations!AI70*$Q70 -> 0 | BA70: =Allocations!AJ70*$Q70 -> 0 | BB70: =Allocations!AK70*$Q70 -> 0 | BC70: =SUM(U70:BB70) -> 0 | BD70: =Q70-BC70 -> 0 | BE70: =B70 -> MEGGETT, Bonita L.
A71: =Allocations!A71 -> 65 | B71: =Allocations!B71 -> MORRIS, GWEN | C71: =Allocations!C71 -> USJP | E71: 1050.94 | F71: 1050.94 | G71: 1050.94 | H71: 1050.94 | I71: 1050.94 | J71: 1050.94 | K71: 1050.94 | L71: 1050.94 | M71: 1050.94 | N71: 1050.94 | O71: 1033.68 | P71: 1033.68 | Q71: =SUM(E71:J71) -> 6305.64 | R71: =E71 -> 1050.94 | T71: 0 | U71: =Allocations!E71*$Q71 -> 0 | V71: =Allocations!F71*$Q71 -> 0 | W71: =Allocations!G71*$Q71 -> 0 | X71: =Allocations!H71*$Q71 -> 0 | Y71: =Allocations!I71*$Q71 -> 0 | Z71: =Allocations!J71*$Q71 -> 0 | AA71: =Allocations!K71*$Q71 -> 0 | AB71: =Allocations!L71*$Q71 -> 0 | ... AV71: =Allocations!AF71*$Q71 -> 0 | AW71: =Allocations!AF71*$Q71 -> 0 | AX71: =Allocations!AG71*$Q71 -> 0 | AY71: =Allocations!AH71*$Q71 -> 0 | AZ71: =Allocations!AI71*$Q71 -> 0 | BA71: =Allocations!AJ71*$Q71 -> 0 | BB71: =Allocations!AK71*$Q71 -> 0 | BC71: =SUM(U71:BB71) -> 6305.64 | BD71: =Q71-BC71 -> 0 | BE71: =B71 -> MORRIS, GWEN
A72: =Allocations!A72 -> 66 | B72: =Allocations!B72 -> RAMBARAN, Sharaini J. | C72: =Allocations!C72 -> Abbott | Q72: =SUM(E72:J72) -> 0 | R72: =E72 -> 0 | U72: =Allocations!E72*$Q72 -> 0 | V72: =Allocations!F72*$Q72 -> 0 | W72: =Allocations!G72*$Q72 -> 0 | X72: =Allocations!H72*$Q72 -> 0 | Y72: =Allocations!I72*$Q72 -> 0 | Z72: =Allocations!J72*$Q72 -> 0 | AA72: =Allocations!K72*$Q72 -> 0 | AB72: =Allocations!L72*$Q72 -> 0 | ... AV72: =Allocations!AF72*$Q72 -> 0 | AW72: =Allocations!AF72*$Q72 -> 0 | AX72: =Allocations!AG72*$Q72 -> 0 | AY72: =Allocations!AH72*$Q72 -> 0 | AZ72: =Allocations!AI72*$Q72 -> 0 | BA72: =Allocations!AJ72*$Q72 -> 0 | BB72: =Allocations!AK72*$Q72 -> 0 | BC72: =SUM(U72:BB72) -> 0 | BD72: =Q72-BC72 -> 0 | BE72: =B72 -> RAMBARAN, Sharaini J.
A73: =Allocations!A73 -> 67 | B73: =Allocations!B73 -> RAMBARAN, Sharaini J. - Summer | C73: =Allocations!C73 -> Abbott | Q73: =SUM(E73:J73) -> 0 | R73: =E73 -> 0 | U73: =Allocations!E73*$Q73 -> 0 | V73: =Allocations!F73*$Q73 -> 0 | W73: =Allocations!G73*$Q73 -> 0 | X73: =Allocations!H73*$Q73 -> 0 | Y73: =Allocations!I73*$Q73 -> 0 | Z73: =Allocations!J73*$Q73 -> 0 | AA73: =Allocations!K73*$Q73 -> 0 | AB73: =Allocations!L73*$Q73 -> 0 | ... AV73: =Allocations!AF73*$Q73 -> 0 | AW73: =Allocations!AF73*$Q73 -> 0 | AX73: =Allocations!AG73*$Q73 -> 0 | AY73: =Allocations!AH73*$Q73 -> 0 | AZ73: =Allocations!AI73*$Q73 -> 0 | BA73: =Allocations!AJ73*$Q73 -> 0 | BB73: =Allocations!AK73*$Q73 -> 0 | BC73: =SUM(U73:BB73) -> 0 | BD73: =Q73-BC73 -> 0 | BE73: =B73 -> RAMBARAN, Sharaini J. - Summer
A74: =Allocations!A74 -> 68 | B74: =Allocations!B74 -> REED, Melissa | C74: =Allocations!C74 -> Americorp | Q74: =SUM(E74:J74) -> 0 | R74: =E74 -> 0 | T74: 0 | U74: =Allocations!E74*$Q74 -> 0 | V74: =Allocations!F74*$Q74 -> 0 | W74: =Allocations!G74*$Q74 -> 0 | X74: =Allocations!H74*$Q74 -> 0 | Y74: =Allocations!I74*$Q74 -> 0 | Z74: =Allocations!J74*$Q74 -> 0 | AA74: =Allocations!K74*$Q74 -> 0 | AB74: =Allocations!L74*$Q74 -> 0 | ... AV74: =Allocations!AF74*$Q74 -> 0 | AW74: =Allocations!AF74*$Q74 -> 0 | AX74: =Allocations!AG74*$Q74 -> 0 | AY74: =Allocations!AH74*$Q74 -> 0 | AZ74: =Allocations!AI74*$Q74 -> 0 | BA74: =Allocations!AJ74*$Q74 -> 0 | BB74: =Allocations!AK74*$Q74 -> 0 | BC74: =SUM(U74:BB74) -> 0 | BD74: =Q74-BC74 -> 0 | BE74: =B74 -> REED, Melissa
A75: =Allocations!A75 -> 69 | B75: =Allocations!B75 -> Robinson, Chantee | C75: =Allocations!C75 -> Americorp | Q75: =SUM(E75:J75) -> 0 | R75: =E75 -> 0 | U75: =Allocations!E75*$Q75 -> 0 | V75: =Allocations!F75*$Q75 -> 0 | W75: =Allocations!G75*$Q75 -> 0 | X75: =Allocations!H75*$Q75 -> 0 | Y75: =Allocations!I75*$Q75 -> 0 | Z75: =Allocations!J75*$Q75 -> 0 | AA75: =Allocations!K75*$Q75 -> 0 | AB75: =Allocations!L75*$Q75 -> 0 | ... AV75: =Allocations!AF75*$Q75 -> 0 | AW75: =Allocations!AF75*$Q75 -> 0 | AX75: =Allocations!AG75*$Q75 -> 0 | AY75: =Allocations!AH75*$Q75 -> 0 | AZ75: =Allocations!AI75*$Q75 -> 0 | BA75: =Allocations!AJ75*$Q75 -> 0 | BB75: =Allocations!AK75*$Q75 -> 0 | BC75: =SUM(U75:BB75) -> 0 | BD75: =Q75-BC75 -> 0 | BE75: =B75 -> Robinson, Chantee
A76: =Allocations!A76 -> 70 | B76: =Allocations!B76 -> ROBBINS, Leonard | C76: =Allocations!C76 -> Real Estate | E76: 1118.65 | F76: 1118.65 | G76: 1118.65 | H76: 1118.65 | I76: 1118.65 | J76: 1118.65 | K76: 1118.65 | L76: 1118.65 | M76: 1118.65 | N76: 1118.65 | O76: 1068.35 | P76: 1068.35 | Q76: =SUM(E76:J76) -> 6711.9 | R76: =E76 -> 1118.65 | T76: 0 | U76: =Allocations!E76*$Q76 -> 0 | V76: =Allocations!F76*$Q76 -> 0 | W76: =Allocations!G76*$Q76 -> 0 | X76: =Allocations!H76*$Q76 -> 0 | Y76: =Allocations!I76*$Q76 -> 0 | Z76: =Allocations!J76*$Q76 -> 0 | AA76: =Allocations!K76*$Q76 -> 0 | AB76: =Allocations!L76*$Q76 -> 0 | ... AV76: =Allocations!AF76*$Q76 -> 0 | AW76: =Allocations!AF76*$Q76 -> 0 | AX76: =Allocations!AG76*$Q76 -> 0 | AY76: =Allocations!AH76*$Q76 -> 0 | AZ76: =Allocations!AI76*$Q76 -> 0 | BA76: =Allocations!AJ76*$Q76 -> 0 | BB76: =Allocations!AK76*$Q76 -> 0 | BC76: =SUM(U76:BB76) -> 6711.9 | BD76: =Q76-BC76 -> 0 | BE76: =B76 -> ROBBINS, Leonard
A77: =Allocations!A77 -> 71 | B77: =Allocations!B77 -> Rogers, Lakeshia | C77: =Allocations!C77 -> Americorp | Q77: =SUM(E77:J77) -> 0 | R77: =E77 -> 0 | S77: =R77/Q77 -> #DIV/0! | T77: 0 | U77: =Allocations!E77*$Q77 -> 0 | V77: =Allocations!F77*$Q77 -> 0 | W77: =Allocations!G77*$Q77 -> 0 | X77: =Allocations!H77*$Q77 -> 0 | Y77: =Allocations!I77*$Q77 -> 0 | Z77: =Allocations!J77*$Q77 -> 0 | AA77: =Allocations!K77*$Q77 -> 0 | AB77: =Allocations!L77*$Q77 -> 0 | ... AV77: =Allocations!AF77*$Q77 -> 0 | AW77: =Allocations!AF77*$Q77 -> 0 | AX77: =Allocations!AG77*$Q77 -> 0 | AY77: =Allocations!AH77*$Q77 -> 0 | AZ77: =Allocations!AI77*$Q77 -> 0 | BA77: =Allocations!AJ77*$Q77 -> 0 | BB77: =Allocations!AK77*$Q77 -> 0 | BC77: =SUM(U77:BB77) -> 0 | BD77: =Q77-BC77 -> 0 | BE77: =B77 -> Rogers, Lakeshia | BN77: 0.3
A78: =Allocations!A78 -> 72 | B78: =Allocations!B78 -> SANTIAGO-RAMOS, Jose A. | C78: =Allocations!C78 -> Facilities | Q78: =SUM(E78:J78) -> 0 | R78: =E78 -> 0 | U78: =Allocations!E78*$Q78 -> 0 | V78: =Allocations!F78*$Q78 -> 0 | W78: =Allocations!G78*$Q78 -> 0 | X78: =Allocations!H78*$Q78 -> 0 | Y78: =Allocations!I78*$Q78 -> 0 | Z78: =Allocations!J78*$Q78 -> 0 | AA78: =Allocations!K78*$Q78 -> 0 | AB78: =Allocations!L78*$Q78 -> 0 | ... AV78: =Allocations!AF78*$Q78 -> 0 | AW78: =Allocations!AF78*$Q78 -> 0 | AX78: =Allocations!AG78*$Q78 -> 0 | AY78: =Allocations!AH78*$Q78 -> 0 | AZ78: =Allocations!AI78*$Q78 -> 0 | BA78: =Allocations!AJ78*$Q78 -> 0 | BB78: =Allocations!AK78*$Q78 -> 0 | BC78: =SUM(U78:BB78) -> 0 | BD78: =Q78-BC78 -> 0 | BE78: =B78 -> SANTIAGO-RAMOS, Jose A.
A79: =Allocations!A79 -> 73 | B79: =Allocations!B79 -> SERMON, Patricia April | C79: =Allocations!C79 -> FOC, Housing, OICA, COO | E79: 1118.65 | F79: 1118.65 | G79: 1118.65 | H79: 1118.65 | I79: 1118.65 | J79: 1118.65 | K79: 1118.65 | L79: 0 | Q79: =SUM(E79:J79) -> 6711.9 | R79: =E79 -> 1118.65 | T79: 0 | U79: =Allocations!E79*$Q79 -> 0 | V79: =Allocations!F79*$Q79 -> 0 | W79: =Allocations!G79*$Q79 -> 0 | X79: =Allocations!H79*$Q79 -> 0 | Y79: =Allocations!I79*$Q79 -> 0 | Z79: =Allocations!J79*$Q79 -> 0 | AA79: =Allocations!K79*$Q79 -> 0 | AB79: =Allocations!L79*$Q79 -> 0 | ... AV79: =Allocations!AF79*$Q79 -> 0 | AW79: =Allocations!AF79*$Q79 -> 0 | AX79: =Allocations!AG79*$Q79 -> 0 | AY79: =Allocations!AH79*$Q79 -> 0 | AZ79: =Allocations!AI79*$Q79 -> 0 | BA79: =Allocations!AJ79*$Q79 -> 1342.38 | BB79: =Allocations!AK79*$Q79 -> 0 | BC79: =SUM(U79:BB79) -> 6711.9 | BD79: =Q79-BC79 -> 0 | BE79: =B79 -> SERMON, Patricia April
A80: =Allocations!A80 -> 74 | B80: =Allocations!B80 -> SERMON, Patricia May | C80: =Allocations!C80 -> FOC, Housing, OICA, COO | E80: 1118.65 | F80: 1118.65 | G80: 1118.65 | H80: 1118.65 | I80: 1118.65 | J80: 1118.65 | L80: 0 | Q80: =SUM(E80:J80) -> 6711.9 | R80: =E80 -> 1118.65 | T80: 1 | U80: =Allocations!E80*$Q80 -> 0 | V80: =Allocations!F80*$Q80 -> 0 | W80: =Allocations!G80*$Q80 -> 0 | X80: =Allocations!H80*$Q80 -> 0 | Y80: =Allocations!I80*$Q80 -> 0 | Z80: =Allocations!J80*$Q80 -> 0 | AA80: =Allocations!K80*$Q80 -> 0 | AB80: =Allocations!L80*$Q80 -> 0 | ... AV80: =Allocations!AF80*$Q80 -> 0 | AW80: =Allocations!AF80*$Q80 -> 0 | AX80: =Allocations!AG80*$Q80 -> 0 | AY80: =Allocations!AH80*$Q80 -> 0 | AZ80: =Allocations!AI80*$Q80 -> 0 | BA80: =Allocations!AJ80*$Q80 -> 1342.38 | BB80: =Allocations!AK80*$Q80 -> 0 | BC80: =SUM(U80:BB80) -> 6711.9 | BD80: =Q80-BC80 -> 0 | BE80: =B80 -> SERMON, Patricia May
A81: =Allocations!A81 -> 75 | B81: =Allocations!B81 -> SERMON, Patricia June | C81: =Allocations!C81 -> FOC, Housing, OICA, COO | Q81: =SUM(E81:J81) -> 0 | R81: =E81 -> 0 | T81: 2 | U81: =Allocations!E81*$Q81 -> 0 | V81: =Allocations!F81*$Q81 -> 0 | W81: =Allocations!G81*$Q81 -> 0 | X81: =Allocations!H81*$Q81 -> 0 | Y81: =Allocations!I81*$Q81 -> 0 | Z81: =Allocations!J81*$Q81 -> 0 | AA81: =Allocations!K81*$Q81 -> 0 | AB81: =Allocations!L81*$Q81 -> 0 | ... AV81: =Allocations!AF81*$Q81 -> 0 | AW81: =Allocations!AF81*$Q81 -> 0 | AX81: =Allocations!AG81*$Q81 -> 0 | AY81: =Allocations!AH81*$Q81 -> 0 | AZ81: =Allocations!AI81*$Q81 -> 0 | BA81: =Allocations!AJ81*$Q81 -> 0 | BB81: =Allocations!AK81*$Q81 -> 0 | BC81: =SUM(U81:BB81) -> 0 | BD81: =Q81-BC81 -> 0 | BE81: =B81 -> SERMON, Patricia June
A82: =Allocations!A82 -> 76 | B82: =Allocations!B82 -> SERMON, Patricia July | C82: =Allocations!C82 -> FOC, Housing, OICA, COO | Q82: =SUM(E82:J82) -> 0 | R82: =E82 -> 0 | T82: 3 | U82: =Allocations!E82*$Q82 -> 0 | V82: =Allocations!F82*$Q82 -> 0 | W82: =Allocations!G82*$Q82 -> 0 | X82: =Allocations!H82*$Q82 -> 0 | Y82: =Allocations!I82*$Q82 -> 0 | Z82: =Allocations!J82*$Q82 -> 0 | AA82: =Allocations!K82*$Q82 -> 0 | AB82: =Allocations!L82*$Q82 -> 0 | ... AV82: =Allocations!AF82*$Q82 -> 0 | AW82: =Allocations!AF82*$Q82 -> 0 | AX82: =Allocations!AG82*$Q82 -> 0 | AY82: =Allocations!AH82*$Q82 -> 0 | AZ82: =Allocations!AI82*$Q82 -> 0 | BA82: =Allocations!AJ82*$Q82 -> 0 | BB82: =Allocations!AK82*$Q82 -> 0 | BC82: =SUM(U82:BB82) -> 0 | BD82: =Q82-BC82 -> 0 | BE82: =B82 -> SERMON, Patricia July
A83: =Allocations!A83 -> 77 | B83: =Allocations!B83 -> SERMON, Patricia August | C83: =Allocations!C83 -> FOC, Housing, OICA, COO | L83: 1118.65 | M83: 1118.65 | N83: 1118.65 | O83: 1068.35 | P83: 1068.35 | Q83: =SUM(E83:J83) -> 0 | R83: =E83 -> 0 | T83: 4 | U83: =Allocations!E83*$Q83 -> 0 | V83: =Allocations!F83*$Q83 -> 0 | W83: =Allocations!G83*$Q83 -> 0 | X83: =Allocations!H83*$Q83 -> 0 | Y83: =Allocations!I83*$Q83 -> 0 | Z83: =Allocations!J83*$Q83 -> 0 | AA83: =Allocations!K83*$Q83 -> 0 | AB83: =Allocations!L83*$Q83 -> 0 | ... BB83: =Allocations!AL83*$Q83 -> 0 | BC83: =SUM(U83:BB83) -> 0 | BD83: =Q83-BC83 -> 0 | BE83: =B83 -> SERMON, Patricia August
A84: =Allocations!A84 -> 78 | B84: =Allocations!B84 -> SESSOMS, Donna M. | C84: =Allocations!C84 -> Americorp | Q84: =SUM(E84:J84) -> 0 | R84: =E84 -> 0 | T84: 0 | U84: =Allocations!E84*$Q84 -> 0 | V84: =Allocations!F84*$Q84 -> 0 | W84: =Allocations!G84*$Q84 -> 0 | X84: =Allocations!H84*$Q84 -> 0 | Y84: =Allocations!I84*$Q84 -> 0 | Z84: =Allocations!J84*$Q84 -> 0 | AA84: =Allocations!K84*$Q84 -> 0 | AB84: =Allocations!L84*$Q84 -> 0 | ... AV84: =Allocations!AF84*$Q84 -> 0 | AW84: =Allocations!AF84*$Q84 -> 0 | AX84: =Allocations!AG84*$Q84 -> 0 | AY84: =Allocations!AH84*$Q84 -> 0 | AZ84: =Allocations!AI84*$Q84 -> 0 | BA84: =Allocations!AJ84*$Q84 -> 0 | BB84: =Allocations!AK84*$Q84 -> 0 | BC84: =SUM(U84:BB84) -> 0 | BD84: =Q84-BC84 -> 0 | BE84: =B84 -> SESSOMS, Donna M.
A85: =Allocations!A85 -> 79 | B85: =Allocations!B85 -> SHARIF, Darrin S. - April | C85: =Allocations!C85 -> Admin, Coding, WF | E85: 1050.94 | F85: 1050.94 | G85: 1050.94 | H85: 1050.94 | I85: 1050.94 | J85: 1050.94 | Q85: =SUM(E85:J85) -> 6305.64 | R85: =E85 -> 1050.94 | T85: 0 | U85: =Allocations!E85*$Q85 -> 0 | V85: =Allocations!F85*$Q85 -> 0 | W85: =Allocations!G85*$Q85 -> 0 | X85: =Allocations!H85*$Q85 -> 0 | Y85: =Allocations!I85*$Q85 -> 0 | Z85: =Allocations!J85*$Q85 -> 0 | AA85: =Allocations!K85*$Q85 -> 0 | AB85: =Allocations!L85*$Q85 -> 0 | ... AV85: =Allocations!AF85*$Q85 -> 0 | AW85: =Allocations!AF85*$Q85 -> 0 | AX85: =Allocations!AG85*$Q85 -> 0 | AY85: =Allocations!AH85*$Q85 -> 0 | AZ85: =Allocations!AI85*$Q85 -> 0 | BA85: =Allocations!AJ85*$Q85 -> 0 | BB85: =Allocations!AK85*$Q85 -> 0 | BC85: =SUM(U85:BB85) -> 6305.64 | BD85: =Q85-BC85 -> 0 | BE85: =B85 -> SHARIF, Darrin S. - April
A86: =Allocations!A86 -> 80 | B86: =Allocations!B86 -> SHARIF, Darrin S. - July | C86: =Allocations!C86 -> Admin, Coding, WF | K86: 1050.94 | L86: 1050.94 | M86: 1050.94 | N86: 1050.94 | O86: 1033.68 | P86: 1033.68 | Q86: =SUM(E86:J86) -> 0 | R86: =E86 -> 0 | T86: 0 | U86: =Allocations!E86*$Q86 -> 0 | V86: =Allocations!F86*$Q86 -> 0 | W86: =Allocations!G86*$Q86 -> 0 | X86: =Allocations!H86*$Q86 -> 0 | Y86: =Allocations!I86*$Q86 -> 0 | Z86: =Allocations!J86*$Q86 -> 0 | AA86: =Allocations!K86*$Q86 -> 0 | AB86: =Allocations!L86*$Q86 -> 0 | ... AI86: =Allocations!S86*$Q86 -> 0 | AJ86: =Allocations!U86*$Q86 -> 0 | AK86: =Allocations!#REF!*$Q86 -> #REF! | AL86: =Allocations!V86*$Q86 -> 0 | AM86: =Allocations!W86*$Q86 -> 0 | AN86: =Allocations!X86*$Q86 -> 0 | AO86: =Allocations!Y86*$Q86 -> 0 | AP86: =Allocations!Z86*$Q86 -> 0 | AQ86: =Allocations!AA86*$Q86 -> 0 | AR86: =Allocations!AB86*$Q86 -> 0 | AS86: =Allocations!AC86*$Q86 -> 0 | ... AV86: =Allocations!AF86*$Q86 -> 0 | AW86: =Allocations!AF86*$Q86 -> 0 | AX86: =Allocations!AG86*$Q86 -> 0 | AY86: =Allocations!AH86*$Q86 -> 0 | AZ86: =Allocations!AI86*$Q86 -> 0 | BA86: =Allocations!AJ86*$Q86 -> 0 | BB86: =Allocations!AK86*$Q86 -> 0 | BC86: =SUM(U86:BB86) -> #REF! | BD86: =Q86-BC86 -> #REF! | BE86: =B86 -> SHARIF, Darrin S. - July
A87: =Allocations!A87 -> 81 | B87: =Allocations!B87 -> SIMMONS, Bertrilla R. | C87: =Allocations!C87 -> Abbott | E87: 781.58 | F87: 781.58 | G87: 781.58 | H87: 781.58 | I87: 781.58 | J87: 781.58 | K87: 781.58 | L87: 781.58 | M87: 781.58 | N87: 781.58 | O87: 768.94 | P87: 768.94 | Q87: =SUM(E87:J87) -> 4689.48 | R87: =E87 -> 781.58 | T87: 0 | U87: =Allocations!E87*$Q87 -> 0 | V87: =Allocations!F87*$Q87 -> 4689.48 | W87: =Allocations!G87*$Q87 -> 0 | X87: =Allocations!H87*$Q87 -> 0 | Y87: =Allocations!I87*$Q87 -> 0 | Z87: =Allocations!J87*$Q87 -> 0 | AA87: =Allocations!K87*$Q87 -> 0 | AB87: =Allocations!L87*$Q87 -> 0 | ... AV87: =Allocations!AF87*$Q87 -> 0 | AW87: =Allocations!AF87*$Q87 -> 0 | AX87: =Allocations!AG87*$Q87 -> 0 | AY87: =Allocations!AH87*$Q87 -> 0 | AZ87: =Allocations!AI87*$Q87 -> 0 | BA87: =Allocations!AJ87*$Q87 -> 0 | BB87: =Allocations!AK87*$Q87 -> 0 | BC87: =SUM(U87:BB87) -> 4689.48 | BD87: =Q87-BC87 -> 0 | BE87: =B87 -> SIMMONS, Bertrilla R.
A88: =Allocations!A88 -> 82 | B88: =Allocations!B88 -> STEWART, Robin D - Summer | C88: =Allocations!C88 -> Abbott | Q88: =SUM(E88:J88) -> 0 | R88: =E88 -> 0 | U88: =Allocations!E88*$Q88 -> 0 | V88: =Allocations!F88*$Q88 -> 0 | W88: =Allocations!G88*$Q88 -> 0 | X88: =Allocations!H88*$Q88 -> 0 | Y88: =Allocations!I88*$Q88 -> 0 | Z88: =Allocations!J88*$Q88 -> 0 | AA88: =Allocations!K88*$Q88 -> 0 | AB88: =Allocations!L88*$Q88 -> 0 | ... AV88: =Allocations!AF88*$Q88 -> 0 | AW88: =Allocations!AF88*$Q88 -> 0 | AX88: =Allocations!AG88*$Q88 -> 0 | AY88: =Allocations!AH88*$Q88 -> 0 | AZ88: =Allocations!AI88*$Q88 -> 0 | BA88: =Allocations!AJ88*$Q88 -> 0 | BB88: =Allocations!AK88*$Q88 -> 0 | BC88: =SUM(U88:BB88) -> 0 | BD88: =Q88-BC88 -> 0 | BE88: =B88 -> STEWART, Robin D - Summer
A89: =Allocations!A89 -> 83 | B89: =Allocations!B89 -> STEWART, Robin D | C89: =Allocations!C89 -> Abbott | E89: 1118.65 | F89: 1118.65 | G89: 1118.65 | H89: 1118.65 | I89: 1118.65 | J89: 1118.65 | K89: 1118.65 | L89: 1118.65 | M89: 1118.65 | N89: 1118.65 | O89: 1068.35 | P89: 1068.35 | Q89: =SUM(E89:J89) -> 6711.9 | R89: =E89 -> 1118.65 | T89: 0 | U89: =Allocations!E89*$Q89 -> 0 | V89: =Allocations!F89*$Q89 -> 6711.9 | W89: =Allocations!G89*$Q89 -> 0 | X89: =Allocations!H89*$Q89 -> 0 | Y89: =Allocations!I89*$Q89 -> 0 | Z89: =Allocations!J89*$Q89 -> 0 | AA89: =Allocations!K89*$Q89 -> 0 | AB89: =Allocations!L89*$Q89 -> 0 | ... AV89: =Allocations!AF89*$Q89 -> 0 | AW89: =Allocations!AF89*$Q89 -> 0 | AX89: =Allocations!AG89*$Q89 -> 0 | AY89: =Allocations!AH89*$Q89 -> 0 | AZ89: =Allocations!AI89*$Q89 -> 0 | BA89: =Allocations!AJ89*$Q89 -> 0 | BB89: =Allocations!AK89*$Q89 -> 0 | BC89: =SUM(U89:BB89) -> 6711.9 | BD89: =Q89-BC89 -> 0 | BE89: =B89 -> STEWART, Robin D
A90: =Allocations!A90 -> 84 | B90: =Allocations!B90 -> TYLER, Patricia | C90: =Allocations!C91 -> Abbott | Q90: =SUM(E90:J90) -> 0 | R90: =E90 -> 0 | T90: 0 | U90: =Allocations!E90*$Q90 -> 0 | V90: =Allocations!F90*$Q90 -> 0 | W90: =Allocations!G90*$Q90 -> 0 | X90: =Allocations!H90*$Q90 -> 0 | Y90: =Allocations!I90*$Q90 -> 0 | Z90: =Allocations!J90*$Q90 -> 0 | AA90: =Allocations!K90*$Q90 -> 0 | AB90: =Allocations!L90*$Q90 -> 0 | ... AV90: =Allocations!AF90*$Q90 -> 0 | AW90: =Allocations!AF90*$Q90 -> 0 | AX90: =Allocations!AG90*$Q90 -> 0 | AY90: =Allocations!AH90*$Q90 -> 0 | AZ90: =Allocations!AI90*$Q90 -> 0 | BA90: =Allocations!AJ90*$Q90 -> 0 | BB90: =Allocations!AK90*$Q90 -> 0 | BC90: =SUM(U90:BB90) -> 0 | BD90: =Q90-BC90 -> 0 | BE90: =B90 -> TYLER, Patricia
A91: =Allocations!A91 -> 85 | B91: =Allocations!B91 -> TYLER, Patricia - Summer | C91: =Allocations!C92 -> EHS | Q91: =SUM(E91:J91) -> 0 | R91: =E91 -> 0 | U91: =Allocations!E91*$Q91 -> 0 | V91: =Allocations!F91*$Q91 -> 0 | W91: =Allocations!G91*$Q91 -> 0 | X91: =Allocations!H91*$Q91 -> 0 | Y91: =Allocations!I91*$Q91 -> 0 | Z91: =Allocations!J91*$Q91 -> 0 | AA91: =Allocations!K91*$Q91 -> 0 | AB91: =Allocations!L91*$Q91 -> 0 | ... AV91: =Allocations!AF91*$Q91 -> 0 | AW91: =Allocations!AF91*$Q91 -> 0 | AX91: =Allocations!AG91*$Q91 -> 0 | AY91: =Allocations!AH91*$Q91 -> 0 | AZ91: =Allocations!AI91*$Q91 -> 0 | BA91: =Allocations!AJ91*$Q91 -> 0 | BB91: =Allocations!AK91*$Q91 -> 0 | BC91: =SUM(U91:BB91) -> 0 | BD91: =Q91-BC91 -> 0 | BE91: =B91 -> TYLER, Patricia - Summer
A92: =Allocations!A92 -> 86 | B92: =Allocations!B92 -> WAH, Alexia | C92: =Allocations!C92 -> EHS | Q92: =SUM(E92:J92) -> 0 | R92: =E92 -> 0 | T92: 0 | U92: =Allocations!E92*$Q92 -> 0 | V92: =Allocations!F92*$Q92 -> 0 | W92: =Allocations!G92*$Q92 -> 0 | X92: =Allocations!H92*$Q92 -> 0 | Y92: =Allocations!I92*$Q92 -> 0 | Z92: =Allocations!J92*$Q92 -> 0 | AA92: =Allocations!K92*$Q92 -> 0 | AB92: =Allocations!L92*$Q92 -> 0 | ... AV92: =Allocations!AF92*$Q92 -> 0 | AW92: =Allocations!AF92*$Q92 -> 0 | AX92: =Allocations!AG92*$Q92 -> 0 | AY92: =Allocations!AH92*$Q92 -> 0 | AZ92: =Allocations!AI92*$Q92 -> 0 | BA92: =Allocations!AJ92*$Q92 -> 0 | BB92: =Allocations!AK92*$Q92 -> 0 | BC92: =SUM(U92:BB92) -> 0 | BD92: =Q92-BC92 -> 0 | BE92: =B92 -> WAH, Alexia
A93: =Allocations!A93 -> 87 | B93: =Allocations!B93 -> WARD, Richard G. - April | C93: =Allocations!C93 -> Admin | H93: 2759.34 | Q93: =SUM(E93:J93) -> 2759.34 | R93: =E93 -> 0 | T93: 0 | U93: =Allocations!E93*$Q93 -> 0 | V93: =Allocations!F93*$Q93 -> 0 | W93: =Allocations!G93*$Q93 -> 0 | X93: =Allocations!H93*$Q93 -> 0 | Y93: =Allocations!I93*$Q93 -> 0 | Z93: =Allocations!J93*$Q93 -> 0 | AA93: =Allocations!K93*$Q93 -> 0 | AB93: =Allocations!L93*$Q93 -> 0 | ... AV93: =Allocations!AF93*$Q93 -> 0 | AW93: =Allocations!AF93*$Q93 -> 0 | AX93: =Allocations!AG93*$Q93 -> 0 | AY93: =Allocations!AH93*$Q93 -> 0 | AZ93: =Allocations!AI93*$Q93 -> 2207.472 | BA93: =Allocations!AJ93*$Q93 -> 0 | BB93: =Allocations!AK93*$Q93 -> 0 | BC93: =SUM(U93:BB93) -> 2759.34 | BD93: =Q93-BC93 -> 0 | BE93: =B93 -> WARD, Richard G. - April
A94: =Allocations!A94 -> 88 | B94: =Allocations!B94 -> WARD, Richard G. -May | C94: =Allocations!C94 -> Admin | I94: 1118.65 | J94: 1118.65 | K94: 1118.65 | Q94: =SUM(E94:J94) -> 2237.3 | R94: =E94 -> 0 | T94: 0 | U94: =Allocations!E94*$Q94 -> 0 | V94: =Allocations!F94*$Q94 -> 0 | W94: =Allocations!G94*$Q94 -> 0 | X94: =Allocations!H94*$Q94 -> 0 | Y94: =Allocations!I94*$Q94 -> 0 | Z94: =Allocations!J94*$Q94 -> 0 | AA94: =Allocations!K94*$Q94 -> 0 | AB94: =Allocations!L94*$Q94 -> 0 | ... AV94: =Allocations!AF94*$Q94 -> 0 | AW94: =Allocations!AF94*$Q94 -> 0 | AX94: =Allocations!AG94*$Q94 -> 0 | AY94: =Allocations!AH94*$Q94 -> 0 | AZ94: =Allocations!AI94*$Q94 -> 1789.84 | BA94: =Allocations!AJ94*$Q94 -> 0 | BB94: =Allocations!AK94*$Q94 -> 0 | BC94: =SUM(U94:BB94) -> 2237.3 | BD94: =Q94-BC94 -> 0 | BE94: =B94 -> WARD, Richard G. -May
A95: =Allocations!A95 -> 89 | B95: =Allocations!B95 -> WARD, Richard G. - August | C95: =Allocations!C95 -> USJP, Finance, Coding, NRTC 19 | L95: 1118.65 | Q95: =SUM(E95:J95) -> 0 | R95: =E95 -> 0 | U95: =Allocations!E95*$Q95 -> 0 | V95: =Allocations!F95*$Q95 -> 0 | W95: =Allocations!G95*$Q95 -> 0 | X95: =Allocations!H95*$Q95 -> 0 | Y95: =Allocations!I95*$Q95 -> 0 | Z95: =Allocations!J95*$Q95 -> 0 | AA95: =Allocations!K95*$Q95 -> 0 | AB95: =Allocations!L95*$Q95 -> 0 | ... AV95: =Allocations!AF95*$Q95 -> 0 | AW95: =Allocations!AF95*$Q95 -> 0 | AX95: =Allocations!AG95*$Q95 -> 0 | AY95: =Allocations!AH95*$Q95 -> 0 | AZ95: =Allocations!AI95*$Q95 -> 0 | BA95: =Allocations!AJ95*$Q95 -> 0 | BB95: =Allocations!AK95*$Q95 -> 0 | BC95: =SUM(U95:BB95) -> 0 | BD95: =Q95-BC95 -> 0 | BE95: =B95 -> WARD, Richard G. - August
A96: =Allocations!A96 -> 90 | B96: =Allocations!B96 -> Wardwick, Lamar | C96: =Allocations!C96 -> NRTC, Housing, PARS, ESG | Q96: =SUM(E96:J96) -> 0 | R96: =E96 -> 0 | T96: 1 | U96: =Allocations!E96*$Q96 -> 0 | V96: =Allocations!F96*$Q96 -> 0 | W96: =Allocations!G96*$Q96 -> 0 | X96: =Allocations!H96*$Q96 -> 0 | Y96: =Allocations!I96*$Q96 -> 0 | Z96: =Allocations!J96*$Q96 -> 0 | AA96: =Allocations!K96*$Q96 -> 0 | AB96: =Allocations!L96*$Q96 -> 0 | ... AV96: =Allocations!AF96*$Q96 -> 0 | AW96: =Allocations!AF96*$Q96 -> 0 | AX96: =Allocations!AG96*$Q96 -> 0 | AY96: =Allocations!AH96*$Q96 -> 0 | AZ96: =Allocations!AI96*$Q96 -> 0 | BA96: =Allocations!AJ96*$Q96 -> 0 | BB96: =Allocations!AK96*$Q96 -> 0 | BC96: =SUM(U96:BB96) -> 0 | BD96: =Q96-BC96 -> 0 | BE96: =B96 -> Wardwick, Lamar
A97: =Allocations!A97 -> 91 | B97: =Allocations!B97 -> WILLIAMS, Kilaina | C97: =Allocations!C97 -> EHS | Q97: =SUM(E97:J97) -> 0 | R97: =E97 -> 0 | U97: =Allocations!E97*$Q97 -> 0 | V97: =Allocations!F97*$Q97 -> 0 | W97: =Allocations!G97*$Q97 -> 0 | X97: =Allocations!H97*$Q97 -> 0 | Y97: =Allocations!I97*$Q97 -> 0 | Z97: =Allocations!J97*$Q97 -> 0 | AA97: =Allocations!K97*$Q97 -> 0 | AB97: =Allocations!L97*$Q97 -> 0 | ... AV97: =Allocations!AF97*$Q97 -> 0 | AW97: =Allocations!AF97*$Q97 -> 0 | AX97: =Allocations!AG97*$Q97 -> 0 | AY97: =Allocations!AH97*$Q97 -> 0 | AZ97: =Allocations!AI97*$Q97 -> 0 | BA97: =Allocations!AJ97*$Q97 -> 0 | BB97: =Allocations!AK97*$Q97 -> 0 | BC97: =SUM(U97:BB97) -> 0 | BD97: =Q97-BC97 -> 0 | BE97: =B97 -> WILLIAMS, Kilaina
A98: =Allocations!A98 -> 92 | B98: =Allocations!B98 -> WOODRIDGE, Rosalind | C98: =Allocations!C98 -> Abbott | Q98: =SUM(E98:J98) -> 0 | R98: =E98 -> 0 | U98: =Allocations!E98*$Q98 -> 0 | V98: =Allocations!F98*$Q98 -> 0 | W98: =Allocations!G98*$Q98 -> 0 | X98: =Allocations!H98*$Q98 -> 0 | Y98: =Allocations!I98*$Q98 -> 0 | Z98: =Allocations!J98*$Q98 -> 0 | AA98: =Allocations!K98*$Q98 -> 0 | AB98: =Allocations!L98*$Q98 -> 0 | ... AV98: =Allocations!AF98*$Q98 -> 0 | AW98: =Allocations!AF98*$Q98 -> 0 | AX98: =Allocations!AG98*$Q98 -> 0 | AY98: =Allocations!AH98*$Q98 -> 0 | AZ98: =Allocations!AI98*$Q98 -> 0 | BA98: =Allocations!AJ98*$Q98 -> 0 | BB98: =Allocations!AK98*$Q98 -> 0 | BC98: =SUM(U98:BB98) -> 0 | BD98: =Q98-BC98 -> 0 | BE98: =B98 -> WOODRIDGE, Rosalind
A99: =Allocations!A99 -> 93 | B99: =Allocations!B99 -> WOODRIDGE, Rosalind - Summer | C99: =Allocations!C99 -> Abbott | Q99: =SUM(E99:J99) -> 0 | R99: =E99 -> 0 | U99: =Allocations!E99*$Q99 -> 0 | V99: =Allocations!F99*$Q99 -> 0 | W99: =Allocations!G99*$Q99 -> 0 | X99: =Allocations!H99*$Q99 -> 0 | Y99: =Allocations!I99*$Q99 -> 0 | Z99: =Allocations!J99*$Q99 -> 0 | AA99: =Allocations!K99*$Q99 -> 0 | AB99: =Allocations!L99*$Q99 -> 0 | ... AV99: =Allocations!AF99*$Q99 -> 0 | AW99: =Allocations!AF99*$Q99 -> 0 | AX99: =Allocations!AG99*$Q99 -> 0 | AY99: =Allocations!AH99*$Q99 -> 0 | AZ99: =Allocations!AI99*$Q99 -> 0 | BA99: =Allocations!AJ99*$Q99 -> 0 | BB99: =Allocations!AK99*$Q99 -> 0 | BC99: =SUM(U99:BB99) -> 0 | BD99: =Q99-BC99 -> 0 | BE99: =B99 -> WOODRIDGE, Rosalind - Summer
A100: =Allocations!A100 -> 94 | B100: =Allocations!B100 -> WILJEAMPS, St Louis | C100: =Allocations!C100 -> Americorp | Q100: =SUM(E100:J100) -> 0 | R100: =E100 -> 0 | U100: =Allocations!E100*$Q100 -> 0 | V100: =Allocations!F100*$Q100 -> 0 | W100: =Allocations!G100*$Q100 -> 0 | X100: =Allocations!H100*$Q100 -> 0 | Y100: =Allocations!I100*$Q100 -> 0 | Z100: =Allocations!J100*$Q100 -> 0 | AA100: =Allocations!K100*$Q100 -> 0 | AB100: =Allocations!L100*$Q100 -> 0 | ... AV100: =Allocations!AF100*$Q100 -> 0 | AW100: =Allocations!AF100*$Q100 -> 0 | AX100: =Allocations!AG100*$Q100 -> 0 | AY100: =Allocations!AH100*$Q100 -> 0 | AZ100: =Allocations!AI100*$Q100 -> 0 | BA100: =Allocations!AJ100*$Q100 -> 0 | BB100: =Allocations!AK100*$Q100 -> 0 | BC100: =SUM(U100:BB100) -> 0 | BD100: =Q100-BC100 -> 0 | BE100: =B100 -> WILJEAMPS, St Louis
A101: =Allocations!A101 -> 95 | B101: =Allocations!B101 -> Wint, Renee | C101: =Allocations!C101 -> Americorp | Q101: =SUM(E101:J101) -> 0 | R101: =E101 -> 0 | U101: =Allocations!E101*$Q101 -> 0 | V101: =Allocations!F101*$Q101 -> 0 | W101: =Allocations!G101*$Q101 -> 0 | X101: =Allocations!H101*$Q101 -> 0 | Y101: =Allocations!I101*$Q101 -> 0 | Z101: =Allocations!J101*$Q101 -> 0 | AA101: =Allocations!K101*$Q101 -> 0 | AB101: =Allocations!L101*$Q101 -> 0 | ... AV101: =Allocations!AF101*$Q101 -> 0 | AW101: =Allocations!AF101*$Q101 -> 0 | AX101: =Allocations!AG101*$Q101 -> 0 | AY101: =Allocations!AH101*$Q101 -> 0 | AZ101: =Allocations!AI101*$Q101 -> 0 | BA101: =Allocations!AJ101*$Q101 -> 0 | BB101: =Allocations!AK101*$Q101 -> 0 | BC101: =SUM(U101:BB101) -> 0 | BD101: =Q101-BC101 -> 0 | BE101: =B101 -> Wint, Renee
A102: =Allocations!A102 -> 96 | B102: =Allocations!B102 -> Janvier, Jhonny | C102: =Allocations!C102 -> Abbott | I102: 287.44 | J102: 663.33 | Q102: =SUM(E102:J102) -> 950.77 | R102: =E102 -> 0 | U102: =Allocations!E102*$Q102 -> 0 | V102: =Allocations!F102*$Q102 -> 950.77 | W102: =Allocations!G102*$Q102 -> 0 | X102: =Allocations!H102*$Q102 -> 0 | Y102: =Allocations!I102*$Q102 -> 0 | Z102: =Allocations!J102*$Q102 -> 0 | AA102: =Allocations!K102*$Q102 -> 0 | AB102: =Allocations!L102*$Q102 -> 0 | ... AV102: =Allocations!AF102*$Q102 -> 0 | AW102: =Allocations!AF102*$Q102 -> 0 | AX102: =Allocations!AG102*$Q102 -> 0 | AY102: =Allocations!AH102*$Q102 -> 0 | AZ102: =Allocations!AI102*$Q102 -> 0 | BA102: =Allocations!AJ102*$Q102 -> 0 | BB102: =Allocations!AK102*$Q102 -> 0 | BC102: =SUM(U102:BB102) -> 950.77 | BD102: =Q102-BC102 -> 0 | BE102: =B102 -> Janvier, Jhonny
...

Sheet 2019 Life Insurance 
T3: Contract
B4: Principal | P4: 12 | R4: 80 20 | T4: Percentage | U4: 10 months | Y4: 12 Months
B5: SALARIES 2018 | C5: 2018 FY BUDGET | E5: Jan | F5: Feb | G5: Mar | H5: April | I5: May | J5: June | K5: July | L5: August | M5: September | N5: October | O5: Nov | P5: Dec | Q5: TOTAL | R5: Employee | S5: Variance | U5: =+Allocations!F1 -> 111 Abbott | V5: =+Allocations!G1 -> 111B Wrap Fees | W5: =+Allocations!H1 -> 111A Other | X5: =+Allocations!I1 -> 111F Food Prog | Y5: =+Allocations!J1 -> 112 EHS/Toddler | Z5: =+Allocations!L1 -> 114 Summer Camp | AA5: =+Allocations!M1 -> 222 DCF Coding | AB5: =+Allocations!S1 -> 368 Wells Fargo 165K | AC5: =+Allocations!N1 -> 223 OICA June 30 | AD5: =+Allocations!O1 -> 225 Americorp | AE5: =+Allocations!O1 -> 225 Americorp | AF5: =+Allocations!Q1 -> 335 NRTC 19 40K | AG5: =+Allocations!R1 -> 339 ULEC OC | AH5: =+Allocations!S1 -> 368 Wells Fargo 165K | AI5: =+Allocations!T1 -> 451 SENIORS / USJP | AJ5: =+Allocations!U1 -> 452 PACE $211K | AK5: =+Allocations!V1 -> 460 Ihop Training $34k | AL5: =+Allocations!W1 -> 468 Nwk Alliance $95K | AM5: =+Allocations!X1 -> 467 United Airlines 125K Business Dev | ... AT5: =+Allocations!AE1 -> 567 Chase FOC Wksp 3K- Delete | AU5: =+Allocations!AG1 -> 600Admin | AV5: =+Allocations!AH1 -> 610 CEO Victoria Fdn | AW5: =+Allocations!AI1 -> 620 CFO | AX5: =+Allocations!AJ1 -> 630 COO | AY5: =+Allocations!AK1 -> 640 Development | AZ5: =+Allocations!AL1 -> 650 Facilities | BA5: =+Allocations!AM1 -> Proof | BB5: =+Allocations!AN1 -> 0
B6: Salaried | E6: 1 | F6: 2 | G6: 3 | H6: 4 | I6: 5 | J6: 6 | K6: 7 | L6: 8 | M6: 9 | N6: 10 | O6: 11 | P6: 12
A7: =Allocations!A7 -> 1 | B7: =Allocations!B7 -> AIKEN-SANZONE, Charlene | C7: =Allocations!C7 -> Americorp | Q7: =E7*$P$4 -> 0 | R7: 0 | S7: 0 | T7: 0 | U7: =Allocations!F7*$Q7 -> 0 | V7: =Allocations!G7*$Q7 -> 0 | W7: =Allocations!H7*$Q7 -> 0 | X7: =Allocations!I7*$Q7 -> 0 | Y7: =Allocations!J7*$Q7 -> 0 | Z7: =Allocations!L7*$Q7 -> 0 | AA7: =Allocations!M7*$Q7 -> 0 | AB7: =Allocations!S7*$Q7 -> 0 | AC7: =Allocations!N7*$Q7 -> 0 | AE7: =Allocations!O7*$Q7 -> 0 | AF7: =Allocations!Q7*$Q7 -> 0 | AG7: =Allocations!E7*$Q7 -> 0 | AH7: =Allocations!T7*$Q7 -> 0 | AI7: =Allocations!AE7*$Q7 -> 0 | AK7: =Allocations!Z7*$Q7 -> 0 | AL7: =Allocations!AA7*$Q7 -> 0 | AM7: =Allocations!AB7*$Q7 -> 0 | AO7: =Allocations!AC7*$Q7 -> 0 | AP7: =Allocations!Y7*$Q7 -> 0 | AQ7: =Allocations!X7*$Q7 -> 0 | AR7: =Allocations!V7*$Q7 -> 0 | AS7: =Allocations!W7*$Q7 -> 0 | AT7: =Allocations!R7*$Q7 -> 0 | AU7: =Allocations!AG7*$Q7 -> 0 | AV7: =Allocations!AH7*$Q7 -> 0 | AW7: =Allocations!AI7*$Q7 -> 0 | AX7: =Allocations!AJ7*$Q7 -> 0 | AY7: =Allocations!AK7*$Q7 -> 0 | AZ7: =Allocations!AL7*$Q7 -> 0 | BA7: =SUM(U7:AZ7) -> 0 | BB7: =Q7-BA7 -> 0 | BC7: =B7 -> AIKEN-SANZONE, Charlene
A8: =Allocations!A8 -> 2 | B8: =Allocations!B8 -> AIKEN-SANZONE, Charlene June 30 | C8: =Allocations!C8 -> OICA | Q8: =E8*$P$4 -> 0 | R8: 0 | S8: 0 | T8: 0 | U8: =Allocations!F8*$Q8 -> 0 | V8: =Allocations!G8*$Q8 -> 0 | W8: =Allocations!H8*$Q8 -> 0 | X8: =Allocations!I8*$Q8 -> 0 | Y8: =Allocations!J8*$Q8 -> 0 | Z8: =Allocations!L8*$Q8 -> 0 | AA8: =Allocations!M8*$Q8 -> 0 | AB8: =Allocations!S8*$Q8 -> 0 | AC8: =Allocations!N8*$Q8 -> 0 | AE8: =Allocations!O8*$Q8 -> 0 | AF8: =Allocations!Q8*$Q8 -> 0 | AG8: =Allocations!E8*$Q8 -> 0 | AH8: =Allocations!T8*$Q8 -> 0 | AI8: =Allocations!AE8*$Q8 -> 0 | AK8: =Allocations!Z8*$Q8 -> 0 | AL8: =Allocations!AA8*$Q8 -> 0 | AM8: =Allocations!AB8*$Q8 -> 0 | AO8: =Allocations!AC8*$Q8 -> 0 | AP8: =Allocations!Y8*$Q8 -> 0 | AQ8: =Allocations!X8*$Q8 -> 0 | AR8: =Allocations!V8*$Q8 -> 0 | AS8: =Allocations!W8*$Q8 -> 0 | AT8: =Allocations!R8*$Q8 -> 0 | AU8: =Allocations!AG8*$Q8 -> 0 | AV8: =Allocations!AH8*$Q8 -> 0 | AW8: =Allocations!AI8*$Q8 -> 0 | AX8: =Allocations!AJ8*$Q8 -> 0 | AY8: =Allocations!AK8*$Q8 -> 0 | AZ8: =Allocations!AL8*$Q8 -> 0 | BA8: =SUM(U8:AZ8) -> 0 | BB8: =Q8-BA8 -> 0 | BC8: =B8 -> AIKEN-SANZONE, Charlene June 30
A9: =Allocations!A9 -> 3 | B9: =Allocations!B9 -> ALFORD, Sebrania R. | C9: =Allocations!C9 -> Abbott | Q9: =E9*$P$4 -> 0 | R9: 0 | S9: 0 | T9: 0 | U9: =Allocations!F9*$Q9 -> 0 | V9: =Allocations!G9*$Q9 -> 0 | W9: =Allocations!H9*$Q9 -> 0 | X9: =Allocations!I9*$Q9 -> 0 | Y9: =Allocations!J9*$Q9 -> 0 | Z9: =Allocations!L9*$Q9 -> 0 | AA9: =Allocations!M9*$Q9 -> 0 | AB9: =Allocations!S9*$Q9 -> 0 | AC9: =Allocations!N9*$Q9 -> 0 | AE9: =Allocations!O9*$Q9 -> 0 | AF9: =Allocations!Q9*$Q9 -> 0 | AG9: =Allocations!E9*$Q9 -> 0 | AH9: =Allocations!T9*$Q9 -> 0 | AI9: =Allocations!AE9*$Q9 -> 0 | AK9: =Allocations!Z9*$Q9 -> 0 | AL9: =Allocations!AA9*$Q9 -> 0 | AM9: =Allocations!AB9*$Q9 -> 0 | AO9: =Allocations!AC9*$Q9 -> 0 | AP9: =Allocations!Y9*$Q9 -> 0 | AQ9: =Allocations!X9*$Q9 -> 0 | AR9: =Allocations!V9*$Q9 -> 0 | AS9: =Allocations!W9*$Q9 -> 0 | AT9: =Allocations!R9*$Q9 -> 0 | AU9: =Allocations!AG9*$Q9 -> 0 | AV9: =Allocations!AH9*$Q9 -> 0 | AW9: =Allocations!AI9*$Q9 -> 0 | AX9: =Allocations!AJ9*$Q9 -> 0 | AY9: =Allocations!AK9*$Q9 -> 0 | AZ9: =Allocations!AL9*$Q9 -> 0 | BA9: =SUM(U9:AZ9) -> 0 | BB9: =Q9-BA9 -> 0 | BC9: =B9 -> ALFORD, Sebrania R.
A10: =Allocations!A10 -> 4 | B10: =Allocations!B10 -> ALMANZAR, Alberto | C10: =Allocations!C10 -> USJP | Q10: =E10*$P$4 -> 0 | R10: 0 | S10: 0 | T10: 0 | U10: =Allocations!F10*$Q10 -> 0 | V10: =Allocations!G10*$Q10 -> 0 | W10: =Allocations!H10*$Q10 -> 0 | X10: =Allocations!I10*$Q10 -> 0 | Y10: =Allocations!J10*$Q10 -> 0 | Z10: =Allocations!L10*$Q10 -> 0 | AA10: =Allocations!M10*$Q10 -> 0 | AB10: =Allocations!S10*$Q10 -> 0 | AC10: =Allocations!N10*$Q10 -> 0 | AE10: =Allocations!O10*$Q10 -> 0 | AF10: =Allocations!Q10*$Q10 -> 0 | AG10: =Allocations!E10*$Q10 -> 0 | AH10: =Allocations!T10*$Q10 -> 0 | AI10: =Allocations!AE10*$Q10 -> 0 | AK10: =Allocations!Z10*$Q10 -> 0 | AL10: =Allocations!AA10*$Q10 -> 0 | AM10: =Allocations!AB10*$Q10 -> 0 | AO10: =Allocations!AC10*$Q10 -> 0 | AP10: =Allocations!Y10*$Q10 -> 0 | AQ10: =Allocations!X10*$Q10 -> 0 | AR10: =Allocations!V10*$Q10 -> 0 | AS10: =Allocations!W10*$Q10 -> 0 | AT10: =Allocations!R10*$Q10 -> 0 | AU10: =Allocations!AG10*$Q10 -> 0 | AV10: =Allocations!AH10*$Q10 -> 0 | AW10: =Allocations!AI10*$Q10 -> 0 | AX10: =Allocations!AJ10*$Q10 -> 0 | AY10: =Allocations!AK10*$Q10 -> 0 | AZ10: =Allocations!AL10*$Q10 -> 0 | BA10: =SUM(U10:AZ10) -> 0 | BB10: =Q10-BA10 -> 0 | BC10: =B10 -> ALMANZAR, Alberto
A11: =Allocations!A11 -> 5 | B11: =Allocations!B11 -> ANDREWS, Cora - Summer | C11: =Allocations!C11 -> Abbott | Q11: =E11*$P$4 -> 0 | R11: 0 | S11: 0 | T11: 0 | U11: =Allocations!F11*$Q11 -> 0 | V11: =Allocations!G11*$Q11 -> 0 | W11: =Allocations!H11*$Q11 -> 0 | X11: =Allocations!I11*$Q11 -> 0 | Y11: =Allocations!J11*$Q11 -> 0 | Z11: =Allocations!L11*$Q11 -> 0 | AA11: =Allocations!M11*$Q11 -> 0 | AB11: =Allocations!S11*$Q11 -> 0 | AC11: =Allocations!N11*$Q11 -> 0 | AE11: =Allocations!O11*$Q11 -> 0 | AF11: =Allocations!Q11*$Q11 -> 0 | AG11: =Allocations!E11*$Q11 -> 0 | AH11: =Allocations!T11*$Q11 -> 0 | AI11: =Allocations!AE11*$Q11 -> 0 | AK11: =Allocations!Z11*$Q11 -> 0 | AL11: =Allocations!AA11*$Q11 -> 0 | AM11: =Allocations!AB11*$Q11 -> 0 | AO11: =Allocations!AC11*$Q11 -> 0 | AP11: =Allocations!Y11*$Q11 -> 0 | AQ11: =Allocations!X11*$Q11 -> 0 | AR11: =Allocations!V11*$Q11 -> 0 | AS11: =Allocations!W11*$Q11 -> 0 | AT11: =Allocations!R11*$Q11 -> 0 | AU11: =Allocations!AG11*$Q11 -> 0 | AV11: =Allocations!AH11*$Q11 -> 0 | AW11: =Allocations!AI11*$Q11 -> 0 | AX11: =Allocations!AJ11*$Q11 -> 0 | AY11: =Allocations!AK11*$Q11 -> 0 | AZ11: =Allocations!AL11*$Q11 -> 0 | BA11: =SUM(U11:AZ11) -> 0 | BB11: =Q11-BA11 -> 0 | BC11: =B11 -> ANDREWS, Cora - Summer
A12: =Allocations!A12 -> 6 | B12: =Allocations!B12 -> ANDREWS, Cora | C12: =Allocations!C12 -> Abbott | Q12: =E12*$P$4 -> 0 | R12: 0 | S12: 0 | T12: 0 | U12: =Allocations!F12*$Q12 -> 0 | V12: =Allocations!G12*$Q12 -> 0 | W12: =Allocations!H12*$Q12 -> 0 | X12: =Allocations!I12*$Q12 -> 0 | Y12: =Allocations!J12*$Q12 -> 0 | Z12: =Allocations!L12*$Q12 -> 0 | AA12: =Allocations!M12*$Q12 -> 0 | AB12: =Allocations!S12*$Q12 -> 0 | AC12: =Allocations!N12*$Q12 -> 0 | AE12: =Allocations!O12*$Q12 -> 0 | AF12: =Allocations!Q12*$Q12 -> 0 | AG12: =Allocations!E12*$Q12 -> 0 | AH12: =Allocations!T12*$Q12 -> 0 | AI12: =Allocations!AE12*$Q12 -> 0 | AK12: =Allocations!Z12*$Q12 -> 0 | AL12: =Allocations!AA12*$Q12 -> 0 | AM12: =Allocations!AB12*$Q12 -> 0 | AO12: =Allocations!AC12*$Q12 -> 0 | AP12: =Allocations!Y12*$Q12 -> 0 | AQ12: =Allocations!X12*$Q12 -> 0 | AR12: =Allocations!V12*$Q12 -> 0 | AS12: =Allocations!W12*$Q12 -> 0 | AT12: =Allocations!R12*$Q12 -> 0 | AU12: =Allocations!AG12*$Q12 -> 0 | AV12: =Allocations!AH12*$Q12 -> 0 | AW12: =Allocations!AI12*$Q12 -> 0 | AX12: =Allocations!AJ12*$Q12 -> 0 | AY12: =Allocations!AK12*$Q12 -> 0 | AZ12: =Allocations!AL12*$Q12 -> 0 | BA12: =SUM(U12:AZ12) -> 0 | BB12: =Q12-BA12 -> 0 | BC12: =B12 -> ANDREWS, Cora
A13: =Allocations!A13 -> 7 | B13: =Allocations!B13 -> ANDREWS, Courtney A. | C13: =Allocations!C13 -> Americorp | Q13: =E13*$P$4 -> 0 | R13: 0 | S13: 0 | T13: 0 | U13: =Allocations!F13*$Q13 -> 0 | V13: =Allocations!G13*$Q13 -> 0 | W13: =Allocations!H13*$Q13 -> 0 | X13: =Allocations!I13*$Q13 -> 0 | Y13: =Allocations!J13*$Q13 -> 0 | Z13: =Allocations!L13*$Q13 -> 0 | AA13: =Allocations!M13*$Q13 -> 0 | AB13: =Allocations!S13*$Q13 -> 0 | AC13: =Allocations!N13*$Q13 -> 0 | AE13: =Allocations!O13*$Q13 -> 0 | AF13: =Allocations!Q13*$Q13 -> 0 | AG13: =Allocations!E13*$Q13 -> 0 | AH13: =Allocations!T13*$Q13 -> 0 | AI13: =Allocations!AE13*$Q13 -> 0 | AK13: =Allocations!Z13*$Q13 -> 0 | AL13: =Allocations!AA13*$Q13 -> 0 | AM13: =Allocations!AB13*$Q13 -> 0 | AO13: =Allocations!AC13*$Q13 -> 0 | AP13: =Allocations!Y13*$Q13 -> 0 | AQ13: =Allocations!X13*$Q13 -> 0 | AR13: =Allocations!V13*$Q13 -> 0 | AS13: =Allocations!W13*$Q13 -> 0 | AT13: =Allocations!R13*$Q13 -> 0 | AU13: =Allocations!AG13*$Q13 -> 0 | AV13: =Allocations!AH13*$Q13 -> 0 | AW13: =Allocations!AI13*$Q13 -> 0 | AX13: =Allocations!AJ13*$Q13 -> 0 | AY13: =Allocations!AK13*$Q13 -> 0 | AZ13: =Allocations!AL13*$Q13 -> 0 | BA13: =SUM(U13:AZ13) -> 0 | BB13: =Q13-BA13 -> 0 | BC13: =B13 -> ANDREWS, Courtney A.
A14: =Allocations!A14 -> 8 | B14: =Allocations!B14 -> BIRDSONG, Rhonda June 30 | C14: =Allocations!C14 -> OICA | Q14: =E14*$P$4 -> 0 | R14: 0 | U14: =Allocations!F14*$Q14 -> 0 | V14: =Allocations!G14*$Q14 -> 0 | W14: =Allocations!H14*$Q14 -> 0 | X14: =Allocations!I14*$Q14 -> 0 | Y14: =Allocations!J14*$Q14 -> 0 | Z14: =Allocations!L14*$Q14 -> 0 | AA14: =Allocations!M14*$Q14 -> 0 | AB14: =Allocations!S14*$Q14 -> 0 | AC14: =Allocations!N14*$Q14 -> 0 | AE14: =Allocations!O14*$Q14 -> 0 | AF14: =Allocations!Q14*$Q14 -> 0 | AG14: =Allocations!E14*$Q14 -> 0 | AH14: =Allocations!T14*$Q14 -> 0 | AI14: =Allocations!AE14*$Q14 -> 0 | AK14: =Allocations!Z14*$Q14 -> 0 | AL14: =Allocations!AA14*$Q14 -> 0 | AM14: =Allocations!AB14*$Q14 -> 0 | AO14: =Allocations!AC14*$Q14 -> 0 | AP14: =Allocations!Y14*$Q14 -> 0 | AQ14: =Allocations!X14*$Q14 -> 0 | AR14: =Allocations!V14*$Q14 -> 0 | AS14: =Allocations!W14*$Q14 -> 0 | AT14: =Allocations!R14*$Q14 -> 0 | AU14: =Allocations!AG14*$Q14 -> 0 | AV14: =Allocations!AH14*$Q14 -> 0 | AW14: =Allocations!AI14*$Q14 -> 0 | AX14: =Allocations!AJ14*$Q14 -> 0 | AY14: =Allocations!AK14*$Q14 -> 0 | AZ14: =Allocations!AL14*$Q14 -> 0 | BA14: =SUM(U14:AZ14) -> 0 | BB14: =Q14-BA14 -> 0 | BC14: =B14 -> BIRDSONG, Rhonda June 30
A15: =Allocations!A15 -> 9 | B15: =Allocations!B15 -> Bizi, Raymond | C15: =Allocations!C15 -> Americorp | Q15: =E15*$P$4 -> 0 | R15: 0 | S15: 0 | T15: 0 | U15: =Allocations!F15*$Q15 -> 0 | V15: =Allocations!G15*$Q15 -> 0 | W15: =Allocations!H15*$Q15 -> 0 | X15: =Allocations!I15*$Q15 -> 0 | Y15: =Allocations!J15*$Q15 -> 0 | Z15: =Allocations!L15*$Q15 -> 0 | AA15: =Allocations!M15*$Q15 -> 0 | AB15: =Allocations!S15*$Q15 -> 0 | AC15: =Allocations!N15*$Q15 -> 0 | AE15: =Allocations!O15*$Q15 -> 0 | AF15: =Allocations!Q15*$Q15 -> 0 | AG15: =Allocations!E15*$Q15 -> 0 | AH15: =Allocations!T15*$Q15 -> 0 | AI15: =Allocations!AE15*$Q15 -> 0 | AK15: =Allocations!Z15*$Q15 -> 0 | AL15: =Allocations!AA15*$Q15 -> 0 | AM15: =Allocations!AB15*$Q15 -> 0 | AO15: =Allocations!AC15*$Q15 -> 0 | AP15: =Allocations!Y15*$Q15 -> 0 | AQ15: =Allocations!X15*$Q15 -> 0 | AR15: =Allocations!V15*$Q15 -> 0 | AS15: =Allocations!W15*$Q15 -> 0 | AT15: =Allocations!R15*$Q15 -> 0 | AU15: =Allocations!AG15*$Q15 -> 0 | AV15: =Allocations!AH15*$Q15 -> 0 | AW15: =Allocations!AI15*$Q15 -> 0 | AX15: =Allocations!AJ15*$Q15 -> 0 | AY15: =Allocations!AK15*$Q15 -> 0 | AZ15: =Allocations!AL15*$Q15 -> 0 | BA15: =SUM(U15:AZ15) -> 0 | BB15: =Q15-BA15 -> 0 | BC15: =B15 -> Bizi, Raymond
A16: =Allocations!A16 -> 10 | B16: =Allocations!B16 -> BROWN,Denise- Wrap | C16: =Allocations!C16 -> Abbott | Q16: =E16*$P$4 -> 0 | R16: 0 | S16: 0 | T16: 0 | U16: =Allocations!F16*$Q16 -> 0 | V16: =Allocations!G16*$Q16 -> 0 | W16: =Allocations!H16*$Q16 -> 0 | X16: =Allocations!I16*$Q16 -> 0 | Y16: =Allocations!J16*$Q16 -> 0 | Z16: =Allocations!L16*$Q16 -> 0 | AA16: =Allocations!M16*$Q16 -> 0 | AB16: =Allocations!S16*$Q16 -> 0 | AC16: =Allocations!N16*$Q16 -> 0 | AE16: =Allocations!O16*$Q16 -> 0 | AF16: =Allocations!Q16*$Q16 -> 0 | AG16: =Allocations!E16*$Q16 -> 0 | AH16: =Allocations!T16*$Q16 -> 0 | AI16: =Allocations!AE16*$Q16 -> 0 | AK16: =Allocations!Z16*$Q16 -> 0 | AL16: =Allocations!AA16*$Q16 -> 0 | AM16: =Allocations!AB16*$Q16 -> 0 | AO16: =Allocations!AC16*$Q16 -> 0 | AP16: =Allocations!Y16*$Q16 -> 0 | AQ16: =Allocations!X16*$Q16 -> 0 | AR16: =Allocations!V16*$Q16 -> 0 | AS16: =Allocations!W16*$Q16 -> 0 | AT16: =Allocations!R16*$Q16 -> 0 | AU16: =Allocations!AG16*$Q16 -> 0 | AV16: =Allocations!AH16*$Q16 -> 0 | AW16: =Allocations!AI16*$Q16 -> 0 | AX16: =Allocations!AJ16*$Q16 -> 0 | AY16: =Allocations!AK16*$Q16 -> 0 | AZ16: =Allocations!AL16*$Q16 -> 0 | BA16: =SUM(U16:AZ16) -> 0 | BB16: =Q16-BA16 -> 0 | BC16: =B16 -> BROWN,Denise- Wrap
A17: =Allocations!A17 -> 11 | B17: =Allocations!B17 -> BROWN,Denise - Summer
A18: =Allocations!A18 -> 12 | B18: =Allocations!B18 -> BRYANT, Roni- Summer | C18: =Allocations!C18 -> Abbott | Q18: =E18*$P$4 -> 0 | R18: 0 | S18: 0 | T18: 0 | U18: =Allocations!F18*$Q18 -> 0 | V18: =Allocations!G18*$Q18 -> 0 | W18: =Allocations!H18*$Q18 -> 0 | X18: =Allocations!I18*$Q18 -> 0 | Y18: =Allocations!J18*$Q18 -> 0 | Z18: =Allocations!L18*$Q18 -> 0 | AA18: =Allocations!M18*$Q18 -> 0 | AB18: =Allocations!S18*$Q18 -> 0 | AC18: =Allocations!N18*$Q18 -> 0 | AE18: =Allocations!O18*$Q18 -> 0 | AF18: =Allocations!Q18*$Q18 -> 0 | AG18: =Allocations!E18*$Q18 -> 0 | AH18: =Allocations!T18*$Q18 -> 0 | AI18: =Allocations!AE18*$Q18 -> 0 | AK18: =Allocations!Z18*$Q18 -> 0 | AL18: =Allocations!AA18*$Q18 -> 0 | AM18: =Allocations!AB18*$Q18 -> 0 | AO18: =Allocations!AC18*$Q18 -> 0 | AP18: =Allocations!Y18*$Q18 -> 0 | AQ18: =Allocations!X18*$Q18 -> 0 | AR18: =Allocations!V18*$Q18 -> 0 | AS18: =Allocations!W18*$Q18 -> 0 | AT18: =Allocations!R18*$Q18 -> 0 | AU18: =Allocations!AG18*$Q18 -> 0 | AV18: =Allocations!AH18*$Q18 -> 0 | AW18: =Allocations!AI18*$Q18 -> 0 | AX18: =Allocations!AJ18*$Q18 -> 0 | AY18: =Allocations!AK18*$Q18 -> 0 | AZ18: =Allocations!AL18*$Q18 -> 0 | BA18: =SUM(U18:AZ18) -> 0 | BB18: =Q18-BA18 -> 0 | BC18: =B18 -> BRYANT, Roni- Summer
A19: =Allocations!A19 -> 13 | B19: =Allocations!B19 -> BRYANT, Roni | C19: =Allocations!C19 -> Abbott | Q19: =E19*$P$4 -> 0 | R19: 0 | U19: =Allocations!F19*$Q19 -> 0 | V19: =Allocations!G19*$Q19 -> 0 | W19: =Allocations!H19*$Q19 -> 0 | X19: =Allocations!I19*$Q19 -> 0 | Y19: =Allocations!J19*$Q19 -> 0 | Z19: =Allocations!L19*$Q19 -> 0 | AA19: =Allocations!M19*$Q19 -> 0 | AB19: =Allocations!S19*$Q19 -> 0 | AC19: =Allocations!N19*$Q19 -> 0 | AE19: =Allocations!O19*$Q19 -> 0 | AF19: =Allocations!Q19*$Q19 -> 0 | AG19: =Allocations!E19*$Q19 -> 0 | AH19: =Allocations!T19*$Q19 -> 0 | AI19: =Allocations!AE19*$Q19 -> 0 | AK19: =Allocations!Z19*$Q19 -> 0 | AL19: =Allocations!AA19*$Q19 -> 0 | AM19: =Allocations!AB19*$Q19 -> 0 | AO19: =Allocations!AC19*$Q19 -> 0 | AP19: =Allocations!Y19*$Q19 -> 0 | AQ19: =Allocations!X19*$Q19 -> 0 | AR19: =Allocations!V19*$Q19 -> 0 | AS19: =Allocations!W19*$Q19 -> 0 | AT19: =Allocations!R19*$Q19 -> 0 | AU19: =Allocations!AG19*$Q19 -> 0 | AV19: =Allocations!AH19*$Q19 -> 0 | AW19: =Allocations!AI19*$Q19 -> 0 | AX19: =Allocations!AJ19*$Q19 -> 0 | AY19: =Allocations!AK19*$Q19 -> 0 | AZ19: =Allocations!AL19*$Q19 -> 0 | BA19: =SUM(U19:AZ19) -> 0 | BB19: =Q19-BA19 -> 0 | BC19: =B19 -> BRYANT, Roni
A20: =Allocations!A20 -> 14 | B20: =Allocations!B20 -> BUTLER, Ciji | C20: =Allocations!C20 -> USJP | Q20: =E20*$P$4 -> 0 | R20: 0 | S20: 0 | T20: 0 | U20: =Allocations!F20*$Q20 -> 0 | V20: =Allocations!G20*$Q20 -> 0 | W20: =Allocations!H20*$Q20 -> 0 | X20: =Allocations!I20*$Q20 -> 0 | Y20: =Allocations!J20*$Q20 -> 0 | Z20: =Allocations!L20*$Q20 -> 0 | AA20: =Allocations!M20*$Q20 -> 0 | AB20: =Allocations!S20*$Q20 -> 0 | AC20: =Allocations!N20*$Q20 -> 0 | AE20: =Allocations!O20*$Q20 -> 0 | AF20: =Allocations!Q20*$Q20 -> 0 | AG20: =Allocations!E20*$Q20 -> 0 | AH20: =Allocations!T20*$Q20 -> 0 | AI20: =Allocations!AE20*$Q20 -> 0 | AK20: =Allocations!Z20*$Q20 -> 0 | AL20: =Allocations!AA20*$Q20 -> 0 | AM20: =Allocations!AB20*$Q20 -> 0 | AO20: =Allocations!AC20*$Q20 -> 0 | AP20: =Allocations!Y20*$Q20 -> 0 | AQ20: =Allocations!X20*$Q20 -> 0 | AR20: =Allocations!V20*$Q20 -> 0 | AS20: =Allocations!W20*$Q20 -> 0 | AT20: =Allocations!R20*$Q20 -> 0 | AU20: =Allocations!AG20*$Q20 -> 0 | AV20: =Allocations!AH20*$Q20 -> 0 | AW20: =Allocations!AI20*$Q20 -> 0 | AX20: =Allocations!AJ20*$Q20 -> 0 | AY20: =Allocations!AK20*$Q20 -> 0 | AZ20: =Allocations!AL20*$Q20 -> 0 | BA20: =SUM(U20:AZ20) -> 0 | BB20: =Q20-BA20 -> 0 | BC20: =B20 -> BUTLER, Ciji
A21: =Allocations!A21 -> 15 | B21: =Allocations!B21 -> CAMPBELL, Nikiesha K. | C21: =Allocations!C21 -> Americorp | Q21: =E21*$P$4 -> 0 | R21: 0 | S21: 0 | T21: 0 | U21: =Allocations!F21*$Q21 -> 0 | V21: =Allocations!G21*$Q21 -> 0 | W21: =Allocations!H21*$Q21 -> 0 | X21: =Allocations!I21*$Q21 -> 0 | Y21: =Allocations!J21*$Q21 -> 0 | Z21: =Allocations!L21*$Q21 -> 0 | AA21: =Allocations!M21*$Q21 -> 0 | AB21: =Allocations!S21*$Q21 -> 0 | AC21: =Allocations!N21*$Q21 -> 0 | AE21: =Allocations!O21*$Q21 -> 0 | AF21: =Allocations!Q21*$Q21 -> 0 | AG21: =Allocations!E21*$Q21 -> 0 | AH21: =Allocations!T21*$Q21 -> 0 | AI21: =Allocations!AE21*$Q21 -> 0 | AK21: =Allocations!Z21*$Q21 -> 0 | AL21: =Allocations!AA21*$Q21 -> 0 | AM21: =Allocations!AB21*$Q21 -> 0 | AO21: =Allocations!AC21*$Q21 -> 0 | AP21: =Allocations!Y21*$Q21 -> 0 | AQ21: =Allocations!X21*$Q21 -> 0 | AR21: =Allocations!V21*$Q21 -> 0 | AS21: =Allocations!W21*$Q21 -> 0 | AT21: =Allocations!R21*$Q21 -> 0 | AU21: =Allocations!AG21*$Q21 -> 0 | AV21: =Allocations!AH21*$Q21 -> 0 | AW21: =Allocations!AI21*$Q21 -> 0 | AX21: =Allocations!AJ21*$Q21 -> 0 | AY21: =Allocations!AK21*$Q21 -> 0 | AZ21: =Allocations!AL21*$Q21 -> 0 | BA21: =SUM(U21:AZ21) -> 0 | BB21: =Q21-BA21 -> 0 | BC21: =B21 -> CAMPBELL, Nikiesha K.
A22: =Allocations!A22 -> 16 | B22: =Allocations!B22 -> CASTELLANOS, Rita J. | C22: =Allocations!C22 -> Abbott | Q22: =E22*$P$4 -> 0 | R22: 0 | S22: 0 | T22: 0 | U22: =Allocations!F22*$Q22 -> 0 | V22: =Allocations!G22*$Q22 -> 0 | W22: =Allocations!H22*$Q22 -> 0 | X22: =Allocations!I22*$Q22 -> 0 | Y22: =Allocations!J22*$Q22 -> 0 | Z22: =Allocations!L22*$Q22 -> 0 | AA22: =Allocations!M22*$Q22 -> 0 | AB22: =Allocations!S22*$Q22 -> 0 | AC22: =Allocations!N22*$Q22 -> 0 | AE22: =Allocations!O22*$Q22 -> 0 | AF22: =Allocations!Q22*$Q22 -> 0 | AG22: =Allocations!E22*$Q22 -> 0 | AH22: =Allocations!T22*$Q22 -> 0 | AI22: =Allocations!AE22*$Q22 -> 0 | AK22: =Allocations!Z22*$Q22 -> 0 | AL22: =Allocations!AA22*$Q22 -> 0 | AM22: =Allocations!AB22*$Q22 -> 0 | AO22: =Allocations!AC22*$Q22 -> 0 | AP22: =Allocations!Y22*$Q22 -> 0 | AQ22: =Allocations!X22*$Q22 -> 0 | AR22: =Allocations!V22*$Q22 -> 0 | AS22: =Allocations!W22*$Q22 -> 0 | AT22: =Allocations!R22*$Q22 -> 0 | AU22: =Allocations!AG22*$Q22 -> 0 | AV22: =Allocations!AH22*$Q22 -> 0 | AW22: =Allocations!AI22*$Q22 -> 0 | AX22: =Allocations!AJ22*$Q22 -> 0 | AY22: =Allocations!AK22*$Q22 -> 0 | AZ22: =Allocations!AL22*$Q22 -> 0 | BA22: =SUM(U22:AZ22) -> 0 | BB22: =Q22-BA22 -> 0 | BC22: =B22 -> CASTELLANOS, Rita J.
A23: =Allocations!A23 -> 17 | B23: =Allocations!B23 -> CERNA, Irene | C23: =Allocations!C23 -> USJP | Q23: =E23*$P$4 -> 0 | R23: 0 | S23: 0 | T23: 0 | U23: =Allocations!F23*$Q23 -> 0 | V23: =Allocations!G23*$Q23 -> 0 | W23: =Allocations!H23*$Q23 -> 0 | X23: =Allocations!I23*$Q23 -> 0 | Y23: =Allocations!J23*$Q23 -> 0 | Z23: =Allocations!L23*$Q23 -> 0 | AA23: =Allocations!M23*$Q23 -> 0 | AB23: =Allocations!S23*$Q23 -> 0 | AC23: =Allocations!N23*$Q23 -> 0 | AE23: =Allocations!O23*$Q23 -> 0 | AF23: =Allocations!Q23*$Q23 -> 0 | AG23: =Allocations!E23*$Q23 -> 0 | AH23: =Allocations!T23*$Q23 -> 0 | AI23: =Allocations!AE23*$Q23 -> 0 | AK23: =Allocations!Z23*$Q23 -> 0 | AL23: =Allocations!AA23*$Q23 -> 0 | AM23: =Allocations!AB23*$Q23 -> 0 | AO23: =Allocations!AC23*$Q23 -> 0 | AP23: =Allocations!Y23*$Q23 -> 0 | AQ23: =Allocations!X23*$Q23 -> 0 | AR23: =Allocations!V23*$Q23 -> 0 | AS23: =Allocations!W23*$Q23 -> 0 | AT23: =Allocations!R23*$Q23 -> 0 | AU23: =Allocations!AG23*$Q23 -> 0 | AV23: =Allocations!AH23*$Q23 -> 0 | AW23: =Allocations!AI23*$Q23 -> 0 | AX23: =Allocations!AJ23*$Q23 -> 0 | AY23: =Allocations!AK23*$Q23 -> 0 | AZ23: =Allocations!AL23*$Q23 -> 0 | BA23: =SUM(U23:AZ23) -> 0 | BB23: =Q23-BA23 -> 0 | BC23: =B23 -> CERNA, Irene
A24: =Allocations!A24 -> 18 | B24: =Allocations!B24 -> COLEMAN, Zabrina J. | C24: =Allocations!C24 -> EHS | Q24: =E24*$P$4 -> 0 | R24: 0 | U24: =Allocations!F24*$Q24 -> 0 | V24: =Allocations!G24*$Q24 -> 0 | W24: =Allocations!H24*$Q24 -> 0 | X24: =Allocations!I24*$Q24 -> 0 | Y24: =Allocations!J24*$Q24 -> 0 | Z24: =Allocations!L24*$Q24 -> 0 | AA24: =Allocations!M24*$Q24 -> 0 | AB24: =Allocations!S24*$Q24 -> 0 | AC24: =Allocations!N24*$Q24 -> 0 | AE24: =Allocations!O24*$Q24 -> 0 | AF24: =Allocations!Q24*$Q24 -> 0 | AG24: =Allocations!E24*$Q24 -> 0 | AH24: =Allocations!T24*$Q24 -> 0 | AI24: =Allocations!AE24*$Q24 -> 0 | AK24: =Allocations!Z24*$Q24 -> 0 | AL24: =Allocations!AA24*$Q24 -> 0 | AM24: =Allocations!AB24*$Q24 -> 0 | AO24: =Allocations!AC24*$Q24 -> 0 | AP24: =Allocations!Y24*$Q24 -> 0 | AQ24: =Allocations!X24*$Q24 -> 0 | AR24: =Allocations!V24*$Q24 -> 0 | AS24: =Allocations!W24*$Q24 -> 0 | AT24: =Allocations!R24*$Q24 -> 0 | AU24: =Allocations!AG24*$Q24 -> 0 | AV24: =Allocations!AH24*$Q24 -> 0 | AW24: =Allocations!AI24*$Q24 -> 0 | AX24: =Allocations!AJ24*$Q24 -> 0 | AY24: =Allocations!AK24*$Q24 -> 0 | AZ24: =Allocations!AL24*$Q24 -> 0 | BA24: =SUM(U24:AZ24) -> 0 | BB24: =Q24-BA24 -> 0 | BC24: =B24 -> COLEMAN, Zabrina J.
A25: =Allocations!A25 -> 19 | B25: =Allocations!B25 -> COOPER, Cassandra June 30 | C25: =Allocations!C25 -> OICA | Q25: =E25*$P$4 -> 0 | R25: 0 | S25: 0 | T25: 0 | U25: =Allocations!F25*$Q25 -> 0 | V25: =Allocations!G25*$Q25 -> 0 | W25: =Allocations!H25*$Q25 -> 0 | X25: =Allocations!I25*$Q25 -> 0 | Y25: =Allocations!J25*$Q25 -> 0 | Z25: =Allocations!L25*$Q25 -> 0 | AA25: =Allocations!M25*$Q25 -> 0 | AB25: =Allocations!S25*$Q25 -> 0 | AC25: =Allocations!N25*$Q25 -> 0 | AE25: =Allocations!O25*$Q25 -> 0 | AF25: =Allocations!Q25*$Q25 -> 0 | AG25: =Allocations!E25*$Q25 -> 0 | AH25: =Allocations!T25*$Q25 -> 0 | AI25: =Allocations!AE25*$Q25 -> 0 | AK25: =Allocations!Z25*$Q25 -> 0 | AL25: =Allocations!AA25*$Q25 -> 0 | AM25: =Allocations!AB25*$Q25 -> 0 | AO25: =Allocations!AC25*$Q25 -> 0 | AP25: =Allocations!Y25*$Q25 -> 0 | AQ25: =Allocations!X25*$Q25 -> 0 | AR25: =Allocations!V25*$Q25 -> 0 | AS25: =Allocations!W25*$Q25 -> 0 | AT25: =Allocations!R25*$Q25 -> 0 | AU25: =Allocations!AG25*$Q25 -> 0 | AV25: =Allocations!AH25*$Q25 -> 0 | AW25: =Allocations!AI25*$Q25 -> 0 | AX25: =Allocations!AJ25*$Q25 -> 0 | AY25: =Allocations!AK25*$Q25 -> 0 | AZ25: =Allocations!AL25*$Q25 -> 0 | BA25: =SUM(U25:AZ25) -> 0 | BB25: =Q25-BA25 -> 0 | BC25: =B25 -> COOPER, Cassandra June 30 | BS25: =Allocations!#REF! -> #REF! | BT25: =Allocations!#REF! -> #REF! | BU25: =Allocations!#REF! -> #REF! | BV25: =Allocations!#REF! -> #REF! | BW25: =Allocations!#REF! -> #REF! | BX25: =Allocations!#REF! -> #REF! | BY25: =Allocations!#REF! -> #REF! | BZ25: =Allocations!#REF! -> #REF! | ... XEF25: =Allocations!#REF! -> #REF!
A26: =Allocations!A26 -> 20 | B26: =Allocations!B26 -> COOPER, Cassandra July | C26: =Allocations!C26 -> FOC, ESG
A27: =Allocations!A27 -> 21 | B27: =Allocations!B27 -> Counts, Monique Lamae | C27: =Allocations!C27 -> Americorp | Q27: =E27*$P$4 -> 0 | R27: 0 | S27: 0 | T27: 0 | U27: =Allocations!F27*$Q27 -> 0 | V27: =Allocations!G27*$Q27 -> 0 | W27: =Allocations!H27*$Q27 -> 0 | X27: =Allocations!I27*$Q27 -> 0 | Y27: =Allocations!J27*$Q27 -> 0 | Z27: =Allocations!L27*$Q27 -> 0 | AA27: =Allocations!M27*$Q27 -> 0 | AB27: =Allocations!S27*$Q27 -> 0 | AC27: =Allocations!N27*$Q27 -> 0 | AE27: =Allocations!O27*$Q27 -> 0 | AF27: =Allocations!Q27*$Q27 -> 0 | AG27: =Allocations!E27*$Q27 -> 0 | AH27: =Allocations!T27*$Q27 -> 0 | AI27: =Allocations!AE27*$Q27 -> 0 | AK27: =Allocations!Z27*$Q27 -> 0 | AL27: =Allocations!AA27*$Q27 -> 0 | AM27: =Allocations!AB27*$Q27 -> 0 | AO27: =Allocations!AC27*$Q27 -> 0 | AP27: =Allocations!Y27*$Q27 -> 0 | AQ27: =Allocations!X27*$Q27 -> 0 | AR27: =Allocations!V27*$Q27 -> 0 | AS27: =Allocations!W27*$Q27 -> 0 | AT27: =Allocations!R27*$Q27 -> 0 | AU27: =Allocations!AG27*$Q27 -> 0 | AV27: =Allocations!AH27*$Q27 -> 0 | AW27: =Allocations!AI27*$Q27 -> 0 | AX27: =Allocations!AJ27*$Q27 -> 0 | AY27: =Allocations!AK27*$Q27 -> 0 | AZ27: =Allocations!AL27*$Q27 -> 0 | BA27: =SUM(U27:AZ27) -> 0 | BB27: =Q27-BA27 -> 0 | BC27: =B27 -> Counts, Monique Lamae
