Workbook

Sheet Nov 2019 Alloc 
B1: November Cost Allocations | M1: 7251 | N1: 7252 | O1: 7253 | P1: 7254 | Q1: 7260.1 | R1: 8140 | S1: 7515.5 | T1: 7521 | U1: 7521 | V1: 8112 | W1: 8135.5 | X1: 8191 | Y1: 8210.5 | Z1: 8229.1 | AA1: 8239 | AB1: 8265 | AC1: 8266 | AF1: 7248
M2: FICA | N2: MEDI | O2: SUI | P2: Disability | Q2: Payroll Fees | R2: Postage | S2: IT Consultants | T2: Audit Fees | U2: Acctg Fees | V2: Supplies | W2: Telephone | X2: Web Hosting | Y2: Utilities | Z2: Eq Lease | AA2: Repairs | AB2: Mortgage Int | AC2: Gen Insur | AF2: W/ Comp
M3: =M46 -> 10024 | N3: =N46 -> 2446 | O3: =O46 -> 2449 | P3: =P46 -> 481 | Q3: =Q46 -> 1981 | S3: 3006 | T3: 6000 | U3: =10655-6000 -> 4655 | V3: 2022 | W3: 733 | X3: 312 | Y3: 1261 | Z3: 2637 | AA3: 765 | AB3: 1985 | AC3: 4654 | AF3: 6787
G4: headcount | M4: 1 | N4: 2 | O4: 3 | P4: 4 | Q4: 5 | R4: 6 | S4: 7 | T4: 8 | U4: 8 | V4: 9 | W4: 10 | X4: 11 | Y4: 12 | Z4: 13 | AA4: 14 | AB4: 15 | AC4: 15 | AF4: 0.04
D5: 7222 | E5: Taxes | F5: W/C | J5: Taxes | K5: Salary | L5: Headcount
B6: 41 | C6: Thriftworks | H6: 0 | J6: =H6/$I$35 -> 0 | K6: =H6/$I$37 -> 0 | L6: =G6/$G$38 -> 0 | M6: =J6*$M$3 -> 0 | N6: =J6*$N$3 -> 0 | O6: =J6*$O$3 -> 0 | P6: =J6*$P$3 -> 0 | Q6: =K6*$Q$3 -> 0 | R6: =K6*$R$3 -> 0 | S6: =K6*$S$3 -> 0 | T6: =K6*$T$3 -> 0 | U6: =K6*$U$3 -> 0 | V6: =K6*$V$3 -> 0 | W6: =K6*$W$3 -> 0 | X6: =K6*$X$3 -> 0 | Y6: =K6*$Y$3 -> 0 | Z6: =K6*$Z$3 -> 0 | AA6: =K6*$AA$3 -> 0 | AB6: =J6*$AB$3 -> 0 | AC6: =K6*$AC$3 -> 0 | AE6: =H6/$H$39 -> 0 | AF6: =AE6*$AF$3 -> 0
B7: 111 | C7: Abbott | G7: 8 | H7: 46682 | J7: =H7/$I$35 -> 0.26998327 | K7: =H7/$I$37 -> 0.24606292 | L7: =G7/$G$38 -> 0.22857143 | M7: =J7*$M$3 -> 2706.3123 | N7: =J7*$N$3 -> 660.37908 | O7: =J7*$O$3 -> 661.18903 | P7: =J7*$P$3 -> 129.86195 | Q7: =K7*$Q$3 -> 487.45065 | R7: =K7*$R$3 -> 0 | S7: =K7*$S$3 -> 739.66515 | T7: =K7*$T$3 -> 1476.3775 | U7: =K7*$U$3 -> 1145.4229 | V7: =K7*$V$3 -> 497.53923 | W7: =K7*$W$3 -> 180.36412 | X7: =K7*$X$3 -> 76.771633 | Y7: =K7*$Y$3 -> 310.28535 | Z7: =K7*$Z$3 -> 648.86793 | AA7: =K7*$AA$3 -> 188.23814 | AB7: =J7*$AB$3 -> 535.91679 | AC7: =K7*$AC$3 -> 1145.1769 | AE7: =H7/$H$39 -> 0.16288621 | AF7: =AE7*$AF$3 -> 1105.5087
B8: 111B | C8: Abbott Fees | G8: 1 | H8: 2588 | J8: =H8/$I$35 -> 0.014967583 | K8: =H8/$I$37 -> 0.013641465 | L8: =G8/$G$38 -> 0.028571429 | M8: =J8*$M$3 -> 150.03505 | N8: =J8*$N$3 -> 36.610708 | O8: =J8*$O$3 -> 36.65561 | P8: =J8*$P$3 -> 7.1994074 | Q8: =K8*$Q$3 -> 27.023741 | R8: =K8*$R$3 -> 0 | S8: =K8*$S$3 -> 41.006242 | T8: =K8*$T$3 -> 81.848787 | U8: =K8*$U$3 -> 63.501018 | V8: =K8*$V$3 -> 27.583041 | W8: =K8*$W$3 -> 9.9991935 | X8: =K8*$X$3 -> 4.2561369 | Y8: =K8*$Y$3 -> 17.201887 | Z8: =K8*$Z$3 -> 35.972542 | AA8: =K8*$AA$3 -> 10.43572 | AB8: =J8*$AB$3 -> 29.710652 | AC8: =K8*$AC$3 -> 63.487376 | AE8: =H8/$H$39 -> 0.009030237 | AF8: =AE8*$AF$3 -> 61.288218
B9: 111A | C9: Abbott - Other | G9: 1 | H9: 3654 | J9: =H9/$I$35 -> 0.021132746 | K9: =H9/$I$37 -> 0.019260399 | L9: =G9/$G$38 -> 0.028571429 | M9: =J9*$M$3 -> 211.83465 | N9: =J9*$N$3 -> 51.690698 | O9: =J9*$O$3 -> 51.754096 | P9: =J9*$P$3 -> 10.164851 | Q9: =K9*$Q$3 -> 38.15485 | R9: =K9*$R$3 -> 0 | S9: =K9*$S$3 -> 57.896758 | T9: =K9*$T$3 -> 115.56239 | U9: =K9*$U$3 -> 89.657155 | V9: =K9*$V$3 -> 38.944526 | W9: =K9*$W$3 -> 14.117872 | X9: =K9*$X$3 -> 6.0092444 | Y9: =K9*$Y$3 -> 24.287363 | Z9: =K9*$Z$3 -> 50.789671 | AA9: =K9*$AA$3 -> 14.734205 | AB9: =J9*$AB$3 -> 41.948502 | AC9: =K9*$AC$3 -> 89.637895 | AE9: =H9/$H$39 -> 0.012749801 | AF9: =AE9*$AF$3 -> 86.532902
B10: 111F | C10: Abbott Food | G10: 0 | H10: 358 | J10: =H10/$I$35 -> 0.0020704771 | K10: =H10/$I$37 -> 0.0018870341 | L10: =G10/$G$38 -> 0 | M10: =J10*$M$3 -> 20.754462 | N10: =J10*$N$3 -> 5.0643869 | O10: =J10*$O$3 -> 5.0705984 | P10: =J10*$P$3 -> 0.99589947 | Q10: =K10*$Q$3 -> 3.7382146 | R10: =K10*$R$3 -> 0 | S10: =K10*$S$3 -> 5.6724246 | T10: =K10*$T$3 -> 11.322205 | U10: =K10*$U$3 -> 8.7841439 | V10: =K10*$V$3 -> 3.815583 | W10: =K10*$W$3 -> 1.383196 | X10: =K10*$X$3 -> 0.58875465 | Y10: =K10*$Y$3 -> 2.37955 | Z10: =K10*$Z$3 -> 4.976109 | AA10: =K10*$AA$3 -> 1.4435811 | AB10: =J10*$AB$3 -> 4.109897 | AC10: =K10*$AC$3 -> 8.7822568 | AE10: =H10/$H$39 -> 0.0012491595 | AF10: =AE10*$AF$3 -> 8.4780457
B11: 112 | C11: EHS | G11: 1 | H11: 7522 | J11: =H11/$I$35 -> 0.043503152 | K11: =H11/$I$37 -> 0.039648801 | L11: =G11/$G$38 -> 0.028571429 | M11: =J11*$M$3 -> 436.0756 | N11: =J11*$N$3 -> 106.40871 | O11: =J11*$O$3 -> 106.53922 | P11: =J11*$P$3 -> 20.925016 | Q11: =K11*$Q$3 -> 78.544274 | R11: =K11*$R$3 -> 0 | S11: =K11*$S$3 -> 119.1843 | T11: =K11*$T$3 -> 237.8928 | U11: =K11*$U$3 -> 184.56517 | V11: =K11*$V$3 -> 80.169875 | W11: =K11*$W$3 -> 29.062571 | X11: =K11*$X$3 -> 12.370426 | Y11: =K11*$Y$3 -> 49.997138 | Z11: =K11*$Z$3 -> 104.55389 | AA11: =K11*$AA$3 -> 30.331333 | AB11: =J11*$AB$3 -> 86.353757 | AC11: =K11*$AC$3 -> 184.52552 | AE11: =H11/$H$39 -> 0.026246307 | AF11: =AE11*$AF$3 -> 178.13369
B12: 114 | C12: Summer Camp | H12: 0 | J12: =H12/$I$35 -> 0 | K12: =H12/$I$37 -> 0 | L12: =G12/$G$38 -> 0 | M12: =J12*$M$3 -> 0 | N12: =J12*$N$3 -> 0 | O12: =J12*$O$3 -> 0 | P12: =J12*$P$3 -> 0 | Q12: =K12*$Q$3 -> 0 | R12: =K12*$R$3 -> 0 | S12: =K12*$S$3 -> 0 | T12: =K12*$T$3 -> 0 | U12: =K12*$U$3 -> 0 | V12: =K12*$V$3 -> 0 | W12: =K12*$W$3 -> 0 | X12: =K12*$X$3 -> 0 | Y12: =K12*$Y$3 -> 0 | Z12: =K12*$Z$3 -> 0 | AA12: =K12*$AA$3 -> 0 | AB12: =J12*$AB$3 -> 0 | AC12: =K12*$AC$3 -> 0 | AE12: =H12/$H$39 -> 0 | AF12: =AE12*$AF$3 -> 0
B13: 222 | C13: DCF- Coding | G13: 0.5 | H13: 5481 | J13: =H13/$I$35 -> 0.03169912 | K13: =H13/$I$37 -> 0.028890598 | L13: =G13/$G$38 -> 0.014285714 | M13: =J13*$M$3 -> 317.75198 | N13: =J13*$N$3 -> 77.536047 | O13: =J13*$O$3 -> 77.631144 | P13: =J13*$P$3 -> 15.247277 | Q13: =K13*$Q$3 -> 57.232274 | R13: =K13*$R$3 -> 0 | S13: =K13*$S$3 -> 86.845137 | T13: =K13*$T$3 -> 173.34359 | U13: =K13*$U$3 -> 134.48573 | V13: =K13*$V$3 -> 58.416789 | W13: =K13*$W$3 -> 21.176808 | X13: =K13*$X$3 -> 9.0138665 | Y13: =K13*$Y$3 -> 36.431044 | Z13: =K13*$Z$3 -> 76.184507 | AA13: =K13*$AA$3 -> 22.101307 | AB13: =J13*$AB$3 -> 62.922753 | AC13: =K13*$AC$3 -> 134.45684 | AE13: =H13/$H$39 -> 0.019124702 | AF13: =AE13*$AF$3 -> 129.79935
B14: 223 | C14: OICA | H14: 0 | J14: =H14/$I$35 -> 0 | K14: =H14/$I$37 -> 0 | L14: =G14/$G$38 -> 0 | M14: =J14*$M$3 -> 0 | N14: =J14*$N$3 -> 0 | O14: =J14*$O$3 -> 0 | P14: =J14*$P$3 -> 0 | Q14: =K14*$Q$3 -> 0 | R14: =K14*$R$3 -> 0 | S14: =K14*$S$3 -> 0 | T14: =K14*$T$3 -> 0 | U14: =K14*$U$3 -> 0 | V14: =K14*$V$3 -> 0 | W14: =K14*$W$3 -> 0 | X14: =K14*$X$3 -> 0 | Y14: =K14*$Y$3 -> 0 | Z14: =K14*$Z$3 -> 0 | AA14: =K14*$AA$3 -> 0 | AB14: =J14*$AB$3 -> 0 | AC14: =K14*$AC$3 -> 0 | AE14: =H14/$H$39 -> 0 | AF14: =AE14*$AF$3 -> 0
B15: 334 | C15: NRTC - Admin | H15: 0 | J15: =H15/$I$35 -> 0 | K15: =H15/$I$37 -> 0 | L15: =G15/$G$38 -> 0 | M15: =J15*$M$3 -> 0 | N15: =J15*$N$3 -> 0 | O15: =J15*$O$3 -> 0 | P15: =J15*$P$3 -> 0 | Q15: =K15*$Q$3 -> 0 | R15: =K15*$R$3 -> 0 | S15: =K15*$S$3 -> 0 | T15: =K15*$T$3 -> 0 | U15: =K15*$U$3 -> 0 | V15: =K15*$V$3 -> 0 | W15: =K15*$W$3 -> 0 | X15: =K15*$X$3 -> 0 | Y15: =K15*$Y$3 -> 0 | Z15: =K15*$Z$3 -> 0 | AA15: =K15*$AA$3 -> 0 | AB15: =J15*$AB$3 -> 0 | AC15: =K15*$AC$3 -> 0 | AE15: =H15/$H$39 -> 0 | AF15: =AE15*$AF$3 -> 0
B16: 334H | C16: NRTC - Housing | G16: 0.5 | H16: 1725 | J16: =H16/$I$35 -> 0.0099764608 | K16: =H16/$I$37 -> 0.0090925527 | L16: =G16/$G$38 -> 0.014285714 | M16: =J16*$M$3 -> 100.00404 | N16: =J16*$N$3 -> 24.402423 | O16: =J16*$O$3 -> 24.432352 | P16: =J16*$P$3 -> 4.7986776 | Q16: =K16*$Q$3 -> 18.012347 | R16: =K16*$R$3 -> 0 | S16: =K16*$S$3 -> 27.332213 | T16: =K16*$T$3 -> 54.555316 | U16: =K16*$U$3 -> 42.325833 | V16: =K16*$V$3 -> 18.385142 | W16: =K16*$W$3 -> 6.6648411 | X16: =K16*$X$3 -> 2.8368764 | Y16: =K16*$Y$3 -> 11.465709 | Z16: =K16*$Z$3 -> 23.977061 | AA16: =K16*$AA$3 -> 6.9558028 | AB16: =J16*$AB$3 -> 19.803275 | AC16: =K16*$AC$3 -> 42.31674 | AE16: =H16/$H$39 -> 0.0060189949 | AF16: =AE16*$AF$3 -> 40.850918
B17: 334F | C17: NRTC FOC | H17: 0 | J17: =H17/$I$35 -> 0 | K17: =H17/$I$37 -> 0 | L17: =G17/$G$38 -> 0 | M17: =J17*$M$3 -> 0 | N17: =J17*$N$3 -> 0 | O17: =J17*$O$3 -> 0 | P17: =J17*$P$3 -> 0 | Q17: =K17*$Q$3 -> 0 | R17: =K17*$R$3 -> 0 | S17: =K17*$S$3 -> 0 | T17: =K17*$T$3 -> 0 | U17: =K17*$U$3 -> 0 | V17: =K17*$V$3 -> 0 | W17: =K17*$W$3 -> 0 | X17: =K17*$X$3 -> 0 | Y17: =K17*$Y$3 -> 0 | Z17: =K17*$Z$3 -> 0 | AA17: =K17*$AA$3 -> 0 | AB17: =J17*$AB$3 -> 0 | AC17: =K17*$AC$3 -> 0 | AE17: =H17/$H$39 -> 0 | AF17: =AE17*$AF$3 -> 0
B18: 335 | C18: NRTC 19 | G18: 0.5 | H18: 1269 | J18: =H18/$I$35 -> 0.007339205 | K18: =H18/$I$37 -> 0.0066889562 | L18: =G18/$G$38 -> 0.014285714 | M18: =J18*$M$3 -> 73.568191 | N18: =J18*$N$3 -> 17.951696 | O18: =J18*$O$3 -> 17.973713 | P18: =J18*$P$3 -> 3.5301576 | Q18: =K18*$Q$3 -> 13.250822 | R18: =K18*$R$3 -> 0 | S18: =K18*$S$3 -> 20.107002 | T18: =K18*$T$3 -> 40.133737 | U18: =K18*$U$3 -> 31.137091 | V18: =K18*$V$3 -> 13.525069 | W18: =K18*$W$3 -> 4.9030049 | X18: =K18*$X$3 -> 2.0869543 | Y18: =K18*$Y$3 -> 8.4347737 | Z18: =K18*$Z$3 -> 17.638777 | AA18: =K18*$AA$3 -> 5.1170515 | AB18: =J18*$AB$3 -> 14.568322 | AC18: =K18*$AC$3 -> 31.130402 | AE18: =H18/$H$39 -> 0.0044278867 | AF18: =AE18*$AF$3 -> 30.052067
B19: 368 | C19: Wells Fargo | G19: 1.5 | H19: 9028 | J19: =H19/$I$35 -> 0.052213036 | K19: =H19/$I$37 -> 0.047586995 | L19: =G19/$G$38 -> 0.042857143 | M19: =J19*$M$3 -> 523.38348 | N19: =J19*$N$3 -> 127.71309 | O19: =J19*$O$3 -> 127.86973 | P19: =J19*$P$3 -> 25.11447 | Q19: =K19*$Q$3 -> 94.269836 | R19: =K19*$R$3 -> 0 | S19: =K19*$S$3 -> 143.04651 | T19: =K19*$T$3 -> 285.52197 | U19: =K19*$U$3 -> 221.51746 | V19: =K19*$V$3 -> 96.220903 | W19: =K19*$W$3 -> 34.881267 | X19: =K19*$X$3 -> 14.847142 | Y19: =K19*$Y$3 -> 60.0072 | Z19: =K19*$Z$3 -> 125.4869 | AA19: =K19*$AA$3 -> 36.404051 | AB19: =J19*$AB$3 -> 103.64288 | AC19: =K19*$AC$3 -> 221.46987 | AE19: =H19/$H$39 -> 0.031501151 | AF19: =AE19*$AF$3 -> 213.79831
B20: 451 | C20: USJP | G20: 5.5 | H20: 24343 | J20: =H20/$I$35 -> 0.14078666 | K20: =H20/$I$37 -> 0.12831305 | L20: =G20/$G$38 -> 0.15714286 | M20: =J20*$M$3 -> 1411.2455 | N20: =J20*$N$3 -> 344.36416 | O20: =J20*$O$3 -> 344.78652 | P20: =J20*$P$3 -> 67.718382 | Q20: =K20*$Q$3 -> 254.18815 | R20: =K20*$R$3 -> 0 | S20: =K20*$S$3 -> 385.70903 | T20: =K20*$T$3 -> 769.8783 | U20: =K20*$U$3 -> 597.29725 | V20: =K20*$V$3 -> 259.44899 | W20: =K20*$W$3 -> 94.053465 | X20: =K20*$X$3 -> 40.033671 | Y20: =K20*$Y$3 -> 161.80276 | Z20: =K20*$Z$3 -> 338.36151 | AA20: =K20*$AA$3 -> 98.159483 | AB20: =J20*$AB$3 -> 279.46152 | AC20: =K20*$AC$3 -> 597.16893 | AE20: =H20/$H$39 -> 0.084939358 | AF20: =AE20*$AF$3 -> 576.48342
B21: 452 | C21: PACE | G21: 2 | H21: 3660 | J21: =H21/$I$35 -> 0.021167447 | K21: =H21/$I$37 -> 0.019292025 | L21: =G21/$G$38 -> 0.057142857 | M21: =J21*$M$3 -> 212.18249 | N21: =J21*$N$3 -> 51.775576 | O21: =J21*$O$3 -> 51.839078 | P21: =J21*$P$3 -> 10.181542 | Q21: =K21*$Q$3 -> 38.217501 | R21: =K21*$R$3 -> 0 | S21: =K21*$S$3 -> 57.991827 | T21: =K21*$T$3 -> 115.75215 | U21: =K21*$U$3 -> 89.804376 | V21: =K21*$V$3 -> 39.008474 | W21: =K21*$W$3 -> 14.141054 | X21: =K21*$X$3 -> 6.0191118 | Y21: =K21*$Y$3 -> 24.327243 | Z21: =K21*$Z$3 -> 50.87307 | AA21: =K21*$AA$3 -> 14.758399 | AB21: =J21*$AB$3 -> 42.017383 | AC21: =K21*$AC$3 -> 89.785084 | AE21: =H21/$H$39 -> 0.012770737 | AF21: =AE21*$AF$3 -> 86.674992
B22: 454 | C22: Prudential #1 Workforce | K22: =H22/$I$37 -> 0 | L22: =G22/$G$38 -> 0 | Q22: =K22*$Q$3 -> 0 | R22: =K22*$R$3 -> 0 | S22: =K22*$S$3 -> 0 | T22: =K22*$T$3 -> 0 | U22: =K22*$U$3 -> 0 | V22: =K22*$V$3 -> 0 | W22: =K22*$W$3 -> 0 | X22: =K22*$X$3 -> 0 | Y22: =K22*$Y$3 -> 0 | Z22: =K22*$Z$3 -> 0 | AA22: =K22*$AA$3 -> 0 | AB22: =J22*$AB$3 -> 0 | AC22: =K22*$AC$3 -> 0
B23: 467 | C23: WF - United Airlines | G23: 2 | H23: 10250 | J23: =H23/$I$35 -> 0.059280419 | K23: =H23/$I$37 -> 0.054028212 | L23: =G23/$G$38 -> 0.057142857 | M23: =J23*$M$3 -> 594.22692 | N23: =J23*$N$3 -> 144.9999 | O23: =J23*$O$3 -> 145.17775 | P23: =J23*$P$3 -> 28.513882 | Q23: =K23*$Q$3 -> 107.02989 | R23: =K23*$R$3 -> 0 | S23: =K23*$S$3 -> 162.4088 | T23: =K23*$T$3 -> 324.16927 | U23: =K23*$U$3 -> 251.50133 | V23: =K23*$V$3 -> 109.24504 | W23: =K23*$W$3 -> 39.602679 | X23: =K23*$X$3 -> 16.856802 | Y23: =K23*$Y$3 -> 68.129575 | Z23: =K23*$Z$3 -> 142.47239 | AA23: =K23*$AA$3 -> 41.331582 | AB23: =J23*$AB$3 -> 117.67163 | AC23: =K23*$AC$3 -> 251.4473 | AE23: =H23/$H$39 -> 0.035765042 | AF23: =AE23*$AF$3 -> 242.73734
B24: 468 | C24: Newark Alliance | G24: 1 | H24: 9462 | J24: =H24/$I$35 -> 0.054723056 | K24: =H24/$I$37 -> 0.049874628 | L24: =G24/$G$38 -> 0.028571429 | M24: =J24*$M$3 -> 548.54391 | N24: =J24*$N$3 -> 133.8526 | O24: =J24*$O$3 -> 134.01676 | P24: =J24*$P$3 -> 26.32179 | Q24: =K24*$Q$3 -> 98.801638 | R24: =K24*$R$3 -> 0 | S24: =K24*$S$3 -> 149.92313 | T24: =K24*$T$3 -> 299.24777 | U24: =K24*$U$3 -> 232.16639 | V24: =K24*$V$3 -> 100.8465 | W24: =K24*$W$3 -> 36.558102 | X24: =K24*$X$3 -> 15.560884 | Y24: =K24*$Y$3 -> 62.891906 | Z24: =K24*$Z$3 -> 131.51939 | AA24: =K24*$AA$3 -> 38.154091 | AB24: =J24*$AB$3 -> 108.62527 | AC24: =K24*$AC$3 -> 232.11652 | AE24: =H24/$H$39 -> 0.033015496 | AF24: =AE24*$AF$3 -> 224.07617
B25: 502 | C25: ESG | G25: 1.5 | H25: 2518 | J25: =H25/$I$35 -> 0.014562741 | K25: =H25/$I$37 -> 0.013272491 | L25: =G25/$G$38 -> 0.042857143 | M25: =J25*$M$3 -> 145.97692 | N25: =J25*$N$3 -> 35.620464 | O25: =J25*$O$3 -> 35.664153 | P25: =J25*$P$3 -> 7.0046784 | Q25: =K25*$Q$3 -> 26.292805 | R25: =K25*$R$3 -> 0 | S25: =K25*$S$3 -> 39.897109 | T25: =K25*$T$3 -> 79.634949 | U25: =K25*$U$3 -> 61.783448 | V25: =K25*$V$3 -> 26.836978 | W25: =K25*$W$3 -> 9.7287362 | X25: =K25*$X$3 -> 4.1410173 | Y25: =K25*$Y$3 -> 16.736612 | Z25: =K25*$Z$3 -> 34.99956 | AA25: =K25*$AA$3 -> 10.153456 | AB25: =J25*$AB$3 -> 28.907041 | AC25: =K25*$AC$3 -> 61.770175 | AE25: =H25/$H$39 -> 0.0087859879 | AF25: =AE25*$AF$3 -> 59.6305
B26: 515 | C26: FOC - HUD NUL PARS | G26: 1.5 | H26: 2596 | J26: =H26/$I$35 -> 0.015013851 | K26: =H26/$I$37 -> 0.013683633 | L26: =G26/$G$38 -> 0.042857143 | M26: =J26*$M$3 -> 150.49884 | N26: =J26*$N$3 -> 36.723878 | O26: =J26*$O$3 -> 36.76892 | P26: =J26*$P$3 -> 7.2216621 | Q26: =K26*$Q$3 -> 27.107277 | R26: =K26*$R$3 -> 0 | S26: =K26*$S$3 -> 41.133001 | T26: =K26*$T$3 -> 82.101798 | U26: =K26*$U$3 -> 63.697311 | V26: =K26*$V$3 -> 27.668306 | W26: =K26*$W$3 -> 10.030103 | X26: =K26*$X$3 -> 4.2692935 | Y26: =K26*$Y$3 -> 17.255061 | Z26: =K26*$Z$3 -> 36.08374 | AA26: =K26*$AA$3 -> 10.467979 | AB26: =J26*$AB$3 -> 29.802493 | AC26: =K26*$AC$3 -> 63.683628 | AE26: =H26/$H$39 -> 0.0090581512 | AF26: =AE26*$AF$3 -> 61.477672
B27: 525 | C27: CDBG - Housing | G27: 1 | H27: 4350 | J27: =H27/$I$35 -> 0.025158031 | K27: =H27/$I$37 -> 0.022929046 | L27: =G27/$G$38 -> 0.028571429 | M27: =J27*$M$3 -> 252.18411 | N27: =J27*$N$3 -> 61.536545 | O27: =J27*$O$3 -> 61.612019 | P27: =J27*$P$3 -> 12.101013 | Q27: =K27*$Q$3 -> 45.42244 | R27: =K27*$R$3 -> 0 | S27: =K27*$S$3 -> 68.924712 | T27: =K27*$T$3 -> 137.57428 | U27: =K27*$U$3 -> 106.73471 | V27: =K27*$V$3 -> 46.362531 | W27: =K27*$W$3 -> 16.806991 | X27: =K27*$X$3 -> 7.1538623 | Y27: =K27*$Y$3 -> 28.913527 | Z27: =K27*$Z$3 -> 60.463894 | AA27: =K27*$AA$3 -> 17.54072 | AB27: =J27*$AB$3 -> 49.938692 | AC27: =K27*$AC$3 -> 106.71178 | AE27: =H27/$H$39 -> 0.015178335 | AF27: =AE27*$AF$3 -> 103.01536
B28: 560 | C28: CAP 1 - Save Up | H28: 0 | J28: =H28/$I$35 -> 0 | K28: =H28/$I$37 -> 0 | L28: =G28/$G$38 -> 0 | M28: =J28*$M$3 -> 0 | N28: =J28*$N$3 -> 0 | O28: =J28*$O$3 -> 0 | P28: =J28*$P$3 -> 0 | Q28: =K28*$Q$3 -> 0 | R28: =K28*$R$3 -> 0 | S28: =K28*$S$3 -> 0 | T28: =K28*$T$3 -> 0 | U28: =K28*$U$3 -> 0 | V28: =K28*$V$3 -> 0 | W28: =K28*$W$3 -> 0 | X28: =K28*$X$3 -> 0 | Y28: =K28*$Y$3 -> 0 | Z28: =K28*$Z$3 -> 0 | AA28: =K28*$AA$3 -> 0 | AB28: =J28*$AB$3 -> 0 | AC28: =K28*$AC$3 -> 0 | AE28: =H28/$H$39 -> 0 | AF28: =AE28*$AF$3 -> 0
B29: 561 | C29: LISC FOC 2019 | G29: 1 | H29: 6577 | J29: =H29/$I$35 -> 0.038037787 | K29: =H29/$I$37 -> 0.034667663 | L29: =G29/$G$38 -> 0.028571429 | M29: =J29*$M$3 -> 381.29078 | N29: =J29*$N$3 -> 93.040427 | O29: =J29*$O$3 -> 93.15454 | P29: =J29*$P$3 -> 18.296175 | Q29: =K29*$Q$3 -> 68.676641 | R29: =K29*$R$3 -> 0 | S29: =K29*$S$3 -> 104.211 | T29: =K29*$T$3 -> 208.00598 | U29: =K29*$U$3 -> 161.37797 | V29: =K29*$V$3 -> 70.098015 | W29: =K29*$W$3 -> 25.411397 | X29: =K29*$X$3 -> 10.816311 | Y29: =K29*$Y$3 -> 43.715923 | Z29: =K29*$Z$3 -> 91.418628 | AA29: =K29*$AA$3 -> 26.520762 | AB29: =J29*$AB$3 -> 75.505007 | AC29: =K29*$AC$3 -> 161.3433 | AE29: =H29/$H$39 -> 0.022948945 | AF29: =AE29*$AF$3 -> 155.75449
B30: 563 | C30: Prudential #1 FOC | G30: 1 | H30: 4490 | J30: =H30/$I$35 -> 0.025967715 | K30: =H30/$I$37 -> 0.023666992 | L30: =G30/$G$38 -> 0.028571429 | M30: =J30*$M$3 -> 260.30038 | N30: =J30*$N$3 -> 63.517031 | O30: =J30*$O$3 -> 63.594935 | P30: =J30*$P$3 -> 12.490471 | Q30: =K30*$Q$3 -> 46.884312 | R30: =K30*$R$3 -> 0 | S30: =K30*$S$3 -> 71.142979 | T30: =K30*$T$3 -> 142.00195 | U30: =K30*$U$3 -> 110.16985 | V30: =K30*$V$3 -> 47.854658 | W30: =K30*$W$3 -> 17.347905 | X30: =K30*$X$3 -> 7.3841016 | Y30: =K30*$Y$3 -> 29.844077 | Z30: =K30*$Z$3 -> 62.409859 | AA30: =K30*$AA$3 -> 18.105249 | AB30: =J30*$AB$3 -> 51.545915 | AC30: =K30*$AC$3 -> 110.14618 | AE30: =H30/$H$39 -> 0.015666833 | AF30: =AE30*$AF$3 -> 106.3308
B31: 610 | C31: CEO | G31: 1 | H31: 17885 | J31: =H31/$I$35 -> 0.1034371 | K31: =H31/$I$37 -> 0.094272641 | L31: =G31/$G$38 -> 0.028571429 | M31: =J31*$M$3 -> 1036.8535 | N31: =J31*$N$3 -> 253.00715 | O31: =J31*$O$3 -> 253.31746 | P31: =J31*$P$3 -> 49.753246 | Q31: =K31*$Q$3 -> 186.7541 | R31: =K31*$R$3 -> 0 | S31: =K31*$S$3 -> 283.38356 | T31: =K31*$T$3 -> 565.63584 | U31: =K31*$U$3 -> 438.83914 | V31: =K31*$V$3 -> 190.61928 | W31: =K31*$W$3 -> 69.101846 | X31: =K31*$X$3 -> 29.413064 | Y31: =K31*$Y$3 -> 118.8778 | Z31: =K31*$Z$3 -> 248.59695 | AA31: =K31*$AA$3 -> 72.11857 | AB31: =J31*$AB$3 -> 205.32265 | AC31: =K31*$AC$3 -> 438.74487 | AE31: =H31/$H$39 -> 0.062405637 | AF31: =AE31*$AF$3 -> 423.54706
B32: 620 | C32: CFO | G32: 1 | H32: 8020 | J32: =H32/$I$35 -> 0.046383313 | K32: =H32/$I$37 -> 0.042273781 | L32: =G32/$G$38 -> 0.028571429 | M32: =J32*$M$3 -> 464.94633 | N32: =J32*$N$3 -> 113.45358 | O32: =J32*$O$3 -> 113.59273 | P32: =J32*$P$3 -> 22.310374 | Q32: =K32*$Q$3 -> 83.744361 | R32: =K32*$R$3 -> 0 | S32: =K32*$S$3 -> 127.07499 | T32: =K32*$T$3 -> 253.64269 | U32: =K32*$U$3 -> 196.78445 | V32: =K32*$V$3 -> 85.477586 | W32: =K32*$W$3 -> 30.986682 | X32: =K32*$X$3 -> 13.18942 | Y32: =K32*$Y$3 -> 53.307238 | Z32: =K32*$Z$3 -> 111.47596 | AA32: =K32*$AA$3 -> 32.339443 | AB32: =J32*$AB$3 -> 92.070877 | AC32: =K32*$AC$3 -> 196.74218 | AE32: =H32/$H$39 -> 0.027983965 | AF32: =AE32*$AF$3 -> 189.92717
B33: 630 | C33: COO | G33: 1 | H33: 0 | J33: =H33/$I$35 -> 0 | K33: =H33/$I$37 -> 0 | L33: =G33/$G$38 -> 0.028571429 | M33: =J33*$M$3 -> 0 | N33: =J33*$N$3 -> 0 | O33: =J33*$O$3 -> 0 | P33: =J33*$P$3 -> 0 | Q33: =K33*$Q$3 -> 0 | R33: =K33*$R$3 -> 0 | S33: =K33*$S$3 -> 0 | T33: =K33*$T$3 -> 0 | U33: =K33*$U$3 -> 0 | V33: =K33*$V$3 -> 0 | W33: =K33*$W$3 -> 0 | X33: =K33*$X$3 -> 0 | Y33: =K33*$Y$3 -> 0 | Z33: =K33*$Z$3 -> 0 | AA33: =K33*$AA$3 -> 0 | AB33: =J33*$AB$3 -> 0 | AC33: =K33*$AC$3 -> 0 | AE33: =H33/$H$39 -> 0 | AF33: =AE33*$AF$3 -> 0
B34: 650 | C34: Facilities | H34: 449 | J34: =H34/$I$35 -> 0.0025967715 | K34: =H34/$I$37 -> 0.0023666992 | L34: =G34/$G$38 -> 0 | M34: =J34*$M$3 -> 26.030038 | N34: =J34*$N$3 -> 6.3517031 | O34: =J34*$O$3 -> 6.3594935 | P34: =J34*$P$3 -> 1.2490471 | Q34: =K34*$Q$3 -> 4.6884312 | R34: =K34*$R$3 -> 0 | S34: =K34*$S$3 -> 7.1142979 | T34: =K34*$T$3 -> 14.200195 | U34: =K34*$U$3 -> 11.016985 | V34: =K34*$V$3 -> 4.7854658 | W34: =K34*$W$3 -> 1.7347905 | X34: =K34*$X$3 -> 0.73841016 | Y34: =K34*$Y$3 -> 2.9844077 | Z34: =K34*$Z$3 -> 6.2409859 | AA34: =K34*$AA$3 -> 1.8105249 | AB34: =J34*$AB$3 -> 5.1545915 | AC34: =K34*$AC$3 -> 11.014618 | AE34: =H34/$H$39 -> 0.0015666833 | AF34: =AE34*$AF$3 -> 10.63308
B35: 600 | C35: Admin | H35: 0.01 | I35: =SUM(H6:H35) -> 172907.01 | J35: =H35/$I$35 -> 5.7834555e-08 | K35: =H35/$I$37 -> 5.271045e-08 | L35: =G35/$G$38 -> 0 | M35: =J35*$M$3 -> 0.00057973358 | N35: =J35*$N$3 -> 0.00014146332 | O35: =J35*$O$3 -> 0.00014163683 | P35: =J35*$P$3 -> 2.7818421e-05 | Q35: =K35*$Q$3 -> 0.0001044194 | R35: =K35*$R$3 -> 0 | S35: =K35*$S$3 -> 0.00015844761 | T35: =K35*$T$3 -> 0.0003162627 | U35: =K35*$U$3 -> 0.00024536715 | V35: =K35*$V$3 -> 0.00010658053 | W35: =K35*$W$3 -> 3.863676e-05 | X35: =K35*$X$3 -> 1.6445661e-05 | Y35: =K35*$Y$3 -> 6.6467878e-05 | Z35: =K35*$Z$3 -> 0.00013899746 | AA35: =K35*$AA$3 -> 4.0323495e-05 | AB35: =J35*$AB$3 -> 0.00011480159 | AC35: =K35*$AC$3 -> 0.00024531444 | AE35: =H35/$H$39 -> 3.4892724e-08 | AF35: =AE35*$AF$3 -> 0.00023681692
B36: 339 | C36: Opport Corp | G36: 1.5 | H36: =I56 -> 10470.69 | K36: =H36/$I$37 -> 0.055191479 | L36: =G36/$G$38 -> 0.042857143 | M36: =J36*$M$3 -> 0 | N36: =J36*$N$3 -> 0 | O36: =J36*$O$3 -> 0 | P36: =J36*$P$3 -> 0 | Q36: =K36*$Q$3 -> 109.33432 | R36: =K36*$R$3 -> 0 | S36: =K36*$S$3 -> 165.90558 | T36: =K36*$T$3 -> 331.14887 | U36: =K36*$U$3 -> 256.91633 | V36: =K36*$V$3 -> 111.59717 | W36: =K36*$W$3 -> 40.455354 | X36: =K36*$X$3 -> 17.219741 | Y36: =K36*$Y$3 -> 69.596455 | Z36: =K36*$Z$3 -> 145.53993 | AA36: =K36*$AA$3 -> 42.221481 | AB36: =J36*$AB$3 -> 0 | AC36: =K36*$AC$3 -> 256.86114 | AE36: =H36/$H$39 -> 0.03653509 | AF36: =AE36*$AF$3 -> 247.96365
B37: 225 | C37: AmeriCorp | G37: 0 | H37: =J54 -> 6338 | I37: =I35+H36+H37 -> 189715.7 | K37: =H37/$I$37 -> 0.033407883 | L37: =G37/$G$38 -> 0 | Q37: =K37*$Q$3 -> 66.181017 | R37: =K37*$R$3 -> 0 | S37: =K37*$S$3 -> 100.4241 | T37: =K37*$T$3 -> 200.4473 | U37: =K37*$U$3 -> 155.5137 | V37: =K37*$V$3 -> 67.55074 | W37: =K37*$W$3 -> 24.487979 | X37: =K37*$X$3 -> 10.42326 | Y37: =K37*$Y$3 -> 42.127341 | Z37: =K37*$Z$3 -> 88.096589 | AA37: =K37*$AA$3 -> 25.557031 | AB37: =J37*$AB$3 -> 0 | AC37: =K37*$AC$3 -> 155.48029 | AE37: =H37/$H$39 -> 0.022115009 | AF37: =AE37*$AF$3 -> 150.09456
B38: 451 | C38: USJP - Participants | F38: 96842 | G38: =SUM(G6:G37) -> 35 | H38: 96877 | Q38: =K38*$Q$3 -> 0 | AE38: =H38/$H$39 -> 0.33803024 | AF38: =AE38*$AF$3 -> 2294.2113
H39: =SUM(H6:H38) -> 286592.7 | J39: =SUM(J6:J38) -> 1 | K39: =SUM(K6:K38) -> 1 | L39: =SUM(L6:L38) -> 1 | M39: =SUM(M6:M38) -> 10024 | N39: =SUM(N6:N38) -> 2446 | O39: =SUM(O6:O38) -> 2449 | P39: =SUM(P6:P38) -> 481 | Q39: =SUM(Q6:Q38) -> 1981 | ... AC39: =SUM(AC6:AC38) -> 4654 | AE39: =SUM(AE6:AE38) -> 1 | AF39: =SUM(AF6:AF38) -> 6787
H40: Salary | J40: Hourly | M40: =M3-M39 -> 0 | N40: =N3-N39 -> 0 | O40: =O3-O39 -> 0 | P40: =P3-P39 -> 0 | Q40: =Q3-Q39 -> 0 | R40: =R3-R39 -> 0 | S40: =S3-S39 -> 0 | T40: =T3-T39 -> 0 | ... AA40: =AA3-AA39 -> 0 | AC40: =AC3-AC39 -> 0 | AE40: =AE3-AE39 -> -1 | AF40: =AF3-AF39 -> 0
C41: 43770 | H41: 57985.52 | M41: 3465 | N41: 810 | O41: 846 | P41: 166 | Q41: 677
C42: 43784 | H42: 58543 | M42: 3432 | N42: 819 | O42: 835 | P42: 164 | Q42: 627
C43: 43799 | H43: 58541 | J43: 0 | M43: 3127 | N43: 817 | O43: 768 | P43: 151 | Q43: 677
H44: =I54 -> 8307.69
H45: =J54 -> 6338
H46: =SUM(H41:H45) -> 189715.21 | M46: =SUM(M41:M43) -> 10024 | N46: =SUM(N41:N43) -> 2446 | O46: =SUM(O41:O43) -> 2449 | P46: =SUM(P41:P43) -> 481 | Q46: =SUM(Q41:Q43) -> 1981
H47: =H39-H46 -> 96877.49 | AJ47: 114.44
I48: Opp Corp | J48: Americ | AJ48: 151.65
F49: =I35-H45 -> 166569.01
I50: 2769.23 | J50: 2113
I51: 2769.23 | J51: 2113
I52: 2769.23 | J52: 2112
I54: =SUM(I50:I53) -> 8307.69 | J54: =SUM(J50:J53) -> 6338 | K54: =SUM(I54:J54) -> 14645.69
I55: 2163
I56: =SUM(I54:I55) -> 10470.69

Sheet Oct 2019 Alloc
B1: October Cost Allocations | M1: 7251 | N1: 7252 | O1: 7253 | P1: 7254 | Q1: 7260.1 | R1: 8140 | S1: 7515.5 | T1: 7521 | U1: 8112 | V1: 8135.5 | W1: 8191 | X1: 8210.5 | Y1: 8229.1 | Z1: 8239 | AA1: 8265 | AB1: 8266 | AE1: 7248
M2: FICA | N2: MEDI | O2: SUI | P2: Disability | Q2: Payroll Fees | R2: Postage | S2: IT Consultants | T2: Acctg Fees | U2: Supplies | V2: Telephone | W2: Web Hosting | X2: Utilities | Y2: Eq Lease | Z2: Repairs | AA2: Mortgage Int | AB2: General Insurance | AE2: W/ Comp
M3: 6886 | N3: 1610 | O3: 1649 | P3: 324 | Q3: 1268 | R3: 302 | S3: 3006 | T3: 6125 | U3: 2281 | V3: 1420 | W3: 312 | X3: 1301 | Y3: 2456 | Z3: 1170 | AA3: 1927 | AB3: 4654 | AE3: 6787
G4: headcount | M4: 1 | N4: 2 | O4: 3 | P4: 4 | Q4: 5 | R4: 6 | S4: 7 | T4: 8 | U4: 9 | V4: 10 | W4: 11 | X4: 12 | Y4: 13 | Z4: 14 | AA4: 15 | AB4: 15 | AE4: 0.04
D5: 7222 | E5: Taxes | F5: W/C | J5: Taxes | K5: Salary | L5: Headcount
B6: 41 | C6: Thriftworks | H6: 0 | J6: =H6/$I$35 -> 0 | K6: =H6/$I$37 -> 0 | L6: =G6/$G$38 -> 0 | M6: =J6*$M$3 -> 0 | N6: =J6*$N$3 -> 0 | O6: =J6*$O$3 -> 0 | P6: =J6*$P$3 -> 0 | Q6: =K6*$Q$3 -> 0 | R6: =K6*$R$3 -> 0 | S6: =K6*$S$3 -> 0 | T6: =K6*$T$3 -> 0 | U6: =K6*$U$3 -> 0 | V6: =K6*$V$3 -> 0 | W6: =K6*$W$3 -> 0 | X6: =K6*$X$3 -> 0 | Y6: =K6*$Y$3 -> 0 | Z6: =K6*$Z$3 -> 0 | AA6: =J6*$AA$3 -> 0 | AB6: =K6*$AB$3 -> 0 | AD6: =H6/$H$39 -> 0 | AE6: =AD6*$AE$3 -> 0
B7: 111 | C7: Abbott | G7: 8 | H7: 30054.56 | J7: =H7/$I$35 -> 0.26608178 | K7: =H7/$I$37 -> 0.2400242 | L7: =G7/$G$38 -> 0.22857143 | M7: =J7*$M$3 -> 1832.2392 | N7: =J7*$N$3 -> 428.39167 | O7: =J7*$O$3 -> 438.76886 | P7: =J7*$P$3 -> 86.210498 | Q7: =K7*$Q$3 -> 304.35068 | R7: =K7*$R$3 -> 72.487307 | S7: =K7*$S$3 -> 721.51273 | T7: =K7*$T$3 -> 1470.1482 | U7: =K7*$U$3 -> 547.49519 | V7: =K7*$V$3 -> 340.83436 | W7: =K7*$W$3 -> 74.887549 | X7: =K7*$X$3 -> 312.27148 | Y7: =K7*$Y$3 -> 589.49942 | Z7: =K7*$Z$3 -> 280.82831 | AA7: =J7*$AA$3 -> 512.7396 | AB7: =K7*$AB$3 -> 1117.0726 | AD7: =H7/$H$39 -> 0.13534633 | AE7: =AD7*$AE$3 -> 918.59552
B8: 111B | C8: Abbott Fees | G8: 1 | H8: 3231.11 | J8: =H8/$I$35 -> 0.028605959 | K8: =H8/$I$37 -> 0.025804556 | L8: =G8/$G$38 -> 0.028571429 | M8: =J8*$M$3 -> 196.98063 | N8: =J8*$N$3 -> 46.055594 | O8: =J8*$O$3 -> 47.171226 | P8: =J8*$P$3 -> 9.2683307 | Q8: =K8*$Q$3 -> 32.720177 | R8: =K8*$R$3 -> 7.7929759 | S8: =K8*$S$3 -> 77.568495 | T8: =K8*$T$3 -> 158.05291 | U8: =K8*$U$3 -> 58.860192 | V8: =K8*$V$3 -> 36.64247 | W8: =K8*$W$3 -> 8.0510215 | X8: =K8*$X$3 -> 33.571727 | Y8: =K8*$Y$3 -> 63.37599 | Z8: =K8*$Z$3 -> 30.191331 | AA8: =J8*$AA$3 -> 55.123683 | AB8: =K8*$AB$3 -> 120.0944 | AD8: =H8/$H$39 -> 0.014550833 | AE8: =AD8*$AE$3 -> 98.7565
B9: 111A | C9: Abbott - Other | G9: 1 | H9: 2702.31 | J9: =H9/$I$35 -> 0.023924338 | K9: =H9/$I$37 -> 0.02158141 | L9: =G9/$G$38 -> 0.028571429 | M9: =J9*$M$3 -> 164.74299 | N9: =J9*$N$3 -> 38.518185 | O9: =J9*$O$3 -> 39.451234 | P9: =J9*$P$3 -> 7.7514856 | Q9: =K9*$Q$3 -> 27.365228 | R9: =K9*$R$3 -> 6.5175858 | S9: =K9*$S$3 -> 64.873719 | T9: =K9*$T$3 -> 132.18614 | U9: =K9*$U$3 -> 49.227196 | V9: =K9*$V$3 -> 30.645602 | W9: =K9*$W$3 -> 6.7333999 | X9: =K9*$X$3 -> 28.077414 | Y9: =K9*$Y$3 -> 53.003943 | Z9: =K9*$Z$3 -> 25.25025 | AA9: =J9*$AA$3 -> 46.1022 | AB9: =K9*$AB$3 -> 100.43988 | AD9: =H9/$H$39 -> 0.012169459 | AE9: =AD9*$AE$3 -> 82.594117
B10: 111F | C10: Abbott Food | G10: 0 | H10: 261.6 | J10: =H10/$I$35 -> 0.0023160211 | K10: =H10/$I$37 -> 0.0020892114 | L10: =G10/$G$38 -> 0 | M10: =J10*$M$3 -> 15.948121 | N10: =J10*$N$3 -> 3.7287939 | O10: =J10*$O$3 -> 3.8191188 | P10: =J10*$P$3 -> 0.75039083 | Q10: =K10*$Q$3 -> 2.6491201 | R10: =K10*$R$3 -> 0.63094184 | S10: =K10*$S$3 -> 6.2801695 | T10: =K10*$T$3 -> 12.79642 | U10: =K10*$U$3 -> 4.7654912 | V10: =K10*$V$3 -> 2.9666802 | W10: =K10*$W$3 -> 0.65183396 | X10: =K10*$X$3 -> 2.718064 | Y10: =K10*$Y$3 -> 5.1311032 | Z10: =K10*$Z$3 -> 2.4443773 | AA10: =J10*$AA$3 -> 4.4629726 | AB10: =K10*$AB$3 -> 9.7231899 | AD10: =H10/$H$39 -> 0.0011780774 | AE10: =AD10*$AE$3 -> 7.9956116
B11: 112 | C11: EHS | G11: 1 | H11: 5008.5 | J11: =H11/$I$35 -> 0.044341711 | K11: =H11/$I$37 -> 0.039999294 | L11: =G11/$G$38 -> 0.028571429 | M11: =J11*$M$3 -> 305.33702 | N11: =J11*$N$3 -> 71.390154 | O11: =J11*$O$3 -> 73.119481 | P11: =J11*$P$3 -> 14.366714 | Q11: =K11*$Q$3 -> 50.719105 | R11: =K11*$R$3 -> 12.079787 | S11: =K11*$S$3 -> 120.23788 | T11: =K11*$T$3 -> 244.99568 | U11: =K11*$U$3 -> 91.23839 | V11: =K11*$V$3 -> 56.798997 | W11: =K11*$W$3 -> 12.47978 | X11: =K11*$X$3 -> 52.039082 | Y11: =K11*$Y$3 -> 98.238266 | Z11: =K11*$Z$3 -> 46.799174 | AA11: =J11*$AA$3 -> 85.446477 | AB11: =K11*$AB$3 -> 186.15671 | AD11: =H11/$H$39 -> 0.022555049 | AE11: =AD11*$AE$3 -> 153.08112
B12: 114 | C12: Summer Camp | H12: 0 | J12: =H12/$I$35 -> 0 | K12: =H12/$I$37 -> 0 | L12: =G12/$G$38 -> 0 | M12: =J12*$M$3 -> 0 | N12: =J12*$N$3 -> 0 | O12: =J12*$O$3 -> 0 | P12: =J12*$P$3 -> 0 | Q12: =K12*$Q$3 -> 0 | R12: =K12*$R$3 -> 0 | S12: =K12*$S$3 -> 0 | T12: =K12*$T$3 -> 0 | U12: =K12*$U$3 -> 0 | V12: =K12*$V$3 -> 0 | W12: =K12*$W$3 -> 0 | X12: =K12*$X$3 -> 0 | Y12: =K12*$Y$3 -> 0 | Z12: =K12*$Z$3 -> 0 | AA12: =J12*$AA$3 -> 0 | AB12: =K12*$AB$3 -> 0 | AD12: =H12/$H$39 -> 0 | AE12: =AD12*$AE$3 -> 0
B13: 222 | C13: DCF- Coding | G13: 0.5 | H13: 3653.71 | J13: =H13/$I$35 -> 0.03234736 | K13: =H13/$I$37 -> 0.029179559 | L13: =G13/$G$38 -> 0.014285714 | M13: =J13*$M$3 -> 222.74392 | N13: =J13*$N$3 -> 52.07925 | O13: =J13*$O$3 -> 53.340797 | P13: =J13*$P$3 -> 10.480545 | Q13: =K13*$Q$3 -> 36.999681 | R13: =K13*$R$3 -> 8.8122268 | S13: =K13*$S$3 -> 87.713754 | T13: =K13*$T$3 -> 178.7248 | U13: =K13*$U$3 -> 66.558574 | V13: =K13*$V$3 -> 41.434974 | W13: =K13*$W$3 -> 9.1040224 | X13: =K13*$X$3 -> 37.962606 | Y13: =K13*$Y$3 -> 71.664997 | Z13: =K13*$Z$3 -> 34.140084 | AA13: =J13*$AA$3 -> 62.333363 | AB13: =K13*$AB$3 -> 135.80167 | AD13: =H13/$H$39 -> 0.01645395 | AE13: =AD13*$AE$3 -> 111.67296
B14: 223 | C14: OICA | H14: 0 | J14: =H14/$I$35 -> 0 | K14: =H14/$I$37 -> 0 | L14: =G14/$G$38 -> 0 | M14: =J14*$M$3 -> 0 | N14: =J14*$N$3 -> 0 | O14: =J14*$O$3 -> 0 | P14: =J14*$P$3 -> 0 | Q14: =K14*$Q$3 -> 0 | R14: =K14*$R$3 -> 0 | S14: =K14*$S$3 -> 0 | T14: =K14*$T$3 -> 0 | U14: =K14*$U$3 -> 0 | V14: =K14*$V$3 -> 0 | W14: =K14*$W$3 -> 0 | X14: =K14*$X$3 -> 0 | Y14: =K14*$Y$3 -> 0 | Z14: =K14*$Z$3 -> 0 | AA14: =J14*$AA$3 -> 0 | AB14: =K14*$AB$3 -> 0 | AD14: =H14/$H$39 -> 0 | AE14: =AD14*$AE$3 -> 0
B15: 334 | C15: NRTC - Admin | H15: 0 | J15: =H15/$I$35 -> 0 | K15: =H15/$I$37 -> 0 | L15: =G15/$G$38 -> 0 | M15: =J15*$M$3 -> 0 | N15: =J15*$N$3 -> 0 | O15: =J15*$O$3 -> 0 | P15: =J15*$P$3 -> 0 | Q15: =K15*$Q$3 -> 0 | R15: =K15*$R$3 -> 0 | S15: =K15*$S$3 -> 0 | T15: =K15*$T$3 -> 0 | U15: =K15*$U$3 -> 0 | V15: =K15*$V$3 -> 0 | W15: =K15*$W$3 -> 0 | X15: =K15*$X$3 -> 0 | Y15: =K15*$Y$3 -> 0 | Z15: =K15*$Z$3 -> 0 | AA15: =J15*$AA$3 -> 0 | AB15: =K15*$AB$3 -> 0 | AD15: =H15/$H$39 -> 0 | AE15: =AD15*$AE$3 -> 0
B16: 334H | C16: NRTC - Housing | G16: 0.5 | H16: 1150 | J16: =H16/$I$35 -> 0.010181285 | K16: =H16/$I$37 -> 0.0091842244 | L16: =G16/$G$38 -> 0.014285714 | M16: =J16*$M$3 -> 70.108331 | N16: =J16*$N$3 -> 16.391869 | O16: =J16*$O$3 -> 16.788939 | P16: =J16*$P$3 -> 3.2987364 | Q16: =K16*$Q$3 -> 11.645597 | R16: =K16*$R$3 -> 2.7736358 | S16: =K16*$S$3 -> 27.607779 | T16: =K16*$T$3 -> 56.253375 | U16: =K16*$U$3 -> 20.949216 | V16: =K16*$V$3 -> 13.041599 | W16: =K16*$W$3 -> 2.865478 | X16: =K16*$X$3 -> 11.948676 | Y16: =K16*$Y$3 -> 22.556455 | Z16: =K16*$Z$3 -> 10.745543 | AA16: =J16*$AA$3 -> 19.619337 | AB16: =K16*$AB$3 -> 42.743381 | AD16: =H16/$H$39 -> 0.0051788572 | AE16: =AD16*$AE$3 -> 35.148904
B17: 334F | C17: NRTC FOC | H17: 0 | J17: =H17/$I$35 -> 0 | K17: =H17/$I$37 -> 0 | L17: =G17/$G$38 -> 0 | M17: =J17*$M$3 -> 0 | N17: =J17*$N$3 -> 0 | O17: =J17*$O$3 -> 0 | P17: =J17*$P$3 -> 0 | Q17: =K17*$Q$3 -> 0 | R17: =K17*$R$3 -> 0 | S17: =K17*$S$3 -> 0 | T17: =K17*$T$3 -> 0 | U17: =K17*$U$3 -> 0 | V17: =K17*$V$3 -> 0 | W17: =K17*$W$3 -> 0 | X17: =K17*$X$3 -> 0 | Y17: =K17*$Y$3 -> 0 | Z17: =K17*$Z$3 -> 0 | AA17: =J17*$AA$3 -> 0 | AB17: =K17*$AB$3 -> 0 | AD17: =H17/$H$39 -> 0 | AE17: =AD17*$AE$3 -> 0
B18: 335 | C18: NRTC 19 | G18: 0.5 | H18: 846.15 | J18: =H18/$I$35 -> 0.0074912127 | K18: =H18/$I$37 -> 0.0067575926 | L18: =G18/$G$38 -> 0.014285714 | M18: =J18*$M$3 -> 51.58449 | N18: =J18*$N$3 -> 12.060852 | O18: =J18*$O$3 -> 12.35301 | P18: =J18*$P$3 -> 2.4271529 | Q18: =K18*$Q$3 -> 8.5686274 | R18: =K18*$R$3 -> 2.040793 | S18: =K18*$S$3 -> 20.313323 | T18: =K18*$T$3 -> 41.390255 | U18: =K18*$U$3 -> 15.414069 | V18: =K18*$V$3 -> 9.5957815 | W18: =K18*$W$3 -> 2.1083689 | X18: =K18*$X$3 -> 8.791628 | Y18: =K18*$Y$3 -> 16.596647 | Z18: =K18*$Z$3 -> 7.9063834 | AA18: =J18*$AA$3 -> 14.435567 | AB18: =K18*$AB$3 -> 31.449836 | AD18: =H18/$H$39 -> 0.0038105131 | AE18: =AD18*$AE$3 -> 25.861952
B19: 368 | C19: Wells Fargo | G19: 1.5 | H19: 6018.91 | J19: =H19/$I$35 -> 0.053287165 | K19: =H19/$I$37 -> 0.048068713 | L19: =G19/$G$38 -> 0.042857143 | M19: =J19*$M$3 -> 366.93542 | N19: =J19*$N$3 -> 85.792336 | O19: =J19*$O$3 -> 87.870535 | P19: =J19*$P$3 -> 17.265042 | Q19: =K19*$Q$3 -> 60.951129 | R19: =K19*$R$3 -> 14.516751 | S19: =K19*$S$3 -> 144.49455 | T19: =K19*$T$3 -> 294.42087 | U19: =K19*$U$3 -> 109.64474 | V19: =K19*$V$3 -> 68.257573 | W19: =K19*$W$3 -> 14.997439 | X19: =K19*$X$3 -> 62.537396 | Y19: =K19*$Y$3 -> 118.05676 | Z19: =K19*$Z$3 -> 56.240395 | AA19: =J19*$AA$3 -> 102.68437 | AB19: =K19*$AB$3 -> 223.71179 | AD19: =H19/$H$39 -> 0.027105283 | AE19: =AD19*$AE$3 -> 183.96356
B20: 451 | C20: USJP | G20: 5.5 | H20: 13963.15 | J20: =H20/$I$35 -> 0.12361984 | K20: =H20/$I$37 -> 0.11151366 | L20: =G20/$G$38 -> 0.15714286 | M20: =J20*$M$3 -> 851.24621 | N20: =J20*$N$3 -> 199.02794 | O20: =J20*$O$3 -> 203.84911 | P20: =J20*$P$3 -> 40.052828 | Q20: =K20*$Q$3 -> 141.39931 | R20: =K20*$R$3 -> 33.677124 | S20: =K20*$S$3 -> 335.21005 | T20: =K20*$T$3 -> 683.02114 | U20: =K20*$U$3 -> 254.36265 | V20: =K20*$V$3 -> 158.34939 | W20: =K20*$W$3 -> 34.79226 | X20: =K20*$X$3 -> 145.07927 | Y20: =K20*$Y$3 -> 273.87754 | Z20: =K20*$Z$3 -> 130.47098 | AA20: =J20*$AA$3 -> 238.21543 | AB20: =K20*$AB$3 -> 518.98455 | AD20: =H20/$H$39 -> 0.062881009 | AE20: =AD20*$AE$3 -> 426.77341
B21: 452 | C21: PACE | G21: 2 | H21: 1950 | J21: =H21/$I$35 -> 0.017263919 | K21: =H21/$I$37 -> 0.01557325 | L21: =G21/$G$38 -> 0.057142857 | M21: =J21*$M$3 -> 118.87934 | N21: =J21*$N$3 -> 27.794909 | O21: =J21*$O$3 -> 28.468202 | P21: =J21*$P$3 -> 5.5935096 | Q21: =K21*$Q$3 -> 19.746881 | R21: =K21*$R$3 -> 4.7031215 | S21: =K21*$S$3 -> 46.81319 | T21: =K21*$T$3 -> 95.386157 | U21: =K21*$U$3 -> 35.522584 | V21: =K21*$V$3 -> 22.114015 | W21: =K21*$W$3 -> 4.858854 | X21: =K21*$X$3 -> 20.260798 | Y21: =K21*$Y$3 -> 38.247902 | Z21: =K21*$Z$3 -> 18.220703 | AA21: =J21*$AA$3 -> 33.267571 | AB21: =K21*$AB$3 -> 72.477906 | AD21: =H21/$H$39 -> 0.0087815405 | AE21: =AD21*$AE$3 -> 59.600316
B22: 454 | C22: Prudential #1 Workforce | K22: =H22/$I$37 -> 0 | L22: =G22/$G$38 -> 0 | Q22: =K22*$Q$3 -> 0 | R22: =K22*$R$3 -> 0 | S22: =K22*$S$3 -> 0 | T22: =K22*$T$3 -> 0 | U22: =K22*$U$3 -> 0 | V22: =K22*$V$3 -> 0 | W22: =K22*$W$3 -> 0 | X22: =K22*$X$3 -> 0 | Y22: =K22*$Y$3 -> 0 | Z22: =K22*$Z$3 -> 0 | AA22: =J22*$AA$3 -> 0 | AB22: =K22*$AB$3 -> 0
B23: 467 | C23: WF - United Airlines | G23: 2 | H23: 6903.87 | J23: =H23/$I$35 -> 0.061121974 | K23: =H23/$I$37 -> 0.055136254 | L23: =G23/$G$38 -> 0.057142857 | M23: =J23*$M$3 -> 420.88591 | N23: =J23*$N$3 -> 98.406378 | O23: =J23*$O$3 -> 100.79014 | P23: =J23*$P$3 -> 19.80352 | Q23: =K23*$Q$3 -> 69.91277 | R23: =K23*$R$3 -> 16.651149 | S23: =K23*$S$3 -> 165.73958 | T23: =K23*$T$3 -> 337.70955 | U23: =K23*$U$3 -> 125.76579 | V23: =K23*$V$3 -> 78.29348 | W23: =K23*$W$3 -> 17.202511 | X23: =K23*$X$3 -> 71.732266 | Y23: =K23*$Y$3 -> 135.41464 | Z23: =K23*$Z$3 -> 64.509417 | AA23: =J23*$AA$3 -> 117.78204 | AB23: =K23*$AB$3 -> 256.60412 | AD23: =H23/$H$39 -> 0.031090571 | AE23: =AD23*$AE$3 -> 211.01171
B24: 468 | C24: Newark Alliance | G24: 1 | H24: 6307.7 | J24: =H24/$I$35 -> 0.055843907 | K24: =H24/$I$37 -> 0.050375072 | L24: =G24/$G$38 -> 0.028571429 | M24: =J24*$M$3 -> 384.54115 | N24: =J24*$N$3 -> 89.908691 | O24: =J24*$O$3 -> 92.086603 | P24: =J24*$P$3 -> 18.093426 | Q24: =K24*$Q$3 -> 63.875591 | R24: =K24*$R$3 -> 15.213272 | S24: =K24*$S$3 -> 151.42747 | T24: =K24*$T$3 -> 308.54731 | U24: =K24*$U$3 -> 114.90554 | V24: =K24*$V$3 -> 71.532602 | W24: =K24*$W$3 -> 15.717022 | X24: =K24*$X$3 -> 65.537968 | Y24: =K24*$Y$3 -> 123.72118 | Z24: =K24*$Z$3 -> 58.938834 | AA24: =J24*$AA$3 -> 107.61121 | AB24: =K24*$AB$3 -> 234.44558 | AD24: =H24/$H$39 -> 0.028405807 | AE24: =AD24*$AE$3 -> 192.79021
B25: 502 | C25: ESG | G25: 1.5 | H25: 1657.17 | J25: =H25/$I$35 -> 0.014671409 | K25: =H25/$I$37 -> 0.013234627 | L25: =G25/$G$38 -> 0.042857143 | M25: =J25*$M$3 -> 101.02732 | N25: =J25*$N$3 -> 23.620969 | O25: =J25*$O$3 -> 24.193154 | P25: =J25*$P$3 -> 4.7535366 | Q25: =K25*$Q$3 -> 16.781507 | R25: =K25*$R$3 -> 3.9968574 | S25: =K25*$S$3 -> 39.783289 | T25: =K25*$T$3 -> 81.062091 | U25: =K25*$U$3 -> 30.188185 | V25: =K25*$V$3 -> 18.793171 | W25: =K25*$W$3 -> 4.1292037 | X25: =K25*$X$3 -> 17.21825 | Y25: =K25*$Y$3 -> 32.504244 | Z25: =K25*$Z$3 -> 15.484514 | AA25: =J25*$AA$3 -> 28.271806 | AB25: =K25*$AB$3 -> 61.593955 | AD25: =H25/$H$39 -> 0.0074628233 | AE25: =AD25*$AE$3 -> 50.650182
B26: 515 | C26: FOC - HUD NUL PARS | G26: 1.5 | H26: 1730.77 | J26: =H26/$I$35 -> 0.015323011 | K26: =H26/$I$37 -> 0.013822418 | L26: =G26/$G$38 -> 0.042857143 | M26: =J26*$M$3 -> 105.51426 | N26: =J26*$N$3 -> 24.670048 | O26: =J26*$O$3 -> 25.267646 | P26: =J26*$P$3 -> 4.9646557 | Q26: =K26*$Q$3 -> 17.526825 | R26: =K26*$R$3 -> 4.1743701 | S26: =K26*$S$3 -> 41.550187 | T26: =K26*$T$3 -> 84.662307 | U26: =K26*$U$3 -> 31.528934 | V26: =K26*$V$3 -> 19.627833 | W26: =K26*$W$3 -> 4.3125943 | X26: =K26*$X$3 -> 17.982965 | Y26: =K26*$Y$3 -> 33.947857 | Z26: =K26*$Z$3 -> 16.172228 | AA26: =J26*$AA$3 -> 29.527443 | AB26: =K26*$AB$3 -> 64.329531 | AD26: =H26/$H$39 -> 0.0077942702 | AE26: =AD26*$AE$3 -> 52.899712
B27: 525 | C27: CDBG - Housing | G27: 1 | H27: 2900 | J27: =H27/$I$35 -> 0.025674546 | K27: =H27/$I$37 -> 0.023160218 | L27: =G27/$G$38 -> 0.028571429 | M27: =J27*$M$3 -> 176.79492 | N27: =J27*$N$3 -> 41.336018 | O27: =J27*$O$3 -> 42.337326 | P27: =J27*$P$3 -> 8.3185528 | Q27: =K27*$Q$3 -> 29.367157 | R27: =K27*$R$3 -> 6.9943859 | S27: =K27*$S$3 -> 69.619616 | T27: =K27*$T$3 -> 141.85634 | U27: =K27*$U$3 -> 52.828458 | V27: =K27*$V$3 -> 32.88751 | W27: =K27*$W$3 -> 7.2259881 | X27: =K27*$X$3 -> 30.131444 | Y27: =K27*$Y$3 -> 56.881496 | Z27: =K27*$Z$3 -> 27.097455 | AA27: =J27*$AA$3 -> 49.474849 | AB27: =K27*$AB$3 -> 107.78766 | AD27: =H27/$H$39 -> 0.013059727 | AE27: =AD27*$AE$3 -> 88.636367
B28: 560 | C28: CAP 1 - Save Up | H28: 0 | J28: =H28/$I$35 -> 0 | K28: =H28/$I$37 -> 0 | L28: =G28/$G$38 -> 0 | M28: =J28*$M$3 -> 0 | N28: =J28*$N$3 -> 0 | O28: =J28*$O$3 -> 0 | P28: =J28*$P$3 -> 0 | Q28: =K28*$Q$3 -> 0 | R28: =K28*$R$3 -> 0 | S28: =K28*$S$3 -> 0 | T28: =K28*$T$3 -> 0 | U28: =K28*$U$3 -> 0 | V28: =K28*$V$3 -> 0 | W28: =K28*$W$3 -> 0 | X28: =K28*$X$3 -> 0 | Y28: =K28*$Y$3 -> 0 | Z28: =K28*$Z$3 -> 0 | AA28: =J28*$AA$3 -> 0 | AB28: =K28*$AB$3 -> 0 | AD28: =H28/$H$39 -> 0 | AE28: =AD28*$AE$3 -> 0
B29: 561 | C29: LISC FOC 2019 | G29: 1 | H29: 4384.62 | J29: =H29/$I$35 -> 0.038818319 | K29: =H29/$I$37 -> 0.035016812 | L29: =G29/$G$38 -> 0.028571429 | M29: =J29*$M$3 -> 267.30295 | N29: =J29*$N$3 -> 62.497494 | O29: =J29*$O$3 -> 64.011409 | P29: =J29*$P$3 -> 12.577135 | Q29: =K29*$Q$3 -> 44.401318 | R29: =K29*$R$3 -> 10.575077 | S29: =K29*$S$3 -> 105.26054 | T29: =K29*$T$3 -> 214.47798 | U29: =K29*$U$3 -> 79.873349 | V29: =K29*$V$3 -> 49.723873 | W29: =K29*$W$3 -> 10.925245 | X29: =K29*$X$3 -> 45.556873 | Y29: =K29*$Y$3 -> 86.001291 | Z29: =K29*$Z$3 -> 40.96967 | AA29: =J29*$AA$3 -> 74.802901 | AB29: =K29*$AB$3 -> 162.96824 | AD29: =H29/$H$39 -> 0.019745497 | AE29: =AD29*$AE$3 -> 134.01269
B30: 563 | C30: Prudential #1 FOC | G30: 1 | H30: 2929.2 | J30: =H30/$I$35 -> 0.025933062 | K30: =H30/$I$37 -> 0.023393418 | L30: =G30/$G$38 -> 0.028571429 | M30: =J30*$M$3 -> 178.57506 | N30: =J30*$N$3 -> 41.752229 | O30: =J30*$O$3 -> 42.763619 | P30: =J30*$P$3 -> 8.402312 | Q30: =K30*$Q$3 -> 29.662854 | R30: =K30*$R$3 -> 7.0648121 | S30: =K30*$S$3 -> 70.320613 | T30: =K30*$T$3 -> 143.28468 | U30: =K30*$U$3 -> 53.360386 | V30: =K30*$V$3 -> 33.218653 | W30: =K30*$W$3 -> 7.2987463 | X30: =K30*$X$3 -> 30.434836 | Y30: =K30*$Y$3 -> 57.454234 | Z30: =K30*$Z$3 -> 27.370299 | AA30: =J30*$AA$3 -> 49.97301 | AB30: =K30*$AB$3 -> 108.87297 | AD30: =H30/$H$39 -> 0.013191225 | AE30: =AD30*$AE$3 -> 89.528843
B31: 610 | C31: CEO | G31: 1 | H31: 11923.08 | J31: =H31/$I$35 -> 0.1055585 | K31: =H31/$I$37 -> 0.095221081 | L31: =G31/$G$38 -> 0.028571429 | M31: =J31*$M$3 -> 726.87586 | N31: =J31*$N$3 -> 169.94919 | O31: =J31*$O$3 -> 174.06597 | P31: =J31*$P$3 -> 34.200955 | Q31: =K31*$Q$3 -> 120.74033 | R31: =K31*$R$3 -> 28.756766 | S31: =K31*$S$3 -> 286.23457 | T31: =K31*$T$3 -> 583.22912 | U31: =K31*$U$3 -> 217.19928 | V31: =K31*$V$3 -> 135.21393 | W31: =K31*$W$3 -> 29.708977 | X31: =K31*$X$3 -> 123.88263 | Y31: =K31*$Y$3 -> 233.86297 | Z31: =K31*$Z$3 -> 111.40866 | AA31: =J31*$AA$3 -> 203.41124 | AB31: =K31*$AB$3 -> 443.15891 | AD31: =H31/$H$39 -> 0.053693851 | AE31: =AD31*$AE$3 -> 364.42017
B32: 620 | C32: CFO | G32: 1 | H32: 5076.92 | J32: =H32/$I$35 -> 0.044947453 | K32: =H32/$I$37 -> 0.040545715 | L32: =G32/$G$38 -> 0.028571429 | M32: =J32*$M$3 -> 309.50816 | N32: =J32*$N$3 -> 72.365399 | O32: =J32*$O$3 -> 74.11835 | P32: =J32*$P$3 -> 14.562975 | Q32: =K32*$Q$3 -> 51.411967 | R32: =K32*$R$3 -> 12.244806 | S32: =K32*$S$3 -> 121.88042 | T32: =K32*$T$3 -> 248.34251 | U32: =K32*$U$3 -> 92.484777 | V32: =K32*$V$3 -> 57.574916 | W32: =K32*$W$3 -> 12.650263 | X32: =K32*$X$3 -> 52.749976 | Y32: =K32*$Y$3 -> 99.580277 | Z32: =K32*$Z$3 -> 47.438487 | AA32: =J32*$AA$3 -> 86.613742 | AB32: =K32*$AB$3 -> 188.69976 | AD32: =H32/$H$39 -> 0.022863169 | AE32: =AD32*$AE$3 -> 155.17233
B33: 630 | C33: COO | G33: 1 | H33: 0 | J33: =H33/$I$35 -> 0 | K33: =H33/$I$37 -> 0 | L33: =G33/$G$38 -> 0.028571429 | M33: =J33*$M$3 -> 0 | N33: =J33*$N$3 -> 0 | O33: =J33*$O$3 -> 0 | P33: =J33*$P$3 -> 0 | Q33: =K33*$Q$3 -> 0 | R33: =K33*$R$3 -> 0 | S33: =K33*$S$3 -> 0 | T33: =K33*$T$3 -> 0 | U33: =K33*$U$3 -> 0 | V33: =K33*$V$3 -> 0 | W33: =K33*$W$3 -> 0 | X33: =K33*$X$3 -> 0 | Y33: =K33*$Y$3 -> 0 | Z33: =K33*$Z$3 -> 0 | AA33: =J33*$AA$3 -> 0 | AB33: =K33*$AB$3 -> 0 | AD33: =H33/$H$39 -> 0 | AE33: =AD33*$AE$3 -> 0
B34: 650 | C34: Facilities | H34: 299 | J34: =H34/$I$35 -> 0.0026471342 | K34: =H34/$I$37 -> 0.0023878984 | L34: =G34/$G$38 -> 0 | M34: =J34*$M$3 -> 18.228166 | N34: =J34*$N$3 -> 4.261886 | O34: =J34*$O$3 -> 4.3651243 | P34: =J34*$P$3 -> 0.85767147 | Q34: =K34*$Q$3 -> 3.0278551 | R34: =K34*$R$3 -> 0.7211453 | S34: =K34*$S$3 -> 7.1780225 | T34: =K34*$T$3 -> 14.625877 | U34: =K34*$U$3 -> 5.4467961 | V34: =K34*$V$3 -> 3.3908157 | W34: =K34*$W$3 -> 0.74502429 | X34: =K34*$X$3 -> 3.1066558 | Y34: =K34*$Y$3 -> 5.8646784 | Z34: =K34*$Z$3 -> 2.7938411 | AA34: =J34*$AA$3 -> 5.1010276 | AB34: =K34*$AB$3 -> 11.113279 | AD34: =H34/$H$39 -> 0.0013465029 | AE34: =AD34*$AE$3 -> 9.1387151
B35: 600 | C35: Admin | H35: 0.01 | I35: =SUM(H6:H35) -> 112952.34 | J35: =H35/$I$35 -> 8.8532916e-08 | K35: =H35/$I$37 -> 7.9862821e-08 | L35: =G35/$G$38 -> 0 | M35: =J35*$M$3 -> 0.00060963766 | N35: =J35*$N$3 -> 0.00014253799 | O35: =J35*$O$3 -> 0.00014599078 | P35: =J35*$P$3 -> 2.8684665e-05 | Q35: =K35*$Q$3 -> 0.00010126606 | R35: =K35*$R$3 -> 2.4118572e-05 | S35: =K35*$S$3 -> 0.00024006764 | T35: =K35*$T$3 -> 0.00048915978 | U35: =K35*$U$3 -> 0.0001821671 | V35: =K35*$V$3 -> 0.00011340521 | W35: =K35*$W$3 -> 2.49172e-05 | X35: =K35*$X$3 -> 0.00010390153 | Y35: =K35*$Y$3 -> 0.00019614309 | Z35: =K35*$Z$3 -> 9.3439501e-05 | AA35: =J35*$AA$3 -> 0.00017060293 | AB35: =K35*$AB$3 -> 0.00037168157 | AD35: =H35/$H$39 -> 4.5033541e-08 | AE35: =AD35*$AE$3 -> 0.00030564264
B36: 339 | C36: Opport Corp | G36: 1.5 | H36: =I55 -> 6980.77 | K36: =H36/$I$37 -> 0.055750399 | L36: =G36/$G$38 -> 0.042857143 | M36: =J36*$M$3 -> 0 | N36: =J36*$N$3 -> 0 | O36: =J36*$O$3 -> 0 | P36: =J36*$P$3 -> 0 | Q36: =K36*$Q$3 -> 70.691505 | R36: =K36*$R$3 -> 16.83662 | S36: =K36*$S$3 -> 167.5857 | T36: =K36*$T$3 -> 341.47119 | U36: =K36*$U$3 -> 127.16666 | V36: =K36*$V$3 -> 79.165566 | W36: =K36*$W$3 -> 17.394124 | X36: =K36*$X$3 -> 72.531269 | Y36: =K36*$Y$3 -> 136.92298 | Z36: =K36*$Z$3 -> 65.227966 | AA36: =J36*$AA$3 -> 0 | AB36: =K36*$AB$3 -> 259.46236 | AD36: =H36/$H$39 -> 0.031436879 | AE36: =AD36*$AE$3 -> 213.3621
B37: 225 | C37: AmeriCorp | G37: 0 | H37: =J53 -> 5281.6 | I37: =I35+H36+H37 -> 125214.71 | K37: =H37/$I$37 -> 0.042180348 | L37: =G37/$G$38 -> 0 | Q37: =K37*$Q$3 -> 53.484681 | R37: =K37*$R$3 -> 12.738465 | S37: =K37*$S$3 -> 126.79413 | T37: =K37*$T$3 -> 258.35463 | U37: =K37*$U$3 -> 96.213373 | V37: =K37*$V$3 -> 59.896094 | W37: =K37*$W$3 -> 13.160268 | X37: =K37*$X$3 -> 54.876632 | Y37: =K37*$Y$3 -> 103.59493 | Z37: =K37*$Z$3 -> 49.351007 | AA37: =J37*$AA$3 -> 0 | AB37: =K37*$AB$3 -> 196.30734 | AD37: =H37/$H$39 -> 0.023784915 | AE37: =AD37*$AE$3 -> 161.42822
B38: 451 | C38: USJP - Participants | F38: 96842 | G38: =SUM(G6:G37) -> 35 | H38: 96842 | Q38: =K38*$Q$3 -> 0 | AD38: =H38/$H$39 -> 0.43611382 | AE38: =AD38*$AE$3 -> 2959.9045
H39: =SUM(H6:H38) -> 222056.71 | J39: =SUM(J6:J38) -> 1 | K39: =SUM(K6:K38) -> 1 | L39: =SUM(L6:L38) -> 1 | M39: =SUM(M6:M38) -> 6886 | N39: =SUM(N6:N38) -> 1610 | O39: =SUM(O6:O38) -> 1649 | P39: =SUM(P6:P38) -> 324 | Q39: =SUM(Q6:Q38) -> 1268 | ... AE39: =SUM(AE6:AE38) -> 6787
H40: Salary | J40: Hourly | M40: =M3-M39 -> 0 | N40: =N3-N39 -> 0 | O40: =O3-O39 -> 0 | P40: =P3-P39 -> 0 | Q40: =Q3-Q39 -> 0 | R40: =R3-R39 -> 0 | S40: =S3-S39 -> 0 | T40: =T3-T39 -> 0 | ... Z40: =Z3-Z39 -> 0 | AB40: =AB3-AB39 -> 0 | AC40: =AC3-AC39 -> 0 | AD40: =AD3-AD39 -> -1 | AE40: =AE3-AE39 -> 0
C41: 43742 | H41: 58487.22 | M41: 3522 | N41: 823 | O41: 860 | P41: 169
C42: 43756 | H42: 55907.43 | J42: 0 | M42: 3364 | N42: 787 | O42: 789 | P42: 155
H43: 5538.46
H44: 5281.6
H45: =SUM(H41:H44) -> 125214.71 | M45: =SUM(M41:M42) -> 6886 | N45: =SUM(N41:N42) -> 1610 | O45: =SUM(O41:O42) -> 1649 | P45: =SUM(P41:P42) -> 324 | Q45: =SUM(Q41:Q42) -> 0
H46: =H39-H45 -> 96842 | AI46: 114.44
I47: Opp Corp | J47: Americ | AI47: 151.65
F48: =I35-H44 -> 107670.74
I49: 2769.23 | J49: 2640.8
I50: 2769.23 | J50: 2640.8
I53: =SUM(I49:I52) -> 5538.46 | J53: =SUM(J49:J52) -> 5281.6 | K53: =SUM(I53:J53) -> 10820.06
I54: 1442.31
I55: =SUM(I53:I54) -> 6980.77

Sheet Sept 2019 Alloc  (2)
B1: September Cost Allocations | L1: 7251 | M1: 7252 | N1: 7253 | O1: 7254 | P1: 7260.1 | Q1: 8140 | R1: 7515.5 | S1: 7521 | T1: 8112 | U1: 8135.5 | V1: 8191 | W1: 8210.5 | X1: 8229.1 | Y1: 8239 | Z1: 8266 | AC1: 7248
L2: FICA | M2: MEDI | N2: SUI | O2: Disability | P2: Payroll Fees | Q2: Postage | R2: IT Consultants | S2: Acctg Fees | T2: Supplies | U2: Telephone | V2: Web Hosting | W2: Utilities | X2: Eq Lease | Y2: Repairs | Z2: General Insurance | AC2: W/ Comp
L3: 6530.93 | M3: 1527.46 | N3: 1598.57 | O3: 313.99 | P3: 1330.76 | R3: 3006 | S3: 4900 | U3: 640.74 | V3: 312 | W3: 1092 | X3: 2321.34 | Y3: 764.51 | Z3: 3972.48 | AC3: 6645.7
L4: 1 | M4: 2 | N4: 3 | O4: 4 | P4: 5 | Q4: 6 | R4: 7 | S4: 8 | T4: 9 | U4: 10 | V4: 11 | W4: 12 | X4: 13 | Y4: 14 | Z4: 15 | AC4: 0.04
D5: 7222 | E5: Taxes | F5: W/C | J5: Taxes | K5: Expenses
B6: 41 | C6: Thriftworks | H6: 0 | J6: =H6/$I$35 -> 0 | K6: =H6/$I$37 -> 0 | L6: =J6*$L$3 -> 0 | M6: =J6*$M$3 -> 0 | N6: =J6*$N$3 -> 0 | O6: =J6*$O$3 -> 0 | P6: =J6*$P$3 -> 0 | Q6: =K6*$Q$3 -> 0 | R6: =K6*$R$3 -> 0 | S6: =K6*$S$3 -> 0 | T6: =K6*$T$3 -> 0 | U6: =K6*$U$3 -> 0 | V6: =K6*$V$3 -> 0 | W6: =K6*$W$3 -> 0 | X6: =K6*$X$3 -> 0 | Y6: =K6*$Y$3 -> 0 | Z6: =K6*$Z$3 -> 0 | AB6: =H6/$H$39 -> 0 | AC6: =AB6*$AC$3 -> 0
B7: 111 | C7: Abbott | H7: 25010.78 | J7: =H7/$I$35 -> 0.2318441 | K7: =H7/$I$37 -> 0.20698113 | L7: =J7*$L$3 -> 1514.1576 | M7: =J7*$M$3 -> 354.13258 | N7: =J7*$N$3 -> 370.61902 | O7: =J7*$O$3 -> 72.796728 | P7: =J7*$P$3 -> 308.52885 | Q7: =K7*$Q$3 -> 0 | R7: =K7*$R$3 -> 622.18527 | S7: =K7*$S$3 -> 1014.2075 | T7: =K7*$T$3 -> 0 | U7: =K7*$U$3 -> 132.62109 | V7: =K7*$V$3 -> 64.578112 | W7: =K7*$W$3 -> 226.02339 | X7: =K7*$X$3 -> 480.47357 | Y7: =K7*$Y$3 -> 158.23914 | Z7: =K7*$Z$3 -> 822.2284 | AB7: =H7/$H$39 -> 0.11765538 | AC7: =AB7*$AC$3 -> 781.90234
B8: 111A | C8: Abbott - Other | H8: 2617.28 | J8: =H8/$I$35 -> 0.024261575 | K8: =H8/$I$37 -> 0.021659763 | L8: =J8*$L$3 -> 158.45065 | M8: =J8*$M$3 -> 37.058585 | N8: =J8*$N$3 -> 38.783826 | O8: =J8*$O$3 -> 7.6178919 | P8: =J8*$P$3 -> 32.286334 | Q8: =K8*$Q$3 -> 0 | R8: =K8*$R$3 -> 65.109248 | S8: =K8*$S$3 -> 106.13284 | T8: =K8*$T$3 -> 0 | U8: =K8*$U$3 -> 13.878277 | V8: =K8*$V$3 -> 6.7578461 | W8: =K8*$W$3 -> 23.652461 | X8: =K8*$X$3 -> 50.279674 | Y8: =K8*$Y$3 -> 16.559105 | Z8: =K8*$Z$3 -> 86.042976 | AB8: =H8/$H$39 -> 0.012312174 | AC8: =AB8*$AC$3 -> 81.823012
B9: 111B | C9: Abbott Fees | H9: 1203.77 | J9: =H9/$I$35 -> 0.011158667 | K9: =H9/$I$37 -> 0.0099620113 | L9: =J9*$L$3 -> 72.876474 | M9: =J9*$M$3 -> 17.044418 | N9: =J9*$N$3 -> 17.83791 | O9: =J9*$O$3 -> 3.5037099 | P9: =J9*$P$3 -> 14.849508 | Q9: =K9*$Q$3 -> 0 | R9: =K9*$R$3 -> 29.945806 | S9: =K9*$S$3 -> 48.813856 | T9: =K9*$T$3 -> 0 | U9: =K9*$U$3 -> 6.3830591 | V9: =K9*$V$3 -> 3.1081475 | W9: =K9*$W$3 -> 10.878516 | X9: =K9*$X$3 -> 23.125215 | Y9: =K9*$Y$3 -> 7.6160573 | Z9: =K9*$Z$3 -> 39.573891 | AB9: =H9/$H$39 -> 0.0056627587 | AC9: =AB9*$AC$3 -> 37.632996
B10: 111F | C10: Abbott Food | H10: 254.47 | J10: =H10/$I$35 -> 0.0023588775 | K10: =H10/$I$37 -> 0.0021059114 | L10: =J10*$L$3 -> 15.405664 | M10: =J10*$M$3 -> 3.6030911 | N10: =J10*$N$3 -> 3.7708309 | O10: =J10*$O$3 -> 0.74066396 | P10: =J10*$P$3 -> 3.1390999 | Q10: =K10*$Q$3 -> 0 | R10: =K10*$R$3 -> 6.3303698 | S10: =K10*$S$3 -> 10.318966 | T10: =K10*$T$3 -> 0 | U10: =K10*$U$3 -> 1.3493417 | V10: =K10*$V$3 -> 0.65704437 | W10: =K10*$W$3 -> 2.2996553 | X10: =K10*$X$3 -> 4.8885365 | Y10: =K10*$Y$3 -> 1.6099904 | Z10: =K10*$Z$3 -> 8.3656911 | AB10: =H10/$H$39 -> 0.0011970744 | AC10: =AB10*$AC$3 -> 7.9553972
B11: 112 | C11: EHS | H11: 5625.65 | J11: =H11/$I$35 -> 0.052148463 | K11: =H11/$I$37 -> 0.046556061 | L11: =J11*$L$3 -> 340.57796 | M11: =J11*$M$3 -> 79.654691 | N11: =J11*$N$3 -> 83.362969 | O11: =J11*$O$3 -> 16.374096 | P11: =J11*$P$3 -> 69.397089 | Q11: =K11*$Q$3 -> 0 | R11: =K11*$R$3 -> 139.94752 | S11: =K11*$S$3 -> 228.1247 | T11: =K11*$T$3 -> 0 | U11: =K11*$U$3 -> 29.83033 | V11: =K11*$V$3 -> 14.525491 | W11: =K11*$W$3 -> 50.839218 | X11: =K11*$X$3 -> 108.07245 | Y11: =K11*$Y$3 -> 35.592574 | Z11: =K11*$Z$3 -> 184.94302 | AB11: =H11/$H$39 -> 0.026464108 | AC11: =AB11*$AC$3 -> 175.87252
B12: 114 | C12: Summer Camp | H12: 0 | J12: =H12/$I$35 -> 0 | K12: =H12/$I$37 -> 0 | L12: =J12*$L$3 -> 0 | M12: =J12*$M$3 -> 0 | N12: =J12*$N$3 -> 0 | O12: =J12*$O$3 -> 0 | P12: =J12*$P$3 -> 0 | Q12: =K12*$Q$3 -> 0 | R12: =K12*$R$3 -> 0 | S12: =K12*$S$3 -> 0 | T12: =K12*$T$3 -> 0 | U12: =K12*$U$3 -> 0 | V12: =K12*$V$3 -> 0 | W12: =K12*$W$3 -> 0 | X12: =K12*$X$3 -> 0 | Y12: =K12*$Y$3 -> 0 | Z12: =K12*$Z$3 -> 0 | AB12: =H12/$H$39 -> 0 | AC12: =AB12*$AC$3 -> 0
B13: 222 | C13: DCF- Coding | H13: 2480.65 | J13: =H13/$I$35 -> 0.022995047 | K13: =H13/$I$37 -> 0.020529057 | L13: =J13*$L$3 -> 150.17904 | M13: =J13*$M$3 -> 35.124014 | N13: =J13*$N$3 -> 36.759192 | O13: =J13*$O$3 -> 7.2202147 | P13: =J13*$P$3 -> 30.600888 | Q13: =K13*$Q$3 -> 0 | R13: =K13*$R$3 -> 61.710347 | S13: =K13*$S$3 -> 100.59238 | T13: =K13*$T$3 -> 0 | U13: =K13*$U$3 -> 13.153788 | V13: =K13*$V$3 -> 6.4050659 | W13: =K13*$W$3 -> 22.417731 | X13: =K13*$X$3 -> 47.654922 | Y13: =K13*$Y$3 -> 15.69467 | Z13: =K13*$Z$3 -> 81.55127 | AB13: =H13/$H$39 -> 0.011669441 | AC13: =AB13*$AC$3 -> 77.551601
B14: 223 | C14: OICA | H14: 0 | J14: =H14/$I$35 -> 0 | K14: =H14/$I$37 -> 0 | L14: =J14*$L$3 -> 0 | M14: =J14*$M$3 -> 0 | N14: =J14*$N$3 -> 0 | O14: =J14*$O$3 -> 0 | P14: =J14*$P$3 -> 0 | Q14: =K14*$Q$3 -> 0 | R14: =K14*$R$3 -> 0 | S14: =K14*$S$3 -> 0 | T14: =K14*$T$3 -> 0 | U14: =K14*$U$3 -> 0 | V14: =K14*$V$3 -> 0 | W14: =K14*$W$3 -> 0 | X14: =K14*$X$3 -> 0 | Y14: =K14*$Y$3 -> 0 | Z14: =K14*$Z$3 -> 0 | AB14: =H14/$H$39 -> 0 | AC14: =AB14*$AC$3 -> 0
B15: 334 | C15: NRTC - Admin | H15: 0 | J15: =H15/$I$35 -> 0 | K15: =H15/$I$37 -> 0 | L15: =J15*$L$3 -> 0 | M15: =J15*$M$3 -> 0 | N15: =J15*$N$3 -> 0 | O15: =J15*$O$3 -> 0 | P15: =J15*$P$3 -> 0 | Q15: =K15*$Q$3 -> 0 | R15: =K15*$R$3 -> 0 | S15: =K15*$S$3 -> 0 | T15: =K15*$T$3 -> 0 | U15: =K15*$U$3 -> 0 | V15: =K15*$V$3 -> 0 | W15: =K15*$W$3 -> 0 | X15: =K15*$X$3 -> 0 | Y15: =K15*$Y$3 -> 0 | Z15: =K15*$Z$3 -> 0 | AB15: =H15/$H$39 -> 0 | AC15: =AB15*$AC$3 -> 0
B16: 334H | C16: NRTC - Housing | H16: 1150 | J16: =H16/$I$35 -> 0.010660232 | K16: =H16/$I$37 -> 0.0095170282 | L16: =J16*$L$3 -> 69.621227 | M16: =J16*$M$3 -> 16.283078 | N16: =J16*$N$3 -> 17.041127 | O16: =J16*$O$3 -> 3.3472062 | P16: =J16*$P$3 -> 14.18621 | Q16: =K16*$Q$3 -> 0 | R16: =K16*$R$3 -> 28.608187 | S16: =K16*$S$3 -> 46.633438 | T16: =K16*$T$3 -> 0 | U16: =K16*$U$3 -> 6.0979406 | V16: =K16*$V$3 -> 2.9693128 | W16: =K16*$W$3 -> 10.392595 | X16: =K16*$X$3 -> 22.092258 | Y16: =K16*$Y$3 -> 7.2758632 | Z16: =K16*$Z$3 -> 37.806204 | AB16: =H16/$H$39 -> 0.0054098146 | AC16: =AB16*$AC$3 -> 35.952005
B17: 334F | C17: NRTC FOC | H17: 0 | J17: =H17/$I$35 -> 0 | K17: =H17/$I$37 -> 0 | L17: =J17*$L$3 -> 0 | M17: =J17*$M$3 -> 0 | N17: =J17*$N$3 -> 0 | O17: =J17*$O$3 -> 0 | P17: =J17*$P$3 -> 0 | Q17: =K17*$Q$3 -> 0 | R17: =K17*$R$3 -> 0 | S17: =K17*$S$3 -> 0 | T17: =K17*$T$3 -> 0 | U17: =K17*$U$3 -> 0 | V17: =K17*$V$3 -> 0 | W17: =K17*$W$3 -> 0 | X17: =K17*$X$3 -> 0 | Y17: =K17*$Y$3 -> 0 | Z17: =K17*$Z$3 -> 0 | AB17: =H17/$H$39 -> 0 | AC17: =AB17*$AC$3 -> 0
B18: 335 | C18: NRTC 19 | H18: 846.15 | J18: =H18/$I$35 -> 0.0078436131 | K18: =H18/$I$37 -> 0.0070024638 | L18: =J18*$L$3 -> 51.226088 | M18: =J18*$M$3 -> 11.980805 | N18: =J18*$N$3 -> 12.538565 | O18: =J18*$O$3 -> 2.4628161 | P18: =J18*$P$3 -> 10.437967 | Q18: =K18*$Q$3 -> 0 | R18: =K18*$R$3 -> 21.049406 | S18: =K18*$S$3 -> 34.312073 | T18: =K18*$T$3 -> 0 | U18: =K18*$U$3 -> 4.4867587 | V18: =K18*$V$3 -> 2.1847687 | W18: =K18*$W$3 -> 7.6466905 | X18: =K18*$X$3 -> 16.255099 | Y18: =K18*$Y$3 -> 5.3534536 | Z18: =K18*$Z$3 -> 27.817148 | AB18: =H18/$H$39 -> 0.0039804475 | AC18: =AB18*$AC$3 -> 26.45286
B19: 368 | C19: Wells Fargo | H19: 5985.24 | J19: =H19/$I$35 -> 0.055481779 | K19: =H19/$I$37 -> 0.049531911 | L19: =J19*$L$3 -> 362.34761 | M19: =J19*$M$3 -> 84.746197 | N19: =J19*$N$3 -> 88.691507 | O19: =J19*$O$3 -> 17.420724 | P19: =J19*$P$3 -> 73.832932 | Q19: =K19*$Q$3 -> 0 | R19: =K19*$R$3 -> 148.89292 | S19: =K19*$S$3 -> 242.70636 | T19: =K19*$T$3 -> 0 | U19: =K19*$U$3 -> 31.737077 | V19: =K19*$V$3 -> 15.453956 | W19: =K19*$W$3 -> 54.088847 | X19: =K19*$X$3 -> 114.98041 | Y19: =K19*$Y$3 -> 37.867641 | Z19: =K19*$Z$3 -> 196.76453 | AB19: =H19/$H$39 -> 0.028155686 | AC19: =AB19*$AC$3 -> 187.11424
B20: 451 | C20: USJP | H20: 14938.24 | J20: =H20/$I$35 -> 0.138474 | K20: =H20/$I$37 -> 0.12362404 | L20: =J20*$L$3 -> 904.364 | M20: =J20*$M$3 -> 211.5135 | N20: =J20*$N$3 -> 221.36038 | O20: =J20*$O$3 -> 43.479451 | P20: =J20*$P$3 -> 184.27566 | Q20: =K20*$Q$3 -> 0 | R20: =K20*$R$3 -> 371.61388 | S20: =K20*$S$3 -> 605.75782 | T20: =K20*$T$3 -> 0 | U20: =K20*$U$3 -> 79.21087 | V20: =K20*$V$3 -> 38.570702 | W20: =K20*$W$3 -> 134.99746 | X20: =K20*$X$3 -> 286.97344 | Y20: =K20*$Y$3 -> 94.511818 | Z20: =K20*$Z$3 -> 491.09404 | AB20: =H20/$H$39 -> 0.070272269 | AC20: =AB20*$AC$3 -> 467.00842
B21: 452 | C21: PACE | H21: 0 | J21: =H21/$I$35 -> 0 | K21: =H21/$I$37 -> 0 | L21: =J21*$L$3 -> 0 | M21: =J21*$M$3 -> 0 | N21: =J21*$N$3 -> 0 | O21: =J21*$O$3 -> 0 | P21: =J21*$P$3 -> 0 | Q21: =K21*$Q$3 -> 0 | R21: =K21*$R$3 -> 0 | S21: =K21*$S$3 -> 0 | T21: =K21*$T$3 -> 0 | U21: =K21*$U$3 -> 0 | V21: =K21*$V$3 -> 0 | W21: =K21*$W$3 -> 0 | X21: =K21*$X$3 -> 0 | Y21: =K21*$Y$3 -> 0 | Z21: =K21*$Z$3 -> 0 | AB21: =H21/$H$39 -> 0 | AC21: =AB21*$AC$3 -> 0
B22: 454 | C22: Prudential #1 Workforce | K22: =H22/$I$37 -> 0 | Q22: =K22*$Q$3 -> 0 | R22: =K22*$R$3 -> 0 | S22: =K22*$S$3 -> 0 | T22: =K22*$T$3 -> 0 | U22: =K22*$U$3 -> 0 | V22: =K22*$V$3 -> 0 | W22: =K22*$W$3 -> 0 | X22: =K22*$X$3 -> 0 | Y22: =K22*$Y$3 -> 0 | Z22: =K22*$Z$3 -> 0
B23: 467 | C23: WF - United Airlines | H23: 9532.71 | J23: =H23/$I$35 -> 0.088365998 | K23: =H23/$I$37 -> 0.078889626 | L23: =J23*$L$3 -> 577.11215 | M23: =J23*$M$3 -> 134.97553 | N23: =J23*$N$3 -> 141.25923 | O23: =J23*$O$3 -> 27.74604 | P23: =J23*$P$3 -> 117.59394 | Q23: =K23*$Q$3 -> 0 | R23: =K23*$R$3 -> 237.14222 | S23: =K23*$S$3 -> 386.55917 | T23: =K23*$T$3 -> 0 | U23: =K23*$U$3 -> 50.547739 | V23: =K23*$V$3 -> 24.613563 | W23: =K23*$W$3 -> 86.147472 | X23: =K23*$X$3 -> 183.12964 | Y23: =K23*$Y$3 -> 60.311908 | Z23: =K23*$Z$3 -> 313.38746 | AB23: =H23/$H$39 -> 0.044843647 | AC23: =AB23*$AC$3 -> 298.01742
B24: 468 | C24: Newark Alliance | H24: 6307.7 | J24: =H24/$I$35 -> 0.058470907 | K24: =H24/$I$37 -> 0.052200486 | L24: =J24*$L$3 -> 381.8694 | M24: =J24*$M$3 -> 89.311972 | N24: =J24*$N$3 -> 93.469839 | O24: =J24*$O$3 -> 18.35928 | P24: =J24*$P$3 -> 77.810745 | Q24: =K24*$Q$3 -> 0 | R24: =K24*$R$3 -> 156.91466 | S24: =K24*$S$3 -> 255.78238 | T24: =K24*$T$3 -> 0 | U24: =K24*$U$3 -> 33.446939 | V24: =K24*$V$3 -> 16.286552 | W24: =K24*$W$3 -> 57.002931 | X24: =K24*$X$3 -> 121.17508 | Y24: =K24*$Y$3 -> 39.907793 | Z24: =K24*$Z$3 -> 207.36539 | AB24: =H24/$H$39 -> 0.029672598 | AC24: =AB24*$AC$3 -> 197.19518
B25: 502 | C25: ESG | H25: 1678.6 | J25: =H25/$I$35 -> 0.01556023 | K25: =H25/$I$37 -> 0.013891551 | L25: =J25*$L$3 -> 101.62278 | M25: =J25*$M$3 -> 23.76763 | N25: =J25*$N$3 -> 24.874118 | O25: =J25*$O$3 -> 4.8857567 | P25: =J25*$P$3 -> 20.706932 | Q25: =K25*$Q$3 -> 0 | R25: =K25*$R$3 -> 41.758002 | S25: =K25*$S$3 -> 68.068599 | T25: =K25*$T$3 -> 0 | U25: =K25*$U$3 -> 8.9008723 | V25: =K25*$V$3 -> 4.3341639 | W25: =K25*$W$3 -> 15.169574 | X25: =K25*$X$3 -> 32.247013 | Y25: =K25*$Y$3 -> 10.62023 | Z25: =K25*$Z$3 -> 55.183908 | AB25: =H25/$H$39 -> 0.0078964477 | AC25: =AB25*$AC$3 -> 52.477422
B26: 515 | C26: FOC - HUD NUL PARS | H26: 1730.77 | J26: =H26/$I$35 -> 0.016043834 | K26: =H26/$I$37 -> 0.014323293 | L26: =J26*$L$3 -> 104.78116 | M26: =J26*$M$3 -> 24.506315 | N26: =J26*$N$3 -> 25.647192 | O26: =J26*$O$3 -> 5.0376035 | P26: =J26*$P$3 -> 21.350493 | Q26: =K26*$Q$3 -> 0 | R26: =K26*$R$3 -> 43.055819 | S26: =K26*$S$3 -> 70.184135 | T26: =K26*$T$3 -> 0 | U26: =K26*$U$3 -> 9.1775067 | V26: =K26*$V$3 -> 4.4688674 | W26: =K26*$W$3 -> 15.641036 | X26: =K26*$X$3 -> 33.249233 | Y26: =K26*$Y$3 -> 10.950301 | Z26: =K26*$Z$3 -> 56.898995 | AB26: =H26/$H$39 -> 0.0081418651 | AC26: =AB26*$AC$3 -> 54.108393
B27: 525 | C27: CDBG - Housing | H27: 2900 | J27: =H27/$I$35 -> 0.026882323 | K27: =H27/$I$37 -> 0.023999462 | L27: =J27*$L$3 -> 175.56657 | M27: =J27*$M$3 -> 41.061674 | N27: =J27*$N$3 -> 42.973276 | O27: =J27*$O$3 -> 8.4407807 | P27: =J27*$P$3 -> 35.773921 | Q27: =K27*$Q$3 -> 0 | R27: =K27*$R$3 -> 72.142384 | S27: =K27*$S$3 -> 117.59737 | T27: =K27*$T$3 -> 0 | U27: =K27*$U$3 -> 15.377416 | V27: =K27*$V$3 -> 7.4878323 | W27: =K27*$W$3 -> 26.207413 | X27: =K27*$X$3 -> 55.710912 | Y27: =K27*$Y$3 -> 18.347829 | Z27: =K27*$Z$3 -> 95.337384 | AB27: =H27/$H$39 -> 0.013642141 | AC27: =AB27*$AC$3 -> 90.661578
B28: 560 | C28: CAP 1 - Save Up | H28: 0 | J28: =H28/$I$35 -> 0 | K28: =H28/$I$37 -> 0 | L28: =J28*$L$3 -> 0 | M28: =J28*$M$3 -> 0 | N28: =J28*$N$3 -> 0 | O28: =J28*$O$3 -> 0 | P28: =J28*$P$3 -> 0 | Q28: =K28*$Q$3 -> 0 | R28: =K28*$R$3 -> 0 | S28: =K28*$S$3 -> 0 | T28: =K28*$T$3 -> 0 | U28: =K28*$U$3 -> 0 | V28: =K28*$V$3 -> 0 | W28: =K28*$W$3 -> 0 | X28: =K28*$X$3 -> 0 | Y28: =K28*$Y$3 -> 0 | Z28: =K28*$Z$3 -> 0 | AB28: =H28/$H$39 -> 0 | AC28: =AB28*$AC$3 -> 0
B29: 561 | C29: LISC FOC 2019 | H29: 4384.62 | J29: =H29/$I$35 -> 0.040644405 | K29: =H29/$I$37 -> 0.036285698 | L29: =J29*$L$3 -> 265.44576 | M29: =J29*$M$3 -> 62.082702 | N29: =J29*$N$3 -> 64.972926 | O29: =J29*$O$3 -> 12.761937 | P29: =J29*$P$3 -> 54.087948 | Q29: =K29*$Q$3 -> 0 | R29: =K29*$R$3 -> 109.07481 | S29: =K29*$S$3 -> 177.79992 | T29: =K29*$T$3 -> 0 | U29: =K29*$U$3 -> 23.249698 | V29: =K29*$V$3 -> 11.321138 | W29: =K29*$W$3 -> 39.623982 | X29: =K29*$X$3 -> 84.231441 | Y29: =K29*$Y$3 -> 27.740779 | Z29: =K29*$Z$3 -> 144.14421 | AB29: =H29/$H$39 -> 0.020626071 | AC29: =AB29*$AC$3 -> 137.07468
B30: 563 | C30: Prudential #1 FOC | H30: 2993.49 | J30: =H30/$I$35 -> 0.027748954 | K30: =H30/$I$37 -> 0.024773155 | L30: =J30*$L$3 -> 181.22648 | M30: =J30*$M$3 -> 42.385417 | N30: =J30*$N$3 -> 44.358645 | O30: =J30*$O$3 -> 8.7128941 | P30: =J30*$P$3 -> 36.927198 | Q30: =K30*$Q$3 -> 0 | R30: =K30*$R$3 -> 74.468105 | S30: =K30*$S$3 -> 121.38846 | T30: =K30*$T$3 -> 0 | U30: =K30*$U$3 -> 15.873152 | V30: =K30*$V$3 -> 7.7292245 | W30: =K30*$W$3 -> 27.052286 | X30: =K30*$X$3 -> 57.506917 | Y30: =K30*$Y$3 -> 18.939325 | Z30: =K30*$Z$3 -> 98.410864 | AB30: =H30/$H$39 -> 0.014081936 | AC30: =AB30*$AC$3 -> 93.58432
B31: 610 | C31: CEO | H31: 11923.08 | J31: =H31/$I$35 -> 0.11052417 | K31: =H31/$I$37 -> 0.098671555 | L31: =J31*$L$3 -> 721.82562 | M31: =J31*$M$3 -> 168.82125 | N31: =J31*$N$3 -> 176.68062 | O31: =J31*$O$3 -> 34.703484 | P31: =J31*$P$3 -> 147.08114 | Q31: =K31*$Q$3 -> 0 | R31: =K31*$R$3 -> 296.6067 | S31: =K31*$S$3 -> 483.49062 | T31: =K31*$T$3 -> 0 | U31: =K31*$U$3 -> 63.222812 | V31: =K31*$V$3 -> 30.785525 | W31: =K31*$W$3 -> 107.74934 | X31: =K31*$X$3 -> 229.05023 | Y31: =K31*$Y$3 -> 75.435391 | Z31: =K31*$Z$3 -> 391.97078 | AB31: =H31/$H$39 -> 0.056088394 | AC31: =AB31*$AC$3 -> 372.74664
B32: 620 | C32: CFO | H32: 6015.39 | J32: =H32/$I$35 -> 0.055761262 | K32: =H32/$I$37 -> 0.049781423 | L32: =J32*$L$3 -> 364.1729 | M32: =J32*$M$3 -> 85.173097 | N32: =J32*$N$3 -> 89.138281 | O32: =J32*$O$3 -> 17.508479 | P32: =J32*$P$3 -> 74.204857 | Q32: =K32*$Q$3 -> 0 | R32: =K32*$R$3 -> 149.64296 | S32: =K32*$S$3 -> 243.92897 | T32: =K32*$T$3 -> 0 | U32: =K32*$U$3 -> 31.896949 | V32: =K32*$V$3 -> 15.531804 | W32: =K32*$W$3 -> 54.361314 | X32: =K32*$X$3 -> 115.55961 | Y32: =K32*$Y$3 -> 38.058396 | Z32: =K32*$Z$3 -> 197.75571 | AB32: =H32/$H$39 -> 0.028297517 | AC32: =AB32*$AC$3 -> 188.05681
B33: 630 | C33: COO | H33: 0 | J33: =H33/$I$35 -> 0 | K33: =H33/$I$37 -> 0 | L33: =J33*$L$3 -> 0 | M33: =J33*$M$3 -> 0 | N33: =J33*$N$3 -> 0 | O33: =J33*$O$3 -> 0 | P33: =J33*$P$3 -> 0 | Q33: =K33*$Q$3 -> 0 | R33: =K33*$R$3 -> 0 | S33: =K33*$S$3 -> 0 | T33: =K33*$T$3 -> 0 | U33: =K33*$U$3 -> 0 | V33: =K33*$V$3 -> 0 | W33: =K33*$W$3 -> 0 | X33: =K33*$X$3 -> 0 | Y33: =K33*$Y$3 -> 0 | Z33: =K33*$Z$3 -> 0 | AB33: =H33/$H$39 -> 0 | AC33: =AB33*$AC$3 -> 0
B34: 650 | C34: Facilities | H34: 299 | J34: =H34/$I$35 -> 0.0027716602 | K34: =H34/$I$37 -> 0.0024744273 | L34: =J34*$L$3 -> 18.101519 | M34: =J34*$M$3 -> 4.2336002 | N34: =J34*$N$3 -> 4.4306929 | O34: =J34*$O$3 -> 0.8702736 | P34: =J34*$P$3 -> 3.6884146 | Q34: =K34*$Q$3 -> 0 | R34: =K34*$R$3 -> 7.4381286 | S34: =K34*$S$3 -> 12.124694 | T34: =K34*$T$3 -> 0 | U34: =K34*$U$3 -> 1.5854646 | V34: =K34*$V$3 -> 0.77202133 | W34: =K34*$W$3 -> 2.7020746 | X34: =K34*$X$3 -> 5.7439871 | Y34: =K34*$Y$3 -> 1.8917244 | Z34: =K34*$Z$3 -> 9.8296131 | AB34: =H34/$H$39 -> 0.0014065518 | AC34: =AB34*$AC$3 -> 9.3475213
B35: 600 | C35: Admin | H35: -0.01 | I35: =SUM(H6:H35) -> 107877.58 | J35: =H35/$I$35 -> -9.2697667e-08 | K35: =H35/$I$37 -> -8.2756767e-08 | L35: =J35*$L$3 -> -0.00060540198 | M35: =J35*$M$3 -> -0.00014159198 | N35: =J35*$N$3 -> -0.00014818371 | O35: =J35*$O$3 -> -2.910614e-05 | P35: =J35*$P$3 -> -0.00012335835 | Q35: =K35*$Q$3 -> 0 | R35: =K35*$R$3 -> -0.00024876684 | S35: =K35*$S$3 -> -0.00040550816 | T35: =K35*$T$3 -> 0 | U35: =K35*$U$3 -> -5.3025571e-05 | V35: =K35*$V$3 -> -2.5820111e-05 | W35: =K35*$W$3 -> -9.0370389e-05 | X35: =K35*$X$3 -> -0.00019210659 | Y35: =K35*$Y$3 -> -6.3268376e-05 | Z35: =K35*$Z$3 -> -0.0003287496 | AB35: =H35/$H$39 -> -4.7041866e-08 | AC35: =AB35*$AC$3 -> -0.00031262613
B36: 339 | C36: Opport Corp | H36: =J53 -> 7420 | K36: =H36/$I$37 -> 0.061405521 | L36: =J36*$L$3 -> 0 | M36: =J36*$M$3 -> 0 | N36: =J36*$N$3 -> 0 | O36: =J36*$O$3 -> 0 | P36: =J36*$P$3 -> 0 | Q36: =K36*$Q$3 -> 0 | R36: =K36*$R$3 -> 184.585 | S36: =K36*$S$3 -> 300.88705 | T36: =K36*$T$3 -> 0 | U36: =K36*$U$3 -> 39.344974 | V36: =K36*$V$3 -> 19.158523 | W36: =K36*$W$3 -> 67.054829 | X36: =K36*$X$3 -> 142.54309 | Y36: =K36*$Y$3 -> 46.945135 | Z36: =K36*$Z$3 -> 243.9322 | AB36: =H36/$H$39 -> 0.034905065 | AC36: =AB36*$AC$3 -> 231.96859
B37: 225 | C37: AmeriCorp | H37: =I53 -> 5538.46 | I37: =I35+H36+H37 -> 120836.04 | K37: =H37/$I$37 -> 0.045834504 | Q37: =K37*$Q$3 -> 0 | R37: =K37*$R$3 -> 137.77852 | S37: =K37*$S$3 -> 224.58907 | T37: =K37*$T$3 -> 0 | U37: =K37*$U$3 -> 29.368 | V37: =K37*$V$3 -> 14.300365 | W37: =K37*$W$3 -> 50.051279 | X37: =K37*$X$3 -> 106.39747 | Y37: =K37*$Y$3 -> 35.040937 | Z37: =K37*$Z$3 -> 182.07665 | AB37: =H37/$H$39 -> 0.026053949 | AC37: =AB37*$AC$3 -> 173.14673
B38: 451 | C38: USJP - Participants | F38: 91740.56 | H38: 91740.56 | AB38: =H38/$H$39 -> 0.43156472 | AC38: =AB38*$AC$3 -> 2868.0496
H39: =SUM(H6:H38) -> 212576.6 | J39: =SUM(J6:J38) -> 1 | K39: =SUM(K6:K38) -> 1 | L39: =SUM(L6:L38) -> 6530.93 | M39: =SUM(M6:M38) -> 1527.46 | N39: =SUM(N6:N38) -> 1598.57 | O39: =SUM(O6:O38) -> 313.99 | P39: =SUM(P6:P38) -> 1330.76 | Q39: =SUM(Q6:Q38) -> 0 | ... AC39: =SUM(AC6:AC38) -> 6645.7
H40: Salary | J40: Hourly | L40: =L3-L39 -> 0 | M40: =M3-M39 -> 0 | N40: =N3-N39 -> 0 | O40: =O3-O39 -> 0 | P40: =P3-P39 -> 0 | Q40: =Q3-Q39 -> 0 | R40: =R3-R39 -> 0 | S40: =S3-S39 -> 0 | ... AC40: =AC3-AC39 -> 0
C41: 43717 | H41: 50893.35 | L41: 3872.3 | M41: 905.65 | N41: 1253.04 | O41: 229.72
C42: 43728 | H42: 58065.96 | J42: 0 | L42: 3698.62 | M42: 865.02 | N42: 1101.14 | O42: 201.86
H43: -1081.74
H44: =K53 -> 12958.46
H45: =SUM(H41:H44) -> 120836.03 | L45: =SUM(L41:L42) -> 7570.92 | M45: =SUM(M41:M42) -> 1770.67 | N45: =SUM(N41:N42) -> 2354.18 | O45: =SUM(O41:O42) -> 431.58 | P45: =SUM(P41:P42) -> 0
H46: =H39-H45 -> 91740.57 | AG46: 114.44
I47: Opp Corp | J47: Americ | AG47: 151.65
F48: =I35-H44 -> 94919.12
I49: 2769.23 | J49: 3168.96
I50: 2769.23 | J50: 3168.96
J51: 0.34
J52: 1081.74
I53: =SUM(I49:I52) -> 5538.46 | J53: =SUM(J49:J52) -> 7420 | K53: =SUM(I53:J53) -> 12958.46
J55: =J53+'May 2019 Alloc '!I60+'April 2019 Alloc '!H44+'April 2019 Alloc '!H45 -> 30659.03

Sheet Sept 2019 Alloc 
B1: September Cost Allocations | L1: 7251 | M1: 7252 | N1: 7253 | O1: 7254 | P1: 7260.1 | Q1: 8140 | R1: 7515.5 | S1: 7521 | T1: 8112 | U1: 8135.5 | V1: 8191 | W1: 8210.5 | X1: 8229.1 | Y1: 8239 | Z1: 8266 | AC1: 7248
L2: FICA | M2: MEDI | N2: SUI | O2: Disability | P2: Payroll Fees | Q2: Postage | R2: IT Consultants | S2: Acctg Fees | T2: Supplies | U2: Telephone | V2: Web Hosting | W2: Utilities | X2: Eq Lease | Y2: Repairs | Z2: General Insurance | AC2: W/ Comp
L3: 6530.93 | M3: 1527.46 | N3: 1598.57 | O3: 313.99 | P3: 1330.76 | R3: 3006 | S3: 4900 | U3: 640.74 | V3: 312 | W3: 1092 | X3: 2321.34 | Y3: 764.51 | Z3: 3972.48 | AC3: 6645.7
L4: 1 | M4: 2 | N4: 3 | O4: 4 | P4: 5 | Q4: 6 | R4: 7 | S4: 8 | T4: 9 | U4: 10 | V4: 11 | W4: 12 | X4: 13 | Y4: 14 | Z4: 15 | AC4: 0.04
D5: 7222 | E5: Taxes | F5: W/C | J5: Taxes | K5: Expenses
B6: 41 | C6: Thriftworks | H6: 0 | J6: =H6/$I$35 -> 0 | K6: =H6/$I$37 -> 0 | L6: =J6*$L$3 -> 0 | M6: =J6*$M$3 -> 0 | N6: =J6*$N$3 -> 0 | O6: =J6*$O$3 -> 0 | P6: =J6*$P$3 -> 0 | Q6: =K6*$Q$3 -> 0 | R6: =K6*$R$3 -> 0 | S6: =K6*$S$3 -> 0 | T6: =K6*$T$3 -> 0 | U6: =K6*$U$3 -> 0 | V6: =K6*$V$3 -> 0 | W6: =K6*$W$3 -> 0 | X6: =K6*$X$3 -> 0 | Y6: =K6*$Y$3 -> 0 | Z6: =K6*$Z$3 -> 0 | AB6: =H6/$H$39 -> 0 | AC6: =AB6*$AC$3 -> 0
B7: 111 | C7: Abbott | H7: 25010.78 | J7: =H7/$I$35 -> 0.2318441 | K7: =H7/$I$37 -> 0.20698113 | L7: =J7*$L$3 -> 1514.1576 | M7: =J7*$M$3 -> 354.13258 | N7: =J7*$N$3 -> 370.61902 | O7: =J7*$O$3 -> 72.796728 | P7: =J7*$P$3 -> 308.52885 | Q7: =K7*$Q$3 -> 0 | R7: =K7*$R$3 -> 622.18527 | S7: =K7*$S$3 -> 1014.2075 | T7: =K7*$T$3 -> 0 | U7: =K7*$U$3 -> 132.62109 | V7: =K7*$V$3 -> 64.578112 | W7: =K7*$W$3 -> 226.02339 | X7: =K7*$X$3 -> 480.47357 | Y7: =K7*$Y$3 -> 158.23914 | Z7: =K7*$Z$3 -> 822.2284 | AB7: =H7/$H$39 -> 0.11765538 | AC7: =AB7*$AC$3 -> 781.90234
B8: 111A | C8: Abbott - Other | H8: 2617.28 | J8: =H8/$I$35 -> 0.024261575 | K8: =H8/$I$37 -> 0.021659763 | L8: =J8*$L$3 -> 158.45065 | M8: =J8*$M$3 -> 37.058585 | N8: =J8*$N$3 -> 38.783826 | O8: =J8*$O$3 -> 7.6178919 | P8: =J8*$P$3 -> 32.286334 | Q8: =K8*$Q$3 -> 0 | R8: =K8*$R$3 -> 65.109248 | S8: =K8*$S$3 -> 106.13284 | T8: =K8*$T$3 -> 0 | U8: =K8*$U$3 -> 13.878277 | V8: =K8*$V$3 -> 6.7578461 | W8: =K8*$W$3 -> 23.652461 | X8: =K8*$X$3 -> 50.279674 | Y8: =K8*$Y$3 -> 16.559105 | Z8: =K8*$Z$3 -> 86.042976 | AB8: =H8/$H$39 -> 0.012312174 | AC8: =AB8*$AC$3 -> 81.823012
B9: 111B | C9: Abbott Fees | H9: 1203.77 | J9: =H9/$I$35 -> 0.011158667 | K9: =H9/$I$37 -> 0.0099620113 | L9: =J9*$L$3 -> 72.876474 | M9: =J9*$M$3 -> 17.044418 | N9: =J9*$N$3 -> 17.83791 | O9: =J9*$O$3 -> 3.5037099 | P9: =J9*$P$3 -> 14.849508 | Q9: =K9*$Q$3 -> 0 | R9: =K9*$R$3 -> 29.945806 | S9: =K9*$S$3 -> 48.813856 | T9: =K9*$T$3 -> 0 | U9: =K9*$U$3 -> 6.3830591 | V9: =K9*$V$3 -> 3.1081475 | W9: =K9*$W$3 -> 10.878516 | X9: =K9*$X$3 -> 23.125215 | Y9: =K9*$Y$3 -> 7.6160573 | Z9: =K9*$Z$3 -> 39.573891 | AB9: =H9/$H$39 -> 0.0056627587 | AC9: =AB9*$AC$3 -> 37.632996
B10: 111F | C10: Abbott Food | H10: 254.47 | J10: =H10/$I$35 -> 0.0023588775 | K10: =H10/$I$37 -> 0.0021059114 | L10: =J10*$L$3 -> 15.405664 | M10: =J10*$M$3 -> 3.6030911 | N10: =J10*$N$3 -> 3.7708309 | O10: =J10*$O$3 -> 0.74066396 | P10: =J10*$P$3 -> 3.1390999 | Q10: =K10*$Q$3 -> 0 | R10: =K10*$R$3 -> 6.3303698 | S10: =K10*$S$3 -> 10.318966 | T10: =K10*$T$3 -> 0 | U10: =K10*$U$3 -> 1.3493417 | V10: =K10*$V$3 -> 0.65704437 | W10: =K10*$W$3 -> 2.2996553 | X10: =K10*$X$3 -> 4.8885365 | Y10: =K10*$Y$3 -> 1.6099904 | Z10: =K10*$Z$3 -> 8.3656911 | AB10: =H10/$H$39 -> 0.0011970744 | AC10: =AB10*$AC$3 -> 7.9553972
B11: 112 | C11: EHS | H11: 5625.65 | J11: =H11/$I$35 -> 0.052148463 | K11: =H11/$I$37 -> 0.046556061 | L11: =J11*$L$3 -> 340.57796 | M11: =J11*$M$3 -> 79.654691 | N11: =J11*$N$3 -> 83.362969 | O11: =J11*$O$3 -> 16.374096 | P11: =J11*$P$3 -> 69.397089 | Q11: =K11*$Q$3 -> 0 | R11: =K11*$R$3 -> 139.94752 | S11: =K11*$S$3 -> 228.1247 | T11: =K11*$T$3 -> 0 | U11: =K11*$U$3 -> 29.83033 | V11: =K11*$V$3 -> 14.525491 | W11: =K11*$W$3 -> 50.839218 | X11: =K11*$X$3 -> 108.07245 | Y11: =K11*$Y$3 -> 35.592574 | Z11: =K11*$Z$3 -> 184.94302 | AB11: =H11/$H$39 -> 0.026464108 | AC11: =AB11*$AC$3 -> 175.87252
B12: 114 | C12: Summer Camp | H12: 0 | J12: =H12/$I$35 -> 0 | K12: =H12/$I$37 -> 0 | L12: =J12*$L$3 -> 0 | M12: =J12*$M$3 -> 0 | N12: =J12*$N$3 -> 0 | O12: =J12*$O$3 -> 0 | P12: =J12*$P$3 -> 0 | Q12: =K12*$Q$3 -> 0 | R12: =K12*$R$3 -> 0 | S12: =K12*$S$3 -> 0 | T12: =K12*$T$3 -> 0 | U12: =K12*$U$3 -> 0 | V12: =K12*$V$3 -> 0 | W12: =K12*$W$3 -> 0 | X12: =K12*$X$3 -> 0 | Y12: =K12*$Y$3 -> 0 | Z12: =K12*$Z$3 -> 0 | AB12: =H12/$H$39 -> 0 | AC12: =AB12*$AC$3 -> 0
B13: 222 | C13: DCF- Coding | H13: 2480.65 | J13: =H13/$I$35 -> 0.022995047 | K13: =H13/$I$37 -> 0.020529057 | L13: =J13*$L$3 -> 150.17904 | M13: =J13*$M$3 -> 35.124014 | N13: =J13*$N$3 -> 36.759192 | O13: =J13*$O$3 -> 7.2202147 | P13: =J13*$P$3 -> 30.600888 | Q13: =K13*$Q$3 -> 0 | R13: =K13*$R$3 -> 61.710347 | S13: =K13*$S$3 -> 100.59238 | T13: =K13*$T$3 -> 0 | U13: =K13*$U$3 -> 13.153788 | V13: =K13*$V$3 -> 6.4050659 | W13: =K13*$W$3 -> 22.417731 | X13: =K13*$X$3 -> 47.654922 | Y13: =K13*$Y$3 -> 15.69467 | Z13: =K13*$Z$3 -> 81.55127 | AB13: =H13/$H$39 -> 0.011669441 | AC13: =AB13*$AC$3 -> 77.551601
B14: 223 | C14: OICA | H14: 0 | J14: =H14/$I$35 -> 0 | K14: =H14/$I$37 -> 0 | L14: =J14*$L$3 -> 0 | M14: =J14*$M$3 -> 0 | N14: =J14*$N$3 -> 0 | O14: =J14*$O$3 -> 0 | P14: =J14*$P$3 -> 0 | Q14: =K14*$Q$3 -> 0 | R14: =K14*$R$3 -> 0 | S14: =K14*$S$3 -> 0 | T14: =K14*$T$3 -> 0 | U14: =K14*$U$3 -> 0 | V14: =K14*$V$3 -> 0 | W14: =K14*$W$3 -> 0 | X14: =K14*$X$3 -> 0 | Y14: =K14*$Y$3 -> 0 | Z14: =K14*$Z$3 -> 0 | AB14: =H14/$H$39 -> 0 | AC14: =AB14*$AC$3 -> 0
B15: 334 | C15: NRTC - Admin | H15: 0 | J15: =H15/$I$35 -> 0 | K15: =H15/$I$37 -> 0 | L15: =J15*$L$3 -> 0 | M15: =J15*$M$3 -> 0 | N15: =J15*$N$3 -> 0 | O15: =J15*$O$3 -> 0 | P15: =J15*$P$3 -> 0 | Q15: =K15*$Q$3 -> 0 | R15: =K15*$R$3 -> 0 | S15: =K15*$S$3 -> 0 | T15: =K15*$T$3 -> 0 | U15: =K15*$U$3 -> 0 | V15: =K15*$V$3 -> 0 | W15: =K15*$W$3 -> 0 | X15: =K15*$X$3 -> 0 | Y15: =K15*$Y$3 -> 0 | Z15: =K15*$Z$3 -> 0 | AB15: =H15/$H$39 -> 0 | AC15: =AB15*$AC$3 -> 0
B16: 334H | C16: NRTC - Housing | H16: 1150 | J16: =H16/$I$35 -> 0.010660232 | K16: =H16/$I$37 -> 0.0095170282 | L16: =J16*$L$3 -> 69.621227 | M16: =J16*$M$3 -> 16.283078 | N16: =J16*$N$3 -> 17.041127 | O16: =J16*$O$3 -> 3.3472062 | P16: =J16*$P$3 -> 14.18621 | Q16: =K16*$Q$3 -> 0 | R16: =K16*$R$3 -> 28.608187 | S16: =K16*$S$3 -> 46.633438 | T16: =K16*$T$3 -> 0 | U16: =K16*$U$3 -> 6.0979406 | V16: =K16*$V$3 -> 2.9693128 | W16: =K16*$W$3 -> 10.392595 | X16: =K16*$X$3 -> 22.092258 | Y16: =K16*$Y$3 -> 7.2758632 | Z16: =K16*$Z$3 -> 37.806204 | AB16: =H16/$H$39 -> 0.0054098146 | AC16: =AB16*$AC$3 -> 35.952005
B17: 334F | C17: NRTC FOC | H17: 0 | J17: =H17/$I$35 -> 0 | K17: =H17/$I$37 -> 0 | L17: =J17*$L$3 -> 0 | M17: =J17*$M$3 -> 0 | N17: =J17*$N$3 -> 0 | O17: =J17*$O$3 -> 0 | P17: =J17*$P$3 -> 0 | Q17: =K17*$Q$3 -> 0 | R17: =K17*$R$3 -> 0 | S17: =K17*$S$3 -> 0 | T17: =K17*$T$3 -> 0 | U17: =K17*$U$3 -> 0 | V17: =K17*$V$3 -> 0 | W17: =K17*$W$3 -> 0 | X17: =K17*$X$3 -> 0 | Y17: =K17*$Y$3 -> 0 | Z17: =K17*$Z$3 -> 0 | AB17: =H17/$H$39 -> 0 | AC17: =AB17*$AC$3 -> 0
B18: 335 | C18: NRTC 19 | H18: 3134.45 | J18: =H18/$I$35 -> 0.02905562 | K18: =H18/$I$37 -> 0.025939695 | L18: =J18*$L$3 -> 189.76022 | M18: =J18*$M$3 -> 44.381298 | N18: =J18*$N$3 -> 46.447443 | O18: =J18*$O$3 -> 9.1231742 | P18: =J18*$P$3 -> 38.666057 | Q18: =K18*$Q$3 -> 0 | R18: =K18*$R$3 -> 77.974723 | S18: =K18*$S$3 -> 127.1045 | T18: =K18*$T$3 -> 0 | U18: =K18*$U$3 -> 16.6206 | V18: =K18*$V$3 -> 8.0931848 | W18: =K18*$W$3 -> 28.326147 | X18: =K18*$X$3 -> 60.214851 | Y18: =K18*$Y$3 -> 19.831156 | Z18: =K18*$Z$3 -> 103.04492 | AB18: =H18/$H$39 -> 0.014745038 | AC18: =AB18*$AC$3 -> 97.991098
B19: 368 | C19: Wells Fargo | H19: 3696.94 | J19: =H19/$I$35 -> 0.034269771 | K19: =H19/$I$37 -> 0.03059468 | L19: =J19*$L$3 -> 223.81348 | M19: =J19*$M$3 -> 52.345705 | N19: =J19*$N$3 -> 54.782628 | O19: =J19*$O$3 -> 10.760366 | P19: =J19*$P$3 -> 45.604841 | Q19: =K19*$Q$3 -> 0 | R19: =K19*$R$3 -> 91.967609 | S19: =K19*$S$3 -> 149.91393 | T19: =K19*$T$3 -> 0 | U19: =K19*$U$3 -> 19.603235 | V19: =K19*$V$3 -> 9.5455402 | W19: =K19*$W$3 -> 33.409391 | X19: =K19*$X$3 -> 71.020655 | Y19: =K19*$Y$3 -> 23.389939 | Z19: =K19*$Z$3 -> 121.53676 | AB19: =H19/$H$39 -> 0.017391096 | AC19: =AB19*$AC$3 -> 115.576
B20: 451 | C20: USJP | H20: 14938.24 | J20: =H20/$I$35 -> 0.138474 | K20: =H20/$I$37 -> 0.12362404 | L20: =J20*$L$3 -> 904.364 | M20: =J20*$M$3 -> 211.5135 | N20: =J20*$N$3 -> 221.36038 | O20: =J20*$O$3 -> 43.479451 | P20: =J20*$P$3 -> 184.27566 | Q20: =K20*$Q$3 -> 0 | R20: =K20*$R$3 -> 371.61388 | S20: =K20*$S$3 -> 605.75782 | T20: =K20*$T$3 -> 0 | U20: =K20*$U$3 -> 79.21087 | V20: =K20*$V$3 -> 38.570702 | W20: =K20*$W$3 -> 134.99746 | X20: =K20*$X$3 -> 286.97344 | Y20: =K20*$Y$3 -> 94.511818 | Z20: =K20*$Z$3 -> 491.09404 | AB20: =H20/$H$39 -> 0.070272269 | AC20: =AB20*$AC$3 -> 467.00842
B21: 452 | C21: PACE | H21: 0 | J21: =H21/$I$35 -> 0 | K21: =H21/$I$37 -> 0 | L21: =J21*$L$3 -> 0 | M21: =J21*$M$3 -> 0 | N21: =J21*$N$3 -> 0 | O21: =J21*$O$3 -> 0 | P21: =J21*$P$3 -> 0 | Q21: =K21*$Q$3 -> 0 | R21: =K21*$R$3 -> 0 | S21: =K21*$S$3 -> 0 | T21: =K21*$T$3 -> 0 | U21: =K21*$U$3 -> 0 | V21: =K21*$V$3 -> 0 | W21: =K21*$W$3 -> 0 | X21: =K21*$X$3 -> 0 | Y21: =K21*$Y$3 -> 0 | Z21: =K21*$Z$3 -> 0 | AB21: =H21/$H$39 -> 0 | AC21: =AB21*$AC$3 -> 0
B22: 454 | C22: Prudential #1 Workforce | K22: =H22/$I$37 -> 0 | Q22: =K22*$Q$3 -> 0 | R22: =K22*$R$3 -> 0 | S22: =K22*$S$3 -> 0 | T22: =K22*$T$3 -> 0 | U22: =K22*$U$3 -> 0 | V22: =K22*$V$3 -> 0 | W22: =K22*$W$3 -> 0 | X22: =K22*$X$3 -> 0 | Y22: =K22*$Y$3 -> 0 | Z22: =K22*$Z$3 -> 0
B23: 467 | C23: WF - United Airlines | H23: 9532.71 | J23: =H23/$I$35 -> 0.088365998 | K23: =H23/$I$37 -> 0.078889626 | L23: =J23*$L$3 -> 577.11215 | M23: =J23*$M$3 -> 134.97553 | N23: =J23*$N$3 -> 141.25923 | O23: =J23*$O$3 -> 27.74604 | P23: =J23*$P$3 -> 117.59394 | Q23: =K23*$Q$3 -> 0 | R23: =K23*$R$3 -> 237.14222 | S23: =K23*$S$3 -> 386.55917 | T23: =K23*$T$3 -> 0 | U23: =K23*$U$3 -> 50.547739 | V23: =K23*$V$3 -> 24.613563 | W23: =K23*$W$3 -> 86.147472 | X23: =K23*$X$3 -> 183.12964 | Y23: =K23*$Y$3 -> 60.311908 | Z23: =K23*$Z$3 -> 313.38746 | AB23: =H23/$H$39 -> 0.044843647 | AC23: =AB23*$AC$3 -> 298.01742
B24: 468 | C24: Newark Alliance | H24: 6307.7 | J24: =H24/$I$35 -> 0.058470907 | K24: =H24/$I$37 -> 0.052200486 | L24: =J24*$L$3 -> 381.8694 | M24: =J24*$M$3 -> 89.311972 | N24: =J24*$N$3 -> 93.469839 | O24: =J24*$O$3 -> 18.35928 | P24: =J24*$P$3 -> 77.810745 | Q24: =K24*$Q$3 -> 0 | R24: =K24*$R$3 -> 156.91466 | S24: =K24*$S$3 -> 255.78238 | T24: =K24*$T$3 -> 0 | U24: =K24*$U$3 -> 33.446939 | V24: =K24*$V$3 -> 16.286552 | W24: =K24*$W$3 -> 57.002931 | X24: =K24*$X$3 -> 121.17508 | Y24: =K24*$Y$3 -> 39.907793 | Z24: =K24*$Z$3 -> 207.36539 | AB24: =H24/$H$39 -> 0.029672598 | AC24: =AB24*$AC$3 -> 197.19518
B25: 502 | C25: ESG | H25: 1678.6 | J25: =H25/$I$35 -> 0.01556023 | K25: =H25/$I$37 -> 0.013891551 | L25: =J25*$L$3 -> 101.62278 | M25: =J25*$M$3 -> 23.76763 | N25: =J25*$N$3 -> 24.874118 | O25: =J25*$O$3 -> 4.8857567 | P25: =J25*$P$3 -> 20.706932 | Q25: =K25*$Q$3 -> 0 | R25: =K25*$R$3 -> 41.758002 | S25: =K25*$S$3 -> 68.068599 | T25: =K25*$T$3 -> 0 | U25: =K25*$U$3 -> 8.9008723 | V25: =K25*$V$3 -> 4.3341639 | W25: =K25*$W$3 -> 15.169574 | X25: =K25*$X$3 -> 32.247013 | Y25: =K25*$Y$3 -> 10.62023 | Z25: =K25*$Z$3 -> 55.183908 | AB25: =H25/$H$39 -> 0.0078964477 | AC25: =AB25*$AC$3 -> 52.477422
B26: 515 | C26: FOC - HUD NUL PARS | H26: 1730.77 | J26: =H26/$I$35 -> 0.016043834 | K26: =H26/$I$37 -> 0.014323293 | L26: =J26*$L$3 -> 104.78116 | M26: =J26*$M$3 -> 24.506315 | N26: =J26*$N$3 -> 25.647192 | O26: =J26*$O$3 -> 5.0376035 | P26: =J26*$P$3 -> 21.350493 | Q26: =K26*$Q$3 -> 0 | R26: =K26*$R$3 -> 43.055819 | S26: =K26*$S$3 -> 70.184135 | T26: =K26*$T$3 -> 0 | U26: =K26*$U$3 -> 9.1775067 | V26: =K26*$V$3 -> 4.4688674 | W26: =K26*$W$3 -> 15.641036 | X26: =K26*$X$3 -> 33.249233 | Y26: =K26*$Y$3 -> 10.950301 | Z26: =K26*$Z$3 -> 56.898995 | AB26: =H26/$H$39 -> 0.0081418651 | AC26: =AB26*$AC$3 -> 54.108393
B27: 525 | C27: CDBG - Housing | H27: 2900 | J27: =H27/$I$35 -> 0.026882323 | K27: =H27/$I$37 -> 0.023999462 | L27: =J27*$L$3 -> 175.56657 | M27: =J27*$M$3 -> 41.061674 | N27: =J27*$N$3 -> 42.973276 | O27: =J27*$O$3 -> 8.4407807 | P27: =J27*$P$3 -> 35.773921 | Q27: =K27*$Q$3 -> 0 | R27: =K27*$R$3 -> 72.142384 | S27: =K27*$S$3 -> 117.59737 | T27: =K27*$T$3 -> 0 | U27: =K27*$U$3 -> 15.377416 | V27: =K27*$V$3 -> 7.4878323 | W27: =K27*$W$3 -> 26.207413 | X27: =K27*$X$3 -> 55.710912 | Y27: =K27*$Y$3 -> 18.347829 | Z27: =K27*$Z$3 -> 95.337384 | AB27: =H27/$H$39 -> 0.013642141 | AC27: =AB27*$AC$3 -> 90.661578
B28: 560 | C28: CAP 1 - Save Up | H28: 0 | J28: =H28/$I$35 -> 0 | K28: =H28/$I$37 -> 0 | L28: =J28*$L$3 -> 0 | M28: =J28*$M$3 -> 0 | N28: =J28*$N$3 -> 0 | O28: =J28*$O$3 -> 0 | P28: =J28*$P$3 -> 0 | Q28: =K28*$Q$3 -> 0 | R28: =K28*$R$3 -> 0 | S28: =K28*$S$3 -> 0 | T28: =K28*$T$3 -> 0 | U28: =K28*$U$3 -> 0 | V28: =K28*$V$3 -> 0 | W28: =K28*$W$3 -> 0 | X28: =K28*$X$3 -> 0 | Y28: =K28*$Y$3 -> 0 | Z28: =K28*$Z$3 -> 0 | AB28: =H28/$H$39 -> 0 | AC28: =AB28*$AC$3 -> 0
B29: 561 | C29: LISC FOC 2019 | H29: 4384.62 | J29: =H29/$I$35 -> 0.040644405 | K29: =H29/$I$37 -> 0.036285698 | L29: =J29*$L$3 -> 265.44576 | M29: =J29*$M$3 -> 62.082702 | N29: =J29*$N$3 -> 64.972926 | O29: =J29*$O$3 -> 12.761937 | P29: =J29*$P$3 -> 54.087948 | Q29: =K29*$Q$3 -> 0 | R29: =K29*$R$3 -> 109.07481 | S29: =K29*$S$3 -> 177.79992 | T29: =K29*$T$3 -> 0 | U29: =K29*$U$3 -> 23.249698 | V29: =K29*$V$3 -> 11.321138 | W29: =K29*$W$3 -> 39.623982 | X29: =K29*$X$3 -> 84.231441 | Y29: =K29*$Y$3 -> 27.740779 | Z29: =K29*$Z$3 -> 144.14421 | AB29: =H29/$H$39 -> 0.020626071 | AC29: =AB29*$AC$3 -> 137.07468
B30: 563 | C30: Prudential #1 FOC | H30: 2993.49 | J30: =H30/$I$35 -> 0.027748954 | K30: =H30/$I$37 -> 0.024773155 | L30: =J30*$L$3 -> 181.22648 | M30: =J30*$M$3 -> 42.385417 | N30: =J30*$N$3 -> 44.358645 | O30: =J30*$O$3 -> 8.7128941 | P30: =J30*$P$3 -> 36.927198 | Q30: =K30*$Q$3 -> 0 | R30: =K30*$R$3 -> 74.468105 | S30: =K30*$S$3 -> 121.38846 | T30: =K30*$T$3 -> 0 | U30: =K30*$U$3 -> 15.873152 | V30: =K30*$V$3 -> 7.7292245 | W30: =K30*$W$3 -> 27.052286 | X30: =K30*$X$3 -> 57.506917 | Y30: =K30*$Y$3 -> 18.939325 | Z30: =K30*$Z$3 -> 98.410864 | AB30: =H30/$H$39 -> 0.014081936 | AC30: =AB30*$AC$3 -> 93.58432
B31: 610 | C31: CEO | H31: 11923.08 | J31: =H31/$I$35 -> 0.11052417 | K31: =H31/$I$37 -> 0.098671555 | L31: =J31*$L$3 -> 721.82562 | M31: =J31*$M$3 -> 168.82125 | N31: =J31*$N$3 -> 176.68062 | O31: =J31*$O$3 -> 34.703484 | P31: =J31*$P$3 -> 147.08114 | Q31: =K31*$Q$3 -> 0 | R31: =K31*$R$3 -> 296.6067 | S31: =K31*$S$3 -> 483.49062 | T31: =K31*$T$3 -> 0 | U31: =K31*$U$3 -> 63.222812 | V31: =K31*$V$3 -> 30.785525 | W31: =K31*$W$3 -> 107.74934 | X31: =K31*$X$3 -> 229.05023 | Y31: =K31*$Y$3 -> 75.435391 | Z31: =K31*$Z$3 -> 391.97078 | AB31: =H31/$H$39 -> 0.056088394 | AC31: =AB31*$AC$3 -> 372.74664
B32: 620 | C32: CFO | H32: 6015.39 | J32: =H32/$I$35 -> 0.055761262 | K32: =H32/$I$37 -> 0.049781423 | L32: =J32*$L$3 -> 364.1729 | M32: =J32*$M$3 -> 85.173097 | N32: =J32*$N$3 -> 89.138281 | O32: =J32*$O$3 -> 17.508479 | P32: =J32*$P$3 -> 74.204857 | Q32: =K32*$Q$3 -> 0 | R32: =K32*$R$3 -> 149.64296 | S32: =K32*$S$3 -> 243.92897 | T32: =K32*$T$3 -> 0 | U32: =K32*$U$3 -> 31.896949 | V32: =K32*$V$3 -> 15.531804 | W32: =K32*$W$3 -> 54.361314 | X32: =K32*$X$3 -> 115.55961 | Y32: =K32*$Y$3 -> 38.058396 | Z32: =K32*$Z$3 -> 197.75571 | AB32: =H32/$H$39 -> 0.028297517 | AC32: =AB32*$AC$3 -> 188.05681
B33: 630 | C33: COO | H33: 0 | J33: =H33/$I$35 -> 0 | K33: =H33/$I$37 -> 0 | L33: =J33*$L$3 -> 0 | M33: =J33*$M$3 -> 0 | N33: =J33*$N$3 -> 0 | O33: =J33*$O$3 -> 0 | P33: =J33*$P$3 -> 0 | Q33: =K33*$Q$3 -> 0 | R33: =K33*$R$3 -> 0 | S33: =K33*$S$3 -> 0 | T33: =K33*$T$3 -> 0 | U33: =K33*$U$3 -> 0 | V33: =K33*$V$3 -> 0 | W33: =K33*$W$3 -> 0 | X33: =K33*$X$3 -> 0 | Y33: =K33*$Y$3 -> 0 | Z33: =K33*$Z$3 -> 0 | AB33: =H33/$H$39 -> 0 | AC33: =AB33*$AC$3 -> 0
B34: 650 | C34: Facilities | H34: 299 | J34: =H34/$I$35 -> 0.0027716602 | K34: =H34/$I$37 -> 0.0024744273 | L34: =J34*$L$3 -> 18.101519 | M34: =J34*$M$3 -> 4.2336002 | N34: =J34*$N$3 -> 4.4306929 | O34: =J34*$O$3 -> 0.8702736 | P34: =J34*$P$3 -> 3.6884146 | Q34: =K34*$Q$3 -> 0 | R34: =K34*$R$3 -> 7.4381286 | S34: =K34*$S$3 -> 12.124694 | T34: =K34*$T$3 -> 0 | U34: =K34*$U$3 -> 1.5854646 | V34: =K34*$V$3 -> 0.77202133 | W34: =K34*$W$3 -> 2.7020746 | X34: =K34*$X$3 -> 5.7439871 | Y34: =K34*$Y$3 -> 1.8917244 | Z34: =K34*$Z$3 -> 9.8296131 | AB34: =H34/$H$39 -> 0.0014065518 | AC34: =AB34*$AC$3 -> 9.3475213
B35: 600 | C35: Admin | H35: -0.01 | I35: =SUM(H6:H35) -> 107877.58 | J35: =H35/$I$35 -> -9.2697667e-08 | K35: =H35/$I$37 -> -8.2756767e-08 | L35: =J35*$L$3 -> -0.00060540198 | M35: =J35*$M$3 -> -0.00014159198 | N35: =J35*$N$3 -> -0.00014818371 | O35: =J35*$O$3 -> -2.910614e-05 | P35: =J35*$P$3 -> -0.00012335835 | Q35: =K35*$Q$3 -> 0 | R35: =K35*$R$3 -> -0.00024876684 | S35: =K35*$S$3 -> -0.00040550816 | T35: =K35*$T$3 -> 0 | U35: =K35*$U$3 -> -5.3025571e-05 | V35: =K35*$V$3 -> -2.5820111e-05 | W35: =K35*$W$3 -> -9.0370389e-05 | X35: =K35*$X$3 -> -0.00019210659 | Y35: =K35*$Y$3 -> -6.3268376e-05 | Z35: =K35*$Z$3 -> -0.0003287496 | AB35: =H35/$H$39 -> -4.7041866e-08 | AC35: =AB35*$AC$3 -> -0.00031262613
B36: 339 | C36: Opport Corp | H36: =J53 -> 7420 | K36: =H36/$I$37 -> 0.061405521 | L36: =J36*$L$3 -> 0 | M36: =J36*$M$3 -> 0 | N36: =J36*$N$3 -> 0 | O36: =J36*$O$3 -> 0 | P36: =J36*$P$3 -> 0 | Q36: =K36*$Q$3 -> 0 | R36: =K36*$R$3 -> 184.585 | S36: =K36*$S$3 -> 300.88705 | T36: =K36*$T$3 -> 0 | U36: =K36*$U$3 -> 39.344974 | V36: =K36*$V$3 -> 19.158523 | W36: =K36*$W$3 -> 67.054829 | X36: =K36*$X$3 -> 142.54309 | Y36: =K36*$Y$3 -> 46.945135 | Z36: =K36*$Z$3 -> 243.9322 | AB36: =H36/$H$39 -> 0.034905065 | AC36: =AB36*$AC$3 -> 231.96859
B37: 225 | C37: AmeriCorp | H37: =I53 -> 5538.46 | I37: =I35+H36+H37 -> 120836.04 | K37: =H37/$I$37 -> 0.045834504 | Q37: =K37*$Q$3 -> 0 | R37: =K37*$R$3 -> 137.77852 | S37: =K37*$S$3 -> 224.58907 | T37: =K37*$T$3 -> 0 | U37: =K37*$U$3 -> 29.368 | V37: =K37*$V$3 -> 14.300365 | W37: =K37*$W$3 -> 50.051279 | X37: =K37*$X$3 -> 106.39747 | Y37: =K37*$Y$3 -> 35.040937 | Z37: =K37*$Z$3 -> 182.07665 | AB37: =H37/$H$39 -> 0.026053949 | AC37: =AB37*$AC$3 -> 173.14673
B38: 451 | C38: USJP - Participants | F38: 91740.56 | H38: 91740.56 | AB38: =H38/$H$39 -> 0.43156472 | AC38: =AB38*$AC$3 -> 2868.0496
H39: =SUM(H6:H38) -> 212576.6 | J39: =SUM(J6:J38) -> 1 | K39: =SUM(K6:K38) -> 1 | L39: =SUM(L6:L38) -> 6530.93 | M39: =SUM(M6:M38) -> 1527.46 | N39: =SUM(N6:N38) -> 1598.57 | O39: =SUM(O6:O38) -> 313.99 | P39: =SUM(P6:P38) -> 1330.76 | Q39: =SUM(Q6:Q38) -> 0 | ... AC39: =SUM(AC6:AC38) -> 6645.7
H40: Salary | J40: Hourly | L40: =L3-L39 -> 0 | M40: =M3-M39 -> 0 | N40: =N3-N39 -> 0 | O40: =O3-O39 -> 0 | P40: =P3-P39 -> 0 | Q40: =Q3-Q39 -> 0 | R40: =R3-R39 -> 0 | S40: =S3-S39 -> 0 | ... AC40: =AC3-AC39 -> 0
C41: 43717 | H41: 50893.35 | L41: 3872.3 | M41: 905.65 | N41: 1253.04 | O41: 229.72
C42: 43728 | H42: 58065.96 | J42: 0 | L42: 3698.62 | M42: 865.02 | N42: 1101.14 | O42: 201.86
H43: -1081.74
H44: =K53 -> 12958.46
H45: =SUM(H41:H44) -> 120836.03 | L45: =SUM(L41:L42) -> 7570.92 | M45: =SUM(M41:M42) -> 1770.67 | N45: =SUM(N41:N42) -> 2354.18 | O45: =SUM(O41:O42) -> 431.58 | P45: =SUM(P41:P42) -> 0
H46: =H39-H45 -> 91740.57 | AG46: 114.44
I47: Opp Corp | J47: Americ | AG47: 151.65
F48: =I35-H44 -> 94919.12
I49: 2769.23 | J49: 3168.96
I50: 2769.23 | J50: 3168.96
J51: 0.34
J52: 1081.74
I53: =SUM(I49:I52) -> 5538.46 | J53: =SUM(J49:J52) -> 7420 | K53: =SUM(I53:J53) -> 12958.46
J55: =J53+'May 2019 Alloc '!I60+'April 2019 Alloc '!H44+'April 2019 Alloc '!H45 -> 30659.03

Sheet August 2019 Alloc  (2)
B1: August Cost Allocations | L1: 7251 | M1: 7252 | N1: 7253 | O1: 7254 | P1: 7260.1 | Q1: 8140 | R1: 7515.5 | S1: 7521 | T1: 8112 | U1: 8135.5 | V1: 8191 | W1: 8210.5 | X1: 8229.1 | Y1: 8239 | Z1: 8266 | AC1: 7248
L2: FICA | M2: MEDI | N2: SUI | O2: Disability | P2: Payroll Fees | Q2: Postage | R2: IT Consultants | S2: Acctg Fees | T2: Supplies | U2: Telephone | V2: Web Hosting | W2: Utilities | X2: Eq Lease | Y2: Repairs | Z2: General Insurance | AC2: W/ Comp
L3: 7432.33 | M3: 1738.27 | N3: 1878 | O3: 399.73 | P3: 1535.69 | Q3: 300.57 | R3: 3006 | S3: 3920 | T3: 676.56 | U3: 879.99 | V3: 312 | W3: 1393.15 | X3: 2321.34 | Y3: 764.51 | Z3: 3972.48 | AC3: 6645.7
L4: 1 | M4: 2 | N4: 3 | O4: 4 | P4: 5 | Q4: 6 | R4: 7 | S4: 8 | T4: 9 | U4: 10 | V4: 11 | W4: 12 | X4: 13 | Y4: 14 | Z4: 15 | AC4: 0.04
D5: 7222 | E5: Taxes | F5: W/C | J5: Taxes | K5: Expenses
B6: 41 | C6: Thriftworks | H6: 0 | J6: =H6/$I$35 -> 0 | K6: =H6/$I$37 -> 0 | L6: =J6*$L$3 -> 0 | M6: =J6*$M$3 -> 0 | N6: =J6*$N$3 -> 0 | O6: =J6*$O$3 -> 0 | P6: =J6*$P$3 -> 0 | Q6: =K6*$Q$3 -> 0 | R6: =K6*$R$3 -> 0 | S6: =K6*$S$3 -> 0 | T6: =K6*$T$3 -> 0 | U6: =K6*$U$3 -> 0 | V6: =K6*$V$3 -> 0 | W6: =K6*$W$3 -> 0 | X6: =K6*$X$3 -> 0 | Y6: =K6*$Y$3 -> 0 | Z6: =K6*$Z$3 -> 0 | AB6: =H6/$H$39 -> 0 | AC6: =AB6*$AC$3 -> 0
B7: 111 | C7: Abbott | H7: 9175.98 | J7: =H7/$I$35 -> 0.074231873 | K7: =H7/$I$37 -> 0.067725018 | L7: =J7*$L$3 -> 551.71578 | M7: =J7*$M$3 -> 129.03504 | N7: =J7*$N$3 -> 139.40746 | O7: =J7*$O$3 -> 29.672707 | P7: =J7*$P$3 -> 113.99715 | Q7: =K7*$Q$3 -> 20.356109 | R7: =K7*$R$3 -> 203.5814 | S7: =K7*$S$3 -> 265.48207 | T7: =K7*$T$3 -> 45.820038 | U7: =K7*$U$3 -> 59.597338 | V7: =K7*$V$3 -> 21.130205 | W7: =K7*$W$3 -> 94.351108 | X7: =K7*$X$3 -> 157.21279 | Y7: =K7*$Y$3 -> 51.776453 | Z7: =K7*$Z$3 -> 269.03628 | AB7: =H7/$H$39 -> 0.039796458 | AC7: =AB7*$AC$3 -> 264.47532
B8: 111A | C8: Abbott - Other | H8: 2314.82 | J8: =H8/$I$35 -> 0.018726438 | K8: =H8/$I$37 -> 0.017084957 | L8: =J8*$L$3 -> 139.18107 | M8: =J8*$M$3 -> 32.551606 | N8: =J8*$N$3 -> 35.168251 | O8: =J8*$O$3 -> 7.4855192 | P8: =J8*$P$3 -> 28.758004 | Q8: =K8*$Q$3 -> 5.1352256 | R8: =K8*$R$3 -> 51.357381 | S8: =K8*$S$3 -> 66.973032 | T8: =K8*$T$3 -> 11.558999 | U8: =K8*$U$3 -> 15.034591 | V8: =K8*$V$3 -> 5.3305066 | W8: =K8*$W$3 -> 23.801908 | X8: =K8*$X$3 -> 39.659994 | Y8: =K8*$Y$3 -> 13.061621 | Z8: =K8*$Z$3 -> 67.869651 | AB8: =H8/$H$39 -> 0.010039433 | AC8: =AB8*$AC$3 -> 66.719061
B9: 111B | C9: Abbott Fees | H9: 0 | J9: =H9/$I$35 -> 0 | K9: =H9/$I$37 -> 0 | L9: =J9*$L$3 -> 0 | M9: =J9*$M$3 -> 0 | N9: =J9*$N$3 -> 0 | O9: =J9*$O$3 -> 0 | P9: =J9*$P$3 -> 0 | Q9: =K9*$Q$3 -> 0 | R9: =K9*$R$3 -> 0 | S9: =K9*$S$3 -> 0 | T9: =K9*$T$3 -> 0 | U9: =K9*$U$3 -> 0 | V9: =K9*$V$3 -> 0 | W9: =K9*$W$3 -> 0 | X9: =K9*$X$3 -> 0 | Y9: =K9*$Y$3 -> 0 | Z9: =K9*$Z$3 -> 0 | AB9: =H9/$H$39 -> 0 | AC9: =AB9*$AC$3 -> 0
B10: 111F | C10: Abbott Food | H10: 0 | J10: =H10/$I$35 -> 0 | K10: =H10/$I$37 -> 0 | L10: =J10*$L$3 -> 0 | M10: =J10*$M$3 -> 0 | N10: =J10*$N$3 -> 0 | O10: =J10*$O$3 -> 0 | P10: =J10*$P$3 -> 0 | Q10: =K10*$Q$3 -> 0 | R10: =K10*$R$3 -> 0 | S10: =K10*$S$3 -> 0 | T10: =K10*$T$3 -> 0 | U10: =K10*$U$3 -> 0 | V10: =K10*$V$3 -> 0 | W10: =K10*$W$3 -> 0 | X10: =K10*$X$3 -> 0 | Y10: =K10*$Y$3 -> 0 | Z10: =K10*$Z$3 -> 0 | AB10: =H10/$H$39 -> 0 | AC10: =AB10*$AC$3 -> 0
B11: 112 | C11: EHS | H11: 25477.99 | J11: =H11/$I$35 -> 0.20611193 | K11: =H11/$I$37 -> 0.18804502 | L11: =J11*$L$3 -> 1531.8919 | M11: =J11*$M$3 -> 358.27818 | N11: =J11*$N$3 -> 387.0782 | O11: =J11*$O$3 -> 82.389121 | P11: =J11*$P$3 -> 316.52403 | Q11: =K11*$Q$3 -> 56.520691 | R11: =K11*$R$3 -> 565.26332 | S11: =K11*$S$3 -> 737.13647 | T11: =K11*$T$3 -> 127.22374 | U11: =K11*$U$3 -> 165.47773 | V11: =K11*$V$3 -> 58.670045 | W11: =K11*$W$3 -> 261.97492 | X11: =K11*$X$3 -> 436.51642 | Y11: =K11*$Y$3 -> 143.7623 | Z11: =K11*$Z$3 -> 747.00507 | AB11: =H11/$H$39 -> 0.11049869 | AC11: =AB11*$AC$3 -> 734.34114
B12: 114 | C12: Summer Camp | H12: 10446.9 | J12: =H12/$I$35 -> 0.084513366 | K12: =H12/$I$37 -> 0.077105278 | L12: =J12*$L$3 -> 628.13123 | M12: =J12*$M$3 -> 146.90705 | N12: =J12*$N$3 -> 158.7161 | O12: =J12*$O$3 -> 33.782528 | P12: =J12*$P$3 -> 129.78633 | Q12: =K12*$Q$3 -> 23.175533 | R12: =K12*$R$3 -> 231.77846 | S12: =K12*$S$3 -> 302.25269 | T12: =K12*$T$3 -> 52.166347 | U12: =K12*$U$3 -> 67.851873 | V12: =K12*$V$3 -> 24.056847 | W12: =K12*$W$3 -> 107.41922 | X12: =K12*$X$3 -> 178.98757 | Y12: =K12*$Y$3 -> 58.947756 | Z12: =K12*$Z$3 -> 306.29917 | AB12: =H12/$H$39 -> 0.04530847 | AC12: =AB12*$AC$3 -> 301.1065
B13: 222 | C13: DCF- Coding | H13: 2480.65 | J13: =H13/$I$35 -> 0.020067971 | K13: =H13/$I$37 -> 0.018308896 | L13: =J13*$L$3 -> 149.15178 | M13: =J13*$M$3 -> 34.883551 | N13: =J13*$N$3 -> 37.687649 | O13: =J13*$O$3 -> 8.0217699 | P13: =J13*$P$3 -> 30.818182 | Q13: =K13*$Q$3 -> 5.5031049 | R13: =K13*$R$3 -> 55.036542 | S13: =K13*$S$3 -> 71.770873 | T13: =K13*$T$3 -> 12.387067 | U13: =K13*$U$3 -> 16.111646 | V13: =K13*$V$3 -> 5.7123756 | W13: =K13*$W$3 -> 25.507039 | X13: =K13*$X$3 -> 42.501173 | Y13: =K13*$Y$3 -> 13.997334 | Z13: =K13*$Z$3 -> 72.731724 | AB13: =H13/$H$39 -> 0.010758642 | AC13: =AB13*$AC$3 -> 71.498707
B14: 223 | C14: OICA | H14: 0 | J14: =H14/$I$35 -> 0 | K14: =H14/$I$37 -> 0 | L14: =J14*$L$3 -> 0 | M14: =J14*$M$3 -> 0 | N14: =J14*$N$3 -> 0 | O14: =J14*$O$3 -> 0 | P14: =J14*$P$3 -> 0 | Q14: =K14*$Q$3 -> 0 | R14: =K14*$R$3 -> 0 | S14: =K14*$S$3 -> 0 | T14: =K14*$T$3 -> 0 | U14: =K14*$U$3 -> 0 | V14: =K14*$V$3 -> 0 | W14: =K14*$W$3 -> 0 | X14: =K14*$X$3 -> 0 | Y14: =K14*$Y$3 -> 0 | Z14: =K14*$Z$3 -> 0 | AB14: =H14/$H$39 -> 0 | AC14: =AB14*$AC$3 -> 0
B15: 334 | C15: NRTC - Admin | H15: 0 | J15: =H15/$I$35 -> 0 | K15: =H15/$I$37 -> 0 | L15: =J15*$L$3 -> 0 | M15: =J15*$M$3 -> 0 | N15: =J15*$N$3 -> 0 | O15: =J15*$O$3 -> 0 | P15: =J15*$P$3 -> 0 | Q15: =K15*$Q$3 -> 0 | R15: =K15*$R$3 -> 0 | S15: =K15*$S$3 -> 0 | T15: =K15*$T$3 -> 0 | U15: =K15*$U$3 -> 0 | V15: =K15*$V$3 -> 0 | W15: =K15*$W$3 -> 0 | X15: =K15*$X$3 -> 0 | Y15: =K15*$Y$3 -> 0 | Z15: =K15*$Z$3 -> 0 | AB15: =H15/$H$39 -> 0 | AC15: =AB15*$AC$3 -> 0
B16: 334H | C16: NRTC - Housing | H16: 1150 | J16: =H16/$I$35 -> 0.0093032738 | K16: =H16/$I$37 -> 0.0084877877 | L16: =J16*$L$3 -> 69.145001 | M16: =J16*$M$3 -> 16.171602 | N16: =J16*$N$3 -> 17.471548 | O16: =J16*$O$3 -> 3.7187976 | P16: =J16*$P$3 -> 14.286945 | Q16: =K16*$Q$3 -> 2.5511743 | R16: =K16*$R$3 -> 25.51429 | S16: =K16*$S$3 -> 33.272128 | T16: =K16*$T$3 -> 5.7424976 | U16: =K16*$U$3 -> 7.4691683 | V16: =K16*$V$3 -> 2.6481898 | W16: =K16*$W$3 -> 11.824761 | X16: =K16*$X$3 -> 19.703041 | Y16: =K16*$Y$3 -> 6.4889986 | Z16: =K16*$Z$3 -> 33.717567 | AB16: =H16/$H$39 -> 0.0049875792 | AC16: =AB16*$AC$3 -> 33.145955
B17: 334F | C17: NRTC FOC | H17: 0 | J17: =H17/$I$35 -> 0 | K17: =H17/$I$37 -> 0 | L17: =J17*$L$3 -> 0 | M17: =J17*$M$3 -> 0 | N17: =J17*$N$3 -> 0 | O17: =J17*$O$3 -> 0 | P17: =J17*$P$3 -> 0 | Q17: =K17*$Q$3 -> 0 | R17: =K17*$R$3 -> 0 | S17: =K17*$S$3 -> 0 | T17: =K17*$T$3 -> 0 | U17: =K17*$U$3 -> 0 | V17: =K17*$V$3 -> 0 | W17: =K17*$W$3 -> 0 | X17: =K17*$X$3 -> 0 | Y17: =K17*$Y$3 -> 0 | Z17: =K17*$Z$3 -> 0 | AB17: =H17/$H$39 -> 0 | AC17: =AB17*$AC$3 -> 0
B18: 335 | C18: NRTC 19 | H18: 846.15 | J18: =H18/$I$35 -> 0.0068451871 | K18: =H18/$I$37 -> 0.0062451666 | L18: =J18*$L$3 -> 50.875689 | M18: =J18*$M$3 -> 11.898783 | N18: =J18*$N$3 -> 12.855261 | O18: =J18*$O$3 -> 2.7362266 | P18: =J18*$P$3 -> 10.512085 | Q18: =K18*$Q$3 -> 1.8771097 | R18: =K18*$R$3 -> 18.772971 | S18: =K18*$S$3 -> 24.481053 | T18: =K18*$T$3 -> 4.2252299 | U18: =K18*$U$3 -> 5.4956841 | V18: =K18*$V$3 -> 1.948492 | W18: =K18*$W$3 -> 8.7004538 | X18: =K18*$X$3 -> 14.497155 | Y18: =K18*$Y$3 -> 4.7744923 | Z18: =K18*$Z$3 -> 24.808799 | AB18: =H18/$H$39 -> 0.003669774 | AC18: =AB18*$AC$3 -> 24.388217
B19: 368 | C19: Wells Fargo | H19: 4903.5 | J19: =H19/$I$35 -> 0.03966835 | K19: =H19/$I$37 -> 0.036191189 | L19: =J19*$L$3 -> 294.82827 | M19: =J19*$M$3 -> 68.954303 | N19: =J19*$N$3 -> 74.497162 | O19: =J19*$O$3 -> 15.85663 | P19: =J19*$P$3 -> 60.918289 | Q19: =K19*$Q$3 -> 10.877986 | R19: =K19*$R$3 -> 108.79071 | S19: =K19*$S$3 -> 141.86946 | T19: =K19*$T$3 -> 24.485511 | U19: =K19*$U$3 -> 31.847884 | V19: =K19*$V$3 -> 11.291651 | W19: =K19*$W$3 -> 50.419754 | X19: =K19*$X$3 -> 84.012054 | Y19: =K19*$Y$3 -> 27.668526 | Z19: =K19*$Z$3 -> 143.76877 | AB19: =H19/$H$39 -> 0.021266604 | AC19: =AB19*$AC$3 -> 141.33147
B20: 451 | C20: USJP | H20: 17145.76 | J20: =H20/$I$35 -> 0.13870583 | K20: =H20/$I$37 -> 0.12654745 | L20: =J20*$L$3 -> 1030.9075 | M20: =J20*$M$3 -> 241.10818 | N20: =J20*$N$3 -> 260.48954 | O20: =J20*$O$3 -> 55.44488 | P20: =J20*$P$3 -> 213.00915 | Q20: =K20*$Q$3 -> 38.036368 | R20: =K20*$R$3 -> 380.40164 | S20: =K20*$S$3 -> 496.06602 | T20: =K20*$T$3 -> 85.616945 | U20: =K20*$U$3 -> 111.36049 | V20: =K20*$V$3 -> 39.482805 | W20: =K20*$W$3 -> 176.29958 | X20: =K20*$X$3 -> 293.75966 | Y20: =K20*$Y$3 -> 96.746793 | Z20: =K20*$Z$3 -> 502.70723 | AB20: =H20/$H$39 -> 0.074361596 | AC20: =AB20*$AC$3 -> 494.18486
B21: 452 | C21: PACE | H21: 2250 | J21: =H21/$I$35 -> 0.018202057 | K21: =H21/$I$37 -> 0.016606541 | L21: =J21*$L$3 -> 135.2837 | M21: =J21*$M$3 -> 31.64009 | N21: =J21*$N$3 -> 34.183464 | O21: =J21*$O$3 -> 7.2759084 | P21: =J21*$P$3 -> 27.952718 | Q21: =K21*$Q$3 -> 4.9914281 | R21: =K21*$R$3 -> 49.919263 | S21: =K21*$S$3 -> 65.097641 | T21: =K21*$T$3 -> 11.235321 | U21: =K21*$U$3 -> 14.61359 | V21: =K21*$V$3 -> 5.1812408 | W21: =K21*$W$3 -> 23.135403 | X21: =K21*$X$3 -> 38.549428 | Y21: =K21*$Y$3 -> 12.695867 | Z21: =K21*$Z$3 -> 65.969153 | AB21: =H21/$H$39 -> 0.0097583071 | AC21: =AB21*$AC$3 -> 64.850782
B22: 454 | C22: Prudential #1 Workforce | K22: =H22/$I$37 -> 0 | Q22: =K22*$Q$3 -> 0 | R22: =K22*$R$3 -> 0 | S22: =K22*$S$3 -> 0 | T22: =K22*$T$3 -> 0 | U22: =K22*$U$3 -> 0 | V22: =K22*$V$3 -> 0 | W22: =K22*$W$3 -> 0 | X22: =K22*$X$3 -> 0 | Y22: =K22*$Y$3 -> 0 | Z22: =K22*$Z$3 -> 0
B23: 467 | C23: WF - United Airlines | H23: 8847.87 | J23: =H23/$I$35 -> 0.071577528 | K23: =H23/$I$37 -> 0.065303341 | L23: =J23*$L$3 -> 531.98781 | M23: =J23*$M$3 -> 124.42107 | N23: =J23*$N$3 -> 134.4226 | O23: =J23*$O$3 -> 28.611685 | P23: =J23*$P$3 -> 109.92089 | Q23: =K23*$Q$3 -> 19.628225 | R23: =K23*$R$3 -> 196.30184 | S23: =K23*$S$3 -> 255.9891 | T23: =K23*$T$3 -> 44.181628 | U23: =K23*$U$3 -> 57.466287 | V23: =K23*$V$3 -> 20.374642 | W23: =K23*$W$3 -> 90.977349 | X23: =K23*$X$3 -> 151.59126 | Y23: =K23*$Y$3 -> 49.925057 | Z23: =K23*$Z$3 -> 259.41622 | AB23: =H23/$H$39 -> 0.038373437 | AC23: =AB23*$AC$3 -> 255.01835
B24: 468 | C24: Newark Alliance | H24: 6307.7 | J24: =H24/$I$35 -> 0.051028052 | K24: =H24/$I$37 -> 0.046555146 | L24: =J24*$L$3 -> 379.25732 | M24: =J24*$M$3 -> 88.700532 | N24: =J24*$N$3 -> 95.830682 | O24: =J24*$O$3 -> 20.397443 | P24: =J24*$P$3 -> 78.363269 | Q24: =K24*$Q$3 -> 13.99308 | R24: =K24*$R$3 -> 139.94477 | S24: =K24*$S$3 -> 182.49617 | T24: =K24*$T$3 -> 31.49735 | U24: =K24*$U$3 -> 40.968063 | V24: =K24*$V$3 -> 14.525206 | W24: =K24*$W$3 -> 64.858302 | X24: =K24*$X$3 -> 108.07032 | Y24: =K24*$Y$3 -> 35.591875 | Z24: =K24*$Z$3 -> 184.93939 | AB24: =H24/$H$39 -> 0.027356655 | AC24: =AB24*$AC$3 -> 181.80412
B25: 502 | C25: ESG | H25: 1748.25 | J25: =H25/$I$35 -> 0.014142999 | K25: =H25/$I$37 -> 0.012903282 | L25: =J25*$L$3 -> 105.11543 | M25: =J25*$M$3 -> 24.58435 | N25: =J25*$N$3 -> 26.560551 | O25: =J25*$O$3 -> 5.6533808 | P25: =J25*$P$3 -> 21.719262 | Q25: =K25*$Q$3 -> 3.8783396 | R25: =K25*$R$3 -> 38.787267 | S25: =K25*$S$3 -> 50.580867 | T25: =K25*$T$3 -> 8.7298448 | U25: =K25*$U$3 -> 11.35476 | V25: =K25*$V$3 -> 4.0258241 | W25: =K25*$W$3 -> 17.976208 | X25: =K25*$X$3 -> 29.952906 | Y25: =K25*$Y$3 -> 9.8646885 | Z25: =K25*$Z$3 -> 51.258032 | AB25: =H25/$H$39 -> 0.0075822046 | AC25: =AB25*$AC$3 -> 50.389057
B26: 515 | C26: FOC - HUD NUL PARS | H26: 1730.77 | J26: =H26/$I$35 -> 0.014001589 | K26: =H26/$I$37 -> 0.012774268 | L26: =J26*$L$3 -> 104.06443 | M26: =J26*$M$3 -> 24.338542 | N26: =J26*$N$3 -> 26.294984 | O26: =J26*$O$3 -> 5.5968551 | P26: =J26*$P$3 -> 21.5021 | Q26: =K26*$Q$3 -> 3.8395618 | R26: =K26*$R$3 -> 38.39945 | S26: =K26*$S$3 -> 50.075131 | T26: =K26*$T$3 -> 8.6425588 | U26: =K26*$U$3 -> 11.241228 | V26: =K26*$V$3 -> 3.9855716 | W26: =K26*$W$3 -> 17.796472 | X26: =K26*$X$3 -> 29.65342 | Y26: =K26*$Y$3 -> 9.7660557 | Z26: =K26*$Z$3 -> 50.745525 | AB26: =H26/$H$39 -> 0.0075063934 | AC26: =AB26*$AC$3 -> 49.885239
B27: 525 | C27: CDBG - Housing | H27: 2900 | J27: =H27/$I$35 -> 0.02346043 | K27: =H27/$I$37 -> 0.021403986 | L27: =J27*$L$3 -> 174.36565 | M27: =J27*$M$3 -> 40.780561 | N27: =J27*$N$3 -> 44.058687 | O27: =J27*$O$3 -> 9.3778375 | P27: =J27*$P$3 -> 36.027947 | Q27: =K27*$Q$3 -> 6.4333962 | R27: =K27*$R$3 -> 64.340383 | S27: =K27*$S$3 -> 83.903627 | T27: =K27*$T$3 -> 14.481081 | U27: =K27*$U$3 -> 18.835294 | V27: =K27*$V$3 -> 6.6780437 | W27: =K27*$W$3 -> 29.818964 | X27: =K27*$X$3 -> 49.68593 | Y27: =K27*$Y$3 -> 16.363562 | Z27: =K27*$Z$3 -> 85.026908 | AB27: =H27/$H$39 -> 0.012577374 | AC27: =AB27*$AC$3 -> 83.585452
B28: 560 | C28: CAP 1 - Save Up | H28: 0 | J28: =H28/$I$35 -> 0 | K28: =H28/$I$37 -> 0 | L28: =J28*$L$3 -> 0 | M28: =J28*$M$3 -> 0 | N28: =J28*$N$3 -> 0 | O28: =J28*$O$3 -> 0 | P28: =J28*$P$3 -> 0 | Q28: =K28*$Q$3 -> 0 | R28: =K28*$R$3 -> 0 | S28: =K28*$S$3 -> 0 | T28: =K28*$T$3 -> 0 | U28: =K28*$U$3 -> 0 | V28: =K28*$V$3 -> 0 | W28: =K28*$W$3 -> 0 | X28: =K28*$X$3 -> 0 | Y28: =K28*$Y$3 -> 0 | Z28: =K28*$Z$3 -> 0 | AB28: =H28/$H$39 -> 0 | AC28: =AB28*$AC$3 -> 0
B29: 561 | C29: LISC FOC 2019 | H29: 4384.62 | J29: =H29/$I$35 -> 0.035470713 | K29: =H29/$I$37 -> 0.032361499 | L29: =J29*$L$3 -> 263.63005 | M29: =J29*$M$3 -> 61.657677 | N29: =J29*$N$3 -> 66.614 | O29: =J29*$O$3 -> 14.178708 | P29: =J29*$P$3 -> 54.47202 | Q29: =K29*$Q$3 -> 9.7268957 | R29: =K29*$R$3 -> 97.278666 | S29: =K29*$S$3 -> 126.85708 | T29: =K29*$T$3 -> 21.894496 | U29: =K29*$U$3 -> 28.477795 | V29: =K29*$V$3 -> 10.096788 | W29: =K29*$W$3 -> 45.084422 | X29: =K29*$X$3 -> 75.122042 | Y29: =K29*$Y$3 -> 24.740689 | Z29: =K29*$Z$3 -> 128.55541 | AB29: =H29/$H$39 -> 0.019016208 | AC29: =AB29*$AC$3 -> 126.37602
B30: 563 | C30: Prudential #1 FOC | H30: 3202.43 | J30: =H30/$I$35 -> 0.025907029 | K30: =H30/$I$37 -> 0.023636127 | L30: =J30*$L$3 -> 192.54959 | M30: =J30*$M$3 -> 45.033411 | N30: =J30*$N$3 -> 48.6534 | O30: =J30*$O$3 -> 10.355817 | P30: =J30*$P$3 -> 39.785165 | Q30: =K30*$Q$3 -> 7.1043107 | R30: =K30*$R$3 -> 71.050198 | S30: =K30*$S$3 -> 92.653618 | T30: =K30*$T$3 -> 15.991258 | U30: =K30*$U$3 -> 20.799555 | V30: =K30*$V$3 -> 7.3744716 | W30: =K30*$W$3 -> 32.92867 | X30: =K30*$X$3 -> 54.867487 | Y30: =K30*$Y$3 -> 18.070055 | Z30: =K30*$Z$3 -> 93.894041 | AB30: =H30/$H$39 -> 0.01388902 | AC30: =AB30*$AC$3 -> 92.302262
B31: 610 | C31: CEO | H31: 11923.08 | J31: =H31/$I$35 -> 0.096455372 | K31: =H31/$I$37 -> 0.088000497 | L31: =J31*$L$3 -> 716.88815 | M31: =J31*$M$3 -> 167.66548 | N31: =J31*$N$3 -> 181.14319 | O31: =J31*$O$3 -> 38.556106 | P31: =J31*$P$3 -> 148.12555 | Q31: =K31*$Q$3 -> 26.450309 | R31: =K31*$R$3 -> 264.52949 | S31: =K31*$S$3 -> 344.96195 | T31: =K31*$T$3 -> 59.537616 | U31: =K31*$U$3 -> 77.439557 | V31: =K31*$V$3 -> 27.456155 | W31: =K31*$W$3 -> 122.59789 | X31: =K31*$X$3 -> 204.27907 | Y31: =K31*$Y$3 -> 67.27726 | Z31: =K31*$Z$3 -> 349.58021 | AB31: =H31/$H$39 -> 0.051710701 | AC31: =AB31*$AC$3 -> 343.6538
B32: 620 | C32: CFO | H32: 6076.92 | J32: =H32/$I$35 -> 0.049161087 | K32: =H32/$I$37 -> 0.044851832 | L32: =J32*$L$3 -> 365.38142 | M32: =J32*$M$3 -> 85.455243 | N32: =J32*$N$3 -> 92.324522 | O32: =J32*$O$3 -> 19.651161 | P32: =J32*$P$3 -> 75.49619 | Q32: =K32*$Q$3 -> 13.481115 | R32: =K32*$R$3 -> 134.82461 | S32: =K32*$S$3 -> 175.81918 | T32: =K32*$T$3 -> 30.344955 | U32: =K32*$U$3 -> 39.469164 | V32: =K32*$V$3 -> 13.993772 | W32: =K32*$W$3 -> 62.48533 | X32: =K32*$X$3 -> 104.11635 | Y32: =K32*$Y$3 -> 34.289674 | Z32: =K32*$Z$3 -> 178.17301 | AB32: =H32/$H$39 -> 0.026355756 | AC32: =AB32*$AC$3 -> 175.15245
B33: 630 | C33: COO | H33: 0 | J33: =H33/$I$35 -> 0 | K33: =H33/$I$37 -> 0 | L33: =J33*$L$3 -> 0 | M33: =J33*$M$3 -> 0 | N33: =J33*$N$3 -> 0 | O33: =J33*$O$3 -> 0 | P33: =J33*$P$3 -> 0 | Q33: =K33*$Q$3 -> 0 | R33: =K33*$R$3 -> 0 | S33: =K33*$S$3 -> 0 | T33: =K33*$T$3 -> 0 | U33: =K33*$U$3 -> 0 | V33: =K33*$V$3 -> 0 | W33: =K33*$W$3 -> 0 | X33: =K33*$X$3 -> 0 | Y33: =K33*$Y$3 -> 0 | Z33: =K33*$Z$3 -> 0 | AB33: =H33/$H$39 -> 0 | AC33: =AB33*$AC$3 -> 0
B34: 650 | C34: Facilities | H34: 299 | J34: =H34/$I$35 -> 0.0024188512 | K34: =H34/$I$37 -> 0.0022068248 | L34: =J34*$L$3 -> 17.9777 | M34: =J34*$M$3 -> 4.2046164 | N34: =J34*$N$3 -> 4.5426025 | O34: =J34*$O$3 -> 0.96688738 | P34: =J34*$P$3 -> 3.7146056 | Q34: =K34*$Q$3 -> 0.66330533 | R34: =K34*$R$3 -> 6.6337154 | S34: =K34*$S$3 -> 8.6507532 | T34: =K34*$T$3 -> 1.4930494 | U34: =K34*$U$3 -> 1.9419838 | V34: =K34*$V$3 -> 0.68852934 | W34: =K34*$W$3 -> 3.074438 | X34: =K34*$X$3 -> 5.1227907 | Y34: =K34*$Y$3 -> 1.6871396 | Z34: =K34*$Z$3 -> 8.7665674 | AB34: =H34/$H$39 -> 0.0012967706 | AC34: =AB34*$AC$3 -> 8.6179483
B35: 600 | C35: Admin | H35: 0.01 | I35: =SUM(H6:H35) -> 123612.4 | J35: =H35/$I$35 -> 8.0898033e-08 | K35: =H35/$I$37 -> 7.380685e-08 | L35: =J35*$L$3 -> 0.00060126088 | M35: =J35*$M$3 -> 0.00014062262 | N35: =J35*$N$3 -> 0.00015192651 | O35: =J35*$O$3 -> 3.2337371e-05 | P35: =J35*$P$3 -> 0.0001242343 | Q35: =K35*$Q$3 -> 2.2184125e-05 | R35: =K35*$R$3 -> 0.00022186339 | S35: =K35*$S$3 -> 0.00028932285 | T35: =K35*$T$3 -> 4.9934762e-05 | U35: =K35*$U$3 -> 6.494929e-05 | V35: =K35*$V$3 -> 2.3027737e-05 | W35: =K35*$W$3 -> 0.00010282401 | X35: =K35*$X$3 -> 0.00017133079 | Y35: =K35*$Y$3 -> 5.6426075e-05 | Z35: =K35*$Z$3 -> 0.00029319623 | AB35: =H35/$H$39 -> 4.3370254e-08 | AC35: =AB35*$AC$3 -> 0.0002882257
B36: 339 | C36: Opport Corp | H36: 5538.46 | K36: =H36/$I$37 -> 0.040877628 | L36: =J36*$L$3 -> 0 | M36: =J36*$M$3 -> 0 | N36: =J36*$N$3 -> 0 | O36: =J36*$O$3 -> 0 | P36: =J36*$P$3 -> 0 | Q36: =K36*$Q$3 -> 12.286589 | R36: =K36*$R$3 -> 122.87815 | S36: =K36*$S$3 -> 160.2403 | T36: =K36*$T$3 -> 27.656168 | U36: =K36*$U$3 -> 35.971904 | V36: =K36*$V$3 -> 12.75382 | W36: =K36*$W$3 -> 56.948668 | X36: =K36*$X$3 -> 94.890874 | Y36: =K36*$Y$3 -> 31.251356 | Z36: =K36*$Z$3 -> 162.38556 | AB36: =U42/$H$39 -> 0.024020442 | AC36: =AB36*$AC$3 -> 159.63265
B37: 225 | C37: AmeriCorp | H37: 6337.92 | I37: =I35+H36+H37 -> 135488.78 | K37: =H37/$I$37 -> 0.046778191 | Q37: =K37*$Q$3 -> 14.060121 | R37: =K37*$R$3 -> 140.61524 | S37: =K37*$S$3 -> 183.37051 | T37: =K37*$T$3 -> 31.648253 | U37: =K37*$U$3 -> 41.16434 | V37: =K37*$V$3 -> 14.594796 | W37: =K37*$W$3 -> 65.169036 | X37: =K37*$X$3 -> 108.58809 | Y37: =K37*$Y$3 -> 35.762395 | Z37: =K37*$Z$3 -> 185.82543 | AB37: =U43/$H$39 -> 0.02748772 | AC37: =AB37*$AC$3 -> 182.67514
B38: 451 | C38: USJP - Participants | F38: 95614.3 | H38: 95084 | AB38: =H38/$H$39 -> 0.41238172 | AC38: =AB38*$AC$3 -> 2740.5652
H39: =SUM(H6:H38) -> 230572.78 | J39: =SUM(J6:J38) -> 1 | K39: =SUM(K6:K38) -> 1 | L39: =SUM(L6:L38) -> 7432.33 | M39: =SUM(M6:M38) -> 1738.27 | N39: =SUM(N6:N38) -> 1878 | O39: =SUM(O6:O38) -> 399.73 | P39: =SUM(P6:P38) -> 1535.69 | Q39: =SUM(Q6:Q38) -> 300.57 | ... AC39: =SUM(AC6:AC38) -> 6645.7
H40: Salary | J40: Hourly | L40: =L3-L39 -> 0 | M40: =M3-M39 -> 0 | N40: =N3-N39 -> 0 | O40: =O3-O39 -> 0 | P40: =P3-P39 -> 0 | Q40: =Q3-Q39 -> 0 | R40: =R3-R39 -> 0 | S40: =S3-S39 -> 0 | ... AC40: =AC3-AC39 -> 0
C41: 43686 | H41: 62468.63 | L41: 3872.3 | M41: 905.65 | N41: 1253.04 | O41: 229.72
C42: 43700 | H42: 60411.39 | J42: 0 | L42: 3698.62 | M42: 865.02 | N42: 1101.14 | O42: 201.86 | U42: 5538.46
H43: 732.38 | U43: 6337.92
H44: =SUM(H41:H43) -> 123612.4 | L44: =SUM(L41:L42) -> 7570.92 | M44: =SUM(M41:M42) -> 1770.67 | N44: =SUM(N41:N42) -> 2354.18 | O44: =SUM(O41:O42) -> 431.58 | P44: =SUM(P41:P42) -> 0
H45: =H38 -> 95084 | AG45: 114.44
I46: Opp Corp | J46: Americ | L46: 196.5 | M46: 45.96 | P46: =SUM(L46:O46) -> 242.46 | AG46: 151.65
F47: =I35-H43 -> 122880.02 | L47: 229.25 | M47: 53.62 | P47: =SUM(L47:O47) -> 282.87 | R47: =SUM(P46:P47) -> 525.33 | S47: =R47+'May 2019 Alloc '!N58+'April 2019 Alloc '!R45 -> 2303.36
H48: 43630 | I48: 2769.23 | J48: 3168.96 | L48: 165.08 | M48: 38.61 | N48: 83.08 | O48: 15.23
H49: 43644 | I49: 2769.23 | J49: 3168.96 | L49: 165.08 | M49: 38.61 | N49: 83.08 | O49: 15.23
I52: =SUM(I48:I51) -> 5538.46 | J52: =SUM(J48:J51) -> 6337.92
J54: =J52+'May 2019 Alloc '!I60+'April 2019 Alloc '!H44+'April 2019 Alloc '!H45 -> 29576.95
I60: 2900

Sheet August 2019 Alloc 
B1: August Cost Allocations | L1: 7251 | M1: 7252 | N1: 7253 | O1: 7254 | P1: 7260.1 | Q1: 8140 | R1: 7515.5 | S1: 7521 | T1: 8112 | U1: 8135.5 | V1: 8191 | W1: 8210.5 | X1: 8229.1 | Y1: 8239 | Z1: 8266 | AC1: 7248
L2: FICA | M2: MEDI | N2: SUI | O2: Disability | P2: Payroll Fees | Q2: Postage | R2: IT Consultants | S2: Acctg Fees | T2: Supplies | U2: Telephone | V2: Web Hosting | W2: Utilities | X2: Eq Lease | Y2: Repairs | Z2: General Insurance | AC2: W/ Comp
L3: 7432.33 | M3: 1738.27 | N3: 1878 | O3: 399.73 | P3: 1535.69 | Q3: 300.57 | R3: 3006 | S3: 3920 | T3: 676.56 | U3: 879.99 | V3: 312 | W3: 1393.15 | X3: 2321.34 | Y3: 764.51 | Z3: 3972.48 | AC3: 6645.7
L4: 1 | M4: 2 | N4: 3 | O4: 4 | P4: 5 | Q4: 6 | R4: 7 | S4: 8 | T4: 9 | U4: 10 | V4: 11 | W4: 12 | X4: 13 | Y4: 14 | Z4: 15 | AC4: 0.04
D5: 7222 | E5: Taxes | F5: W/C | J5: Taxes | K5: Expenses
B6: 41 | C6: Thriftworks | H6: 0 | J6: =H6/$I$35 -> 0 | K6: =H6/$I$37 -> 0 | L6: =J6*$L$3 -> 0 | M6: =J6*$M$3 -> 0 | N6: =J6*$N$3 -> 0 | O6: =J6*$O$3 -> 0 | P6: =J6*$P$3 -> 0 | Q6: =K6*$Q$3 -> 0 | R6: =K6*$R$3 -> 0 | S6: =K6*$S$3 -> 0 | T6: =K6*$T$3 -> 0 | U6: =K6*$U$3 -> 0 | V6: =K6*$V$3 -> 0 | W6: =K6*$W$3 -> 0 | X6: =K6*$X$3 -> 0 | Y6: =K6*$Y$3 -> 0 | Z6: =K6*$Z$3 -> 0 | AB6: =H6/$H$39 -> 0 | AC6: =AB6*$AC$3 -> 0
B7: 111 | C7: Abbott | H7: 8175.82 | J7: =H7/$I$35 -> 0.066140776 | K7: =H7/$I$37 -> 0.060343152 | L7: =J7*$L$3 -> 491.58007 | M7: =J7*$M$3 -> 114.97053 | N7: =J7*$N$3 -> 124.21238 | O7: =J7*$O$3 -> 26.438452 | P7: =J7*$P$3 -> 101.57173 | Q7: =K7*$Q$3 -> 18.137341 | R7: =K7*$R$3 -> 181.39151 | S7: =K7*$S$3 -> 236.54515 | T7: =K7*$T$3 -> 40.825763 | U7: =K7*$U$3 -> 53.10137 | V7: =K7*$V$3 -> 18.827063 | W7: =K7*$W$3 -> 84.067062 | X7: =K7*$X$3 -> 140.07697 | Y7: =K7*$Y$3 -> 46.132943 | Z7: =K7*$Z$3 -> 239.71196 | AB7: =H7/$H$39 -> 0.035458739 | AC7: =AB7*$AC$3 -> 235.64814
B8: 111A | C8: Abbott - Other | H8: 2314.82 | J8: =H8/$I$35 -> 0.018726438 | K8: =H8/$I$37 -> 0.017084957 | L8: =J8*$L$3 -> 139.18107 | M8: =J8*$M$3 -> 32.551606 | N8: =J8*$N$3 -> 35.168251 | O8: =J8*$O$3 -> 7.4855192 | P8: =J8*$P$3 -> 28.758004 | Q8: =K8*$Q$3 -> 5.1352256 | R8: =K8*$R$3 -> 51.357381 | S8: =K8*$S$3 -> 66.973032 | T8: =K8*$T$3 -> 11.558999 | U8: =K8*$U$3 -> 15.034591 | V8: =K8*$V$3 -> 5.3305066 | W8: =K8*$W$3 -> 23.801908 | X8: =K8*$X$3 -> 39.659994 | Y8: =K8*$Y$3 -> 13.061621 | Z8: =K8*$Z$3 -> 67.869651 | AB8: =H8/$H$39 -> 0.010039433 | AC8: =AB8*$AC$3 -> 66.719061
B9: 111B | C9: Abbott Fees | H9: 0 | J9: =H9/$I$35 -> 0 | K9: =H9/$I$37 -> 0 | L9: =J9*$L$3 -> 0 | M9: =J9*$M$3 -> 0 | N9: =J9*$N$3 -> 0 | O9: =J9*$O$3 -> 0 | P9: =J9*$P$3 -> 0 | Q9: =K9*$Q$3 -> 0 | R9: =K9*$R$3 -> 0 | S9: =K9*$S$3 -> 0 | T9: =K9*$T$3 -> 0 | U9: =K9*$U$3 -> 0 | V9: =K9*$V$3 -> 0 | W9: =K9*$W$3 -> 0 | X9: =K9*$X$3 -> 0 | Y9: =K9*$Y$3 -> 0 | Z9: =K9*$Z$3 -> 0 | AB9: =H9/$H$39 -> 0 | AC9: =AB9*$AC$3 -> 0
B10: 111F | C10: Abbott Food | H10: 0 | J10: =H10/$I$35 -> 0 | K10: =H10/$I$37 -> 0 | L10: =J10*$L$3 -> 0 | M10: =J10*$M$3 -> 0 | N10: =J10*$N$3 -> 0 | O10: =J10*$O$3 -> 0 | P10: =J10*$P$3 -> 0 | Q10: =K10*$Q$3 -> 0 | R10: =K10*$R$3 -> 0 | S10: =K10*$S$3 -> 0 | T10: =K10*$T$3 -> 0 | U10: =K10*$U$3 -> 0 | V10: =K10*$V$3 -> 0 | W10: =K10*$W$3 -> 0 | X10: =K10*$X$3 -> 0 | Y10: =K10*$Y$3 -> 0 | Z10: =K10*$Z$3 -> 0 | AB10: =H10/$H$39 -> 0 | AC10: =AB10*$AC$3 -> 0
B11: 112 | C11: EHS | H11: 26478.15 | J11: =H11/$I$35 -> 0.21420302 | K11: =H11/$I$37 -> 0.19542688 | L11: =J11*$L$3 -> 1592.0276 | M11: =J11*$M$3 -> 372.34269 | N11: =J11*$N$3 -> 402.27328 | O11: =J11*$O$3 -> 85.623375 | P11: =J11*$P$3 -> 328.94944 | Q11: =K11*$Q$3 -> 58.739458 | R11: =K11*$R$3 -> 587.45321 | S11: =K11*$S$3 -> 766.07338 | T11: =K11*$T$3 -> 132.21801 | U11: =K11*$U$3 -> 171.9737 | V11: =K11*$V$3 -> 60.973188 | W11: =K11*$W$3 -> 272.25896 | X11: =K11*$X$3 -> 453.65224 | Y11: =K11*$Y$3 -> 149.40581 | Z11: =K11*$Z$3 -> 776.32939 | AB11: =H11/$H$39 -> 0.11483641 | AC11: =AB11*$AC$3 -> 763.16832
B12: 114 | C12: Summer Camp | H12: 10446.9 | J12: =H12/$I$35 -> 0.084513366 | K12: =H12/$I$37 -> 0.077105278 | L12: =J12*$L$3 -> 628.13123 | M12: =J12*$M$3 -> 146.90705 | N12: =J12*$N$3 -> 158.7161 | O12: =J12*$O$3 -> 33.782528 | P12: =J12*$P$3 -> 129.78633 | Q12: =K12*$Q$3 -> 23.175533 | R12: =K12*$R$3 -> 231.77846 | S12: =K12*$S$3 -> 302.25269 | T12: =K12*$T$3 -> 52.166347 | U12: =K12*$U$3 -> 67.851873 | V12: =K12*$V$3 -> 24.056847 | W12: =K12*$W$3 -> 107.41922 | X12: =K12*$X$3 -> 178.98757 | Y12: =K12*$Y$3 -> 58.947756 | Z12: =K12*$Z$3 -> 306.29917 | AB12: =H12/$H$39 -> 0.04530847 | AC12: =AB12*$AC$3 -> 301.1065
B13: 222 | C13: DCF- Coding | H13: 2480.65 | J13: =H13/$I$35 -> 0.020067971 | K13: =H13/$I$37 -> 0.018308896 | L13: =J13*$L$3 -> 149.15178 | M13: =J13*$M$3 -> 34.883551 | N13: =J13*$N$3 -> 37.687649 | O13: =J13*$O$3 -> 8.0217699 | P13: =J13*$P$3 -> 30.818182 | Q13: =K13*$Q$3 -> 5.5031049 | R13: =K13*$R$3 -> 55.036542 | S13: =K13*$S$3 -> 71.770873 | T13: =K13*$T$3 -> 12.387067 | U13: =K13*$U$3 -> 16.111646 | V13: =K13*$V$3 -> 5.7123756 | W13: =K13*$W$3 -> 25.507039 | X13: =K13*$X$3 -> 42.501173 | Y13: =K13*$Y$3 -> 13.997334 | Z13: =K13*$Z$3 -> 72.731724 | AB13: =H13/$H$39 -> 0.010758642 | AC13: =AB13*$AC$3 -> 71.498707
B14: 223 | C14: OICA | H14: 0 | J14: =H14/$I$35 -> 0 | K14: =H14/$I$37 -> 0 | L14: =J14*$L$3 -> 0 | M14: =J14*$M$3 -> 0 | N14: =J14*$N$3 -> 0 | O14: =J14*$O$3 -> 0 | P14: =J14*$P$3 -> 0 | Q14: =K14*$Q$3 -> 0 | R14: =K14*$R$3 -> 0 | S14: =K14*$S$3 -> 0 | T14: =K14*$T$3 -> 0 | U14: =K14*$U$3 -> 0 | V14: =K14*$V$3 -> 0 | W14: =K14*$W$3 -> 0 | X14: =K14*$X$3 -> 0 | Y14: =K14*$Y$3 -> 0 | Z14: =K14*$Z$3 -> 0 | AB14: =H14/$H$39 -> 0 | AC14: =AB14*$AC$3 -> 0
B15: 334 | C15: NRTC - Admin | H15: 0 | J15: =H15/$I$35 -> 0 | K15: =H15/$I$37 -> 0 | L15: =J15*$L$3 -> 0 | M15: =J15*$M$3 -> 0 | N15: =J15*$N$3 -> 0 | O15: =J15*$O$3 -> 0 | P15: =J15*$P$3 -> 0 | Q15: =K15*$Q$3 -> 0 | R15: =K15*$R$3 -> 0 | S15: =K15*$S$3 -> 0 | T15: =K15*$T$3 -> 0 | U15: =K15*$U$3 -> 0 | V15: =K15*$V$3 -> 0 | W15: =K15*$W$3 -> 0 | X15: =K15*$X$3 -> 0 | Y15: =K15*$Y$3 -> 0 | Z15: =K15*$Z$3 -> 0 | AB15: =H15/$H$39 -> 0 | AC15: =AB15*$AC$3 -> 0
B16: 334H | C16: NRTC - Housing | H16: 1207.5 | J16: =H16/$I$35 -> 0.0097684375 | K16: =H16/$I$37 -> 0.0089121771 | L16: =J16*$L$3 -> 72.602251 | M16: =J16*$M$3 -> 16.980182 | N16: =J16*$N$3 -> 18.345126 | O16: =J16*$O$3 -> 3.9047375 | P16: =J16*$P$3 -> 15.001292 | Q16: =K16*$Q$3 -> 2.6787331 | R16: =K16*$R$3 -> 26.790004 | S16: =K16*$S$3 -> 34.935734 | T16: =K16*$T$3 -> 6.0296225 | U16: =K16*$U$3 -> 7.8426267 | V16: =K16*$V$3 -> 2.7805992 | W16: =K16*$W$3 -> 12.416 | X16: =K16*$X$3 -> 20.688193 | Y16: =K16*$Y$3 -> 6.8134485 | Z16: =K16*$Z$3 -> 35.403445 | AB16: =H16/$H$39 -> 0.0052369582 | AC16: =AB16*$AC$3 -> 34.803253
B17: 334F | C17: NRTC FOC | H17: 0 | J17: =H17/$I$35 -> 0 | K17: =H17/$I$37 -> 0 | L17: =J17*$L$3 -> 0 | M17: =J17*$M$3 -> 0 | N17: =J17*$N$3 -> 0 | O17: =J17*$O$3 -> 0 | P17: =J17*$P$3 -> 0 | Q17: =K17*$Q$3 -> 0 | R17: =K17*$R$3 -> 0 | S17: =K17*$S$3 -> 0 | T17: =K17*$T$3 -> 0 | U17: =K17*$U$3 -> 0 | V17: =K17*$V$3 -> 0 | W17: =K17*$W$3 -> 0 | X17: =K17*$X$3 -> 0 | Y17: =K17*$Y$3 -> 0 | Z17: =K17*$Z$3 -> 0 | AB17: =H17/$H$39 -> 0 | AC17: =AB17*$AC$3 -> 0
B18: 335 | C18: NRTC 19 | H18: 3134.45 | J18: =H18/$I$35 -> 0.025357084 | K18: =H18/$I$37 -> 0.023134388 | L18: =J18*$L$3 -> 188.46222 | M18: =J18*$M$3 -> 44.077458 | N18: =J18*$N$3 -> 47.620604 | O18: =J18*$O$3 -> 10.135987 | P18: =J18*$P$3 -> 38.94062 | Q18: =K18*$Q$3 -> 6.953503 | R18: =K18*$R$3 -> 69.54197 | S18: =K18*$S$3 -> 90.686801 | T18: =K18*$T$3 -> 15.651802 | U18: =K18*$U$3 -> 20.35803 | V18: =K18*$V$3 -> 7.217929 | W18: =K18*$W$3 -> 32.229673 | X18: =K18*$X$3 -> 53.70278 | Y18: =K18*$Y$3 -> 17.686471 | Z18: =K18*$Z$3 -> 91.900893 | AB18: =H18/$H$39 -> 0.013594189 | AC18: =AB18*$AC$3 -> 90.342903
B19: 368 | C19: Wells Fargo | H19: 2615.2 | J19: =H19/$I$35 -> 0.021156454 | K19: =H19/$I$37 -> 0.019301967 | L19: =J19*$L$3 -> 157.24174 | M19: =J19*$M$3 -> 36.775629 | N19: =J19*$N$3 -> 39.73182 | O19: =J19*$O$3 -> 8.4568692 | P19: =J19*$P$3 -> 32.489754 | Q19: =K19*$Q$3 -> 5.8015923 | R19: =K19*$R$3 -> 58.021714 | S19: =K19*$S$3 -> 75.663712 | T19: =K19*$T$3 -> 13.058939 | U19: =K19*$U$3 -> 16.985538 | V19: =K19*$V$3 -> 6.0222138 | W19: =K19*$W$3 -> 26.890536 | X19: =K19*$X$3 -> 44.806429 | Y19: =K19*$Y$3 -> 14.756547 | Z19: =K19*$Z$3 -> 76.676679 | AB19: =H19/$H$39 -> 0.011342189 | AC19: =AB19*$AC$3 -> 75.376784
B20: 451 | C20: USJP | H20: 17145.83 | J20: =H20/$I$35 -> 0.13870639 | K20: =H20/$I$37 -> 0.12654797 | L20: =J20*$L$3 -> 1030.9117 | M20: =J20*$M$3 -> 241.10916 | N20: =J20*$N$3 -> 260.4906 | O20: =J20*$O$3 -> 55.445106 | P20: =J20*$P$3 -> 213.01002 | Q20: =K20*$Q$3 -> 38.036523 | R20: =K20*$R$3 -> 380.4032 | S20: =K20*$S$3 -> 496.06804 | T20: =K20*$T$3 -> 85.617294 | U20: =K20*$U$3 -> 111.36095 | V20: =K20*$V$3 -> 39.482966 | W20: =K20*$W$3 -> 176.3003 | X20: =K20*$X$3 -> 293.76086 | Y20: =K20*$Y$3 -> 96.747188 | Z20: =K20*$Z$3 -> 502.70928 | AB20: =H20/$H$39 -> 0.0743619 | AC20: =AB20*$AC$3 -> 494.18688
B21: 452 | C21: PACE | H21: 2250 | J21: =H21/$I$35 -> 0.018202057 | K21: =H21/$I$37 -> 0.016606541 | L21: =J21*$L$3 -> 135.2837 | M21: =J21*$M$3 -> 31.64009 | N21: =J21*$N$3 -> 34.183464 | O21: =J21*$O$3 -> 7.2759084 | P21: =J21*$P$3 -> 27.952718 | Q21: =K21*$Q$3 -> 4.9914281 | R21: =K21*$R$3 -> 49.919263 | S21: =K21*$S$3 -> 65.097641 | T21: =K21*$T$3 -> 11.235321 | U21: =K21*$U$3 -> 14.61359 | V21: =K21*$V$3 -> 5.1812408 | W21: =K21*$W$3 -> 23.135403 | X21: =K21*$X$3 -> 38.549428 | Y21: =K21*$Y$3 -> 12.695867 | Z21: =K21*$Z$3 -> 65.969153 | AB21: =H21/$H$39 -> 0.0097583071 | AC21: =AB21*$AC$3 -> 64.850782
B22: 454 | C22: Prudential #1 Workforce | K22: =H22/$I$37 -> 0 | Q22: =K22*$Q$3 -> 0 | R22: =K22*$R$3 -> 0 | S22: =K22*$S$3 -> 0 | T22: =K22*$T$3 -> 0 | U22: =K22*$U$3 -> 0 | V22: =K22*$V$3 -> 0 | W22: =K22*$W$3 -> 0 | X22: =K22*$X$3 -> 0 | Y22: =K22*$Y$3 -> 0 | Z22: =K22*$Z$3 -> 0
B23: 467 | C23: WF - United Airlines | H23: 7211.73 | J23: =H23/$I$35 -> 0.058341477 | K23: =H23/$I$37 -> 0.053227507 | L23: =J23*$L$3 -> 433.61311 | M23: =J23*$M$3 -> 101.41324 | N23: =J23*$N$3 -> 109.56529 | O23: =J23*$O$3 -> 23.320839 | P23: =J23*$P$3 -> 89.594423 | Q23: =K23*$Q$3 -> 15.998592 | R23: =K23*$R$3 -> 160.00189 | S23: =K23*$S$3 -> 208.65183 | T23: =K23*$T$3 -> 36.011602 | U23: =K23*$U$3 -> 46.839674 | V23: =K23*$V$3 -> 16.606982 | W23: =K23*$W$3 -> 74.153902 | X23: =K23*$X$3 -> 123.55914 | Y23: =K23*$Y$3 -> 40.692961 | Z23: =K23*$Z$3 -> 211.44521 | AB23: =H23/$H$39 -> 0.031277456 | AC23: =AB23*$AC$3 -> 207.86059
B24: 468 | C24: Newark Alliance | H24: 6307.7 | J24: =H24/$I$35 -> 0.051028052 | K24: =H24/$I$37 -> 0.046555146 | L24: =J24*$L$3 -> 379.25732 | M24: =J24*$M$3 -> 88.700532 | N24: =J24*$N$3 -> 95.830682 | O24: =J24*$O$3 -> 20.397443 | P24: =J24*$P$3 -> 78.363269 | Q24: =K24*$Q$3 -> 13.99308 | R24: =K24*$R$3 -> 139.94477 | S24: =K24*$S$3 -> 182.49617 | T24: =K24*$T$3 -> 31.49735 | U24: =K24*$U$3 -> 40.968063 | V24: =K24*$V$3 -> 14.525206 | W24: =K24*$W$3 -> 64.858302 | X24: =K24*$X$3 -> 108.07032 | Y24: =K24*$Y$3 -> 35.591875 | Z24: =K24*$Z$3 -> 184.93939 | AB24: =H24/$H$39 -> 0.027356655 | AC24: =AB24*$AC$3 -> 181.80412
B25: 502 | C25: ESG | H25: 1810.75 | J25: =H25/$I$35 -> 0.014648611 | K25: =H25/$I$37 -> 0.013364575 | L25: =J25*$L$3 -> 108.87331 | M25: =J25*$M$3 -> 25.463242 | N25: =J25*$N$3 -> 27.510092 | O25: =J25*$O$3 -> 5.8554894 | P25: =J25*$P$3 -> 22.495726 | Q25: =K25*$Q$3 -> 4.0169904 | R25: =K25*$R$3 -> 40.173913 | S25: =K25*$S$3 -> 52.389135 | T25: =K25*$T$3 -> 9.0419371 | U25: =K25*$U$3 -> 11.760693 | V25: =K25*$V$3 -> 4.1697475 | W25: =K25*$W$3 -> 18.618858 | X25: =K25*$X$3 -> 31.023723 | Y25: =K25*$Y$3 -> 10.217351 | Z25: =K25*$Z$3 -> 53.090508 | AB25: =H25/$H$39 -> 0.0078532687 | AC25: =AB25*$AC$3 -> 52.190468
B26: 515 | C26: FOC - HUD NUL PARS | H26: 2247.79 | J26: =H26/$I$35 -> 0.018184179 | K26: =H26/$I$37 -> 0.01659023 | L26: =J26*$L$3 -> 135.15082 | M26: =J26*$M$3 -> 31.609013 | N26: =J26*$N$3 -> 34.149888 | O26: =J26*$O$3 -> 7.2687618 | P26: =J26*$P$3 -> 27.925262 | Q26: =K26*$Q$3 -> 4.9865254 | R26: =K26*$R$3 -> 49.870231 | S26: =K26*$S$3 -> 65.033701 | T26: =K26*$T$3 -> 11.224286 | U26: =K26*$U$3 -> 14.599236 | V26: =K26*$V$3 -> 5.1761517 | W26: =K26*$W$3 -> 23.112679 | X26: =K26*$X$3 -> 38.511564 | Y26: =K26*$Y$3 -> 12.683397 | Z26: =K26*$Z$3 -> 65.904356 | AB26: =H26/$H$39 -> 0.0097487223 | AC26: =AB26*$AC$3 -> 64.787084
B27: 525 | C27: CDBG - Housing | H27: 3206.01 | J27: =H27/$I$35 -> 0.02593599 | K27: =H27/$I$37 -> 0.02366255 | L27: =J27*$L$3 -> 192.76484 | M27: =J27*$M$3 -> 45.083754 | N27: =J27*$N$3 -> 48.70779 | O27: =J27*$O$3 -> 10.367393 | P27: =J27*$P$3 -> 39.829641 | Q27: =K27*$Q$3 -> 7.1122526 | R27: =K27*$R$3 -> 71.129625 | S27: =K27*$S$3 -> 92.757195 | T27: =K27*$T$3 -> 16.009135 | U27: =K27*$U$3 -> 20.822807 | V27: =K27*$V$3 -> 7.3827155 | W27: =K27*$W$3 -> 32.965481 | X27: =K27*$X$3 -> 54.928823 | Y27: =K27*$Y$3 -> 18.090256 | Z27: =K27*$Z$3 -> 93.999006 | AB27: =H27/$H$39 -> 0.013904547 | AC27: =AB27*$AC$3 -> 92.405446
B28: 560 | C28: CAP 1 - Save Up | H28: 77 | J28: =H28/$I$35 -> 0.00062291485 | K28: =H28/$I$37 -> 0.00056831274 | L28: =J28*$L$3 -> 4.6297088 | M28: =J28*$M$3 -> 1.0827942 | N28: =J28*$N$3 -> 1.1698341 | O28: =J28*$O$3 -> 0.24899775 | P28: =J28*$P$3 -> 0.95660411 | Q28: =K28*$Q$3 -> 0.17081776 | R28: =K28*$R$3 -> 1.7083481 | S28: =K28*$S$3 -> 2.2277859 | T28: =K28*$T$3 -> 0.38449767 | U28: =K28*$U$3 -> 0.50010953 | V28: =K28*$V$3 -> 0.17731358 | W28: =K28*$W$3 -> 0.7917449 | X28: =K28*$X$3 -> 1.3192471 | Y28: =K28*$Y$3 -> 0.43448077 | Z28: =K28*$Z$3 -> 2.257611 | AB28: =H28/$H$39 -> 0.00033395095 | AC28: =AB28*$AC$3 -> 2.2193379
B29: 561 | C29: LISC FOC 2019 | H29: 5000.65 | J29: =H29/$I$35 -> 0.040454275 | K29: =H29/$I$37 -> 0.036908222 | L29: =J29*$L$3 -> 300.66952 | M29: =J29*$M$3 -> 70.320452 | N29: =J29*$N$3 -> 75.973128 | O29: =J29*$O$3 -> 16.170787 | P29: =J29*$P$3 -> 62.125225 | Q29: =K29*$Q$3 -> 11.093504 | R29: =K29*$R$3 -> 110.94612 | S29: =K29*$S$3 -> 144.68023 | T29: =K29*$T$3 -> 24.970627 | U29: =K29*$U$3 -> 32.478866 | V29: =K29*$V$3 -> 11.515365 | W29: =K29*$W$3 -> 51.41869 | X29: =K29*$X$3 -> 85.676533 | Y29: =K29*$Y$3 -> 28.216705 | Z29: =K29*$Z$3 -> 146.61717 | AB29: =H29/$H$39 -> 0.021687946 | AC29: =AB29*$AC$3 -> 144.13158
B30: 563 | C30: Prudential #1 FOC | H30: 3202.43 | J30: =H30/$I$35 -> 0.025907029 | K30: =H30/$I$37 -> 0.023636127 | L30: =J30*$L$3 -> 192.54959 | M30: =J30*$M$3 -> 45.033411 | N30: =J30*$N$3 -> 48.6534 | O30: =J30*$O$3 -> 10.355817 | P30: =J30*$P$3 -> 39.785165 | Q30: =K30*$Q$3 -> 7.1043107 | R30: =K30*$R$3 -> 71.050198 | S30: =K30*$S$3 -> 92.653618 | T30: =K30*$T$3 -> 15.991258 | U30: =K30*$U$3 -> 20.799555 | V30: =K30*$V$3 -> 7.3744716 | W30: =K30*$W$3 -> 32.92867 | X30: =K30*$X$3 -> 54.867487 | Y30: =K30*$Y$3 -> 18.070055 | Z30: =K30*$Z$3 -> 93.894041 | AB30: =H30/$H$39 -> 0.01388902 | AC30: =AB30*$AC$3 -> 92.302262
B31: 610 | C31: CEO | H31: 11923.08 | J31: =H31/$I$35 -> 0.096455372 | K31: =H31/$I$37 -> 0.088000497 | L31: =J31*$L$3 -> 716.88815 | M31: =J31*$M$3 -> 167.66548 | N31: =J31*$N$3 -> 181.14319 | O31: =J31*$O$3 -> 38.556106 | P31: =J31*$P$3 -> 148.12555 | Q31: =K31*$Q$3 -> 26.450309 | R31: =K31*$R$3 -> 264.52949 | S31: =K31*$S$3 -> 344.96195 | T31: =K31*$T$3 -> 59.537616 | U31: =K31*$U$3 -> 77.439557 | V31: =K31*$V$3 -> 27.456155 | W31: =K31*$W$3 -> 122.59789 | X31: =K31*$X$3 -> 204.27907 | Y31: =K31*$Y$3 -> 67.27726 | Z31: =K31*$Z$3 -> 349.58021 | AB31: =H31/$H$39 -> 0.051710701 | AC31: =AB31*$AC$3 -> 343.6538
B32: 620 | C32: CFO | H32: 6076.93 | J32: =H32/$I$35 -> 0.049161168 | K32: =H32/$I$37 -> 0.044851906 | L32: =J32*$L$3 -> 365.38203 | M32: =J32*$M$3 -> 85.455384 | N32: =J32*$N$3 -> 92.324674 | O32: =J32*$O$3 -> 19.651194 | P32: =J32*$P$3 -> 75.496315 | Q32: =K32*$Q$3 -> 13.481137 | R32: =K32*$R$3 -> 134.82483 | S32: =K32*$S$3 -> 175.81947 | T32: =K32*$T$3 -> 30.345005 | U32: =K32*$U$3 -> 39.469229 | V32: =K32*$V$3 -> 13.993795 | W32: =K32*$W$3 -> 62.485433 | X32: =K32*$X$3 -> 104.11652 | Y32: =K32*$Y$3 -> 34.289731 | Z32: =K32*$Z$3 -> 178.1733 | AB32: =H32/$H$39 -> 0.0263558 | AC32: =AB32*$AC$3 -> 175.15274
B33: 630 | C33: COO | H33: 0 | J33: =H33/$I$35 -> 0 | K33: =H33/$I$37 -> 0 | L33: =J33*$L$3 -> 0 | M33: =J33*$M$3 -> 0 | N33: =J33*$N$3 -> 0 | O33: =J33*$O$3 -> 0 | P33: =J33*$P$3 -> 0 | Q33: =K33*$Q$3 -> 0 | R33: =K33*$R$3 -> 0 | S33: =K33*$S$3 -> 0 | T33: =K33*$T$3 -> 0 | U33: =K33*$U$3 -> 0 | V33: =K33*$V$3 -> 0 | W33: =K33*$W$3 -> 0 | X33: =K33*$X$3 -> 0 | Y33: =K33*$Y$3 -> 0 | Z33: =K33*$Z$3 -> 0 | AB33: =H33/$H$39 -> 0 | AC33: =AB33*$AC$3 -> 0
B34: 650 | C34: Facilities | H34: 299 | J34: =H34/$I$35 -> 0.0024188512 | K34: =H34/$I$37 -> 0.0022068248 | L34: =J34*$L$3 -> 17.9777 | M34: =J34*$M$3 -> 4.2046164 | N34: =J34*$N$3 -> 4.5426025 | O34: =J34*$O$3 -> 0.96688738 | P34: =J34*$P$3 -> 3.7146056 | Q34: =K34*$Q$3 -> 0.66330533 | R34: =K34*$R$3 -> 6.6337154 | S34: =K34*$S$3 -> 8.6507532 | T34: =K34*$T$3 -> 1.4930494 | U34: =K34*$U$3 -> 1.9419838 | V34: =K34*$V$3 -> 0.68852934 | W34: =K34*$W$3 -> 3.074438 | X34: =K34*$X$3 -> 5.1227907 | Y34: =K34*$Y$3 -> 1.6871396 | Z34: =K34*$Z$3 -> 8.7665674 | AB34: =H34/$H$39 -> 0.0012967706 | AC34: =AB34*$AC$3 -> 8.6179483
B35: 600 | C35: Admin | H35: 0.01 | I35: =SUM(H6:H35) -> 123612.4 | J35: =H35/$I$35 -> 8.0898033e-08 | K35: =H35/$I$37 -> 7.380685e-08 | L35: =J35*$L$3 -> 0.00060126088 | M35: =J35*$M$3 -> 0.00014062262 | N35: =J35*$N$3 -> 0.00015192651 | O35: =J35*$O$3 -> 3.2337371e-05 | P35: =J35*$P$3 -> 0.0001242343 | Q35: =K35*$Q$3 -> 2.2184125e-05 | R35: =K35*$R$3 -> 0.00022186339 | S35: =K35*$S$3 -> 0.00028932285 | T35: =K35*$T$3 -> 4.9934762e-05 | U35: =K35*$U$3 -> 6.494929e-05 | V35: =K35*$V$3 -> 2.3027737e-05 | W35: =K35*$W$3 -> 0.00010282401 | X35: =K35*$X$3 -> 0.00017133079 | Y35: =K35*$Y$3 -> 5.6426075e-05 | Z35: =K35*$Z$3 -> 0.00029319623 | AB35: =H35/$H$39 -> 4.3370254e-08 | AC35: =AB35*$AC$3 -> 0.0002882257
B36: 339 | C36: Opport Corp | H36: 5538.46 | K36: =H36/$I$37 -> 0.040877628 | L36: =J36*$L$3 -> 0 | M36: =J36*$M$3 -> 0 | N36: =J36*$N$3 -> 0 | O36: =J36*$O$3 -> 0 | P36: =J36*$P$3 -> 0 | Q36: =K36*$Q$3 -> 12.286589 | R36: =K36*$R$3 -> 122.87815 | S36: =K36*$S$3 -> 160.2403 | T36: =K36*$T$3 -> 27.656168 | U36: =K36*$U$3 -> 35.971904 | V36: =K36*$V$3 -> 12.75382 | W36: =K36*$W$3 -> 56.948668 | X36: =K36*$X$3 -> 94.890874 | Y36: =K36*$Y$3 -> 31.251356 | Z36: =K36*$Z$3 -> 162.38556 | AB36: =U42/$H$39 -> 0.024020442 | AC36: =AB36*$AC$3 -> 159.63265
B37: 225 | C37: AmeriCorp | H37: 6337.92 | I37: =I35+H36+H37 -> 135488.78 | K37: =H37/$I$37 -> 0.046778191 | Q37: =K37*$Q$3 -> 14.060121 | R37: =K37*$R$3 -> 140.61524 | S37: =K37*$S$3 -> 183.37051 | T37: =K37*$T$3 -> 31.648253 | U37: =K37*$U$3 -> 41.16434 | V37: =K37*$V$3 -> 14.594796 | W37: =K37*$W$3 -> 65.169036 | X37: =K37*$X$3 -> 108.58809 | Y37: =K37*$Y$3 -> 35.762395 | Z37: =K37*$Z$3 -> 185.82543 | AB37: =U43/$H$39 -> 0.02748772 | AC37: =AB37*$AC$3 -> 182.67514
B38: 451 | C38: USJP - Participants | F38: 95614.3 | H38: 95084 | AB38: =H38/$H$39 -> 0.41238172 | AC38: =AB38*$AC$3 -> 2740.5652
H39: =SUM(H6:H38) -> 230572.78 | J39: =SUM(J6:J38) -> 1 | K39: =SUM(K6:K38) -> 1 | L39: =SUM(L6:L38) -> 7432.33 | M39: =SUM(M6:M38) -> 1738.27 | N39: =SUM(N6:N38) -> 1878 | O39: =SUM(O6:O38) -> 399.73 | P39: =SUM(P6:P38) -> 1535.69 | Q39: =SUM(Q6:Q38) -> 300.57 | ... AC39: =SUM(AC6:AC38) -> 6645.7
H40: Salary | J40: Hourly | L40: =L3-L39 -> 0 | M40: =M3-M39 -> 0 | N40: =N3-N39 -> 0 | O40: =O3-O39 -> 0 | P40: =P3-P39 -> 0 | Q40: =Q3-Q39 -> 0 | R40: =R3-R39 -> 0 | S40: =S3-S39 -> 0 | ... AC40: =AC3-AC39 -> 0
C41: 43686 | H41: 62468.63 | L41: 3872.3 | M41: 905.65 | N41: 1253.04 | O41: 229.72
C42: 43700 | H42: 60411.39 | J42: 0 | L42: 3698.62 | M42: 865.02 | N42: 1101.14 | O42: 201.86 | U42: 5538.46
H43: 732.38 | U43: 6337.92
H44: =SUM(H41:H43) -> 123612.4 | L44: =SUM(L41:L42) -> 7570.92 | M44: =SUM(M41:M42) -> 1770.67 | N44: =SUM(N41:N42) -> 2354.18 | O44: =SUM(O41:O42) -> 431.58 | P44: =SUM(P41:P42) -> 0
H45: =H38 -> 95084 | AG45: 114.44
I46: Opp Corp | J46: Americ | L46: 196.5 | M46: 45.96 | P46: =SUM(L46:O46) -> 242.46 | AG46: 151.65
F47: =I35-H43 -> 122880.02 | L47: 229.25 | M47: 53.62 | P47: =SUM(L47:O47) -> 282.87 | R47: =SUM(P46:P47) -> 525.33 | S47: =R47+'May 2019 Alloc '!N58+'April 2019 Alloc '!R45 -> 2303.36
H48: 43630 | I48: 2769.23 | J48: 3168.96 | L48: 165.08 | M48: 38.61 | N48: 83.08 | O48: 15.23
H49: 43644 | I49: 2769.23 | J49: 3168.96 | L49: 165.08 | M49: 38.61 | N49: 83.08 | O49: 15.23
I52: =SUM(I48:I51) -> 5538.46 | J52: =SUM(J48:J51) -> 6337.92
J54: =J52+'May 2019 Alloc '!I60+'April 2019 Alloc '!H44+'April 2019 Alloc '!H45 -> 29576.95

Sheet July 2019 Alloc (2)
B1: July Cost Allocations | L1: 7251 | M1: 7252 | N1: 7253 | O1: 7254 | P1: 7260.1 | R1: 7515.5 | S1: 7521 | T1: 8112 | U1: 8135.5 | V1: 8191 | W1: 8210.5 | X1: 8229.1 | Y1: 8239 | Z1: 8266 | AC1: 7248
L2: FICA | M2: MEDI | N2: SUI | O2: Disability | P2: Payroll Fees | R2: IT Consultants | S2: Acctg Fees | T2: Supplies | U2: Telephone | V2: Web Hosting | W2: Utilities | X2: Eq Lease | Y2: Repairs | Z2: General Insurance | AC2: W/ Comp
L3: =L44 -> 7570.92 | M3: =M44 -> 1770.67 | N3: =N44 -> 2354.18 | O3: =O44 -> 431.58 | P3: 1584.05 | R3: 3006 | S3: 18480 | T3: 688.51 | U3: 880.75 | V3: 327 | W3: 1396.03 | X3: 2489 | Y3: 2719.51 | Z3: 3972.48 | AC3: 6645.7
L4: 1 | M4: 2 | N4: 3 | O4: 4 | P4: 5 | Q4: 6 | R4: 15 | S4: 9 | T4: 7 | U4: 11 | V4: 16 | W4: 10 | X4: 8 | Y4: 13 | Z4: 14 | AC4: 0.04
D5: 7222 | E5: Taxes | F5: W/C | J5: Taxes | K5: Expenses
B6: 41 | C6: Thriftworks | H6: 3538.46 | J6: =H6/$I$35 -> 0.029281103 | K6: =H6/$I$37 -> 0.026660916 | L6: =J6*$L$3 -> 221.68489 | M6: =J6*$M$3 -> 51.847171 | N6: =J6*$N$3 -> 68.932988 | O6: =J6*$O$3 -> 12.637139 | P6: =J6*$P$3 -> 46.382732 | R6: =K6*$R$3 -> 80.142714 | S6: =K6*$S$3 -> 492.69373 | T6: =K6*$T$3 -> 18.356307 | U6: =K6*$U$3 -> 23.481602 | V6: =K6*$V$3 -> 8.7181196 | W6: =K6*$W$3 -> 37.219439 | X6: =K6*$X$3 -> 66.359021 | Y6: =K6*$Y$3 -> 72.504628 | Z6: =K6*$Z$3 -> 105.90996 | AB6: =H6/$H$39 -> 0.018440008 | AC6: =AB6*$AC$3 -> 122.54676
B7: 111 | C7: Abbott | H7: 9404.49 | J7: =H7/$I$35 -> 0.077823077 | K7: =H7/$I$37 -> 0.070859165 | L7: =J7*$L$3 -> 589.19229 | M7: =J7*$M$3 -> 137.79899 | N7: =J7*$N$3 -> 183.20953 | O7: =J7*$O$3 -> 33.586883 | P7: =J7*$P$3 -> 123.27564 | R7: =K7*$R$3 -> 213.00265 | S7: =K7*$S$3 -> 1309.4774 | T7: =K7*$T$3 -> 48.787244 | U7: =K7*$U$3 -> 62.409209 | V7: =K7*$V$3 -> 23.170947 | W7: =K7*$W$3 -> 98.92152 | X7: =K7*$X$3 -> 176.36846 | Y7: =K7*$Y$3 -> 192.70221 | Z7: =K7*$Z$3 -> 281.48661 | AB7: =H7/$H$39 -> 0.049009703 | AC7: =AB7*$AC$3 -> 325.70378
B8: 111A | C8: Abbott - Other | H8: 2314.83 | J8: =H8/$I$35 -> 0.019155445 | K8: =H8/$I$37 -> 0.017441341 | L8: =J8*$L$3 -> 145.02434 | M8: =J8*$M$3 -> 33.917972 | N8: =J8*$N$3 -> 45.095366 | O8: =J8*$O$3 -> 8.267107 | P8: =J8*$P$3 -> 30.343183 | R8: =K8*$R$3 -> 52.428672 | S8: =K8*$S$3 -> 322.31599 | T8: =K8*$T$3 -> 12.008538 | U8: =K8*$U$3 -> 15.361461 | V8: =K8*$V$3 -> 5.7033186 | W8: =K8*$W$3 -> 24.348636 | X8: =K8*$X$3 -> 43.411499 | Y8: =K8*$Y$3 -> 47.431902 | Z8: =K8*$Z$3 -> 69.28538 | AB8: =H8/$H$39 -> 0.012063294 | AC8: =AB8*$AC$3 -> 80.169035
B9: 111B | C9: Abbott Fees | H9: 0 | J9: =H9/$I$35 -> 0 | K9: =H9/$I$37 -> 0 | L9: =J9*$L$3 -> 0 | M9: =J9*$M$3 -> 0 | N9: =J9*$N$3 -> 0 | O9: =J9*$O$3 -> 0 | P9: =J9*$P$3 -> 0 | R9: =K9*$R$3 -> 0 | S9: =K9*$S$3 -> 0 | T9: =K9*$T$3 -> 0 | U9: =K9*$U$3 -> 0 | V9: =K9*$V$3 -> 0 | W9: =K9*$W$3 -> 0 | X9: =K9*$X$3 -> 0 | Y9: =K9*$Y$3 -> 0 | Z9: =K9*$Z$3 -> 0 | AB9: =H9/$H$39 -> 0 | AC9: =AB9*$AC$3 -> 0
B10: 111F | C10: Abbott Food | H10: 0 | J10: =H10/$I$35 -> 0 | K10: =H10/$I$37 -> 0 | L10: =J10*$L$3 -> 0 | M10: =J10*$M$3 -> 0 | N10: =J10*$N$3 -> 0 | O10: =J10*$O$3 -> 0 | P10: =J10*$P$3 -> 0 | R10: =K10*$R$3 -> 0 | S10: =K10*$S$3 -> 0 | T10: =K10*$T$3 -> 0 | U10: =K10*$U$3 -> 0 | V10: =K10*$V$3 -> 0 | W10: =K10*$W$3 -> 0 | X10: =K10*$X$3 -> 0 | Y10: =K10*$Y$3 -> 0 | Z10: =K10*$Z$3 -> 0 | AB10: =H10/$H$39 -> 0 | AC10: =AB10*$AC$3 -> 0
B11: 112 | C11: EHS | H11: 25758.43 | J11: =H11/$I$35 -> 0.21315353 | K11: =H11/$I$37 -> 0.19407973 | L11: =J11*$L$3 -> 1613.7683 | M11: =J11*$M$3 -> 377.42457 | N11: =J11*$N$3 -> 501.80178 | O11: =J11*$O$3 -> 91.992802 | P11: =J11*$P$3 -> 337.64585 | R11: =K11*$R$3 -> 583.40365 | S11: =K11*$S$3 -> 3586.5933 | T11: =K11*$T$3 -> 133.62583 | U11: =K11*$U$3 -> 170.93572 | V11: =K11*$V$3 -> 63.46407 | W11: =K11*$W$3 -> 270.94112 | X11: =K11*$X$3 -> 483.06444 | Y11: =K11*$Y$3 -> 527.80175 | Z11: =K11*$Z$3 -> 770.97783 | AB11: =H11/$H$39 -> 0.13423514 | AC11: =AB11*$AC$3 -> 892.08645
B12: 114 | C12: Summer Camp | H12: 11979.83 | J12: =H12/$I$35 -> 0.099134268 | K12: =H12/$I$37 -> 0.090263347 | L12: =J12*$L$3 -> 750.53761 | M12: =J12*$M$3 -> 175.53407 | N12: =J12*$N$3 -> 233.37991 | O12: =J12*$O$3 -> 42.784367 | P12: =J12*$P$3 -> 157.03364 | R12: =K12*$R$3 -> 271.33162 | S12: =K12*$S$3 -> 1668.0667 | T12: =K12*$T$3 -> 62.147217 | U12: =K12*$U$3 -> 79.499443 | V12: =K12*$V$3 -> 29.516115 | W12: =K12*$W$3 -> 126.01034 | X12: =K12*$X$3 -> 224.66547 | Y12: =K12*$Y$3 -> 245.47208 | Z12: =K12*$Z$3 -> 358.56934 | AB12: =H12/$H$39 -> 0.062430595 | AC12: =AB12*$AC$3 -> 414.89501
B13: 222 | C13: DCF- Coding | H13: 2480.65 | J13: =H13/$I$35 -> 0.020527622 | K13: =H13/$I$37 -> 0.01869073 | L13: =J13*$L$3 -> 155.41298 | M13: =J13*$M$3 -> 36.347644 | N13: =J13*$N$3 -> 48.325717 | O13: =J13*$O$3 -> 8.8593111 | P13: =J13*$P$3 -> 32.516779 | R13: =K13*$R$3 -> 56.184336 | S13: =K13*$S$3 -> 345.4047 | T13: =K13*$T$3 -> 12.868755 | U13: =K13*$U$3 -> 16.461861 | V13: =K13*$V$3 -> 6.1118688 | W13: =K13*$W$3 -> 26.09282 | X13: =K13*$X$3 -> 46.521228 | Y13: =K13*$Y$3 -> 50.829628 | Z13: =K13*$Z$3 -> 74.248553 | AB13: =H13/$H$39 -> 0.012927434 | AC13: =AB13*$AC$3 -> 85.911845
B14: 223 | C14: OICA | H14: 0 | J14: =H14/$I$35 -> 0 | K14: =H14/$I$37 -> 0 | L14: =J14*$L$3 -> 0 | M14: =J14*$M$3 -> 0 | N14: =J14*$N$3 -> 0 | O14: =J14*$O$3 -> 0 | P14: =J14*$P$3 -> 0 | R14: =K14*$R$3 -> 0 | S14: =K14*$S$3 -> 0 | T14: =K14*$T$3 -> 0 | U14: =K14*$U$3 -> 0 | V14: =K14*$V$3 -> 0 | W14: =K14*$W$3 -> 0 | X14: =K14*$X$3 -> 0 | Y14: =K14*$Y$3 -> 0 | Z14: =K14*$Z$3 -> 0 | AB14: =H14/$H$39 -> 0 | AC14: =AB14*$AC$3 -> 0
B15: 334 | C15: NRTC - Admin | H15: 2146.15 | J15: =H15/$I$35 -> 0.017759602 | K15: =H15/$I$37 -> 0.016170403 | L15: =J15*$L$3 -> 134.45652 | M15: =J15*$M$3 -> 31.446394 | N15: =J15*$N$3 -> 41.809299 | O15: =J15*$O$3 -> 7.6646889 | P15: =J15*$P$3 -> 28.132097 | R15: =K15*$R$3 -> 48.608232 | S15: =K15*$S$3 -> 298.82905 | T15: =K15*$T$3 -> 11.133484 | U15: =K15*$U$3 -> 14.242083 | V15: =K15*$V$3 -> 5.2877219 | W15: =K15*$W$3 -> 22.574368 | X15: =K15*$X$3 -> 40.248134 | Y15: =K15*$Y$3 -> 43.975574 | Z15: =K15*$Z$3 -> 64.236604 | AB15: =H15/$H$39 -> 0.011184251 | AC15: =AB15*$AC$3 -> 74.327175
B16: 334H | C16: NRTC - Housing | H16: 1990.25 | J16: =H16/$I$35 -> 0.016469514 | K16: =H16/$I$37 -> 0.014995758 | L16: =J16*$L$3 -> 124.68937 | M16: =J16*$M$3 -> 29.162074 | N16: =J16*$N$3 -> 38.7722 | O16: =J16*$O$3 -> 7.1079128 | P16: =J16*$P$3 -> 26.088533 | R16: =K16*$R$3 -> 45.077247 | S16: =K16*$S$3 -> 277.1216 | T16: =K16*$T$3 -> 10.324729 | U16: =K16*$U$3 -> 13.207514 | V16: =K16*$V$3 -> 4.9036127 | W16: =K16*$W$3 -> 20.934528 | X16: =K16*$X$3 -> 37.324441 | Y16: =K16*$Y$3 -> 40.781113 | Z16: =K16*$Z$3 -> 59.570347 | AB16: =H16/$H$39 -> 0.010371808 | AC16: =AB16*$AC$3 -> 68.927922
B17: 334F | C17: NRTC FOC | H17: 0 | J17: =H17/$I$35 -> 0 | K17: =H17/$I$37 -> 0 | L17: =J17*$L$3 -> 0 | M17: =J17*$M$3 -> 0 | N17: =J17*$N$3 -> 0 | O17: =J17*$O$3 -> 0 | P17: =J17*$P$3 -> 0 | R17: =K17*$R$3 -> 0 | S17: =K17*$S$3 -> 0 | T17: =K17*$T$3 -> 0 | U17: =K17*$U$3 -> 0 | V17: =K17*$V$3 -> 0 | W17: =K17*$W$3 -> 0 | X17: =K17*$X$3 -> 0 | Y17: =K17*$Y$3 -> 0 | Z17: =K17*$Z$3 -> 0 | AB17: =H17/$H$39 -> 0 | AC17: =AB17*$AC$3 -> 0
B18: 335 | C18: NRTC 19 | H18: 846.15 | J18: =H18/$I$35 -> 0.0070019742 | K18: =H18/$I$37 -> 0.0063754103 | L18: =J18*$L$3 -> 53.011386 | M18: =J18*$M$3 -> 12.398186 | N18: =J18*$N$3 -> 16.483908 | O18: =J18*$O$3 -> 3.021912 | P18: =J18*$P$3 -> 11.091477 | R18: =K18*$R$3 -> 19.164483 | S18: =K18*$S$3 -> 117.81758 | T18: =K18*$T$3 -> 4.3895337 | U18: =K18*$U$3 -> 5.6151426 | V18: =K18*$V$3 -> 2.0847592 | W18: =K18*$W$3 -> 8.900264 | X18: =K18*$X$3 -> 15.868396 | Y18: =K18*$Y$3 -> 17.337992 | Z18: =K18*$Z$3 -> 25.32619 | AB18: =H18/$H$39 -> 0.0044095491 | AC18: =AB18*$AC$3 -> 29.30454
B19: 368 | C19: Wells Fargo | H19: 4903.5 | J19: =H19/$I$35 -> 0.040576943 | K19: =H19/$I$37 -> 0.03694596 | L19: =J19*$L$3 -> 307.20479 | M19: =J19*$M$3 -> 71.848376 | N19: =J19*$N$3 -> 95.525428 | O19: =J19*$O$3 -> 17.512197 | P19: =J19*$P$3 -> 64.275907 | R19: =K19*$R$3 -> 111.05956 | S19: =K19*$S$3 -> 682.76135 | T19: =K19*$T$3 -> 25.437663 | U19: =K19*$U$3 -> 32.540155 | V19: =K19*$V$3 -> 12.081329 | W19: =K19*$W$3 -> 51.577669 | X19: =K19*$X$3 -> 91.958495 | Y19: =K19*$Y$3 -> 100.47491 | Z19: =K19*$Z$3 -> 146.76709 | AB19: =H19/$H$39 -> 0.025553653 | AC19: =AB19*$AC$3 -> 169.82191
B20: 451 | C20: USJP | H20: 10715.26 | J20: =H20/$I$35 -> 0.088669827 | K20: =H20/$I$37 -> 0.080735306 | L20: =J20*$L$3 -> 671.31217 | M20: =J20*$M$3 -> 157.005 | N20: =J20*$N$3 -> 208.74473 | O20: =J20*$O$3 -> 38.268124 | P20: =J20*$P$3 -> 140.45744 | R20: =K20*$R$3 -> 242.69033 | S20: =K20*$S$3 -> 1491.9884 | T20: =K20*$T$3 -> 55.587065 | U20: =K20*$U$3 -> 71.10762 | V20: =K20*$V$3 -> 26.400445 | W20: =K20*$W$3 -> 112.70891 | X20: =K20*$X$3 -> 200.95018 | Y20: =K20*$Y$3 -> 219.56047 | Z20: =K20*$Z$3 -> 320.71939 | AB20: =H20/$H$39 -> 0.05584053 | AC20: =AB20*$AC$3 -> 371.09941
B21: 452 | C21: PACE | J21: =H21/$I$35 -> 0 | K21: =H21/$I$37 -> 0 | L21: =J21*$L$3 -> 0 | M21: =J21*$M$3 -> 0 | N21: =J21*$N$3 -> 0 | O21: =J21*$O$3 -> 0 | P21: =J21*$P$3 -> 0 | R21: =K21*$R$3 -> 0 | S21: =K21*$S$3 -> 0 | T21: =K21*$T$3 -> 0 | U21: =K21*$U$3 -> 0 | V21: =K21*$V$3 -> 0 | W21: =K21*$W$3 -> 0 | X21: =K21*$X$3 -> 0 | Y21: =K21*$Y$3 -> 0 | Z21: =K21*$Z$3 -> 0 | AB21: =H21/$H$39 -> 0 | AC21: =AB21*$AC$3 -> 0
B22: 454 | C22: Prudential #1 Workforce | K22: =H22/$I$37 -> 0 | R22: =K22*$R$3 -> 0 | S22: =K22*$S$3 -> 0 | T22: =K22*$T$3 -> 0 | U22: =K22*$U$3 -> 0 | V22: =K22*$V$3 -> 0 | W22: =K22*$W$3 -> 0 | X22: =K22*$X$3 -> 0 | Y22: =K22*$Y$3 -> 0 | Z22: =K22*$Z$3 -> 0
B23: 467 | C23: WF - United Airlines | H23: 6346.17 | J23: =H23/$I$35 -> 0.052515179 | K23: =H23/$I$37 -> 0.047815916 | L23: =J23*$L$3 -> 397.58822 | M23: =J23*$M$3 -> 92.987052 | N23: =J23*$N$3 -> 123.63018 | O23: =J23*$O$3 -> 22.664501 | P23: =J23*$P$3 -> 83.186669 | R23: =K23*$R$3 -> 143.73464 | S23: =K23*$S$3 -> 883.63813 | T23: =K23*$T$3 -> 32.921736 | U23: =K23*$U$3 -> 42.113868 | V23: =K23*$V$3 -> 15.635805 | W23: =K23*$W$3 -> 66.752454 | X23: =K23*$X$3 -> 119.01382 | Y23: =K23*$Y$3 -> 130.03586 | Z23: =K23*$Z$3 -> 189.94777 | AB23: =H23/$H$39 -> 0.033071852 | AC23: =AB23*$AC$3 -> 219.78561
B24: 468 | C24: Newark Alliance | H24: 6307.7 | J24: =H24/$I$35 -> 0.052196836 | K24: =H24/$I$37 -> 0.04752606 | L24: =J24*$L$3 -> 395.17807 | M24: =J24*$M$3 -> 92.423371 | N24: =J24*$N$3 -> 122.88075 | O24: =J24*$O$3 -> 22.52711 | P24: =J24*$P$3 -> 82.682398 | R24: =K24*$R$3 -> 142.86334 | S24: =K24*$S$3 -> 878.28158 | T24: =K24*$T$3 -> 32.722167 | U24: =K24*$U$3 -> 41.858577 | V24: =K24*$V$3 -> 15.541022 | W24: =K24*$W$3 -> 66.347805 | X24: =K24*$X$3 -> 118.29236 | Y24: =K24*$Y$3 -> 129.24759 | Z24: =K24*$Z$3 -> 188.79632 | AB24: =H24/$H$39 -> 0.032871373 | AC24: =AB24*$AC$3 -> 218.45329
B25: 502 | C25: ESG | H25: 2022.12 | J25: =H25/$I$35 -> 0.016733241 | K25: =H25/$I$37 -> 0.015235886 | L25: =J25*$L$3 -> 126.68603 | M25: =J25*$M$3 -> 29.629048 | N25: =J25*$N$3 -> 39.393062 | O25: =J25*$O$3 -> 7.2217322 | P25: =J25*$P$3 -> 26.506291 | R25: =K25*$R$3 -> 45.799072 | S25: =K25*$S$3 -> 281.55917 | T25: =K25*$T$3 -> 10.49006 | U25: =K25*$U$3 -> 13.419006 | V25: =K25*$V$3 -> 4.9821346 | W25: =K25*$W$3 -> 21.269753 | X25: =K25*$X$3 -> 37.922119 | Y25: =K25*$Y$3 -> 41.434143 | Z25: =K25*$Z$3 -> 60.524251 | AB25: =H25/$H$39 -> 0.010537892 | AC25: =AB25*$AC$3 -> 70.031669
B26: 515 | C26: FOC - HUD NUL PARS | H26: 2659.26 | J26: =H26/$I$35 -> 0.022005637 | K26: =H26/$I$37 -> 0.020036487 | L26: =J26*$L$3 -> 166.60292 | M26: =J26*$M$3 -> 38.964722 | N26: =J26*$N$3 -> 51.805231 | O26: =J26*$O$3 -> 9.4971929 | P26: =J26*$P$3 -> 34.85803 | R26: =K26*$R$3 -> 60.22968 | S26: =K26*$S$3 -> 370.27428 | T26: =K26*$T$3 -> 13.795322 | U26: =K26*$U$3 -> 17.647136 | V26: =K26*$V$3 -> 6.5519313 | W26: =K26*$W$3 -> 27.971537 | X26: =K26*$X$3 -> 49.870816 | Y26: =K26*$Y$3 -> 54.489427 | Z26: =K26*$Z$3 -> 79.594544 | AB26: =H26/$H$39 -> 0.013858225 | AC26: =AB26*$AC$3 -> 92.097609
B27: 525 | C27: CDBG - Housing | H27: 3244.23 | J27: =H27/$I$35 -> 0.026846321 | K27: =H27/$I$37 -> 0.024444008 | L27: =J27*$L$3 -> 203.25135 | M27: =J27*$M$3 -> 47.535976 | N27: =J27*$N$3 -> 63.201073 | O27: =J27*$O$3 -> 11.586335 | P27: =J27*$P$3 -> 42.525915 | R27: =K27*$R$3 -> 73.478688 | S27: =K27*$S$3 -> 451.72527 | T27: =K27*$T$3 -> 16.829944 | U27: =K27*$U$3 -> 21.52906 | V27: =K27*$V$3 -> 7.9931906 | W27: =K27*$W$3 -> 34.124568 | X27: =K27*$X$3 -> 60.841136 | Y27: =K27*$Y$3 -> 66.475724 | Z27: =K27*$Z$3 -> 97.103333 | AB27: =H27/$H$39 -> 0.016906685 | AC27: =AB27*$AC$3 -> 112.35676
B28: 560 | C28: CAP 1 - Save Up | H28: 115.39 | J28: =H28/$I$35 -> 0.00095486356 | K28: =H28/$I$37 -> 0.00086941865 | L28: =J28*$L$3 -> 7.2291956 | M28: =J28*$M$3 -> 1.6907483 | N28: =J28*$N$3 -> 2.2479207 | O28: =J28*$O$3 -> 0.41210002 | P28: =J28*$P$3 -> 1.5125516 | R28: =K28*$R$3 -> 2.6134725 | S28: =K28*$S$3 -> 16.066857 | T28: =K28*$T$3 -> 0.59860344 | U28: =K28*$U$3 -> 0.76574048 | V28: =K28*$V$3 -> 0.2842999 | W28: =K28*$W$3 -> 1.2137345 | X28: =K28*$X$3 -> 2.163983 | Y28: =K28*$Y$3 -> 2.3643927 | Z28: =K28*$Z$3 -> 3.4537482 | AB28: =H28/$H$39 -> 0.00060133294 | AC28: =AB28*$AC$3 -> 3.9962783
B29: 564 | C29: LISC FOC 2019 | H29: 4519.24 | J29: =H29/$I$35 -> 0.037397154 | K29: =H29/$I$37 -> 0.034050711 | L29: =J29*$L$3 -> 283.13086 | M29: =J29*$M$3 -> 66.218019 | N29: =J29*$N$3 -> 88.039632 | O29: =J29*$O$3 -> 16.139864 | P29: =J29*$P$3 -> 59.238962 | R29: =K29*$R$3 -> 102.35644 | S29: =K29*$S$3 -> 629.25714 | T29: =K29*$T$3 -> 23.444255 | U29: =K29*$U$3 -> 29.990164 | V29: =K29*$V$3 -> 11.134583 | W29: =K29*$W$3 -> 47.535814 | X29: =K29*$X$3 -> 84.75222 | Y29: =K29*$Y$3 -> 92.601249 | Z29: =K29*$Z$3 -> 135.26577 | AB29: =H29/$H$39 -> 0.023551156 | AC29: =AB29*$AC$3 -> 156.51392
B30: 563 | C30: Prudential #1 FOC | H30: 2707.22 | J30: =H30/$I$35 -> 0.022402511 | K30: =H30/$I$37 -> 0.020397847 | L30: =J30*$L$3 -> 169.60762 | M30: =J30*$M$3 -> 39.667454 | N30: =J30*$N$3 -> 52.739543 | O30: =J30*$O$3 -> 9.6684756 | P30: =J30*$P$3 -> 35.486697 | R30: =K30*$R$3 -> 61.315928 | S30: =K30*$S$3 -> 376.95221 | T30: =K30*$T$3 -> 14.044122 | U30: =K30*$U$3 -> 17.965404 | V30: =K30*$V$3 -> 6.670096 | W30: =K30*$W$3 -> 28.476006 | X30: =K30*$X$3 -> 50.770241 | Y30: =K30*$Y$3 -> 55.472149 | Z30: =K30*$Z$3 -> 81.030039 | AB30: =H30/$H$39 -> 0.01410816 | AC30: =AB30*$AC$3 -> 93.758597
B31: 610 | C31: CEO | H31: 9776.93 | J31: =H31/$I$35 -> 0.080905054 | K31: =H31/$I$37 -> 0.073665355 | L31: =J31*$L$3 -> 612.52569 | M31: =J31*$M$3 -> 143.25615 | N31: =J31*$N$3 -> 190.46506 | O31: =J31*$O$3 -> 34.917003 | P31: =J31*$P$3 -> 128.15765 | R31: =K31*$R$3 -> 221.43806 | S31: =K31*$S$3 -> 1361.3358 | T31: =K31*$T$3 -> 50.719334 | U31: =K31*$U$3 -> 64.880761 | V31: =K31*$V$3 -> 24.088571 | W31: =K31*$W$3 -> 102.83905 | X31: =K31*$X$3 -> 183.35307 | Y31: =K31*$Y$3 -> 200.33367 | Z31: =K31*$Z$3 -> 292.63415 | AB31: =H31/$H$39 -> 0.050950603 | AC31: =AB31*$AC$3 -> 338.60242
B32: 620 | C32: CFO | H32: 6769.23 | J32: =H32/$I$35 -> 0.056016042 | K32: =H32/$I$37 -> 0.051003508 | L32: =J32*$L$3 -> 424.09297 | M32: =J32*$M$3 -> 99.185925 | N32: =J32*$N$3 -> 131.87185 | O32: =J32*$O$3 -> 24.175403 | P32: =J32*$P$3 -> 88.732211 | R32: =K32*$R$3 -> 153.31655 | S32: =K32*$S$3 -> 942.54483 | T32: =K32*$T$3 -> 35.116426 | U32: =K32*$U$3 -> 44.92134 | V32: =K32*$V$3 -> 16.678147 | W32: =K32*$W$3 -> 71.202428 | X32: =K32*$X$3 -> 126.94773 | Y32: =K32*$Y$3 -> 138.70455 | Z32: =K32*$Z$3 -> 202.61042 | AB32: =H32/$H$39 -> 0.035276549 | AC32: =AB32*$AC$3 -> 234.43736
B33: 630 | C33: COO | H33: 0 | J33: =H33/$I$35 -> 0 | K33: =H33/$I$37 -> 0 | L33: =J33*$L$3 -> 0 | M33: =J33*$M$3 -> 0 | N33: =J33*$N$3 -> 0 | O33: =J33*$O$3 -> 0 | P33: =J33*$P$3 -> 0 | R33: =K33*$R$3 -> 0 | S33: =K33*$S$3 -> 0 | T33: =K33*$T$3 -> 0 | U33: =K33*$U$3 -> 0 | V33: =K33*$V$3 -> 0 | W33: =K33*$W$3 -> 0 | X33: =K33*$X$3 -> 0 | Y33: =K33*$Y$3 -> 0 | Z33: =K33*$Z$3 -> 0 | AB33: =H33/$H$39 -> 0 | AC33: =AB33*$AC$3 -> 0
B34: 650 | C34: Facilities | H34: 299 | J34: =H34/$I$35 -> 0.0024742543 | K34: =H34/$I$37 -> 0.0022528484 | L34: =J34*$L$3 -> 18.732381 | M34: =J34*$M$3 -> 4.3810879 | N34: =J34*$N$3 -> 5.82484 | O34: =J34*$O$3 -> 1.0678387 | P34: =J34*$P$3 -> 3.9193425 | R34: =K34*$R$3 -> 6.7720623 | S34: =K34*$S$3 -> 41.632638 | T34: =K34*$T$3 -> 1.5511087 | U34: =K34*$U$3 -> 1.9841962 | V34: =K34*$V$3 -> 0.73668143 | W34: =K34*$W$3 -> 3.145044 | X34: =K34*$X$3 -> 5.6073397 | Y34: =K34*$Y$3 -> 6.1266438 | Z34: =K34*$Z$3 -> 8.9493952 | AB34: =H34/$H$39 -> 0.0015581814 | AC34: =AB34*$AC$3 -> 10.355206
B35: 600 | C35: Admin | H35: 0.01 | I35: =SUM(H6:H34) -> 120844.49 | J35: =H35/$I$35 -> 8.275098e-08 | K35: =H35/$I$37 -> 7.53461e-08 | L35: =J35*$L$3 -> 0.00062650105 | M35: =J35*$M$3 -> 0.00014652468 | N35: =J35*$N$3 -> 0.0001948107 | O35: =J35*$O$3 -> 3.5713668e-05 | P35: =J35*$P$3 -> 0.00013108169 | R35: =K35*$R$3 -> 0.00022649038 | S35: =K35*$S$3 -> 0.0013923959 | T35: =K35*$T$3 -> 5.1876544e-05 | U35: =K35*$U$3 -> 6.6361078e-05 | V35: =K35*$V$3 -> 2.4638175e-05 | W35: =K35*$W$3 -> 0.00010518542 | X35: =K35*$X$3 -> 0.00018753644 | Y35: =K35*$Y$3 -> 0.00020490447 | Z35: =K35*$Z$3 -> 0.00029931088 | AB35: =H35/$H$39 -> 5.2113089e-08 | AC35: =AB35*$AC$3 -> 0.00034632796
B36: 339 | C36: Opport Corp | H36: 5538.46 | K36: =H36/$I$37 -> 0.041730136 | L36: =J36*$L$3 -> 0 | M36: =J36*$M$3 -> 0 | N36: =J36*$N$3 -> 0 | O36: =J36*$O$3 -> 0 | P36: =J36*$P$3 -> 0 | R36: =K36*$R$3 -> 125.44079 | S36: =K36*$S$3 -> 771.17292 | T36: =K36*$T$3 -> 28.731616 | U36: =K36*$U$3 -> 36.753818 | V36: =K36*$V$3 -> 13.645755 | W36: =K36*$W$3 -> 58.256522 | X36: =K36*$X$3 -> 103.86631 | Y36: =K36*$Y$3 -> 113.48552 | Z36: =K36*$Z$3 -> 165.77213 | AB36: =U42/$H$39 -> 0.028862626 | AC36: =AB36*$AC$3 -> 191.81235
B37: 225 | C37: AmeriCorp | H37: 6337.92 | I37: =I35+H36+H37 -> 132720.87 | K37: =H37/$I$37 -> 0.047753756 | R37: =K37*$R$3 -> 143.54779 | S37: =K37*$S$3 -> 882.48941 | T37: =K37*$T$3 -> 32.878938 | U37: =K37*$U$3 -> 42.05912 | V37: =K37*$V$3 -> 15.615478 | W37: =K37*$W$3 -> 66.665676 | X37: =K37*$X$3 -> 118.8591 | Y37: =K37*$Y$3 -> 129.86682 | Z37: =K37*$Z$3 -> 189.70084 | AB37: =U43/$H$39 -> 0.033028859 | AC37: =AB37*$AC$3 -> 219.49989
B38: 451 | C38: USJP - Participants | H38: 59169.49 | AB38: =H38/$H$39 -> 0.30835049 | AC38: =AB38*$AC$3 -> 2049.2049
H39: =SUM(H6:H38) -> 191890.37 | J39: =SUM(J6:J38) -> 1.0000001 | K39: =SUM(K6:K38) -> 1.0000001 | L39: =SUM(L6:L38) -> 7570.9206 | M39: =SUM(M6:M38) -> 1770.6701 | N39: =SUM(N6:N38) -> 2354.1802 | O39: =SUM(O6:O38) -> 431.58004 | P39: =SUM(P6:P38) -> 1584.0501 | Q39: =SUM(Q6:Q38) -> 0 | ... AC39: =SUM(AC6:AC38) -> 6645.7
H40: Salary | J40: Hourly | L40: =L3-L39 -> -0.00062650105 | M40: =M3-M39 -> -0.00014652468 | N40: =N3-N39 -> -0.0001948107 | O40: =O3-O39 -> -3.5713668e-05 | P40: =P3-P39 -> -0.00013108169 | Q40: =Q3-Q39 -> 0 | R40: =R3-R39 -> -0.00022649038 | S40: =S3-S39 -> -0.0013923959 | ... AC40: =AC3-AC39 -> 0
C41: 43658 | H41: 65009 | L41: 3872.3 | M41: 905.65 | N41: 1253.04 | O41: 229.72
C42: 43675 | H42: 61825.69 | J42: 0 | L42: 3698.62 | M42: 865.02 | N42: 1101.14 | O42: 201.86 | U42: 5538.46
C43: June Accrual | H43: -5990.2 | U43: 6337.92
H44: =SUM(H41:H43) -> 120844.49 | L44: =SUM(L41:L42) -> 7570.92 | M44: =SUM(M41:M42) -> 1770.67 | N44: =SUM(N41:N42) -> 2354.18 | O44: =SUM(O41:O42) -> 431.58 | P44: =SUM(P41:P42) -> 0
H45: =H38 -> 59169.49 | AG45: 114.44
B46: Americorp | I46: Opp Corp | J46: Americ | L46: 196.5 | M46: 45.96 | P46: =SUM(L46:O46) -> 242.46 | AG46: 151.65
F47: =I35-H43 -> 126834.69 | L47: 229.25 | M47: 53.62 | P47: =SUM(L47:O47) -> 282.87 | R47: =SUM(P46:P47) -> 525.33 | S47: =R47+'May 2019 Alloc '!N58+'April 2019 Alloc '!R45 -> 2303.36
B48: Opport Corp | H48: 43630 | I48: 2769.23 | J48: 3697.12 | L48: 165.08 | M48: 38.61 | N48: 83.08 | O48: 15.23
H49: 43644 | I49: 2769.23 | J49: 3168.96 | L49: 165.08 | M49: 38.61 | N49: 83.08 | O49: 15.23
I52: =SUM(I48:I51) -> 5538.46 | J52: =SUM(J48:J51) -> 6866.08
J54: =J52+'May 2019 Alloc '!I60+'April 2019 Alloc '!H44+'April 2019 Alloc '!H45 -> 30105.11

Sheet July 2019 Alloc
B1: July Cost Allocations | L1: 7251 | M1: 7252 | N1: 7253 | O1: 7254 | P1: 7260.1 | R1: 7515.5 | S1: 7521 | T1: 8112 | U1: 8135.5 | V1: 8191 | W1: 8210.5 | X1: 8229.1 | Y1: 8239 | Z1: 8266 | AC1: 7248
L2: FICA | M2: MEDI | N2: SUI | O2: Disability | P2: Payroll Fees | R2: IT Consultants | S2: Acctg Fees | T2: Supplies | U2: Telephone | V2: Web Hosting | W2: Utilities | X2: Eq Lease | Y2: Repairs | Z2: General Insurance | AC2: W/ Comp
L3: =L44 -> 7570.92 | M3: =M44 -> 1770.67 | N3: =N44 -> 2354.18 | O3: =O44 -> 431.58 | P3: 1584.05 | R3: 3006 | S3: 18480 | T3: 688.51 | U3: 880.75 | V3: 327 | W3: 1396.03 | X3: 2489 | Y3: 2719.51 | Z3: 3972.48 | AC3: 6645.7
L4: 1 | M4: 2 | N4: 3 | O4: 4 | P4: 5 | Q4: 6 | R4: 15 | S4: 9 | T4: 7 | U4: 11 | V4: 16 | W4: 10 | X4: 8 | Y4: 13 | Z4: 14 | AC4: 0.04
D5: 7222 | E5: Taxes | F5: W/C | J5: Taxes | K5: Expenses
B6: 41 | C6: Thriftworks | H6: 3538.46 | J6: =H6/$I$35 -> 0.029242944 | K6: =H6/$I$37 -> 0.026629277 | L6: =J6*$L$3 -> 221.39599 | M6: =J6*$M$3 -> 51.779604 | N6: =J6*$N$3 -> 68.843154 | O6: =J6*$O$3 -> 12.62067 | P6: =J6*$P$3 -> 46.322286 | R6: =K6*$R$3 -> 80.047607 | S6: =K6*$S$3 -> 492.10904 | T6: =K6*$T$3 -> 18.334524 | U6: =K6*$U$3 -> 23.453736 | V6: =K6*$V$3 -> 8.7077736 | W6: =K6*$W$3 -> 37.17527 | X6: =K6*$X$3 -> 66.280271 | Y6: =K6*$Y$3 -> 72.418585 | Z6: =K6*$Z$3 -> 105.78427 | AB6: =H6/$H$39 -> 0.018424867 | AC6: =AB6*$AC$3 -> 122.44614
B7: 111 | C7: Abbott | H7: 9375.24 | J7: =H7/$I$35 -> 0.077479926 | K7: =H7/$I$37 -> 0.070554949 | L7: =J7*$L$3 -> 586.59432 | M7: =J7*$M$3 -> 137.19138 | N7: =J7*$N$3 -> 182.40169 | O7: =J7*$O$3 -> 33.438787 | P7: =J7*$P$3 -> 122.73208 | R7: =K7*$R$3 -> 212.08818 | S7: =K7*$S$3 -> 1303.8555 | T7: =K7*$T$3 -> 48.577788 | U7: =K7*$U$3 -> 62.141271 | V7: =K7*$V$3 -> 23.071468 | W7: =K7*$W$3 -> 98.496825 | X7: =K7*$X$3 -> 175.61127 | Y7: =K7*$Y$3 -> 191.87489 | Z7: =K7*$Z$3 -> 280.27812 | AB7: =H7/$H$39 -> 0.048817155 | AC7: =AB7*$AC$3 -> 324.42417
B8: 111A | C8: Abbott - Other | H8: 1238.46 | J8: =H8/$I$35 -> 0.010235022 | K8: =H8/$I$37 -> 0.0093202395 | L8: =J8*$L$3 -> 77.488534 | M8: =J8*$M$3 -> 18.122847 | N8: =J8*$N$3 -> 24.095085 | O8: =J8*$O$3 -> 4.4172309 | P8: =J8*$P$3 -> 16.212787 | R8: =K8*$R$3 -> 28.01664 | S8: =K8*$S$3 -> 172.23803 | T8: =K8*$T$3 -> 6.4170781 | U8: =K8*$U$3 -> 8.2088009 | V8: =K8*$V$3 -> 3.0477183 | W8: =K8*$W$3 -> 13.011334 | X8: =K8*$X$3 -> 23.198076 | Y8: =K8*$Y$3 -> 25.346484 | Z8: =K8*$Z$3 -> 37.024465 | AB8: =H8/$H$39 -> 0.0064486983 | AC8: =AB8*$AC$3 -> 42.856114
B9: 111B | C9: Abbott Fees | H9: 0 | J9: =H9/$I$35 -> 0 | K9: =H9/$I$37 -> 0 | L9: =J9*$L$3 -> 0 | M9: =J9*$M$3 -> 0 | N9: =J9*$N$3 -> 0 | O9: =J9*$O$3 -> 0 | P9: =J9*$P$3 -> 0 | R9: =K9*$R$3 -> 0 | S9: =K9*$S$3 -> 0 | T9: =K9*$T$3 -> 0 | U9: =K9*$U$3 -> 0 | V9: =K9*$V$3 -> 0 | W9: =K9*$W$3 -> 0 | X9: =K9*$X$3 -> 0 | Y9: =K9*$Y$3 -> 0 | Z9: =K9*$Z$3 -> 0 | AB9: =H9/$H$39 -> 0 | AC9: =AB9*$AC$3 -> 0
B10: 111F | C10: Abbott Food | H10: 0 | J10: =H10/$I$35 -> 0 | K10: =H10/$I$37 -> 0 | L10: =J10*$L$3 -> 0 | M10: =J10*$M$3 -> 0 | N10: =J10*$N$3 -> 0 | O10: =J10*$O$3 -> 0 | P10: =J10*$P$3 -> 0 | R10: =K10*$R$3 -> 0 | S10: =K10*$S$3 -> 0 | T10: =K10*$T$3 -> 0 | U10: =K10*$U$3 -> 0 | V10: =K10*$V$3 -> 0 | W10: =K10*$W$3 -> 0 | X10: =K10*$X$3 -> 0 | Y10: =K10*$Y$3 -> 0 | Z10: =K10*$Z$3 -> 0 | AB10: =H10/$H$39 -> 0 | AC10: =AB10*$AC$3 -> 0
B11: 112 | C11: EHS | H11: 26864.05 | J11: =H11/$I$35 -> 0.22201294 | K11: =H11/$I$37 -> 0.20216994 | L11: =J11*$L$3 -> 1680.8422 | M11: =J11*$M$3 -> 393.11166 | N11: =J11*$N$3 -> 522.65843 | O11: =J11*$O$3 -> 95.816346 | P11: =J11*$P$3 -> 351.6796 | R11: =K11*$R$3 -> 607.72283 | S11: =K11*$S$3 -> 3736.1004 | T11: =K11*$T$3 -> 139.19602 | U11: =K11*$U$3 -> 178.06117 | V11: =K11*$V$3 -> 66.109569 | W11: =K11*$W$3 -> 282.2353 | X11: =K11*$X$3 -> 503.20097 | Y11: =K11*$Y$3 -> 549.80316 | Z11: =K11*$Z$3 -> 803.11603 | AB11: =H11/$H$39 -> 0.13988191 | AC11: =AB11*$AC$3 -> 929.61323
B12: 114 | C12: Summer Camp | H12: 11979.83 | J12: =H12/$I$35 -> 0.099005076 | K12: =H12/$I$37 -> 0.09015623 | L12: =J12*$L$3 -> 749.55951 | M12: =J12*$M$3 -> 175.30532 | N12: =J12*$N$3 -> 233.07577 | O12: =J12*$O$3 -> 42.728611 | P12: =J12*$P$3 -> 156.82899 | R12: =K12*$R$3 -> 271.00963 | S12: =K12*$S$3 -> 1666.0871 | T12: =K12*$T$3 -> 62.073466 | U12: =K12*$U$3 -> 79.405099 | V12: =K12*$V$3 -> 29.481087 | W12: =K12*$W$3 -> 125.8608 | X12: =K12*$X$3 -> 224.39886 | Y12: =K12*$Y$3 -> 245.18077 | Z12: =K12*$Z$3 -> 358.14382 | AB12: =H12/$H$39 -> 0.062379334 | AC12: =AB12*$AC$3 -> 414.55434
B13: 222 | C13: DCF- Coding | H13: 2480.65 | J13: =H13/$I$35 -> 0.02050087 | K13: =H13/$I$37 -> 0.01866855 | L13: =J13*$L$3 -> 155.21045 | M13: =J13*$M$3 -> 36.300276 | N13: =J13*$N$3 -> 48.262739 | O13: =J13*$O$3 -> 8.8477656 | P13: =J13*$P$3 -> 32.474404 | R13: =K13*$R$3 -> 56.11766 | S13: =K13*$S$3 -> 344.9948 | T13: =K13*$T$3 -> 12.853483 | U13: =K13*$U$3 -> 16.442325 | V13: =K13*$V$3 -> 6.1046157 | W13: =K13*$W$3 -> 26.061855 | X13: =K13*$X$3 -> 46.46602 | Y13: =K13*$Y$3 -> 50.769308 | Z13: =K13*$Z$3 -> 74.16044 | AB13: =H13/$H$39 -> 0.012916819 | AC13: =AB13*$AC$3 -> 85.841303
B14: 223 | C14: OICA | H14: 0 | J14: =H14/$I$35 -> 0 | K14: =H14/$I$37 -> 0 | L14: =J14*$L$3 -> 0 | M14: =J14*$M$3 -> 0 | N14: =J14*$N$3 -> 0 | O14: =J14*$O$3 -> 0 | P14: =J14*$P$3 -> 0 | R14: =K14*$R$3 -> 0 | S14: =K14*$S$3 -> 0 | T14: =K14*$T$3 -> 0 | U14: =K14*$U$3 -> 0 | V14: =K14*$V$3 -> 0 | W14: =K14*$W$3 -> 0 | X14: =K14*$X$3 -> 0 | Y14: =K14*$Y$3 -> 0 | Z14: =K14*$Z$3 -> 0 | AB14: =H14/$H$39 -> 0 | AC14: =AB14*$AC$3 -> 0
B15: 334 | C15: NRTC - Admin | H15: 2146.15 | J15: =H15/$I$35 -> 0.017736457 | K15: =H15/$I$37 -> 0.016151214 | L15: =J15*$L$3 -> 134.2813 | M15: =J15*$M$3 -> 31.405413 | N15: =J15*$N$3 -> 41.754813 | O15: =J15*$O$3 -> 7.6547002 | P15: =J15*$P$3 -> 28.095435 | R15: =K15*$R$3 -> 48.550548 | S15: =K15*$S$3 -> 298.47443 | T15: =K15*$T$3 -> 11.120272 | U15: =K15*$U$3 -> 14.225181 | V15: =K15*$V$3 -> 5.2814468 | W15: =K15*$W$3 -> 22.547579 | X15: =K15*$X$3 -> 40.200371 | Y15: =K15*$Y$3 -> 43.923387 | Z15: =K15*$Z$3 -> 64.160373 | AB15: =H15/$H$39 -> 0.011175067 | AC15: =AB15*$AC$3 -> 74.266145
B16: 334H | C16: NRTC - Housing | H16: 3225.25 | J16: =H16/$I$35 -> 0.026654478 | K16: =H16/$I$37 -> 0.024272162 | L16: =J16*$L$3 -> 201.79892 | M16: =J16*$M$3 -> 47.196285 | N16: =J16*$N$3 -> 62.74944 | O16: =J16*$O$3 -> 11.50354 | P16: =J16*$P$3 -> 42.222027 | R16: =K16*$R$3 -> 72.96212 | S16: =K16*$S$3 -> 448.54956 | T16: =K16*$T$3 -> 16.711627 | U16: =K16*$U$3 -> 21.377707 | V16: =K16*$V$3 -> 7.9369971 | W16: =K16*$W$3 -> 33.884667 | X16: =K16*$X$3 -> 60.413412 | Y16: =K16*$Y$3 -> 66.008389 | Z16: =K16*$Z$3 -> 96.42068 | AB16: =H16/$H$39 -> 0.016793973 | AC16: =AB16*$AC$3 -> 111.60771
B17: 334F | C17: NRTC FOC | H17: 230.77 | J17: =H17/$I$35 -> 0.0019071557 | K17: =H17/$I$37 -> 0.0017366985 | L17: =J17*$L$3 -> 14.438923 | M17: =J17*$M$3 -> 3.3769434 | N17: =J17*$N$3 -> 4.4897879 | O17: =J17*$O$3 -> 0.82309027 | P17: =J17*$P$3 -> 3.02103 | R17: =K17*$R$3 -> 5.2205158 | S17: =K17*$S$3 -> 32.094189 | T17: =K17*$T$3 -> 1.1957343 | U17: =K17*$U$3 -> 1.5295972 | V17: =K17*$V$3 -> 0.56790042 | W17: =K17*$W$3 -> 2.4244833 | X17: =K17*$X$3 -> 4.3226426 | Y17: =K17*$Y$3 -> 4.722969 | Z17: =K17*$Z$3 -> 6.8990002 | AB17: =H17/$H$39 -> 0.0012016263 | AC17: =AB17*$AC$3 -> 7.9856479
B18: 335 | C18: NRTC 19 | H18: 3134.45 | J18: =H18/$I$35 -> 0.025904079 | K18: =H18/$I$37 -> 0.023588832 | L18: =J18*$L$3 -> 196.11771 | M18: =J18*$M$3 -> 45.867575 | N18: =J18*$N$3 -> 60.982864 | O18: =J18*$O$3 -> 11.179682 | P18: =J18*$P$3 -> 41.033356 | R18: =K18*$R$3 -> 70.908028 | S18: =K18*$S$3 -> 435.92161 | T18: =K18*$T$3 -> 16.241147 | U18: =K18*$U$3 -> 20.775864 | V18: =K18*$V$3 -> 7.713548 | W18: =K18*$W$3 -> 32.930717 | X18: =K18*$X$3 -> 58.712602 | Y18: =K18*$Y$3 -> 64.150064 | Z18: =K18*$Z$3 -> 93.706162 | AB18: =H18/$H$39 -> 0.016321175 | AC18: =AB18*$AC$3 -> 108.46563
B19: 368 | C19: Wells Fargo | H19: 2615.2 | J19: =H19/$I$35 -> 0.021612834 | K19: =H19/$I$37 -> 0.019681128 | L19: =J19*$L$3 -> 163.62904 | M19: =J19*$M$3 -> 38.269196 | N19: =J19*$N$3 -> 50.880501 | O19: =J19*$O$3 -> 9.3276668 | P19: =J19*$P$3 -> 34.235809 | R19: =K19*$R$3 -> 59.161472 | S19: =K19*$S$3 -> 363.70725 | T19: =K19*$T$3 -> 13.550654 | U19: =K19*$U$3 -> 17.334154 | V19: =K19*$V$3 -> 6.435729 | W19: =K19*$W$3 -> 27.475446 | X19: =K19*$X$3 -> 48.986329 | Y19: =K19*$Y$3 -> 53.523025 | Z19: =K19*$Z$3 -> 78.182889 | AB19: =H19/$H$39 -> 0.013617425 | AC19: =AB19*$AC$3 -> 90.497319
B20: 451 | C20: USJP | H20: 10746.79 | J20: =H20/$I$35 -> 0.088814846 | K20: =H20/$I$37 -> 0.08087678 | L20: =J20*$L$3 -> 672.41009 | M20: =J20*$M$3 -> 157.26178 | N20: =J20*$N$3 -> 209.08613 | O20: =J20*$O$3 -> 38.330711 | P20: =J20*$P$3 -> 140.68716 | R20: =K20*$R$3 -> 243.1156 | S20: =K20*$S$3 -> 1494.6029 | T20: =K20*$T$3 -> 55.684471 | U20: =K20*$U$3 -> 71.232224 | V20: =K20*$V$3 -> 26.446707 | W20: =K20*$W$3 -> 112.90641 | X20: =K20*$X$3 -> 201.3023 | Y20: =K20*$Y$3 -> 219.94521 | Z20: =K20*$Z$3 -> 321.28139 | AB20: =H20/$H$39 -> 0.055958857 | AC20: =AB20*$AC$3 -> 371.88578
B21: 452 | C21: PACE | J21: =H21/$I$35 -> 0 | K21: =H21/$I$37 -> 0 | L21: =J21*$L$3 -> 0 | M21: =J21*$M$3 -> 0 | N21: =J21*$N$3 -> 0 | O21: =J21*$O$3 -> 0 | P21: =J21*$P$3 -> 0 | R21: =K21*$R$3 -> 0 | S21: =K21*$S$3 -> 0 | T21: =K21*$T$3 -> 0 | U21: =K21*$U$3 -> 0 | V21: =K21*$V$3 -> 0 | W21: =K21*$W$3 -> 0 | X21: =K21*$X$3 -> 0 | Y21: =K21*$Y$3 -> 0 | Z21: =K21*$Z$3 -> 0 | AB21: =H21/$H$39 -> 0 | AC21: =AB21*$AC$3 -> 0
B22: 454 | C22: Prudential #1 Workforce | K22: =H22/$I$37 -> 0 | R22: =K22*$R$3 -> 0 | S22: =K22*$S$3 -> 0 | T22: =K22*$T$3 -> 0 | U22: =K22*$U$3 -> 0 | V22: =K22*$V$3 -> 0 | W22: =K22*$W$3 -> 0 | X22: =K22*$X$3 -> 0 | Y22: =K22*$Y$3 -> 0 | Z22: =K22*$Z$3 -> 0
B23: 467 | C23: WF - United Airlines | H23: 6576.94 | J23: =H23/$I$35 -> 0.054353897 | K23: =H23/$I$37 -> 0.049495871 | L23: =J23*$L$3 -> 411.509 | M23: =J23*$M$3 -> 96.242814 | N23: =J23*$N$3 -> 127.95886 | O23: =J23*$O$3 -> 23.458055 | P23: =J23*$P$3 -> 86.09929 | R23: =K23*$R$3 -> 148.78459 | S23: =K23*$S$3 -> 914.68369 | T23: =K23*$T$3 -> 34.078402 | U23: =K23*$U$3 -> 43.593488 | V23: =K23*$V$3 -> 16.18515 | W23: =K23*$W$3 -> 69.09772 | X23: =K23*$X$3 -> 123.19522 | Y23: =K23*$Y$3 -> 134.60451 | Z23: =K23*$Z$3 -> 196.62136 | AB23: =H23/$H$39 -> 0.034246324 | AC23: =AB23*$AC$3 -> 227.59079
B24: 468 | C24: Newark Alliance | H24: 6307.7 | J24: =H24/$I$35 -> 0.052128813 | K24: =H24/$I$37 -> 0.04746966 | L24: =J24*$L$3 -> 394.66307 | M24: =J24*$M$3 -> 92.302925 | N24: =J24*$N$3 -> 122.72061 | O24: =J24*$O$3 -> 22.497753 | P24: =J24*$P$3 -> 82.574646 | R24: =K24*$R$3 -> 142.6938 | S24: =K24*$S$3 -> 877.23931 | T24: =K24*$T$3 -> 32.683335 | U24: =K24*$U$3 -> 41.808903 | V24: =K24*$V$3 -> 15.522579 | W24: =K24*$W$3 -> 66.269069 | X24: =K24*$X$3 -> 118.15198 | Y24: =K24*$Y$3 -> 129.09421 | Z24: =K24*$Z$3 -> 188.57227 | AB24: =H24/$H$39 -> 0.032844383 | AC24: =AB24*$AC$3 -> 218.27391
B25: 502 | C25: ESG | H25: 1636.38 | J25: =H25/$I$35 -> 0.013523558 | K25: =H25/$I$37 -> 0.012314854 | L25: =J25*$L$3 -> 102.38578 | M25: =J25*$M$3 -> 23.945758 | N25: =J25*$N$3 -> 31.83689 | O25: =J25*$O$3 -> 5.8364972 | P25: =J25*$P$3 -> 21.421992 | R25: =K25*$R$3 -> 37.01845 | S25: =K25*$S$3 -> 227.57849 | T25: =K25*$T$3 -> 8.4788998 | U25: =K25*$U$3 -> 10.846307 | V25: =K25*$V$3 -> 4.0269571 | W25: =K25*$W$3 -> 17.191905 | X25: =K25*$X$3 -> 30.65167 | Y25: =K25*$Y$3 -> 33.490367 | Z25: =K25*$Z$3 -> 48.920509 | AB25: =H25/$H$39 -> 0.0085206797 | AC25: =AB25*$AC$3 -> 56.625881
B26: 515 | C26: FOC - HUD NUL PARS | H26: 2749.65 | J26: =H26/$I$35 -> 0.022723971 | K26: =H26/$I$37 -> 0.020692955 | L26: =J26*$L$3 -> 172.04136 | M26: =J26*$M$3 -> 40.236653 | N26: =J26*$N$3 -> 53.496317 | O26: =J26*$O$3 -> 9.8072113 | P26: =J26*$P$3 -> 35.995906 | R26: =K26*$R$3 -> 62.203021 | S26: =K26*$S$3 -> 382.4058 | T26: =K26*$T$3 -> 14.247306 | U26: =K26*$U$3 -> 18.22532 | V26: =K26*$V$3 -> 6.7665961 | W26: =K26*$W$3 -> 28.887985 | X26: =K26*$X$3 -> 51.504764 | Y26: =K26*$Y$3 -> 56.274697 | Z26: =K26*$Z$3 -> 82.202348 | AB26: =H26/$H$39 -> 0.01431751 | AC26: =AB26*$AC$3 -> 95.149876
B27: 525 | C27: CDBG - Housing | H27: 115.39 | J27: =H27/$I$35 -> 0.00095361918 | K27: =H27/$I$37 -> 0.00086838689 | L27: =J27*$L$3 -> 7.2197745 | M27: =J27*$M$3 -> 1.6885449 | N27: =J27*$N$3 -> 2.2449912 | O27: =J27*$O$3 -> 0.41156297 | P27: =J27*$P$3 -> 1.5105805 | R27: =K27*$R$3 -> 2.610371 | S27: =K27*$S$3 -> 16.04779 | T27: =K27*$T$3 -> 0.59789306 | U27: =K27*$U$3 -> 0.76483176 | V27: =K27*$V$3 -> 0.28396251 | W27: =K27*$W$3 -> 1.2122942 | X27: =K27*$X$3 -> 2.161415 | Y27: =K27*$Y$3 -> 2.3615868 | Z27: =K27*$Z$3 -> 3.4496496 | AB27: =H27/$H$39 -> 0.00060083919 | AC27: =AB27*$AC$3 -> 3.992997
B28: 560 | C28: CAP 1 - Save Up | H28: 230.77 | J28: =H28/$I$35 -> 0.0019071557 | K28: =H28/$I$37 -> 0.0017366985 | L28: =J28*$L$3 -> 14.438923 | M28: =J28*$M$3 -> 3.3769434 | N28: =J28*$N$3 -> 4.4897879 | O28: =J28*$O$3 -> 0.82309027 | P28: =J28*$P$3 -> 3.02103 | R28: =K28*$R$3 -> 5.2205158 | S28: =K28*$S$3 -> 32.094189 | T28: =K28*$T$3 -> 1.1957343 | U28: =K28*$U$3 -> 1.5295972 | V28: =K28*$V$3 -> 0.56790042 | W28: =K28*$W$3 -> 2.4244833 | X28: =K28*$X$3 -> 4.3226426 | Y28: =K28*$Y$3 -> 4.722969 | Z28: =K28*$Z$3 -> 6.8990002 | AB28: =H28/$H$39 -> 0.0012016263 | AC28: =AB28*$AC$3 -> 7.9856479
B29: 564 | C29: LISC FOC 2019 | H29: 6444.24 | J29: =H29/$I$35 -> 0.053257222 | K29: =H29/$I$37 -> 0.048497214 | L29: =J29*$L$3 -> 403.20617 | M29: =J29*$M$3 -> 94.300966 | N29: =J29*$N$3 -> 125.37709 | O29: =J29*$O$3 -> 22.984752 | P29: =J29*$P$3 -> 84.362103 | R29: =K29*$R$3 -> 145.78263 | S29: =K29*$S$3 -> 896.22852 | T29: =K29*$T$3 -> 33.390817 | U29: =K29*$U$3 -> 42.713921 | V29: =K29*$V$3 -> 15.858589 | W29: =K29*$W$3 -> 67.703566 | X29: =K29*$X$3 -> 120.70957 | Y29: =K29*$Y$3 -> 131.88866 | Z29: =K29*$Z$3 -> 192.65421 | AB29: =H29/$H$39 -> 0.033555351 | AC29: =AB29*$AC$3 -> 222.99879
B30: 563 | C30: Prudential #1 FOC | H30: 2520.65 | J30: =H30/$I$35 -> 0.020831443 | K30: =H30/$I$37 -> 0.018969576 | L30: =J30*$L$3 -> 157.71319 | M30: =J30*$M$3 -> 36.885611 | N30: =J30*$N$3 -> 49.040966 | O30: =J30*$O$3 -> 8.9904341 | P30: =J30*$P$3 -> 32.998047 | R30: =K30*$R$3 -> 57.022547 | S30: =K30*$S$3 -> 350.55777 | T30: =K30*$T$3 -> 13.060743 | U30: =K30*$U$3 -> 16.707454 | V30: =K30*$V$3 -> 6.2030515 | W30: =K30*$W$3 -> 26.482098 | X30: =K30*$X$3 -> 47.215276 | Y30: =K30*$Y$3 -> 51.587953 | Z30: =K30*$Z$3 -> 75.356263 | AB30: =H30/$H$39 -> 0.0131251 | AC30: =AB30*$AC$3 -> 87.225477
B31: 610 | C31: CEO | H31: 9776.93 | J31: =H31/$I$35 -> 0.080799619 | K31: =H31/$I$37 -> 0.073577935 | L31: =J31*$L$3 -> 611.72745 | M31: =J31*$M$3 -> 143.06946 | N31: =J31*$N$3 -> 190.21685 | O31: =J31*$O$3 -> 34.871499 | P31: =J31*$P$3 -> 127.99064 | R31: =K31*$R$3 -> 221.17527 | S31: =K31*$S$3 -> 1359.7202 | T31: =K31*$T$3 -> 50.659144 | U31: =K31*$U$3 -> 64.803766 | V31: =K31*$V$3 -> 24.059985 | W31: =K31*$W$3 -> 102.717 | X31: =K31*$X$3 -> 183.13548 | Y31: =K31*$Y$3 -> 200.09593 | Z31: =K31*$Z$3 -> 292.28687 | AB31: =H31/$H$39 -> 0.050908767 | AC31: =AB31*$AC$3 -> 338.32439
B32: 620 | C32: CFO | H32: 6769.23 | J32: =H32/$I$35 -> 0.055943042 | K32: =H32/$I$37 -> 0.050942981 | L32: =J32*$L$3 -> 423.54029 | M32: =J32*$M$3 -> 99.056666 | N32: =J32*$N$3 -> 131.69999 | O32: =J32*$O$3 -> 24.143898 | P32: =J32*$P$3 -> 88.616575 | R32: =K32*$R$3 -> 153.1346 | S32: =K32*$S$3 -> 941.42629 | T32: =K32*$T$3 -> 35.074752 | U32: =K32*$U$3 -> 44.868031 | V32: =K32*$V$3 -> 16.658355 | W32: =K32*$W$3 -> 71.11793 | X32: =K32*$X$3 -> 126.79708 | Y32: =K32*$Y$3 -> 138.53995 | Z32: =K32*$Z$3 -> 202.36997 | AB32: =H32/$H$39 -> 0.035247583 | AC32: =AB32*$AC$3 -> 234.24486
B33: 630 | C33: COO | H33: 0 | J33: =H33/$I$35 -> 0 | K33: =H33/$I$37 -> 0 | L33: =J33*$L$3 -> 0 | M33: =J33*$M$3 -> 0 | N33: =J33*$N$3 -> 0 | O33: =J33*$O$3 -> 0 | P33: =J33*$P$3 -> 0 | R33: =K33*$R$3 -> 0 | S33: =K33*$S$3 -> 0 | T33: =K33*$T$3 -> 0 | U33: =K33*$U$3 -> 0 | V33: =K33*$V$3 -> 0 | W33: =K33*$W$3 -> 0 | X33: =K33*$X$3 -> 0 | Y33: =K33*$Y$3 -> 0 | Z33: =K33*$Z$3 -> 0 | AB33: =H33/$H$39 -> 0 | AC33: =AB33*$AC$3 -> 0
B34: 650 | C34: Facilities | H34: 299 | J34: =H34/$I$35 -> 0.0024710299 | K34: =H34/$I$37 -> 0.0022501749 | L34: =J34*$L$3 -> 18.707969 | M34: =J34*$M$3 -> 4.3753784 | N34: =J34*$N$3 -> 5.8172491 | O34: =J34*$O$3 -> 1.0664471 | P34: =J34*$P$3 -> 3.9142349 | R34: =K34*$R$3 -> 6.7640257 | S34: =K34*$S$3 -> 41.583232 | T34: =K34*$T$3 -> 1.5492679 | U34: =K34*$U$3 -> 1.9818415 | V34: =K34*$V$3 -> 0.73580719 | W34: =K34*$W$3 -> 3.1413117 | X34: =K34*$X$3 -> 5.6006853 | Y34: =K34*$Y$3 -> 6.1193731 | Z34: =K34*$Z$3 -> 8.9387748 | AB34: =H34/$H$39 -> 0.001556902 | AC34: =AB34*$AC$3 -> 10.346703
B35: 600 | C35: Admin | H35: 0.01 | I35: =SUM(H6:H34) -> 121002.18 | J35: =H35/$I$35 -> 8.2643139e-08 | K35: =H35/$I$37 -> 7.5256686e-08 | L35: =J35*$L$3 -> 0.0006256846 | M35: =J35*$M$3 -> 0.00014633373 | N35: =J35*$N$3 -> 0.00019455683 | O35: =J35*$O$3 -> 3.5667126e-05 | P35: =J35*$P$3 -> 0.00013091086 | R35: =K35*$R$3 -> 0.0002262216 | S35: =K35*$S$3 -> 0.0013907435 | T35: =K35*$T$3 -> 5.1814981e-05 | U35: =K35*$U$3 -> 6.6282326e-05 | V35: =K35*$V$3 -> 2.4608936e-05 | W35: =K35*$W$3 -> 0.00010506059 | X35: =K35*$X$3 -> 0.00018731389 | Y35: =K35*$Y$3 -> 0.00020466131 | Z35: =K35*$Z$3 -> 0.00029895568 | AB35: =H35/$H$39 -> 5.2070299e-08 | AC35: =AB35*$AC$3 -> 0.00034604359
B36: 339 | C36: Opport Corp | H36: 5538.46 | K36: =H36/$I$37 -> 0.041680614 | L36: =J36*$L$3 -> 0 | M36: =J36*$M$3 -> 0 | N36: =J36*$N$3 -> 0 | O36: =J36*$O$3 -> 0 | P36: =J36*$P$3 -> 0 | R36: =K36*$R$3 -> 125.29193 | S36: =K36*$S$3 -> 770.25775 | T36: =K36*$T$3 -> 28.69752 | U36: =K36*$U$3 -> 36.710201 | V36: =K36*$V$3 -> 13.629561 | W36: =K36*$W$3 -> 58.187388 | X36: =K36*$X$3 -> 103.74305 | Y36: =K36*$Y$3 -> 113.35085 | Z36: =K36*$Z$3 -> 165.57541 | AB36: =U42/$H$39 -> 0.028838927 | AC36: =AB36*$AC$3 -> 191.65486
B37: 225 | C37: AmeriCorp | H37: 6337.92 | I37: =I35+H36+H37 -> 132878.56 | K37: =H37/$I$37 -> 0.047697085 | R37: =K37*$R$3 -> 143.37744 | S37: =K37*$S$3 -> 881.44213 | T37: =K37*$T$3 -> 32.83992 | U37: =K37*$U$3 -> 42.009208 | V37: =K37*$V$3 -> 15.596947 | W37: =K37*$W$3 -> 66.586562 | X37: =K37*$X$3 -> 118.71805 | Y37: =K37*$Y$3 -> 129.7127 | Z37: =K37*$Z$3 -> 189.47572 | AB37: =U43/$H$39 -> 0.033001739 | AC37: =AB37*$AC$3 -> 219.31966
B38: 451 | C38: USJP - Participants | H38: 59169.49 | AB38: =H38/$H$39 -> 0.30809731 | AC38: =AB38*$AC$3 -> 2047.5223
H39: =SUM(H6:H38) -> 192048.06 | J39: =SUM(J6:J38) -> 1.0000001 | K39: =SUM(K6:K38) -> 1.0000001 | L39: =SUM(L6:L38) -> 7570.9206 | M39: =SUM(M6:M38) -> 1770.6701 | N39: =SUM(N6:N38) -> 2354.1802 | O39: =SUM(O6:O38) -> 431.58004 | P39: =SUM(P6:P38) -> 1584.0501 | Q39: =SUM(Q6:Q38) -> 0 | ... AC39: =SUM(AC6:AC38) -> 6645.7
H40: Salary | J40: Hourly | L40: =L3-L39 -> -0.0006256846 | M40: =M3-M39 -> -0.00014633373 | N40: =N3-N39 -> -0.00019455683 | O40: =O3-O39 -> -3.5667126e-05 | P40: =P3-P39 -> -0.00013091086 | Q40: =Q3-Q39 -> 0 | R40: =R3-R39 -> -0.0002262216 | S40: =S3-S39 -> -0.0013907435 | ... AC40: =AC3-AC39 -> 0
C41: 43658 | H41: 65009 | L41: 3872.3 | M41: 905.65 | N41: 1253.04 | O41: 229.72
C42: 43675 | H42: 61825.69 | J42: 0 | L42: 3698.62 | M42: 865.02 | N42: 1101.14 | O42: 201.86 | U42: 5538.46
C43: June Accrual | H43: =-'June 2019 Alloc - Mise USJP'!H43 -> -5832.51 | U43: 6337.92
H44: =SUM(H41:H43) -> 121002.18 | L44: =SUM(L41:L42) -> 7570.92 | M44: =SUM(M41:M42) -> 1770.67 | N44: =SUM(N41:N42) -> 2354.18 | O44: =SUM(O41:O42) -> 431.58 | P44: =SUM(P41:P42) -> 0
H45: =H38 -> 59169.49 | AG45: 114.44
B46: Americorp | I46: Opp Corp | J46: Americ | L46: 196.5 | M46: 45.96 | P46: =SUM(L46:O46) -> 242.46 | AG46: 151.65
F47: =I35-H43 -> 126834.69 | L47: 229.25 | M47: 53.62 | P47: =SUM(L47:O47) -> 282.87 | R47: =SUM(P46:P47) -> 525.33 | S47: =R47+'May 2019 Alloc '!N58+'April 2019 Alloc '!R45 -> 2303.36
B48: Opport Corp | H48: 43630 | I48: 2769.23 | J48: 3697.12 | L48: 165.08 | M48: 38.61 | N48: 83.08 | O48: 15.23
H49: 43644 | I49: 2769.23 | J49: 3168.96 | L49: 165.08 | M49: 38.61 | N49: 83.08 | O49: 15.23
I52: =SUM(I48:I51) -> 5538.46 | J52: =SUM(J48:J51) -> 6866.08
J54: =J52+'May 2019 Alloc '!I60+'April 2019 Alloc '!H44+'April 2019 Alloc '!H45 -> 30105.11

Sheet June 2019 Alloc - NRTC
B1: June Cost Allocations | L1: 7251 | M1: 7252 | N1: 7253 | O1: 7254 | P1: 7260.1 | R1: 7515.5 | S1: 7521 | T1: 8112 | U1: 8135.5 | V1: 8191 | W1: 8210.5 | X1: 8229.1 | Y1: 8239 | Z1: 8266 | AC1: 7248
L2: FICA | M2: MEDI | N2: SUI | O2: Disability | P2: Payroll Fees | R2: IT Consultants | S2: Acctg Fees | T2: Supplies | U2: Telephone | V2: Web Hosting | W2: Utilities | X2: Eq Lease | Y2: Repairs | Z2: General Insurance | AC2: W/ Comp
L3: 8356.56 | M3: 1954.34 | N3: 2970.08 | O3: 544.51 | P3: 2025.21 | R3: 3006 | S3: 4500 | T3: 1692.11 | U3: 1223.42 | V3: 312 | W3: 1366.79 | X3: 2489 | Y3: 1124.51 | Z3: 3972.48 | AC3: 6645.7
L4: 1 | M4: 2 | N4: 3 | O4: 4 | P4: 5 | Q4: 6 | R4: 15 | S4: 9 | T4: 7 | U4: 11 | V4: 16 | W4: 10 | X4: 8 | Y4: 13 | Z4: 14 | AC4: 0.04
D5: 7222 | E5: Taxes | F5: W/C | J5: Taxes | K5: Expenses
B6: 41 | C6: Thriftworks | H6: 0 | J6: =H6/$I$34 -> 0 | K6: =H6/$H$39 -> 0 | L6: =J6*$L$3 -> 0 | M6: =J6*$M$3 -> 0 | N6: =J6*$N$3 -> 0 | O6: =J6*$O$3 -> 0 | P6: =J6*$P$3 -> 0 | R6: =J6*$R$3 -> 0 | S6: =J6*$S$3 -> 0 | T6: =J6*$T$3 -> 0 | U6: =J6*$U$3 -> 0 | V6: =J6*$V$3 -> 0 | W6: =J6*$W$3 -> 0 | X6: =J6*$X$3 -> 0 | Y6: =J6*$Y$3 -> 0 | Z6: =J6*$Z$3 -> 0 | AB6: =H6/$H$39 -> 0 | AC6: =AB6*$AC$3 -> 0
B7: 111 | C7: Abbott | H7: 27503.3 | J7: =H7/$I$34 -> 0.18907743 | K7: =H7/$I$36 -> 0.17422032 | L7: =J7*$L$3 -> 1580.0369 | M7: =J7*$M$3 -> 369.52159 | N7: =J7*$N$3 -> 561.57511 | O7: =J7*$O$3 -> 102.95455 | P7: =J7*$P$3 -> 382.92151 | R7: =K7*$R$3 -> 523.70629 | S7: =K7*$S$3 -> 783.99145 | T7: =K7*$T$3 -> 294.79995 | U7: =K7*$U$3 -> 213.14463 | V7: =K7*$V$3 -> 54.356741 | W7: =K7*$W$3 -> 238.1226 | X7: =K7*$X$3 -> 433.63438 | Y7: =K7*$Y$3 -> 195.9125 | Z7: =K7*$Z$3 -> 692.08675 | AB7: =H7/$H$39 -> 0.083767815 | AC7: =AB7*$AC$3 -> 556.69577
B8: 111B | C8: Abbott Fees | H8: 2686.88 | J8: =H8/$I$34 -> 0.018471543 | K8: =H8/$I$36 -> 0.017020107 | L8: =J8*$L$3 -> 154.35855 | M8: =J8*$M$3 -> 36.099674 | N8: =J8*$N$3 -> 54.861959 | O8: =J8*$O$3 -> 10.05794 | P8: =J8*$P$3 -> 37.408753 | R8: =K8*$R$3 -> 51.162441 | S8: =K8*$S$3 -> 76.59048 | T8: =K8*$T$3 -> 28.799893 | U8: =K8*$U$3 -> 20.822739 | V8: =K8*$V$3 -> 5.3102733 | W8: =K8*$W$3 -> 23.262912 | X8: =K8*$X$3 -> 42.363046 | Y8: =K8*$Y$3 -> 19.13928 | Z8: =K8*$Z$3 -> 67.612034 | AB8: =H8/$H$39 -> 0.0081835295 | AC8: =AB8*$AC$3 -> 54.385282
B9: 111A | C9: Abbott - Other | H9: 2583.91 | J9: =H9/$I$34 -> 0.017763653 | K9: =H9/$I$36 -> 0.016367841 | L9: =J9*$L$3 -> 148.44303 | M9: =J9*$M$3 -> 34.716217 | N9: =J9*$N$3 -> 52.75947 | O9: =J9*$O$3 -> 9.6724866 | P9: =J9*$P$3 -> 35.975127 | R9: =K9*$R$3 -> 49.201729 | S9: =K9*$S$3 -> 73.655283 | T9: =K9*$T$3 -> 27.696187 | U9: =K9*$U$3 -> 20.024744 | V9: =K9*$V$3 -> 5.1067663 | W9: =K9*$W$3 -> 22.371401 | X9: =K9*$X$3 -> 40.739556 | Y9: =K9*$Y$3 -> 18.405801 | Z9: =K9*$Z$3 -> 65.02092 | AB9: =H9/$H$39 -> 0.00786991 | AC9: =AB9*$AC$3 -> 52.301061
B10: 111F | C10: Abbott Food | H10: 253.28 | J10: =H10/$I$34 -> 0.0017412286 | K10: =H10/$I$36 -> 0.0016044083 | L10: =J10*$L$3 -> 14.550681 | M10: =J10*$M$3 -> 3.4029527 | N10: =J10*$N$3 -> 5.1715882 | O10: =J10*$O$3 -> 0.94811638 | P10: =J10*$P$3 -> 3.5263536 | R10: =K10*$R$3 -> 4.8228514 | S10: =K10*$S$3 -> 7.2198374 | T10: =K10*$T$3 -> 2.7148354 | U10: =K10*$U$3 -> 1.9628652 | V10: =K10*$V$3 -> 0.5005754 | W10: =K10*$W$3 -> 2.1928893 | X10: =K10*$X$3 -> 3.9933723 | Y10: =K10*$Y$3 -> 1.8041732 | Z10: =K10*$Z$3 -> 6.37348 | AB10: =H10/$H$39 -> 0.00077142424 | AC10: =AB10*$AC$3 -> 5.1266541
B11: 112 | C11: EHS | H11: 26768.54 | J11: =H11/$I$34 -> 0.18402617 | K11: =H11/$I$36 -> 0.16956597 | L11: =J11*$L$3 -> 1537.8257 | M11: =J11*$M$3 -> 359.6497 | N11: =J11*$N$3 -> 546.57244 | O11: =J11*$O$3 -> 100.20409 | P11: =J11*$P$3 -> 372.69163 | R11: =K11*$R$3 -> 509.7153 | S11: =K11*$S$3 -> 763.04686 | T11: =K11*$T$3 -> 286.92427 | U11: =K11*$U$3 -> 207.4504 | V11: =K11*$V$3 -> 52.904582 | W11: =K11*$W$3 -> 231.76107 | X11: =K11*$X$3 -> 422.04969 | Y11: =K11*$Y$3 -> 190.67863 | Z11: =K11*$Z$3 -> 673.59742 | AB11: =H11/$H$39 -> 0.08152993 | AC11: =AB11*$AC$3 -> 541.82345
B12: 222 | C12: DCF- Coding | H12: 2480.65 | J12: =H12/$I$34 -> 0.017053769 | K12: =H12/$I$36 -> 0.015713738 | L12: =J12*$L$3 -> 142.51085 | M12: =J12*$M$3 -> 33.328864 | N12: =J12*$N$3 -> 50.65106 | O12: =J12*$O$3 -> 9.285948 | P12: =J12*$P$3 -> 34.537464 | R12: =K12*$R$3 -> 47.235496 | S12: =K12*$S$3 -> 70.71182 | T12: =K12*$T$3 -> 26.589373 | U12: =K12*$U$3 -> 19.224501 | V12: =K12*$V$3 -> 4.9026862 | W12: =K12*$W$3 -> 21.47738 | X12: =K12*$X$3 -> 39.111493 | Y12: =K12*$Y$3 -> 17.670255 | Z12: =K12*$Z$3 -> 62.422509 | AB12: =H12/$H$39 -> 0.0075554072 | AC12: =AB12*$AC$3 -> 50.21097
B13: 223 | C13: OICA | H13: 5471.42 | J13: =H13/$I$34 -> 0.03761447 | K13: =H13/$I$36 -> 0.034658843 | L13: =J13*$L$3 -> 314.32758 | M13: =J13*$M$3 -> 73.511463 | N13: =J13*$N$3 -> 111.71799 | O13: =J13*$O$3 -> 20.481455 | P13: =J13*$P$3 -> 76.177201 | R13: =K13*$R$3 -> 104.18448 | S13: =K13*$S$3 -> 155.96479 | T13: =K13*$T$3 -> 58.646575 | U13: =K13*$U$3 -> 42.402322 | V13: =K13*$V$3 -> 10.813559 | W13: =K13*$W$3 -> 47.37136 | X13: =K13*$X$3 -> 86.26586 | Y13: =K13*$Y$3 -> 38.974216 | Z13: =K13*$Z$3 -> 137.68156 | AB13: =H13/$H$39 -> 0.016664506 | AC13: =AB13*$AC$3 -> 110.74731
B14: 566 | C14: FOC -Americorp | J14: =H14/$I$34 -> 0 | K14: =H14/$I$36 -> 0 | L14: =$J$36*L3 -> 0 | M14: =$J$36*M3 -> 0 | N14: =$J$36*N3 -> 0 | O14: =$J$36*O3 -> 0 | P14: =$J$36*P3 -> 0 | Q14: =$J$36*Q3 -> 0 | R14: =K14*$R$3 -> 0 | S14: =K14*$S$3 -> 0 | T14: =K14*$T$3 -> 0 | U14: =K14*$U$3 -> 0 | V14: =K14*$V$3 -> 0 | W14: =K14*$W$3 -> 0 | X14: =K14*$X$3 -> 0 | Y14: =K14*$Y$3 -> 0 | Z14: =K14*$Z$3 -> 0 | AB14: =H14/$H$39 -> 0 | AC14: =AB14*$AC$3 -> 0
B15: 334D | C15: NRTC - Admin | H15: 2146.15 | J15: =H15/$I$34 -> 0.014754176 | K15: =H15/$I$36 -> 0.013594839 | L15: =J15*$L$3 -> 123.29416 | M15: =J15*$M$3 -> 28.834677 | N15: =J15*$N$3 -> 43.821084 | O15: =J15*$O$3 -> 8.0337965 | P15: =J15*$P$3 -> 29.880305 | R15: =K15*$R$3 -> 40.866087 | S15: =K15*$S$3 -> 61.176777 | T15: =K15*$T$3 -> 23.003964 | U15: =K15*$U$3 -> 16.632198 | V15: =K15*$V$3 -> 4.2415899 | W15: =K15*$W$3 -> 18.581291 | X15: =K15*$X$3 -> 33.837555 | Y15: =K15*$Y$3 -> 15.287533 | Z15: =K15*$Z$3 -> 54.005228 | AB15: =H15/$H$39 -> 0.0065366082 | AC15: =AB15*$AC$3 -> 43.440337
B16: 334E | C16: NRTC - 2016 Thriftworks | H16: 3538.46 | J16: =H16/$I$34 -> 0.024325915 | K16: =H16/$I$36 -> 0.022414461 | L16: =J16*$L$3 -> 203.28097 | M16: =J16*$M$3 -> 47.541109 | N16: =J16*$N$3 -> 72.249914 | O16: =J16*$O$3 -> 13.245704 | P16: =J16*$P$3 -> 49.265086 | R16: =K16*$R$3 -> 67.37787 | S16: =K16*$S$3 -> 100.86507 | T16: =K16*$T$3 -> 37.927734 | U16: =K16*$U$3 -> 27.4223 | V16: =K16*$V$3 -> 6.9933118 | W16: =K16*$W$3 -> 30.635861 | X16: =K16*$X$3 -> 55.789593 | Y16: =K16*$Y$3 -> 25.205285 | Z16: =K16*$Z$3 -> 89.040998 | AB16: =H16/$H$39 -> 0.010777218 | AC16: =AB16*$AC$3 -> 71.622159
B17: 334H | C17: NRTC - Housing | H17: 4580 | J17: =H17/$I$34 -> 0.031486209 | K17: =H17/$I$36 -> 0.029012121 | L17: =J17*$L$3 -> 263.11639 | M17: =J17*$M$3 -> 61.534757 | N17: =J17*$N$3 -> 93.516559 | O17: =J17*$O$3 -> 17.144556 | P17: =J17*$P$3 -> 63.766185 | R17: =K17*$R$3 -> 87.210437 | S17: =K17*$S$3 -> 130.55455 | T17: =K17*$T$3 -> 49.091701 | U17: =K17*$U$3 -> 35.49401 | V17: =K17*$V$3 -> 9.0517819 | W17: =K17*$W$3 -> 39.653477 | X17: =K17*$X$3 -> 72.21117 | Y17: =K17*$Y$3 -> 32.624421 | Z17: =K17*$Z$3 -> 115.25007 | AB17: =H17/$H$39 -> 0.013949475 | AC17: =AB17*$AC$3 -> 92.704026
B18: 334F | C18: NRTC FOC | H18: 1538.46 | J18: =H18/$I$34 -> 0.010576479 | K18: =H18/$I$36 -> 0.0097454123 | L18: =J18*$L$3 -> 88.38298 | M18: =J18*$M$3 -> 20.670036 | N18: =J18*$N$3 -> 31.412988 | O18: =J18*$O$3 -> 5.7589985 | P18: =J18*$P$3 -> 21.419591 | R18: =K18*$R$3 -> 29.294709 | S18: =K18*$S$3 -> 43.854355 | T18: =K18*$T$3 -> 16.49031 | U18: =K18*$U$3 -> 11.922732 | V18: =K18*$V$3 -> 3.0405686 | W18: =K18*$W$3 -> 13.319932 | X18: =K18*$X$3 -> 24.256331 | Y18: =K18*$Y$3 -> 10.958814 | Z18: =K18*$Z$3 -> 38.713455 | AB18: =H18/$H$39 -> 0.0046857444 | AC18: =AB18*$AC$3 -> 31.140051
B19: 335 | C19: NRTC 19 | H19: 846.15 | J19: =H19/$I$34 -> 0.0058170427 | K19: =H19/$I$36 -> 0.0053599578 | L19: =J19*$L$3 -> 48.610466 | M19: =J19*$M$3 -> 11.368479 | N19: =J19*$N$3 -> 17.277082 | O19: =J19*$O$3 -> 3.1674379 | P19: =J19*$P$3 -> 11.780733 | R19: =K19*$R$3 -> 16.112033 | S19: =K19*$S$3 -> 24.11981 | T19: =K19*$T$3 -> 9.0696381 | U19: =K19*$U$3 -> 6.5574795 | V19: =K19*$V$3 -> 1.6723068 | W19: =K19*$W$3 -> 7.3259367 | X19: =K19*$X$3 -> 13.340935 | Y19: =K19*$Y$3 -> 6.0273261 | Z19: =K19*$Z$3 -> 21.292325 | AB19: =H19/$H$39 -> 0.0025771503 | AC19: =AB19*$AC$3 -> 17.126968
B20: 368 | C20: Wells Fargo | H20: 4903.5 | J20: =H20/$I$34 -> 0.03371018 | K20: =H20/$I$36 -> 0.03106134 | L20: =J20*$L$3 -> 281.70114 | M20: =J20*$M$3 -> 65.881154 | N20: =J20*$N$3 -> 100.12193 | O20: =J20*$O$3 -> 18.35553 | P20: =J20*$P$3 -> 68.270194 | R20: =K20*$R$3 -> 93.370388 | S20: =K20*$S$3 -> 139.77603 | T20: =K20*$T$3 -> 52.559204 | U20: =K20*$U$3 -> 38.001065 | V20: =K20*$V$3 -> 9.6911381 | W20: =K20*$W$3 -> 42.454329 | X20: =K20*$X$3 -> 77.311675 | Y20: =K20*$Y$3 -> 34.928787 | Z20: =K20*$Z$3 -> 123.39055 | AB20: =H20/$H$39 -> 0.014934771 | AC20: =AB20*$AC$3 -> 99.252006
B21: 451 | C21: USJP | H21: 23537.96 | J21: =H21/$I$34 -> 0.16181684 | K21: =H21/$I$36 -> 0.14910178 | L21: =J21*$L$3 -> 1352.2321 | M21: =J21*$M$3 -> 316.24512 | N21: =J21*$N$3 -> 480.60896 | O21: =J21*$O$3 -> 88.110887 | P21: =J21*$P$3 -> 327.71308 | R21: =K21*$R$3 -> 448.19995 | S21: =K21*$S$3 -> 670.95801 | T21: =K21*$T$3 -> 252.29661 | U21: =K21*$U$3 -> 182.4141 | V21: =K21*$V$3 -> 46.519755 | W21: =K21*$W$3 -> 203.79082 | X21: =K21*$X$3 -> 371.11433 | Y21: =K21*$Y$3 -> 167.66644 | Z21: =K21*$Z$3 -> 592.30384 | AB21: =H21/$H$39 -> 0.071690433 | AC21: =AB21*$AC$3 -> 476.43311
B22: 467 | C22: WF - United Airlines | H22: 3476.56 | J22: =H22/$I$34 -> 0.02390037 | K22: =H22/$I$36 -> 0.022022354 | L22: =J22*$L$3 -> 199.72488 | M22: =J22*$M$3 -> 46.709449 | N22: =J22*$N$3 -> 70.986011 | O22: =J22*$O$3 -> 13.01399 | P22: =J22*$P$3 -> 48.403268 | R22: =K22*$R$3 -> 66.199196 | S22: =K22*$S$3 -> 99.100593 | T22: =K22*$T$3 -> 37.264245 | U22: =K22*$U$3 -> 26.942588 | V22: =K22*$V$3 -> 6.8709744 | W22: =K22*$W$3 -> 30.099933 | X22: =K22*$X$3 -> 54.813639 | Y22: =K22*$Y$3 -> 24.764357 | Z22: =K22*$Z$3 -> 87.48336 | AB22: =H22/$H$39 -> 0.010588687 | AC22: =AB22*$AC$3 -> 70.369237
B23: 468 | C23: Newark Alliance | H23: 6307.7 | J23: =H23/$I$34 -> 0.043363659 | K23: =H23/$I$36 -> 0.039956279 | L23: =J23*$L$3 -> 362.37102 | M23: =J23*$M$3 -> 84.747334 | N23: =J23*$N$3 -> 128.79354 | O23: =J23*$O$3 -> 23.611946 | P23: =J23*$P$3 -> 87.820516 | R23: =K23*$R$3 -> 120.10858 | S23: =K23*$S$3 -> 179.80326 | T23: =K23*$T$3 -> 67.610419 | U23: =K23*$U$3 -> 48.883311 | V23: =K23*$V$3 -> 12.466359 | W23: =K23*$W$3 -> 54.611843 | X23: =K23*$X$3 -> 99.451179 | Y23: =K23*$Y$3 -> 44.931235 | Z23: =K23*$Z$3 -> 158.72552 | AB23: =H23/$H$39 -> 0.019211595 | AC23: =AB23*$AC$3 -> 127.67449
B24: 502 | C24: ESG | H24: 1915 | J24: =H24/$I$34 -> 0.013165085 | K24: =H24/$I$36 -> 0.012130614 | L24: =J24*$L$3 -> 110.01482 | M24: =J24*$M$3 -> 25.729053 | N24: =J24*$N$3 -> 39.101356 | O24: =J24*$O$3 -> 7.1685205 | P24: =J24*$P$3 -> 26.662062 | R24: =K24*$R$3 -> 36.464626 | S24: =K24*$S$3 -> 54.587763 | T24: =K24*$T$3 -> 20.526333 | U24: =K24*$U$3 -> 14.840836 | V24: =K24*$V$3 -> 3.7847516 | W24: =K24*$W$3 -> 16.580002 | X24: =K24*$X$3 -> 30.193098 | Y24: =K24*$Y$3 -> 13.640997 | Z24: =K24*$Z$3 -> 48.188622 | AB24: =H24/$H$39 -> 0.0058325861 | AC24: =AB24*$AC$3 -> 38.761618
B25: 515 | C25: FOC - HUD NUL PARS | H25: 3338.08 | J25: =H25/$I$34 -> 0.022948359 | K25: =H25/$I$36 -> 0.021145149 | L25: =J25*$L$3 -> 191.76934 | M25: =J25*$M$3 -> 44.848896 | N25: =J25*$N$3 -> 68.158462 | O25: =J25*$O$3 -> 12.495611 | P25: =J25*$P$3 -> 46.475246 | R25: =K25*$R$3 -> 63.562318 | S25: =K25*$S$3 -> 95.15317 | T25: =K25*$T$3 -> 35.779918 | U25: =K25*$U$3 -> 25.869398 | V25: =K25*$V$3 -> 6.5972865 | W25: =K25*$W$3 -> 28.900978 | X25: =K25*$X$3 -> 52.630276 | Y25: =K25*$Y$3 -> 23.777931 | Z25: =K25*$Z$3 -> 83.998681 | AB25: =H25/$H$39 -> 0.010166913 | AC25: =AB25*$AC$3 -> 67.566256
B26: 525 | C26: CDBG - Housing | H26: 2076.93 | J26: =H26/$I$34 -> 0.014278308 | K26: =H26/$I$36 -> 0.013156364 | L26: =J26*$L$3 -> 119.31754 | M26: =J26*$M$3 -> 27.904669 | N26: =J26*$N$3 -> 42.407718 | O26: =J26*$O$3 -> 7.7746816 | P26: =J26*$P$3 -> 28.916573 | R26: =K26*$R$3 -> 39.548029 | S26: =K26*$S$3 -> 59.203636 | T26: =K26*$T$3 -> 22.262014 | U26: =K26*$U$3 -> 16.095758 | V26: =K26*$V$3 -> 4.1047854 | W26: =K26*$W$3 -> 17.981986 | X26: =K26*$X$3 -> 32.746189 | Y26: =K26*$Y$3 -> 14.794462 | Z26: =K26*$Z$3 -> 52.263391 | AB26: =H26/$H$39 -> 0.0063257823 | AC26: =AB26*$AC$3 -> 42.039252
B27: 560 | C27: CAP 1 - Save Up | H27: 230.77 | J27: =H27/$I$34 -> 0.0015864787 | K27: =H27/$I$36 -> 0.0014618182 | L27: =J27*$L$3 -> 13.257504 | M27: =J27*$M$3 -> 3.1005188 | N27: =J27*$N$3 -> 4.7119686 | O27: =J27*$O$3 -> 0.86385351 | P27: =J27*$P$3 -> 3.2129525 | R27: =K27*$R$3 -> 4.3942254 | S27: =K27*$S$3 -> 6.5781818 | T27: =K27*$T$3 -> 2.4735572 | U27: =K27*$U$3 -> 1.7884176 | V27: =K27*$V$3 -> 0.45608727 | W27: =K27*$W$3 -> 1.9979985 | X27: =K27*$X$3 -> 3.6384654 | Y27: =K27*$Y$3 -> 1.6438292 | Z27: =K27*$Z$3 -> 5.8070435 | AB27: =H27/$H$39 -> 0.0007028647 | AC27: =AB27*$AC$3 -> 4.6710279
B28: 561 | C28: LISC FOC | H28: 2461.54 | J28: =H28/$I$34 -> 0.016922394 | K28: =H28/$I$36 -> 0.015592685 | L28: =J28*$L$3 -> 141.413 | M28: =J28*$M$3 -> 33.072111 | N28: =J28*$N$3 -> 50.260863 | O28: =J28*$O$3 -> 9.2144125 | P28: =J28*$P$3 -> 34.271401 | R28: =K28*$R$3 -> 46.871611 | S28: =K28*$S$3 -> 70.167083 | T28: =K28*$T$3 -> 26.384538 | U28: =K28*$U$3 -> 19.076403 | V28: =K28*$V$3 -> 4.8649177 | W28: =K28*$W$3 -> 21.311926 | X28: =K28*$X$3 -> 38.810193 | Y28: =K28*$Y$3 -> 17.53413 | Z28: =K28*$Z$3 -> 61.941629 | AB28: =H28/$H$39 -> 0.0074972032 | AC28: =AB28*$AC$3 -> 49.824163
B29: 567 | C29: FOC - Chase | H29: 0 | J29: =H29/$I$34 -> 0 | K29: =H29/$I$36 -> 0 | L29: =J29*$L$3 -> 0 | M29: =J29*$M$3 -> 0 | N29: =J29*$N$3 -> 0 | O29: =J29*$O$3 -> 0 | P29: =J29*$P$3 -> 0 | R29: =K29*$R$3 -> 0 | S29: =K29*$S$3 -> 0 | T29: =K29*$T$3 -> 0 | U29: =K29*$U$3 -> 0 | V29: =K29*$V$3 -> 0 | W29: =K29*$W$3 -> 0 | X29: =K29*$X$3 -> 0 | Y29: =K29*$Y$3 -> 0 | Z29: =K29*$Z$3 -> 0 | AB29: =H29/$H$39 -> 0 | AC29: =AB29*$AC$3 -> 0
B30: 610 | C30: CEO | H30: 9776.93 | J30: =H30/$I$34 -> 0.067213638 | K30: =H30/$I$36 -> 0.061932201 | L30: =J30*$L$3 -> 561.6748 | M30: =J30*$M$3 -> 131.3583 | N30: =J30*$N$3 -> 199.62988 | O30: =J30*$O$3 -> 36.598498 | P30: =J30*$P$3 -> 136.12173 | R30: =K30*$R$3 -> 186.1682 | S30: =K30*$S$3 -> 278.6949 | T30: =K30*$T$3 -> 104.7961 | U30: =K30*$U$3 -> 75.769093 | V30: =K30*$V$3 -> 19.322847 | W30: =K30*$W$3 -> 84.648313 | X30: =K30*$X$3 -> 154.14925 | Y30: =K30*$Y$3 -> 69.643379 | Z30: =K30*$Z$3 -> 246.02443 | AB30: =H30/$H$39 -> 0.029777956 | AC30: =AB30*$AC$3 -> 197.89536
... B33: 650 | C33: Facilities | H33: 269.1 | J33: =H33/$I$34 -> 0.0018499866 | K33: =H33/$I$36 -> 0.0017046205 | L33: =J33*$L$3 -> 15.459524 | M33: =J33*$M$3 -> 3.6155029 | N33: =J33*$N$3 -> 5.4946083 | O33: =J33*$O$3 -> 1.0073362 | P33: =J33*$P$3 -> 3.7466114 | R33: =K33*$R$3 -> 5.1240892 | S33: =K33*$S$3 -> 7.6707922 | T33: =K33*$T$3 -> 2.8844054 | U33: =K33*$U$3 -> 2.0854668 | V33: =K33*$V$3 -> 0.5318416 | W33: =K33*$W$3 -> 2.3298582 | X33: =K33*$X$3 -> 4.2428004 | Y33: =K33*$Y$3 -> 1.9168628 | Z33: =K33*$Z$3 -> 6.7715708 | AB33: =H33/$H$39 -> 0.0008196078 | AC33: =AB33*$AC$3 -> 5.4468675
B34: 600 | C34: Admin | H34: 0.01 | I34: =SUM(H6:H34) -> 145460.51 | J34: =H34/$I$34 -> 6.8747181e-08 | K34: =H34/$I$36 -> 6.3345243e-08 | L34: =J34*$L$3 -> 0.00057448994 | M34: =J34*$M$3 -> 0.00013435537 | N34: =J34*$N$3 -> 0.00020418463 | O34: =J34*$O$3 -> 3.7433527e-05 | P34: =J34*$P$3 -> 0.00013922748 | R34: =K34*$R$3 -> 0.0001904158 | S34: =K34*$S$3 -> 0.00028505359 | T34: =K34*$T$3 -> 0.00010718712 | U34: =K34*$U$3 -> 7.7497838e-05 | V34: =K34*$V$3 -> 1.9763716e-05 | W34: =K34*$W$3 -> 8.6579645e-05 | X34: =K34*$X$3 -> 0.00015766631 | Y34: =K34*$Y$3 -> 7.123236e-05 | Z34: =K34*$Z$3 -> 0.00025163771 | AB34: =H34/$H$39 -> 3.0457369e-08 | AC34: =AB34*$AC$3 -> 0.00020241054
B35: 339 | C35: Opport Corp | H35: 5538.46 | K35: =H35/$I$36 -> 0.03508351 | L35: =J35*$L$3 -> 0 | M35: =J35*$M$3 -> 0 | N35: =J35*$N$3 -> 0 | O35: =J35*$O$3 -> 0 | P35: =J35*$P$3 -> 0 | R35: =K35*$R$3 -> 105.46103 | S35: =K35*$S$3 -> 157.87579 | T35: =K35*$T$3 -> 59.365157 | U35: =K35*$U$3 -> 42.921867 | V35: =K35*$V$3 -> 10.946055 | W35: =K35*$W$3 -> 47.95179 | X35: =K35*$X$3 -> 87.322855 | Y35: =K35*$Y$3 -> 39.451757 | Z35: =K35*$Z$3 -> 139.36854 | AB35: =H35/$H$39 -> 0.016868692 | AC35: =AB35*$AC$3 -> 112.10427
B36: 225 | C36: AmeriCorp | H36: 6866.08 | I36: =I34+H35+H36 -> 157865.05 | K36: =H36/$I$36 -> 0.043493351 | R36: =K36*$R$3 -> 130.74101 | S36: =K36*$S$3 -> 195.72008 | T36: =K36*$T$3 -> 73.595534 | U36: =K36*$U$3 -> 53.210635 | V36: =K36*$V$3 -> 13.569925 | W36: =K36*$W$3 -> 59.446277 | X36: =K36*$X$3 -> 108.25495 | Y36: =K36*$Y$3 -> 48.908708 | Z36: =K36*$Z$3 -> 172.77647 | AB36: =H36/$H$39 -> 0.020912273 | AC36: =AB36*$AC$3 -> 138.97669
K37: =H37/$I$36 -> 0 | L37: =J37*$L$3 -> 0 | M37: =J37*$M$3 -> 0 | N37: =J37*$N$3 -> 0 | O37: =J37*$O$3 -> 0 | P37: =J37*$P$3 -> 0 | R37: =K37*$R$3 -> 0 | S37: =K37*$S$3 -> 0 | T37: =K37*$T$3 -> 0 | U37: =K37*$U$3 -> 0 | V37: =K37*$V$3 -> 0 | W37: =K37*$W$3 -> 0 | X37: =K37*$X$3 -> 0 | Y37: =K37*$Y$3 -> 0 | Z37: =K37*$Z$3 -> 0 | AB37: =H37/$H$39 -> 0 | AC37: =AB37*$AC$3 -> 0
B38: 451 | C38: USJP - Participants | H38: 170462.72 | AB38: =H38/$H$39 -> 0.51918459 | AC38: =AB38*$AC$3 -> 3450.3451
H39: =SUM(H7:H38) -> 328327.77 | J39: =SUM(J7:J37) -> 1 | K39: =SUM(K7:K37) -> 1 | L39: =SUM(L7:L37) -> 8356.56 | M39: =SUM(M7:M37) -> 1954.34 | N39: =SUM(N7:N37) -> 2970.08 | O39: =SUM(O7:O37) -> 544.51 | P39: =SUM(P7:P37) -> 2025.21 | Q39: =SUM(Q7:Q37) -> 0 | ... Z39: =SUM(Z7:Z37) -> 3972.48 | AB39: =SUM(AB7:AB38) -> 1 | AC39: =SUM(AC7:AC38) -> 6645.7
H40: Salary | J40: Hourly
C41: 43630 | H41: 69758.32 | L41: 4171.8 | M41: 975.65 | N41: 1497 | O41: 274.45
C42: 43644 | H42: 69712.19 | J42: 0 | L42: 4184.76 | M42: 978.69 | N42: 1473.08 | O42: 270.06
H43: 5832.51
H44: =SUM(H41:H43) -> 145303.02 | L44: =SUM(L41:L42) -> 8356.56 | M44: =SUM(M41:M42) -> 1954.34 | N44: =SUM(N41:N42) -> 2970.08 | O44: =SUM(O41:O42) -> 544.51 | P44: =SUM(P41:P42) -> 0
H45: =H38 -> 170462.72 | AG45: 114.44
B46: Americorp | I46: Opp Corp | J46: Americ | L46: 196.5 | M46: 45.96 | P46: =SUM(L46:O46) -> 242.46 | AG46: 151.65
L47: 229.25 | M47: 53.62 | P47: =SUM(L47:O47) -> 282.87 | R47: =SUM(P46:P47) -> 525.33 | S47: =R47+'[1]May 2019 Alloc '!N58+'[1]April 2019 Alloc '!R45 -> 2303.36
B48: Opport Corp | H48: 43630 | I48: 2769.23 | J48: 3697.12 | L48: 165.08 | M48: 38.61 | N48: 83.08 | O48: 15.23
H49: 43644 | I49: 2769.23 | J49: 3168.96 | L49: 165.08 | M49: 38.61 | N49: 83.08 | O49: 15.23
I52: =SUM(I48:I51) -> 5538.46 | J52: =SUM(J48:J51) -> 6866.08
J54: =J52+'[1]May 2019 Alloc '!I60+'[1]April 2019 Alloc '!H44+'[1]April 2019 Alloc '!H45 -> 30105.11

Sheet June 2019 Alloc - Mise USJP
B1: June Cost Allocations | L1: 7251 | M1: 7252 | N1: 7253 | O1: 7254 | P1: 7260.1 | R1: 7515.5 | S1: 7521 | T1: 8112 | U1: 8135.5 | V1: 8191 | W1: 8210.5 | X1: 8229.1 | Y1: 8239 | Z1: 8266 | AC1: 7248
L2: FICA | M2: MEDI | N2: SUI | O2: Disability | P2: Payroll Fees | R2: IT Consultants | S2: Acctg Fees | T2: Supplies | U2: Telephone | V2: Web Hosting | W2: Utilities | X2: Eq Lease | Y2: Repairs | Z2: General Insurance | AC2: W/ Comp
L3: 8356.56 | M3: 1954.34 | N3: 2970.08 | O3: 544.51 | P3: 2025.21 | R3: 3006 | S3: 4500 | T3: 1692.11 | U3: 1223.42 | V3: 312 | W3: 1366.79 | X3: 2489 | Y3: 1124.51 | Z3: 3972.48 | AC3: 6645.7
L4: 1 | M4: 2 | N4: 3 | O4: 4 | P4: 5 | Q4: 6 | R4: 15 | S4: 9 | T4: 7 | U4: 11 | V4: 16 | W4: 10 | X4: 8 | Y4: 13 | Z4: 14 | AC4: 0.04
D5: 7222 | E5: Taxes | F5: W/C | J5: Taxes | K5: Expenses
B6: 41 | C6: Thriftworks | H6: 0 | J6: =H6/$I$34 -> 0 | K6: =H6/$H$39 -> 0 | L6: =J6*$L$3 -> 0 | M6: =J6*$M$3 -> 0 | N6: =J6*$N$3 -> 0 | O6: =J6*$O$3 -> 0 | P6: =J6*$P$3 -> 0 | R6: =J6*$R$3 -> 0 | S6: =J6*$S$3 -> 0 | T6: =J6*$T$3 -> 0 | U6: =J6*$U$3 -> 0 | V6: =J6*$V$3 -> 0 | W6: =J6*$W$3 -> 0 | X6: =J6*$X$3 -> 0 | Y6: =J6*$Y$3 -> 0 | Z6: =J6*$Z$3 -> 0 | AB6: =H6/$H$39 -> 0 | AC6: =AB6*$AC$3 -> 0
B7: 111 | C7: Abbott | H7: 26415.68 | J7: =H7/$I$34 -> 0.18179744 | K7: =H7/$I$36 -> 0.16749808 | L7: =J7*$L$3 -> 1519.2012 | M7: =J7*$M$3 -> 355.294 | N7: =J7*$N$3 -> 539.95293 | O7: =J7*$O$3 -> 98.990521 | P7: =J7*$P$3 -> 368.17798 | R7: =K7*$R$3 -> 503.49923 | S7: =K7*$S$3 -> 753.74136 | T7: =K7*$T$3 -> 283.42518 | U7: =K7*$U$3 -> 204.9205 | V7: =K7*$V$3 -> 52.259401 | W7: =K7*$W$3 -> 228.9347 | X7: =K7*$X$3 -> 416.90272 | Y7: =K7*$Y$3 -> 188.35327 | Z7: =K7*$Z$3 -> 665.38277 | AB7: =H7/$H$39 -> 0.080493871 | AC7: =AB7*$AC$3 -> 534.93812
B8: 111B | C8: Abbott Fees | H8: 2686.88 | J8: =H8/$I$34 -> 0.018491589 | K8: =H8/$I$36 -> 0.017037125 | L8: =J8*$L$3 -> 154.52607 | M8: =J8*$M$3 -> 36.138852 | N8: =J8*$N$3 -> 54.921498 | O8: =J8*$O$3 -> 10.068855 | P8: =J8*$P$3 -> 37.449351 | R8: =K8*$R$3 -> 51.213598 | S8: =K8*$S$3 -> 76.667062 | T8: =K8*$T$3 -> 28.82869 | U8: =K8*$U$3 -> 20.843559 | V8: =K8*$V$3 -> 5.315583 | W8: =K8*$W$3 -> 23.286172 | X8: =K8*$X$3 -> 42.405404 | Y8: =K8*$Y$3 -> 19.158417 | Z8: =K8*$Z$3 -> 67.679638 | AB8: =H8/$H$39 -> 0.0081874618 | AC8: =AB8*$AC$3 -> 54.411415
B9: 111A | C9: Abbott - Other | H9: 2583.91 | J9: =H9/$I$34 -> 0.017782931 | K9: =H9/$I$36 -> 0.016384207 | L9: =J9*$L$3 -> 148.60413 | M9: =J9*$M$3 -> 34.753893 | N9: =J9*$N$3 -> 52.816727 | O9: =J9*$O$3 -> 9.6829837 | P9: =J9*$P$3 -> 36.014169 | R9: =K9*$R$3 -> 49.250926 | S9: =K9*$S$3 -> 73.728931 | T9: =K9*$T$3 -> 27.72388 | U9: =K9*$U$3 -> 20.044766 | V9: =K9*$V$3 -> 5.1118725 | W9: =K9*$W$3 -> 22.39377 | X9: =K9*$X$3 -> 40.780291 | Y9: =K9*$Y$3 -> 18.424204 | Z9: =K9*$Z$3 -> 65.085934 | AB9: =H9/$H$39 -> 0.0078736916 | AC9: =AB9*$AC$3 -> 52.326192
B10: 111F | C10: Abbott Food | H10: 253.28 | J10: =H10/$I$34 -> 0.0017431183 | K10: =H10/$I$36 -> 0.0016060126 | L10: =J10*$L$3 -> 14.566472 | M10: =J10*$M$3 -> 3.4066458 | N10: =J10*$N$3 -> 5.1772007 | O10: =J10*$O$3 -> 0.94914533 | P10: =J10*$P$3 -> 3.5301805 | R10: =K10*$R$3 -> 4.8276737 | S10: =K10*$S$3 -> 7.2270565 | T10: =K10*$T$3 -> 2.7175499 | U10: =K10*$U$3 -> 1.9648279 | V10: =K10*$V$3 -> 0.50107592 | W10: =K10*$W$3 -> 2.1950819 | X10: =K10*$X$3 -> 3.9973652 | Y10: =K10*$Y$3 -> 1.8059772 | Z10: =K10*$Z$3 -> 6.3798528 | AB10: =H10/$H$39 -> 0.00077179492 | AC10: =AB10*$AC$3 -> 5.1291175
B11: 112 | C11: EHS | H11: 27856.16 | J11: =H11/$I$34 -> 0.19171108 | K11: =H11/$I$36 -> 0.17663196 | L11: =J11*$L$3 -> 1602.0451 | M11: =J11*$M$3 -> 374.66862 | N11: =J11*$N$3 -> 569.39723 | O11: =J11*$O$3 -> 104.3886 | P11: =J11*$P$3 -> 388.25519 | R11: =K11*$R$3 -> 530.95567 | S11: =K11*$S$3 -> 794.84382 | T11: =K11*$T$3 -> 298.8807 | U11: =K11*$U$3 -> 216.09507 | V11: =K11*$V$3 -> 55.109171 | W11: =K11*$W$3 -> 241.4188 | X11: =K11*$X$3 -> 439.63695 | Y11: =K11*$Y$3 -> 198.6244 | Z11: =K11*$Z$3 -> 701.66693 | AB11: =H11/$H$39 -> 0.084883302 | AC11: =AB11*$AC$3 -> 564.10896
B12: 222 | C12: DCF- Coding | H12: 2480.65 | J12: =H12/$I$34 -> 0.017072277 | K12: =H12/$I$36 -> 0.01572945 | L12: =J12*$L$3 -> 142.66551 | M12: =J12*$M$3 -> 33.365034 | N12: =J12*$N$3 -> 50.706029 | O12: =J12*$O$3 -> 9.2960256 | P12: =J12*$P$3 -> 34.574946 | R12: =K12*$R$3 -> 47.282726 | S12: =K12*$S$3 -> 70.782524 | T12: =K12*$T$3 -> 26.615959 | U12: =K12*$U$3 -> 19.243723 | V12: =K12*$V$3 -> 4.9075883 | W12: =K12*$W$3 -> 21.498855 | X12: =K12*$X$3 -> 39.150601 | Y12: =K12*$Y$3 -> 17.687924 | Z12: =K12*$Z$3 -> 62.484925 | AB12: =H12/$H$39 -> 0.0075590377 | AC12: =AB12*$AC$3 -> 50.235097
B13: 223 | C13: OICA | H13: 5471.42 | J13: =H13/$I$34 -> 0.037655291 | K13: =H13/$I$36 -> 0.034693498 | L13: =J13*$L$3 -> 314.6687 | M13: =J13*$M$3 -> 73.591242 | N13: =J13*$N$3 -> 111.83923 | O13: =J13*$O$3 -> 20.503683 | P13: =J13*$P$3 -> 76.259872 | R13: =K13*$R$3 -> 104.28866 | S13: =K13*$S$3 -> 156.12074 | T13: =K13*$T$3 -> 58.705215 | U13: =K13*$U$3 -> 42.444719 | V13: =K13*$V$3 -> 10.824371 | W13: =K13*$W$3 -> 47.418726 | X13: =K13*$X$3 -> 86.352117 | Y13: =K13*$Y$3 -> 39.013186 | Z13: =K13*$Z$3 -> 137.81923 | AB13: =H13/$H$39 -> 0.016672513 | AC13: =AB13*$AC$3 -> 110.80052
B14: 566 | C14: FOC -Americorp | J14: =H14/$I$34 -> 0 | K14: =H14/$I$36 -> 0 | L14: =$J$36*L3 -> 0 | M14: =$J$36*M3 -> 0 | N14: =$J$36*N3 -> 0 | O14: =$J$36*O3 -> 0 | P14: =$J$36*P3 -> 0 | Q14: =$J$36*Q3 -> 0 | R14: =K14*$R$3 -> 0 | S14: =K14*$S$3 -> 0 | T14: =K14*$T$3 -> 0 | U14: =K14*$U$3 -> 0 | V14: =K14*$V$3 -> 0 | W14: =K14*$W$3 -> 0 | X14: =K14*$X$3 -> 0 | Y14: =K14*$Y$3 -> 0 | Z14: =K14*$Z$3 -> 0 | AB14: =H14/$H$39 -> 0 | AC14: =AB14*$AC$3 -> 0
B15: 334D | C15: NRTC - Admin | H15: 2146.15 | J15: =H15/$I$34 -> 0.014770188 | K15: =H15/$I$36 -> 0.013608433 | L15: =J15*$L$3 -> 123.42796 | M15: =J15*$M$3 -> 28.86597 | N15: =J15*$N$3 -> 43.868641 | O15: =J15*$O$3 -> 8.0425152 | P15: =J15*$P$3 -> 29.912733 | R15: =K15*$R$3 -> 40.906949 | S15: =K15*$S$3 -> 61.237947 | T15: =K15*$T$3 -> 23.026965 | U15: =K15*$U$3 -> 16.648829 | V15: =K15*$V$3 -> 4.245831 | W15: =K15*$W$3 -> 18.59987 | X15: =K15*$X$3 -> 33.871389 | Y15: =K15*$Y$3 -> 15.302819 | Z15: =K15*$Z$3 -> 54.059227 | AB15: =H15/$H$39 -> 0.0065397491 | AC15: =AB15*$AC$3 -> 43.461211
B16: 334E | C16: NRTC - 2016 Thriftworks | H16: 3538.46 | J16: =H16/$I$34 -> 0.024352315 | K16: =H16/$I$36 -> 0.022436873 | L16: =J16*$L$3 -> 203.50158 | M16: =J16*$M$3 -> 47.592703 | N16: =J16*$N$3 -> 72.328323 | O16: =J16*$O$3 -> 13.260079 | P16: =J16*$P$3 -> 49.318551 | R16: =K16*$R$3 -> 67.44524 | S16: =K16*$S$3 -> 100.96593 | T16: =K16*$T$3 -> 37.965657 | U16: =K16*$U$3 -> 27.449719 | V16: =K16*$V$3 -> 7.0003044 | W16: =K16*$W$3 -> 30.666494 | X16: =K16*$X$3 -> 55.845377 | Y16: =K16*$Y$3 -> 25.230488 | Z16: =K16*$Z$3 -> 89.130029 | AB16: =H16/$H$39 -> 0.010782397 | AC16: =AB16*$AC$3 -> 71.656574
B17: 334H | C17: NRTC - Housing | H17: 3780 | J17: =H17/$I$34 -> 0.026014636 | K17: =H17/$I$36 -> 0.023968444 | L17: =J17*$L$3 -> 217.39287 | M17: =J17*$M$3 -> 50.841444 | N17: =J17*$N$3 -> 77.265551 | O17: =J17*$O$3 -> 14.16523 | P17: =J17*$P$3 -> 52.685101 | R17: =K17*$R$3 -> 72.049142 | S17: =K17*$S$3 -> 107.858 | T17: =K17*$T$3 -> 40.557243 | U17: =K17*$U$3 -> 29.323474 | V17: =K17*$V$3 -> 7.4781545 | W17: =K17*$W$3 -> 32.759829 | X17: =K17*$X$3 -> 59.657457 | Y17: =K17*$Y$3 -> 26.952755 | Z17: =K17*$Z$3 -> 95.214164 | AB17: =H17/$H$39 -> 0.011518418 | AC17: =AB17*$AC$3 -> 76.547947
B18: 334F | C18: NRTC FOC | H18: 2000 | J18: =H18/$I$34 -> 0.013764358 | K18: =H18/$I$36 -> 0.012681716 | L18: =J18*$L$3 -> 115.02268 | M18: =J18*$M$3 -> 26.900235 | N18: =J18*$N$3 -> 40.881244 | O18: =J18*$O$3 -> 7.4948305 | P18: =J18*$P$3 -> 27.875715 | R18: =K18*$R$3 -> 38.121239 | S18: =K18*$S$3 -> 57.067723 | T18: =K18*$T$3 -> 21.458859 | U18: =K18*$U$3 -> 15.515065 | V18: =K18*$V$3 -> 3.9566955 | W18: =K18*$W$3 -> 17.333243 | X18: =K18*$X$3 -> 31.564792 | Y18: =K18*$Y$3 -> 14.260717 | Z18: =K18*$Z$3 -> 50.377864 | AB18: =H18/$H$39 -> 0.0060944008 | AC18: =AB18*$AC$3 -> 40.501559
B19: 335 | C19: NRTC 19 | H19: 3134.45 | J19: =H19/$I$34 -> 0.021571846 | K19: =H19/$I$36 -> 0.019875103 | L19: =J19*$L$3 -> 180.26642 | M19: =J19*$M$3 -> 42.158721 | N19: =J19*$N$3 -> 64.070107 | O19: =J19*$O$3 -> 11.746086 | P19: =J19*$P$3 -> 43.687517 | R19: =K19*$R$3 -> 59.744559 | S19: =K19*$S$3 -> 89.437963 | T19: =K19*$T$3 -> 33.63086 | U19: =K19*$U$3 -> 24.315598 | V19: =K19*$V$3 -> 6.2010321 | W19: =K19*$W$3 -> 27.165092 | X19: =K19*$X$3 -> 49.469131 | Y19: =K19*$Y$3 -> 22.349752 | Z19: =K19*$Z$3 -> 78.953449 | AB19: =H19/$H$39 -> 0.0095512973 | AC19: =AB19*$AC$3 -> 63.475056
B20: 368 | C20: Wells Fargo | H20: 2615.2 | J20: =H20/$I$34 -> 0.017998274 | K20: =H20/$I$36 -> 0.016582612 | L20: =J20*$L$3 -> 150.40366 | M20: =J20*$M$3 -> 35.174747 | N20: =J20*$N$3 -> 53.456314 | O20: =J20*$O$3 -> 9.8002403 | P20: =J20*$P$3 -> 36.450285 | R20: =K20*$R$3 -> 49.847332 | S20: =K20*$S$3 -> 74.621755 | T20: =K20*$T$3 -> 28.059604 | U20: =K20*$U$3 -> 20.287499 | V20: =K20*$V$3 -> 5.173775 | W20: =K20*$W$3 -> 22.664949 | X20: =K20*$X$3 -> 41.274122 | Y20: =K20*$Y$3 -> 18.647313 | Z20: =K20*$Z$3 -> 65.874096 | AB20: =H20/$H$39 -> 0.0079690385 | AC20: =AB20*$AC$3 -> 52.959839
B21: 451 | C21: USJP | H21: 23396.04 | J21: =H21/$I$34 -> 0.16101573 | K21: =H21/$I$36 -> 0.14835097 | L21: =J21*$L$3 -> 1345.5376 | M21: =J21*$M$3 -> 314.67949 | N21: =J21*$N$3 -> 478.22961 | O21: =J21*$O$3 -> 87.674677 | P21: =J21*$P$3 -> 326.09067 | R21: =K21*$R$3 -> 445.94302 | S21: =K21*$S$3 -> 667.57937 | T21: =K21*$T$3 -> 251.02616 | U21: =K21*$U$3 -> 181.49555 | V21: =K21*$V$3 -> 46.285503 | W21: =K21*$W$3 -> 202.76462 | X21: =K21*$X$3 -> 369.24557 | Y21: =K21*$Y$3 -> 166.82215 | Z21: =K21*$Z$3 -> 589.32127 | AB21: =H21/$H$39 -> 0.071292423 | AC21: =AB21*$AC$3 -> 473.78805
B22: 467 | C22: WF - United Airlines | H22: 3938.1 | J22: =H22/$I$34 -> 0.027102709 | K22: =H22/$I$36 -> 0.024970934 | L22: =J22*$L$3 -> 226.48541 | M22: =J22*$M$3 -> 52.967908 | N22: =J22*$N$3 -> 80.497213 | O22: =J22*$O$3 -> 14.757696 | P22: =J22*$P$3 -> 54.888677 | R22: =K22*$R$3 -> 75.062626 | S22: =K22*$S$3 -> 112.3692 | T22: =K22*$T$3 -> 42.253566 | U22: =K22*$U$3 -> 30.549939 | V22: =K22*$V$3 -> 7.7909313 | W22: =K22*$W$3 -> 34.130022 | X22: =K22*$X$3 -> 62.152653 | Y22: =K22*$Y$3 -> 28.080064 | Z22: =K22*$Z$3 -> 99.196534 | AB22: =H22/$H$39 -> 0.01200018 | AC22: =AB22*$AC$3 -> 79.749596
B23: 468 | C23: Newark Alliance | H23: 6307.7 | J23: =H23/$I$34 -> 0.04341072 | K23: =H23/$I$36 -> 0.039996231 | L23: =J23*$L$3 -> 362.76428 | M23: =J23*$M$3 -> 84.839306 | N23: =J23*$N$3 -> 128.93331 | O23: =J23*$O$3 -> 23.637571 | P23: =J23*$P$3 -> 87.915824 | R23: =K23*$R$3 -> 120.22867 | S23: =K23*$S$3 -> 179.98304 | T23: =K23*$T$3 -> 67.678022 | U23: =K23*$U$3 -> 48.932189 | V23: =K23*$V$3 -> 12.478824 | W23: =K23*$W$3 -> 54.666449 | X23: =K23*$X$3 -> 99.550619 | Y23: =K23*$Y$3 -> 44.976162 | Z23: =K23*$Z$3 -> 158.88423 | AB23: =H23/$H$39 -> 0.019220826 | AC23: =AB23*$AC$3 -> 127.73584
B24: 502 | C24: ESG | H24: 1915 | J24: =H24/$I$34 -> 0.013179373 | K24: =H24/$I$36 -> 0.012142743 | L24: =J24*$L$3 -> 110.13422 | M24: =J24*$M$3 -> 25.756975 | N24: =J24*$N$3 -> 39.143791 | O24: =J24*$O$3 -> 7.1763002 | P24: =J24*$P$3 -> 26.690997 | R24: =K24*$R$3 -> 36.501087 | S24: =K24*$S$3 -> 54.642345 | T24: =K24*$T$3 -> 20.546857 | U24: =K24*$U$3 -> 14.855675 | V24: =K24*$V$3 -> 3.7885359 | W24: =K24*$W$3 -> 16.59658 | X24: =K24*$X$3 -> 30.223288 | Y24: =K24*$Y$3 -> 13.654636 | Z24: =K24*$Z$3 -> 48.236805 | AB24: =H24/$H$39 -> 0.0058353888 | AC24: =AB24*$AC$3 -> 38.780243
B25: 515 | C25: FOC - HUD NUL PARS | H25: 3891.54 | J25: =H25/$I$34 -> 0.026782274 | K25: =H25/$I$36 -> 0.024675703 | L25: =J25*$L$3 -> 223.80768 | M25: =J25*$M$3 -> 52.34167 | N25: =J25*$N$3 -> 79.545498 | O25: =J25*$O$3 -> 14.583216 | P25: =J25*$P$3 -> 54.23973 | R25: =K25*$R$3 -> 74.175164 | S25: =K25*$S$3 -> 111.04066 | T25: =K25*$T$3 -> 41.754004 | U25: =K25*$U$3 -> 30.188749 | V25: =K25*$V$3 -> 7.6988194 | W25: =K25*$W$3 -> 33.726504 | X25: =K25*$X$3 -> 61.417825 | Y25: =K25*$Y$3 -> 27.748075 | Z25: =K25*$Z$3 -> 98.023737 | AB25: =H25/$H$39 -> 0.011858302 | AC25: =AB25*$AC$3 -> 78.806719
