Workbook

Sheet June Salary & Benefits 
B2: Payroll Register Attached | K2: Check Date | L2: Pay Period
K3: 43658 | L3: 06/23/19 - 07/06/19
K4: 43672 | L4: 07/07/19 - 07/20/19
B8: Salary Breakdown | C8: 43658 | D8: 43672 | F8: Total | G8: USJP Hours | H8: Allocation Rate
J9: Report | K9: GL
B10: COO Patricia Sermon | C10: 0 | D10: 0 | E10: 0 | F10: =SUM(C10:E10) -> 0 | H10: 0.5 | I10: =F10*H10 -> 0
B11: Director Gwendolyn Morris | F11: =SUM(C11:E11) -> 0 | H11: 1 | I11: =F11*H11 -> 0
B12: Director Gwendolyn Morris - Program | F12: =SUM(C12:E12) -> 0 | H12: 1 | I12: =F12*H12 -> 0
B13: Site Coordinator (Essex) Rahmel Leake - Program | F13: =SUM(C13:E13) -> 0 | H13: 0.2 | I13: =F13*H13 -> 0 | J13: =SUM(I10:I13) -> 0 | K13: =SUM(I10:I13) -> 0
B14: Site Coordinator (Passaic) Irene Cerna - Program
B15: Site Coordinator (Morris) Alberto Almanzar - Program | F15: =SUM(C15:E15) -> 0 | H15: 1 | I15: =F15*H15 -> 0 | J15: =I15 -> 0 | K15: =I15 -> 0 | L15: Educational Services
B16: Program Assistant Joanna Martinez - Admin
B17: Program Assistant Joanna Martinez - Program
B18: Staff Accountant - TBH | F18: =SUM(C18:E18) -> 0
F19: =SUM(C19:E19) -> 0
C20: =SUM(C10:C19) -> 0 | D20: =SUM(D10:D19) -> 0 | E20: =SUM(E10:E19) -> 0 | F20: =SUM(F10:F19) -> 0 | I20: =SUM(I10:I19) -> 0 | J20: =SUM(J10:J19) -> 0 | K20: =SUM(K10:K19) -> 0
B22: Payroll Taxes | I22: 0
B23: Payroll Fee Allocation | I23: 0 | J23: =SUM(I22:I23) -> 0 | K23: =J23 -> 0
B26: Benefits | C26: Medical | D26: Dental | F26: Total | H26: Allocation Rate
J27: Report | K27: GL
B28: Sermon | C28: 1118.65 | D28: 63.88 | F28: =SUM(C28:E28) -> 1182.53 | H28: 0.5 | I28: 0 | J28: =SUM(I28:I30) -> 0 | K28: =J28 -> 0
B29: Birdsong | F29: =SUM(C29:E29) -> 0 | H29: 1 | I29: =F29*H29 -> 0
B30: Cooper | F30: =SUM(C30:E30) -> 0 | H30: 1 | I30: =F30*H30 -> 0
B31: Johnson | C31: 1073.08 | D31: 67.82 | F31: =SUM(C31:E31) -> 1140.9 | H31: 0.2 | I31: 0 | J31: =I31 -> 0 | K31: =J31 -> 0
B32: Johnson | F32: =SUM(C32:E32) -> 0 | H32: 1 | I32: =F32*H32 -> 0 | J32: =I32 -> 0 | K32: =J32 -> 0
B33: Aikens | F33: =SUM(C33:E33) -> 0 | H33: 1 | I33: 0 | J33: =I33 -> 0 | K33: =J33 -> 0
F34: =SUM(C34:E34) -> 0 | J34: =SUM(J28:J33) -> 0 | K34: =SUM(K28:K33) -> 0
F35: =SUM(C35:E35) -> 0
F36: =SUM(C36:E36) -> 0
C37: =SUM(C28:C36) -> 2191.73 | D37: =SUM(D28:D36) -> 131.7 | F37: =SUM(F28:F36) -> 2323.43 | I37: =SUM(I28:I36) -> 0
I39: =I22+I37+I23 -> 0 | J39: =J34+J23 -> 0 | K39: =K34+K23 -> 0

Sheet Salaries & Fringe Allocations
A1: Urban Seniors Jobs Program PY 19 | D1: Month | E1: September
A2: ='Jul-2019'!A2 -> Urban League of Essex County | D2: Year | E2: 2019
A4: Payroll Period 07/01/19 - 07/06/19 | B4: Check Date | D4: 43658
A5: Staff Member | B5: USJP HOURS | C5: Total Hours | D5: Time Allocation (%) | E5: Total Salary | F5: USJP Salary | H5: ER Taxes Monthly Allocation | I5: Payroll Fees Monthly Allocation | J5: Monthly Health Ins. Medical | K5: Bi-weekly Medical Deduction | L5: Dental & Life Insurance | M5: Biweekly Dental Insur Deduction | N5: W/Comp Monthly Allocation | O5: Pension | P5: Enter other | Q5: Total Benefits
A6: COO Patricia Sermon - Admin | B6: 7 | C6: 35 | D6: =B6/C6 -> 0.2 | E6: =3153.85-1576.93 -> 1576.92 | F6: =ROUND(D6*E6,2) -> 315.38 | K6: =-103.26*D6 -> -20.652 | M6: =-3.37*D6 -> -0.674 | Q6: =SUM(H6:P6) -> -21.326
A7: Director Gwendolyn Morris - Admin | B7: 14.5 | C7: 35 | D7: =B7/C7 -> 0.41428571 | E7: =2500/2 -> 1250 | F7: =ROUND(D7*E7,2) -> 517.86 | K7: =-94.11*D7 -> -38.988429 | M7: =-3.37*D7 -> -1.3961429 | Q7: =SUM(H7:P7) -> -40.384571
A8: Director Gwendolyn Morris - Program | B8: 20.5 | C8: 35 | D8: =B8/C8 -> 0.58571429 | F8: =ROUND(D8*E7,2) -> 732.14 | K8: =-94.11*D8 -> -55.121571 | M8: =-3.37*D8 -> -1.9738571 | Q8: =SUM(H8:P8) -> -57.095429
A9: Site Coordinator (Essex) Rahmel Leake - Program | B9: 0 | C9: 0 | D9: 0 | E9: 0 | F9: =ROUND(E9,2) -> 0 | K9: 0 | Q9: =SUM(H9:P9) -> 0
A10: Site Coordinator (Passaic) Irene Cerna - Program | B10: 35 | C10: 35 | D10: =B10/C10 -> 1 | E10: =1038.47-461.44 -> 577.03 | F10: =ROUND(E10,2) -> 577.03 | K10: =-103.26*D10 -> -103.26 | Q10: =SUM(H10:P10) -> -103.26
A11: Site Coordinator (Morris) Alberto Almanzar - Program | B11: 24 | C11: =+B11 -> 24 | D11: =B11/C11 -> 1 | E11: =1278.68-932.6 -> 346.08 | F11: =ROUND(E11,2) -> 346.08 | K11: 0 | Q11: =SUM(H11:P11) -> 0
A12: Program Assistant Joanna Martinez - Admin | B12: 15 | C12: 35 | D12: =B12/C12 -> 0.42857143 | E12: =2538.47-1769.23 -> 769.24 | F12: =ROUND(D12*E12,2) -> 329.67 | K12: =-191.25*D12 -> -81.964286 | M12: =-6.08*D12 -> -2.6057143 | Q12: =SUM(H12:P12) -> -84.57
A13: Program Assistant Joanna Martinez - Program | B13: 20 | C13: 35 | D13: =B13/C13 -> 0.57142857 | F13: =ROUND(D13*E12,2) -> 439.57 | K13: =-191.25*D13 -> -109.28571 | M13: =-6.08*D13 -> -3.4742857 | Q13: =SUM(H13:P13) -> -112.76
A14: Staff Accountant - TBH | Q14: =SUM(H14:P14) -> 0
A15: Total | C15: =SUM(C6:C14) -> 234 | E15: =SUBTOTAL(109,'Salaries & Fringe Allocations'!E6:E14) -> 4519.27 | F15: =SUBTOTAL(109,'Salaries & Fringe Allocations'!F6:F14) -> 3257.73 | H15: =SUBTOTAL(109,'Salaries & Fringe Allocations'!H6:H14) -> 0 | I15: =SUBTOTAL(109,'Salaries & Fringe Allocations'!I6:I14) -> 0 | J15: =SUBTOTAL(109,'Salaries & Fringe Allocations'!J6:J14) -> 0 | K15: =SUBTOTAL(109,'Salaries & Fringe Allocations'!K6:K14) -> -409.272 | L15: =SUBTOTAL(109,'Salaries & Fringe Allocations'!L6:L14) -> 0 | M15: =SUBTOTAL(109,'Salaries & Fringe Allocations'!M6:M14) -> -10.124 | N15: =SUBTOTAL(109,'Salaries & Fringe Allocations'!N6:N14) -> 0 | O15: =SUBTOTAL(109,'Salaries & Fringe Allocations'!O6:O14) -> 0 | ... Q15: =SUBTOTAL(109,'Salaries & Fringe Allocations'!Q6:Q14) -> -419.396
A17: Payroll Period Ending 07/07/19 - 07/20/19 | B17: Check Date | D17: 43672
A18: Staff Member | B18: USJP HOURS | C18: Total Hours | D18: Time Allocation (%) | E18: Total Salary | F18: USJP Salary | H18: ER Taxes Monthly Allocation | I18: Payroll Fees Monthly Allocation | J18: Monthly Health Ins. Medical | K18: Bi-weekly Medical Deduction | L18: Dental & Life Insurance | M18: Biweekly Dental Insur Deduction | N18: W/Comp Monthly Allocation | O18: Pension | P18: Enter other | Q18: Total Benefits
A19: COO Patricia Sermon - Admin | B19: 14 | C19: 70 | D19: =B19/C19 -> 0.2 | E19: 3153.85 | F19: =ROUND(D19*E19,2) -> 630.77 | K19: =-103.26*D19 -> -20.652 | M19: =-3.37*D19 -> -0.674 | Q19: =SUM(H19:P19) -> -21.326
A20: Director Gwendolyn Morris - Admin | B20: =14+15 -> 29 | C20: 70 | D20: =B20/C20 -> 0.41428571 | E20: 2500 | F20: =ROUND(D20*E20,2) -> 1035.71 | K20: =-97.01*D20 -> -40.189857 | M20: =-3.37*D20 -> -1.3961429 | Q20: =SUM(H20:P20) -> -41.586
A21: Director Gwendolyn Morris - Program | B21: =21+20 -> 41 | D21: =B21/C20 -> 0.58571429 | E21: 0 | F21: =ROUND(D21*E20,2) -> 1464.29 | K21: =-97.01*D21 -> -56.820143 | M21: =-3.37*D21 -> -1.9738571 | Q21: =SUM(H21:P21) -> -58.794
A22: Site Coordinator (Essex) Rahmel Leake - Program | B22: 35 | C22: 35 | D22: =B22/C22 -> 1 | E22: 769.24 | F22: =ROUND(D22*E22,2) -> 769.24 | K22: 0 | Q22: =SUM(H22:P22) -> 0
A23: Site Coordinator (Passaic) Irene Cerna - Program | B23: 70 | C23: 70 | D23: =B23/C23 -> 1 | E23: 1153.85 | F23: =ROUND(D23*E23,2) -> 1153.85 | K23: =-103.26*D23 -> -103.26 | Q23: =SUM(H23:P23) -> -103.26
A24: Site Coordinator (Morris) Alberto Almanzar - Program | B24: 60 | C24: 60 | D24: =B24/C24 -> 1 | E24: 865.2 | F24: =ROUND(D24*E24,2) -> 865.2 | K24: 0 | Q24: =SUM(H24:P24) -> 0
A25: Program Assistant Joanna Martinez - Admin | B25: 30 | C25: 70 | D25: =B25/C25 -> 0.42857143 | E25: 1538.47 | F25: =ROUND(D25*E25,2) -> 659.34 | K25: =-127.17*D25 -> -54.501429 | M25: =-6.08*D25 -> -2.6057143 | Q25: =SUM(H25:P25) -> -57.107143
A26: Program Assistant Joanna Martinez - Program | B26: 40 | D26: =B26/C25 -> 0.57142857 | E26: 0 | F26: =ROUND(D26*E25,2) -> 879.13 | K26: =-127.17*D26 -> -72.668571 | M26: =-6.08*D26 -> -3.4742857 | Q26: =SUM(H26:P26) -> -76.142857
A27: Staff Accountant - TBH | Q27: =SUM(H27:P27) -> 0
A28: Total | C28: =SUM(C19:C27) -> 375 | E28: =SUBTOTAL(109,'Salaries & Fringe Allocations'!E19:E27) -> 9980.61 | F28: =SUBTOTAL(109,'Salaries & Fringe Allocations'!F19:F27) -> 7457.53 | H28: =SUBTOTAL(109,'Salaries & Fringe Allocations'!H19:H27) -> 0 | I28: =SUBTOTAL(109,'Salaries & Fringe Allocations'!I19:I27) -> 0 | J28: =SUBTOTAL(109,'Salaries & Fringe Allocations'!J19:J27) -> 0 | K28: =SUBTOTAL(109,'Salaries & Fringe Allocations'!K19:K27) -> -348.092 | L28: =SUBTOTAL(109,'Salaries & Fringe Allocations'!L19:L27) -> 0 | M28: =SUBTOTAL(109,'Salaries & Fringe Allocations'!M19:M27) -> -10.124 | N28: =SUBTOTAL(109,'Salaries & Fringe Allocations'!N19:N27) -> 0 | O28: =SUBTOTAL(109,'Salaries & Fringe Allocations'!O19:O27) -> 0 | ... Q28: =SUBTOTAL(109,'Salaries & Fringe Allocations'!Q19:Q27) -> -358.216
A30: Monthly Total for July 2019
A31: Staff Member | B31: USJP HOURS | C31: Total Hours | D31: Time Allocation (%) | E31: Total Salary | F31: USJP Salary | G31: Allocation % | H31: ER Taxes Monthly Allocation | I31: Payroll Fees Monthly Allocation | J31: Monthly Health Ins. Medical | K31: Bi-weekly Medical Deduction | L31: Dental & Life Insurance | M31: Biweekly Dental Insur Deduction | N31: W/Comp Monthly Allocation | O31: Pension | P31: Enter other | Q31: Total Benefits
A32: COO Patricia Sermon - Admin | B32: =+B6+B19 -> 21 | C32: =+C6+C19 -> 105 | D32: =B32/C32 -> 0.2 | E32: =+E6+E19 -> 4730.77 | F32: =ROUND(D32*E32,2) -> 946.15 | G32: =+F32/$F$41 -> 0.088299304 | H32: =+G32*'Jul-2019 GL'!$G$60 -> 94.950891 | I32: =+G32*'Jul-2019 GL'!$G$63 -> 12.40252 | J32: =1118.65*D32 -> 223.73 | K32: =+K6+K19 -> -41.304 | L32: =63.88*D32 -> 12.776 | M32: =+M6+M19 -> -1.348 | N32: =+$G32*'Jul-2019 GL'!$G$45 -> 32.767872 | O32: =+O6+O19 -> 0 | P32: =+P6+P19 -> 0 | Q32: =SUM(H32:P32) -> 333.97528 | R32: ADMIN
A33: Director Gwendolyn Morris - Admin | B33: =+B7+B20 -> 43.5 | C33: =+C7+C20 -> 105 | D33: =B33/C33 -> 0.41428571 | E33: =+E7+E20 -> 3750 | F33: =ROUND(D33*E33,2) -> 1553.57 | G33: =+F33/$F$41 -> 0.14498668 | H33: =+G33*'Jul-2019 GL'!$G$60 -> 155.90853 | I33: =+G33*'Jul-2019 GL'!$G$63 -> 20.364829 | J33: =1050.94*D33 -> 435.38943 | K33: =+K7+K20 -> -79.178286 | L33: =79.63*D33 -> 32.989571 | M33: =+M7+M20 -> -2.7922857 | N33: =+$G33*'Jul-2019 GL'!$G$45 -> 53.804558 | O33: =+O7+O20 -> 0 | P33: =+P7+P20 -> 0 | Q33: =SUM(H33:P33) -> 616.48635 | R33: ADMIN
A34: Director Gwendolyn Morris - Program | B34: =+B8+B21 -> 61.5 | D34: =B34/C33 -> 0.58571429 | E34: =+E8+E21 -> 0 | F34: =ROUND(D34*E33,2) -> 2196.43 | G34: =+F34/$F$41 -> 0.20498149 | H34: =+G34*'Jul-2019 GL'!$G$60 -> 220.42275 | I34: =+G34*'Jul-2019 GL'!$G$63 -> 28.791701 | J34: =1050.94*D34 -> 615.55057 | K34: =+K8+K21 -> -111.94171 | L34: =79.63*D34 -> 46.640429 | M34: =+M8+M21 -> -3.9477143 | N34: =+$G34*'Jul-2019 GL'!$G$45 -> 76.068632 | O34: =+O8+O21 -> 0 | P34: =+P8+P21 -> 0 | Q34: =SUM(H34:P34) -> 871.58465
A35: Site Coordinator (Essex) Rahmel Leake - Program | B35: =+B9+B22 -> 35 | C35: =+C9+C22 -> 35 | D35: =B35/C35 -> 1 | E35: =+E9+E22 -> 769.24 | F35: =ROUND(D35*E35,2) -> 769.24 | G35: =+F35/$F$41 -> 0.071789205 | H35: =+G35*'Jul-2019 GL'!$G$60 -> 77.197086 | I35: =+G35*'Jul-2019 GL'!$G$63 -> 10.083512 | J35: 0 | K35: =+K9+K22 -> 0 | L35: 0 | M35: =+M9+M22 -> 0 | N35: =+$G35*'Jul-2019 GL'!$G$45 -> 26.640974 | O35: =+O9+O22 -> 0 | P35: =+P9+P22 -> 0 | Q35: =SUM(H35:P35) -> 113.92157
A36: Site Coordinator (Passaic) Irene Cerna - Program | B36: =+B10+B23 -> 105 | C36: =+C10+C23 -> 105 | D36: =B36/C36 -> 1 | E36: =+E10+E23 -> 1730.88 | F36: =ROUND(D36*E36,2) -> 1730.88 | G36: =+F36/$F$41 -> 0.16153411 | H36: =+G36*'Jul-2019 GL'!$G$60 -> 173.70248 | I36: =+G36*'Jul-2019 GL'!$G$63 -> 22.689081 | J36: 1118.65 | K36: =+K10+K23 -> -206.52 | L36: 0 | M36: =+M10+M23 -> 0 | N36: =+$G36*'Jul-2019 GL'!$G$45 -> 59.945309 | O36: =+O10+O23 -> 0 | P36: =+P10+P23 -> 0 | Q36: =SUM(H36:P36) -> 1168.4669
A37: Site Coordinator (Morris) Alberto Almanzar - Program | B37: =+B11+B24 -> 84 | C37: =+C11+C24 -> 84 | D37: =B37/C37 -> 1 | E37: =+E11+E24 -> 1211.28 | F37: =ROUND(D37*E37,2) -> 1211.28 | G37: =+F37/$F$41 -> 0.11304252 | H37: =+G37*'Jul-2019 GL'!$G$60 -> 121.55801 | I37: =+G37*'Jul-2019 GL'!$G$63 -> 15.877952 | J37: 0 | K37: =+K11+K24 -> 0 | L37: 0 | M37: =+M11+M24 -> 0 | N37: =+$G37*'Jul-2019 GL'!$G$45 -> 41.950079 | O37: =+O11+O24 -> 0 | P37: =+P11+P24 -> 0 | Q37: =SUM(H37:P37) -> 179.38605
A38: Program Assistant Joanna Martinez - Admin | B38: =+B12+B25 -> 45 | C38: =+C12+C25 -> 105 | D38: =B38/C38 -> 0.42857143 | E38: =+E12+E25 -> 2307.71 | F38: =ROUND(D38*E38,2) -> 989.02 | G38: =+F38/$F$41 -> 0.09230014 | H38: =+G38*'Jul-2019 GL'!$G$60 -> 99.25311 | I38: =+G38*'Jul-2019 GL'!$G$63 -> 12.964478 | J38: =1377.69*D38 -> 590.43857 | K38: =+K12+K25 -> -136.46571 | L38: =77.55*D38 -> 33.235714 | M38: =+M12+M25 -> -5.2114286 | N38: =+$G38*'Jul-2019 GL'!$G$45 -> 34.252582 | O38: =+O12+O25 -> 0 | P38: =+P12+P25 -> 0 | Q38: =SUM(H38:P38) -> 628.46731 | R38: ADMIN
A39: Program Assistant Joanna Martinez - Program | B39: =+B13+B26 -> 60 | D39: =B39/C38 -> 0.57142857 | E39: =+E13+E26 -> 0 | F39: =ROUND(D39*E38,2) -> 1318.69 | G39: =+F39/$F$41 -> 0.12306654 | H39: =+G39*'Jul-2019 GL'!$G$60 -> 132.33715 | I39: =+G39*'Jul-2019 GL'!$G$63 -> 17.285927 | J39: =1377.69*D39 -> 787.25143 | K39: =+K13+K26 -> -181.95429 | L39: =77.55*D39 -> 44.314286 | M39: =+M13+M26 -> -6.9485714 | N39: =+$G39*'Jul-2019 GL'!$G$45 -> 45.669994 | O39: =+O13+O26 -> 0 | P39: =+P13+P26 -> 0 | Q39: =SUM(H39:P39) -> 837.95592
A40: Staff Accountant - TBH | Q40: =SUM(H40:P40) -> 0 | R40: ADMIN
A41: Total per USJP Report | C41: =SUM(C32:C40) -> 539 | E41: =SUBTOTAL(109,'Salaries & Fringe Allocations'!E32:E40) -> 14499.88 | F41: =SUBTOTAL(109,'Salaries & Fringe Allocations'!F32:F40) -> 10715.26 | G41: =SUM(G32:G40) -> 1 | H41: =SUBTOTAL(109,'Salaries & Fringe Allocations'!H32:H40) -> 1075.33 | I41: =SUBTOTAL(109,'Salaries & Fringe Allocations'!I32:I40) -> 140.46 | J41: =SUBTOTAL(109,'Salaries & Fringe Allocations'!J32:J40) -> 3771.01 | K41: =SUBTOTAL(109,'Salaries & Fringe Allocations'!K32:K40) -> -757.364 | L41: =SUBTOTAL(109,'Salaries & Fringe Allocations'!L32:L40) -> 169.956 | M41: =SUBTOTAL(109,'Salaries & Fringe Allocations'!M32:M40) -> -20.248 | N41: =SUBTOTAL(109,'Salaries & Fringe Allocations'!N32:N40) -> 371.1 | O41: =SUBTOTAL(109,'Salaries & Fringe Allocations'!O32:O40) -> 0 | ... Q41: =SUBTOTAL(109,'Salaries & Fringe Allocations'!Q32:Q40) -> 4750.244
A45: Payroll Period 07/21/19 - 08/03/19 | B45: Check Date | D45: 43686
A46: Staff Member | B46: USJP HOURS | C46: Total Hours | D46: Time Allocation (%) | E46: Total Salary | F46: USJP Salary | H46: ER Taxes Monthly Allocation | I46: Payroll Fees Monthly Allocation | J46: Monthly Health Ins. Medical | K46: Bi-weekly Medical Deduction | L46: Dental & Life Insurance | M46: Biweekly Dental Insur Deduction | N46: W/Comp Monthly Allocation | O46: Pension | P46: Enter other | Q46: Total Benefits
A47: COO Patricia Sermon - Admin | B47: 14 | C47: 70 | D47: =B47/C47 -> 0.2 | E47: 3153.85 | F47: =ROUND(D47*E47,2) -> 630.77 | K47: =-103.26*D47 -> -20.652 | M47: =-3.37*D47 -> -0.674 | Q47: =SUM(H47:P47) -> -21.326
A48: Director Gwendolyn Morris - Admin | B48: =14.5+15.5 -> 30 | C48: 70 | D48: =B48/C48 -> 0.42857143 | E48: 2500 | F48: =ROUND(D48*E48,2) -> 1071.43 | K48: =-97.01*D48 -> -41.575714 | M48: =-3.37*D48 -> -1.4442857 | Q48: =SUM(H48:P48) -> -43.02
A49: Director Gwendolyn Morris - Program | B49: =20.5+19.5 -> 40 | C49: 70 | D49: =B49/C49 -> 0.57142857 | F49: =ROUND(D49*E48,2) -> 1428.57 | K49: =-97.01*D49 -> -55.434286 | M49: =-3.37*D49 -> -1.9257143 | Q49: =SUM(H49:P49) -> -57.36
A50: Site Coordinator (Essex) Rahmel Leake - Program | B50: 70 | C50: 70 | D50: =B50/C50 -> 1 | E50: 1538.47 | F50: =ROUND(E50,2) -> 1538.47 | K50: 0 | Q50: =SUM(H50:P50) -> 0
A51: Site Coordinator (Passaic) Irene Cerna - Program | B51: 70 | C51: 70 | D51: =B51/C51 -> 1 | E51: 1153.85 | F51: =ROUND(E51,2) -> 1153.85 | K51: =-103.26*D51 -> -103.26 | Q51: =SUM(H51:P51) -> -103.26
A52: Site Coordinator (Morris) Alberto Almanzar - Program | B52: 60 | C52: 60 | D52: =B52/C52 -> 1 | E52: 865.2 | F52: =ROUND(E52,2) -> 865.2 | K52: 0 | Q52: =SUM(H52:P52) -> 0
A53: Program Assistant Joanna Martinez - Admin | B53: 30 | C53: 70 | D53: =B53/C53 -> 0.42857143 | E53: 1538.47 | F53: =ROUND(D53*E53,2) -> 659.34 | K53: =-127.17*D53 -> -54.501429 | M53: =-6.08*D53 -> -2.6057143 | Q53: =SUM(H53:P53) -> -57.107143
A54: Program Assistant Joanna Martinez - Program | B54: =18.25*2 -> 36.5 | C54: 70 | D54: =B54/C54 -> 0.52142857 | F54: =ROUND(D54*E53,2) -> 802.2 | K54: =-127.17*D54 -> -66.310071 | M54: =-6.08*D54 -> -3.1702857 | Q54: =SUM(H54:P54) -> -69.480357
A55: Staff Accountant - Gregory Ward | B55: 7 | C55: 70 | D55: =B55/C55 -> 0.1 | E55: 4230.77 | F55: =ROUND(D55*E55,2) -> 423.08 | K55: =-103.26*D55 -> -10.326 | M55: =-3.37*D55 -> -0.337 | Q55: =SUM(H55:P55) -> -10.663
A56: Total | E56: =SUBTOTAL(109,'Salaries & Fringe Allocations'!E47:E55) -> 14980.61 | F56: =SUBTOTAL(109,'Salaries & Fringe Allocations'!F47:F55) -> 8572.91 | H56: =SUBTOTAL(109,'Salaries & Fringe Allocations'!H47:H55) -> 0 | I56: =SUBTOTAL(109,'Salaries & Fringe Allocations'!I47:I55) -> 0 | J56: =SUBTOTAL(109,'Salaries & Fringe Allocations'!J47:J55) -> 0 | K56: =SUBTOTAL(109,'Salaries & Fringe Allocations'!K47:K55) -> -352.0595 | L56: =SUBTOTAL(109,'Salaries & Fringe Allocations'!L47:L55) -> 0 | M56: =SUBTOTAL(109,'Salaries & Fringe Allocations'!M47:M55) -> -10.157 | N56: =SUBTOTAL(109,'Salaries & Fringe Allocations'!N47:N55) -> 0 | O56: =SUBTOTAL(109,'Salaries & Fringe Allocations'!O47:O55) -> 0 | ... Q56: =SUBTOTAL(109,'Salaries & Fringe Allocations'!Q47:Q55) -> -362.2165
A58: Payroll Period Ending 08/04/19 - 08/17/19 | B58: Check Date | D58: 43700
A59: Staff Member | B59: USJP HOURS | C59: Total Hours | D59: Time Allocation (%) | E59: Total Salary | F59: USJP Salary | H59: ER Taxes Monthly Allocation | I59: Payroll Fees Monthly Allocation | J59: Monthly Health Ins. Medical | K59: Bi-weekly Medical Deduction | L59: Dental & Life Insurance | M59: Biweekly Dental Insur Deduction | N59: W/Comp Monthly Allocation | O59: Pension | P59: Enter other | Q59: Total Benefits
A60: COO Patricia Sermon - Admin | B60: 14 | C60: 70 | D60: =B60/C60 -> 0.2 | E60: 3153.85 | F60: =ROUND(D60*E60,2) -> 630.77 | K60: =-103.26*D60 -> -20.652 | M60: =-3.37*D60 -> -0.674 | Q60: =SUM(H60:P60) -> -21.326
A61: Director Gwendolyn Morris - Admin | B61: =14+15 -> 29 | C61: 70 | D61: =B61/C61 -> 0.41428571 | E61: 2500 | F61: =ROUND(D61*E61,2) -> 1035.71 | K61: =-97.01*D61 -> -40.189857 | M61: =-3.37*D61 -> -1.3961429 | Q61: =SUM(H61:P61) -> -41.586
A62: Director Gwendolyn Morris - Program | B62: =21+20 -> 41 | C62: 70 | D62: =B62/C61 -> 0.58571429 | E62: 0 | F62: =ROUND(D62*E61,2) -> 1464.29 | K62: =-97.01*D62 -> -56.820143 | M62: =-3.37*D62 -> -1.9738571 | Q62: =SUM(H62:P62) -> -58.794
A63: Site Coordinator (Essex) Rahmel Leake - Program | B63: 70 | C63: 70 | D63: =B63/C63 -> 1 | E63: 1538.47 | F63: =ROUND(D63*E63,2) -> 1538.47 | K63: 0 | Q63: =SUM(H63:P63) -> 0
A64: Site Coordinator (Passaic) Irene Cerna - Program | B64: 70 | C64: 70 | D64: =B64/C64 -> 1 | E64: 1153.85 | F64: =ROUND(D64*E64,2) -> 1153.85 | K64: =-103.26*D64 -> -103.26 | Q64: =SUM(H64:P64) -> -103.26
A65: Site Coordinator (Morris) Alberto Almanzar - Program | B65: 60 | C65: 60 | D65: =B65/C65 -> 1 | E65: 865.2 | F65: =ROUND(D65*E65,2) -> 865.2 | K65: 0 | Q65: =SUM(H65:P65) -> 0
A66: Program Assistant Joanna Martinez - Admin | B66: =15*2 -> 30 | C66: 70 | D66: =B66/C66 -> 0.42857143 | E66: 1538.47 | F66: =ROUND(D66*E66,2) -> 659.34 | K66: =-127.17*D66 -> -54.501429 | M66: =-6.08*D66 -> -2.6057143 | Q66: =SUM(H66:P66) -> -57.107143
A67: Program Assistant Joanna Martinez - Program | B67: =18.25*2 -> 36.5 | C67: 70 | D67: =B67/C66 -> 0.52142857 | E67: 0 | F67: =ROUND(D67*E66,2) -> 802.2 | K67: =-127.17*D67 -> -66.310071 | M67: =-6.08*D67 -> -3.1702857 | Q67: =SUM(H67:P67) -> -69.480357
A68: Staff Accountant - Gregory Ward | B68: 7 | C68: 70 | D68: =B68/C68 -> 0.1 | E68: 4230.77 | F68: =ROUND(D68*E68,2) -> 423.08 | K68: =-103.26*D68 -> -10.326 | M68: =-3.37*D68 -> -0.337 | Q68: =SUM(H68:P68) -> -10.663
A69: Total | E69: =SUBTOTAL(109,'Salaries & Fringe Allocations'!E60:E68) -> 14980.61 | F69: =SUBTOTAL(109,'Salaries & Fringe Allocations'!F60:F68) -> 8572.91 | H69: =SUBTOTAL(109,'Salaries & Fringe Allocations'!H60:H68) -> 0 | I69: =SUBTOTAL(109,'Salaries & Fringe Allocations'!I60:I68) -> 0 | J69: =SUBTOTAL(109,'Salaries & Fringe Allocations'!J60:J68) -> 0 | K69: =SUBTOTAL(109,'Salaries & Fringe Allocations'!K60:K68) -> -352.0595 | L69: =SUBTOTAL(109,'Salaries & Fringe Allocations'!L60:L68) -> 0 | M69: =SUBTOTAL(109,'Salaries & Fringe Allocations'!M60:M68) -> -10.157 | N69: =SUBTOTAL(109,'Salaries & Fringe Allocations'!N60:N68) -> 0 | O69: =SUBTOTAL(109,'Salaries & Fringe Allocations'!O60:O68) -> 0 | ... Q69: =SUBTOTAL(109,'Salaries & Fringe Allocations'!Q60:Q68) -> -362.2165
A71: Monthly Total for August 2019
A72: Staff Member | B72: USJP HOURS | C72: Total Hours | D72: Time Allocation (%) | E72: Total Salary | F72: USJP Salary | G72: Allocation % | H72: ER Taxes Monthly Allocation | I72: Payroll Fees Monthly Allocation | J72: Monthly Health Ins. Medical | K72: Bi-weekly Medical Deduction | L72: Dental & Life Insurance | M72: Biweekly Dental Insur Deduction | N72: W/Comp Monthly Allocation | O72: Pension | P72: Enter other | Q72: Total Benefits
A73: COO Patricia Sermon - Admin | B73: =+B47+B60 -> 28 | C73: =+C47+C60 -> 140 | D73: =B73/C73 -> 0.2 | E73: =+E47+E60 -> 6307.7 | F73: =ROUND(D73*E73,2) -> 1261.54 | G73: =+F73/$F$122 -> 0.084450377 | H73: =+G73*'Aug 2019 GL'!$G$62 -> 134.02275 | I73: =+G73*'Aug 2019 GL'!$G$66 -> 17.98793 | J73: =1118.65*D73 -> 223.73 | K73: =+K47+K60 -> -41.304 | L73: =63.88*D73 -> 12.776 | M73: =+M47+M60 -> -1.348 | N73: =+$G73*'Aug 2019 GL'!$G$47 -> 41.718486 | O73: =+O47+O60 -> 0 | P73: =+P47+P60 -> 0 | Q73: =SUM(H73:P73) -> 387.58316 | R73: ADMIN
A74: Director Gwendolyn Morris - Admin | B74: =+B48+B61 -> 59 | C74: =+C48+C61 -> 140 | D74: =B74/C74 -> 0.42142857 | E74: =+E48+E61 -> 5000 | F74: =ROUND(D74*E74,2) -> 2107.14 | G74: =+F74/$F$122 -> 0.14105678 | H74: =+G74*'Aug 2019 GL'!$G$62 -> 223.85711 | I74: =+G74*'Aug 2019 GL'!$G$66 -> 30.045094 | J74: =1050.94*D74 -> 442.89614 | K74: =+K48+K61 -> -81.765571 | L74: =79.63*D74 -> 33.558357 | M74: =+M48+M61 -> -2.8404286 | N74: =+$G74*'Aug 2019 GL'!$G$47 -> 69.682048 | O74: =+O48+O61 -> 0 | P74: =+P48+P61 -> 0 | Q74: =SUM(H74:P74) -> 715.43275 | R74: ADMIN
A75: Director Gwendolyn Morris - Program | B75: =+B49+B62 -> 81 | D75: =B75/C74 -> 0.57857143 | E75: =+E49+E62 -> 0 | F75: =ROUND(D75*E74,2) -> 2892.86 | G75: =+F75/$F$122 -> 0.19365467 | H75: =+G75*'Aug 2019 GL'!$G$62 -> 307.32997 | I75: =+G75*'Aug 2019 GL'!$G$66 -> 41.248446 | J75: =1050.94*D75 -> 608.04386 | K75: =+K49+K62 -> -112.25443 | L75: =79.63*D75 -> 46.071643 | M75: =+M49+M62 -> -3.8995714 | N75: =+$G75*'Aug 2019 GL'!$G$47 -> 95.665409 | O75: =+O49+O62 -> 0 | P75: =+P49+P62 -> 0 | Q75: =SUM(H75:P75) -> 982.20532
A76: Site Coordinator (Essex) Rahmel Leake - Program | B76: =+B50+B63 -> 140 | C76: =+C50+C63 -> 140 | D76: =B76/C76 -> 1 | E76: =+E50+E63 -> 3076.94 | F76: =ROUND(D76*E76,2) -> 3076.94 | G76: =+F76/$F$122 -> 0.20597741 | H76: =+G76*'Aug 2019 GL'!$G$62 -> 326.88615 | I76: =+G76*'Aug 2019 GL'!$G$66 -> 43.873189 | J76: 0 | K76: =+K50+K63 -> 0 | L76: 0 | M76: =+M50+M63 -> 0 | N76: =+$G76*'Aug 2019 GL'!$G$47 -> 101.75284 | O76: =+O50+O63 -> 0 | P76: =+P50+P63 -> 0 | Q76: =SUM(H76:P76) -> 472.51218
A77: Site Coordinator (Passaic) Irene Cerna - Program | B77: =+B51+B64 -> 140 | C77: =+C51+C64 -> 140 | D77: =B77/C77 -> 1 | E77: =+E51+E64 -> 2307.7 | F77: =ROUND(D77*E77,2) -> 2307.7 | G77: =+F77/$F$122 -> 0.15448272 | H77: =+G77*'Aug 2019 GL'!$G$62 -> 245.16408 | I77: =+G77*'Aug 2019 GL'!$G$66 -> 32.90482 | J77: 1118.65 | K77: =+K51+K64 -> -206.52 | L77: 0 | M77: =+M51+M64 -> 0 | N77: =+$G77*'Aug 2019 GL'!$G$47 -> 76.314465 | O77: =+O51+O64 -> 0 | P77: =+P51+P64 -> 0 | Q77: =SUM(H77:P77) -> 1266.5134
A78: Site Coordinator (Morris) Alberto Almanzar - Program | B78: =+B52+B65 -> 120 | C78: =+C52+C65 -> 120 | D78: =B78/C78 -> 1 | E78: =+E52+E65 -> 1730.4 | F78: =ROUND(D78*E78,2) -> 1730.4 | G78: =+F78/$F$122 -> 0.11583694 | H78: =+G78*'Aug 2019 GL'!$G$62 -> 183.83322 | I78: =+G78*'Aug 2019 GL'!$G$66 -> 24.673268 | J78: 0 | K78: =+K52+K65 -> 0 | L78: 0 | M78: =+M52+M65 -> 0 | N78: =+$G78*'Aug 2019 GL'!$G$47 -> 57.223448 | O78: =+O52+O65 -> 0 | P78: =+P52+P65 -> 0 | Q78: =SUM(H78:P78) -> 265.72994
A79: Program Assistant Joanna Martinez - Admin | B79: =+B53+B66 -> 60 | C79: =+C53+C66 -> 140 | D79: =B79/C79 -> 0.42857143 | E79: =+E53+E66 -> 3076.94 | F79: =ROUND(D79*E79,2) -> 1318.69 | G79: =+F79/$F$122 -> 0.088276129 | H79: =+G79*'Aug 2019 GL'!$G$62 -> 140.09422 | I79: =+G79*'Aug 2019 GL'!$G$66 -> 18.802815 | J79: =1377.69*D79 -> 590.43857 | K79: =+K53+K66 -> -109.00286 | L79: =77.55*D79 -> 33.235714 | M79: =+M53+M66 -> -5.2114286 | N79: =+$G79*'Aug 2019 GL'!$G$47 -> 43.608408 | O79: =+O53+O66 -> 0 | P79: =+P53+P66 -> 0 | Q79: =SUM(H79:P79) -> 711.96544 | R79: ADMIN
A80: Program Assistant Joanna Martinez - Program | B80: =+B54+B67 -> 73 | D80: =B80/C79 -> 0.52142857 | E80: =+E54+E67 -> 0 | F80: =ROUND(D80*E79,2) -> 1604.4 | G80: =+F80/$F$122 -> 0.10740221 | H80: =+G80*'Aug 2019 GL'!$G$62 -> 170.44731 | I80: =+G80*'Aug 2019 GL'!$G$66 -> 22.876671 | J80: =1377.69*D80 -> 718.36693 | K80: =+K54+K67 -> -132.62014 | L80: =77.55*D80 -> 40.436786 | M80: =+M54+M67 -> -6.3405714 | N80: =+$G80*'Aug 2019 GL'!$G$47 -> 53.056692 | O80: =+O54+O67 -> 0 | P80: =+P54+P67 -> 0 | Q80: =SUM(H80:P80) -> 866.22367
A81: Staff Accountant - Gregory Ward - Admin | B81: =+B55+B68 -> 14 | C81: =+C55+C68 -> 140 | D81: =B81/C81 -> 0.1 | E81: =+E55+E68 -> 8461.54 | F81: =ROUND(D81*E81,2) -> 846.15 | G81: =+F81/$F$122 -> 0.056643219 | H81: =+G81*'Aug 2019 GL'!$G$62 -> 89.892789 | I81: =+G81*'Aug 2019 GL'!$G$66 -> 12.065006 | J81: =1118.65*D81 -> 111.865 | K81: =+K55+K68 -> -20.652 | L81: =49.83*D81 -> 4.983 | M81: =+M55+M68 -> -0.674 | N81: =+$G81*'Aug 2019 GL'!$G$47 -> 27.98175 | O81: =+O55+O68 -> 0 | Q81: =SUM(H81:P81) -> 225.46154 | R81: ADMIN
A82: Total per USJP Report | E82: =SUBTOTAL(109,'Salaries & Fringe Allocations'!E73:E81) -> 29961.22 | F82: =SUBTOTAL(109,'Salaries & Fringe Allocations'!F73:F81) -> 17145.82 | G82: =SUM(G73:G81) -> 1.1477805 | H82: =SUBTOTAL(109,'Salaries & Fringe Allocations'!H73:H81) -> 1821.5276 | I82: =SUBTOTAL(109,'Salaries & Fringe Allocations'!I73:I81) -> 244.47724 | J82: =SUBTOTAL(109,'Salaries & Fringe Allocations'!J73:J81) -> 3813.9905 | K82: =SUBTOTAL(109,'Salaries & Fringe Allocations'!K73:K81) -> -704.119 | L82: =SUBTOTAL(109,'Salaries & Fringe Allocations'!L73:L81) -> 171.0615 | M82: =SUBTOTAL(109,'Salaries & Fringe Allocations'!M73:M81) -> -20.314 | N82: =SUBTOTAL(109,'Salaries & Fringe Allocations'!N73:N81) -> 567.00355 | O82: =SUBTOTAL(109,'Salaries & Fringe Allocations'!O73:O81) -> 0 | ... Q82: =SUBTOTAL(109,'Salaries & Fringe Allocations'!Q73:Q81) -> 5893.6274
A85: Payroll Period 08/18/19 - 08/31/19 | B85: Check Date | D85: 43714
A86: Staff Member | B86: USJP HOURS | C86: Total Hours | D86: Time Allocation (%) | E86: Total Salary | F86: USJP Salary | H86: ER Taxes Monthly Allocation | I86: Payroll Fees Monthly Allocation | J86: Monthly Health Ins. Medical | K86: Bi-weekly Medical Deduction | L86: Dental & Life Insurance | M86: Biweekly Dental Insur Deduction | N86: W/Comp Monthly Allocation | O86: Pension | P86: Enter other | Q86: Total Benefits
A87: COO Patricia Sermon - Admin | B87: 14 | C87: 70 | D87: =B87/C87 -> 0.2 | E87: 3153.85 | F87: =ROUND(D87*E87,2) -> 630.77 | K87: =-103.26*D87 -> -20.652 | M87: =-3.37*D87 -> -0.674 | Q87: =SUM(H87:P87) -> -21.326
A88: Director Gwendolyn Morris - Admin | B88: 29 | C88: 70 | D88: =B88/C88 -> 0.41428571 | E88: 2500 | F88: =ROUND(D88*E88,2) -> 1035.71 | K88: =-97.01*D88 -> -40.189857 | M88: =-3.37*D88 -> -1.3961429 | Q88: =SUM(H88:P88) -> -41.586
A89: Director Gwendolyn Morris - Program | B89: 41 | C89: 70 | D89: =B89/C89 -> 0.58571429 | F89: =ROUND(D89*E88,2) -> 1464.29 | K89: =-97.01*D89 -> -56.820143 | M89: =-3.37*D89 -> -1.9738571 | Q89: =SUM(H89:P89) -> -58.794
A90: Site Coordinator (Essex) Rahmel Leake - Program | B90: 70 | C90: 70 | D90: =B90/C90 -> 1 | E90: 1538.47 | F90: =ROUND(E90,2) -> 1538.47 | K90: 0 | Q90: =SUM(H90:P90) -> 0
A91: Site Coordinator (Passaic) Irene Cerna - Program | B91: 35 | C91: 35 | D91: =B91/C91 -> 1 | E91: 576.93 | F91: =ROUND(E91,2) -> 576.93 | K91: =-103.26*D91 -> -103.26 | Q91: =SUM(H91:P91) -> -103.26
A92: Site Coordinator (Morris) Alberto Almanzar - Program | B92: 60 | C92: 60 | D92: =B92/C92 -> 1 | E92: 865.2 | F92: =ROUND(E92,2) -> 865.2 | K92: 0 | Q92: =SUM(H92:P92) -> 0
A93: Program Assistant Joanna Martinez - Admin | B93: 30 | C93: 70 | D93: =B93/C93 -> 0.42857143 | E93: 1538.47 | F93: =ROUND(D93*E93,2) -> 659.34 | K93: =-127.17*D93 -> -54.501429 | M93: =-6.08*D93 -> -2.6057143 | Q93: =SUM(H93:P93) -> -57.107143
A94: Program Assistant Joanna Martinez - Program | B94: =18.25*2 -> 36.5 | C94: 70 | D94: =B94/C94 -> 0.52142857 | F94: =ROUND(D94*E93,2) -> 802.2 | K94: =-127.17*D94 -> -66.310071 | M94: =-6.08*D94 -> -3.1702857 | Q94: =SUM(H94:P94) -> -69.480357
A95: Staff Accountant - Gregory Ward | B95: 7 | C95: 70 | D95: =B95/C95 -> 0.1 | E95: 4230.77 | F95: =ROUND(D95*E95,2) -> 423.08 | K95: =-103.26*D95 -> -10.326 | M95: =-3.37*D95 -> -0.337 | Q95: =SUM(H95:P95) -> -10.663
A96: Total | E96: =SUBTOTAL(109,'Salaries & Fringe Allocations'!E87:E95) -> 14403.69 | F96: =SUBTOTAL(109,'Salaries & Fringe Allocations'!F87:F95) -> 7995.99 | H96: =SUBTOTAL(109,'Salaries & Fringe Allocations'!H87:H95) -> 0 | I96: =SUBTOTAL(109,'Salaries & Fringe Allocations'!I87:I95) -> 0 | J96: =SUBTOTAL(109,'Salaries & Fringe Allocations'!J87:J95) -> 0 | K96: =SUBTOTAL(109,'Salaries & Fringe Allocations'!K87:K95) -> -352.0595 | L96: =SUBTOTAL(109,'Salaries & Fringe Allocations'!L87:L95) -> 0 | M96: =SUBTOTAL(109,'Salaries & Fringe Allocations'!M87:M95) -> -10.157 | N96: =SUBTOTAL(109,'Salaries & Fringe Allocations'!N87:N95) -> 0 | O96: =SUBTOTAL(109,'Salaries & Fringe Allocations'!O87:O95) -> 0 | ... Q96: =SUBTOTAL(109,'Salaries & Fringe Allocations'!Q87:Q95) -> -362.2165
A98: Payroll Period Ending 09/01/19 - 09/14/19 | B98: Check Date | D98: 43728
A99: Staff Member | B99: USJP HOURS | C99: Total Hours | D99: Time Allocation (%) | E99: Total Salary | F99: USJP Salary | H99: ER Taxes Monthly Allocation | I99: Payroll Fees Monthly Allocation | J99: Monthly Health Ins. Medical | K99: Bi-weekly Medical Deduction | L99: Dental & Life Insurance | M99: Biweekly Dental Insur Deduction | N99: W/Comp Monthly Allocation | O99: Pension | P99: Enter other | Q99: Total Benefits
A100: COO Patricia Sermon - Admin | B100: 14 | C100: 70 | D100: =B100/C100 -> 0.2 | E100: 3153.85 | F100: =ROUND(D100*E100,2) -> 630.77 | K100: =-103.26*D100 -> -20.652 | M100: =-3.37*D100 -> -0.674 | Q100: =SUM(H100:P100) -> -21.326
A101: Director Gwendolyn Morris - Admin | B101: =14+15 -> 29 | C101: 70 | D101: =B101/C101 -> 0.41428571 | E101: 2500 | F101: =ROUND(D101*E101,2) -> 1035.71 | K101: =-97.01*D101 -> -40.189857 | M101: =-3.37*D101 -> -1.3961429 | Q101: =SUM(H101:P101) -> -41.586
A102: Director Gwendolyn Morris - Program | B102: =21+20 -> 41 | C102: 70 | D102: =B102/C101 -> 0.58571429 | E102: 0 | F102: =ROUND(D102*E101,2) -> 1464.29 | K102: =-97.01*D102 -> -56.820143 | M102: =-3.37*D102 -> -1.9738571 | Q102: =SUM(H102:P102) -> -58.794
A103: Site Coordinator (Essex) Rahmel Leake - Program | B103: 70 | C103: 70 | D103: =B103/C103 -> 1 | E103: 1538.47 | F103: =ROUND(D103*E103,2) -> 1538.47 | K103: 0 | Q103: =SUM(H103:P103) -> 0
A104: Site Coordinator (Passaic) Irene Cerna - Program | B104: 70 | C104: 70 | D104: =B104/C104 -> 1 | E104: 1153.85 | F104: =ROUND(D104*E104,2) -> 1153.85 | K104: =-103.26*D104 -> -103.26 | Q104: =SUM(H104:P104) -> -103.26
A105: Site Coordinator (Morris) Alberto Almanzar - Program | B105: 28 | C105: 28 | D105: =B105/C105 -> 1 | E105: 403.76 | F105: =ROUND(D105*E105,2) -> 403.76 | K105: 0 | Q105: =SUM(H105:P105) -> 0
A106: Program Assistant Joanna Martinez - Admin | B106: 2 | C106: 14 | D106: =B106/C106 -> 0.14285714 | E106: 307.7 | F106: =ROUND(D106*E106,2) -> 43.96 | K106: =-127.17*D106 -> -18.167143 | M106: =-6.08*D106 -> -0.86857143 | Q106: =SUM(H106:P106) -> -19.035714
A107: Program Assistant Joanna Martinez - Program | B107: 11.3 | C107: 14 | D107: =B107/C106 -> 0.80714286 | E107: 0 | F107: =ROUND(D107*E106,2) -> 248.36 | K107: =-127.17*D107 -> -102.64436 | M107: =-6.08*D107 -> -4.9074286 | Q107: =SUM(H107:P107) -> -107.55179
A108: Staff Accountant - Gregory Ward | B108: 7 | C108: 70 | D108: =B108/C108 -> 0.1 | E108: 4230.77 | F108: =ROUND(D108*E108,2) -> 423.08 | K108: =-103.26*D108 -> -10.326 | M108: =-3.37*D108 -> -0.337 | Q108: =SUM(H108:P108) -> -10.663
A109: Total | E109: =SUBTOTAL(109,'Salaries & Fringe Allocations'!E100:E108) -> 13288.4 | F109: =SUBTOTAL(109,'Salaries & Fringe Allocations'!F100:F108) -> 6942.25 | H109: =SUBTOTAL(109,'Salaries & Fringe Allocations'!H100:H108) -> 0 | I109: =SUBTOTAL(109,'Salaries & Fringe Allocations'!I100:I108) -> 0 | J109: =SUBTOTAL(109,'Salaries & Fringe Allocations'!J100:J108) -> 0 | K109: =SUBTOTAL(109,'Salaries & Fringe Allocations'!K100:K108) -> -352.0595 | L109: =SUBTOTAL(109,'Salaries & Fringe Allocations'!L100:L108) -> 0 | M109: =SUBTOTAL(109,'Salaries & Fringe Allocations'!M100:M108) -> -10.157 | N109: =SUBTOTAL(109,'Salaries & Fringe Allocations'!N100:N108) -> 0 | O109: =SUBTOTAL(109,'Salaries & Fringe Allocations'!O100:O108) -> 0 | ... Q109: =SUBTOTAL(109,'Salaries & Fringe Allocations'!Q100:Q108) -> -362.2165
A111: Monthly Total for September 2019
A112: Staff Member | B112: USJP HOURS | C112: Total Hours | D112: Time Allocation (%) | E112: Total Salary | F112: USJP Salary | G112: Allocation % | H112: ER Taxes Monthly Allocation | I112: Payroll Fees Monthly Allocation | J112: Monthly Health Ins. Medical | K112: Bi-weekly Medical Deduction | L112: Dental & Life Insurance | M112: Biweekly Dental Insur Deduction | N112: W/Comp Monthly Allocation | O112: Pension | P112: Enter other | Q112: Total Benefits
...

Sheet Jul-2019
A1: Urban Seniors Jobs Program PY 19 | E1: Invoice # 1 | G1: 43647 | I1: %
A2: Urban League of Essex County | I2: Spent
A3: 1. PERSONNEL | E3: TOTAL
C4: ENROLLEE | D4: OPC | E4: MONTHLY | F4: CUMULATIVE | G4: TOTAL | H4: BUDGET
A5: POSITION TITLE | B5: ADMIN | C5: WAGES & FB | D5: PROGRAM | E5: AMOUNT | F5: EXPENSES | G5: BUDGET | H5: REMAINING
A6: COO Patricia Sermon | B6: =+'Salaries & Fringe Allocations'!F32 -> 946.15 | E6: =SUM(B6:D6) -> 946.15 | F6: =E6 -> 946.15 | G6: 16400 | H6: =G6-F6 -> 15453.85 | I6: =F6/G6 -> 0.057692073
A7: Director Gwendolyn Morris | B7: =+'Salaries & Fringe Allocations'!F33 -> 1553.57 | D7: =+'Salaries & Fringe Allocations'!F34 -> 2196.43 | E7: =SUM(B7:D7) -> 3750 | F7: =E7 -> 3750 | G7: 66000 | H7: =G7-F7 -> 62250 | I7: =F7/G7 -> 0.056818182
A8: Prog Site Coordinator (Essex) Rahmel Leake | D8: =+'Salaries & Fringe Allocations'!F35 -> 769.24 | E8: =SUM(B8:D8) -> 769.24 | F8: =E8 -> 769.24 | G8: 40000 | H8: =G8-F8 -> 39230.76 | I8: =F8/G8 -> 0.019231
A9: Prog Site Coordinator (Passaic) Irene Cerna | D9: =+'Salaries & Fringe Allocations'!F36 -> 1730.88 | E9: =SUM(B9:D9) -> 1730.88 | F9: =E9 -> 1730.88 | G9: 30000 | H9: =G9-F9 -> 28269.12 | I9: =F9/G9 -> 0.057696
A10: Prog Site Coordinator (Morris) Alberto Almanzar | D10: =+'Salaries & Fringe Allocations'!F37 -> 1211.28 | E10: =SUM(B10:D10) -> 1211.28 | F10: =E10 -> 1211.28 | G10: 21500 | H10: =G10-F10 -> 20288.72 | I10: =F10/G10 -> 0.056338605
A11: Program Assistant Joanna Martinez | B11: =+'Salaries & Fringe Allocations'!F38 -> 989.02 | D11: =+'Salaries & Fringe Allocations'!F39 -> 1318.69 | E11: =SUM(B11:D11) -> 2307.71 | F11: =E11 -> 2307.71 | G11: 36000 | H11: =G11-F11 -> 33692.29 | I11: =F11/G11 -> 0.064103056
A12: Staff Accountant - TBH | E12: =SUM(B12:D12) -> 0 | F12: =E12 -> 0 | G12: 4000 | H12: =G12-F12 -> 4000 | I12: =F12/G12 -> 0
A16: Total Salaries | B16: =SUM(B6:B15) -> 3488.74 | C16: =SUM(C6:C15) -> 0 | D16: =SUM(D6:D15) -> 7226.52 | E16: =SUM(E6:E15) -> 10715.26 | F16: =SUM(F6:F15) -> 10715.26 | G16: =SUM(G6:G15) -> 213900 | H16: =SUM(H6:H15) -> 203184.74 | I16: =F16/G16 -> 0.050094717
A18: Fringe Benefits Rate | B18: =+'Salaries & Fringe Allocations'!Q32+'Salaries & Fringe Allocations'!Q33+'Salaries & Fringe Allocations'!Q38+'Salaries & Fringe Allocations'!Q40 -> 1578.9289 | D18: =+'Salaries & Fringe Allocations'!Q34+'Salaries & Fringe Allocations'!Q35+'Salaries & Fringe Allocations'!Q36+'Salaries & Fringe Allocations'!Q37+'Salaries & Fringe Allocations'!Q39 -> 3171.3151 | E18: =SUM(B18:D18) -> 4750.244 | F18: =E18 -> 4750.244 | G18: 68136 | H18: =G18-F18 -> 63385.756 | I18: =F18/G18 -> 0.069717095
A20: TOTAL PERSONNEL (Salaries + Fringe Benefits) | B20: =B16+B18 -> 5067.6689 | C20: =C16+C18 -> 0 | D20: =D16+D18 -> 10397.835 | E20: =E16+E18 -> 15465.504 | F20: =F16+F18 -> 15465.504 | G20: =G16+G18 -> 282036 | H20: =H16+H18 -> 266570.5 | I20: =F20/G20 -> 0.054835213
A22: 2. Non-Personnel Operating Costs
A23: Travel | D23: =+'Jul-2019 GL'!G72 -> 268.02 | E23: =SUM(B23:D23) -> 268.02 | F23: =E23 -> 268.02 | G23: 4000 | H23: =G23-F23 -> 3731.98 | I23: =F23/G23 -> 0.067005
A24: Supplies | B24: =+'Jul-2019 GL'!G76 -> 55.59 | E24: =SUM(B24:D24) -> 55.59 | F24: =E24 -> 55.59 | G24: 7000 | H24: =G24-F24 -> 6944.41 | I24: =F24/G24 -> 0.0079414286
A25: Staff Development | E25: =SUM(B25:D25) -> 0 | F25: =E25 -> 0 | G25: 2000 | H25: =G25-F25 -> 2000 | I25: =F25/G25 -> 0
A26: Contractual/Consultants | B26: =+'Jul-2019 GL'!G81 -> 361.69 | E26: =SUM(B26:D26) -> 361.69 | F26: =E26 -> 361.69 | G26: 13200 | H26: =G26-F26 -> 12838.31 | I26: =F26/G26 -> 0.027400758
A27: Occupancy | B27: =+'Jul-2019 GL'!G94 -> 332.27 | D27: =+'Jul-2019 GL'!G86 -> 648 | E27: =SUM(B27:D27) -> 980.27 | F27: =E27 -> 980.27 | G27: 12000 | H27: =G27-F27 -> 11019.73 | I27: =F27/G27 -> 0.081689167
A28: Audit (100% Admin) | B28: =+'Jul-2019 GL'!G101 -> 1130.29 | E28: =SUM(B28:D28) -> 1130.29 | F28: =E28 -> 1130.29 | G28: 6000 | H28: =G28-F28 -> 4869.71 | I28: =F28/G28 -> 0.18838167
A29: Marketing and Outreach | E29: =SUM(B29:D29) -> 0 | F29: =E29 -> 0 | G29: 570 | H29: =G29-F29 -> 570 | I29: =F29/G29 -> 0
A30: Rental Equipment | B30: =+'Jul-2019 GL'!G106 -> 200.95 | E30: =SUM(B30:D30) -> 200.95 | F30: =E30 -> 200.95 | G30: 6475 | H30: =G30-F30 -> 6274.05 | I30: =F30/G30 -> 0.031034749
A31: Participant Payroll fees | B31: =+'Jul-2019 GL'!G25 -> 872.26 | E31: =SUM(B31:D31) -> 872.26 | F31: =E31 -> 872.26 | G31: 13000 | H31: =G31-F31 -> 12127.74 | I31: =F31/G31 -> 0.067096923
A32: Infrastructure Costs | E32: =SUM(B32:D32) -> 0 | F32: =E32 -> 0 | G32: 1500 | H32: =G32-F32 -> 1500 | I32: =F32/G32 -> 0
A33: Other Operating costs | B33: =+'Jul-2019 GL'!G115 -> 267.88 | E33: =SUM(B33:D33) -> 267.88 | F33: =E33 -> 267.88 | G33: 3000.7 | H33: =G33-F33 -> 2732.82 | I33: =F33/G33 -> 0.089272503
A34: Communications | B34: =+'Jul-2019 GL'!G129 -> 182.85 | E34: =SUM(B34:D34) -> 182.85 | F34: =E34 -> 182.85 | G34: 3000 | H34: =G34-F34 -> 2817.15 | I34: =F34/G34 -> 0.06095
A35: Insurance | B35: =+'Jul-2019 GL'!G134 -> 320.72 | E35: =SUM(B35:D35) -> 320.72 | F35: =E35 -> 320.72 | G35: 4000 | H35: =G35-F35 -> 3679.28 | I35: =F35/G35 -> 0.08018
A36: Postage | E36: =SUM(B36:D36) -> 0 | F36: =E36 -> 0 | G36: 1000 | H36: =G36-F36 -> 1000 | I36: =F36/G36 -> 0
A37: Total NPOC | B37: =SUM(B23:B36) -> 3724.5 | C37: =SUM(C23:C36) -> 0 | D37: =SUM(D23:D36) -> 916.02 | E37: =SUM(E23:E36) -> 4640.52 | F37: =SUM(F23:F36) -> 4640.52 | G37: =SUM(G23:G36) -> 76745.7 | H37: =SUM(H23:H36) -> 72105.18 | I37: =F37/G37 -> 0.060466189
A40: 3. Participant Costs
A41: Participant Wages | C41: =+'Jul-2019 GL'!G10 -> 58923.44 | E41: =SUM(B41:D41) -> 58923.44 | F41: =E41 -> 58923.44 | G41: 1452829.2 | H41: =G41-F41-F42 -> 1393905.8 | I41: =F41/G41 -> 0.040557719
A42: Reimbursable Participant Wage(Paid by Affiliate) | C42: 0 | E42: =SUM(B42:D42) -> 0 | F42: =E42 -> 0 | I42: =F42/G42 -> #DIV/0!
A43: Participant Specialized Training Wage | C43: 0 | E43: =SUM(B43:D43) -> 0 | F43: =E43 -> 0 | G43: 12820 | H43: =G43-F43 -> 12820 | I43: =F43/G43 -> 0
A44: Participant FICA and other taxes | C44: =+'Jul-2019 GL'!G18 -> 4535.75 | E44: =SUM(B44:D44) -> 4535.75 | F44: =E44 -> 4535.75 | G44: 111141.44 | H44: =G44-F44 -> 106605.69 | I44: =F44/G44 -> 0.04081061
A45: Workers compensation | C45: =+'Jul-2019 GL'!G20 -> 2049.2 | E45: =SUM(B45:D45) -> 2049.2 | F45: =E45 -> 2049.2 | G45: 22373.57 | H45: =G45-F45 -> 20324.37 | I45: =F45/G45 -> 0.091590211
A46: Support Services | C46: 0 | E46: =SUM(B46:D46) -> 0 | F46: =E46 -> 0 | G46: 8500 | H46: =G46-F46 -> 8500 | I46: =F46/G46 -> 0
A47: Specialized Training vendor | C47: 0 | E47: =SUM(B47:D47) -> 0 | F47: =E47 -> 0 | G47: 29630 | H47: =G47-F47 -> 29630 | I47: =F47/G47 -> 0
A48: Total Participant Costs | B48: =SUM(B41:B47) -> 0 | C48: =SUM(C41:C47) -> 65508.39 | D48: =SUM(D41:D47) -> 0 | E48: =SUM(E41:E47) -> 65508.39 | F48: =SUM(F41:F47) -> 65508.39 | G48: =SUM(G41:G47) -> 1637294.2 | H48: =SUM(H41:H47) -> 1571785.9 | I48: =F48/G48 -> 0.040010151
A50: 4. Indirect ('%) | B50: 0 | E50: =B50 -> 0 | F50: =E50 -> 0 | G50: 17532.59 | H50: =G50-F50 -> 17532.59 | I50: =F50/G50 -> 0
A52: 5.Total Federal Expenses | B52: =B20+B37+B48+B50 -> 8792.1689 | C52: =C20+C37+C48 -> 65508.39 | D52: =D20+D37+D48 -> 11313.855 | E52: =E37+E20+E48+E50 -> 85614.414 | F52: =F37+F20+F48+F50 -> 85614.414 | G52: =G37+G20+G48+G50 -> 2013608.5 | H52: =H37+H20+H48+H50 -> 1927994.1 | I52: =F52/G52 -> 0.042517904
A54: 6. Non Federal Match | E54: 7492.14 | F54: =E54 -> 7492.14 | G54: 242467.32 | H54: =G54-F54 -> 234975.18 | I54: =F54/G54 -> 0.030899587
A56: 7. Total Expenses | B56: =B52+B54 -> 8792.1689 | C56: =C52+C54 -> 65508.39 | D56: =D52+D54 -> 11313.855 | E56: =E52+E54 -> 93106.554 | F56: =F52+F54 -> 93106.554 | G56: =G52+G54 -> 2256075.9 | H56: =H52+H54 -> 2162969.3 | I56: =F56/G56 -> 0.041269248
F57: AFFILIATES- ENTER NOTES TO THIS INVOICE HERE
A58: 8. Total Reimbursable expenses | E58: =+E20+E37-E31+E42+E45+E46+E47+E50 -> 21282.964
A60: FOR NUL USE ONLY
A62: TOTAL INVOICE SUBMITTED | E62: =E58 -> 21282.964
A65: COSTS DISALLOWED
A68: OTHER ADJUSTMENTS
A71: CASH DUE TO/DUE FROM AFFILIATE
A73: SIGNATURE AND DATE:
A78: Affiliate Finance Officer | B78: Date | F78: Affiliate CEO | H78: Date
A82: Affiliate Project Director | B82: Date | F82: NUL Vice President, Workforce Development | H82: Date

Sheet Jul-2019 GL
A1: URBAN LEAGUE OF ESSEX COUNTY
A2: 451 USJP Program Transaction Detail by Account
A3: July 2019
B5: Date | C5: Trans Type | D5: Num | E5: Name | F5: Memo/Description | G5: Amount | H5: Check #
A6: 7100 Participant Salaries & Wages
A7: 7112 Participant Wages - USJP
B8: 07/15/2019 | C8: Journal Entry | D8: 00122 USJP | F8: USJP Participant Salaries 07/15 | G8: 13768.8
B9: 07/29/2019 | C9: Journal Entry | D9: 00123 USJP | F9: USJP Participant Salaries 07/29 | G9: 45154.64
A10: Total for 7112 Participant Wages - USJP | G10: =SUM(G8:G9) -> 58923.44
A11: 7112.1 USJP Manual Checks
B12: 07/29/2019 | C12: Journal Entry | D12: 00123 USJP | F12: USJP Participant Salaries 07/29 PY 2018 | G12: 284.81
B13: 07/30/2019 | C13: Deposit | E13: Paycom Payroll, LLC | F13: Paycheck/Salary Refund - Pamela flagg PY 2018 19-50-07 | G13: -38.76
A14: Total for 7112.1 USJP Manual Checks | G14: =SUM(G12:G13) -> 246.05
A15: 7120 Payroll Taxes
B16: 07/15/2019 | C16: Journal Entry | D16: 00122 USJP | F16: USJP Participant Salaries 07/15 | G16: 1052.81
B17: 07/29/2019 | C17: Journal Entry | D17: 00123 USJP | F17: USJP Participant Salaries 07/29 | G17: 3482.94
A18: Total for 7120 Payroll Taxes | G18: =SUM(G16:G17) -> 4535.75
A19: 7130 Worker's Compensation - USJP
B20: 07/31/2019 | C20: Journal Entry | D20: 139 | F20: Workers Comp Alloc - Participants | G20: 2049.2
A21: Total for 7130 Worker's Compensation - USJP | G21: =SUM(G20) -> 2049.2
A22: 7132 Payroll Expenses - Fees
B23: 07/15/2019 | C23: Journal Entry | D23: 00122 USJP | F23: USJP Participant Salaries 07/15 | G23: 393.64
B24: 07/29/2019 | C24: Journal Entry | D24: 00123 USJP | F24: USJP Participant Salaries 07/29 | G24: 478.62
A25: Total for 7132 Payroll Expenses - Fees | G25: =SUM(G23:G24) -> 872.26
A26: 7220 Salaries & Wages
B27: 07/31/2019 | C27: Journal Entry | D27: 00127 Salaries | F27: Salary Allocation - July | G27: 10715.26
A28: Total for 7220 Salaries & Wages | G28: =SUM(G27:G27) -> 10715.26
A29: 7240 Employee Benefits
A30: 7241 Health Insurance
B31: 07/31/2019 | C31: Journal Entry | D31: 153 | E31: Horizon Bluecross Blueshield | F31: Employee Health Insurance - Patricia Sermon | G31: 223.73 | H31: Online
B32: 07/31/2019 | C32: Journal Entry | D32: 153 | E32: Horizon Bluecross Blueshield | F32: Employee Health Insurance - USJP Staff | G32: 3547.28 | H32: Online
A33: Total for 7241 Health Insurance | G33: =SUM(G31:G32) -> 3771.01
A34: 7242 Life and Dental Insurance
B35: 07/01/2019 | C35: Bill | D35: 7.1.19PL | E35: Principal Financial Group | F35: Life, Dental & AD&D - USJP | G35: 169.96 | H35: 12274
A36: Total for 7242 Life and Dental Insurance | G36: =SUM(G35) -> 169.96
A37: 7244 Employee Contrib - Health
B38: 07/31/2019 | C38: Journal Entry | D38: 154 | F38: Employee Medical Contrib | G38: -757.36
A39: Total for 7244 Employee Contrib - Health | G39: =SUM(G38) -> -757.36
A40: 7247 Emp-ee Contrib -Dental
B41: 07/31/2019 | C41: Journal Entry | D41: 155 | F41: Employee Dental Contrib | G41: -20.25
A42: Total for 7247 Emp-ee Contrib -Dental | G42: =SUM(G41) -> -20.25
A43: Total for 7240 Employee Benefits | G43: =+G33+G36+G39+G42 -> 3163.36
A44: 7245 Worker's Compensation Insurance
B45: 07/31/2019 | C45: Journal Entry | D45: 139 | F45: Workers Comp Alloc - USJP Staff | G45: 371.1
A46: Total for 7248 Allocated W Comp | G46: =SUM(G45) -> 371.1
A47: EMPLOYER TAXES
A48: 7251 Social Security
B49: 07/31/2019 | C49: Journal Entry | D49: 133 | F49: Fica | G49: 671.31
A50: Total for 7251 Social Security | G50: =SUM(G49) -> 671.31
A51: 7252 Medicare
B52: 07/31/2019 | C52: Journal Entry | D52: 134 | F52: Medi Alloc | G52: 157.01
A53: Total for 7252 Medicare | G53: =SUM(G52) -> 157.01
A54: 7253 Unemployment
B55: 07/31/2019 | C55: Journal Entry | D55: 135 | F55: SUI Alloc | G55: 208.74
A56: Total for 7253 Unemployment | G56: =SUM(G55) -> 208.74
A57: 7254 Disability
B58: 07/31/2019 | C58: Journal Entry | D58: 137 | F58: Disability Alloc | G58: 38.27
A59: Total for 7254 Disability | G59: =SUM(G58) -> 38.27
A60: Total for EMPLOYER TAXES | G60: =+G50+G53+G56+G59 -> 1075.33
A61: 7260.1 Allocated Payroll Fees
B62: 07/31/2019 | C62: Journal Entry | D62: 146 | F62: Payroll Fees | G62: 140.46
A63: Total for 7260.1 Allocated Payroll Fees | G63: =SUM(G62) -> 140.46
A65: Total FRINGE BENEFITS | G65: =+G43+G46+G60+G63 -> 4750.25
A67: TRAVEL
A68: 8310 Transportation & Parking
B69: 07/01/2019 | C69: Bill | D69: 07.01.19CTW | E69: Center for Transformative Work | F69: USJP Paterson Office Monthly Parking Permit July 2019 | G69: 150 | H69: 12260
B70: 07/19/2019 | C70: Bill | D70: 07.19.19RJ | E70: Rachel Jacobs | F70: Mileage reimbursement - 07/01/19 - 07/31/19 | G70: 15.12 | H70: 12343
B71: 07/26/2019 | C71: Bill | D71: 07.26.19AA | E71: Alberto Almanzar | F71: USJP Mileage Reimbursement 07.19 | G71: 102.9 | H71: 12358
A72: Total for Travel | G72: 268.02
A74: SUPPLIES
B75: 07/31/2019 | C75: Journal Entry | D75: 144 | F75: Supplies Alloc | G75: 55.59
A76: Total for 8110 Supplies | G76: =SUM(G75) -> 55.59
A78: CONTRACTUAL CONSULTANTS
A79: 7521 Allocated Acctg and Audit
B80: 07/31/2019 | C80: Journal Entry | D80: 145 | F80: Acctg Fee Alloc | G80: 361.69
A81: Total for CONTRACTUAL CONSULTANTS | G81: =SUM(G80) -> 361.69
A83: OCCUPANCY
A84: 8205 Rent, Parking, Other Occupancy
B85: 07/01/2019 | C85: Bill | D85: 07.01.19R | E85: Center for Transformative Work | F85: USJP - Rent Expense July 2019 | G85: 648 | H85: 12260
A86: Total for OCCUPANCY - PROGRAM TOTAL 8205 Rent | G86: =SUM(G85) -> 648
A87: 8210 Utilities
A88: 8210.5 Allocated Utilities
B89: 07/31/2019 | C89: Journal Entry | D89: 148 | F89: Utilities | G89: 112.71
A90: Total for 8210.5 Allocated Utilities | G90: =SUM(G89) -> 112.71
A91: 8230 Building Repair & Maintenance
B92: 07/31/2019 | C92: Journal Entry | D92: 151 | F92: Repairs | G92: 219.56
A93: Total for 8239 Alloc Repairs and Maint | G93: =SUM(G92) -> 219.56
A94: OCCUPANCY - ADMIN TOTAL | G94: =+G90+G93 -> 332.27
A96: Total for OCCUPANCY PROGRAM & ADMIN | G96: =+G86+G94 -> 980.27
A98: AUDIT & ACCOUNTING FEES
A99: 7521 Allocated Acctg and Audit
B100: 07/31/2019 | C100: Journal Entry | D100: 145 | F100: AUDIT Fee Alloc | G100: 1130.29
A101: Total for AUDIT & ACCOUNTING FEES | G101: =SUM(G100) -> 1130.29
A103: RENTAL EQUIPMENT
A104: 8229.1 Allocated Cost
B105: 07/31/2019 | C105: Journal Entry | D105: 141 | F105: Equipment Leases | G105: 200.95
A106: Total for RENTAL EQUIPMENT | G106: =SUM(G105) -> 200.95
A108: OTHER OPERATING COSTS
A109: 7515 IT Support
B110: 07/31/2019 | C110: Journal Entry | D110: 142 | F110: IT Consultants | G110: 242.69
...

Sheet JULY FR
A1: National Urban League Financial Report
A2: 1. Funding Agency- National Urban League | I2: 2. Federal Grant Name - Urban Seniors Jobs Program CFDA 17.235 | N2: PY 19
A3: 3. Recipient Organization - URBAN LEAGUE OF ESSEX COUNTY
A4: 508 CENTRAL AVENUE, NEWARK NJ 07107 | M4: 4. Final Report (mark X) Yes No | N4: 5. Basis of Reporting □ Accrual
A5: 6. Project/Grant Period From: July 1-2019 | H5: To: June 31, 2020 | M5: 7. Reporting Period End Date 7/31/2019
A6: 8. Transactions | M6: Cumulative
A7: Federal Cash:
A8: a. Cash Receipts
A9: b. Cash Disbursements | M9: =M8 -> 0
A10: c. Cash on Hand (line a minus b) | M10: =M8-M9 -> 0
A11: Federal Expenditures and Unobligated Balance:
A12: d. Approved Budget | M12: =+'Jul-2019'!G56 -> 2256075.9
A13: e. Federal Share of Expenditures -Program Costs | M13: =M9 -> 0
A14: f. Federal Share of Expenditures -Administrative Costs | M14: 0
A15: g. Federal Share of Unliquidated Obligations ( ACCRUALS) | M15: 0
A16: h. Total Federal Obligations (sum of lines e and g) | M16: =M13+M14+M15 -> 0
A17: i. Unobligated Balance of Federal Funds (line d minus h) | M17: =M12-M16 -> 2256075.9
A18: Recipient Share: Cost Sharing/ Matching/ In-Kind Costs
A19: j. Total Match and Inkind Required if Applicable | M19: =+'Jul-2019'!G54 -> 242467.32
A20: k. Total Receipient share reported if Applicable | M20: =+'Jul-2019'!E54 -> 7492.14
A21: l. Remaining Recipient Share to Be Provided (line j minus k) | M21: =M19-M20 -> 234975.18
A22: Program Income:
A23: m. Total Program Income Earned if applicable | M23: 0
A24: n. Program Income Expended in Accordance with the Addition Method | M24: 0
A25: o. Unexpended Program Income (line m minus line n) | M25: =M23-M24 -> 0
A26: 9. Remarks: (Attach any explanations deemed necessary or information required by Federal sponsoring agency in compliance with governing legislation.)
A28: 10. Indirect Expenditures
A29: a. Type of Rate | C29: b. Rate | D29: c. Rate Approval Date | G29: d. Period From (MM/DD/YYYY) | I29: Period To (MM/DD/YYYY) | J29: e. Base | M29: f. Amount Charged | N29: g. Federal Share
A32: 11. Certification: By signing this report, I certify to the best of my knowledge and belief that the report is true, complete, and accurate, and the expenditures, disbursements and cash receipts are for the purposes and objectives set forth in the terms and conditions of the Federal award. I am aware that any false, fictitious, or fraudulent information, or the omission of any material fact, may subject me to criminal, civil or administrative penalties for fraud, false statements, false claims or otherwise. (U.S. Code Title 18, Section 1001 and Title 31, Sections 3729–3730 and 3801–3812).
A33: a. Typed or Printed Name and Title of Authorized Certifying Official | M33: c. Telephone (Area code, number, and extension)
M34: d. Email Address
A35: b. Signature of Authorized Certifying Official | M35: e. Date Report Submitted (MM/DD/YYYY)

Sheet Aug-2019
A1: Urban Seniors Jobs Program PY 19 | G1: 43678 | I1: %
A2: Urban League of Essex County | E2: Invoice # 2 | I2: Spent
A3: 1. PERSONNEL | E3: TOTAL
C4: ENROLLEE | D4: OPC | E4: MONTHLY | F4: CUMULATIVE | G4: TOTAL | H4: BUDGET
A5: POSITION TITLE | B5: ADMIN | C5: WAGES & FB | D5: PROGRAM | E5: AMOUNT | F5: EXPENSES | G5: BUDGET | H5: REMAINING
A6: COO Patricia Sermon | B6: =+'Salaries & Fringe Allocations'!F73 -> 1261.54 | E6: =SUM(B6:D6) -> 1261.54 | F6: =E6+'Jul-2019'!F6 -> 2207.69 | G6: 16400 | H6: =G6-F6 -> 14192.31 | I6: =F6/G6 -> 0.13461524
A7: Director Gwendolyn Morris | B7: =+'Salaries & Fringe Allocations'!F74 -> 2107.14 | D7: =+'Salaries & Fringe Allocations'!F75 -> 2892.86 | E7: =SUM(B7:D7) -> 5000 | F7: =E7+'Jul-2019'!F7 -> 8750 | G7: 66000 | H7: =G7-F7 -> 57250 | I7: =F7/G7 -> 0.13257576
A8: Prog Site Coordinator (Essex) Rahmel Leake | D8: =+'Salaries & Fringe Allocations'!F76 -> 3076.94 | E8: =SUM(B8:D8) -> 3076.94 | F8: =E8+'Jul-2019'!F8 -> 3846.18 | G8: 40000 | H8: =G8-F8 -> 36153.82 | I8: =F8/G8 -> 0.0961545
A9: Prog Site Coordinator (Passaic) Irene Cerna | D9: =+'Salaries & Fringe Allocations'!F77 -> 2307.7 | E9: =SUM(B9:D9) -> 2307.7 | F9: =E9+'Jul-2019'!F9 -> 4038.58 | G9: 30000 | H9: =G9-F9 -> 25961.42 | I9: =F9/G9 -> 0.13461933
A10: Prog Site Coordinator (Morris) Alberto Almanzar | D10: =+'Salaries & Fringe Allocations'!F78 -> 1730.4 | E10: =SUM(B10:D10) -> 1730.4 | F10: =E10+'Jul-2019'!F10 -> 2941.68 | G10: 21500 | H10: =G10-F10 -> 18558.32 | I10: =F10/G10 -> 0.13682233
A11: Program Assistant Joanna Martinez | B11: =+'Salaries & Fringe Allocations'!F79 -> 1318.69 | D11: =+'Salaries & Fringe Allocations'!F80 -> 1604.4 | E11: =SUM(B11:D11) -> 2923.09 | F11: =E11+'Jul-2019'!F11 -> 5230.8 | G11: 36000 | H11: =G11-F11 -> 30769.2 | I11: =F11/G11 -> 0.1453
A12: Staff Accountant - Gregory Ward | B12: =+'Salaries & Fringe Allocations'!F81 -> 846.15 | E12: =SUM(B12:D12) -> 846.15 | F12: =E12+'Jul-2019'!F12 -> 846.15 | G12: 4000 | H12: =G12-F12 -> 3153.85 | I12: =F12/G12 -> 0.2115375
A16: Total Salaries | B16: =SUM(B6:B15) -> 5533.52 | C16: =SUM(C6:C15) -> 0 | D16: =SUM(D6:D15) -> 11612.3 | E16: =SUM(E6:E15) -> 17145.82 | F16: =SUM(F6:F15) -> 27861.08 | G16: =SUM(G6:G15) -> 213900 | H16: =SUM(H6:H15) -> 186038.92 | I16: =F16/G16 -> 0.13025283
A18: Fringe Benefits Rate | B18: =+'Salaries & Fringe Allocations'!Q73+'Salaries & Fringe Allocations'!Q74+'Salaries & Fringe Allocations'!Q79+'Salaries & Fringe Allocations'!Q81 -> 2040.4429 | D18: =+'Salaries & Fringe Allocations'!Q75+'Salaries & Fringe Allocations'!Q76+'Salaries & Fringe Allocations'!Q77+'Salaries & Fringe Allocations'!Q78+'Salaries & Fringe Allocations'!Q80 -> 3853.1845 | E18: =SUM(B18:D18) -> 5893.6274 | F18: =E18+'Jul-2019'!F18 -> 10643.871 | G18: 68136 | H18: =G18-F18 -> 57492.129 | I18: =F18/G18 -> 0.15621509
H19: =G19-F19 -> 0
A20: TOTAL PERSONNEL (Salaries + Fringe Benefits) | B20: =B16+B18 -> 7573.9629 | C20: =C16+C18 -> 0 | D20: =D16+D18 -> 15465.484 | E20: =E16+E18 -> 23039.447 | F20: =F16+F18 -> 38504.951 | G20: =G16+G18 -> 282036 | H20: =H16+H18 -> 243531.05 | I20: =F20/G20 -> 0.13652495
A22: 2. Non-Personnel Operating Costs
A23: Travel | D23: =+'Aug 2019 GL'!G77 -> 287.13 | E23: =SUM(B23:D23) -> 287.13 | F23: =E23+'Jul-2019'!F23 -> 555.15 | G23: 4000 | H23: =G23-F23 -> 3444.85 | I23: =F23/G23 -> 0.1387875
A24: ='Jul-2019'!A24 -> Supplies | B24: =+'Aug 2019 GL'!G85 -> 86 | D24: =+'Aug 2019 GL'!G81 -> 329.9 | E24: =SUM(B24:D24) -> 415.9 | F24: =E24+'Jul-2019'!F24 -> 471.49 | G24: 7000 | H24: =G24-F24 -> 6528.51 | I24: =F24/G24 -> 0.067355714
A25: ='Jul-2019'!A25 -> Staff Development | E25: =SUM(B25:D25) -> 0 | F25: =E25+'Jul-2019'!F25 -> 0 | G25: 2000 | H25: =G25-F25 -> 2000 | I25: =F25/G25 -> 0
A26: ='Jul-2019'!A26 -> Contractual/Consultants | B26: =+'Aug 2019 GL'!G92 -> 496 | E26: =SUM(B26:D26) -> 496 | F26: =E26+'Jul-2019'!F26 -> 857.69 | G26: 13200 | H26: =G26-F26 -> 12342.31 | I26: =F26/G26 -> 0.064976515
A27: ='Jul-2019'!A27 -> Occupancy | B27: =+'Aug 2019 GL'!G105 -> 273 | D27: =+'Aug 2019 GL'!G97 -> 648 | E27: =SUM(B27:D27) -> 921 | F27: =E27+'Jul-2019'!F27 -> 1901.27 | G27: 12000 | H27: =G27-F27 -> 10098.73 | I27: =F27/G27 -> 0.15843917
A28: ='Jul-2019'!A28 -> Audit (100% Admin) | E28: =SUM(B28:D28) -> 0 | F28: =E28+'Jul-2019'!F28 -> 1130.29 | G28: 6000 | H28: =G28-F28 -> 4869.71 | I28: =F28/G28 -> 0.18838167
A29: ='Jul-2019'!A29 -> Marketing and Outreach | E29: =SUM(B29:D29) -> 0 | F29: =E29+'Jul-2019'!F29 -> 0 | G29: 570 | H29: =G29-F29 -> 570 | I29: =F29/G29 -> 0
A30: ='Jul-2019'!A30 -> Rental Equipment | B30: =+'Aug 2019 GL'!G116 -> 522 | E30: =SUM(B30:D30) -> 522 | F30: =E30+'Jul-2019'!F30 -> 722.95 | G30: 6475 | H30: =G30-F30 -> 5752.05 | I30: =F30/G30 -> 0.11165251
A31: ='Jul-2019'!A31 -> Participant Payroll fees | B31: =+'Aug 2019 GL'!G25 -> 1001.69 | E31: =SUM(B31:D31) -> 1001.69 | F31: =E31+'Jul-2019'!F31 -> 1873.95 | G31: 13000 | H31: =G31-F31 -> 11126.05 | I31: =F31/G31 -> 0.14415
A32: ='Jul-2019'!A32 -> Infrastructure Costs | E32: =SUM(B32:D32) -> 0 | F32: =E32+'Jul-2019'!F32 -> 0 | G32: 1500 | H32: =G32-F32 -> 1500 | I32: =F32/G32 -> 0
A33: ='Jul-2019'!A33 -> Other Operating costs | B33: =+'Aug 2019 GL'!G132 -> 575.94 | E33: =SUM(B33:D33) -> 575.94 | F33: =E33+'Jul-2019'!F33 -> 843.82 | G33: 3000.7 | H33: =G33-F33 -> 2156.88 | I33: =F33/G33 -> 0.28120772
A34: Communications | B34: =+'Aug 2019 GL'!G141 -> 272 | E34: =SUM(B34:D34) -> 272 | F34: =E34+'Jul-2019'!F34 -> 454.85 | G34: 3000 | H34: =G34-F34 -> 2545.15 | I34: =F34/G34 -> 0.15161667
A35: Insurance | B35: =+'Aug 2019 GL'!G147 -> 503 | E35: =SUM(B35:D35) -> 503 | F35: =E35+'Jul-2019'!F35 -> 823.72 | G35: 4000 | H35: =G35-F35 -> 3176.28 | I35: =F35/G35 -> 0.20593
A36: Postage | B36: =+'Aug 2019 GL'!G152 -> 38 | E36: =SUM(B36:D36) -> 38 | F36: =E36+'Jul-2019'!F36 -> 38 | G36: 1000 | H36: =G36-F36 -> 962 | I36: =F36/G36 -> 0.038
A37: Total NPOC | B37: =SUM(B23:B36) -> 3767.63 | C37: =SUM(C23:C36) -> 0 | D37: =SUM(D23:D36) -> 1265.03 | E37: =SUM(E23:E36) -> 5032.66 | F37: =SUM(F23:F36) -> 9673.18 | G37: =SUM(G23:G36) -> 76745.7 | H37: =SUM(H23:H36) -> 67072.52 | I37: =F37/G37 -> 0.12604198
A40: 3. Participant Costs
A41: Participant Wages | C41: =+'Aug 2019 GL'!G9-C42 -> 94574.04 | E41: =SUM(B41:D41) -> 94574.04 | F41: =E41+'Jul-2019'!F41 -> 153497.48 | G41: 1452829.2 | H41: =G41-F41-F42 -> 1298821.8 | I41: =F41/G41 -> 0.10565418
A42: Reimbursable Participant Wage(Paid by Affiliate) | C42: =SUM('Aug 2019 GL'!G11:G12) -> 509.96 | E42: =SUM(B42:D42) -> 509.96 | F42: =E42+'Jul-2019'!F42 -> 509.96 | I42: =F42/G42 -> #DIV/0!
A43: Participant Specialized Training Wage | E43: =SUM(B43:D43) -> 0 | F43: =E43+'Jul-2019'!F43 -> 0 | G43: 12820 | H43: =G43-F43 -> 12820 | I43: =F43/G43 -> 0
A44: Participant FICA and other taxes | C44: =+'Aug 2019 GL'!G18 -> 7276 | E44: =SUM(B44:D44) -> 7276 | F44: =E44+'Jul-2019'!F44 -> 11811.75 | G44: 111141.44 | H44: =G44-F44 -> 99329.69 | I44: =F44/G44 -> 0.10627674
A45: Workers compensation | C45: =+'Aug 2019 GL'!G21 -> 2741 | E45: =SUM(B45:D45) -> 2741 | F45: =E45+'Jul-2019'!F45 -> 4790.2 | G45: 22373.57 | H45: =G45-F45 -> 17583.37 | I45: =F45/G45 -> 0.21410083
A46: Support Services | E46: =SUM(B46:D46) -> 0 | F46: =E46+'Jul-2019'!F46 -> 0 | G46: 8500 | H46: =G46-F46 -> 8500 | I46: =F46/G46 -> 0
A47: Specialized Training vendor | E47: =SUM(B47:D47) -> 0 | F47: =E47+'Jul-2019'!F47 -> 0 | G47: 29630 | H47: =G47-F47 -> 29630 | I47: =F47/G47 -> 0
A48: Total Participant Costs | B48: =SUM(B41:B47) -> 0 | C48: =SUM(C41:C47) -> 105101 | D48: =SUM(D41:D47) -> 0 | E48: =SUM(E41:E47) -> 105101 | F48: =SUM(F41:F47) -> 170609.39 | G48: =SUM(G41:G47) -> 1637294.2 | H48: =SUM(H41:H47) -> 1466684.9 | I48: =F48/G48 -> 0.10420203
A50: 4. Indirect ('%) | B50: 0 | E50: =B50 -> 0 | F50: =E50+'Jul-2019'!F50 -> 0 | G50: 17532.59 | H50: =G50-F50 -> 17532.59 | I50: =F50/G50 -> 0
A52: 5.Total Federal Expenses | B52: =B20+B37+B48+B50 -> 11341.593 | C52: =C20+C37+C48 -> 105101 | D52: =D20+D37+D48 -> 16730.514 | E52: =E37+E20+E48+E50 -> 133173.11 | F52: =F37+F20+F48+F50 -> 218787.52 | G52: =G37+G20+G48+G50 -> 2013608.5 | H52: =H37+H20+H48+H50 -> 1794821 | I52: =F52/G52 -> 0.10865445
A54: 6. Non Federal Match | E54: 0 | F54: =E54+'Jul-2019'!F54 -> 7492.14 | G54: 242467.32 | H54: =G54-F54 -> 234975.18 | I54: =F54/G54 -> 0.030899587
A56: 7. Total Expenses | B56: =B52+B54 -> 11341.593 | C56: =C52+C54 -> 105101 | D56: =D52+D54 -> 16730.514 | E56: =E52+E54 -> 133173.11 | F56: =F52+F54 -> 226279.66 | G56: =G52+G54 -> 2256075.9 | H56: =H52+H54 -> 2029796.2 | I56: =F56/G56 -> 0.1002979
F57: AFFILIATES- ENTER NOTES TO THIS INVOICE HERE
A58: 8. Total Reimbursable expenses | E58: =+E20+E37-E31+E42+E45+E46+E47+E50 -> 30321.377
A60: FOR NUL USE ONLY
A62: TOTAL INVOICE SUBMITTED | E62: =E58 -> 30321.377
A65: COSTS DISALLOWED
A68: OTHER ADJUSTMENTS
A71: CASH DUE TO/DUE FROM AFFILIATE
A73: SIGNATURE AND DATE:
A77: Greg Ward | F77: Vivian Cox Fraser
A78: Fiscal Manager | B78: Date | F78: Affiliate CEO | H78: Date
A81: Gwendolyn Morris | F81: Patricia Sermon
A82: Project Director | B82: Date | F82: Chief Operating Officer | H82: Date

Sheet Aug 2019 GL
A1: URBAN LEAGUE OF ESSEX COUNTY
A2: 451 USJP Program Transaction Detail by Account
A3: August 2019
B5: Date | C5: Transaction Type | D5: Num | E5: Name | F5: Memo/Description | G5: Amount | H5: Check #
A6: 7100 Participant Salaries & Wages
B7: 08/12/2019 | C7: Journal Entry | D7: 00124 USJP | F7: USJP Participant Salaries 08/12 | G7: 46610
B8: 08/26/2019 | C8: Journal Entry | D8: 162 | F8: USJP Participant Salaries 08/26 | G8: 48474
A9: Total for 7112 Participant Wages - USJP | G9: =SUM(G7:G8) -> 95084
A10: 7112.1 USJP Manual Checks
B11: 08/13/2019 | C11: Bill | D11: 08.13.19RP | E11: Renee Portee | F11: Renee Portee owed hours for non-payment- 07/18/19 - 07/31/19 | G11: 236.8 | H11: 12375
B12: 08/13/2019 | C12: Bill | D12: 08.13.19KP | E12: Karen Peterson | F12: Hours owed for non payment - 07/18/19 - 07/31/19 | G12: 273.16 | H12: 12376
A13: Total for 7112.1 USJP Manual Checks | G13: =SUM(G11:G12) -> 509.96
A14: Total for 7112 Participant Wages - USJP with subs | G14: =+G13+G9 -> 95593.96
A15: 7120 Payroll Taxes
B16: 08/12/2019 | C16: Journal Entry | D16: 00124 USJP | F16: Employer Liability | G16: 3565.8
B17: 08/26/2019 | C17: Journal Entry | D17: 162 | F17: Employer Liability | G17: 3710.2
A18: Total for 7120 Payroll Taxes | G18: 7276
A19: 7130 Worker's Compensation - USJP
B20: 08/31/2019 | C20: Journal Entry | D20: 192 | F20: Workers Comp Alloc | G20: 2741
A21: Total for 7130 Worker's Compensation - USJP | G21: =SUM(G20) -> 2741
A22: 7132 Payroll Expenses - Fees
B23: 08/12/2019 | C23: Journal Entry | D23: 00124 USJP | F23: USJP Payroll Fee | G23: 401.87
B24: 08/26/2019 | C24: Journal Entry | D24: 162 | F24: USJP Payroll Fee | G24: 599.82
A25: Total for 7132 Payroll Expenses - Fees | G25: =SUM(G23:G24) -> 1001.69
A26: 7200 Salaries & Related Expenses
A27: 7220 Salaries & Wages
B28: 08/31/2019 | C28: Journal Entry | D28: 175 | F28: USJP Staff Salary Allocation - August | G28: 17145.83
A29: Total for 7220 Salaries & Wages | G29: =SUM(G28) -> 17145.83
A30: 7240 Employee Benefits
A31: 7241 Health Insurance
B32: 08/30/2019 | C32: Journal Entry | D32: 202 | F32: Horizon Health Insurance | G32: 3813.99 | H32: ONLINE
A33: Total for 7241 Health Insurance | G33: =SUM(G32) -> 3813.99
A34: 7242 Life and Dental Insurance
B35: 08/09/2019 | C35: Bill | E35: Principal Financial Group | F35: Life, Dental & AD&D - USJP | G35: 171.06 | H35: 12345
A36: Total for 7242 Life and Dental Insurance | G36: =SUM(G35) -> 171.06
A37: 7244 Employee Contrib - Health
B38: 43708 | C38: Journal Entry | D38: 154 | F38: Employee Medical Contrib | G38: -704.12
A39: Total for 7244 Employee Contrib - Health | G39: =SUM(G38) -> -704.12
A40: 7247 Emp-ee Contrib -Dental
B41: 43708 | C41: Journal Entry | D41: 155 | F41: Employee Dental Contrib | G41: -20.31
A42: Total for 7247 Emp-ee Contrib -Dental | G42: =SUM(G41) -> -20.31
A43: Total for 7240 Employee Benefits | G43: =+G33+G36+G39+G42 -> 3260.62
A45: 7245 Worker's Compensation Insurance
B46: 08/31/2019 | C46: Journal Entry | D46: 192 | F46: Workers Comp Alloc | G46: 494
A47: Total for 7248 Allocated W Comp | G47: =SUM(G46) -> 494
A48: EMPLOYER TAXES
A49: 7251 Social Security
B50: 08/31/2019 | C50: Journal Entry | D50: 202 | F50: Fica | G50: 1031
A51: Total for 7251 Social Security | G51: =SUM(G50) -> 1031
A52: 7252 Medicare
B53: 08/31/2019 | C53: Journal Entry | D53: 200 | F53: Medi Alloc | G53: 241
A54: Total for 7252 Medicare | G54: 241
A55: 7253 Unemployment
B56: 08/31/2019 | C56: Journal Entry | D56: 199 | F56: SUI Alloc | G56: 260
A57: Total for 7253 Unemployment | G57: 260
A58: 7254 Disability
B59: 08/31/2019 | C59: Journal Entry | D59: 194 | F59: Disability Alloc | G59: 55
A60: Total for 7254 Disability | G60: 55
A62: Total for 7250 Payroll Taxes, etc. | G62: =+G51+G54+G57+G60 -> 1587
A63: 7260 Payroll Service Fees
A64: 7260.1 Allocated Payroll Fees
B65: 08/31/2019 | C65: Journal Entry | D65: 198 | F65: Payroll Fees | G65: 213
A66: Total for 7260 Payroll Service Fees | G66: =SUM(G65) -> 213
A68: Total FRINGE BENEFITS | G68: =+G43+G47+G62+G66 -> 5554.62
A70: TRAVEL
A71: 8300 Travel & Meetings Expenses
A72: 8310 Transportation & Parking
B73: 08/14/2019 | C73: Check | D73: 12381 | E73: City of Paterson Parking Authority | F73: Parking Passaic County Site Coordinator Irene Cerna August 2019 | G73: 150 | H73: 12381
B74: 08/14/2019 | C74: Bill | D74: 08.14.19IC | E74: Irene Cerna | F74: Mileage Reimbursement - USJP July 2019 | G74: 57.89 | H74: 12461
B75: 08/29/2019 | C75: Bill | D75: 08.29.19MT | E75: Mary Tanner | F75: Mileage From Passaic to Newark (Pickup checks for Passaic) | G75: 30.24 | H75: 12462
B76: 08/29/2019 | C76: Bill | D76: 08.29.19AA | E76: Alberto Almanzar | F76: USJP Mileage Reimbursement 08.19 | G76: 49 | H76: 12463
A77: Total for 8300 Travel & Meetings Expenses | G77: =SUM(G73:G76) -> 287.13
A79: 8110 Supplies
B80: 08/19/2019 | C80: Bill | D80: 7300289614-01 | E80: Staples Advantage | F80: 10 Cases Copy Paper - Order #7300289614-0-1 | G80: 329.9 | H80: 12449
A81: Total for 8110 Supplies | G81: =SUM(G80) -> 329.9
A83: 8112 Alloc Supplies
B84: 08/31/2019 | C84: Journal Entry | D84: 185 | F84: Supplies Alloc | G84: 86
A85: Total for 8112 Alloc Supplies | G85: =SUM(G84) -> 86
A87: Total for 8110 Supplies | G87: =+G81+G85 -> 415.9
A89: CONTRACTUAL CONSULTANTS
A90: 7520 Accounting Fees
B91: 08/31/2019 | C91: Journal Entry | D91: 180 | F91: Acctg Fee Alloc | G91: 496
A92: Total for CONTRACTUAL CONSULTANTS | G92: 496
A94: OCCUPANCY
A95: 8205 Rent, Parking, Other Occupancy
B96: 08/01/2019 | C96: Bill | D96: 07.31.19CFT | E96: Center for Transformative Work | F96: USJP - Rent Expense August 2019 | G96: 648 | H96: 12363
A97: Total for OCCUPANCY - PROGRAM TOTAL 8205 Rent | G97: 648
A98: 8210 Utilities
A99: 8210.5 Allocated Utilities
B100: 08/31/2019 | C100: Journal Entry | D100: 189 | F100: Utilities | G100: 176
A101: Total for 8210.5 Allocated Utilities | G101: 176
A102: 8230 Building Repair & Maintenance
B103: 08/31/2019 | C103: Journal Entry | D103: 184 | F103: Repairs | G103: 97
A104: Total for 8239 Alloc Repairs and Maint | G104: 97
A105: OCCUPANCY - ADMIN TOTAL | G105: =+G101+G104 -> 273
A107: Total for OCCUPANCY PROGRAM & ADMIN | G107: =+G97+G105 -> 921
A109: RENTAL EQUIPMENT
A110: 8227 Equipment Rental
B111: 08/01/2019 | C111: Bill | D111: 3309396317 | E111: Pitney Bowes | F111: Lease Invoice Billing Period 7/30/2019- 10/29/19 | G111: 228 | H111: 12418
A112: Total for 8227 Equipment Rental | G112: =SUM(G111) -> 228
...

Sheet AUG-FR
A1: National Urban League Financial Report
A2: 1. Funding Agency- National Urban League | I2: 2. Federal Grant Name - Urban Seniors Jobs Program CFDA 17.235 | N2: PY 19
A3: 3. Recipient Organization (Name and complete address including Zip code)
M4: 4. Final Report (mark X) Yes No | N4: 5. Basis of Reporting □ Accrual
A5: 6. Project/Grant Period From: July 1-2019 | H5: To: June 31, 2020 | M5: 7. Reporting Period End Date 8/31/2019
A6: 8. Transactions | M6: Cumulative
A7: Federal Cash:
A8: a. Cash Receipts
A9: b. Cash Disbursements | M9: =M8 -> 0
A10: c. Cash on Hand (line a minus b) | M10: =M8-M9 -> 0
A11: Federal Expenditures and Unobligated Balance:
A12: d. Approved Budget
A13: e. Federal Share of Expenditures -Program Costs | M13: =M9 -> 0
A14: f. Federal Share of Expenditures -Administrative Costs | M14: 0
A15: g. Federal Share of Unliquidated Obligations ( ACCRUALS) | M15: 0
A16: h. Total Federal Obligations (sum of lines e and g) | M16: =M13+M14+M15 -> 0
A17: i. Unobligated Balance of Federal Funds (line d minus h) | M17: =M12-M16 -> 0
A18: Recipient Share: Cost Sharing/ Matching/ In-Kind Costs
A19: j. Total Match and Inkind Required if Applicable | M19: 0
A20: k. Total Receipient share reported if Applicable | M20: 0
A21: l. Remaining Recipient Share to Be Provided (line j minus k) | M21: =M19-M20 -> 0
A22: Program Income:
A23: m. Total Program Income Earned if applicable | M23: 0
A24: n. Program Income Expended in Accordance with the Addition Method | M24: 0
A25: o. Unexpended Program Income (line m minus line n) | M25: =M23-M24 -> 0
A26: 9. Remarks: (Attach any explanations deemed necessary or information required by Federal sponsoring agency in compliance with governing legislation.)
A28: 10. Indirect Expenditures
A29: a. Type of Rate | C29: b. Rate | D29: c. Rate Approval Date | G29: d. Period From (MM/DD/YYYY) | I29: Period To (MM/DD/YYYY) | J29: e. Base | M29: f. Amount Charged | N29: g. Federal Share
A32: 11. Certification: By signing this report, I certify to the best of my knowledge and belief that the report is true, complete, and accurate, and the expenditures, disbursements and cash receipts are for the purposes and objectives set forth in the terms and conditions of the Federal award. I am aware that any false, fictitious, or fraudulent information, or the omission of any material fact, may subject me to criminal, civil or administrative penalties for fraud, false statements, false claims or otherwise. (U.S. Code Title 18, Section 1001 and Title 31, Sections 3729–3730 and 3801–3812).
A33: a. Typed or Printed Name and Title of Authorized Certifying Official | M33: c. Telephone (Area code, number, and extension)
M34: d. Email Address
A35: b. Signature of Authorized Certifying Official | M35: e. Date Report Submitted (MM/DD/YYYY)

Sheet Sept-2019
A1: Urban Seniors Jobs Program PY 19 | G1: 43709 | I1: %
A2: Urban League of Essex County | E2: Invoice # 3 | I2: Spent
A3: 1. PERSONNEL | E3: TOTAL
C4: ENROLLEE | D4: OPC | E4: MONTHLY | F4: CUMULATIVE | G4: TOTAL | H4: BUDGET
A5: POSITION TITLE | B5: ADMIN | C5: WAGES & FB | D5: PROGRAM | E5: AMOUNT | F5: EXPENSES | G5: BUDGET | H5: REMAINING
A6: COO Patricia Sermon | B6: =+'Salaries & Fringe Allocations'!F113 -> 1261.54 | E6: =SUM(B6:D6) -> 1261.54 | F6: =E6+'Aug-2019'!F6 -> 3469.23 | G6: 16400 | H6: =G6-F6 -> 12930.77 | I6: =F6/G6 -> 0.21153841
A7: Director Gwendolyn Morris | B7: =+'Salaries & Fringe Allocations'!F114 -> 2071.43 | D7: =+'Salaries & Fringe Allocations'!F115 -> 2928.57 | E7: =SUM(B7:D7) -> 5000 | F7: =E7+'Aug-2019'!F7 -> 13750 | G7: 66000 | H7: =G7-F7 -> 52250 | I7: =F7/G7 -> 0.20833333
A8: Prog Site Coordinator (Essex) Rahmel Leake | D8: =+'Salaries & Fringe Allocations'!F116 -> 3076.94 | E8: =SUM(B8:D8) -> 3076.94 | F8: =E8+'Aug-2019'!F8 -> 6923.12 | G8: 40000 | H8: =G8-F8 -> 33076.88 | I8: =F8/G8 -> 0.173078
A9: Prog Site Coordinator (Passaic) Irene Cerna | D9: =+'Salaries & Fringe Allocations'!F117 -> 1730.78 | E9: =SUM(B9:D9) -> 1730.78 | F9: =E9+'Aug-2019'!F9 -> 5769.36 | G9: 30000 | H9: =G9-F9 -> 24230.64 | I9: =F9/G9 -> 0.192312
A10: Prog Site Coordinator (Morris) Alberto Almanzar | D10: =+'Salaries & Fringe Allocations'!F118 -> 1268.96 | E10: =SUM(B10:D10) -> 1268.96 | F10: =E10+'Aug-2019'!F10 -> 4210.64 | G10: 21500 | H10: =G10-F10 -> 17289.36 | I10: =F10/G10 -> 0.19584372
A11: Program Assistant Joanna Martinez | B11: =+'Salaries & Fringe Allocations'!F119 -> 703.3 | D11: =+'Salaries & Fringe Allocations'!F120 -> 1050.57 | E11: =SUM(B11:D11) -> 1753.87 | F11: =E11+'Aug-2019'!F11 -> 6984.67 | G11: 36000 | H11: =G11-F11 -> 29015.33 | I11: =F11/G11 -> 0.19401861
A12: Staff Accountant - Gregory Ward | B12: =+'Salaries & Fringe Allocations'!F121 -> 846.15 | E12: =SUM(B12:D12) -> 846.15 | F12: =E12+'Aug-2019'!F12 -> 1692.3 | G12: 4000 | H12: =G12-F12 -> 2307.7 | I12: =F12/G12 -> 0.423075
A16: Total Salaries | B16: =SUM(B6:B15) -> 4882.42 | C16: =SUM(C6:C15) -> 0 | D16: =SUM(D6:D15) -> 10055.82 | E16: =SUM(E6:E15) -> 14938.24 | F16: =SUM(F6:F15) -> 42799.32 | G16: =SUM(G6:G15) -> 213900 | H16: =SUM(H6:H15) -> 171100.68 | I16: =F16/G16 -> 0.20009032
A18: Fringe Benefits Rate | B18: =+'Salaries & Fringe Allocations'!Q113+'Salaries & Fringe Allocations'!Q114+'Salaries & Fringe Allocations'!Q119+'Salaries & Fringe Allocations'!Q121 -> 1816.6301 | D18: =+'Salaries & Fringe Allocations'!Q115+'Salaries & Fringe Allocations'!Q116+'Salaries & Fringe Allocations'!Q117+'Salaries & Fringe Allocations'!Q118+'Salaries & Fringe Allocations'!Q120 -> 3474.9889 | E18: =SUM(B18:D18) -> 5291.619 | F18: =E18+'Aug-2019'!F18 -> 15935.49 | G18: 68136 | H18: =G18-F18 -> 52200.51 | I18: =F18/G18 -> 0.23387769
H19: =G19-F19 -> 0
A20: TOTAL PERSONNEL (Salaries + Fringe Benefits) | B20: =B16+B18 -> 6699.0501 | C20: =C16+C18 -> 0 | D20: =D16+D18 -> 13530.809 | E20: =E16+E18 -> 20229.859 | F20: =F16+F18 -> 58734.81 | G20: =G16+G18 -> 282036 | H20: =H16+H18 -> 223301.19 | I20: =F20/G20 -> 0.20825288
A22: 2. Non-Personnel Operating Costs
A23: Travel | B23: =+'Sept-2019 GL'!G81 -> 312.43 | E23: =SUM(B23:D23) -> 312.43 | F23: =E23+'Aug-2019'!F23 -> 867.58 | G23: 4000 | H23: =G23-F23 -> 3132.42 | I23: =F23/G23 -> 0.216895
A24: Supplies | E24: =SUM(B24:D24) -> 0 | F24: =E24+'Aug-2019'!F24 -> 471.49 | G24: 7000 | H24: =G24-F24 -> 6528.51 | I24: =F24/G24 -> 0.067355714
A25: Staff Development | E25: =SUM(B25:D25) -> 0 | F25: =E25+'Aug-2019'!F25 -> 0 | G25: 2000 | H25: =G25-F25 -> 2000 | I25: =F25/G25 -> 0
A26: Contractual/Consultants | B26: =+'Sept-2019 GL'!G86 -> 606 | E26: =SUM(B26:D26) -> 606 | F26: =E26+'Aug-2019'!F26 -> 1463.69 | G26: 13200 | H26: =G26-F26 -> 11736.31 | I26: =F26/G26 -> 0.11088561
A27: Occupancy | B27: =+'Sept-2019 GL'!G100 -> 230 | D27: =+'Sept-2019 GL'!G91 -> 648 | E27: =SUM(B27:D27) -> 878 | F27: =E27+'Aug-2019'!F27 -> 2779.27 | G27: 12000 | H27: =G27-F27 -> 9220.73 | I27: =F27/G27 -> 0.23160583
A28: Audit (100% Admin) | E28: =SUM(B28:D28) -> 0 | F28: =E28+'Aug-2019'!F28 -> 1130.29 | G28: 6000 | H28: =G28-F28 -> 4869.71 | I28: =F28/G28 -> 0.18838167
A29: Marketing and Outreach | E29: =SUM(B29:D29) -> 0 | F29: =E29+'Aug-2019'!F29 -> 0 | G29: 570 | H29: =G29-F29 -> 570 | I29: =F29/G29 -> 0
A30: Rental Equipment | B30: =+'Sept-2019 GL'!G107 -> 287 | E30: =SUM(B30:D30) -> 287 | F30: =E30+'Aug-2019'!F30 -> 1009.95 | G30: 6475 | H30: =G30-F30 -> 5465.05 | I30: =F30/G30 -> 0.15597683
A31: Payroll fees | B31: =+'Sept-2019 GL'!G30 -> 877.52 | E31: =SUM(B31:D31) -> 877.52 | F31: =E31+'Aug-2019'!F31 -> 2751.47 | G31: 13000 | H31: =G31-F31 -> 10248.53 | I31: =F31/G31 -> 0.21165154
A32: Infrastructure Costs | E32: =SUM(B32:D32) -> 0 | F32: =E32+'Aug-2019'!F32 -> 0 | G32: 1500 | H32: =G32-F32 -> 1500 | I32: =F32/G32 -> 0
A33: Other Operating costs | B33: =+'Sept-2019 GL'!G117 -> 411 | E33: =SUM(B33:D33) -> 411 | F33: =E33+'Aug-2019'!F33 -> 1254.82 | G33: 3000.7 | H33: =G33-F33 -> 1745.88 | I33: =F33/G33 -> 0.41817576
A34: Communications | B34: =+'Sept-2019 GL'!G129 -> 226.16 | E34: =SUM(B34:D34) -> 226.16 | F34: =E34+'Aug-2019'!F34 -> 681.01 | G34: 3000 | H34: =G34-F34 -> 2318.99 | I34: =F34/G34 -> 0.22700333
A35: Insurance | B35: =+'Sept-2019 GL'!G135 -> 491 | E35: =SUM(B35:D35) -> 491 | F35: =E35+'Aug-2019'!F35 -> 1314.72 | G35: 4000 | H35: =G35-F35 -> 2685.28 | I35: =F35/G35 -> 0.32868
A36: Postage | E36: =SUM(B36:D36) -> 0 | F36: =E36+'Aug-2019'!F36 -> 38 | G36: 1000 | H36: =G36-F36 -> 962 | I36: =F36/G36 -> 0.038
A37: Total NPOC | B37: =SUM(B23:B36) -> 3441.11 | C37: =SUM(C23:C36) -> 0 | D37: =SUM(D23:D36) -> 648 | E37: =SUM(E23:E36) -> 4089.11 | F37: =SUM(F23:F36) -> 13762.29 | G37: =SUM(G23:G36) -> 76745.7 | H37: =SUM(H23:H36) -> 62983.41 | I37: =F37/G37 -> 0.17932327
A40: 3. Participant Costs
A41: Participant Wages | C41: =+'Sept-2019 GL'!G9 -> 90254 | E41: =SUM(B41:D41) -> 90254 | F41: =E41+'Aug-2019'!F41 -> 243751.48 | G41: 1452829.2 | H41: =G41-F41-F42 -> 1207081.2 | I41: =F41/G41 -> 0.1677771
A42: Reimbursable Participant Wage(Paid by Affiliate) | C42: =+'Sept-2019 GL'!G18 -> 1486.56 | E42: =SUM(B42:D42) -> 1486.56 | F42: =E42+'Aug-2019'!F42 -> 1996.52 | I42: 0
A43: Participant Specialized Training Wage | E43: =SUM(B43:D43) -> 0 | F43: =E43+'Aug-2019'!F43 -> 0 | G43: 12820 | H43: =G43-F43 -> 12820 | I43: =F43/G43 -> 0
A44: Participant FICA and other taxes | C44: =+'Sept-2019 GL'!G23 -> 6904.52 | E44: =SUM(B44:D44) -> 6904.52 | F44: =E44+'Aug-2019'!F44 -> 18716.27 | G44: 111141.44 | H44: =G44-F44 -> 92425.17 | I44: =F44/G44 -> 0.16840046
A45: Workers compensation | C45: =+'Sept-2019 GL'!G26 -> 2868 | E45: =SUM(B45:D45) -> 2868 | F45: =E45+'Aug-2019'!F45 -> 7658.2 | G45: 22373.57 | H45: =G45-F45 -> 14715.37 | I45: =F45/G45 -> 0.3422878
A46: Support Services | E46: =SUM(B46:D46) -> 0 | F46: =E46+'Aug-2019'!F46 -> 0 | G46: 8500 | H46: =G46-F46 -> 8500 | I46: =F46/G46 -> 0
A47: Specialized Training vendor | E47: =SUM(B47:D47) -> 0 | F47: =E47+'Aug-2019'!F47 -> 0 | G47: 29630 | H47: =G47-F47 -> 29630 | I47: =F47/G47 -> 0
A48: Total Participant Costs | B48: =SUM(B41:B47) -> 0 | C48: =SUM(C41:C47) -> 101513.08 | D48: =SUM(D41:D47) -> 0 | E48: =SUM(E41:E47) -> 101513.08 | F48: =SUM(F41:F47) -> 272122.47 | G48: =SUM(G41:G47) -> 1637294.2 | H48: =SUM(H41:H47) -> 1365171.8 | I48: =F48/G48 -> 0.16620254
A50: 4. Indirect ('%) | B50: 0 | E50: =B50 -> 0 | F50: =E50+'Aug-2019'!F50 -> 0 | G50: 17532.59 | H50: =G50-F50 -> 17532.59 | I50: =F50/G50 -> 0
A52: 5.Total Federal Expenses | B52: =B20+B37+B48+B50 -> 10140.16 | C52: =C20+C37+C48 -> 101513.08 | D52: =D20+D37+D48 -> 14178.809 | E52: =E37+E20+E48+E50 -> 125832.05 | F52: =F37+F20+F48+F50 -> 344619.57 | G52: =G37+G20+G48+G50 -> 2013608.5 | H52: =H37+H20+H48+H50 -> 1668989 | I52: =F52/G52 -> 0.17114527
A54: 6. Non Federal Match | E54: 0 | F54: =E54+'Aug-2019'!F54 -> 7492.14 | G54: 242467.32 | H54: =G54-F54 -> 234975.18 | I54: =F54/G54 -> 0.030899587
A56: 7. Total Expenses | B56: =B52+B54 -> 10140.16 | C56: =C52+C54 -> 101513.08 | D56: =D52+D54 -> 14178.809 | E56: =E52+E54 -> 125832.05 | F56: =F52+F54 -> 352111.71 | G56: =G52+G54 -> 2256075.9 | H56: =H52+H54 -> 1903964.1 | I56: =F56/G56 -> 0.15607264
F57: AFFILIATES- ENTER NOTES TO THIS INVOICE HERE
A58: 8. Total Reimbursable expenses | E58: =+E20+E37-E31+E42+E45+E46+E47+E50 -> 27796.009
A60: FOR NUL USE ONLY
A62: TOTAL INVOICE SUBMITTED | E62: =E58 -> 27796.009
A65: COSTS DISALLOWED
A68: OTHER ADJUSTMENTS
A71: CASH DUE TO/DUE FROM AFFILIATE
A73: SIGNATURE AND DATE:
A77: Greg Ward | F77: Vivian Cox Fraser
A78: Fiscal Manager | B78: Date | F78: Affiliate CEO | H78: Date
A81: Gwendolyn Morris | F81: Patricia Sermon
A82: Project Director | B82: Date | F82: Chief Operating Officer | H82: Date

Sheet Sept-2019 GL
A1: URBAN LEAGUE OF ESSEX COUNTY
A2: 451 USJP Program Transaction Detail by Account
A3: September 2019
B5: Date | C5: Transaction Type | D5: Num | E5: Name | F5: Memo/Description | G5: Amount | H5: Check #
A6: 7112 Participant Wages - USJP
B7: 09/09/2019 | C7: Journal Entry | D7: 243 | F7: USJP Participant Salaries 09/09 | G7: 47030
B8: 09/23/2019 | C8: Journal Entry | D8: 245 | F8: USJP Participant Salaries 09/09 | G8: 43224
A9: Total for 7112 Participant Wages - USJP | G9: =SUM(G7:G8) -> 90254
A10: 7112.1 USJP Manual Checks
B11: 09/11/2019 | C11: Bill | D11: 09.11.19CP | E11: Carolyn Parks | F11: Participant Wages 30 Training hours from 08/29 - 09/11/19 | G11: 273.13 | H11: 12506
B12: 09/11/2019 | C12: Bill | D12: 09.11.19CK | E12: Clarence Kersey | F12: 451-USJP - 25 Hrs Training from 08/29 - 09/11/19 | G12: 227.71 | H12: 12507
B13: 09/11/2019 | C13: Bill | D13: 09.11.19DD | E13: Deloris Davis | F13: 451-USJP - 25 Hrs Training from 08/29 - 09/11/19 | G13: 227.7 | H13: 12508
B14: 09/23/2019 | C14: Check | D14: 12494 | E14: David Garrett | F14: USJP 10 hours owed for Pay Period 8/29/19 - 9/11/19 Check Date 9/23/19 was paid for 30 hours instead of 40 hours in error | G14: 101.59 | H14: 12494
B15: 09/23/2019 | C15: Check | D15: 12496 | E15: Jeffrey Matthews | F15: USJP 29 Hours owed for Pay Period 8/29/19 - 9/11/19 Check Date 9/23/19. Employees hours were not included in Payroll file. | G15: 264.05 | H15: 12496
B16: 09/23/2019 | C16: Check | D16: 12497 | E16: Reginald Williams | F16: USJP Participant owed 16 hours for training from 8/29/19 - 9/11/19 Check Date 9/23/19. Not previously paid. | G16: 146.51 | H16: 12497
B17: 09/23/2019 | C17: Check | D17: 12495 | E17: Willie Chestnut | F17: USJP 27 Hours owed for Pay Period 8/29/19 - 9/11/19 Check Date 9/23/19. Employees hours were not included in Payroll file. | G17: 245.87 | H17: 12495
A18: Total for 7112.1 USJP Manual Checks | G18: =SUM(G11:G17) -> 1486.56
A19: Total for 7112 Participant Wages - USJP with subs | G19: =+G18+G9 -> 91740.56
A20: 7120 Payroll Taxes
B21: 09/09/2019 | C21: Journal Entry | D21: 243 | F21: Employer Liability | G21: 3597.9
B22: 09/23/2019 | C22: Journal Entry | D22: 245 | F22: Employer Liability | G22: 3306.62
A23: Total for 7120 Payroll Taxes | G23: 6904.52
A24: 7130 Worker's Compensation - USJP
B25: 43738 | C25: Journal Entry | D25: 192 | F25: Workers Comp Alloc | G25: 2868
A26: Total for 7130 Worker's Compensation - USJP | G26: =SUM(G25) -> 2868
A27: 7132 Payroll Expenses - Fees
B28: 09/09/2019 | C28: Journal Entry | D28: 243 | F28: USJP Payroll Fee | G28: 403.93
B29: 09/23/2019 | C29: Journal Entry | D29: 245 | F29: USJP Payroll Fee | G29: 473.59
A30: Total for 7132 Payroll Expenses - Fees | G30: 877.52
A31: Total for 7100 Participant Salaries & Wages | G31: =+G19+G23+G26+G30 -> 102390.6
A32: 7200 Salaries & Related Expenses
A33: 7220 Salaries & Wages
B34: 09/25/2019 | C34: Journal Entry | D34: 242 | F34: Salary Allocation - September | G34: 14938.24
A35: Total for 7220 Salaries & Wages | G35: =SUM(G34) -> 14938.24
A36: 7240 Employee Benefits
A37: 7241 Health Insurance
B38: 09/01/2019 | C38: Bill | D38: 292271815 | E38: Horizon Blue Cross Blue Shield of NJ | G38: 3813.99 | H38: 12472
A39: Total for 7241 Health Insurance | G39: =SUM(G38:G38) -> 3813.99
A40: 7242 Life and Dental Insurance
B41: 09/01/2019 | C41: Bill | D41: 09.01.19PL | E41: Principal Financial Group | F41: Life, Dental & AD&D - USJP | G41: 171.0615 | H41: 12433
A42: Total for 7242 Life and Dental Insurance | G42: =SUM(G41) -> 171.0615
A44: 7244 Employee Contrib - Health
B45: 43708 | C45: Journal Entry | D45: 154 | F45: Employee Medical Contrib | G45: -704.119
A46: Total for 7244 Employee Contrib - Health | G46: =SUM(G45) -> -704.119
A47: 7247 Emp-ee Contrib -Dental
B48: 43708 | C48: Journal Entry | D48: 155 | F48: Employee Dental Contrib | G48: -20.314
A49: Total for 7247 Emp-ee Contrib -Dental | G49: =SUM(G48) -> -20.314
A50: Total for 7240 Employee Benefits | G50: =+G42+G39+G46+G49 -> 3260.6185
A52: 7245 Worker's Compensation Insurance
A53: 7248 Allocated W Comp
B54: 09/30/2019 | C54: Journal Entry | D54: 261 | F54: Workers Comp Alloc | G54: 467
A55: Total for 7245 Worker's Compensation Insurance | G55: =SUM(G54) -> 467
A56: EMPLOYER TAXES
A57: 7251 Social Security
B58: 09/30/2019 | C58: Journal Entry | D58: 246 | F58: Fica | G58: 904
A59: Total for 7251 Social Security | G59: =SUM(G58) -> 904
A60: 7252 Medicare
B61: 09/30/2019 | C61: Journal Entry | D61: 248 | F61: Medi Alloc | G61: 212
A62: Total for 7252 Medicare | G62: =SUM(G61) -> 212
A63: 7253 Unemployment
B64: 09/30/2019 | C64: Journal Entry | D64: 249 | F64: SUI Alloc | G64: 221
A65: Total for 7253 Unemployment | G65: =SUM(G64) -> 221
A66: 7254 Disability
B67: 09/30/2019 | C67: Journal Entry | D67: 250 | F67: Disability Alloc | G67: 43
A68: Total for 7254 Disability | G68: =SUM(G67) -> 43
A69: TOTAL EMPLOYER TAXES | G69: =+G59+G62+G65+G68 -> 1380
A71: 7260 Payroll Service Fees
B72: 09/30/2019 | C72: Journal Entry | D72: 251 | F72: Payroll Fees | G72: 184
A73: Total for 7260 Payroll Service Fees | G73: =SUM(G72) -> 184
A74: Total for 7200 Salaries & Fringe | G74: =+G35+G50+G55+G69+G73 -> 20229.858
A75: 8300 Travel & Meetings Expenses
A76: 8310 Transportation & Parking
B77: 09/01/2019 | C77: Check | D77: 12457 | E77: City of Paterson Parking Authority | F77: Parking Passaic County Site Coordinator Irene Cerna September 2019 | G77: 150 | H77: 12457
B78: 09/12/2019 | C78: Bill | D78: 09.12.19GM | E78: Gwendolyn Morris | F78: Travel Reimbursement - Mileage - 08/6/19 - 9/10/19 | G78: 101.09 | H78: 12490
B79: 09/12/2019 | C79: Bill | D79: 09.12.19AJ | E79: Armanda Johnson | F79: Mileage From Newark To Morristown 09/10/19 - 09/13/19 | G79: 32.4 | H79: 12489
B80: 09/12/2019 | C80: Bill | D80: 09.12.19IC | E80: Irene Cerna | F80: Mileage Reimbursement - USJP 8/14/19 - 8/28/19 | G80: 28.94 | H80: 12491
A81: Total for 8300 Travel & Meetings Expenses | G81: =SUM(G77:G80) -> 312.43
A83: CONTRACTUAL CONSULTANTS
A84: 7521 Allocated Acctg and Audit
B85: 09/30/2019 | C85: Journal Entry | D85: 253 | F85: Acctg Fee Alloc | G85: 606
A86: Total for 7520 Accounting Fees | G86: =SUM(G85) -> 606
A88: OCCUPANCY
A89: 8205 Rent, Parking, Other Occupancy
B90: 09/01/2019 | C90: Bill | D90: 1967 | E90: Center for Transformative Work | F90: USJP - Rent Expense September 2019 | G90: 648 | H90: 12456
A91: Total for OCCUPANCY - PROGRAM TOTAL 8205 Rent | G91: =SUM(G90) -> 648
A92: 8210 Utilities
A93: 8210.5 Allocated Utilities
B94: 09/30/2019 | C94: Journal Entry | D94: 260 | F94: Utilities | G94: 135
A95: Total for 8210 Utilities | G95: =SUM(G94) -> 135
A96: 8230 Building Repair & Maintenance
A97: 8239 Alloc Repairs and Maint
B98: 09/30/2019 | C98: Journal Entry | D98: 257 | F98: Repairs | G98: 95
A99: Total for 8230 Building Repair & Maintenance | G99: =SUM(G98) -> 95
A100: OCCUPANCY - ADMIN TOTAL | G100: =+G95+G99 -> 230
A102: Total for OCCUPANCY PROGRAM & ADMIN | G102: =+G91+G100 -> 878
A104: EQUIPMENT RENTAL
A105: 8229.1 Allocated Cost
B106: 09/30/2019 | C106: Journal Entry | D106: 256 | F106: Equipment Leases | G106: 287
A107: Total for 8220 Equipment Rental, Repair & Maintenance | G107: =SUM(G106) -> 287
A109: OTHER OPERATING COSTS
...

Sheet Sept-FR
A1: National Urban League Financial Report
A2: 1. Funding Agency- National Urban League | I2: 2. Federal Grant Name - Urban Seniors Jobs Program CFDA 17.235 | N2: PY 19
A3: 3. Recipient Organization (Name and complete address including Zip code)
M4: 4. Final Report (mark X) Yes No | N4: 5. Basis of Reporting □ Accrual
A5: 6. Project/Grant Period From: July 1-2019 | H5: To: June 31, 2020 | M5: 7. Reporting Period End Date 9/30/2019
A6: 8. Transactions | M6: Cumulative
A7: Federal Cash:
A8: a. Cash Receipts
A9: b. Cash Disbursements | M9: =M8 -> 0
A10: c. Cash on Hand (line a minus b) | M10: =M8-M9 -> 0
A11: Federal Expenditures and Unobligated Balance:
A12: d. Approved Budget
A13: e. Federal Share of Expenditures -Program Costs | M13: =M9 -> 0
A14: f. Federal Share of Expenditures -Administrative Costs | M14: 0
A15: g. Federal Share of Unliquidated Obligations ( ACCRUALS) | M15: 0
A16: h. Total Federal Obligations (sum of lines e and g) | M16: =M13+M14+M15 -> 0
A17: i. Unobligated Balance of Federal Funds (line d minus h) | M17: =M12-M16 -> 0
A18: Recipient Share: Cost Sharing/ Matching/ In-Kind Costs
A19: j. Total Match and Inkind Required if Applicable | M19: 0
A20: k. Total Receipient share reported if Applicable | M20: 0
A21: l. Remaining Recipient Share to Be Provided (line j minus k) | M21: =M19-M20 -> 0
A22: Program Income:
A23: m. Total Program Income Earned if applicable | M23: 0
A24: n. Program Income Expended in Accordance with the Addition Method | M24: 0
A25: o. Unexpended Program Income (line m minus line n) | M25: =M23-M24 -> 0
A26: 9. Remarks: (Attach any explanations deemed necessary or information required by Federal sponsoring agency in compliance with governing legislation.)
A28: 10. Indirect Expenditures
A29: a. Type of Rate | C29: b. Rate | D29: c. Rate Approval Date | G29: d. Period From (MM/DD/YYYY) | I29: Period To (MM/DD/YYYY) | J29: e. Base | M29: f. Amount Charged | N29: g. Federal Share
A32: 11. Certification: By signing this report, I certify to the best of my knowledge and belief that the report is true, complete, and accurate, and the expenditures, disbursements and cash receipts are for the purposes and objectives set forth in the terms and conditions of the Federal award. I am aware that any false, fictitious, or fraudulent information, or the omission of any material fact, may subject me to criminal, civil or administrative penalties for fraud, false statements, false claims or otherwise. (U.S. Code Title 18, Section 1001 and Title 31, Sections 3729–3730 and 3801–3812).
A33: a. Typed or Printed Name and Title of Authorized Certifying Official | M33: c. Telephone (Area code, number, and extension)
M34: d. Email Address
A35: b. Signature of Authorized Certifying Official | M35: e. Date Report Submitted (MM/DD/YYYY)

Sheet Oct-2019
A1: Urban Seniors Jobs Program PY 19 | G1: 43739 | I1: %
A2: Urban League of Essex County | E2: Invoice # 4 | I2: Spent
A3: 1. PERSONNEL | E3: TOTAL
C4: ENROLLEE | D4: OPC | E4: MONTHLY | F4: CUMULATIVE | G4: TOTAL | H4: BUDGET
A5: POSITION TITLE | B5: ADMIN | C5: WAGES & FB | D5: PROGRAM | E5: AMOUNT | F5: EXPENSES | G5: BUDGET | H5: REMAINING
A6: COO Patricia Sermon | B6: =+'Salaries & Fringe Allocations'!F155 -> 1261.54 | E6: =SUM(B6:D6) -> 1261.54 | F6: =E6+'Sept-2019'!F6 -> 4730.77 | G6: 16400 | H6: =G6-F6 -> 11669.23 | I6: =F6/G6 -> 0.28846159
A7: Director Gwendolyn Morris | B7: =+'Salaries & Fringe Allocations'!F156 -> 2192.86 | D7: =+'Salaries & Fringe Allocations'!F157 -> 2807.14 | E7: =SUM(B7:D7) -> 5000 | F7: =E7+'Sept-2019'!F7 -> 18750 | G7: 66000 | H7: =G7-F7 -> 47250 | I7: =F7/G7 -> 0.28409091
A8: Prog Site Coordinator (Essex) Rahmel Leake | D8: =+'Salaries & Fringe Allocations'!F158 -> 3076.94 | E8: =SUM(B8:D8) -> 3076.94 | F8: =E8+'Sept-2019'!F8 -> 10000.06 | G8: 40000 | H8: =G8-F8 -> 29999.94 | I8: =F8/G8 -> 0.2500015
A9: Prog Site Coordinator (Passaic) Irene Cerna | D9: =+'Salaries & Fringe Allocations'!F159 -> 2192.32 | E9: =SUM(B9:D9) -> 2192.32 | F9: =E9+'Sept-2019'!F9 -> 7961.68 | G9: 30000 | H9: =G9-F9 -> 22038.32 | I9: =F9/G9 -> 0.26538933
A10: Site Coordinator (Morris) Armanda Johnson | D10: =+'Salaries & Fringe Allocations'!F160 -> 1586.2 | E10: =SUM(B10:D10) -> 1586.2 | F10: =E10+'Sept-2019'!F10 -> 5796.84 | G10: 21500 | H10: =G10-F10 -> 15703.16 | I10: =F10/G10 -> 0.26962047
A11: Program Assistant Joanna Martinez | E11: =SUM(B11:D11) -> 0 | F11: =E11+'Sept-2019'!F11 -> 6984.67 | G11: 36000 | H11: =G11-F11 -> 29015.33 | I11: =F11/G11 -> 0.19401861
A12: Staff Accountant - Gregory Ward | B12: =+'Salaries & Fringe Allocations'!F163 -> 846.15 | E12: =SUM(B12:D12) -> 846.15 | F12: =E12+'Sept-2019'!F12 -> 2538.45 | G12: 4000 | H12: =G12-F12 -> 1461.55 | I12: =F12/G12 -> 0.6346125
E13: =SUM(B13:D13) -> 0
E14: =SUM(B14:D14) -> 0
A16: Total Salaries | B16: =SUM(B6:B15) -> 4300.55 | C16: =SUM(C6:C15) -> 0 | D16: =SUM(D6:D15) -> 9662.6 | E16: =SUM(E6:E15) -> 13963.15 | F16: =SUM(F6:F15) -> 56762.47 | G16: =SUM(G6:G15) -> 213900 | H16: =SUM(H6:H15) -> 157137.53 | I16: =F16/G16 -> 0.26536919
A18: Fringe Benefits Rate | B18: =+'Salaries & Fringe Allocations'!Q155+'Salaries & Fringe Allocations'!Q156+'Salaries & Fringe Allocations'!Q161+'Salaries & Fringe Allocations'!Q163 -> 2590.7237 | D18: =+'Salaries & Fringe Allocations'!Q157+'Salaries & Fringe Allocations'!Q158+'Salaries & Fringe Allocations'!Q159+'Salaries & Fringe Allocations'!Q160+'Salaries & Fringe Allocations'!Q162 -> 2661.3133 | E18: =SUM(B18:D18) -> 5252.037 | F18: =E18+'Sept-2019'!F18 -> 21187.527 | G18: 68136 | H18: =G18-F18 -> 46948.473 | I18: =F18/G18 -> 0.31095937
H19: =G19-F19 -> 0
A20: TOTAL PERSONNEL (Salaries + Fringe Benefits) | B20: =B16+B18 -> 6891.2737 | C20: =C16+C18 -> 0 | D20: =D16+D18 -> 12323.913 | E20: =E16+E18 -> 19215.187 | F20: =F16+F18 -> 77949.997 | G20: =G16+G18 -> 282036 | H20: =H16+H18 -> 204086 | I20: =F20/G20 -> 0.27638315
A22: 2. Non-Personnel Operating Costs
A23: Travel | B23: =+'Oct-2019 GL'!G82 -> 271.3 | E23: =SUM(B23:D23) -> 271.3 | F23: =E23+'Sept-2019'!F23 -> 1138.88 | G23: 4000 | H23: =G23-F23 -> 2861.12 | I23: =F23/G23 -> 0.28472
A24: Supplies | B24: =+'Oct-2019 GL'!G88 -> 254 | D24: =+'Oct-2019 GL'!G85 -> 30.5 | E24: =SUM(B24:D24) -> 284.5 | F24: =E24+'Sept-2019'!F24 -> 755.99 | G24: 7000 | H24: =G24-F24 -> 6244.01 | I24: =F24/G24 -> 0.10799857
A25: Staff Development | E25: =SUM(B25:D25) -> 0 | F25: =E25+'Sept-2019'!F25 -> 0 | G25: 2000 | H25: =G25-F25 -> 2000 | I25: =F25/G25 -> 0
A26: Contractual/Consultants | B26: =+'Oct-2019 GL'!G95 -> 683 | E26: =SUM(B26:D26) -> 683 | F26: =E26+'Sept-2019'!F26 -> 2146.69 | G26: 13200 | H26: =G26-F26 -> 11053.31 | I26: =F26/G26 -> 0.16262803
A27: Occupancy | B27: =+'Oct-2019 GL'!G117 -> 766 | D27: =+'Oct-2019 GL'!G100 -> 648 | E27: =SUM(B27:D27) -> 1414 | F27: =E27+'Sept-2019'!F27 -> 4193.27 | G27: 12000 | H27: =G27-F27 -> 7806.73 | I27: =F27/G27 -> 0.34943917
A28: Audit (100% Admin) | E28: =SUM(B28:D28) -> 0 | F28: =E28+'Sept-2019'!F28 -> 1130.29 | G28: 6000 | H28: =G28-F28 -> 4869.71 | I28: =F28/G28 -> 0.18838167
A29: Marketing and Outreach | E29: =SUM(B29:D29) -> 0 | F29: =E29+'Sept-2019'!F29 -> 0 | G29: 570 | H29: =G29-F29 -> 570 | I29: =F29/G29 -> 0
A30: Rental Equipment | B30: =+'Oct-2019 GL'!G124 -> 274 | E30: =SUM(B30:D30) -> 274 | F30: =E30+'Sept-2019'!F30 -> 1283.95 | G30: 6475 | H30: =G30-F30 -> 5191.05 | I30: =F30/G30 -> 0.19829344
A31: Payroll fees | C31: =+'Oct-2019 GL'!G25 -> 900.49 | E31: =SUM(B31:D31) -> 900.49 | F31: =E31+'Sept-2019'!F31 -> 3651.96 | G31: 13000 | H31: =G31-F31 -> 9348.04 | I31: =F31/G31 -> 0.28092
A32: Infrastructure Costs | E32: =SUM(B32:D32) -> 0 | F32: =E32+'Sept-2019'!F32 -> 0 | G32: 1500 | H32: =G32-F32 -> 1500 | I32: =F32/G32 -> 0
A33: Other Operating costs | B33: =+'Oct-2019 GL'!G137 -> 107 | E33: =SUM(B33:D33) -> 107 | F33: =E33+'Sept-2019'!F33 -> 1361.82 | G33: 3000.7 | H33: =G33-F33 -> 1638.88 | I33: =F33/G33 -> 0.45383411
A34: Communications | B34: =+'Oct-2019 GL'!G152 -> 355.01 | E34: =SUM(B34:D34) -> 355.01 | F34: =E34+'Sept-2019'!F34 -> 1036.02 | G34: 3000 | H34: =G34-F34 -> 1963.98 | I34: =F34/G34 -> 0.34534
A35: Insurance | B35: =+'Oct-2019 GL'!G157 -> 443 | E35: =SUM(B35:D35) -> 443 | F35: =E35+'Sept-2019'!F35 -> 1757.72 | G35: 4000 | H35: =G35-F35 -> 2242.28 | I35: =F35/G35 -> 0.43943
A36: Postage | B36: =+'Oct-2019 GL'!G162 -> 34 | E36: =SUM(B36:D36) -> 34 | F36: =E36+'Sept-2019'!F36 -> 72 | G36: 1000 | H36: =G36-F36 -> 928 | I36: =F36/G36 -> 0.072
A37: Total NPOC | B37: =SUM(B23:B36) -> 3187.31 | C37: =SUM(C23:C36) -> 900.49 | D37: =SUM(D23:D36) -> 678.5 | E37: =SUM(E23:E36) -> 4766.3 | F37: =SUM(F23:F36) -> 18528.59 | G37: =SUM(G23:G36) -> 76745.7 | H37: =SUM(H23:H36) -> 58217.11 | I37: =F37/G37 -> 0.24142838
A40: 3. Participant Costs
A41: Participant Wages | C41: =+'Oct-2019 GL'!G10 -> 96842 | E41: =SUM(B41:D41) -> 96842 | F41: =E41+'Sept-2019'!F41 -> 340593.48 | G41: 1452829.2 | H41: =G41-F41-F42 -> 1110075.1 | I41: =F41/G41 -> 0.23443463
A42: Reimbursable Participant Wage(Paid by Affiliate) | C42: =+'Oct-2019 GL'!G13 -> 164.11 | E42: =SUM(B42:D42) -> 164.11 | F42: =+E42+'Sept-2019'!F42 -> 2160.63 | I42: 0
A43: Participant Specialized Training Wage | E43: =SUM(B43:D43) -> 0 | F43: =E43+'Sept-2019'!F43 -> 0 | G43: 12820 | H43: =G43-F43 -> 12820 | I43: =F43/G43 -> 0
A44: Participant FICA and other taxes | C44: =+'Oct-2019 GL'!G18 -> 7408.45 | E44: =SUM(B44:D44) -> 7408.45 | F44: =E44+'Sept-2019'!F44 -> 26124.72 | G44: 111141.44 | H44: =G44-F44 -> 85016.72 | I44: =F44/G44 -> 0.23505832
A45: Workers compensation | C45: =+'Oct-2019 GL'!G21 -> 2898.28 | E45: =SUM(B45:D45) -> 2898.28 | F45: =E45+'Sept-2019'!F45 -> 10556.48 | G45: 22373.57 | H45: =G45-F45 -> 11817.09 | I45: =F45/G45 -> 0.47182814
A46: Support Services | E46: =SUM(B46:D46) -> 0 | F46: =E46+'Sept-2019'!F46 -> 0 | G46: 8500 | H46: =G46-F46 -> 8500 | I46: =F46/G46 -> 0
A47: Specialized Training vendor | E47: =SUM(B47:D47) -> 0 | F47: =E47+'Sept-2019'!F47 -> 0 | G47: 29630 | H47: =G47-F47 -> 29630 | I47: =F47/G47 -> 0
A48: Total Participant Costs | B48: =SUM(B41:B47) -> 0 | C48: =SUM(C41:C47) -> 107312.84 | D48: =SUM(D41:D47) -> 0 | E48: =SUM(E41:E47) -> 107312.84 | F48: =SUM(F41:F47) -> 379435.31 | G48: =SUM(G41:G47) -> 1637294.2 | H48: =SUM(H41:H47) -> 1257858.9 | I48: =F48/G48 -> 0.23174534
L49: =60*12 -> 720
A50: 4. Indirect ('%) | B50: 0 | E50: =B50 -> 0 | F50: =E50+'Sept-2019'!F50 -> 0 | G50: 17532.59 | H50: =G50-F50 -> 17532.59 | I50: =F50/G50 -> 0
A52: 5.Total Federal Expenses | B52: =B20+B37+B48+B50 -> 10078.584 | C52: =C20+C37+C48 -> 108213.33 | D52: =D20+D37+D48 -> 13002.413 | E52: =E37+E20+E48+E50 -> 131294.33 | F52: =F37+F20+F48+F50 -> 475913.9 | G52: =G37+G20+G48+G50 -> 2013608.5 | H52: =H37+H20+H48+H50 -> 1537694.6 | I52: =F52/G52 -> 0.23634877
A54: 6. Non Federal Match | E54: =+'Oct-2019 GL'!G166 -> 6922.5 | F54: =E54+'Sept-2019'!F54 -> 14414.64 | G54: 242467.32 | H54: =G54-F54 -> 228052.68 | I54: =F54/G54 -> 0.059449826
A56: 7. Total Expenses | B56: =B52+B54 -> 10078.584 | C56: =C52+C54 -> 108213.33 | D56: =D52+D54 -> 13002.413 | E56: =E52+E54 -> 138216.83 | F56: =F52+F54 -> 490328.54 | G56: =G52+G54 -> 2256075.9 | H56: =H52+H54 -> 1765747.3 | I56: =F56/G56 -> 0.2173369
F57: AFFILIATES- ENTER NOTES TO THIS INVOICE HERE
A58: 8. Total Reimbursable expenses | E58: =+E20+E37-E31+E42+E45+E46+E47+E50 -> 26143.387
A60: FOR NUL USE ONLY
A62: TOTAL INVOICE SUBMITTED | E62: =E58 -> 26143.387
A65: COSTS DISALLOWED
A68: OTHER ADJUSTMENTS
A71: CASH DUE TO/DUE FROM AFFILIATE
A73: SIGNATURE AND DATE:
A77: R. Greg Ward | B77: 43776 | F77: Vivian Cox Fraser | H77: 43776
A78: Fiscal Manager | B78: Date | F78: Affiliate CEO | H78: Date
A81: Gwendolyn Morris | B81: 43776
A82: Project Director | B82: Date | F82: Vice President, Workforce Development (NUL) | H82: Date

Sheet Oct-2019 GL
A1: URBAN LEAGUE OF ESSEX COUNTY
A2: 451 USJP Program Transaction Detail by Account
A3: October 2019
B5: Date | C5: Transaction Type | D5: Num | E5: Name | F5: Memo/Description | G5: Amount | H5: Check #
A6: 7100 Participant Salaries & Wages
A7: 7112 Participant Wages - USJP
B8: 10/07/2019 | C8: Journal Entry | D8: 19-432 | F8: Wages - 10/07 | G8: 50385
B9: 10/21/2019 | C9: Journal Entry | D9: 19-433 | F9: Wages - 10/21 | G9: 46457
A10: Total for 7112 Participant Wages - USJP | G10: =SUM(G8:G9) -> 96842
A11: 7112.1 USJP Manual Checks
B12: 10/25/2019 | C12: Check | D12: 12628 | E12: Michael Johnson | F12: Did not receive check for 9/12/19 - 9/25/19 | G12: 164.11 | H12: 12628
A13: Total for 7112.1 USJP Manual Checks | G13: =SUM(G12) -> 164.11
A14: Total for 7112 Participant Wages - USJP with subs | G14: =+G13+G10 -> 97006.11
A15: 7120 Payroll Taxes
B16: 10/07/2019 | C16: Journal Entry | D16: 19-432 | F16: Employer Liability | G16: 3854.47
B17: 10/21/2019 | C17: Journal Entry | D17: 19-433 | F17: Employer Liability | G17: 3553.98
A18: Total for 7120 Payroll Taxes | G18: =SUM(G16:G17) -> 7408.45
A19: 7130 Worker's Compensation - USJP
B20: 43738 | C20: Journal Entry | D20: 192 | F20: Workers Comp Alloc | G20: 2898.28
A21: Total for 7130 Worker's Compensation - USJP | G21: =SUM(G20) -> 2898.28
A22: 7132 Payroll Expenses - Fees
B23: 10/07/2019 | C23: Journal Entry | D23: 19-432 | F23: USJP Payroll Fee | G23: 498.62
B24: 10/21/2019 | C24: Journal Entry | D24: 19-433 | F24: USJP Payroll Fee | G24: 401.87
A25: Total for 7132 Payroll Expenses - Fees | G25: =SUM(G23:G24) -> 900.49
A26: Total for 7100 Participant Salaries & Wages | G26: =+G14+G18+G21+G25 -> 108213.33
A27: 7200 Salaries & Related Expenses
A28: 7220 Salaries & Wages
A29: 7222 Staff
B30: 10/31/2019 | C30: Journal Entry | D30: 19-437 | F30: Salary Allocation - October | G30: 13963.15
A31: Total for 7222 Staff | G31: 13963.15
A32: Total for 7220 Salaries & Wages | G32: 13963.15
A33: 7240 Employee Benefits
A35: 7241 Health Insurance
B36: 10/11/2019 | C36: Bill | D36: 292534359 | E36: Horizon Blue Cross Blue Shield of NJ | F36: To record Horizon Exp. Billing Period10/15/19 - 11/15/19 | G36: 3688.1 | H36: 12569
A37: Total for 7241 Health Insurance | G37: 3688.1
A39: 7242 Life and Dental Insurance
B40: 10/01/2019 | C40: Bill | D40: 10.01.19PL | E40: Principal Financial Group | F40: Life, Dental & AD&D | G40: 179.49 | H40: 12527
A41: Total for 7242 Life and Dental Insurance | G41: 179.49
A42: 7244 Employee Contrib - Health
B43: 43768 | C43: Journal Entry | D43: 154 | F43: Employee Medical Contrib | G43: -454.87
A44: Total for 7244 Employee Contrib - Health | G44: =SUM(G43) -> -454.87
A45: 7247 Emp-ee Contrib -Dental
B46: 43768 | C46: Journal Entry | D46: 155 | F46: Employee Dental Contrib | G46: -13.57
A47: Total for 7247 Emp-ee Contrib -Dental | G47: =SUM(G46) -> -13.57
A49: Total for 7240 Employee Benefits | G49: =+G37+G41+G44+G47 -> 3399.15
A51: Total for 7200 Salaries & Related Expenses | G51: =+G32+G49 -> 17362.3
A53: 7245 Worker's Compensation Insurance
A54: 7248 Allocated W Comp
B55: 43769 | C55: Journal Entry | D55: 261 | F55: Workers Comp Alloc | G55: 417.89
A56: Total for 7245 Worker's Compensation Insurance | G56: =SUM(G55) -> 417.89
A57: EMPLOYER TAXES
A58: 7251 Social Security
B59: 43769 | C59: Journal Entry | D59: 246 | F59: Fica | G59: 851
A60: Total for 7251 Social Security | G60: =SUM(G59) -> 851
A61: 7252 Medicare
B62: 43769 | C62: Journal Entry | D62: 248 | F62: Medi Alloc | G62: 199
A63: Total for 7252 Medicare | G63: =SUM(G62) -> 199
A64: 7253 Unemployment
B65: 43769 | C65: Journal Entry | D65: 249 | F65: SUI Alloc | G65: 204
A66: Total for 7253 Unemployment | G66: =SUM(G65) -> 204
A67: 7254 Disability
B68: 43769 | C68: Journal Entry | D68: 250 | F68: Disability Alloc | G68: 40
A69: Total for 7254 Disability | G69: =SUM(G68) -> 40
A70: TOTAL EMPLOYER TAXES | G70: =+G60+G63+G66+G69 -> 1294
A72: 7260 Payroll Service Fees
B73: 43769 | C73: Journal Entry | D73: 251 | F73: Payroll Fees | G73: 141
A74: Total for 7260 Payroll Service Fees | G74: =SUM(G73) -> 141
A76: Total for 7200 Salaries & Fringe | G76: =+G51+G70+G74+G56 -> 19215.19
A77: 8300 Travel & Meetings Expenses
A78: 8310 Transportation & Parking
B79: 10/01/2019 | C79: Bill | D79: 10.01.19GM3 | E79: Gwendolyn Morris | F79: Travel Reimbursement - Mileage - 09/11/19 - 9/20/19 | G79: 133.06 | H79: 12546
B80: 10/01/2019 | C80: Bill | D80: 10.19.19AJ | E80: Armanda Johnson | F80: Mileage From Newark To Morristown 09/16/19 - 09/27/19 | G80: 108 | H80: 12548
B81: 10/01/2019 | C81: Bill | D81: 10.11.19MT | E81: Mary Tanner | F81: Mileage Reimbursement 9/9/19 & 9/23/19 | G81: 30.24 | H81: 12547
A82: Total for 8310 Transportation & Parking | G82: =SUM(G79:G81) -> 271.3
A83: 8110 Supplies
B84: 10/01/2019 | C84: Bill | D84: 10.01.19GM2 | E84: Gwendolyn Morris | F84: Security - Uniform T- Shirt & Hat | G84: 30.5 | H84: 12546
A85: Total for 8110 Supplies | G85: =SUM(G84) -> 30.5
A86: 8112 Alloc Supplies
B87: 43769 | C87: Journal Entry | D87: 185 | F87: Supplies Alloc | G87: 254
A88: Total for 8112 Alloc Supplies | G88: =SUM(G87) -> 254
A90: Total for 8110 Supplies | G90: =+G84+G88 -> 284.5
A92: CONTRACTUAL CONSULTANTS
A93: 7521 Allocated Acctg and Audit
B94: 43769 | C94: Journal Entry | D94: 253 | F94: Acctg Fee Alloc | G94: 683
A95: Total for 7520 Accounting Fees | G95: =SUM(G94) -> 683
A97: OCCUPANCY
A98: 8205 Rent, Parking, Other Occupancy
B99: 10/01/2019 | C99: Bill | D99: 1985 | E99: Center for Transformative Work | F99: USJP - Rent Expense October r 2019 | G99: 648 | H99: 12535
A100: Total for OCCUPANCY - PROGRAM TOTAL 8205 Rent | G100: =SUM(G99) -> 648
A105: 8210 Utilities
A106: 8210.5 Allocated Utilities
B107: 43769 | C107: Journal Entry | D107: 260 | F107: Utilities | G107: 145
A108: Total for 8210 Utilities | G108: =SUM(G107) -> 145
A109: 8230 Building Repair & Maintenance
A110: 8239 Alloc Repairs and Maint
B111: 43769 | C111: Journal Entry | D111: 257 | F111: Repairs | G111: 130
A112: Total for 8230 Building Repair & Maintenance | G112: =SUM(G111) -> 130
A113: Allocated Mortgage Int
B114: 43769 | C114: Journal Entry | D114: 257 | F114: Mortgage | G114: 491
G115: =SUM(G114) -> 491
...

Sheet Oct-FR
A1: National Urban League Financial Report
A2: 1. Funding Agency- National Urban League | I2: 2. Federal Grant Name - Urban Seniors Jobs Program CFDA 17.235 | N2: PY 19
A3: 3. Recipient Organization (Name and complete address including Zip code)
M4: 4. Final Report (mark X) Yes No | N4: 5. Basis of Reporting □ Accrual
A5: 6. Project/Grant Period From: July 1-2019 | H5: To: June 31, 2020 | M5: 7. Reporting Period End Date 10/31/2019
A6: 8. Transactions | M6: Cumulative
A7: Federal Cash:
A8: a. Cash Receipts
A9: b. Cash Disbursements | M9: =M8 -> 0
A10: c. Cash on Hand (line a minus b) | M10: =M8-M9 -> 0
A11: Federal Expenditures and Unobligated Balance:
A12: d. Approved Budget
A13: e. Federal Share of Expenditures -Program Costs | M13: =M9 -> 0
A14: f. Federal Share of Expenditures -Administrative Costs | M14: 0
A15: g. Federal Share of Unliquidated Obligations ( ACCRUALS) | M15: 0
A16: h. Total Federal Obligations (sum of lines e and g) | M16: =M13+M14+M15 -> 0
A17: i. Unobligated Balance of Federal Funds (line d minus h) | M17: =M12-M16 -> 0
A18: Recipient Share: Cost Sharing/ Matching/ In-Kind Costs
A19: j. Total Match and Inkind Required if Applicable | M19: 0
A20: k. Total Receipient share reported if Applicable | M20: 0
A21: l. Remaining Recipient Share to Be Provided (line j minus k) | M21: =M19-M20 -> 0
A22: Program Income:
A23: m. Total Program Income Earned if applicable | M23: 0
A24: n. Program Income Expended in Accordance with the Addition Method | M24: 0
A25: o. Unexpended Program Income (line m minus line n) | M25: =M23-M24 -> 0
A26: 9. Remarks: (Attach any explanations deemed necessary or information required by Federal sponsoring agency in compliance with governing legislation.)
A28: 10. Indirect Expenditures
A29: a. Type of Rate | C29: b. Rate | D29: c. Rate Approval Date | G29: d. Period From (MM/DD/YYYY) | I29: Period To (MM/DD/YYYY) | J29: e. Base | M29: f. Amount Charged | N29: g. Federal Share
A32: 11. Certification: By signing this report, I certify to the best of my knowledge and belief that the report is true, complete, and accurate, and the expenditures, disbursements and cash receipts are for the purposes and objectives set forth in the terms and conditions of the Federal award. I am aware that any false, fictitious, or fraudulent information, or the omission of any material fact, may subject me to criminal, civil or administrative penalties for fraud, false statements, false claims or otherwise. (U.S. Code Title 18, Section 1001 and Title 31, Sections 3729–3730 and 3801–3812).
A33: a. Typed or Printed Name and Title of Authorized Certifying Official | M33: c. Telephone (Area code, number, and extension)
M34: d. Email Address
A35: b. Signature of Authorized Certifying Official | M35: e. Date Report Submitted (MM/DD/YYYY)

Sheet Nov-2019
A1: Urban Seniors Jobs Program PY 19 | G1: 43770 | I1: %
A2: Urban League of Essex County | E2: Invoice # 5 | I2: Spent
A3: 1. PERSONNEL | E3: TOTAL
C4: ENROLLEE | D4: OPC | E4: MONTHLY | F4: CUMULATIVE | G4: TOTAL | H4: BUDGET
A5: POSITION TITLE | B5: ADMIN | C5: WAGES & FB | D5: PROGRAM | E5: AMOUNT | F5: EXPENSES | G5: BUDGET | H5: REMAINING
A6: COO Patricia Sermon | B6: =+'Salaries & Fringe Allocations'!F208 -> 1892.31 | E6: =SUM(B6:D6) -> 1892.31 | F6: =E6+'Oct-2019'!F6 -> 6623.08 | G6: 16400 | H6: =G6-F6 -> 9776.92 | I6: =F6/G6 -> 0.40384634
A7: Director Gwendolyn Morris | B7: =+'Salaries & Fringe Allocations'!F209 -> 3107.14 | D7: =+'Salaries & Fringe Allocations'!F210 -> 4392.86 | E7: =SUM(B7:D7) -> 7500 | F7: =E7+'Oct-2019'!F7 -> 26250 | G7: 66000 | H7: =G7-F7 -> 39750 | I7: =F7/G7 -> 0.39772727
A8: Prog Site Coordinator (Essex) Rahmel Leake | D8: =+'Salaries & Fringe Allocations'!F211 -> 4615.41 | E8: =SUM(B8:D8) -> 4615.41 | F8: =E8+'Oct-2019'!F8 -> 14615.47 | G8: 40000 | H8: =G8-F8 -> 25384.53 | I8: =F8/G8 -> 0.36538675
A9: Prog Site Coordinator (Passaic) Irene Cerna | D9: =+'Salaries & Fringe Allocations'!F212 -> 3461.55 | E9: =SUM(B9:D9) -> 3461.55 | F9: =E9+'Oct-2019'!F9 -> 11423.23 | G9: 30000 | H9: =G9-F9 -> 18576.77 | I9: =F9/G9 -> 0.38077433
A10: Site Coordinator (Morris) Armanda Johnson | D10: =+'Salaries & Fringe Allocations'!F213 -> 2163 | E10: =SUM(B10:D10) -> 2163 | F10: =E10+'Oct-2019'!F10 -> 7959.84 | G10: 21500 | H10: =G10-F10 -> 13540.16 | I10: =F10/G10 -> 0.37022512
A11: Program Assistant Joanna Martinez | B11: =+'Salaries & Fringe Allocations'!F214 -> 1291.22 | D11: =+'Salaries & Fringe Allocations'!F215 -> 2362.65 | E11: =SUM(B11:D11) -> 3653.87 | F11: =E11+'Oct-2019'!F11 -> 10638.54 | G11: 36000 | H11: =G11-F11 -> 25361.46 | I11: =F11/G11 -> 0.295515
A12: Staff Accountant - Gregory Ward | B12: =+'Salaries & Fringe Allocations'!F216 -> 1057.69 | E12: =SUM(B12:D12) -> 1057.69 | F12: =E12+'Oct-2019'!F12 -> 3596.14 | G12: 4000 | H12: =G12-F12 -> 403.86 | I12: =F12/G12 -> 0.899035
A16: Total Salaries | B16: =SUM(B6:B15) -> 7348.36 | C16: =SUM(C6:C15) -> 0 | D16: =SUM(D6:D15) -> 16995.47 | E16: =SUM(E6:E15) -> 24343.83 | F16: =SUM(F6:F15) -> 81106.3 | G16: =SUM(G6:G15) -> 213900 | H16: =SUM(H6:H15) -> 132793.7 | I16: =F16/G16 -> 0.37917859
A18: Fringe Benefits Rate | B18: =+'Salaries & Fringe Allocations'!Q208+'Salaries & Fringe Allocations'!Q209+'Salaries & Fringe Allocations'!Q214+'Salaries & Fringe Allocations'!Q216 -> 1718.5766 | D18: =+'Salaries & Fringe Allocations'!Q210+'Salaries & Fringe Allocations'!Q211+'Salaries & Fringe Allocations'!Q212+'Salaries & Fringe Allocations'!Q213+'Salaries & Fringe Allocations'!Q215 -> 4161.2976 | E18: =SUM(B18:D18) -> 5879.8742 | F18: =E18+'Oct-2019'!F18 -> 27067.402 | G18: 68136 | H18: =G18-F18 -> 41068.598 | I18: =F18/G18 -> 0.39725551
H19: =G19-F19 -> 0
A20: TOTAL PERSONNEL (Salaries + Fringe Benefits) | B20: =B16+B18 -> 9066.9366 | C20: =C16+C18 -> 0 | D20: =D16+D18 -> 21156.768 | E20: =E16+E18 -> 30223.704 | F20: =F16+F18 -> 108173.7 | G20: =G16+G18 -> 282036 | H20: =H16+H18 -> 173862.3 | I20: =F20/G20 -> 0.38354572
A22: 2. Non-Personnel Operating Costs
A23: Travel | D23: =+'Nov-19 GL'!G84 -> 396.02 | E23: =SUM(B23:D23) -> 396.02 | F23: =E23+'Oct-2019'!F23 -> 1534.9 | G23: 4000 | H23: =G23-F23 -> 2465.1 | I23: =F23/G23 -> 0.383725
A24: Supplies | B24: =+'Nov-19 GL'!G94 -> 259 | D24: =+'Nov-19 GL'!G91 -> 891.21 | E24: =SUM(B24:D24) -> 1150.21 | F24: =E24+'Oct-2019'!F24 -> 1906.2 | G24: 7000 | H24: =G24-F24 -> 5093.8 | I24: =F24/G24 -> 0.27231429
A25: Staff Development | E25: =SUM(B25:D25) -> 0 | F25: =E25+'Oct-2019'!F25 -> 0 | G25: 2000 | H25: =G25-F25 -> 2000 | I25: =F25/G25 -> 0
A26: Contractual/Consultants | B26: =+'Nov-19 GL'!G102 -> 597 | E26: =SUM(B26:D26) -> 597 | F26: =E26+'Oct-2019'!F26 -> 2743.69 | G26: 13200 | H26: =G26-F26 -> 10456.31 | I26: =F26/G26 -> 0.2078553
A27: Occupancy | B27: =+'Nov-19 GL'!G128 -> 539 | D27: =+'Nov-19 GL'!G112 -> 648 | E27: =SUM(B27:D27) -> 1187 | F27: =E27+'Oct-2019'!F27 -> 5380.27 | G27: 12000 | H27: =G27-F27 -> 6619.73 | I27: =F27/G27 -> 0.44835583
A28: Audit (100% Admin) | B28: =+'Nov-19 GL'!G107 -> 770 | E28: =SUM(B28:D28) -> 770 | F28: =E28+'Oct-2019'!F28 -> 1900.29 | G28: 6000 | H28: =G28-F28 -> 4099.71 | I28: =F28/G28 -> 0.316715
A29: Marketing and Outreach | E29: =SUM(B29:D29) -> 0 | F29: =E29+'Oct-2019'!F29 -> 0 | G29: 570 | H29: =G29-F29 -> 570 | I29: =F29/G29 -> 0
A30: Rental Equipment | B30: =+'Nov-19 GL'!G135 -> 338 | E30: =SUM(B30:D30) -> 338 | F30: =E30+'Oct-2019'!F30 -> 1621.95 | G30: 6475 | H30: =G30-F30 -> 4853.05 | I30: =F30/G30 -> 0.25049421
A31: Payroll fees | B31: =+'Nov-19 GL'!G22 -> 825.81 | E31: =SUM(B31:D31) -> 825.81 | F31: =E31+'Oct-2019'!F31 -> 4477.77 | G31: 13000 | H31: =G31-F31 -> 8522.23 | I31: =F31/G31 -> 0.34444385
A32: Infrastructure Costs | E32: =SUM(B32:D32) -> 0 | F32: =E32+'Oct-2019'!F32 -> 0 | G32: 1500 | H32: =G32-F32 -> 1500 | I32: =F32/G32 -> 0
A33: Other Operating costs | B33: =+'Nov-19 GL'!G149 -> 426 | E33: =SUM(B33:D33) -> 426 | F33: =E33+'Oct-2019'!F33 -> 1787.82 | G33: 3000.7 | H33: =G33-F33 -> 1212.88 | I33: =F33/G33 -> 0.59580098
A34: Communications | B34: =+'Nov-19 GL'!G162 -> 261.01 | E34: =SUM(B34:D34) -> 261.01 | F34: =E34+'Oct-2019'!F34 -> 1297.03 | G34: 3000 | H34: =G34-F34 -> 1702.97 | I34: =F34/G34 -> 0.43234333
A35: Insurance | B35: =+'Nov-19 GL'!G167 -> 597 | E35: =SUM(B35:D35) -> 597 | F35: =E35+'Oct-2019'!F35 -> 2354.72 | G35: 4000 | H35: =G35-F35 -> 1645.28 | I35: =F35/G35 -> 0.58868
A36: Postage | E36: =SUM(B36:D36) -> 0 | F36: =E36+'Oct-2019'!F36 -> 72 | G36: 1000 | H36: =G36-F36 -> 928 | I36: =F36/G36 -> 0.072
A37: Total NPOC | B37: =SUM(B23:B36) -> 4612.82 | C37: =SUM(C23:C36) -> 0 | D37: =SUM(D23:D36) -> 1935.23 | E37: =SUM(E23:E36) -> 6548.05 | F37: =SUM(F23:F36) -> 25076.64 | G37: =SUM(G23:G36) -> 76745.7 | H37: =SUM(H23:H36) -> 51669.06 | I37: =F37/G37 -> 0.32674977
A40: 3. Participant Costs
A41: Participant Wages | C41: =+'Nov-19 GL'!G11 -> 93666.89 | E41: =SUM(B41:D41) -> 93666.89 | F41: =E41+'Oct-2019'!F41 -> 434260.37 | G41: 1452829.2 | H41: =G41-F41-F42 -> 1016408.2 | I41: =F41/G41 -> 0.29890668
A42: Reimbursable Participant Wage(Paid by Affiliate) | E42: =SUM(B42:D42) -> 0 | F42: =+E42+'Oct-2019'!F42 -> 2160.63
A43: Participant Specialized Training Wage | E43: =SUM(B43:D43) -> 0 | F43: =E43+'Oct-2019'!F43 -> 0 | G43: 12820 | H43: =G43-F43 -> 12820 | I43: =F43/G43 -> 0
A44: Participant FICA and other taxes | C44: =+'Nov-19 GL'!G15 -> 4818.66 | E44: =SUM(B44:D44) -> 4818.66 | F44: =E44+'Oct-2019'!F44 -> 30943.38 | G44: 111141.44 | H44: =G44-F44 -> 80198.06 | I44: =F44/G44 -> 0.27841442
A45: Workers compensation | C45: =+'Nov-19 GL'!G18 -> 2294 | E45: =SUM(B45:D45) -> 2294 | F45: =E45+'Oct-2019'!F45 -> 12850.48 | G45: 22373.57 | H45: =G45-F45 -> 9523.09 | I45: =F45/G45 -> 0.57435984
A46: Support Services | E46: =SUM(B46:D46) -> 0 | F46: =E46+'Oct-2019'!F46 -> 0 | G46: 8500 | H46: =G46-F46 -> 8500 | I46: =F46/G46 -> 0
A47: Specialized Training vendor | E47: =SUM(B47:D47) -> 0 | F47: =E47+'Oct-2019'!F47 -> 0 | G47: 29630 | H47: =G47-F47 -> 29630 | I47: =F47/G47 -> 0
A48: Total Participant Costs | B48: =SUM(B41:B47) -> 0 | C48: =SUM(C41:C47) -> 100779.55 | D48: =SUM(D41:D47) -> 0 | E48: =SUM(E41:E47) -> 100779.55 | F48: =SUM(F41:F47) -> 480214.86 | G48: =SUM(G41:G47) -> 1637294.2 | H48: =SUM(H41:H47) -> 1157079.4 | I48: =F48/G48 -> 0.29329784
A50: 4. Indirect ('%) | B50: 0 | E50: =B50 -> 0 | F50: =E50+'Oct-2019'!F50 -> 0 | G50: 17532.59 | H50: =G50-F50 -> 17532.59 | I50: =F50/G50 -> 0
A52: 5.Total Federal Expenses | B52: =B20+B37+B48+B50 -> 13679.757 | C52: =C20+C37+C48 -> 100779.55 | D52: =D20+D37+D48 -> 23091.998 | E52: =E37+E20+E48+E50 -> 137551.3 | F52: =F37+F20+F48+F50 -> 613465.2 | G52: =G37+G20+G48+G50 -> 2013608.5 | H52: =H37+H20+H48+H50 -> 1400143.3 | I52: =F52/G52 -> 0.30465961
A54: 6. Non Federal Match | E54: =29634.43-14414.64 -> 15219.79 | F54: =E54+'Oct-2019'!F54 -> 29634.43 | G54: 242467.32 | H54: =G54-F54 -> 212832.89 | I54: =F54/G54 -> 0.12222031
A56: 7. Total Expenses | B56: =B52+B54 -> 13679.757 | C56: =C52+C54 -> 100779.55 | D56: =D52+D54 -> 23091.998 | E56: =E52+E54 -> 152771.09 | F56: =F52+F54 -> 643099.63 | G56: =G52+G54 -> 2256075.9 | H56: =H52+H54 -> 1612976.2 | I56: =F56/G56 -> 0.28505231
F57: AFFILIATES- ENTER NOTES TO THIS INVOICE HERE
A58: 8. Total Reimbursable expenses | E58: =+E20+E37-E31+E42+E45+E46+E47+E50 -> 38239.944
A60: FOR NUL USE ONLY
A62: TOTAL INVOICE SUBMITTED | E62: =E58 -> 38239.944
A65: COSTS DISALLOWED
A68: OTHER ADJUSTMENTS
A71: CASH DUE TO/DUE FROM AFFILIATE
A73: SIGNATURE AND DATE:
A77: R. Greg Ward | F77: Vivian Cox Fraser | H77: 43811
A78: Fiscal Manager | B78: Date | F78: Affiliate CEO | H78: Date
A81: Gwendolyn Morris
A82: Project Director | B82: Date | F82: Vice President, Workforce Development (NUL) | H82: Date

Sheet Nov-19 GL
A1: URBAN LEAGUE OF ESSEX COUNTY
A2: 451 USJP Program Transaction Detail by Account
A3: November 2019
B5: Date | C5: Transaction Type | D5: Num | E5: Name | F5: Memo/Description | G5: Amount | H5: Check #
A7: 7100 Participant Salaries & Wages
A8: 7112 Participant Wages - USJP
B9: 11/04/2019 | C9: Journal Entry | D9: 60 | F9: Wages - 11/04/19 | G9: 46928.89
B10: 11/18/2019 | C10: Journal Entry | D10: 61 | F10: Wages - 11/18/19 | G10: 46738
A11: Total for 7112 Participant Wages - USJP | G11: =SUM(G9:G10) -> 93666.89
A12: 7120 Payroll Taxes
B13: 11/04/2019 | C13: Journal Entry | D13: 60 | F13: Employer Liability | G13: 3602.67
B14: 11/18/2019 | C14: Journal Entry | D14: 61 | F14: Employer Liability | G14: 1215.99
A15: Total for 7120 Payroll Taxes | G15: =SUM(G13:G14) -> 4818.66
A16: 7130 Worker's Compensation - USJP
B17: 11/30/2019 | C17: Journal Entry | D17: 56 | F17: Workers Comp Alloc | G17: 2294
A18: Total for 7130 Worker's Compensation - USJP | G18: =SUM(G17) -> 2294
A19: 7132 Payroll Expenses - Fees
B20: 11/04/2019 | C20: Journal Entry | D20: 60 | F20: USJP Payroll Fee | G20: 425.99
B21: 11/18/2019 | C21: Journal Entry | D21: 61 | F21: USJP Payroll Fee | G21: 399.82
A22: Total for 7132 Payroll Expenses - Fees | G22: =SUM(G20:G21) -> 825.81
A23: Total for 7100 Participant Salaries & Wages | G23: =+G11+G15+G18+G22 -> 101605.36
A24: 7200 Salaries & Related Expenses
A25: 7220 Salaries & Wages
A26: 7222 Staff
B27: 11/30/2019 | C27: Journal Entry | D27: 39 | F27: Salary Allocation - November | G27: 24343
A28: Total for 7222 Staff | G28: =SUM(G27) -> 24343
A29: Total for 7220 Salaries & Wages | G29: =SUM(G28) -> 24343
A30: 7240 Employee Benefits
A31: 7241 Health Insurance
B32: 11/01/2019 | C32: Bill | D32: 292676700 | E32: Horizon Blue Cross Blue Shield of NJ | F32: To record Horizon Exp. Billing Period 11/15/19 - 12/15/19 | G32: 3670.26 | H32: 12658
A33: Total for 7241 Health Insurance | G33: =SUM(G32) -> 3670.26
A34: 7242 Life and Dental Insurance
B35: 11/01/2019 | C35: Bill | D35: 11.01.19PG | E35: Principal Financial Group | F35: Life, Dental & AD&D | G35: 557.8465 | H35: 12665
A36: Total for 7242 Life and Dental Insurance | G36: =SUM(G35) -> 557.8465
A37: 7244 Employee Contrib - Health
B38: 43799 | C38: Journal Entry | D38: 154 | F38: Employee Medical Contrib | G38: -1267.3845
A39: Total for 7244 Employee Contrib - Health | G39: =SUM(G38) -> -1267.3845
A40: 7247 Emp-ee Contrib -Dental
B41: 43799 | C41: Journal Entry | D41: 155 | F41: Employee Dental Contrib | G41: -78.8785
A42: Total for 7247 Emp-ee Contrib -Dental | G42: =SUM(G41) -> -78.8785
A44: Total for 7240 Employee Benefits | G44: =+G33+G36+G39+G42 -> 2881.8435
A46: 7245 Worker's Compensation Insurance
A47: 7248 Allocated W Comp
B48: 11/30/2019 | C48: Journal Entry | D48: 56 | F48: Workers Comp Alloc | G48: 576
A49: Total for 7245 Worker's Compensation Insurance | G49: =SUM(G48) -> 576
A51: EMPLOYER TAXES
A52: 7251 Social Security
B53: 11/30/2019 | C53: Journal Entry | D53: 53 | F53: Fica | G53: 1411
A54: Total for 7251 Social Security | G54: =SUM(G53) -> 1411
A55: 7252 Medicare
B56: 11/30/2019 | C56: Journal Entry | D56: 49 | F56: Medi Alloc | G56: 344
A57: Total for 7252 Medicare | G57: =SUM(G56) -> 344
A58: 7253 Unemployment
B59: 11/30/2019 | C59: Journal Entry | D59: 45 | F59: SUI Alloc | G59: 345
A60: Total for 7253 Unemployment | G60: =SUM(G59) -> 345
A61: 7254 Disability
B62: 11/30/2019 | C62: Journal Entry | D62: 54 | F62: Disability Alloc | G62: 68
A63: Total for 7254 Disability | G63: =SUM(G62) -> 68
A65: TOTAL EMPLOYER TAXES | G65: =+G54+G57+G60+G63 -> 2168
A66: 7260 Payroll Service Fees
B67: 11/30/2019 | C67: Journal Entry | D67: 47 | F67: Payroll Fees | G67: 254
A68: Total for 7260 Payroll Service Fees | G68: =SUM(G67) -> 254
A70: Total for 7200 Salaries & Related Expenses | G70: =+G29+G49+G44+G65+G68 -> 30222.843
A76: 8300 Travel & Meetings Expenses
A77: 8310 Transportation & Parking
B78: 11/01/2019 | C78: Bill | D78: 11.01.19MT | E78: Mary Tanner | F78: Mileage Reimbursement 10/9/19 & 10/21/19 | G78: 30.24 | H78: 12646
B79: 11/01/2019 | C79: Bill | D79: 11.01.19ICSept | E79: Irene Cerna | F79: Mileage Reimbursement - USJP Sept 2019 | G79: 28.94 | H79: 12647
B80: 11/01/2019 | C80: Bill | D80: 11.01.19Ic_Oct | E80: Irene Cerna | F80: Mileage Reimbursement - USJP Oct 2019 | G80: 28.94 | H80: 12647
B81: 11/01/2019 | C81: Bill | D81: 11063 | E81: City of Paterson Parking Authority | F81: Parking Permit for Nov. 2019 | G81: 150 | H81: 12585
B82: 11/01/2019 | C82: Bill | D82: 11.01.19AJ | E82: Armanda Johnson | F82: Mileage Reimbursement for 9/7/19, 9/14/19, 10/21/19 & 10/28/19 | G82: 43.2 | H82: 12648
B83: 11/07/2019 | C83: Bill | D83: 11.01.19GM | E83: Gwendolyn Morris | F83: Mileage Reimbursement October 2019 | G83: 114.7 | H83: 12702
A84: Total for 8300 Travel & Meetings Expenses | G84: 396.02
A86: 8110 Supplies
B87: 11/01/2019 | C87: Bill | D87: 7301479220-0-1 | E87: Staples Advantage | F87: USJP Supplies | G87: 712.92 | H87: 12813
B88: 11/01/2019 | C88: Bill | D88: 7301479220-0-2 | E88: Staples Advantage | F88: USJP Supplies | G88: 17.9 | H88: 12813
B89: 11/04/2019 | C89: Bill | D89: 7301479220-0-3 | E89: Staples Advantage | F89: USJP Supplies | G89: 31.96 | H89: 12813
B90: 11/15/2019 | C90: Bill | D90: 7302154211-0-1 | E90: Staples Advantage | F90: USJP Supplies | G90: 128.43 | H90: 12813
A91: Total for 8110 Supplies | G91: =SUM(G87:G90) -> 891.21
A92: 8112 Alloc Supplies
B93: 11/30/2019 | C93: Journal Entry | D93: 55 | F93: Supplies Alloc | G93: 259
A94: Total for 8112 Alloc Supplies | G94: =SUM(G93) -> 259
A95: Total for 8110 Supplies with subs | G95: =+G94+G91 -> 1150.21
A97: CONTRACTUAL CONSULTANTS
A98: 7520 Accounting Fees
A99: 7521 Allocated Acctg and Audit
B100: 11/30/2019 | C100: Journal Entry | D100: 41 | F100: Acctg Fee Alloc | G100: 597
A101: Total for 7520 Accounting & Audit Fees | G101: =SUM(G100:G100) -> 597
A102: Total for 7500 Contract Service Expenses | G102: =+G101 -> 597
A104: 7520 Audit Fees
A105: 7521 Allocated Audit
B106: 11/30/2019 | C106: Journal Entry | D106: 41 | F106: Audit Fee Alloc | G106: 770
A107: Total for 7520 Audit Fees | G107: =SUM(G106:G106) -> 770
A109: OCCUPANCY
A110: 8205 Rent, Parking, Other Occupancy
B111: 11/01/2019 | C111: Bill | D111: 11.01.19CTW | E111: Center for Transformative Work | F111: USJP - Rent Expense November 2019 | G111: 648 | H111: 12642
A112: Total for OCCUPANCY - PROGRAM TOTAL 8205 Rent | G112: 648
A113: 8210 Utilities
A114: 8210.5 Allocated Utilities
B115: 11/30/2019 | C115: Journal Entry | D115: 40 | F115: Utilities | G115: 162
A116: Total for 8210.5 Allocated Utilities | G116: 162
...

Sheet Nov-FR 
A1: National Urban League Financial Report
A2: 1. Funding Agency- National Urban League | I2: 2. Federal Grant Name - Urban Seniors Jobs Program CFDA 17.235 | N2: PY 19
A3: 3. Recipient Organization (Name and complete address including Zip code)
M4: 4. Final Report (mark X) Yes No | N4: 5. Basis of Reporting □ Accrual
A5: 6. Project/Grant Period From: July 1-2019 | H5: To: June 31, 2020 | M5: 7. Reporting Period End Date 11/30/2019
A6: 8. Transactions | M6: Cumulative
A7: Federal Cash:
A8: a. Cash Receipts
A9: b. Cash Disbursements | M9: =M8 -> 0
A10: c. Cash on Hand (line a minus b) | M10: =M8-M9 -> 0
A11: Federal Expenditures and Unobligated Balance:
A12: d. Approved Budget
A13: e. Federal Share of Expenditures -Program Costs | M13: =M9 -> 0
A14: f. Federal Share of Expenditures -Administrative Costs | M14: 0
A15: g. Federal Share of Unliquidated Obligations ( ACCRUALS) | M15: 0
A16: h. Total Federal Obligations (sum of lines e and g) | M16: =M13+M14+M15 -> 0
A17: i. Unobligated Balance of Federal Funds (line d minus h) | M17: =M12-M16 -> 0
A18: Recipient Share: Cost Sharing/ Matching/ In-Kind Costs
A19: j. Total Match and Inkind Required if Applicable | M19: 0
A20: k. Total Receipient share reported if Applicable | M20: 0
A21: l. Remaining Recipient Share to Be Provided (line j minus k) | M21: =M19-M20 -> 0
A22: Program Income:
A23: m. Total Program Income Earned if applicable | M23: 0
A24: n. Program Income Expended in Accordance with the Addition Method | M24: 0
A25: o. Unexpended Program Income (line m minus line n) | M25: =M23-M24 -> 0
A26: 9. Remarks: (Attach any explanations deemed necessary or information required by Federal sponsoring agency in compliance with governing legislation.)
A28: 10. Indirect Expenditures
A29: a. Type of Rate | C29: b. Rate | D29: c. Rate Approval Date | G29: d. Period From (MM/DD/YYYY) | I29: Period To (MM/DD/YYYY) | J29: e. Base | M29: f. Amount Charged | N29: g. Federal Share
A32: 11. Certification: By signing this report, I certify to the best of my knowledge and belief that the report is true, complete, and accurate, and the expenditures, disbursements and cash receipts are for the purposes and objectives set forth in the terms and conditions of the Federal award. I am aware that any false, fictitious, or fraudulent information, or the omission of any material fact, may subject me to criminal, civil or administrative penalties for fraud, false statements, false claims or otherwise. (U.S. Code Title 18, Section 1001 and Title 31, Sections 3729–3730 and 3801–3812).
A33: a. Typed or Printed Name and Title of Authorized Certifying Official | M33: c. Telephone (Area code, number, and extension)
M34: d. Email Address
A35: b. Signature of Authorized Certifying Official | M35: e. Date Report Submitted (MM/DD/YYYY)

Sheet Dec-2019
A1: Urban Seniors Jobs Program PY 19 | G1: 43800 | I1: %
A2: Urban League of Essex County | E2: Invoice # 6 | I2: Spent
A3: 1. PERSONNEL | E3: TOTAL
C4: ENROLLEE | D4: OPC | E4: MONTHLY | F4: CUMULATIVE | G4: TOTAL | H4: BUDGET
A5: POSITION TITLE | B5: ADMIN | C5: WAGES & FB | D5: PROGRAM | E5: AMOUNT | F5: EXPENSES | G5: BUDGET | H5: REMAINING
A6: COO Patricia Sermon | B6: =+'Salaries & Fringe Allocations'!F249 -> 1261.54 | E6: =SUM(B6:D6) -> 1261.54 | F6: =E6+'Nov-2019'!F6 -> 7884.62 | G6: 16400 | H6: =G6-F6 -> 8515.38 | I6: =F6/G6 -> 0.48076951
A7: Director Gwendolyn Morris | B7: =+'Salaries & Fringe Allocations'!F250 -> 2071.43 | D7: =+'Salaries & Fringe Allocations'!F251 -> 2928.57 | E7: =SUM(B7:D7) -> 5000 | F7: =E7+'Nov-2019'!F7 -> 31250 | G7: 66000 | H7: =G7-F7 -> 34750 | I7: =F7/G7 -> 0.47348485
A8: Prog Site Coordinator (Essex) Rahmel Leake | D8: =+'Salaries & Fringe Allocations'!F252 -> 3076.94 | E8: =SUM(B8:D8) -> 3076.94 | F8: =E8+'Nov-2019'!F8 -> 17692.41 | G8: 40000 | H8: =G8-F8 -> 22307.59 | I8: =F8/G8 -> 0.44231025
A9: Prog Site Coordinator (Passaic) Irene Cerna | D9: =+'Salaries & Fringe Allocations'!F253 -> 2307.7 | E9: =SUM(B9:D9) -> 2307.7 | F9: =E9+'Nov-2019'!F9 -> 13730.93 | G9: 30000 | H9: =G9-F9 -> 16269.07 | I9: =F9/G9 -> 0.45769767
A10: Site Coordinator (Morris) Armanda Johnson | D10: =+'Salaries & Fringe Allocations'!F254 -> 1355.48 | E10: =SUM(B10:D10) -> 1355.48 | F10: =E10+'Nov-2019'!F10 -> 9315.32 | G10: 21500 | H10: =G10-F10 -> 12184.68 | I10: =F10/G10 -> 0.4332707
A11: Program Assistant Joanna Martinez | B11: =+'Salaries & Fringe Allocations'!F255 -> 1032.97 | D11: =+'Salaries & Fringe Allocations'!F256 -> 1890.12 | E11: =SUM(B11:D11) -> 2923.09 | F11: =E11+'Nov-2019'!F11 -> 13561.63 | G11: 36000 | H11: =G11-F11 -> 22438.37 | I11: =F11/G11 -> 0.37671194
A12: Staff Accountant - Gregory Ward | B12: =+'Salaries & Fringe Allocations'!F257 -> 846.15 | E12: =SUM(B12:D12) -> 846.15 | F12: =E12+'Nov-2019'!F12 -> 4442.29 | G12: 4000 | H12: =G12-F12 -> -442.29 | I12: =F12/G12 -> 1.1105725
A16: Total Salaries | B16: =SUM(B6:B15) -> 5212.09 | C16: =SUM(C6:C15) -> 0 | D16: =SUM(D6:D15) -> 11558.81 | E16: =SUM(E6:E15) -> 16770.9 | F16: =SUM(F6:F15) -> 97877.2 | G16: =SUM(G6:G15) -> 213900 | H16: =SUM(H6:H15) -> 116022.8 | I16: =F16/G16 -> 0.45758392
A18: Fringe Benefits Rate | B18: =+'Salaries & Fringe Allocations'!Q249+'Salaries & Fringe Allocations'!Q250+'Salaries & Fringe Allocations'!Q255+'Salaries & Fringe Allocations'!Q257 -> 1660.1697 | D18: =+'Salaries & Fringe Allocations'!Q251+'Salaries & Fringe Allocations'!Q252+'Salaries & Fringe Allocations'!Q253+'Salaries & Fringe Allocations'!Q254+'Salaries & Fringe Allocations'!Q256 -> 3523.3158 | E18: =SUM(B18:D18) -> 5183.4855 | F18: =E18+'Nov-2019'!F18 -> 32250.887 | G18: 68136 | H18: =G18-F18 -> 35885.113 | I18: =F18/G18 -> 0.47333109
H19: =G19-F19 -> 0
A20: TOTAL PERSONNEL (Salaries + Fringe Benefits) | B20: =B16+B18 -> 6872.2597 | C20: =C16+C18 -> 0 | D20: =D16+D18 -> 15082.126 | E20: =E16+E18 -> 21954.386 | F20: =F16+F18 -> 130128.09 | G20: =G16+G18 -> 282036 | H20: =H16+H18 -> 151907.91 | I20: =F20/G20 -> 0.46138822
A22: 2. Non-Personnel Operating Costs
A23: Travel | D23: =+'Dec-19 GL'!G97 -> 349.14 | E23: =SUM(B23:D23) -> 349.14 | F23: =E23+'Nov-2019'!F23 -> 1884.04 | G23: 4000 | H23: =G23-F23 -> 2115.96 | I23: =F23/G23 -> 0.47101
A24: Supplies | B24: =+'Dec-19 GL'!G106 -> 92 | D24: =+'Dec-19 GL'!G103 -> 732.89 | E24: =SUM(B24:D24) -> 824.89 | F24: =E24+'Nov-2019'!F24 -> 2731.09 | G24: 7000 | H24: =G24-F24 -> 4268.91 | I24: =F24/G24 -> 0.39015571
A25: Staff Development | E25: =SUM(B25:D25) -> 0 | F25: =E25+'Nov-2019'!F25 -> 0 | G25: 2000 | H25: =G25-F25 -> 2000 | I25: =F25/G25 -> 0
A26: Contractual/Consultants | B26: =+'Dec-19 GL'!G119 -> 3031 | E26: =SUM(B26:D26) -> 3031 | F26: =E26+'Nov-2019'!F26 -> 5774.69 | G26: 13200 | H26: =G26-F26 -> 7425.31 | I26: =F26/G26 -> 0.43747652
A27: Occupancy | B27: =+'Dec-19 GL'!G141 -> 966 | D27: =+'Dec-19 GL'!G124 -> 648 | E27: =SUM(B27:D27) -> 1614 | F27: =E27+'Nov-2019'!F27 -> 6994.27 | G27: 12000 | H27: =G27-F27 -> 5005.73 | I27: =F27/G27 -> 0.58285583
A28: Audit (100% Admin) | E28: =SUM(B28:D28) -> 0 | F28: =E28+'Nov-2019'!F28 -> 1900.29 | G28: 6000 | H28: =G28-F28 -> 4099.71 | I28: =F28/G28 -> 0.316715
A29: Marketing and Outreach | E29: =SUM(B29:D29) -> 0 | F29: =E29+'Nov-2019'!F29 -> 0 | G29: 570 | H29: =G29-F29 -> 570 | I29: =F29/G29 -> 0
A30: Rental Equipment | B30: =+'Dec-19 GL'!G150 -> 286 | E30: =SUM(B30:D30) -> 286 | F30: =E30+'Nov-2019'!F30 -> 1907.95 | G30: 6475 | H30: =G30-F30 -> 4567.05 | I30: =F30/G30 -> 0.29466409
A31: Payroll fees | B31: =+'Dec-19 GL'!G33 -> 1255.32 | E31: =SUM(B31:D31) -> 1255.32 | F31: =E31+'Nov-2019'!F31 -> 5733.09 | G31: 13000 | H31: =G31-F31 -> 7266.91 | I31: =F31/G31 -> 0.44100692
A32: Infrastructure Costs | E32: =SUM(B32:D32) -> 0 | F32: =E32+'Nov-2019'!F32 -> 0 | G32: 1500 | H32: =G32-F32 -> 1500 | I32: =F32/G32 -> 0
A33: Other Operating costs | B33: =+'Dec-19 GL'!G156 -> 40 | E33: =SUM(B33:D33) -> 40 | F33: =E33+'Nov-2019'!F33 -> 1827.82 | G33: 3000.7 | H33: =G33-F33 -> 1172.88 | I33: =F33/G33 -> 0.6091312
A34: Communications | B34: =+'Dec-19 GL'!G173 -> 319.77 | E34: =SUM(B34:D34) -> 319.77 | F34: =E34+'Nov-2019'!F34 -> 1616.8 | G34: 3000 | H34: =G34-F34 -> 1383.2 | I34: =F34/G34 -> 0.53893333
A35: Insurance | B35: =+'Dec-19 GL'!G185 -> 599 | E35: =SUM(B35:D35) -> 599 | F35: =E35+'Nov-2019'!F35 -> 2953.72 | G35: 4000 | H35: =G35-F35 -> 1046.28 | I35: =F35/G35 -> 0.73843
A36: Postage | D36: =+'Dec-19 GL'!G178 -> 64.58 | E36: =SUM(B36:D36) -> 64.58 | F36: =E36+'Nov-2019'!F36 -> 136.58 | G36: 1000 | H36: =G36-F36 -> 863.42 | I36: =F36/G36 -> 0.13658
A37: Total NPOC | B37: =SUM(B23:B36) -> 6589.09 | C37: =SUM(C23:C36) -> 0 | D37: =SUM(D23:D36) -> 1794.61 | E37: =SUM(E23:E36) -> 8383.7 | F37: =SUM(F23:F36) -> 33460.34 | G37: =SUM(G23:G36) -> 76745.7 | H37: =SUM(H23:H36) -> 43285.36 | I37: =F37/G37 -> 0.43598977
A40: 3. Participant Costs
A41: Participant Wages | C41: =+'Dec-19 GL'!G11 -> 157957.1 | E41: =SUM(B41:D41) -> 157957.1 | F41: =E41+'Nov-2019'!F41 -> 592217.47 | G41: 1452829.2 | H41: =G41-F41-F42 -> 858451.14 | I41: =F41/G41 -> 0.40763047
A42: Reimbursable Participant Wage(Paid by Affiliate) | C42: 0 | E42: =SUM(B42:D42) -> 0 | F42: =+E42+'Nov-2019'!F42 -> 2160.63 | I42: 0
A43: Participant Specialized Training Wage | E43: =SUM(B43:D43) -> 0 | F43: =E43+'Nov-2019'!F43 -> 0 | G43: 12820 | H43: =G43-F43 -> 12820 | I43: =F43/G43 -> 0
A44: Participant FICA and other taxes | C44: =+'Dec-19 GL'!G25 -> 12195.69 | E44: =SUM(B44:D44) -> 12195.69 | F44: =E44+'Nov-2019'!F44 -> 43139.07 | G44: 111141.44 | H44: =G44-F44 -> 68002.37 | I44: =F44/G44 -> 0.38814568
A45: Workers compensation | C45: =+'Dec-19 GL'!G28 -> 2919 | E45: =SUM(B45:D45) -> 2919 | F45: =E45+'Nov-2019'!F45 -> 15769.48 | G45: 22373.57 | H45: =G45-F45 -> 6604.09 | I45: =F45/G45 -> 0.70482627
A46: Support Services | E46: =SUM(B46:D46) -> 0 | F46: =E46+'Nov-2019'!F46 -> 0 | G46: 8500 | H46: =G46-F46 -> 8500 | I46: =F46/G46 -> 0
A47: Specialized Training vendor | E47: =SUM(B47:D47) -> 0 | F47: =E47+'Nov-2019'!F47 -> 0 | G47: 29630 | H47: =G47-F47 -> 29630 | I47: =F47/G47 -> 0
A48: Total Participant Costs | B48: =SUM(B41:B47) -> 0 | C48: =SUM(C41:C47) -> 173071.79 | D48: =SUM(D41:D47) -> 0 | E48: =SUM(E41:E47) -> 173071.79 | F48: =SUM(F41:F47) -> 653286.65 | G48: =SUM(G41:G47) -> 1637294.2 | H48: =SUM(H41:H47) -> 984007.6 | I48: =F48/G48 -> 0.39900381
A50: 4. Indirect ('%) | B50: 0 | E50: =B50 -> 0 | F50: =E50+'Nov-2019'!F50 -> 0 | G50: 17532.59 | H50: =G50-F50 -> 17532.59 | I50: =F50/G50 -> 0
A52: 5.Total Federal Expenses | B52: =B20+B37+B48+B50 -> 13461.35 | C52: =C20+C37+C48 -> 173071.79 | D52: =D20+D37+D48 -> 16876.736 | E52: =E37+E20+E48+E50 -> 203409.88 | F52: =F37+F20+F48+F50 -> 816875.08 | G52: =G37+G20+G48+G50 -> 2013608.5 | H52: =H37+H20+H48+H50 -> 1196733.5 | I52: =F52/G52 -> 0.4056772
A54: 6. Non Federal Match | E54: 20159.28 | F54: =E54+'Nov-2019'!F54 -> 49793.71 | G54: 242467.32 | H54: =G54-F54 -> 192673.61 | I54: =F54/G54 -> 0.20536256
A56: 7. Total Expenses | B56: =B52+B54 -> 13461.35 | C56: =C52+C54 -> 173071.79 | D56: =D52+D54 -> 16876.736 | E56: =E52+E54 -> 223569.16 | F56: =F52+F54 -> 866668.79 | G56: =G52+G54 -> 2256075.9 | H56: =H52+H54 -> 1389407.1 | I56: =F56/G56 -> 0.38414878
F57: AFFILIATES- ENTER NOTES TO THIS INVOICE HERE
A58: 8. Total Reimbursable expenses | E58: =+E20+E37-E31+E42+E45+E46+E47+E50 -> 32001.766
A60: FOR NUL USE ONLY
A62: TOTAL INVOICE SUBMITTED | E62: =E58 -> 32001.766
A65: COSTS DISALLOWED
A68: OTHER ADJUSTMENTS
A71: CASH DUE TO/DUE FROM AFFILIATE
A73: SIGNATURE AND DATE:
A77: R. Greg Ward | F77: Vivian Cox Fraser
A78: Fiscal Manager | B78: Date | F78: Affiliate CEO | H78: Date
A81: Gwendolyn Morris
A82: Project Director | B82: Date | F82: Vice President, Workforce Development (NUL) | H82: Date

Sheet Dec-19 GL
A1: URBAN LEAGUE OF ESSEX COUNTY
A2: 451 USJP Program Transaction Detail by Account
A3: December 2019
B5: Date | C5: Transaction Type | D5: Num | E5: Name | F5: Memo/Description | G5: Amount | H5: Check #
A6: 7100 Participant Salaries & Wages
A7: 7112 Participant Wages - USJP
B8: 12/02/2019 | C8: Journal Entry | D8: 98 | F8: USJP Participant Wages - 12/2/19 | G8: 47009.24
B9: 12/16/2019 | C9: Journal Entry | D9: 99 | F9: USJP Participant Wages - 12/16/19 | G9: 51352.86
B10: 12/30/2019 | C10: Journal Entry | D10: 149 | F10: USJP Participant Wages - 12/30/19 | G10: 59595
A11: Total for 7112 Participant Wages - USJP | G11: =SUM(G8:G10) -> 157957.1
A12: 7112.1 USJP Manual Checks
B13: 12/02/2019 | C13: Bill | D13: 12.02.19VD | E13: Valerie Dixon | F13: Participant Wages for 11/07/19 - 11/20/19 Check Date 12/02/19 - Direct Deposit Returned by Bank | G13: 338.02
B14: 12/05/2019 | C14: Deposit | E14: Paycom Payroll, LLC | F14: Valerie Dixon - Direct Deposit return incomplete account #12/02/19 payroll 19-12-07 | G14: -338.02
B15: 12/16/2019 | C15: Bill | D15: 12.16.19VD | E15: Valerie Dixon | F15: Participant Wages for 11/21/19 - 12/04/19 Check Date 12/16/19 - Direct Deposit Returned by Bank | G15: 338.02
B16: 12/19/2019 | C16: Deposit | E16: Paycom Payroll, LLC | F16: Valerie Dixon - Direct Deposit return closed account #12/16/19 Payroll 19-12-25 | G16: -338.02
B17: 12/20/2019 | C17: Deposit | E17: Paycom Payroll, LLC | F17: USJP Stale check for Edythe Walker Pay Date 06/17/19 19-12-26 | G17: -317.56
B18: 12/20/2019 | C18: Bill | D18: 12.20.19EW | E18: Edythe Walker | F18: Re-issue pay check from 6/17/19 payroll - Check returned as undeliverable by postal service | G18: 317.56
A19: Total for 7112.1 USJP Manual Checks | G19: =SUM(G13:G18) -> 0
A20: Total for 7112 Participant Wages - USJP with subs | G20: =+G11+G19 -> 157957.1
A21: 7120 Payroll Taxes
B22: 12/02/2019 | C22: Journal Entry | D22: 98 | F22: USJP Employer Liability | G22: 3646.17
B23: 12/16/2019 | C23: Journal Entry | D23: 99 | F23: USJP Employer Liability | G23: 3973.66
B24: 12/30/2019 | C24: Journal Entry | D24: 149 | F24: USJP Employer Liability | G24: 4575.86
A25: Total for 7120 Payroll Taxes | G25: =SUM(G22:G24) -> 12195.69
A26: 7130 Worker's Compensation - USJP
B27: 12/30/2019 | C27: Journal Entry | D27: 123 | F27: Workers Comp Alloc | G27: 2919
A28: Total for 7130 Worker's Compensation - USJP | G28: =SUM(G27) -> 2919
A29: 7132 Payroll Expenses - Fees
B30: 12/02/2019 | C30: Journal Entry | D30: 98 | F30: USJP Payroll Fee | G30: 422.45
B31: 12/16/2019 | C31: Journal Entry | D31: 99 | F31: USJP Payroll Fee | G31: 397.76
B32: 12/30/2019 | C32: Journal Entry | D32: 149 | F32: USJP Payroll Fee | G32: 435.11
A33: Total for 7132 Payroll Expenses - Fees | G33: =SUM(G30:G32) -> 1255.32
A34: Total for 7100 Participant Salaries & Wages | G34: =+G20+G25+G28+G33 -> 174327.11
A35: 7200 Salaries & Related Expenses
A36: 7220 Salaries & Wages
A37: 7222 Staff
B38: 12/31/2019 | C38: Journal Entry | D38: 121 | F38: Salary Allocation - December | G38: 16771
A39: Total for 7222 Staff | G39: =SUM(G38) -> 16771
A44: 7240 Employee Benefits
A45: 7241 Health Insurance
B46: 12/01/2019 | C46: Bill | D46: 292879522 | E46: Horizon Blue Cross Blue Shield of NJ | F46: To record Horizon Exp. Billing Period 12/15/19 - 01/15/20 | G46: 3688.1 | H46: 12820
A47: Total for 7241 Health Insurance | G47: =SUM(G46) -> 3688.1
A48: 7242 Life and Dental Insurance
B49: 12/01/2019 | C49: Bill | D49: 12.01.19PG | E49: Principal Financial Group | F49: Life, Dental & AD&D | G49: 264.69 | H49: 12822
A50: Total for 7242 Life and Dental Insurance | G50: =SUM(G49) -> 264.69
A51: 7244 Employee Contrib - Health
B52: 12/31/2019 | C52: Journal Entry | D52: 137 | F52: Employee Medical Contrib | G52: -806.3805
A53: Total for 7244 Employee Contrib - Health | G53: =SUM(G52) -> -806.3805
A54: 7247 Emp-ee Contrib -Dental
B55: 12/31/2019 | C55: Journal Entry | D55: 138 | F55: Employee Dental Contrib | G55: -50.925
A56: Total for 7247 Emp-ee Contrib -Dental | G56: =SUM(G55) -> -50.925
A57: Total for 7240 Employee Benefits | G57: =+G47+G50+G53+G56 -> 3095.4845
A58: 7250 Payroll Taxes, etc.
A59: 7245 Worker's Compensation Insurance
A60: 7248 Allocated W Comp
B61: 12/30/2019 | C61: Journal Entry | D61: 123 | F61: Workers Comp Alloc | G61: 498
A62: Total for 7248 Allocated W Comp | G62: =SUM(G61) -> 498
A64: EMPLOYER TAXES
A65: 7251 Social Security
B66: 12/30/2019 | C66: Journal Entry | D66: 132 | F66: Fica | G66: 913
A67: Total for 7251 Social Security | G67: =SUM(G66) -> 913
A68: 7252 Medicare
B69: 12/30/2019 | C69: Journal Entry | D69: 131 | F69: Medi Alloc | G69: 237
A70: Total for 7252 Medicare | G70: =SUM(G69) -> 237
A71: 7253 Unemployment
B72: 12/30/2019 | C72: Journal Entry | D72: 127 | F72: SUI Alloc | G72: 224
A73: Total for 7253 Unemployment | G73: =SUM(G72) -> 224
A74: 7254 Disability
B75: 12/30/2019 | C75: Journal Entry | D75: 136 | F75: Disability Alloc | G75: 44
A76: Total for 7254 Disability | G76: =SUM(G75) -> 44
A79: TOTAL EMPLOYER TAXES | G79: =+G67+G70+G73+G76 -> 1418
A82: 7260 Payroll Service Fees
A83: 7260.1 Allocated Payroll Fees
B84: 12/30/2019 | C84: Journal Entry | D84: 129 | F84: Payroll Fees | G84: 172
A85: Total for 7260.1 Allocated Payroll Fees | G85: =SUM(G84) -> 172
A87: Total for Fringe Benefits | G87: =+G40+G57+G62+G79+G85 -> 5183.4845
A90: 8300 Travel & Meetings Expenses
A91: 8310 Transportation & Parking
B92: 12/04/2019 | C92: Bill | D92: 12.04.19GM | E92: Gwendolyn Morris | F92: Mileage Reimbursement 11/4/19 - 11/13/19 | G92: 44.06 | H92: 12843
B93: 12/04/2019 | C93: Bill | D93: 11173 | E93: City of Paterson Parking Authority | F93: Parking Permit for Dec. 2019 | G93: 150 | H93: 12831
B94: 12/04/2019 | C94: Bill | D94: 12.04.19IC | E94: Irene Cerna | F94: Mileage Reimbursement - USJP 11/6/19 - 11/21/19 | G94: 57.88 | H94: 12842
B95: 12/09/2019 | C95: Bill | D95: 12.09.19VB | E95: Vanessa Brown | F95: Mileage Reimbursement 11/26/19 - 12/09/19 | G95: 21.6 | H95: 12845
B96: 12/09/2019 | C96: Bill | D96: 12.09.19AJ | E96: Armanda Johnson | F96: Mileage Reimbursement for 11/04/19 - 12/09/19 | G96: 75.6 | H96: 12844
A97: Total for 8310 Transportation & Parking | G97: =SUM(G92:G96) -> 349.14
A99: 8110 Supplies
A100: 8435 GED & ABE Classes
B101: 12/03/2019 | C101: Bill | D101: 138575 | E101: DATA Recognition Corporation | F101: Tabe Test Score-ez | G101: 895.14 | H101: 12919
B102: 43830 | C102: Creditmemo | D102: CM702757 | E102: DATA Recognition Corporation | F102: Tabe Test Score-ez | G102: -162.25 | H102: 12919
A103: Total for 8435 GED & ABE Classes | G103: =SUM(G101:G102) -> 732.89
A104: 8112 Alloc Supplies
B105: 12/30/2019 | C105: Journal Entry | D105: 125 | F105: Supplies Alloc | G105: 92
A106: Total for 8110 Supplies | G106: =SUM(G105) -> 92
A108: Total for Supplies | G108: =+G103+G106 -> 824.89
A110: CONTRACTUAL CONSULTANTS
A111: 7520 Accounting Fees
A112: 7521 Allocated Acctg and Audit
B113: 12/30/2019 | C113: Journal Entry | D113: 135 | F113: Acctg Fee Alloc | G113: 946
A114: Total for 7521 Allocated Acctg and Audit | G114: =SUM(G113) -> 946
A115: 7540 Instructors/Consultants/Subs
B116: 12/27/2019 | C116: Bill | D116: 12.27.19AC | E116: Anthony Clark | F116: Business Development 12/16/19 - 12/27/19 | G116: 1710 | H116: 12862
...

Sheet Dec-FR
A1: National Urban League Financial Report
A2: 1. Funding Agency- National Urban League | I2: 2. Federal Grant Name - Urban Seniors Jobs Program CFDA 17.235 | N2: PY 19
A3: 3. Recipient Organization (Name and complete address including Zip code)
M4: 4. Final Report (mark X) Yes No | N4: 5. Basis of Reporting □ Accrual
A5: 6. Project/Grant Period From: July 1-2019 | H5: To: June 31, 2020 | M5: 7. Reporting Period End Date 12/31/2019
A6: 8. Transactions | M6: Cumulative
A7: Federal Cash:
A8: a. Cash Receipts
A9: b. Cash Disbursements | M9: =M8 -> 0
A10: c. Cash on Hand (line a minus b) | M10: =M8-M9 -> 0
A11: Federal Expenditures and Unobligated Balance:
A12: d. Approved Budget
A13: e. Federal Share of Expenditures -Program Costs | M13: =M9 -> 0
A14: f. Federal Share of Expenditures -Administrative Costs | M14: 0
A15: g. Federal Share of Unliquidated Obligations ( ACCRUALS) | M15: 0
A16: h. Total Federal Obligations (sum of lines e and g) | M16: =M13+M14+M15 -> 0
A17: i. Unobligated Balance of Federal Funds (line d minus h) | M17: =M12-M16 -> 0
A18: Recipient Share: Cost Sharing/ Matching/ In-Kind Costs
A19: j. Total Match and Inkind Required if Applicable | M19: 0
A20: k. Total Receipient share reported if Applicable | M20: 0
A21: l. Remaining Recipient Share to Be Provided (line j minus k) | M21: =M19-M20 -> 0
A22: Program Income:
A23: m. Total Program Income Earned if applicable | M23: 0
A24: n. Program Income Expended in Accordance with the Addition Method | M24: 0
A25: o. Unexpended Program Income (line m minus line n) | M25: =M23-M24 -> 0
A26: 9. Remarks: (Attach any explanations deemed necessary or information required by Federal sponsoring agency in compliance with governing legislation.)
A28: 10. Indirect Expenditures
A29: a. Type of Rate | C29: b. Rate | D29: c. Rate Approval Date | G29: d. Period From (MM/DD/YYYY) | I29: Period To (MM/DD/YYYY) | J29: e. Base | M29: f. Amount Charged | N29: g. Federal Share
A32: 11. Certification: By signing this report, I certify to the best of my knowledge and belief that the report is true, complete, and accurate, and the expenditures, disbursements and cash receipts are for the purposes and objectives set forth in the terms and conditions of the Federal award. I am aware that any false, fictitious, or fraudulent information, or the omission of any material fact, may subject me to criminal, civil or administrative penalties for fraud, false statements, false claims or otherwise. (U.S. Code Title 18, Section 1001 and Title 31, Sections 3729–3730 and 3801–3812).
A33: a. Typed or Printed Name and Title of Authorized Certifying Official | M33: c. Telephone (Area code, number, and extension)
M34: d. Email Address
A35: b. Signature of Authorized Certifying Official | M35: e. Date Report Submitted (MM/DD/YYYY)

Sheet Jan-2020
A1: Urban Seniors Jobs Program PY 19 | G1: 43831 | I1: %
A2: Urban League of Essex County | E2: Invoice # 7 | I2: Spent
A3: 1. PERSONNEL | E3: TOTAL
C4: ENROLLEE | D4: OPC | E4: MONTHLY | F4: CUMULATIVE | G4: TOTAL | H4: BUDGET
A5: POSITION TITLE | B5: ADMIN | C5: WAGES & FB | D5: PROGRAM | E5: AMOUNT | F5: EXPENSES | G5: BUDGET | H5: REMAINING
A6: COO Patricia Sermon | E6: =SUM(B6:D6) -> 0 | F6: =E6+'Dec-2019'!F6 -> 7884.62 | G6: 16400 | H6: =G6-F6 -> 8515.38 | I6: =F6/G6 -> 0.48076951
A7: Director Gwendolyn Morris | E7: =SUM(B7:D7) -> 0 | F7: =E7+'Dec-2019'!F7 -> 31250 | G7: 66000 | H7: =G7-F7 -> 34750 | I7: =F7/G7 -> 0.47348485
A8: Prog Site Coordinator (Essex) Rahmel Leake | E8: =SUM(B8:D8) -> 0 | F8: =E8+'Dec-2019'!F8 -> 17692.41 | G8: 40000 | H8: =G8-F8 -> 22307.59 | I8: =F8/G8 -> 0.44231025
A9: Prog Site Coordinator (Passaic) Irene Cerna | E9: =SUM(B9:D9) -> 0 | F9: =E9+'Dec-2019'!F9 -> 13730.93 | G9: 30000 | H9: =G9-F9 -> 16269.07 | I9: =F9/G9 -> 0.45769767
A10: Site Coordinator (Morris) Armanda Johnson | E10: =SUM(B10:D10) -> 0 | F10: =E10+'Dec-2019'!F10 -> 9315.32 | G10: 21500 | H10: =G10-F10 -> 12184.68 | I10: =F10/G10 -> 0.4332707
A11: Program Assistant Joanna Martinez | E11: =SUM(B11:D11) -> 0 | F11: =E11+'Dec-2019'!F11 -> 13561.63 | G11: 36000 | H11: =G11-F11 -> 22438.37 | I11: =F11/G11 -> 0.37671194
A12: Staff Accountant - Gregory Ward | E12: =SUM(B12:D12) -> 0 | F12: =E12+'Dec-2019'!F12 -> 4442.29 | G12: 4000 | H12: =G12-F12 -> -442.29 | I12: =F12/G12 -> 1.1105725
A16: Total Salaries | B16: =SUM(B6:B15) -> 0 | C16: =SUM(C6:C15) -> 0 | D16: =SUM(D6:D15) -> 0 | E16: =SUM(E6:E15) -> 0 | F16: =SUM(F6:F15) -> 97877.2 | G16: =SUM(G6:G15) -> 213900 | H16: =SUM(H6:H15) -> 116022.8 | I16: =F16/G16 -> 0.45758392
A18: Fringe Benefits Rate | B18: =+'Salaries & Fringe Allocations'!Q291+'Salaries & Fringe Allocations'!Q292+'Salaries & Fringe Allocations'!Q297 -> 1912.1801 | D18: =SUM('Salaries & Fringe Allocations'!Q293:Q296)+'Salaries & Fringe Allocations'!Q298 -> 3850.5529 | E18: =SUM(B18:D18) -> 5762.733 | F18: =E18+'Dec-2019'!F18 -> 38013.62 | G18: 68136 | H18: =G18-F18 -> 30122.38 | I18: =F18/G18 -> 0.55790801
H19: =G19-F19 -> 0
A20: TOTAL PERSONNEL (Salaries + Fringe Benefits) | B20: =B16+B18 -> 1912.1801 | C20: =C16+C18 -> 0 | D20: =D16+D18 -> 3850.5529 | E20: =E16+E18 -> 5762.733 | F20: =F16+F18 -> 135890.82 | G20: =G16+G18 -> 282036 | H20: =H16+H18 -> 146145.18 | I20: =F20/G20 -> 0.48182083
A22: 2. Non-Personnel Operating Costs
A23: Travel | D23: =+'Jan 2020 PL'!$J$190 -> 348.28 | E23: =SUM(B23:D23) -> 348.28 | F23: =E23+'Dec-2019'!F23 -> 2232.32 | G23: 4000 | H23: =G23-F23 -> 1767.68 | I23: =F23/G23 -> 0.55808
A24: Supplies | B24: =+'Jan 2020 PL'!$J$119 -> 344 | D24: =+'Jan 2020 PL'!$J$115 -> 465.27 | E24: =SUM(B24:D24) -> 809.27 | F24: =E24+'Dec-2019'!F24 -> 3540.36 | G24: 7000 | H24: =G24-F24 -> 3459.64 | I24: =F24/G24 -> 0.50576571
A25: Staff Development | E25: =SUM(B25:D25) -> 0 | F25: =E25+'Dec-2019'!F25 -> 0 | G25: 2000 | H25: =G25-F25 -> 2000 | I25: =F25/G25 -> 0
A26: Contractual/Consultants | B26: =+'Jan 2020 PL'!$J$105+'Jan 2020 PL'!$J$110 -> 2480 | E26: =SUM(B26:D26) -> 2480 | F26: =E26+'Dec-2019'!F26 -> 8254.69 | G26: 13200 | H26: =G26-F26 -> 4945.31 | I26: =F26/G26 -> 0.6253553
A27: Occupancy | B27: =+'Jan 2020 PL'!$J$153+'Jan 2020 PL'!$J$164+'Jan 2020 PL'!$J$170 -> 512 | D27: =+'Jan 2020 PL'!$J$147 -> 648 | E27: =SUM(B27:D27) -> 1160 | F27: =E27+'Dec-2019'!F27 -> 8154.27 | G27: 12000 | H27: =G27-F27 -> 3845.73 | I27: =F27/G27 -> 0.6795225
A28: Audit (100% Admin) | E28: =SUM(B28:D28) -> 0 | F28: =E28+'Dec-2019'!F28 -> 1900.29 | G28: 6000 | H28: =G28-F28 -> 4099.71 | I28: =F28/G28 -> 0.316715
A29: Marketing and Outreach | E29: =SUM(B29:D29) -> 0 | F29: =E29+'Dec-2019'!F29 -> 0 | G29: 570 | H29: =G29-F29 -> 570 | I29: =F29/G29 -> 0
A30: Rental Equipment | B30: =+'Jan 2020 PL'!$J$159 -> 224 | E30: =SUM(B30:D30) -> 224 | F30: =E30+'Dec-2019'!F30 -> 2131.95 | G30: 6475 | H30: =G30-F30 -> 4343.05 | I30: =F30/G30 -> 0.32925869
A31: Payroll fees | B31: =+'Jan 2020 PL'!$J$42 -> 2902.81 | E31: =SUM(B31:D31) -> 2902.81 | F31: =E31+'Dec-2019'!F31 -> 8635.9 | G31: 13000 | H31: =G31-F31 -> 4364.1 | I31: =F31/G31 -> 0.6643
A32: Infrastructure Costs | E32: =SUM(B32:D32) -> 0 | F32: =E32+'Dec-2019'!F32 -> 0 | G32: 1500 | H32: =G32-F32 -> 1500 | I32: =F32/G32 -> 0
A33: Other Operating costs | B33: =+'Jan 2020 PL'!$J$100+'Jan 2020 PL'!$J$142 -> 453 | E33: =SUM(B33:D33) -> 453 | F33: =E33+'Dec-2019'!F33 -> 2280.82 | G33: 3000.7 | H33: =G33-F33 -> 719.88 | I33: =F33/G33 -> 0.76009598
A34: Communications | B34: =+'Jan 2020 PL'!$J$133 -> 117 | D34: =+'Jan 2020 PL'!$J$124+'Jan 2020 PL'!$J$129 -> 190.82 | E34: =SUM(B34:D34) -> 307.82 | F34: =E34+'Dec-2019'!F34 -> 1924.62 | G34: 3000 | H34: =G34-F34 -> 1075.38 | I34: =F34/G34 -> 0.64154
A35: Insurance | B35: =+'Jan 2020 PL'!$J$177 -> 436 | E35: =SUM(B35:D35) -> 436 | F35: =E35+'Dec-2019'!F35 -> 3389.72 | G35: 4000 | H35: =G35-F35 -> 610.28 | I35: =F35/G35 -> 0.84743
A36: Postage | D36: =+'Jan 2020 PL'!$J$138 -> 0 | E36: =SUM(B36:D36) -> 0 | F36: =E36+'Dec-2019'!F36 -> 136.58 | G36: 1000 | H36: =G36-F36 -> 863.42 | I36: =F36/G36 -> 0.13658
A37: Total NPOC | B37: =SUM(B23:B36) -> 7468.81 | C37: =SUM(C23:C36) -> 0 | D37: =SUM(D23:D36) -> 1652.37 | E37: =SUM(E23:E36) -> 9121.18 | F37: =SUM(F23:F36) -> 42581.52 | G37: =SUM(G23:G36) -> 76745.7 | H37: =SUM(H23:H36) -> 34164.18 | I37: =F37/G37 -> 0.55483916
A40: 3. Participant Costs
A41: Participant Wages | C41: =+'Jan 2020 PL'!$J$23 -> 114368.25 | E41: =SUM(B41:D41) -> 114368.25 | F41: =E41+'Dec-2019'!F41 -> 706585.72 | G41: 1452829.2 | H41: =G41-F41-F42 -> 744400.45 | I41: =F41/G41 -> 0.48635153
A42: Reimbursable Participant Wage(Paid by Affiliate) | C42: =+'Jan 2020 PL'!$J$30 -> -317.56 | E42: =SUM(B42:D42) -> -317.56 | F42: =+E42+'Dec-2019'!F42 -> 1843.07
A43: Participant Specialized Training Wage | E43: =SUM(B43:D43) -> 0 | F43: =E43+'Dec-2019'!F43 -> 0 | G43: 12820 | H43: =G43-F43 -> 12820 | I43: =F43/G43 -> 0
A44: Participant FICA and other taxes | C44: =+'Jan 2020 PL'!$J$35 -> 8769.51 | E44: =SUM(B44:D44) -> 8769.51 | F44: =E44+'Dec-2019'!F44 -> 51908.58 | G44: 111141.44 | H44: =G44-F44 -> 59232.86 | I44: =F44/G44 -> 0.46704973
A45: Workers compensation | C45: =+'Jan 2020 PL'!$J$38 -> 3064 | E45: =SUM(B45:D45) -> 3064 | F45: =E45+'Dec-2019'!F45 -> 18833.48 | G45: 22373.57 | H45: =G45-F45 -> 3540.09 | I45: =F45/G45 -> 0.84177357
A46: Support Services | E46: =SUM(B46:D46) -> 0 | F46: =E46+'Dec-2019'!F46 -> 0 | G46: 8500 | H46: =G46-F46 -> 8500 | I46: =F46/G46 -> 0
A47: Specialized Training vendor | E47: =SUM(B47:D47) -> 0 | F47: =E47+'Dec-2019'!F47 -> 0 | G47: 29630 | H47: =G47-F47 -> 29630 | I47: =F47/G47 -> 0
A48: Total Participant Costs | B48: =SUM(B41:B47) -> 0 | C48: =SUM(C41:C47) -> 125884.2 | D48: =SUM(D41:D47) -> 0 | E48: =SUM(E41:E47) -> 125884.2 | F48: =SUM(F41:F47) -> 779170.85 | G48: =SUM(G41:G47) -> 1637294.2 | H48: =SUM(H41:H47) -> 858123.4 | I48: =F48/G48 -> 0.47588932
A50: 4. Indirect ('%) | B50: 0 | E50: =B50 -> 0 | F50: =E50+'Dec-2019'!F50 -> 0 | G50: 17532.59 | H50: =G50-F50 -> 17532.59 | I50: =F50/G50 -> 0
A52: 5.Total Federal Expenses | B52: =B20+B37+B48+B50 -> 9380.9901 | C52: =C20+C37+C48 -> 125884.2 | D52: =D20+D37+D48 -> 5502.9229 | E52: =E37+E20+E48+E50 -> 140768.11 | F52: =F37+F20+F48+F50 -> 957643.19 | G52: =G37+G20+G48+G50 -> 2013608.5 | H52: =H37+H20+H48+H50 -> 1055965.3 | I52: =F52/G52 -> 0.47558558
A54: 6. Non Federal Match | E54: =+'Jan 2020 PL'!$J$197 -> 26606.29 | F54: =E54+'Dec-2019'!F54 -> 76400 | G54: 242467.32 | H54: =G54-F54 -> 166067.32 | I54: =F54/G54 -> 0.31509401
A56: 7. Total Expenses | B56: =B52+B54 -> 9380.9901 | C56: =C52+C54 -> 125884.2 | D56: =D52+D54 -> 5502.9229 | E56: =E52+E54 -> 167374.4 | F56: =F52+F54 -> 1034043.2 | G56: =G52+G54 -> 2256075.9 | H56: =H52+H54 -> 1222032.7 | I56: =F56/G56 -> 0.45833707
F57: AFFILIATES- ENTER NOTES TO THIS INVOICE HERE
A58: 8. Total Reimbursable expenses | E58: =+E20+E37-E31+E42+E45+E46+E47+E50 -> 14727.543
A60: FOR NUL USE ONLY
A62: TOTAL INVOICE SUBMITTED | E62: =E58 -> 14727.543
A65: COSTS DISALLOWED
A68: OTHER ADJUSTMENTS
A71: CASH DUE TO/DUE FROM AFFILIATE
A73: SIGNATURE AND DATE:
A78: Fiscal Manager | B78: Date | F78: Affiliate CEO | H78: Date
A82: Project Director | B82: Date | F82: Vice President, Workforce Development (NUL) | H82: Date

Sheet Jan 2020 PL
A1: URBAN LEAGUE OF ESSEX COUNTY
A2: Profit and Loss Detail
A3: January 2020
B5: Date | C5: Transaction Type | D5: Num | E5: Name | F5: Location | G5: Class | H5: Memo/Description | I5: Split | J5: Amount | K5: Balance
A6: Ordinary Income/Expenses
A7: Income
A8: 4500 Revenue from Government Grants
A9: 4520 Federal Grants
A10: 4521.1 USJP - Payroll Reimb
B11: 01/13/2020 | C11: Journal Entry | D11: 187 | G11: 451 USJP Program | H11: USJP Participant Payroll | I11: -Split- | J11: 51390.42 | K11: 51390.42
B12: 01/27/2020 | C12: Journal Entry | D12: 188 | G12: 451 USJP Program | H12: USJP Participant Payroll | I12: -Split- | J12: 50 | K12: 51440.42
B13: 01/27/2020 | C13: Journal Entry | D13: 188 | G13: 451 USJP Program | H13: USJP Participant Payroll | I13: -Split- | J13: 74600.15 | K13: 126040.57
A14: Total for 4521.1 USJP - Payroll Reimb | J14: 126040.57
A15: Total for 4520 Federal Grants | J15: 126040.57
A16: Total for 4500 Revenue from Government Grants | J16: 126040.57
A17: Total for Income | J17: 126040.57
A18: Expenses
A19: 7100 Participant Salaries & Wages
A20: 7112 Participant Wages - USJP
B21: 01/13/2020 | C21: Journal Entry | D21: 187 | G21: 451 USJP Program | H21: USJP Participant Wages - 1/13/20 | I21: -Split- | J21: 47287.5 | K21: 47287.5
B22: 01/27/2020 | C22: Journal Entry | D22: 188 | G22: 451 USJP Program | H22: USJP Participant Wages - 1/27/20 | I22: -Split- | J22: 67080.75 | K22: 114368.25
A23: Total for 7112 Participant Wages - USJP | J23: 114368.25
A24: 7112.1 USJP Manual Checks
B25: 01/03/2020 | C25: Deposit | E25: Paycom Payroll, LLC | G25: 451 USJP Program | H25: USJP Payroll Participant Return - Edythe Walker stale check 20-01-03 | I25: 1010 Cash:Checking Active:Bank of America:BOA Operating Acct 3973 | J25: -317.56 | K25: -317.56
B26: 01/13/2020 | C26: Check | D26: 12899 | E26: Reginald Williams | G26: 451 USJP Program | H26: USJP Participant owed 32 hours for training from 12/19/19 - 01/01/22. Check Date 01/13/20 not previously paid. | I26: 1010 Cash:Checking Active:Bank of America:BOA Operating Acct 3973 | J26: 241.36 | K26: -76.2
B27: 01/17/2020 | C27: Bill | E27: Patricia Borden | G27: 451 USJP Program | H27: Not added on payroll spreadsheet for payment 12.19.19-01.01.20 | I27: 2000 Accounts Payable | J27: 313.17 | K27: 236.97
B28: 01/17/2020 | C28: Check | D28: 12940 | E28: Olivia Wicker | G28: 451 USJP Program | H28: Not included on the payroll spreadsheet 12.19.19 - 01.01.20 | I28: 1010 Cash:Checking Active:Bank of America:BOA Operating Acct 3973 | J28: 183.69 | K28: 420.66
B29: 01/30/2020 | C29: Deposit | E29: Paycom Payroll, LLC | G29: 451 USJP Program | H29: Refund for 0K296-USJP Overpayment pf Payroll for Manual Checks 20-01-49 | I29: 1010 Cash:Checking Active:Bank of America:BOA Operating Acct 3973 | J29: -738.22 | K29: -317.56
A30: Total for 7112.1 USJP Manual Checks | J30: -317.56
A31: Total for 7112 Participant Wages - USJP with sub-accounts | J31: 114050.69
A32: 7120 Payroll Taxes
B33: 01/13/2020 | C33: Journal Entry | D33: 187 | G33: 451 USJP Program | H33: USJP Employer Liability | I33: -Split- | J33: 3637.8 | K33: 3637.8
B34: 01/27/2020 | C34: Journal Entry | D34: 188 | G34: 451 USJP Program | H34: USJP Employer Liability | I34: -Split- | J34: 5131.71 | K34: 8769.51
A35: Total for 7120 Payroll Taxes | J35: 8769.51
A36: 7130 Worker's Compensation - USJP
B37: 01/31/2020 | C37: Journal Entry | D37: 233 | G37: 451 USJP Program | H37: Workers Comp Alloc | I37: -Split- | J37: 3064 | K37: 3064
A38: Total for 7130 Worker's Compensation - USJP | J38: 3064
A39: 7132 Payroll Expenses - Fees
B40: 01/13/2020 | C40: Journal Entry | D40: 187 | G40: 451 USJP Program | H40: USJP Payroll Fee | I40: -Split- | J40: 465.12 | K40: 465.12
B41: 01/27/2020 | C41: Journal Entry | D41: 188 | G41: 451 USJP Program | H41: USJP Payroll Fee | I41: -Split- | J41: 2437.69 | K41: 2902.81
A42: Total for 7132 Payroll Expenses - Fees | J42: 2902.81
A43: Total for 7100 Participant Salaries & Wages | J43: 128787.01
A44: 7200 Salaries & Related Expenses
A45: 7220 Salaries & Wages
A46: 7222 Staff
B47: 01/31/2020 | C47: Journal Entry | D47: 212 | G47: 451 USJP Program | I47: -Split- | J47: 17825 | K47: 17825
A48: Total for 7222 Staff | J48: 17825
A49: Total for 7220 Salaries & Wages | J49: 17825
A50: 7240 Employee Benefits
A51: 7241 Health Insurance
B52: 01/01/2020 | C52: Bill | D52: 293105697 | E52: Horizon Blue Cross Blue Shield of NJ | G52: 451 USJP Program | H52: To record Horizon Exp. Billing Period 01/15/20 - 02/15/20 | I52: 2000 Accounts Payable | J52: 3581.26 | K52: 3581.26
A53: Total for 7241 Health Insurance | J53: 3581.26
A54: 7242 Life and Dental Insurance
B55: 01/01/2020 | C55: Bill | D55: 01.01.20PL | E55: Principal Financial Group | G55: 451 USJP Program | H55: Life, Dental & AD&D | I55: 2000 Accounts Payable | J55: 235.2 | K55: 235.2
A56: Total for 7242 Life and Dental Insurance | J56: 235.2
A57: 7244 Employee Contrib - Health
B58: 01/31/2020 | C58: Journal Entry | D58: 213 | G58: 451 USJP Program | H58: Employee Medical Contrib | I58: -Split- | J58: -661.17 | K58: -661.17
A59: Total for 7244 Employee Contrib - Health | J59: -661.17
A60: 7247 Emp-ee Contrib -Dental
B61: 01/31/2020 | C61: Journal Entry | D61: 214 | G61: 451 USJP Program | H61: Employee Dental Contrib | I61: -Split- | J61: -43.56 | K61: -43.56
A62: Total for 7247 Emp-ee Contrib -Dental | J62: -43.56
A63: Total for 7240 Employee Benefits | J63: 3111.73
A64: 7250 Payroll Taxes, etc.
A65: 7245 Worker's Compensation Insurance
A66: 7248 Allocated W Comp
B67: 01/31/2020 | C67: Journal Entry | D67: 233 | G67: 451 USJP Program | H67: Workers Comp Alloc | I67: -Split- | J67: 479 | K67: 479
A68: Total for 7248 Allocated W Comp | J68: 479
A69: Total for 7245 Worker's Compensation Insurance | J69: 479
A70: 7251 Social Security
B71: 01/30/2020 | C71: Journal Entry | D71: 229 | G71: 451 USJP Program | H71: Fica | I71: -Split- | J71: 0 | K71: 0
B72: 01/30/2020 | C72: Journal Entry | D72: 229 | G72: 451 USJP Program | H72: Fica | I72: -Split- | J72: 1075 | K72: 1075
A73: Total for 7251 Social Security | J73: 1075
A74: 7252 Medicare
B75: 01/30/2020 | C75: Journal Entry | D75: 230 | G75: 451 USJP Program | H75: Medi Alloc | I75: -Split- | J75: 251 | K75: 251
B76: 01/30/2020 | C76: Journal Entry | D76: 230 | G76: 451 USJP Program | H76: Medi Alloc | I76: -Split- | J76: 0 | K76: 251
A77: Total for 7252 Medicare | J77: 251
A78: 7253 Unemployment
B79: 01/31/2020 | C79: Journal Entry | D79: 232 | G79: 451 USJP Program | H79: SUI Alloc | I79: -Split- | J79: 0 | K79: 0
B80: 01/31/2020 | C80: Journal Entry | D80: 232 | G80: 451 USJP Program | H80: SUI Alloc | I80: -Split- | J80: 499 | K80: 499
A81: Total for 7253 Unemployment | J81: 499
A82: 7254 Disability
B83: 01/30/2020 | C83: Journal Entry | D83: 228 | G83: 451 USJP Program | H83: Disability Alloc | I83: -Split- | J83: 0 | K83: 0
B84: 01/30/2020 | C84: Journal Entry | D84: 228 | G84: 451 USJP Program | H84: Disability Alloc | I84: -Split- | J84: 98 | K84: 98
A85: Total for 7254 Disability | J85: 98
A86: Total for 7250 Payroll Taxes, etc. | J86: 2402
A87: 7260 Payroll Service Fees
A88: 7260.1 Allocated Payroll Fees
B89: 01/30/2020 | C89: Journal Entry | D89: 231 | G89: 451 USJP Program | H89: Payroll Fees | I89: -Split- | J89: 0 | K89: 0
B90: 01/30/2020 | C90: Journal Entry | D90: 231 | G90: 451 USJP Program | H90: Payroll Fees | I90: -Split- | J90: 249 | K90: 249
A91: Total for 7260.1 Allocated Payroll Fees | J91: 249
A92: Total for 7260 Payroll Service Fees | J92: 249
A93: Total for 7200 Salaries & Related Expenses | J93: 23587.73
A94: 7500 Contract Service Expenses
A95: 7515 IT Support
A96: 7515.5 Allocated IT consultants
B97: 01/31/2020 | C97: Journal Entry | D97: 235 | G97: 451 USJP Program | H97: IT Consultants | I97: -Split- | J97: 334 | K97: 334
B98: 01/31/2020 | C98: Journal Entry | D98: 235 | G98: 451 USJP Program | H98: IT Consultants | I98: -Split- | J98: 84 | K98: 418
A99: Total for 7515.5 Allocated IT consultants | J99: 418
A100: Total for 7515 IT Support | J100: 418
A101: 7520 Accounting Fees
...

Sheet Jan-FR
A1: National Urban League Financial Report
A2: 1. Funding Agency- National Urban League | I2: 2. Federal Grant Name - Urban Seniors Jobs Program CFDA 17.235 | N2: PY 19
A3: 3. Recipient Organization (Name and complete address including Zip code)
M4: 4. Final Report (mark X) Yes No | N4: 5. Basis of Reporting □ Accrual
A5: 6. Project/Grant Period From: July 1-2019 | H5: To: June 31, 2020 | M5: 7. Reporting Period End Date 1/31/2020
A6: 8. Transactions | M6: Cumulative
A7: Federal Cash:
A8: a. Cash Receipts
A9: b. Cash Disbursements | M9: =M8 -> 0
A10: c. Cash on Hand (line a minus b) | M10: =M8-M9 -> 0
A11: Federal Expenditures and Unobligated Balance:
A12: d. Approved Budget
A13: e. Federal Share of Expenditures -Program Costs | M13: =M9 -> 0
A14: f. Federal Share of Expenditures -Administrative Costs | M14: 0
A15: g. Federal Share of Unliquidated Obligations ( ACCRUALS) | M15: 0
A16: h. Total Federal Obligations (sum of lines e and g) | M16: =M13+M14+M15 -> 0
A17: i. Unobligated Balance of Federal Funds (line d minus h) | M17: =M12-M16 -> 0
A18: Recipient Share: Cost Sharing/ Matching/ In-Kind Costs
A19: j. Total Match and Inkind Required if Applicable | M19: 0
A20: k. Total Receipient share reported if Applicable | M20: 0
A21: l. Remaining Recipient Share to Be Provided (line j minus k) | M21: =M19-M20 -> 0
A22: Program Income:
A23: m. Total Program Income Earned if applicable | M23: 0
A24: n. Program Income Expended in Accordance with the Addition Method | M24: 0
A25: o. Unexpended Program Income (line m minus line n) | M25: =M23-M24 -> 0
A26: 9. Remarks: (Attach any explanations deemed necessary or information required by Federal sponsoring agency in compliance with governing legislation.)
A28: 10. Indirect Expenditures
A29: a. Type of Rate | C29: b. Rate | D29: c. Rate Approval Date | G29: d. Period From (MM/DD/YYYY) | I29: Period To (MM/DD/YYYY) | J29: e. Base | M29: f. Amount Charged | N29: g. Federal Share
A32: 11. Certification: By signing this report, I certify to the best of my knowledge and belief that the report is true, complete, and accurate, and the expenditures, disbursements and cash receipts are for the purposes and objectives set forth in the terms and conditions of the Federal award. I am aware that any false, fictitious, or fraudulent information, or the omission of any material fact, may subject me to criminal, civil or administrative penalties for fraud, false statements, false claims or otherwise. (U.S. Code Title 18, Section 1001 and Title 31, Sections 3729–3730 and 3801–3812).
A33: a. Typed or Printed Name and Title of Authorized Certifying Official | M33: c. Telephone (Area code, number, and extension)
M34: d. Email Address
A35: b. Signature of Authorized Certifying Official | M35: e. Date Report Submitted (MM/DD/YYYY)

Sheet Jan-2020 GL
A1: URBAN LEAGUE OF ESSEX COUNTY
A2: 451 USJP Program Transaction Detail by Account
A3: January 2020
B5: Date | C5: Transaction Type | D5: Num | E5: Name | F5: Memo/Description | G5: Amount | H5: Check #
A6: 7100 Participant Salaries & Wages
A7: 7112 Participant Wages - USJP
B8: 01/13/2020 | C8: Journal Entry | D8: 187 | F8: USJP Participant Wages - 1/13/20 | G8: 47287.5
B9: 01/27/2020 | C9: Journal Entry | D9: 188 | F9: USJP Participant Wages - 1/27/20 | G9: 67080.75
A10: Total for 7112 Participant Wages - USJP | G10: =SUM(G8:G9) -> 114368.25
A11: 7112.1 USJP Manual Checks
B12: 01/13/2020 | C12: Check | D12: 12899 | E12: Reginald Williams | F12: USJP Participant owed 32 hours for training 12/19/19 - 01/01/22. Check Date 01/13/20 not previously paid. | G12: 241.36
B13: 01/17/2020 | C13: Bill | E13: Patricia Borden | F13: Not added on payroll spreadsheet for payment 12.19.19-01.01.20 | G13: 313.17
B14: 01/17/2020 | C14: Check | D14: 12940 | E14: Olivia Wicker | F14: Not included on the payroll spreadsheet 12.19.19 - 01.01.20 | G14: 183.69
B15: 01/30/2020 | C15: Deposit | E15: Paycom Payroll, LLC | F15: Refund for 0K296-USJP Overpayment of Payroll for Manual Checks 20-01-49 | G15: -738.22
A16: Total for 7112.1 USJP Manual Checks | G16: =SUM(G12:G15) -> 0
A18: Total for 7112 Participant Wages - USJP with subs | G18: =+G10+G16 -> 114368.25
A20: 7120 Payroll Taxes
B21: 01/13/2020 | C21: Journal Entry | D21: 187 | F21: USJP Employer Liability | G21: 3637.8
B22: 01/27/2020 | C22: Journal Entry | D22: 188 | F22: USJP Employer Liability | G22: 5131.71
A23: Total for 7120 Payroll Taxes | G23: =SUM(G21:G22) -> 8769.51
A24: 7130 Worker's Compensation - USJP
B25: 01/31/2020 | C25: Journal Entry | D25: 204 | F25: Workers Comp Alloc | G25: 3064
A26: Total for 7130 Worker's Compensation - USJP | G26: =SUM(G25) -> 3064
A27: 7132 Payroll Expenses - Fees
B28: 01/13/2020 | C28: Journal Entry | D28: 187 | F28: USJP Payroll Fee | G28: 465.12
B29: 01/27/2020 | C29: Journal Entry | D29: 188 | F29: USJP Payroll Fee | G29: 2437.69
A30: Total for 7132 Payroll Expenses - Fees | G30: =SUM(G28:G29) -> 2902.81
A31: Total for 7100 Participant Salaries & Wages | G31: =+G18+G23+G26+G30 -> 129104.57
A32: 7200 Salaries & Related Expenses
A33: 7220 Salaries & Wages
A34: 7222 Staff
B35: 01/31/2020 | C35: Journal Entry | D35: 212 | G35: 17825
A36: Total for 7222 Staff | G36: =SUM(G35) -> 17825
A37: Total for 7220 Salaries & Wages | G37: 17825
A42: 7240 Employee Benefits
A43: 7241 Health Insurance
B44: 01/01/2020 | C44: Bill | D44: 293105697 | E44: Horizon Blue Cross Blue Shield of NJ | F44: To record Horizon Exp. Billing Period 01/15/20 - 02/15/20 | G44: 3581.26 | H44: 12878
A45: Total for 7241 Health Insurance | G45: =SUM(G44) -> 3581.26
A46: 7242 Life and Dental Insurance
B47: 01/01/2020 | C47: Bill | D47: 01.01.20PL | E47: Principal Financial Group | F47: Life, Dental & AD&D | G47: 235.2 | H47: 12877
A48: Total for 7242 Life and Dental Insurance | G48: =SUM(G47) -> 235.2
A49: 7244 Employee Contrib - Health
B50: 01/31/2020 | C50: Journal Entry | D50: 213 | F50: Employee Medical Contrib | G50: -661.17
A51: Total for 7244 Employee Contrib - Health | G51: =SUM(G50) -> -661.17
A52: 7247 Emp-ee Contrib -Dental
B53: 01/31/2020 | C53: Journal Entry | D53: 214 | F53: Employee Dental Contrib | G53: -43.56
A54: Total for 7247 Emp-ee Contrib -Dental | G54: =SUM(G53) -> -43.56
A56: Total for 7240 Employee Benefits | G56: =+G45+G48+G51+G54 -> 3111.73
A58: 7245 Worker's Compensation Insurance
A59: 7248 Allocated W Comp
B60: 01/31/2020 | C60: Journal Entry | D60: 204 | F60: Workers Comp Alloc | G60: 479
A61: Total for 7245 Worker's Compensation Insurance | G61: =SUM(G60) -> 479
A63: EMPLOYER TAXES
A64: 7251 Social Security
B65: 01/30/2020 | C65: Journal Entry | D65: 199 | F65: Fica | G65: 1075
A66: Total for 7251 Social Security | G66: =SUM(G65) -> 1075
A67: 7252 Medicare
B68: 01/30/2020 | C68: Journal Entry | D68: 201 | F68: Medi Alloc | G68: 251
A69: Total for 7252 Medicare | G69: =SUM(G68) -> 251
A70: 7253 Unemployment
B71: 01/31/2020 | C71: Journal Entry | D71: 203 | F71: SUI Alloc | G71: 499
A72: Total for 7253 Unemployment | G72: =SUM(G71) -> 499
A73: 7254 Disability
B74: 01/30/2020 | C74: Journal Entry | D74: 198 | F74: Disability Alloc | G74: 98
A75: Total for 7254 Disability | G75: =SUM(G74) -> 98
A77: Total for 7250 Payroll Taxes, etc. | G77: =+G66+G69+G72+G75 -> 1923
A79: 7260 Payroll Service Fees
A80: 7260.1 Allocated Payroll Fees
B81: 01/30/2020 | C81: Journal Entry | D81: 202 | F81: Payroll Fees | G81: 249
A82: Total for 7260.1 Allocated Payroll Fees | G82: =SUM(G81) -> 249
A84: Total for Fringe Benefits | G84: =+G56+G61+G77+G82 -> 5762.73
A86: Total for 7200 Salaries & Related Expenses | G86: =+G36+G56+G61+G77+G82 -> 23587.73
A91: 8300 Travel & Meetings Expenses
A92: 8310 Transportation & Parking
B93: 01/01/2020 | C93: Bill | D93: 11228 | E93: City of Paterson Parking Authority | F93: Parking Permit for Jan. 2020 | G93: 150 | H93: 12936
B94: 01/31/2020 | C94: Bill | D94: 01.31.20GM | E94: Gwendolyn Morris | F94: Mileage Reimbursement 01/01/20 - 01/31/20 | G94: 66.1 | H94: 12959
B95: 01/01/2020 | C95: Bill | D95: 01.01.20IC | E95: Irene Cerna | F95: Mileage Reimbursement - USJP 12/01/2019 - 12/31/2019 | G95: 57.88 | H95: 12960
B96: 01/31/2020 | C96: Bill | D96: 01.31.20IC | E96: Irene Cerna | F96: Mileage Reimbursement - USJP 01/15/20 - 01/29/20 | G96: 28.94 | H96: 12960
B97: 01/01/2020 | C97: Bill | D97: 01.01.20MT | E97: Mary Tanner | F97: Mileage Reimbursement 12/13/2019 | G97: 15.12 | H97: 12958
B98: 01/31/2020 | C98: Bill | D98: 01.31.20MT | E98: Mary Tanner | F98: Mileage Reimbursement 01/10/20 & 01/27/20 | G98: 30.24 | H98: 12958
A99: Total for 8310 Transportation & Parking | G99: =SUM(G93:G98) -> 348.28
A103: 8110 Supplies
A104: 8110 Supplies
B105: 01/03/2020 | C105: Bill | D105: 7303329877-0-1 | E105: Staples Advantage | F105: USJP Supplies | G105: 465.27 | H105: 12933
A106: Total for 8110 Supplies | G106: =SUM(G105) -> 465.27
A107: 8112 Alloc Supplies
B108: 01/31/2020 | C108: Journal Entry | D108: 195 | F108: Supplies Alloc | G108: 275
A109: Total for 8112 Alloc Supplies | G109: =SUM(G108) -> 275
A110: Total for 8110 Supplies with subs | G110: =+G106+G109 -> 740.27
A114: CONTRACTUAL CONSULTANTS
A115: 7520 Accounting Fees
A116: 7521 Allocated Acctg and Audit
B117: 01/31/2020 | C117: Journal Entry | D117: 205 | F117: Allocated Acctg | G117: 544
A118: Total for 7520 Accounting Fees | G118: =SUM(G117) -> 544
A119: 7540 Instructors/Consultants/Subs
B120: 01/17/2020 | C120: Bill | D120: 01.17.20AC | E120: Anthony Clark | F120: Business Development 01/13/20 - 01/17/20 | G120: 900 | H120: 12923
B121: 01/17/2020 | C121: Bill | D121: 01.17.20AC | E121: Anthony Clark | F121: Business Development 01/27/20 - 01/31/20 | G121: 900 | H121: 12976
A122: Total for 7540 Instructors/Consultants/Subs | G122: =SUM(G120:G121) -> 1800
A124: TOTAL FOR CONTRACTUAL CONSULTANTS | G124: =+G118+G122 -> 2344
A127: OCCUPANCY
...

Sheet Feb-2020
A1: Urban Seniors Jobs Program PY 19 | E1: Invoice # 8 | G1: 43862 | I1: %
A2: Urban League of Essex County | I2: Spent
A3: 1. PERSONNEL | E3: TOTAL
C4: ENROLLEE | D4: OPC | E4: MONTHLY | F4: CUMULATIVE | G4: TOTAL | H4: BUDGET
A5: POSITION TITLE | B5: ADMIN | C5: WAGES & FB | D5: PROGRAM | E5: AMOUNT | F5: EXPENSES | G5: BUDGET | H5: REMAINING
A6: COO Patricia Sermon | E6: =SUM(B6:D6) -> 0 | F6: =E6+'Jan-2020'!F6 -> 7884.62 | G6: 16400 | H6: =G6-F6 -> 8515.38 | I6: =F6/G6 -> 0.48076951
A7: Director Gwendolyn Morris | E7: =SUM(B7:D7) -> 0 | F7: =E7+'Jan-2020'!F7 -> 31250 | G7: 66000 | H7: =G7-F7 -> 34750 | I7: =F7/G7 -> 0.47348485
A8: Prog Site Coordinator (Essex) Rahmel Leake | B8: =+'Feb-2020 PL'!$J$38 -> 1538.47 | E8: =SUM(B8:D8) -> 1538.47 | F8: =E8+'Jan-2020'!F8 -> 19230.88 | G8: 40000 | H8: =G8-F8 -> 20769.12 | I8: =F8/G8 -> 0.480772
A9: Prog Site Coordinator (Passaic) Irene Cerna | B9: =+'Feb-2020 PL'!$J$39 -> 1153.85 | C9: =+'Feb-2020 PL'!$J$66 -> 112.68 | E9: =SUM(B9:D9) -> 1266.53 | F9: =E9+'Jan-2020'!F9 -> 14997.46 | G9: 30000 | H9: =G9-F9 -> 15002.54 | I9: =F9/G9 -> 0.49991533
A10: Prog Site Coordinator (Morris) Alberto Almanzar | E10: =SUM(B10:D10) -> 0 | F10: =E10+'Jan-2020'!F10 -> 9315.32 | G10: 21500 | H10: =G10-F10 -> 12184.68 | I10: =F10/G10 -> 0.4332707
A11: Program Assistant Joanna Martinez | E11: =SUM(B11:D11) -> 0 | F11: =E11+'Jan-2020'!F11 -> 13561.63 | G11: 36000 | H11: =G11-F11 -> 22438.37 | I11: =F11/G11 -> 0.37671194
A12: Staff Accountant - TBH | E12: =SUM(B12:D12) -> 0 | F12: =E12+'Jan-2020'!F12 -> 4442.29 | G12: 4000 | H12: =G12-F12 -> -442.29 | I12: =F12/G12 -> 1.1105725
A16: Total Salaries | B16: =SUM(B6:B15) -> 2692.32 | C16: =SUM(C6:C15) -> 112.68 | D16: =SUM(D6:D15) -> 0 | E16: =SUM(E6:E15) -> 2805 | F16: =SUM(F6:F15) -> 100682.2 | G16: =SUM(G6:G15) -> 213900 | H16: =SUM(H6:H15) -> 113217.8 | I16: =F16/G16 -> 0.47069752
A18: Fringe Benefits Rate | E18: =SUM(B18:D18) -> 0 | F18: =E18+'Jan-2020'!F18 -> 38013.62 | G18: 68136 | H18: =G18-F18 -> 30122.38 | I18: =F18/G18 -> 0.55790801
H19: =G19-F19 -> 0
A20: TOTAL PERSONNEL (Salaries + Fringe Benefits) | B20: =B16+B18 -> 2692.32 | C20: =C16+C18 -> 112.68 | D20: =D16+D18 -> 0 | E20: =E16+E18 -> 2805 | F20: =F16+F18 -> 138695.82 | G20: =G16+G18 -> 282036 | H20: =H16+H18 -> 143340.18 | I20: =F20/G20 -> 0.49176637
A22: 2. Non-Personnel Operating Costs
A23: Travel | D23: =+'Feb-2020 PL'!$J$92 -> 165.12 | E23: =SUM(B23:D23) -> 165.12 | F23: =E23+'Jan-2020'!F23 -> 2397.44 | G23: 4000 | H23: =G23-F23 -> 1602.56 | I23: =F23/G23 -> 0.59936
A24: Supplies | E24: =SUM(B24:D24) -> 0 | F24: =E24+'Jan-2020'!F24 -> 3540.36 | G24: 7000 | H24: =G24-F24 -> 3459.64 | I24: =F24/G24 -> 0.50576571
A25: Staff Development | E25: =SUM(B25:D25) -> 0 | F25: =E25+'Jan-2020'!F25 -> 0 | G25: 2000 | H25: =G25-F25 -> 2000 | I25: =F25/G25 -> 0
A26: Contractual/Consultants | B26: =+'Feb-2020 PL'!$J$73 -> 900 | E26: =SUM(B26:D26) -> 900 | F26: =E26+'Jan-2020'!F26 -> 9154.69 | G26: 13200 | H26: =G26-F26 -> 4045.31 | I26: =F26/G26 -> 0.69353712
A27: Occupancy | D27: =+'Feb-2020 PL'!$J$85 -> 648 | E27: =SUM(B27:D27) -> 648 | F27: =E27+'Jan-2020'!F27 -> 8802.27 | G27: 12000 | H27: =G27-F27 -> 3197.73 | I27: =F27/G27 -> 0.7335225
A28: Audit (100% Admin) | E28: =SUM(B28:D28) -> 0 | F28: =E28+'Jan-2020'!F28 -> 1900.29 | G28: 6000 | H28: =G28-F28 -> 4099.71 | I28: =F28/G28 -> 0.316715
A29: Marketing and Outreach | E29: =SUM(B29:D29) -> 0 | F29: =E29+'Jan-2020'!F29 -> 0 | G29: 570 | H29: =G29-F29 -> 570 | I29: =F29/G29 -> 0
A30: Rental Equipment | E30: =SUM(B30:D30) -> 0 | F30: =E30+'Jan-2020'!F30 -> 2131.95 | G30: 6475 | H30: =G30-F30 -> 4343.05 | I30: =F30/G30 -> 0.32925869
A31: Payroll fees | B31: =+'Feb-2020 PL'!$J$31 -> 401.87 | E31: =SUM(B31:D31) -> 401.87 | F31: =E31+'Jan-2020'!F31 -> 9037.77 | G31: 13000 | H31: =G31-F31 -> 3962.23 | I31: =F31/G31 -> 0.69521308
A32: Infrastructure Costs | E32: =SUM(B32:D32) -> 0 | F32: =E32+'Jan-2020'!F32 -> 0 | G32: 1500 | H32: =G32-F32 -> 1500 | I32: =F32/G32 -> 0
A33: Other Operating costs | E33: =SUM(B33:D33) -> 0 | F33: =E33+'Jan-2020'!F33 -> 2280.82 | G33: 3000.7 | H33: =G33-F33 -> 719.88 | I33: =F33/G33 -> 0.76009598
A34: Communications | D34: =+'Feb-2020 PL'!$J$79 -> 135.02 | E34: =SUM(B34:D34) -> 135.02 | F34: =E34+'Jan-2020'!F34 -> 2059.64 | G34: 3000 | H34: =G34-F34 -> 940.36 | I34: =F34/G34 -> 0.68654667
A35: Insurance | E35: =SUM(B35:D35) -> 0 | F35: =E35+'Jan-2020'!F35 -> 3389.72 | G35: 4000 | H35: =G35-F35 -> 610.28 | I35: =F35/G35 -> 0.84743
A36: Postage | E36: =SUM(B36:D36) -> 0 | F36: =E36+'Jan-2020'!F36 -> 136.58 | G36: 1000 | H36: =G36-F36 -> 863.42 | I36: =F36/G36 -> 0.13658
A37: Total NPOC | B37: =SUM(B23:B36) -> 1301.87 | C37: =SUM(C23:C36) -> 0 | D37: =SUM(D23:D36) -> 948.14 | E37: =SUM(E23:E36) -> 2250.01 | F37: =SUM(F23:F36) -> 44831.53 | G37: =SUM(G23:G36) -> 76745.7 | H37: =SUM(H23:H36) -> 31914.17 | I37: =F37/G37 -> 0.5841569
A40: 3. Participant Costs
A41: Participant Wages | C41: =+'Feb-2020 PL'!$J$21 -> 62739.9 | E41: =SUM(B41:D41) -> 62739.9 | F41: =E41+'Jan-2020'!F41 -> 769325.62 | G41: 1452829.2 | H41: =G41-F41-F42 -> 681510.48 | I41: =F41/G41 -> 0.52953616
A42: Reimbursable Participant Wage(Paid by Affiliate) | C42: =+'Feb-2020 PL'!$J$24 -> 150.07 | E42: =SUM(B42:D42) -> 150.07 | F42: =+E42+'Jan-2020'!F42 -> 1993.14 | I42: =F42/G42 -> #DIV/0!
A43: Participant Specialized Training Wage | E43: =SUM(B43:D43) -> 0 | F43: =E43+'Jan-2020'!F43 -> 0 | G43: 12820 | H43: =G43-F43 -> 12820 | I43: =F43/G43 -> 0
A44: Participant FICA and other taxes | C44: =+'Feb-2020 PL'!$J$28 -> 4799.28 | E44: =SUM(B44:D44) -> 4799.28 | F44: =E44+'Jan-2020'!F44 -> 56707.86 | G44: 111141.44 | H44: =G44-F44 -> 54433.58 | I44: =F44/G44 -> 0.51023147
A45: Workers compensation | E45: =SUM(B45:D45) -> 0 | F45: =E45+'Jan-2020'!F45 -> 18833.48 | G45: 22373.57 | H45: =G45-F45 -> 3540.09 | I45: =F45/G45 -> 0.84177357
A46: Support Services | E46: =SUM(B46:D46) -> 0 | F46: =E46+'Jan-2020'!F46 -> 0 | G46: 8500 | H46: =G46-F46 -> 8500 | I46: =F46/G46 -> 0
A47: Specialized Training vendor | E47: =SUM(B47:D47) -> 0 | F47: =E47+'Jan-2020'!F47 -> 0 | G47: 29630 | H47: =G47-F47 -> 29630 | I47: =F47/G47 -> 0
A48: Total Participant Costs | B48: =SUM(B41:B47) -> 0 | C48: =SUM(C41:C47) -> 67689.25 | D48: =SUM(D41:D47) -> 0 | E48: =SUM(E41:E47) -> 67689.25 | F48: =SUM(F41:F47) -> 846860.1 | G48: =SUM(G41:G47) -> 1637294.2 | H48: =SUM(H41:H47) -> 790434.15 | I48: =F48/G48 -> 0.51723146
A50: 4. Indirect ('%) | B50: 0 | E50: =B50 -> 0 | F50: =E50+'Jan-2020'!F50 -> 0 | G50: 17532.59 | H50: =G50-F50 -> 17532.59 | I50: =F50/G50 -> 0
A52: 5.Total Federal Expenses | B52: =B20+B37+B48+B50 -> 3994.19 | C52: =C20+C37+C48 -> 67801.93 | D52: =D20+D37+D48 -> 948.14 | E52: =E37+E20+E48+E50 -> 72744.26 | F52: =F37+F20+F48+F50 -> 1030387.5 | G52: =G37+G20+G48+G50 -> 2013608.5 | H52: =H37+H20+H48+H50 -> 983221.09 | I52: =F52/G52 -> 0.5117119
A54: 6. Non Federal Match | F54: =E54+'Jan-2020'!F54 -> 76400 | G54: 242467.32 | H54: =G54-F54 -> 166067.32 | I54: =F54/G54 -> 0.31509401
A56: 7. Total Expenses | B56: =B52+B54 -> 3994.19 | C56: =C52+C54 -> 67801.93 | D56: =D52+D54 -> 948.14 | E56: =E52+E54 -> 72744.26 | F56: =F52+F54 -> 1106787.5 | G56: =G52+G54 -> 2256075.9 | H56: =H52+H54 -> 1149288.4 | I56: =F56/G56 -> 0.49058078
F57: AFFILIATES- ENTER NOTES TO THIS INVOICE HERE
A58: 8. Total Reimbursable expenses | E58: =+E20+E37-E31+E42+E45+E46+E47+E50 -> 4803.21
A60: FOR NUL USE ONLY
A62: TOTAL INVOICE SUBMITTED | E62: =E58 -> 4803.21
A65: COSTS DISALLOWED
A68: OTHER ADJUSTMENTS
A71: CASH DUE TO/DUE FROM AFFILIATE
A73: SIGNATURE AND DATE:
A78: Fiscal Manager | B78: Date | F78: Affiliate CEO | H78: Date
A82: Project Director | B82: Date | F82: Vice President, Workforce Development (NUL) | H82: Date

Sheet Feb-2020 PL
A1: URBAN LEAGUE OF ESSEX COUNTY
A2: Profit and Loss Detail
A3: February 1 - July 1, 2020
B5: Date | C5: Transaction Type | D5: Num | E5: Name | F5: Location | G5: Class | H5: Memo/Description | I5: Split | J5: Amount | K5: Balance
A6: Ordinary Income/Expenses
A7: Income
A8: 4500 Revenue from Government Grants
A9: 4520 Federal Grants
A10: 4521.1 USJP - Payroll Reimb
B11: 02/10/2020 | C11: Journal Entry | D11: 189 | G11: 451 USJP Program | H11: USJP Participant Payroll | I11: -Split- | J11: 0 | K11: 0
B12: 02/10/2020 | C12: Journal Entry | D12: 189 | G12: 451 USJP Program | H12: USJP Participant Payroll | I12: -Split- | J12: 67941.05 | K12: 67941.05
A13: Total for 4521.1 USJP - Payroll Reimb | J13: 67941.05
A14: Total for 4520 Federal Grants | J14: 67941.05
A15: Total for 4500 Revenue from Government Grants | J15: 67941.05
A16: Total for Income | J16: 67941.05
A17: Expenses
A18: 7100 Participant Salaries & Wages
A19: 7112 Participant Wages - USJP
B20: 02/10/2020 | C20: Journal Entry | D20: 189 | G20: 451 USJP Program | H20: USJP Participant Wages - 2/10/20 | I20: -Split- | J20: 62739.9 | K20: 62739.9
A21: Total for 7112 Participant Wages - USJP | J21: 62739.9
A22: 7112.1 USJP Manual Checks
B23: 02/12/2020 | C23: Bill | D23: 02.12.20DO | E23: Deborah Ore | G23: 451 USJP Program | H23: Net Pay for Retroactive increase for January 1 - February 12, 2020 from $11 per hour to $12.10 per hour | I23: 2000 Accounts Payable | J23: 150.07 | K23: 150.07
A24: Total for 7112.1 USJP Manual Checks | J24: 150.07
A25: Total for 7112 Participant Wages - USJP with sub-accounts | J25: 62889.97
A26: 7120 Payroll Taxes
B27: 02/10/2020 | C27: Journal Entry | D27: 189 | G27: 451 USJP Program | H27: USJP Employer Liability | I27: -Split- | J27: 4799.28 | K27: 4799.28
A28: Total for 7120 Payroll Taxes | J28: 4799.28
A29: 7132 Payroll Expenses - Fees
B30: 02/10/2020 | C30: Journal Entry | D30: 189 | G30: 451 USJP Program | H30: USJP Payroll Fee | I30: -Split- | J30: 401.87 | K30: 401.87
A31: Total for 7132 Payroll Expenses - Fees | J31: 401.87
A32: Total for 7100 Participant Salaries & Wages | J32: 68091.12
A33: 7200 Salaries & Related Expenses
A34: 7220 Salaries & Wages
B35: 06/01/2020 | C35: Journal Entry | D35: 259 | G35: 451 USJP Program | H35: WARD, RICHARD G Payroll 6/1/2020 | I35: -Split- | J35: 0 | K35: 0
B36: 06/01/2020 | C36: Journal Entry | D36: 259 | G36: 451 USJP Program | H36: MORRIS, GWENDOLYN J Payroll 6/1/2020 | I36: -Split- | J36: 2500 | K36: 2500
B37: 06/01/2020 | C37: Journal Entry | D37: 259 | G37: 451 USJP Program | H37: JANVIER, JHONNY Payroll 6/1/2020 | I37: -Split- | J37: 2361.16 | K37: 4861.16
B38: 06/01/2020 | C38: Journal Entry | D38: 259 | G38: 451 USJP Program | H38: LEAKE, RAHMEL Payroll 6/1/2020 | I38: -Split- | J38: 1538.47 | K38: 6399.63
B39: 06/01/2020 | C39: Journal Entry | D39: 259 | G39: 451 USJP Program | H39: CERNA, IRENE Payroll 6/1/2020 | I39: -Split- | J39: 1153.85 | K39: 7553.48
B40: 06/01/2020 | C40: Journal Entry | D40: 259 | G40: 451 USJP Program | H40: SERMON, PATRICIA Payroll 6/1/2020 | I40: -Split- | J40: 630.77 | K40: 8184.25
A41: Total for 7220 Salaries & Wages | J41: 8184.25
A42: 7240 Employee Benefits
A43: 7241 Health Insurance
B44: 02/01/2020 | C44: Bill | D44: 293308978 | E44: Horizon Blue Cross Blue Shield of NJ | G44: 451 USJP Program | H44: To record Horizon Exp. Billing Period 02/15/20 - 03/15/20 | I44: 2000 Accounts Payable | J44: 3688.1 | K44: 3688.1
B45: 03/01/2020 | C45: Bill | E45: Horizon Blue Cross Blue Shield of NJ | G45: 451 USJP Program | H45: To record Horizon Exp. Billing Period 03/15/20 - 04/15/20 | I45: 2000 Accounts Payable | J45: 3581.26 | K45: 7269.36
A46: Total for 7241 Health Insurance | J46: 7269.36
A47: 7242 Life and Dental Insurance
B48: 02/01/2020 | C48: Bill | D48: 02.01.20PL | E48: Principal Financial Group | G48: 451 USJP Program | H48: Life, Dental & AD&D | I48: 2000 Accounts Payable | J48: 241.2 | K48: 241.2
B49: 03/01/2020 | C49: Bill | D49: 03.01.20PL | E49: Principal Financial Group | G49: 451 USJP Program | H49: Life, Dental & AD&D | I49: 2000 Accounts Payable | J49: 241.2 | K49: 482.4
A50: Total for 7242 Life and Dental Insurance | J50: 482.4
A51: Total for 7240 Employee Benefits | J51: 7751.76
A52: 7250 Payroll Taxes, etc.
A53: 7245 Worker's Compensation Insurance
A54: 7248 Allocated W Comp
B55: 02/28/2020 | C55: Journal Entry | D55: 248 | G55: 451 USJP Program | H55: Workers Comp Alloc | I55: -Split- | J55: 3064 | K55: 3064
B56: 02/28/2020 | C56: Journal Entry | D56: 248 | G56: 451 USJP Program | H56: Workers Comp Alloc | I56: -Split- | J56: 479 | K56: 3543
B57: 04/01/2020 | C57: Journal Entry | D57: 250 | G57: 451 USJP Program | H57: Workers Comp Alloc | I57: -Split- | J57: 479 | K57: 4022
A58: Total for 7248 Allocated W Comp | J58: 4022
A59: Total for 7245 Worker's Compensation Insurance | J59: 4022
A60: 7251 Social Security
B61: 06/01/2020 | C61: Journal Entry | D61: 259 | G61: 451 USJP Program | H61: LEAKE, RAHMEL Payroll 6/1/2020 | I61: -Split- | J61: 160.76 | K61: 160.76
B62: 06/01/2020 | C62: Journal Entry | D62: 259 | G62: 451 USJP Program | H62: WARD, RICHARD G Payroll 6/1/2020 | I62: -Split- | J62: 0 | K62: 160.76
B63: 06/01/2020 | C63: Journal Entry | D63: 259 | G63: 451 USJP Program | H63: MORRIS, GWENDOLYN J Payroll 6/1/2020 | I63: -Split- | J63: 183.56 | K63: 344.32
B64: 06/01/2020 | C64: Journal Entry | D64: 259 | G64: 451 USJP Program | H64: JANVIER, JHONNY Payroll 6/1/2020 | I64: -Split- | J64: 241.87 | K64: 586.19
B65: 06/01/2020 | C65: Journal Entry | D65: 259 | G65: 451 USJP Program | H65: SERMON, PATRICIA Payroll 6/1/2020 | I65: -Split- | J65: 46.62 | K65: 632.81
B66: 06/01/2020 | C66: Journal Entry | D66: 259 | G66: 451 USJP Program | H66: CERNA, IRENE Payroll 6/1/2020 | I66: -Split- | J66: 112.68 | K66: 745.49
A67: Total for 7251 Social Security | J67: 745.49
A68: Total for 7250 Payroll Taxes, etc. | J68: 4767.49
A69: Total for 7200 Salaries & Related Expenses | J69: 20703.5
A70: 7500 Contract Service Expenses
A71: 7540 Instructors/Consultants/Subs
B72: 02/21/2020 | C72: Bill | D72: 02.21.20AC | E72: Anthony Clark | F72: 506 Central Ave | G72: 451 USJP Program | H72: Business Development 02/17/20 - 02/21/20 | I72: 2000 Accounts Payable | J72: 900 | K72: 900
A73: Total for 7540 Instructors/Consultants/Subs | J73: 900
A74: Total for 7500 Contract Service Expenses | J74: 900
A75: 8100 Operating Expenses
A76: 8130 Telephone & Telecommunications
A77: 8132 Cell Phone Services
B78: 02/13/2020 | C78: Bill | D78: 9848349443 | E78: Verizon Wireless | G78: 451 USJP Program | H78: Monthly Hotspot Data | I78: 2000 Accounts Payable | J78: 135.02 | K78: 135.02
A79: Total for 8132 Cell Phone Services | J79: 135.02
A80: Total for 8130 Telephone & Telecommunications | J80: 135.02
A81: Total for 8100 Operating Expenses | J81: 135.02
A82: 8200 Facility & Equipment Expenses
A83: 8205 Rent, Parking, Other Occupancy
B84: 02/01/2020 | C84: Bill | E84: Center for Transformative Work | G84: 451 USJP Program | H84: USJP - Rent Expense February 2020 | I84: 2000 Accounts Payable | J84: 648 | K84: 648
A85: Total for 8205 Rent, Parking, Other Occupancy | J85: 648
A86: Total for 8200 Facility & Equipment Expenses | J86: 648
A87: 8300 Travel & Meetings Expenses
A88: 8310 Transportation & Parking
B89: 02/12/2020 | C89: Bill | D89: 02.10.20MT | E89: Mary Tanner | F89: 508 Central Avenue | G89: 451 USJP Program | H89: Mileage Reimbursement 02/10/2020 | I89: 2000 Accounts Payable | J89: 15.12 | K89: 15.12
B90: 02/13/2020 | C90: Bill | E90: City of Paterson Parking Authority | G90: 451 USJP Program | H90: Parking Permit for Feb. 2020 | I90: 2000 Accounts Payable | J90: 150 | K90: 165.12
A91: Total for 8310 Transportation & Parking | J91: 165.12
A92: Total for 8300 Travel & Meetings Expenses | J92: 165.12
A93: 8400 Other Client Specific Expenses
A94: 8430 Job Training
B95: 02/26/2020 | C95: Bill | D95: 9613 | E95: NJ Guard Training | F95: 508 Central Avenue | G95: 451 USJP Program | H95: Specialized Training for SORA License USJP Participants 03/04/20 - 03/05/20 | I95: 2000 Accounts Payable | J95: 780 | K95: 780
A96: Total for 8430 Job Training | J96: 780
A97: Total for 8400 Other Client Specific Expenses | J97: 780
A98: Total for Expenses | J98: 91422.76
A99: Net Income | J99: -23481.71
A102: Monday, Mar 02, 2020 12:14:07 PM GMT-8 - Accrual Basis

Sheet Feb-FR
A1: National Urban League Financial Report
A2: 1. Funding Agency- National Urban League | I2: 2. Federal Grant Name - Urban Seniors Jobs Program CFDA 17.235 | N2: PY 19
A3: 3. Recipient Organization (Name and complete address including Zip code)
M4: 4. Final Report (mark X) Yes No | N4: 5. Basis of Reporting □ Accrual
A5: 6. Project/Grant Period From: July 1-2019 | H5: To: June 31, 2020 | M5: 7. Reporting Period End Date 2/28/2020
A6: 8. Transactions | M6: Cumulative
A7: Federal Cash:
A8: a. Cash Receipts
A9: b. Cash Disbursements | M9: =M8 -> 0
A10: c. Cash on Hand (line a minus b) | M10: =M8-M9 -> 0
A11: Federal Expenditures and Unobligated Balance:
A12: d. Approved Budget
A13: e. Federal Share of Expenditures -Program Costs | M13: =M9 -> 0
A14: f. Federal Share of Expenditures -Administrative Costs | M14: 0
A15: g. Federal Share of Unliquidated Obligations ( ACCRUALS) | M15: 0
A16: h. Total Federal Obligations (sum of lines e and g) | M16: =M13+M14+M15 -> 0
A17: i. Unobligated Balance of Federal Funds (line d minus h) | M17: =M12-M16 -> 0
A18: Recipient Share: Cost Sharing/ Matching/ In-Kind Costs
A19: j. Total Match and Inkind Required if Applicable | M19: 0
A20: k. Total Receipient share reported if Applicable | M20: 0
A21: l. Remaining Recipient Share to Be Provided (line j minus k) | M21: =M19-M20 -> 0
A22: Program Income:
A23: m. Total Program Income Earned if applicable | M23: 0
A24: n. Program Income Expended in Accordance with the Addition Method | M24: 0
A25: o. Unexpended Program Income (line m minus line n) | M25: =M23-M24 -> 0
A26: 9. Remarks: (Attach any explanations deemed necessary or information required by Federal sponsoring agency in compliance with governing legislation.)
A28: 10. Indirect Expenditures
A29: a. Type of Rate | C29: b. Rate | D29: c. Rate Approval Date | G29: d. Period From (MM/DD/YYYY) | I29: Period To (MM/DD/YYYY) | J29: e. Base | M29: f. Amount Charged | N29: g. Federal Share
A32: 11. Certification: By signing this report, I certify to the best of my knowledge and belief that the report is true, complete, and accurate, and the expenditures, disbursements and cash receipts are for the purposes and objectives set forth in the terms and conditions of the Federal award. I am aware that any false, fictitious, or fraudulent information, or the omission of any material fact, may subject me to criminal, civil or administrative penalties for fraud, false statements, false claims or otherwise. (U.S. Code Title 18, Section 1001 and Title 31, Sections 3729–3730 and 3801–3812).
A33: a. Typed or Printed Name and Title of Authorized Certifying Official | M33: c. Telephone (Area code, number, and extension)
M34: d. Email Address
A35: b. Signature of Authorized Certifying Official | M35: e. Date Report Submitted (MM/DD/YYYY)

Sheet Mar-2020
A1: Urban Seniors Jobs Program PY 19 | E1: Invoice # 9 | G1: 43891 | I1: %
A2: Urban League of Essex County | I2: Spent
A3: 1. PERSONNEL | E3: TOTAL
C4: ENROLLEE | D4: OPC | E4: MONTHLY | F4: CUMULATIVE | G4: TOTAL | H4: BUDGET
A5: POSITION TITLE | B5: ADMIN | C5: WAGES & FB | D5: PROGRAM | E5: AMOUNT | F5: EXPENSES | G5: BUDGET | H5: REMAINING
A6: COO Patricia Sermon | E6: =SUM(B6:D6) -> 0 | F6: =E6+'Feb-2020'!F6 -> 7884.62 | G6: 16400 | H6: =G6-F6 -> 8515.38 | I6: =F6/G6 -> 0.48076951
A7: Director Gwendolyn Morris | E7: =SUM(B7:D7) -> 0 | F7: =E7+'Feb-2020'!F7 -> 31250 | G7: 66000 | H7: =G7-F7 -> 34750 | I7: =F7/G7 -> 0.47348485
A8: Prog Site Coordinator (Essex) Rahmel Leake | E8: =SUM(B8:D8) -> 0 | F8: =E8+'Feb-2020'!F8 -> 19230.88 | G8: 40000 | H8: =G8-F8 -> 20769.12 | I8: =F8/G8 -> 0.480772
A9: Prog Site Coordinator (Passaic) Irene Cerna | E9: =SUM(B9:D9) -> 0 | F9: =E9+'Feb-2020'!F9 -> 14997.46 | G9: 30000 | H9: =G9-F9 -> 15002.54 | I9: =F9/G9 -> 0.49991533
A10: Prog Site Coordinator (Morris) Alberto Almanzar | E10: =SUM(B10:D10) -> 0 | F10: =E10+'Feb-2020'!F10 -> 9315.32 | G10: 21500 | H10: =G10-F10 -> 12184.68 | I10: =F10/G10 -> 0.4332707
A11: Program Assistant Joanna Martinez | E11: =SUM(B11:D11) -> 0 | F11: =E11+'Feb-2020'!F11 -> 13561.63 | G11: 36000 | H11: =G11-F11 -> 22438.37 | I11: =F11/G11 -> 0.37671194
A12: Staff Accountant - TBH | E12: =SUM(B12:D12) -> 0 | F12: =E12+'Feb-2020'!F12 -> 4442.29 | G12: 4000 | H12: =G12-F12 -> -442.29 | I12: =F12/G12 -> 1.1105725
A16: Total Salaries | B16: =SUM(B6:B15) -> 0 | C16: =SUM(C6:C15) -> 0 | D16: =SUM(D6:D15) -> 0 | E16: =SUM(E6:E15) -> 0 | F16: =SUM(F6:F15) -> 100682.2 | G16: =SUM(G6:G15) -> 213900 | H16: =SUM(H6:H15) -> 113217.8 | I16: =F16/G16 -> 0.47069752
A18: Fringe Benefits Rate | E18: =SUM(B18:D18) -> 0 | F18: =E18+'Feb-2020'!F18 -> 38013.62 | G18: 68136 | H18: =G18-F18 -> 30122.38 | I18: =F18/G18 -> 0.55790801
H19: =G19-F19 -> 0
A20: TOTAL PERSONNEL (Salaries + Fringe Benefits) | B20: =B16+B18 -> 0 | C20: =C16+C18 -> 0 | D20: =D16+D18 -> 0 | E20: =E16+E18 -> 0 | F20: =F16+F18 -> 138695.82 | G20: =G16+G18 -> 282036 | H20: =H16+H18 -> 143340.18 | I20: =F20/G20 -> 0.49176637
A22: 2. Non-Personnel Operating Costs
A23: Travel | E23: =SUM(B23:D23) -> 0 | F23: =E23+'Feb-2020'!F23 -> 2397.44 | G23: 4000 | H23: =G23-F23 -> 1602.56 | I23: =F23/G23 -> 0.59936
A24: Supplies | E24: =SUM(B24:D24) -> 0 | F24: =E24+'Feb-2020'!F24 -> 3540.36 | G24: 7000 | H24: =G24-F24 -> 3459.64 | I24: =F24/G24 -> 0.50576571
A25: Staff Development | E25: =SUM(B25:D25) -> 0 | F25: =E25+'Feb-2020'!F25 -> 0 | G25: 2000 | H25: =G25-F25 -> 2000 | I25: =F25/G25 -> 0
A26: Contractual/Consultants | E26: =SUM(B26:D26) -> 0 | F26: =E26+'Feb-2020'!F26 -> 9154.69 | G26: 13200 | H26: =G26-F26 -> 4045.31 | I26: =F26/G26 -> 0.69353712
A27: Occupancy | E27: =SUM(B27:D27) -> 0 | F27: =E27+'Feb-2020'!F27 -> 8802.27 | G27: 12000 | H27: =G27-F27 -> 3197.73 | I27: =F27/G27 -> 0.7335225
A28: Audit (100% Admin) | E28: =SUM(B28:D28) -> 0 | F28: =E28+'Feb-2020'!F28 -> 1900.29 | G28: 6000 | H28: =G28-F28 -> 4099.71 | I28: =F28/G28 -> 0.316715
A29: Marketing and Outreach | E29: =SUM(B29:D29) -> 0 | F29: =E29+'Feb-2020'!F29 -> 0 | G29: 570 | H29: =G29-F29 -> 570 | I29: =F29/G29 -> 0
A30: Rental Equipment | E30: =SUM(B30:D30) -> 0 | F30: =E30+'Feb-2020'!F30 -> 2131.95 | G30: 6475 | H30: =G30-F30 -> 4343.05 | I30: =F30/G30 -> 0.32925869
A31: Payroll fees | E31: =SUM(B31:D31) -> 0 | F31: =E31+'Feb-2020'!F31 -> 9037.77 | G31: 13000 | H31: =G31-F31 -> 3962.23 | I31: =F31/G31 -> 0.69521308
A32: Infrastructure Costs | E32: =SUM(B32:D32) -> 0 | F32: =E32+'Feb-2020'!F32 -> 0 | G32: 1500 | H32: =G32-F32 -> 1500 | I32: =F32/G32 -> 0
A33: Other Operating costs | E33: =SUM(B33:D33) -> 0 | F33: =E33+'Feb-2020'!F33 -> 2280.82 | G33: 3000.7 | H33: =G33-F33 -> 719.88 | I33: =F33/G33 -> 0.76009598
A34: Communications | E34: =SUM(B34:D34) -> 0 | F34: =E34+'Feb-2020'!F34 -> 2059.64 | G34: 3000 | H34: =G34-F34 -> 940.36 | I34: =F34/G34 -> 0.68654667
... A36: Postage | E36: =SUM(B36:D36) -> 0 | F36: =E36+'Feb-2020'!F36 -> 136.58 | G36: 1000 | H36: =G36-F36 -> 863.42 | I36: =F36/G36 -> 0.13658
A37: Total NPOC | B37: =SUM(B23:B36) -> 0 | C37: =SUM(C23:C36) -> 0 | D37: =SUM(D23:D36) -> 0 | E37: =SUM(E23:E36) -> 0 | F37: =SUM(F23:F36) -> 44831.53 | G37: =SUM(G23:G36) -> 76745.7 | H37: =SUM(H23:H36) -> 31914.17 | I37: =F37/G37 -> 0.5841569
A40: 3. Participant Costs
A41: Participant Wages | E41: =SUM(B41:D41) -> 0 | F41: =E41+'Feb-2020'!F41 -> 769325.62 | G41: 1452829.2 | H41: =G41-F41-F42 -> 681510.48 | I41: =F41/G41 -> 0.52953616
A42: Reimbursable Participant Wage(Paid by Affiliate) | E42: =SUM(B42:D42) -> 0 | F42: =+E42+'Feb-2020'!F42 -> 1993.14 | I42: =F42/G42 -> #DIV/0!
A43: Participant Specialized Training Wage | E43: =SUM(B43:D43) -> 0 | F43: =E43+'Feb-2020'!F43 -> 0 | G43: 12820 | H43: =G43-F43 -> 12820 | I43: =F43/G43 -> 0
A44: Participant FICA and other taxes | E44: =SUM(B44:D44) -> 0 | F44: =E44+'Feb-2020'!F44 -> 56707.86 | G44: 111141.44 | H44: =G44-F44 -> 54433.58 | I44: =F44/G44 -> 0.51023147
A45: Workers compensation | E45: =SUM(B45:D45) -> 0 | F45: =E45+'Feb-2020'!F45 -> 18833.48 | G45: 22373.57 | H45: =G45-F45 -> 3540.09 | I45: =F45/G45 -> 0.84177357
A46: Support Services | E46: =SUM(B46:D46) -> 0 | F46: =E46+'Feb-2020'!F46 -> 0 | G46: 8500 | H46: =G46-F46 -> 8500 | I46: =F46/G46 -> 0
A47: Specialized Training vendor | E47: =SUM(B47:D47) -> 0 | F47: =E47+'Feb-2020'!F47 -> 0 | G47: 29630 | H47: =G47-F47 -> 29630 | I47: =F47/G47 -> 0
A48: Total Participant Costs | B48: =SUM(B41:B47) -> 0 | C48: =SUM(C41:C47) -> 0 | D48: =SUM(D41:D47) -> 0 | E48: =SUM(E41:E47) -> 0 | F48: =SUM(F41:F47) -> 846860.1 | G48: =SUM(G41:G47) -> 1637294.2 | H48: =SUM(H41:H47) -> 790434.15 | I48: =F48/G48 -> 0.51723146
A50: 4. Indirect ('%) | B50: 0 | E50: =B50 -> 0 | F50: =E50+'Feb-2020'!F50 -> 0 | G50: 17532.59 | H50: =G50-F50 -> 17532.59 | I50: =F50/G50 -> 0
A52: 5.Total Federal Expenses | B52: =B20+B37+B48+B50 -> 0 | C52: =C20+C37+C48 -> 0 | D52: =D20+D37+D48 -> 0 | E52: =E37+E20+E48+E50 -> 0 | F52: =F37+F20+F48+F50 -> 1030387.5 | G52: =G37+G20+G48+G50 -> 2013608.5 | H52: =H37+H20+H48+H50 -> 983221.09 | I52: =F52/G52 -> 0.5117119
A54: 6. Non Federal Match | E54: 0 | F54: =E54+'Feb-2020'!F54 -> 76400 | G54: 242467.32 | H54: =G54-F54 -> 166067.32 | I54: =F54/G54 -> 0.31509401
A56: 7. Total Expenses | B56: =B52+B54 -> 0 | C56: =C52+C54 -> 0 | D56: =D52+D54 -> 0 | E56: =E52+E54 -> 0 | F56: =F52+F54 -> 1106787.5 | G56: =G52+G54 -> 2256075.9 | H56: =H52+H54 -> 1149288.4 | I56: =F56/G56 -> 0.49058078
F57: AFFILIATES- ENTER NOTES TO THIS INVOICE HERE
A58: 8. Total Reimbursable expenses | E58: =+E20+E37-E31+E42+E45+E46+E47+E50 -> 0
A60: FOR NUL USE ONLY
A62: TOTAL INVOICE SUBMITTED | E62: =E58 -> 0
A65: COSTS DISALLOWED
A68: OTHER ADJUSTMENTS
A71: CASH DUE TO/DUE FROM AFFILIATE
A73: SIGNATURE AND DATE:
A78: Fiscal Manager | B78: Date | F78: Affiliate CEO | H78: Date
A82: Project Director | B82: Date | F82: Vice President, Workforce Development (NUL) | H82: Date

Sheet Mar-2020 PL
A1: URBAN LEAGUE OF ESSEX COUNTY
A2: Profit and Loss Detail
A3: March 2020
B5: Date | C5: Transaction Type | D5: Num | E5: Name | F5: Location | G5: Class | H5: Memo/Description | I5: Split | J5: Amount | K5: Balance
A6: Ordinary Income/Expenses
A7: Expenses
A8: 7100 Participant Salaries & Wages
A9: 7112 Participant Wages - USJP
A10: 7112.1 USJP Manual Checks
B11: 03/01/2020 | C11: Bill | D11: 03.01.20DO | E11: Deborah Ore | G11: 451 USJP Program | H11: Net Pay for Retroactive increase for January 1 - February 12, 2020 from $11 per hour to $12.10 per hour | I11: 2000 Accounts Payable | J11: 150.07 | K11: 150.07
B12: 03/12/2020 | C12: Deposit | E12: Paycom Payroll, LLC | G12: 451 USJP Program | H12: Overpayment for check issued to Ms. Deborah Ore on 03/01/20 20-03-25 | I12: 1010 Cash:Checking Active:Bank of America:BOA Operating Acct 3973 | J12: -150.07 | K12: 0
A13: Total for 7112.1 USJP Manual Checks | J13: 0
A14: Total for 7112 Participant Wages - USJP | J14: 0
A15: Total for 7100 Participant Salaries & Wages | J15: 0
A16: 7200 Salaries & Related Expenses
A17: 7220 Salaries & Wages
A18: 7221 Directors
A19: 7221c Director of Operations COO
B20: 03/06/2020 | C20: Journal Entry | D20: 312 | G20: 451 USJP Program | H20: SERMON, PATRICIA Payroll Period 02/16/20 � 02/29/20 | I20: -Split- | J20: 19.78 | K20: 19.78
B21: 03/06/2020 | C21: Journal Entry | D21: 312 | G21: 451 USJP Program | H21: SERMON, PATRICIA Payroll Period 02/16/20 � 02/29/20 | I21: -Split- | J21: 69.23 | K21: 89.01
B22: 03/06/2020 | C22: Journal Entry | D22: 312 | G22: 451 USJP Program | H22: SERMON, PATRICIA Payroll Period 02/16/20 � 02/29/20 | I22: -Split- | J22: 316.48 | K22: 405.49
B23: 03/06/2020 | C23: Journal Entry | D23: 312 | G23: 451 USJP Program | H23: SERMON, PATRICIA Payroll Period 02/16/20 � 02/29/20 | I23: -Split- | J23: 594.51 | K23: 1000
B24: 03/20/2020 | C24: Journal Entry | D24: 313 | G24: 451 USJP Program | H24: SERMON, PATRICIA Payroll Period 03/01/20 � 03/14/20 | I24: -Split- | J24: 692.31 | K24: 1692.31
B25: 03/20/2020 | C25: Journal Entry | D25: 313 | G25: 451 USJP Program | H25: SERMON, PATRICIA Payroll Period 03/01/20 � 03/14/20 | I25: -Split- | J25: 307.69 | K25: 2000
A26: Total for 7221c Director of Operations COO | J26: 2000
A27: 7221g Program Director - Education
